Workbook

Sheet rubros_id_opex
A1: nombre | B1: id
A2: ENERGIA | B2: 1
A3: HABILITACIONES Y CERT | B3: 2
A4: HIGIENE Y SEGURIDAD | B4: 3
A5: IMPUESTOS | B5: 4
A6: INSUMOS | B6: 5
A7: INVERSION | B7: 6
A8: LOGISTICA | B8: 7
A9: M.PRIMAS | B9: 8
A10: MANTENIMIENTO PREVENTIVO | B10: 9
A11: PERSONAL | B11: 10
A12: REPARACIONES | B12: 11
A13: REPOSICION | B13: 12
A14: SERVICIOS | B14: 12

Sheet fer_gral
C29: DEUDA
C30: FARO | D30: UNI
C31: M23 WORMS | D31: UNI
C32: M23 BROKER WORLD | D32: UNI
C33: SOUTHCROSS | D33: UNI
C34: RAUL BRINGAS | D34: UNI
C35: MOLLINS | D35: UNI
C36: NICOLAS AVELLINO | D36: UNI
C37: JORGE FERNANDEZ | D37: UNI
C38: CARBO | D38: UNI
C39: GARANTIZAR | D39: UNI
C40: CIRCULO CERRADO | D40: UNI
C41: SANTIAGO BORSONE | D41: UNI
... C48: CRISTIAN AMEGHINI | D48: UNI

Sheet fer_expo
B2: RUBRO + GASTO | C2: UM | D2: Q | E2: MONEDA | F2: P | G2: TOTAL
B3: ENERGIA
B4: NAFTA | C4: LTS
B5: ENERGIA ELECTRICA | C5: KW/H
B6: GASOIL G2 | C6: LTS
B7: GASOIL G3 | C7: LTS
B8: FULL OIL | C8: KG
B10: HABILITACION & CERT
B11: ISCC | C11: UNI
B12: AMBIENTAL | C12: UNI
B13: MUNICIPAL | C13: UNI
B15: HIGIENE & SEGURIDAD
B16: EPP | C16: UNI
B17: HONORARIOS SERVICIOS | C17: UNI
B19: INSUMO
B20: PRESINTOS ISO TANUQE | C20: UNI
B21: BOBINA PAPEL | C21: UNI
B23: LOGISTICA
B24: FOB | C24: TN
B25: FSA | C25: TN
B26: CIF | C26: TN
B28: MATERIA PRIMA
B29: AFE (S) | C29: TN
B30: AFE (G) | C30: TN
B31: AFE (SG) | C31: TN
B32: TSO | C32: TN
B33: AFE (AL) | C33: TN
B34: ARE (V) - A | C34: TN
B35: ARE (V) - B | C35: TN
B36: AG - A | C36: TN
B37: AG - B | C37: TN
B38: AG - C | C38: TN
B40: MANTENIMIENTO
B41: LIMPIEZA | C41: UNI
B44: RR.HH
B45: SUPERVISOR | C45: UNI
B46: COORDINADOR | C46: UNI
B47: OPERARIO | C47: UNI
B49: REPARACIONES
B50: BIENES DE USO + PARTES | C50: UNI | D50: 51
B52: REPOSICION
B53: BIENES DE USO + PARTES | C53: UNI | D53: 51
B55: SERVICIO
B56: COMEX | C56: TN
B57: TERMINAL | C57: TN
B58: SURBEIOR | C58: TN
B60: COMERCIAL
B61: COMISIONES | C61: UNI
B63: IMPUESTO
B64: GANANCIA | C64: UNI
B65: DREI | C65: UNI
G66: =SUM(G3:G65) -> 0
B68: VENTA
B69: AE FOB | C69: TN
B70: AE FSA | C70: TN
G71: =SUM(G69:G70) -> 0
B73: RESULTADO 1 | G73: =G71-G66 -> 0
B75: SOPERTE
B76: ADMINISTRACION
B77: LABORATORIO
B78: INTENDENCIA
B79: PORTERIA
B80: TALLER
B81: DIRECCION
B82: SEGURIDAD
G83: =SUM(G76:G82) -> 0
A85: EBITDA | B85: RESULTADO 2 | G85: =G73-G83 -> 0
B87: CAPEX
B88: PROYECTO 1 | C88: UNI
B89: PROYECTO 1 | C89: UNI
B90: PROYECTO 1 | C90: UNI
G91: =SUM(G88:G90) -> 0
B93: RESULTADO 3 | G93: =G85-G91 -> 0

Sheet rrrhh_nuevo
A1: Fecha de Factura/Recibo | B1: Nombre de la empresa a mostrar en la factura | C1: Número | D1: Total | E1: Líneas de factura/Etiqueta | F1: Líneas de factura/Precio unitario | G1: Líneas de factura/Unidad de medida | H1: Líneas de factura/Producto | I1: Concepto | J1: # LEGAJO | K1: CCO - SECTOR | L1: Total con signo | M1: LEG. | N1: CUIL | O1: Tipo de Gasto 1 | P1: Tipo de Gasto 2 | Q1: Líneas de factura/Cantidad
A2: 46112 | B2: RRHH WORMS (NUEVO) | C2: ABAD, GONZALO | D2: 6630.4348 | E2: ADMINISTRACION | F2: 6630.4348 | G2: # RRHH | H2: PERSONAL | I2: OPEX | J2: 1005 | K2: CC15 | L2: -6630,4348 | M2: 1005 | N2: 20437193941 | O2: FIJO | P2: DIRECTO | Q2: 1
A3: 46112 | B3: RRHH WORMS (NUEVO) | C3: AGUSTIN ALBERTO LOPEZ | D3: 813389.76 | E3: PORTERIA | F3: 813389.76 | G3: # RRHH | H3: PERSONAL | I3: OPEX | J3: 158 | K3: CC22 | L3: -813389,7595 | M3: 158 | N3: 20418603039 | O3: FIJO | P3: DIRECTO | Q3: 1
A4: 46112 | B4: RRHH WORMS (NUEVO) | C4: ALEJANDRO FABIAN ALVAREZ | D4: 1022001 | E4: PILETAS + BACHAS | F4: 1022001 | G4: # RRHH | H4: PERSONAL | I4: OPEX | J4: 252 | K4: CC21 | L4: -1022000,9986 | M4: 252 | N4: 20324334255 | O4: FIJO | P4: DIRECTO | Q4: 1
A5: 46112 | B5: RRHH WORMS (NUEVO) | C5: ALEJO NAHUEL MARTINEZ | D5: 815631.39 | E5: REACTOR | F5: 815631.39 | G5: # RRHH | H5: PERSONAL | I5: OPEX | J5: 260 | K5: CC5 | L5: -815631,3884 | M5: 260 | N5: 20431280524 | O5: FIJO | P5: DIRECTO | Q5: 1
A6: 46112 | B6: RRHH WORMS (NUEVO) | C6: ANA CIELO SANTA CRUZ | D6: 826212.77 | E6: LABORATORIO | F6: 826212.77 | G6: # RRHH | H6: PERSONAL | I6: OPEX | J6: 213 | K6: CC17 | L6: -826212,7679 | M6: 213 | N6: 27320730835 | O6: FIJO | P6: DIRECTO | Q6: 1
A7: 46112 | B7: RRHH WORMS (NUEVO) | C7: ANDREA ANALI DI PAOLO | D7: 1098479.4 | E7: ADMINISTRACION | F7: 1098479.4 | G7: # RRHH | H7: PERSONAL | I7: OPEX | J7: 235 | K7: CC15 | L7: -1098479,3891 | M7: 235 | N7: 27326483791 | O7: FIJO | P7: INDIRECTO | Q7: 1
A8: 46112 | B8: RRHH WORMS (NUEVO) | C8: ANDRES CULOTA | D8: 3357574.7 | E8: ADMINISTRACION | F8: 3357574.7 | G8: # RRHH | H8: PERSONAL | I8: OPEX | J8: 219 | K8: CC15 | L8: -3357574,6753 | M8: 219 | N8: 20244797513 | O8: FIJO | P8: INDIRECTO | Q8: 1
A9: 46112 | B9: RRHH WORMS (NUEVO) | C9: ANDRES HONORES | D9: 1404307 | E9: REACTOR | F9: 1404307 | G9: # RRHH | H9: PERSONAL | I9: OPEX | J9: 43 | K9: CC5 | L9: -1404307,017 | M9: 43 | N9: 20372612615 | O9: FIJO | P9: DIRECTO | Q9: 1
A10: 46112 | B10: RRHH WORMS (NUEVO) | C10: AXEL MARCOS AREVALO | D10: 827089.77 | E10: TALLER MECANICO | F10: 827089.77 | G10: # RRHH | H10: PERSONAL | I10: OPEX | J10: 251 | K10: CC23 | L10: -827089,7725 | M10: 251 | N10: 20456381023 | O10: FIJO | P10: DIRECTO | Q10: 1
A11: 46112 | B11: RRHH WORMS (NUEVO) | C11: AYRTON RODRIGUEZ | D11: 939543.46 | E11: DISPOSICIÓN FINAL RESIDUOS LIQUIDOS + EXPORTACION | F11: 939543.46 | G11: # RRHH | H11: PERSONAL | I11: OPEX | J11: 196 | K11: CC25 | L11: -939543,4613 | M11: 196 | N11: 20402767139 | O11: FIJO | P11: DIRECTO | Q11: 1
A12: 46112 | B12: RRHH WORMS (NUEVO) | C12: BELTRAMO, ANDRES | D12: 0 | E12: DISPOSICIÓN FINAL RESIDUOS SOLIDOS | F12: 0 | G12: # RRHH | H12: PERSONAL | I12: OPEX | J12: 999 | K12: CC2 | L12: 0 | M12: 999 | N12: 20259420696 | O12: FIJO | P12: DIRECTO | Q12: 1
A13: 46112 | B13: RRHH WORMS (NUEVO) | C13: BRIAN EZEQUIEL GROSSO | D13: 1080740.6 | E13: VIGILANCIA | F13: 1080740.6 | G13: # RRHH | H13: PERSONAL | I13: OPEX | J13: 191 | K13: CC29 | L13: -1080740,6139 | M13: 191 | N13: 20398270070 | O13: FIJO | P13: INDIRECTO | Q13: 1
... A93: 46112 | B93: RRHH WORMS (NUEVO) | C93: VAZQUEZ MATIAS EMANUEL | D93: 893215.88 | E93: PILETAS + BACHAS | F93: 893215.88 | G93: # RRHH | H93: PERSONAL | I93: OPEX | J93: 180 | K93: CC21 | L93: -893215,8764 | M93: 180 | N93: 20395675673 | O93: FIJO | P93: DIRECTO | Q93: 1

Sheet sectores_id
A1: Sector | B1: id_sector | G1: SECTOR | H1: id_sector
A2: Bachas | B2: 1 | G2: BACHAS | H2: 1
A3: Cereal & Polvillo | B3: 2 | G3: CEREAL & POLVILLO | H3: 2
A4: COMPOST & FERTILIZANTES | B4: 10 | G4: COMPOST & FERTILIZANTES | H4: 10
A5: Disp. Final Residuos Líquidos | B5: 3 | G5: DISP. FINAL RESIDUOS LÍQUIDOS | H5: 3
A6: Disp. Final Residuos Sólidos | B6: 4 | G6: DISP. FINAL RESIDUOS SÓLIDOS | H6: 4
A7: DISPOSICIÓN FINAL RESIDUOS LIQUIDOS | B7: 3 | G7: EXPORTACION | H7: 5
A8: DISPOSICIÓN FINAL RESIDUOS SOLIDOS | B8: 4 | G8: NFU | H8: 6
A9: EXPORTACION | B9: 5 | G9: PILETAS | H9: 7
A10: Exportación | B10: 5 | G10: REACTORES | H10: 8
A11: General | B11: 0 | G11: TIERRAS FILTRANTES | H11: 9
A12: NFU | B12: 6 | G12: SALES | H12: 20
A13: PILETAS | B13: 7 | G13: TOTAL | H13: >=0
A14: Piletas / AG | B14: 7
A15: Reactores | B15: 8
A16: TIERRAS FILTRANTES | B16: 9
A17: COMPOST_Y_FERTILIZANTES | B17: 10
A18: DISP FINAL RESIDUOS SOLIDOS | B18: 4
A19: CEREAL & POLVILLO | B19: 2
A20: DISP FINAL RESIDUOS LIQUIDOS | B20: 3
A21: BACHAS | B21: 1
A22: REACTORES | B22: 8
A23: Reactor | B23: 8
A24: Piletas | B24: 7
A25: DISPOSICION FINAL DE R. LIQUIDOS | B25: 3
... A34: TEIRRAS FILTRANTES | B34: 9

Sheet Vista_nueva
A2: id | D2: =_xlfn.XLOOKUP(D3,sectores_id!$G$2:$G$13,sectores_id!$H$2:$H$13) -> >=0 | G2: id | H2: 3 | K2: id | L2: 7 | O2: id | P2: 8
D3: TOTAL
D4: OPEX DIRECTO | F4: =SUM(F5:F17) -> 2.8801021e+09
A5: 1 | B5: OPEX DIRECTO | D5: =F5/$F$4 -> 0.026866489 | E5: =_xlfn.XLOOKUP($A5,'rubros_id_opex (2)'!$B:$B,'rubros_id_opex (2)'!$A:$A) -> ENERGIA | F5: =SUMIFS('bbdd.5.final'!$Y:$Y,'bbdd.5.final'!$AA:$AA,Vista_nueva!A5,'bbdd.5.final'!$Z:$Z,$D$2,'bbdd.5.final'!$J:$J,"Opex",'bbdd.5.final'!$L:$L,"DIRECTO") -> 77378232 | G5: 1
A6: 2 | B6: OPEX DIRECTO | D6: =F6/$F$4 -> 0.00049824623 | E6: =_xlfn.XLOOKUP($A6,'rubros_id_opex (2)'!$B:$B,'rubros_id_opex (2)'!$A:$A) -> HABILITACIONES Y CERT | F6: =SUMIFS('bbdd.5.final'!$Y:$Y,'bbdd.5.final'!$AA:$AA,Vista_nueva!A6,'bbdd.5.final'!$Z:$Z,$D$2,'bbdd.5.final'!$J:$J,"Opex",'bbdd.5.final'!$L:$L,"DIRECTO") -> 1435000 | G6: =G5+1 -> 2
A7: 3 | B7: OPEX DIRECTO | D7: =F7/$F$4 -> 0.00083543398 | E7: =_xlfn.XLOOKUP($A7,'rubros_id_opex (2)'!$B:$B,'rubros_id_opex (2)'!$A:$A) -> HIGIENE Y SEGURIDAD | F7: =SUMIFS('bbdd.5.final'!$Y:$Y,'bbdd.5.final'!$AA:$AA,Vista_nueva!A7,'bbdd.5.final'!$Z:$Z,$D$2,'bbdd.5.final'!$J:$J,"Opex",'bbdd.5.final'!$L:$L,"DIRECTO") -> 2406135.1 | G7: =G6+1 -> 3
A8: 5 | B8: OPEX DIRECTO | D8: =F8/$F$4 -> 0.033931015 | E8: =_xlfn.XLOOKUP($A8,'rubros_id_opex (2)'!$B:$B,'rubros_id_opex (2)'!$A:$A) -> INSUMOS | F8: =SUMIFS('bbdd.5.final'!$Y:$Y,'bbdd.5.final'!$AA:$AA,Vista_nueva!A8,'bbdd.5.final'!$Z:$Z,$D$2,'bbdd.5.final'!$J:$J,"Opex",'bbdd.5.final'!$L:$L,"DIRECTO") -> 97724788 | G8: =#REF!+1 -> #REF!
A9: 6 | B9: OPEX DIRECTO | D9: =F9/$F$4 -> 0 | E9: =_xlfn.XLOOKUP($A9,'rubros_id_opex (2)'!$B:$B,'rubros_id_opex (2)'!$A:$A) -> INVERSION | F9: =SUMIFS('bbdd.5.final'!$Y:$Y,'bbdd.5.final'!$AA:$AA,Vista_nueva!A9,'bbdd.5.final'!$Z:$Z,$D$2,'bbdd.5.final'!$J:$J,"Opex",'bbdd.5.final'!$L:$L,"DIRECTO") -> 0 | G9: =G8+1 -> #REF!
A10: 7 | B10: OPEX DIRECTO | D10: =F10/$F$4 -> 0.014737544 | E10: =_xlfn.XLOOKUP($A10,'rubros_id_opex (2)'!$B:$B,'rubros_id_opex (2)'!$A:$A) -> LOGISTICA | F10: =SUMIFS('bbdd.5.final'!$Y:$Y,'bbdd.5.final'!$AA:$AA,Vista_nueva!A10,'bbdd.5.final'!$Z:$Z,$D$2,'bbdd.5.final'!$J:$J,"Opex",'bbdd.5.final'!$L:$L,"DIRECTO") -> 42445632 | G10: =G9+1 -> #REF!
A11: 8 | B11: OPEX DIRECTO | D11: =F11/$F$4 -> 0.88918031 | E11: =_xlfn.XLOOKUP($A11,'rubros_id_opex (2)'!$B:$B,'rubros_id_opex (2)'!$A:$A) -> M.PRIMAS | F11: =SUMIFS('bbdd.5.final'!$Y:$Y,'bbdd.5.final'!$AA:$AA,Vista_nueva!A11,'bbdd.5.final'!$Z:$Z,$D$2,'bbdd.5.final'!$J:$J,"Opex",'bbdd.5.final'!$L:$L,"DIRECTO") -> 2.5609301e+09 | G11: =G10+1 -> #REF!
A12: 9 | B12: OPEX DIRECTO | D12: =F12/$F$4 -> 0.00022510244 | E12: =_xlfn.XLOOKUP($A12,'rubros_id_opex (2)'!$B:$B,'rubros_id_opex (2)'!$A:$A) -> MANTENIMIENTO PREVENTIVO | F12: =SUMIFS('bbdd.5.final'!$Y:$Y,'bbdd.5.final'!$AA:$AA,Vista_nueva!A12,'bbdd.5.final'!$Z:$Z,$D$2,'bbdd.5.final'!$J:$J,"Opex",'bbdd.5.final'!$L:$L,"DIRECTO") -> 648318 | G12: =G11+1 -> #REF!
A13: 10 | B13: OPEX DIRECTO | D13: =F13/$F$4 -> 0.02385739 | E13: =_xlfn.XLOOKUP($A13,'rubros_id_opex (2)'!$B:$B,'rubros_id_opex (2)'!$A:$A) -> PERSONAL | F13: =SUMIFS('bbdd.5.final'!$Y:$Y,'bbdd.5.final'!$AA:$AA,Vista_nueva!A13,'bbdd.5.final'!$Z:$Z,$D$2,'bbdd.5.final'!$J:$J,"Opex",'bbdd.5.final'!$L:$L,"DIRECTO") -> 68711718 | G13: =G12+1 -> #REF!
A14: 11 | B14: OPEX DIRECTO | D14: =F14/$F$4 -> 0.00075358332 | E14: =_xlfn.XLOOKUP($A14,'rubros_id_opex (2)'!$B:$B,'rubros_id_opex (2)'!$A:$A) -> REPARACIONES | F14: =SUMIFS('bbdd.5.final'!$Y:$Y,'bbdd.5.final'!$AA:$AA,Vista_nueva!A14,'bbdd.5.final'!$Z:$Z,$D$2,'bbdd.5.final'!$J:$J,"Opex",'bbdd.5.final'!$L:$L,"DIRECTO") -> 2170396.9 | G14: =G13+1 -> #REF!
A15: 12 | B15: OPEX DIRECTO | D15: =F15/$F$4 -> 0.00036062735 | E15: =_xlfn.XLOOKUP($A15,'rubros_id_opex (2)'!$B:$B,'rubros_id_opex (2)'!$A:$A) -> REPOSICION | F15: =SUMIFS('bbdd.5.final'!$Y:$Y,'bbdd.5.final'!$AA:$AA,Vista_nueva!A15,'bbdd.5.final'!$Z:$Z,$D$2,'bbdd.5.final'!$J:$J,"Opex",'bbdd.5.final'!$L:$L,"DIRECTO") -> 1038643.6 | G15: =G14+1 -> #REF!
A16: 13 | B16: OPEX DIRECTO | D16: =F16/$F$4 -> 0.0085841958 | E16: =_xlfn.XLOOKUP($A16,'rubros_id_opex (2)'!$B:$B,'rubros_id_opex (2)'!$A:$A) -> SERVICIOS | F16: =SUMIFS('bbdd.5.final'!$Y:$Y,'bbdd.5.final'!$AA:$AA,Vista_nueva!A16,'bbdd.5.final'!$Z:$Z,$D$2,'bbdd.5.final'!$J:$J,"Opex",'bbdd.5.final'!$L:$L,"DIRECTO") -> 24723360 | G16: =G15+1 -> #REF!
A17: 14 | B17: OPEX DIRECTO | D17: =F17/$F$4 -> 0.00017006341 | E17: =_xlfn.XLOOKUP($A17,'rubros_id_opex (2)'!$B:$B,'rubros_id_opex (2)'!$A:$A) -> COMERCIAL | F17: =SUMIFS('bbdd.5.final'!$Y:$Y,'bbdd.5.final'!$AA:$AA,Vista_nueva!A17,'bbdd.5.final'!$Z:$Z,$D$2,'bbdd.5.final'!$J:$J,"Opex",'bbdd.5.final'!$L:$L,"DIRECTO") -> 489799.99 | G17: =G16+1 -> #REF!
D19: VENTAS | F19: =SUMIFS(BBDD_INGRESOS_FINAL!$O:$O,BBDD_INGRESOS_FINAL!$R:$R,Vista_nueva!$D$2) -> 3.453388e+09
D21: RESULTADO 1 (EBIT 1) | F21: =F19-F4 -> 5.732859e+08
D23: OPEX INDIRECTO | F23: =SUM(F24:F36) -> 89367666
A24: 1 | B24: OPEX INDIRECTO | D24: =F24/$F$4 -> 0 | E24: =_xlfn.XLOOKUP($A24,'rubros_id_opex (2)'!$B:$B,'rubros_id_opex (2)'!$A:$A) -> ENERGIA | F24: =SUMIFS('bbdd.5.final'!$Y:$Y,'bbdd.5.final'!$AA:$AA,Vista_nueva!A24,'bbdd.5.final'!$Z:$Z,$D$2,'bbdd.5.final'!$J:$J,"Opex",'bbdd.5.final'!$L:$L,"INDIRECTO") -> 0
A25: 2 | B25: OPEX INDIRECTO | D25: =F25/$F$4 -> 0.00050171832 | E25: =_xlfn.XLOOKUP($A25,'rubros_id_opex (2)'!$B:$B,'rubros_id_opex (2)'!$A:$A) -> HABILITACIONES Y CERT | F25: =SUMIFS('bbdd.5.final'!$Y:$Y,'bbdd.5.final'!$AA:$AA,Vista_nueva!A25,'bbdd.5.final'!$Z:$Z,$D$2,'bbdd.5.final'!$J:$J,"Opex",'bbdd.5.final'!$L:$L,"INDIRECTO") -> 1445000
A26: 3 | B26: OPEX INDIRECTO | D26: =F26/$F$4 -> 0 | E26: =_xlfn.XLOOKUP($A26,'rubros_id_opex (2)'!$B:$B,'rubros_id_opex (2)'!$A:$A) -> HIGIENE Y SEGURIDAD | F26: =SUMIFS('bbdd.5.final'!$Y:$Y,'bbdd.5.final'!$AA:$AA,Vista_nueva!A26,'bbdd.5.final'!$Z:$Z,$D$2,'bbdd.5.final'!$J:$J,"Opex",'bbdd.5.final'!$L:$L,"INDIRECTO") -> 0
A27: 5 | B27: OPEX INDIRECTO | D27: =F27/$F$4 -> 0.00077282931 | E27: =_xlfn.XLOOKUP($A27,'rubros_id_opex (2)'!$B:$B,'rubros_id_opex (2)'!$A:$A) -> INSUMOS | F27: =SUMIFS('bbdd.5.final'!$Y:$Y,'bbdd.5.final'!$AA:$AA,Vista_nueva!A27,'bbdd.5.final'!$Z:$Z,$D$2,'bbdd.5.final'!$J:$J,"Opex",'bbdd.5.final'!$L:$L,"INDIRECTO") -> 2225827.3
A28: 6 | B28: OPEX INDIRECTO | D28: =F28/$F$4 -> 0 | E28: =_xlfn.XLOOKUP($A28,'rubros_id_opex (2)'!$B:$B,'rubros_id_opex (2)'!$A:$A) -> INVERSION | F28: =SUMIFS('bbdd.5.final'!$Y:$Y,'bbdd.5.final'!$AA:$AA,Vista_nueva!A28,'bbdd.5.final'!$Z:$Z,$D$2,'bbdd.5.final'!$J:$J,"Opex",'bbdd.5.final'!$L:$L,"INDIRECTO") -> 0
A29: 7 | B29: OPEX INDIRECTO | D29: =F29/$F$4 -> 0 | E29: =_xlfn.XLOOKUP($A29,'rubros_id_opex (2)'!$B:$B,'rubros_id_opex (2)'!$A:$A) -> LOGISTICA | F29: =SUMIFS('bbdd.5.final'!$Y:$Y,'bbdd.5.final'!$AA:$AA,Vista_nueva!A29,'bbdd.5.final'!$Z:$Z,$D$2,'bbdd.5.final'!$J:$J,"Opex",'bbdd.5.final'!$L:$L,"INDIRECTO") -> 0
A30: 8 | B30: OPEX INDIRECTO | D30: =F30/$F$4 -> 0 | E30: =_xlfn.XLOOKUP($A30,'rubros_id_opex (2)'!$B:$B,'rubros_id_opex (2)'!$A:$A) -> M.PRIMAS | F30: =SUMIFS('bbdd.5.final'!$Y:$Y,'bbdd.5.final'!$AA:$AA,Vista_nueva!A30,'bbdd.5.final'!$Z:$Z,$D$2,'bbdd.5.final'!$J:$J,"Opex",'bbdd.5.final'!$L:$L,"INDIRECTO") -> 0
A31: 9 | B31: OPEX INDIRECTO | D31: =F31/$F$4 -> 0.00032567254 | E31: =_xlfn.XLOOKUP($A31,'rubros_id_opex (2)'!$B:$B,'rubros_id_opex (2)'!$A:$A) -> MANTENIMIENTO PREVENTIVO | F31: =SUMIFS('bbdd.5.final'!$Y:$Y,'bbdd.5.final'!$AA:$AA,Vista_nueva!A31,'bbdd.5.final'!$Z:$Z,$D$2,'bbdd.5.final'!$J:$J,"Opex",'bbdd.5.final'!$L:$L,"INDIRECTO") -> 937970.18
A32: 10 | B32: OPEX INDIRECTO | D32: =F32/$F$4 -> 0.010184318 | E32: =_xlfn.XLOOKUP($A32,'rubros_id_opex (2)'!$B:$B,'rubros_id_opex (2)'!$A:$A) -> PERSONAL | F32: =SUMIFS('bbdd.5.final'!$Y:$Y,'bbdd.5.final'!$AA:$AA,Vista_nueva!A32,'bbdd.5.final'!$Z:$Z,$D$2,'bbdd.5.final'!$J:$J,"Opex",'bbdd.5.final'!$L:$L,"INDIRECTO") -> 29331876
A33: 11 | B33: OPEX INDIRECTO | D33: =F33/$F$4 -> 0.0018696265 | E33: =_xlfn.XLOOKUP($A33,'rubros_id_opex (2)'!$B:$B,'rubros_id_opex (2)'!$A:$A) -> REPARACIONES | F33: =SUMIFS('bbdd.5.final'!$Y:$Y,'bbdd.5.final'!$AA:$AA,Vista_nueva!A33,'bbdd.5.final'!$Z:$Z,$D$2,'bbdd.5.final'!$J:$J,"Opex",'bbdd.5.final'!$L:$L,"INDIRECTO") -> 5384715.1
A34: 12 | B34: OPEX INDIRECTO | D34: =F34/$F$4 -> 0.0008588358 | E34: =_xlfn.XLOOKUP($A34,'rubros_id_opex (2)'!$B:$B,'rubros_id_opex (2)'!$A:$A) -> REPOSICION | F34: =SUMIFS('bbdd.5.final'!$Y:$Y,'bbdd.5.final'!$AA:$AA,Vista_nueva!A34,'bbdd.5.final'!$Z:$Z,$D$2,'bbdd.5.final'!$J:$J,"Opex",'bbdd.5.final'!$L:$L,"INDIRECTO") -> 2473534.8
A35: 13 | B35: OPEX INDIRECTO | D35: =F35/$F$4 -> 0.016516339 | E35: =_xlfn.XLOOKUP($A35,'rubros_id_opex (2)'!$B:$B,'rubros_id_opex (2)'!$A:$A) -> SERVICIOS | F35: =SUMIFS('bbdd.5.final'!$Y:$Y,'bbdd.5.final'!$AA:$AA,Vista_nueva!A35,'bbdd.5.final'!$Z:$Z,$D$2,'bbdd.5.final'!$J:$J,"Opex",'bbdd.5.final'!$L:$L,"INDIRECTO") -> 47568743
A36: 14 | B36: OPEX INDIRECTO | D36: =F36/$F$4 -> 0 | E36: =_xlfn.XLOOKUP($A36,'rubros_id_opex (2)'!$B:$B,'rubros_id_opex (2)'!$A:$A) -> COMERCIAL | F36: =SUMIFS('bbdd.5.final'!$Y:$Y,'bbdd.5.final'!$AA:$AA,Vista_nueva!A36,'bbdd.5.final'!$Z:$Z,$D$2,'bbdd.5.final'!$J:$J,"Opex",'bbdd.5.final'!$L:$L,"INDIRECTO") -> 0
D38: RESULTADO 2 (EBIT 2) | F38: =F21-F23 -> 4.8391824e+08
A39: 4 | D39: IMPUESTOS DIRECTOS | E39: =_xlfn.XLOOKUP(A39,'rubros_id_opex (2)'!$B:$B,'rubros_id_opex (2)'!$A:$A) -> IMPUESTOS | F39: =SUMIFS('bbdd.5.final'!$Y:$Y,'bbdd.5.final'!$AA:$AA,A39,'bbdd.5.final'!$Z:$Z,$D$2,'bbdd.5.final'!$J:$J,"Opex",'bbdd.5.final'!$L:$L,"DIRECTO") -> 1412535.2
A40: 4 | D40: IMPUESTOS INDIRECTOS | E40: =_xlfn.XLOOKUP($A40,'rubros_id_opex (2)'!$B:$B,'rubros_id_opex (2)'!$A:$A) -> IMPUESTOS | F40: =SUMIFS('bbdd.5.final'!$Y:$Y,'bbdd.5.final'!$AA:$AA,Vista_nueva!A40,'bbdd.5.final'!$Z:$Z,$D$2,'bbdd.5.final'!$J:$J,"Opex",'bbdd.5.final'!$L:$L,"INDIRECTO") -> 7040238.6
D42: IMPUESTOS TOTALES DEL SECTOR | F42: =SUM(F39:F40) -> 8452773.8
A44: CAPEX | D44: CAPEX DIRECTO | E44: CAPEX | F44: =SUMIFS('bbdd.5.final'!$Y:$Y,'bbdd.5.final'!$AA:$AA,Vista_nueva!A44,'bbdd.5.final'!$Z:$Z,$D$2,'bbdd.5.final'!$L:$L,"DIRECTO") -> 1.127357e+08
A45: CAPEX | D45: CAPEX INDIRECTO | E45: CAPEX | F45: =SUMIFS('bbdd.5.final'!$Y:$Y,'bbdd.5.final'!$AA:$AA,Vista_nueva!A45,'bbdd.5.final'!$Z:$Z,$D$2,'bbdd.5.final'!$L:$L,"INDIRECTO") -> 1.4250062e+08
D46: CAPEX TOTAL DEL SECTOR | F46: =F44+F45 -> 2.5523632e+08
D48: RESULTADO 3 | F48: =F38-F42-F46 -> 2.2022915e+08
D50: Flujo de Caja al Accionista | F50: =F48 -> 2.2022915e+08
A52: id
A55: 1
A56: =A55+1 -> 2
A57: =A56+1 -> 3
A58: =A57+1 -> 4
A59: =A58+1 -> 5
A60: =A59+1 -> 6
A61: =A60+1 -> 7
A62: =A61+1 -> 8
A63: =A62+1 -> 9
A64: =A63+1 -> 10
A65: =A64+1 -> 11
A66: =A65+1 -> 12
A67: =A66+1 -> 13
A68: =A67+1 -> 14
A80: id
A83: 1
A84: =A83+1 -> 2
A85: =A84+1 -> 3
A86: =A85+1 -> 4
A87: =A86+1 -> 5
A88: =A87+1 -> 6
A89: =A88+1 -> 7
A90: =A89+1 -> 8
A91: =A90+1 -> 9
A92: =A91+1 -> 10
A93: =A92+1 -> 11
A94: =A93+1 -> 12
A95: =A94+1 -> 13
A96: =A95+1 -> 14 | K96: =K95+1 -> 1
D120: CHECK
D122: PRODUCCION_UN | E122: =#REF!+F70+J70+N70+R70+R19+N19+J19+F19+F99 -> #REF!
D123: PRODUCCION_TOTAL | E123: =#REF! -> #REF!
E124: =E122=E123 -> #REF!
D126: OPEX UN | E126: =F4+J4+N4+R4+R54+N54+J54+F54+#REF!+F82+N82 -> #REF!
D127: OPEX total | E127: =#REF! -> #REF!
E128: =MROUND(E127,10000)=MROUND(E126,10000) -> #REF!
D130: CAPEX_UN | E130: =F45+J45+N45+R45+R74+N74+J74+F74+#REF!+F103+N103 -> #REF!
D131: CAPEX_TOTAL | E131: =#REF! -> #REF! | F131: =E130=E131 -> #REF!
D132: DEUDA_UN | E132: =F48+J48+N48+R48+R76+N76+J76+F76+#REF!+F105+N105 -> #REF!
D133: DEUDA_TOTAL | E133: =#REF! -> #REF! | F133: =E132=E133 -> #REF!
D137: UTILIDAD_TOTAL | E137: =#REF! -> #REF!
D138: UTILIDAD_UN | E138: =F21+J21+N21+R21+R72+N72+J72+F72+#REF!+F101+N101 -> #REF! | F138: =MROUND(E138,10000)=MROUND(E137,10000) -> #REF!
D141: Flujo_TOTAL | E141: =#REF! -> #REF!
D142: FLUJO_UN | E142: =F50+J50+N50+R50+R78+N78+J78+F78+#REF!+F107+N107 -> #REF! | F142: =MROUND(E142,10000)=MROUND(E141,10000) -> #REF!

Sheet Vista
B2: WORMS
B5: TOTALES | F5: FIJO/VARIABLE | J5: DIRECTO/INDERECTO
B6: VENTAS | C6: =SUM(BBDD_INGRESOS_FINAL!$O:$O) -> 3.453388e+09 | F6: VENTAS | G6: =SUM(BBDD_INGRESOS_FINAL!$O:$O) -> 3.453388e+09 | J6: VENTAS | K6: =SUM(BBDD_INGRESOS_FINAL!$O:$O) -> 3.453388e+09
B7: OPEX | C7: =SUMIFS('bbdd.5.final'!$Y:$Y,'bbdd.5.final'!$J:$J,Vista!B7) -> 2.9779225e+09 | F7: Fijo | G7: =SUMIFS(BBDD_GASTOS!$H:$H,BBDD_GASTOS!$J:$J,Vista!F7) -> 1.0332095e+08 | J7: DIRECTO | K7: =SUMIFS('bbdd.5.final'!$Y:$Y,'bbdd.5.final'!$L:$L,$J$7) -> 2.9942503e+09
B8: UTILIDAD | C8: =C6-C7 -> 4.7546546e+08 | F8: Variable | G8: =SUMIFS(BBDD_GASTOS!$H:$H,BBDD_GASTOS!$J:$J,Vista!F8) -> 4.6635073e+09 | J8: INDIRECTO | K8: =SUMIFS('bbdd.5.final'!$Y:$Y,'bbdd.5.final'!$L:$L,$J$8) -> 2.3890852e+08
B9: CAPEX | C9: =SUMIFS('bbdd.5.final'!$Y:$Y,'bbdd.5.final'!$J:$J,Vista!B9) -> 2.5523632e+08
B10: DEUDA | C10: =SUMIFS('bbdd.5.final'!$Y:$Y,'bbdd.5.final'!$J:$J,Vista!B10) -> 0
B11: Flujo de Caja al Accionista | C11: =C6-C7-C9-C10 -> 2.2022915e+08 | F11: Flujo de Caja al Accionista | G11: =G6-G7-G8 -> -1.3134403e+09 | J11: Flujo de Caja al Accionista | K11: =K6-K7-K8 -> 2.2022915e+08
A13: id | B13: 4 | E13: id | F13: 3 | I13: id | J13: 7 | M13: id | N13: 8
B14: DISPOSICIÓN FINAL RESIDUOS SOLIDOS | F14: DISPOSICIÓN FINAL RESIDUOS LIQUIDOS | J14: PILETAS | N14: REACTORES
B15: OPEX | D15: =SUM(D16:D29) -> 9091744.7 | F15: OPEX | H15: =SUM(H16:H29) -> 37569201 | J15: OPEX | L15: =SUM(L16:L28) -> 23546614 | M15: 1 | N15: OPEX | P15: =SUM(P16:P29) -> 1.946207e+08
A16: 1 | B16: =D16/$D$15 -> 0.0062786192 | C16: =_xlfn.XLOOKUP($A16,'rubros_id_opex (2)'!$B:$B,'rubros_id_opex (2)'!$A:$A) -> ENERGIA | D16: =SUMIFS('bbdd.5.final'!$Y:$Y,'bbdd.5.final'!$AA:$AA,Vista!A16,'bbdd.5.final'!$Z:$Z,$B$13,'bbdd.5.final'!$J:$J,"Opex") -> 57083.603 | E16: 1 | F16: =H16/$H$15 -> 0.078263435 | G16: =_xlfn.XLOOKUP($E16,'rubros_id_opex (2)'!$B:$B,'rubros_id_opex (2)'!$A:$A) -> ENERGIA | H16: =SUMIFS('bbdd.5.final'!$Y:$Y,'bbdd.5.final'!$AA:$AA,Vista!E16,'bbdd.5.final'!$Z:$Z,$F$13,'bbdd.5.final'!$J:$J,"Opex") -> 2940294.7 | I16: 1 | J16: =L16/$L$15 -> 0.21684449 | K16: =_xlfn.XLOOKUP($I16,'rubros_id_opex (2)'!$B:$B,'rubros_id_opex (2)'!$A:$A) -> ENERGIA | L16: =SUMIFS('bbdd.5.final'!$Y:$Y,'bbdd.5.final'!$AA:$AA,Vista!I16,'bbdd.5.final'!$Z:$Z,$J$13,'bbdd.5.final'!$J:$J,"Opex") -> 5105953.5 | M16: 1 | N16: =P16/$P$15 -> 0.19133692 | O16: =_xlfn.XLOOKUP($M16,'rubros_id_opex (2)'!$B:$B,'rubros_id_opex (2)'!$A:$A) -> ENERGIA | P16: =SUMIFS('bbdd.5.final'!$Y:$Y,'bbdd.5.final'!$AA:$AA,Vista!M16,'bbdd.5.final'!$Z:$Z,$N$13,'bbdd.5.final'!$J:$J,"Opex") -> 37238125
A17: =A16+1 -> 2 | B17: =D17/$D$15 -> 0.00077462129 | C17: =_xlfn.XLOOKUP($A17,'rubros_id_opex (2)'!$B:$B,'rubros_id_opex (2)'!$A:$A) -> HABILITACIONES Y CERT | D17: =SUMIFS('bbdd.5.final'!$Y:$Y,'bbdd.5.final'!$AA:$AA,Vista!A17,'bbdd.5.final'!$Z:$Z,$B$13,'bbdd.5.final'!$J:$J,"Opex") -> 7042.659 | E17: =E16+1 -> 2 | F17: =H17/$H$15 -> 0.0022997058 | G17: =_xlfn.XLOOKUP($E17,'rubros_id_opex (2)'!$B:$B,'rubros_id_opex (2)'!$A:$A) -> HABILITACIONES Y CERT | H17: =SUMIFS('bbdd.5.final'!$Y:$Y,'bbdd.5.final'!$AA:$AA,Vista!E17,'bbdd.5.final'!$Z:$Z,$F$13,'bbdd.5.final'!$J:$J,"Opex") -> 86398.108 | I17: =I16+1 -> 2 | J17: =L17/$L$15 -> 0.0066031776 | K17: =_xlfn.XLOOKUP($I17,'rubros_id_opex (2)'!$B:$B,'rubros_id_opex (2)'!$A:$A) -> HABILITACIONES Y CERT | L17: =SUMIFS('bbdd.5.final'!$Y:$Y,'bbdd.5.final'!$AA:$AA,Vista!I17,'bbdd.5.final'!$Z:$Z,$J$13,'bbdd.5.final'!$J:$J,"Opex") -> 155482.48 | M17: =M16+1 -> 2 | N17: =P17/$P$15 -> 0.00029457803 | O17: =_xlfn.XLOOKUP($M17,'rubros_id_opex (2)'!$B:$B,'rubros_id_opex (2)'!$A:$A) -> HABILITACIONES Y CERT | P17: =SUMIFS('bbdd.5.final'!$Y:$Y,'bbdd.5.final'!$AA:$AA,Vista!M17,'bbdd.5.final'!$Z:$Z,$N$13,'bbdd.5.final'!$J:$J,"Opex") -> 57330.982
A18: =A17+1 -> 3 | B18: =D18/$D$15 -> 0.0012898571 | C18: =_xlfn.XLOOKUP($A18,'rubros_id_opex (2)'!$B:$B,'rubros_id_opex (2)'!$A:$A) -> HIGIENE Y SEGURIDAD | D18: =SUMIFS('bbdd.5.final'!$Y:$Y,'bbdd.5.final'!$AA:$AA,Vista!A18,'bbdd.5.final'!$Z:$Z,$B$13,'bbdd.5.final'!$J:$J,"Opex") -> 11727.051 | E18: =E17+1 -> 3 | F18: =H18/$H$15 -> 0.0038293446 | G18: =_xlfn.XLOOKUP($E18,'rubros_id_opex (2)'!$B:$B,'rubros_id_opex (2)'!$A:$A) -> HIGIENE Y SEGURIDAD | H18: =SUMIFS('bbdd.5.final'!$Y:$Y,'bbdd.5.final'!$AA:$AA,Vista!E18,'bbdd.5.final'!$Z:$Z,$F$13,'bbdd.5.final'!$J:$J,"Opex") -> 143865.42 | I18: =I17+1 -> 3 | J18: =L18/$L$15 -> 0.010995251 | K18: =_xlfn.XLOOKUP($I18,'rubros_id_opex (2)'!$B:$B,'rubros_id_opex (2)'!$A:$A) -> HIGIENE Y SEGURIDAD | L18: =SUMIFS('bbdd.5.final'!$Y:$Y,'bbdd.5.final'!$AA:$AA,Vista!I18,'bbdd.5.final'!$Z:$Z,$J$13,'bbdd.5.final'!$J:$J,"Opex") -> 258900.93 | M18: =M17+1 -> 3 | N18: =P18/$P$15 -> 0.00049051526 | O18: =_xlfn.XLOOKUP($M18,'rubros_id_opex (2)'!$B:$B,'rubros_id_opex (2)'!$A:$A) -> HIGIENE Y SEGURIDAD | P18: =SUMIFS('bbdd.5.final'!$Y:$Y,'bbdd.5.final'!$AA:$AA,Vista!M18,'bbdd.5.final'!$Z:$Z,$N$13,'bbdd.5.final'!$J:$J,"Opex") -> 95464.423
A19: =A18+1 -> 4 | B19: =D19/$D$15 -> 0.0027586388 | C19: =_xlfn.XLOOKUP($A19,'rubros_id_opex (2)'!$B:$B,'rubros_id_opex (2)'!$A:$A) -> IMPUESTOS | D19: =SUMIFS('bbdd.5.final'!$Y:$Y,'bbdd.5.final'!$AA:$AA,Vista!A19,'bbdd.5.final'!$Z:$Z,$B$13,'bbdd.5.final'!$J:$J,"Opex") -> 25080.84 | E19: =E18+1 -> 4 | F19: =H19/$H$15 -> 0.026134634 | G19: =_xlfn.XLOOKUP($E19,'rubros_id_opex (2)'!$B:$B,'rubros_id_opex (2)'!$A:$A) -> IMPUESTOS | H19: =SUMIFS('bbdd.5.final'!$Y:$Y,'bbdd.5.final'!$AA:$AA,Vista!E19,'bbdd.5.final'!$Z:$Z,$F$13,'bbdd.5.final'!$J:$J,"Opex") -> 981857.3 | I19: =I18+1 -> 4 | J19: =L19/$L$15 -> 0.035171393 | K19: =_xlfn.XLOOKUP($I19,'rubros_id_opex (2)'!$B:$B,'rubros_id_opex (2)'!$A:$A) -> IMPUESTOS | L19: =SUMIFS('bbdd.5.final'!$Y:$Y,'bbdd.5.final'!$AA:$AA,Vista!I19,'bbdd.5.final'!$Z:$Z,$J$13,'bbdd.5.final'!$J:$J,"Opex") -> 828167.22 | M19: =M18+1 -> 4 | N19: =P19/$P$15 -> 0.0010490731 | O19: =_xlfn.XLOOKUP($M19,'rubros_id_opex (2)'!$B:$B,'rubros_id_opex (2)'!$A:$A) -> IMPUESTOS | P19: =SUMIFS('bbdd.5.final'!$Y:$Y,'bbdd.5.final'!$AA:$AA,Vista!M19,'bbdd.5.final'!$Z:$Z,$N$13,'bbdd.5.final'!$J:$J,"Opex") -> 204171.35
A20: =A19+1 -> 5 | B20: =D20/$D$15 -> 0.0010196387 | C20: =_xlfn.XLOOKUP($A20,'rubros_id_opex (2)'!$B:$B,'rubros_id_opex (2)'!$A:$A) -> INSUMOS | D20: =SUMIFS('bbdd.5.final'!$Y:$Y,'bbdd.5.final'!$AA:$AA,Vista!A20,'bbdd.5.final'!$Z:$Z,$B$13,'bbdd.5.final'!$J:$J,"Opex") -> 9270.2951 | E20: =E19+1 -> 5 | F20: =H20/$H$15 -> 0.0030271168 | G20: =_xlfn.XLOOKUP($E20,'rubros_id_opex (2)'!$B:$B,'rubros_id_opex (2)'!$A:$A) -> INSUMOS | H20: =SUMIFS('bbdd.5.final'!$Y:$Y,'bbdd.5.final'!$AA:$AA,Vista!E20,'bbdd.5.final'!$Z:$Z,$F$13,'bbdd.5.final'!$J:$J,"Opex") -> 113726.36 | I20: =I19+1 -> 5 | J20: =L20/$L$15 -> 0.0086918031 | K20: =_xlfn.XLOOKUP($I20,'rubros_id_opex (2)'!$B:$B,'rubros_id_opex (2)'!$A:$A) -> INSUMOS | L20: =SUMIFS('bbdd.5.final'!$Y:$Y,'bbdd.5.final'!$AA:$AA,Vista!I20,'bbdd.5.final'!$Z:$Z,$J$13,'bbdd.5.final'!$J:$J,"Opex") -> 204662.53 | M20: =M19+1 -> 5 | N20: =P20/$P$15 -> 0.47965492 | O20: =_xlfn.XLOOKUP($M20,'rubros_id_opex (2)'!$B:$B,'rubros_id_opex (2)'!$A:$A) -> INSUMOS | P20: =SUMIFS('bbdd.5.final'!$Y:$Y,'bbdd.5.final'!$AA:$AA,Vista!M20,'bbdd.5.final'!$Z:$Z,$N$13,'bbdd.5.final'!$J:$J,"Opex") -> 93350777
A21: =A20+1 -> 6 | B21: =D21/$D$15 -> 0 | C21: =_xlfn.XLOOKUP($A21,'rubros_id_opex (2)'!$B:$B,'rubros_id_opex (2)'!$A:$A) -> INVERSION | D21: =SUMIFS('bbdd.5.final'!$Y:$Y,'bbdd.5.final'!$AA:$AA,Vista!A21,'bbdd.5.final'!$Z:$Z,$B$13,'bbdd.5.final'!$J:$J,"Opex") -> 0 | E21: =E20+1 -> 6 | F21: =H21/$H$15 -> 0 | G21: =_xlfn.XLOOKUP($E21,'rubros_id_opex (2)'!$B:$B,'rubros_id_opex (2)'!$A:$A) -> INVERSION | H21: =SUMIFS('bbdd.5.final'!$Y:$Y,'bbdd.5.final'!$AA:$AA,Vista!E21,'bbdd.5.final'!$Z:$Z,$F$13,'bbdd.5.final'!$J:$J,"Opex") -> 0 | I21: =I20+1 -> 6 | J21: =L21/$L$15 -> 0 | K21: =_xlfn.XLOOKUP($I21,'rubros_id_opex (2)'!$B:$B,'rubros_id_opex (2)'!$A:$A) -> INVERSION | L21: =SUMIFS('bbdd.5.final'!$Y:$Y,'bbdd.5.final'!$AA:$AA,Vista!I21,'bbdd.5.final'!$Z:$Z,$J$13,'bbdd.5.final'!$J:$J,"Opex") -> 0 | M21: =M20+1 -> 6 | N21: =P21/$P$15 -> 0 | O21: =_xlfn.XLOOKUP($M21,'rubros_id_opex (2)'!$B:$B,'rubros_id_opex (2)'!$A:$A) -> INVERSION | P21: =SUMIFS('bbdd.5.final'!$Y:$Y,'bbdd.5.final'!$AA:$AA,Vista!M21,'bbdd.5.final'!$Z:$Z,$N$13,'bbdd.5.final'!$J:$J,"Opex") -> 0
A22: =A21+1 -> 7 | B22: =D22/$D$15 -> 0 | C22: =_xlfn.XLOOKUP($A22,'rubros_id_opex (2)'!$B:$B,'rubros_id_opex (2)'!$A:$A) -> LOGISTICA | D22: =SUMIFS('bbdd.5.final'!$Y:$Y,'bbdd.5.final'!$AA:$AA,Vista!A22,'bbdd.5.final'!$Z:$Z,$B$13,'bbdd.5.final'!$J:$J,"Opex") -> 0 | E22: =E21+1 -> 7 | F22: =H22/$H$15 -> 0 | G22: =_xlfn.XLOOKUP($E22,'rubros_id_opex (2)'!$B:$B,'rubros_id_opex (2)'!$A:$A) -> LOGISTICA | H22: =SUMIFS('bbdd.5.final'!$Y:$Y,'bbdd.5.final'!$AA:$AA,Vista!E22,'bbdd.5.final'!$Z:$Z,$F$13,'bbdd.5.final'!$J:$J,"Opex") -> 0 | I22: =I21+1 -> 7 | J22: =L22/$L$15 -> 0 | K22: =_xlfn.XLOOKUP($I22,'rubros_id_opex (2)'!$B:$B,'rubros_id_opex (2)'!$A:$A) -> LOGISTICA | L22: =SUMIFS('bbdd.5.final'!$Y:$Y,'bbdd.5.final'!$AA:$AA,Vista!I22,'bbdd.5.final'!$Z:$Z,$J$13,'bbdd.5.final'!$J:$J,"Opex") -> 0 | M22: =M21+1 -> 7 | N22: =P22/$P$15 -> 0.003873329 | O22: =_xlfn.XLOOKUP($M22,'rubros_id_opex (2)'!$B:$B,'rubros_id_opex (2)'!$A:$A) -> LOGISTICA | P22: =SUMIFS('bbdd.5.final'!$Y:$Y,'bbdd.5.final'!$AA:$AA,Vista!M22,'bbdd.5.final'!$Z:$Z,$N$13,'bbdd.5.final'!$J:$J,"Opex") -> 753830
A23: =A22+1 -> 8 | B23: =D23/$D$15 -> 0.096249174 | C23: =_xlfn.XLOOKUP($A23,'rubros_id_opex (2)'!$B:$B,'rubros_id_opex (2)'!$A:$A) -> M.PRIMAS | D23: =SUMIFS('bbdd.5.final'!$Y:$Y,'bbdd.5.final'!$AA:$AA,Vista!A23,'bbdd.5.final'!$Z:$Z,$B$13,'bbdd.5.final'!$J:$J,"Opex") -> 875072.92 | E23: =E22+1 -> 8 | F23: =H23/$H$15 -> 0 | G23: =_xlfn.XLOOKUP($E23,'rubros_id_opex (2)'!$B:$B,'rubros_id_opex (2)'!$A:$A) -> M.PRIMAS | H23: =SUMIFS('bbdd.5.final'!$Y:$Y,'bbdd.5.final'!$AA:$AA,Vista!E23,'bbdd.5.final'!$Z:$Z,$F$13,'bbdd.5.final'!$J:$J,"Opex") -> 0 | I23: =I22+1 -> 8 | J23: =L23/$L$15 -> 0 | K23: =_xlfn.XLOOKUP($I23,'rubros_id_opex (2)'!$B:$B,'rubros_id_opex (2)'!$A:$A) -> M.PRIMAS | L23: =SUMIFS('bbdd.5.final'!$Y:$Y,'bbdd.5.final'!$AA:$AA,Vista!I23,'bbdd.5.final'!$Z:$Z,$J$13,'bbdd.5.final'!$J:$J,"Opex") -> 0 | M23: =M22+1 -> 8 | N23: =P23/$P$15 -> 0.23278621 | O23: =_xlfn.XLOOKUP($M23,'rubros_id_opex (2)'!$B:$B,'rubros_id_opex (2)'!$A:$A) -> M.PRIMAS | P23: =SUMIFS('bbdd.5.final'!$Y:$Y,'bbdd.5.final'!$AA:$AA,Vista!M23,'bbdd.5.final'!$Z:$Z,$N$13,'bbdd.5.final'!$J:$J,"Opex") -> 45305016
A24: =A23+1 -> 9 | B24: =D24/$D$15 -> 0.00072738971 | C24: =_xlfn.XLOOKUP($A24,'rubros_id_opex (2)'!$B:$B,'rubros_id_opex (2)'!$A:$A) -> MANTENIMIENTO PREVENTIVO | D24: =SUMIFS('bbdd.5.final'!$Y:$Y,'bbdd.5.final'!$AA:$AA,Vista!A24,'bbdd.5.final'!$Z:$Z,$B$13,'bbdd.5.final'!$J:$J,"Opex") -> 6613.2415 | E24: =E23+1 -> 9 | F24: =H24/$H$15 -> 0.002159484 | G24: =_xlfn.XLOOKUP($E24,'rubros_id_opex (2)'!$B:$B,'rubros_id_opex (2)'!$A:$A) -> MANTENIMIENTO PREVENTIVO | H24: =SUMIFS('bbdd.5.final'!$Y:$Y,'bbdd.5.final'!$AA:$AA,Vista!E24,'bbdd.5.final'!$Z:$Z,$F$13,'bbdd.5.final'!$J:$J,"Opex") -> 81130.09 | I24: =I23+1 -> 9 | J24: =L24/$L$15 -> 0.006200557 | K24: =_xlfn.XLOOKUP($I24,'rubros_id_opex (2)'!$B:$B,'rubros_id_opex (2)'!$A:$A) -> MANTENIMIENTO PREVENTIVO | L24: =SUMIFS('bbdd.5.final'!$Y:$Y,'bbdd.5.final'!$AA:$AA,Vista!I24,'bbdd.5.final'!$Z:$Z,$J$13,'bbdd.5.final'!$J:$J,"Opex") -> 146002.12 | M24: =M23+1 -> 9 | N24: =P24/$P$15 -> 0.00027661649 | O24: =_xlfn.XLOOKUP($M24,'rubros_id_opex (2)'!$B:$B,'rubros_id_opex (2)'!$A:$A) -> MANTENIMIENTO PREVENTIVO | P24: =SUMIFS('bbdd.5.final'!$Y:$Y,'bbdd.5.final'!$AA:$AA,Vista!M24,'bbdd.5.final'!$Z:$Z,$N$13,'bbdd.5.final'!$J:$J,"Opex") -> 53835.296
A25: =A24+1 -> 10 | B25: =D25/$D$15 -> 0.87293138 | C25: =_xlfn.XLOOKUP($A25,'rubros_id_opex (2)'!$B:$B,'rubros_id_opex (2)'!$A:$A) -> PERSONAL | D25: =SUMIFS('bbdd.5.final'!$Y:$Y,'bbdd.5.final'!$AA:$AA,Vista!A25,'bbdd.5.final'!$Z:$Z,$B$13,'bbdd.5.final'!$J:$J,"Opex") -> 7936469.3 | E25: =E24+1 -> 10 | F25: =H25/$H$15 -> 0.28405587 | G25: =_xlfn.XLOOKUP($E25,'rubros_id_opex (2)'!$B:$B,'rubros_id_opex (2)'!$A:$A) -> PERSONAL | H25: =SUMIFS('bbdd.5.final'!$Y:$Y,'bbdd.5.final'!$AA:$AA,Vista!E25,'bbdd.5.final'!$Z:$Z,$F$13,'bbdd.5.final'!$J:$J,"Opex") -> 10671752 | I25: =I24+1 -> 10 | J25: =L25/$L$15 -> 0.56134057 | K25: =_xlfn.XLOOKUP($I25,'rubros_id_opex (2)'!$B:$B,'rubros_id_opex (2)'!$A:$A) -> PERSONAL | L25: =SUMIFS('bbdd.5.final'!$Y:$Y,'bbdd.5.final'!$AA:$AA,Vista!I25,'bbdd.5.final'!$Z:$Z,$J$13,'bbdd.5.final'!$J:$J,"Opex") -> 13217670 | M25: =M24+1 -> 10 | N25: =P25/$P$15 -> 0.075384612 | O25: =_xlfn.XLOOKUP($M25,'rubros_id_opex (2)'!$B:$B,'rubros_id_opex (2)'!$A:$A) -> PERSONAL | P25: =SUMIFS('bbdd.5.final'!$Y:$Y,'bbdd.5.final'!$AA:$AA,Vista!M25,'bbdd.5.final'!$Z:$Z,$N$13,'bbdd.5.final'!$J:$J,"Opex") -> 14671406
A26: =A25+1 -> 11 | B26: =D26/$D$15 -> 0.0035443052 | C26: =_xlfn.XLOOKUP($A26,'rubros_id_opex (2)'!$B:$B,'rubros_id_opex (2)'!$A:$A) -> REPARACIONES | D26: =SUMIFS('bbdd.5.final'!$Y:$Y,'bbdd.5.final'!$AA:$AA,Vista!A26,'bbdd.5.final'!$Z:$Z,$B$13,'bbdd.5.final'!$J:$J,"Opex") -> 32223.918 | E26: =E25+1 -> 11 | F26: =H26/$H$15 -> 0.01052238 | G26: =_xlfn.XLOOKUP($E26,'rubros_id_opex (2)'!$B:$B,'rubros_id_opex (2)'!$A:$A) -> REPARACIONES | H26: =SUMIFS('bbdd.5.final'!$Y:$Y,'bbdd.5.final'!$AA:$AA,Vista!E26,'bbdd.5.final'!$Z:$Z,$F$13,'bbdd.5.final'!$J:$J,"Opex") -> 395317.39 | I26: =I25+1 -> 11 | J26: =L26/$L$15 -> 0.030213057 | K26: =_xlfn.XLOOKUP($I26,'rubros_id_opex (2)'!$B:$B,'rubros_id_opex (2)'!$A:$A) -> REPARACIONES | L26: =SUMIFS('bbdd.5.final'!$Y:$Y,'bbdd.5.final'!$AA:$AA,Vista!I26,'bbdd.5.final'!$Z:$Z,$J$13,'bbdd.5.final'!$J:$J,"Opex") -> 711415.19 | M26: =M25+1 -> 11 | N26: =P26/$P$15 -> 0.0021699634 | O26: =_xlfn.XLOOKUP($M26,'rubros_id_opex (2)'!$B:$B,'rubros_id_opex (2)'!$A:$A) -> REPARACIONES | P26: =SUMIFS('bbdd.5.final'!$Y:$Y,'bbdd.5.final'!$AA:$AA,Vista!M26,'bbdd.5.final'!$Z:$Z,$N$13,'bbdd.5.final'!$J:$J,"Opex") -> 422319.8
A27: =A26+1 -> 12 | B27: =D27/$D$15 -> 0.00073784449 | C27: =_xlfn.XLOOKUP($A27,'rubros_id_opex (2)'!$B:$B,'rubros_id_opex (2)'!$A:$A) -> REPOSICION | D27: =SUMIFS('bbdd.5.final'!$Y:$Y,'bbdd.5.final'!$AA:$AA,Vista!A27,'bbdd.5.final'!$Z:$Z,$B$13,'bbdd.5.final'!$J:$J,"Opex") -> 6708.2937 | E27: =E26+1 -> 12 | F27: =H27/$H$15 -> 0.0021905223 | G27: =_xlfn.XLOOKUP($E27,'rubros_id_opex (2)'!$B:$B,'rubros_id_opex (2)'!$A:$A) -> REPOSICION | H27: =SUMIFS('bbdd.5.final'!$Y:$Y,'bbdd.5.final'!$AA:$AA,Vista!E27,'bbdd.5.final'!$Z:$Z,$F$13,'bbdd.5.final'!$J:$J,"Opex") -> 82296.174 | I27: =I26+1 -> 12 | J27: =L27/$L$15 -> 0.0094914743 | K27: =_xlfn.XLOOKUP($I27,'rubros_id_opex (2)'!$B:$B,'rubros_id_opex (2)'!$A:$A) -> REPOSICION | L27: =SUMIFS('bbdd.5.final'!$Y:$Y,'bbdd.5.final'!$AA:$AA,Vista!I27,'bbdd.5.final'!$Z:$Z,$J$13,'bbdd.5.final'!$J:$J,"Opex") -> 223492.08 | M27: =M26+1 -> 12 | N27: =P27/$P$15 -> 0.0074776906 | O27: =_xlfn.XLOOKUP($M27,'rubros_id_opex (2)'!$B:$B,'rubros_id_opex (2)'!$A:$A) -> REPOSICION | P27: =SUMIFS('bbdd.5.final'!$Y:$Y,'bbdd.5.final'!$AA:$AA,Vista!M27,'bbdd.5.final'!$Z:$Z,$N$13,'bbdd.5.final'!$J:$J,"Opex") -> 1455313.4
A28: =A27+1 -> 13 | B28: =D28/$D$15 -> 0.013425965 | C28: =_xlfn.XLOOKUP($A28,'rubros_id_opex (2)'!$B:$B,'rubros_id_opex (2)'!$A:$A) -> SERVICIOS | D28: =SUMIFS('bbdd.5.final'!$Y:$Y,'bbdd.5.final'!$AA:$AA,Vista!A28,'bbdd.5.final'!$Z:$Z,$B$13,'bbdd.5.final'!$J:$J,"Opex") -> 122065.45 | E28: =E27+1 -> 13 | F28: =H28/$H$15 -> 0.58673799 | G28: =_xlfn.XLOOKUP($E28,'rubros_id_opex (2)'!$B:$B,'rubros_id_opex (2)'!$A:$A) -> SERVICIOS | H28: =SUMIFS('bbdd.5.final'!$Y:$Y,'bbdd.5.final'!$AA:$AA,Vista!E28,'bbdd.5.final'!$Z:$Z,$F$13,'bbdd.5.final'!$J:$J,"Opex") -> 22043278 | I28: =I27+1 -> 13 | J28: =L28/$L$15 -> 0.11444823 | K28: =_xlfn.XLOOKUP($I28,'rubros_id_opex (2)'!$B:$B,'rubros_id_opex (2)'!$A:$A) -> SERVICIOS | L28: =SUMIFS('bbdd.5.final'!$Y:$Y,'bbdd.5.final'!$AA:$AA,Vista!I28,'bbdd.5.final'!$Z:$Z,$J$13,'bbdd.5.final'!$J:$J,"Opex") -> 2694868.3 | M28: =M27+1 -> 13 | N28: =P28/$P$15 -> 0.0051057135 | O28: =_xlfn.XLOOKUP($M28,'rubros_id_opex (2)'!$B:$B,'rubros_id_opex (2)'!$A:$A) -> SERVICIOS | P28: =SUMIFS('bbdd.5.final'!$Y:$Y,'bbdd.5.final'!$AA:$AA,Vista!M28,'bbdd.5.final'!$Z:$Z,$N$13,'bbdd.5.final'!$J:$J,"Opex") -> 993677.54
A29: =A28+1 -> 14 | B29: =D29/$D$15 -> 0.00026256713 | C29: =_xlfn.XLOOKUP($A29,'rubros_id_opex (2)'!$B:$B,'rubros_id_opex (2)'!$A:$A) -> COMERCIAL | D29: =SUMIFS('bbdd.5.final'!$Y:$Y,'bbdd.5.final'!$AA:$AA,Vista!A29,'bbdd.5.final'!$Z:$Z,$B$13,'bbdd.5.final'!$J:$J,"Opex") -> 2387.1933 | E29: =E28+1 -> 14 | F29: =H29/$H$15 -> 0.00077951271 | G29: =_xlfn.XLOOKUP($E29,'rubros_id_opex (2)'!$B:$B,'rubros_id_opex (2)'!$A:$A) -> COMERCIAL | H29: =SUMIFS('bbdd.5.final'!$Y:$Y,'bbdd.5.final'!$AA:$AA,Vista!E29,'bbdd.5.final'!$Z:$Z,$F$13,'bbdd.5.final'!$J:$J,"Opex") -> 29285.67 | I29: =I28+1 -> 14 | J29: =L29/$L$15 -> 0.0022382258 | K29: =_xlfn.XLOOKUP($I29,'rubros_id_opex (2)'!$B:$B,'rubros_id_opex (2)'!$A:$A) -> COMERCIAL | L29: =SUMIFS('bbdd.5.final'!$Y:$Y,'bbdd.5.final'!$AA:$AA,Vista!I29,'bbdd.5.final'!$Z:$Z,$J$13,'bbdd.5.final'!$J:$J,"Opex") -> 52702.64 | M29: =M28+1 -> 14 | N29: =P29/$P$15 -> 9.9850737e-05 | O29: =_xlfn.XLOOKUP($M29,'rubros_id_opex (2)'!$B:$B,'rubros_id_opex (2)'!$A:$A) -> COMERCIAL | P29: =SUMIFS('bbdd.5.final'!$Y:$Y,'bbdd.5.final'!$AA:$AA,Vista!M29,'bbdd.5.final'!$Z:$Z,$N$13,'bbdd.5.final'!$J:$J,"Opex") -> 19433.02
B31: VENTAS | D31: =SUMIFS(BBDD_INGRESOS_FINAL!$O:$O,BBDD_INGRESOS_FINAL!$D:$D,B14) -> 5365216.3 | F31: VENTAS | H31: =SUMIFS(BBDD_INGRESOS_FINAL!$O:$O,BBDD_INGRESOS_FINAL!$D:$D,F14) -> 1.712503e+08 | J31: VENTAS | L31: =SUMIFS(BBDD_INGRESOS_FINAL!$O:$O,BBDD_INGRESOS_FINAL!$D:$D,J14) -> 253547470 | N31: VENTAS | P31: =SUMIFS(BBDD_INGRESOS_FINAL!$O:$O,BBDD_INGRESOS_FINAL!$D:$D,N14) -> 2.1218758e+08
B33: UTILDAD | D33: =D31-D15 -> -3726528.4 | F33: UTILDAD | H33: =H31-H15 -> 1.336811e+08 | J33: UTILDAD | L33: =L31-L15 -> 2.3000086e+08 | N33: UTILDAD | P33: =P31-P15 -> 17566880
B35: CAPEX | D35: =SUMIFS('bbdd.5.final'!$Y:$Y,'bbdd.5.final'!$J:$J,"Capex",'bbdd.5.final'!$Z:$Z,$B$13) -> 10596.047 | F35: CAPEX | H35: =SUMIFS('bbdd.5.final'!$Y:$Y,'bbdd.5.final'!$J:$J,"Capex",'bbdd.5.final'!$Z:$Z,$F$13) -> 1.8221133e+08 | J35: CAPEX | L35: =SUMIFS('bbdd.5.final'!$Y:$Y,'bbdd.5.final'!$J:$J,"Capex",'bbdd.5.final'!$Z:$Z,$J$13) -> 314945.75 | N35: CAPEX | P35: =SUMIFS('bbdd.5.final'!$Y:$Y,'bbdd.5.final'!$J:$J,"Capex",'bbdd.5.final'!$Z:$Z,$N$13) -> 13258557
B37: DEUDA | D37: =SUMIFS('bbdd.5.final'!$Y:$Y,'bbdd.5.final'!$J:$J,"Deuda",'bbdd.5.final'!$V:$V,B14) -> 0 | F37: DEUDA | H37: =SUMIFS('bbdd.5.final'!$Y:$Y,'bbdd.5.final'!$J:$J,"Deuda",'bbdd.5.final'!$V:$V,F14) -> 0 | J37: DEUDA | L37: =SUMIFS('bbdd.5.final'!$Y:$Y,'bbdd.5.final'!$J:$J,"deuda",'bbdd.5.final'!$V:$V,J14) -> 0 | N37: DEUDA | P37: =SUMIFS('bbdd.5.final'!$Y:$Y,'bbdd.5.final'!$J:$J,"deuda",'bbdd.5.final'!$V:$V,N14) -> 0
B39: Flujo de Caja al Accionista | D39: =D33-D37-D35 -> -3737124.5 | F39: Flujo de Caja al Accionista | H39: =H33-H37-H35 -> -48530232 | J39: Flujo de Caja al Accionista | L39: =L33-L37-L35 -> 2.2968591e+08 | N39: Flujo de Caja al Accionista | P39: =P33-P37-P35 -> 4308322.7
A41: id | B41: 1 | E41: id | F41: 6 | I41: id | J41: 10 | M41: id | N41: 2
B42: BACHAS | F42: NFU | J42: COMPOST & FERTILIZANTES | N42: CEREAL & POLVILLO
B43: OPEX | D43: =SUM(D44:D57) -> 1.0830115e+08 | F43: OPEX | H43: =SUM(H44:H57) -> 31513345 | J43: OPEX | L43: =SUM(L44:L57) -> 5032274.4 | N43: OPEX | P43: =SUM(P44:P57) -> 5360775.9
A44: 1 | B44: =D44/$D$43 -> 0.057430276 | C44: =_xlfn.XLOOKUP($A44,'rubros_id_opex (2)'!$B:$B,'rubros_id_opex (2)'!$A:$A) -> ENERGIA | D44: =SUMIFS('bbdd.5.final'!$Y:$Y,'bbdd.5.final'!$AA:$AA,Vista!A44,'bbdd.5.final'!$Z:$Z,$B$41,'bbdd.5.final'!$J:$J,"Opex") -> 6219764.7 | E44: 1 | F44: =H44/$H$43 -> 0.45344772 | G44: =_xlfn.XLOOKUP($A44,'rubros_id_opex (2)'!$B:$B,'rubros_id_opex (2)'!$A:$A) -> ENERGIA | H44: =SUMIFS('bbdd.5.final'!$Y:$Y,'bbdd.5.final'!$AA:$AA,Vista!E44,'bbdd.5.final'!$Z:$Z,$F$41,'bbdd.5.final'!$J:$J,"Opex") -> 14289655 | I44: 1 | J44: =L44/$L$43 -> 0.0011912217 | K44: =_xlfn.XLOOKUP($A44,'rubros_id_opex (2)'!$B:$B,'rubros_id_opex (2)'!$A:$A) -> ENERGIA | L44: =SUMIFS('bbdd.5.final'!$Y:$Y,'bbdd.5.final'!$AA:$AA,Vista!I44,'bbdd.5.final'!$Z:$Z,$J$41,'bbdd.5.final'!$J:$J,"Opex") -> 5994.5544 | M44: 1 | N44: =P44/$P$43 -> 0.018836213 | O44: =_xlfn.XLOOKUP($A44,'rubros_id_opex (2)'!$B:$B,'rubros_id_opex (2)'!$A:$A) -> ENERGIA | P44: =SUMIFS('bbdd.5.final'!$Y:$Y,'bbdd.5.final'!$AA:$AA,Vista!M44,'bbdd.5.final'!$Z:$Z,$N$41,'bbdd.5.final'!$J:$J,"Opex") -> 100976.72
A45: =A44+1 -> 2 | B45: =D45/$D$43 -> 0.00043252458 | C45: =_xlfn.XLOOKUP($A45,'rubros_id_opex (2)'!$B:$B,'rubros_id_opex (2)'!$A:$A) -> HABILITACIONES Y CERT | D45: =SUMIFS('bbdd.5.final'!$Y:$Y,'bbdd.5.final'!$AA:$AA,Vista!A45,'bbdd.5.final'!$Z:$Z,$B$41,'bbdd.5.final'!$J:$J,"Opex") -> 46842.907 | E45: =E44+1 -> 2 | F45: =H45/$H$43 -> 0.00064494846 | G45: =_xlfn.XLOOKUP($A45,'rubros_id_opex (2)'!$B:$B,'rubros_id_opex (2)'!$A:$A) -> HABILITACIONES Y CERT | H45: =SUMIFS('bbdd.5.final'!$Y:$Y,'bbdd.5.final'!$AA:$AA,Vista!E45,'bbdd.5.final'!$Z:$Z,$F$41,'bbdd.5.final'!$J:$J,"Opex") -> 20324.484 | I45: =I44+1 -> 2 | J45: =L45/$L$43 -> 0.00011673438 | K45: =_xlfn.XLOOKUP($A45,'rubros_id_opex (2)'!$B:$B,'rubros_id_opex (2)'!$A:$A) -> HABILITACIONES Y CERT | L45: =SUMIFS('bbdd.5.final'!$Y:$Y,'bbdd.5.final'!$AA:$AA,Vista!I45,'bbdd.5.final'!$Z:$Z,$J$41,'bbdd.5.final'!$J:$J,"Opex") -> 587.43945 | M45: =M44+1 -> 2 | N45: =P45/$P$43 -> 0.0019029499 | O45: =_xlfn.XLOOKUP($A45,'rubros_id_opex (2)'!$B:$B,'rubros_id_opex (2)'!$A:$A) -> HABILITACIONES Y CERT | P45: =SUMIFS('bbdd.5.final'!$Y:$Y,'bbdd.5.final'!$AA:$AA,Vista!M45,'bbdd.5.final'!$Z:$Z,$N$41,'bbdd.5.final'!$J:$J,"Opex") -> 10201.288
A46: =A45+1 -> 3 | B46: =D46/$D$43 -> 0.00072021632 | C46: =_xlfn.XLOOKUP($A46,'rubros_id_opex (2)'!$B:$B,'rubros_id_opex (2)'!$A:$A) -> HIGIENE Y SEGURIDAD | D46: =SUMIFS('bbdd.5.final'!$Y:$Y,'bbdd.5.final'!$AA:$AA,Vista!A46,'bbdd.5.final'!$Z:$Z,$B$41,'bbdd.5.final'!$J:$J,"Opex") -> 78000.253 | E46: =E45+1 -> 3 | F46: =H46/$H$43 -> 0.001073933 | G46: =_xlfn.XLOOKUP($A46,'rubros_id_opex (2)'!$B:$B,'rubros_id_opex (2)'!$A:$A) -> HIGIENE Y SEGURIDAD | H46: =SUMIFS('bbdd.5.final'!$Y:$Y,'bbdd.5.final'!$AA:$AA,Vista!E46,'bbdd.5.final'!$Z:$Z,$F$41,'bbdd.5.final'!$J:$J,"Opex") -> 33843.221 | I46: =I45+1 -> 3 | J46: =L46/$L$43 -> 0.00019437973 | K46: =_xlfn.XLOOKUP($A46,'rubros_id_opex (2)'!$B:$B,'rubros_id_opex (2)'!$A:$A) -> HIGIENE Y SEGURIDAD | L46: =SUMIFS('bbdd.5.final'!$Y:$Y,'bbdd.5.final'!$AA:$AA,Vista!I46,'bbdd.5.final'!$Z:$Z,$J$41,'bbdd.5.final'!$J:$J,"Opex") -> 978.17212 | M46: =M45+1 -> 3 | N46: =P46/$P$43 -> 0.0031686884 | O46: =_xlfn.XLOOKUP($A46,'rubros_id_opex (2)'!$B:$B,'rubros_id_opex (2)'!$A:$A) -> HIGIENE Y SEGURIDAD | P46: =SUMIFS('bbdd.5.final'!$Y:$Y,'bbdd.5.final'!$AA:$AA,Vista!M46,'bbdd.5.final'!$Z:$Z,$N$41,'bbdd.5.final'!$J:$J,"Opex") -> 16986.628
A47: =A46+1 -> 4 | B47: =D47/$D$43 -> 0.0015403386 | C47: =_xlfn.XLOOKUP($A47,'rubros_id_opex (2)'!$B:$B,'rubros_id_opex (2)'!$A:$A) -> IMPUESTOS | D47: =SUMIFS('bbdd.5.final'!$Y:$Y,'bbdd.5.final'!$AA:$AA,Vista!A47,'bbdd.5.final'!$Z:$Z,$B$41,'bbdd.5.final'!$J:$J,"Opex") -> 166820.44 | E47: =E46+1 -> 4 | F47: =H47/$H$43 -> 0.029369377 | G47: =_xlfn.XLOOKUP($A47,'rubros_id_opex (2)'!$B:$B,'rubros_id_opex (2)'!$A:$A) -> IMPUESTOS | H47: =SUMIFS('bbdd.5.final'!$Y:$Y,'bbdd.5.final'!$AA:$AA,Vista!E47,'bbdd.5.final'!$Z:$Z,$F$41,'bbdd.5.final'!$J:$J,"Opex") -> 925527.33 | I47: =I46+1 -> 4 | J47: =L47/$L$43 -> 0.033488186 | K47: =_xlfn.XLOOKUP($A47,'rubros_id_opex (2)'!$B:$B,'rubros_id_opex (2)'!$A:$A) -> IMPUESTOS | L47: =SUMIFS('bbdd.5.final'!$Y:$Y,'bbdd.5.final'!$AA:$AA,Vista!I47,'bbdd.5.final'!$Z:$Z,$J$41,'bbdd.5.final'!$J:$J,"Opex") -> 168521.74 | M47: =M46+1 -> 4 | N47: =P47/$P$43 -> 0.0067769265 | O47: =_xlfn.XLOOKUP($A47,'rubros_id_opex (2)'!$B:$B,'rubros_id_opex (2)'!$A:$A) -> IMPUESTOS | P47: =SUMIFS('bbdd.5.final'!$Y:$Y,'bbdd.5.final'!$AA:$AA,Vista!M47,'bbdd.5.final'!$Z:$Z,$N$41,'bbdd.5.final'!$J:$J,"Opex") -> 36329.584
A48: =A47+1 -> 5 | B48: =D48/$D$43 -> 0.044643114 | C48: =_xlfn.XLOOKUP($A48,'rubros_id_opex (2)'!$B:$B,'rubros_id_opex (2)'!$A:$A) -> INSUMOS | D48: =SUMIFS('bbdd.5.final'!$Y:$Y,'bbdd.5.final'!$AA:$AA,Vista!A48,'bbdd.5.final'!$Z:$Z,$B$41,'bbdd.5.final'!$J:$J,"Opex") -> 4834900.4 | E48: =E47+1 -> 5 | F48: =H48/$H$43 -> 0.0008489496 | G48: =_xlfn.XLOOKUP($A48,'rubros_id_opex (2)'!$B:$B,'rubros_id_opex (2)'!$A:$A) -> INSUMOS | H48: =SUMIFS('bbdd.5.final'!$Y:$Y,'bbdd.5.final'!$AA:$AA,Vista!E48,'bbdd.5.final'!$Z:$Z,$F$41,'bbdd.5.final'!$J:$J,"Opex") -> 26753.242 | I48: =I47+1 -> 5 | J48: =L48/$L$43 -> 0.00015365818 | K48: =_xlfn.XLOOKUP($A48,'rubros_id_opex (2)'!$B:$B,'rubros_id_opex (2)'!$A:$A) -> INSUMOS | L48: =SUMIFS('bbdd.5.final'!$Y:$Y,'bbdd.5.final'!$AA:$AA,Vista!I48,'bbdd.5.final'!$Z:$Z,$J$41,'bbdd.5.final'!$J:$J,"Opex") -> 773.25014 | M48: =M47+1 -> 5 | N48: =P48/$P$43 -> 0.0025048646 | O48: =_xlfn.XLOOKUP($A48,'rubros_id_opex (2)'!$B:$B,'rubros_id_opex (2)'!$A:$A) -> INSUMOS | P48: =SUMIFS('bbdd.5.final'!$Y:$Y,'bbdd.5.final'!$AA:$AA,Vista!M48,'bbdd.5.final'!$Z:$Z,$N$41,'bbdd.5.final'!$J:$J,"Opex") -> 13428.018
A49: =A48+1 -> 6 | B49: =D49/$D$43 -> 0 | C49: =_xlfn.XLOOKUP($A49,'rubros_id_opex (2)'!$B:$B,'rubros_id_opex (2)'!$A:$A) -> INVERSION | D49: =SUMIFS('bbdd.5.final'!$Y:$Y,'bbdd.5.final'!$AA:$AA,Vista!A49,'bbdd.5.final'!$Z:$Z,$B$41,'bbdd.5.final'!$J:$J,"Opex") -> 0 | E49: =E48+1 -> 6 | F49: =H49/$H$43 -> 0 | G49: =_xlfn.XLOOKUP($A49,'rubros_id_opex (2)'!$B:$B,'rubros_id_opex (2)'!$A:$A) -> INVERSION | H49: =SUMIFS('bbdd.5.final'!$Y:$Y,'bbdd.5.final'!$AA:$AA,Vista!E49,'bbdd.5.final'!$Z:$Z,$F$41,'bbdd.5.final'!$J:$J,"Opex") -> 0 | I49: =I48+1 -> 6 | J49: =L49/$L$43 -> 0 | K49: =_xlfn.XLOOKUP($A49,'rubros_id_opex (2)'!$B:$B,'rubros_id_opex (2)'!$A:$A) -> INVERSION | L49: =SUMIFS('bbdd.5.final'!$Y:$Y,'bbdd.5.final'!$AA:$AA,Vista!I49,'bbdd.5.final'!$Z:$Z,$J$41,'bbdd.5.final'!$J:$J,"Opex") -> 0 | M49: =M48+1 -> 6 | N49: =P49/$P$43 -> 0 | O49: =_xlfn.XLOOKUP($A49,'rubros_id_opex (2)'!$B:$B,'rubros_id_opex (2)'!$A:$A) -> INVERSION | P49: =SUMIFS('bbdd.5.final'!$Y:$Y,'bbdd.5.final'!$AA:$AA,Vista!M49,'bbdd.5.final'!$Z:$Z,$N$41,'bbdd.5.final'!$J:$J,"Opex") -> 0
A50: =A49+1 -> 7 | B50: =D50/$D$43 -> 0 | C50: =_xlfn.XLOOKUP($A50,'rubros_id_opex (2)'!$B:$B,'rubros_id_opex (2)'!$A:$A) -> LOGISTICA | D50: =SUMIFS('bbdd.5.final'!$Y:$Y,'bbdd.5.final'!$AA:$AA,Vista!A50,'bbdd.5.final'!$Z:$Z,$B$41,'bbdd.5.final'!$J:$J,"Opex") -> 0 | E50: =E49+1 -> 7 | F50: =H50/$H$43 -> 9.2151435e-05 | G50: =_xlfn.XLOOKUP($A50,'rubros_id_opex (2)'!$B:$B,'rubros_id_opex (2)'!$A:$A) -> LOGISTICA | H50: =SUMIFS('bbdd.5.final'!$Y:$Y,'bbdd.5.final'!$AA:$AA,Vista!E50,'bbdd.5.final'!$Z:$Z,$F$41,'bbdd.5.final'!$J:$J,"Opex") -> 2904 | I50: =I49+1 -> 7 | J50: =L50/$L$43 -> 0 | K50: =_xlfn.XLOOKUP($A50,'rubros_id_opex (2)'!$B:$B,'rubros_id_opex (2)'!$A:$A) -> LOGISTICA | L50: =SUMIFS('bbdd.5.final'!$Y:$Y,'bbdd.5.final'!$AA:$AA,Vista!I50,'bbdd.5.final'!$Z:$Z,$J$41,'bbdd.5.final'!$J:$J,"Opex") -> 0 | M50: =M49+1 -> 7 | N50: =P50/$P$43 -> 0.077973788 | O50: =_xlfn.XLOOKUP($A50,'rubros_id_opex (2)'!$B:$B,'rubros_id_opex (2)'!$A:$A) -> LOGISTICA | P50: =SUMIFS('bbdd.5.final'!$Y:$Y,'bbdd.5.final'!$AA:$AA,Vista!M50,'bbdd.5.final'!$Z:$Z,$N$41,'bbdd.5.final'!$J:$J,"Opex") -> 418000
A51: =A50+1 -> 8 | B51: =D51/$D$43 -> 0.80828689 | C51: =_xlfn.XLOOKUP($A51,'rubros_id_opex (2)'!$B:$B,'rubros_id_opex (2)'!$A:$A) -> M.PRIMAS | D51: =SUMIFS('bbdd.5.final'!$Y:$Y,'bbdd.5.final'!$AA:$AA,Vista!A51,'bbdd.5.final'!$Z:$Z,$B$41,'bbdd.5.final'!$J:$J,"Opex") -> 87538396 | E51: =E50+1 -> 8 | F51: =H51/$H$43 -> 0 | G51: =_xlfn.XLOOKUP($A51,'rubros_id_opex (2)'!$B:$B,'rubros_id_opex (2)'!$A:$A) -> M.PRIMAS | H51: =SUMIFS('bbdd.5.final'!$Y:$Y,'bbdd.5.final'!$AA:$AA,Vista!E51,'bbdd.5.final'!$Z:$Z,$F$41,'bbdd.5.final'!$J:$J,"Opex") -> 0 | I51: =I50+1 -> 8 | J51: =L51/$L$43 -> 0 | K51: =_xlfn.XLOOKUP($A51,'rubros_id_opex (2)'!$B:$B,'rubros_id_opex (2)'!$A:$A) -> M.PRIMAS | L51: =SUMIFS('bbdd.5.final'!$Y:$Y,'bbdd.5.final'!$AA:$AA,Vista!I51,'bbdd.5.final'!$Z:$Z,$J$41,'bbdd.5.final'!$J:$J,"Opex") -> 0 | M51: =M50+1 -> 8 | N51: =P51/$P$43 -> 0 | O51: =_xlfn.XLOOKUP($A51,'rubros_id_opex (2)'!$B:$B,'rubros_id_opex (2)'!$A:$A) -> M.PRIMAS | P51: =SUMIFS('bbdd.5.final'!$Y:$Y,'bbdd.5.final'!$AA:$AA,Vista!M51,'bbdd.5.final'!$Z:$Z,$N$41,'bbdd.5.final'!$J:$J,"Opex") -> 0
A52: =A51+1 -> 9 | B52: =D52/$D$43 -> 0.00040615192 | C52: =_xlfn.XLOOKUP($A52,'rubros_id_opex (2)'!$B:$B,'rubros_id_opex (2)'!$A:$A) -> MANTENIMIENTO PREVENTIVO | D52: =SUMIFS('bbdd.5.final'!$Y:$Y,'bbdd.5.final'!$AA:$AA,Vista!A52,'bbdd.5.final'!$Z:$Z,$B$41,'bbdd.5.final'!$J:$J,"Opex") -> 43986.718 | E52: =E51+1 -> 9 | F52: =H52/$H$43 -> 0.0078849294 | G52: =_xlfn.XLOOKUP($A52,'rubros_id_opex (2)'!$B:$B,'rubros_id_opex (2)'!$A:$A) -> MANTENIMIENTO PREVENTIVO | H52: =SUMIFS('bbdd.5.final'!$Y:$Y,'bbdd.5.final'!$AA:$AA,Vista!E52,'bbdd.5.final'!$Z:$Z,$F$41,'bbdd.5.final'!$J:$J,"Opex") -> 248480.5 | I52: =I51+1 -> 9 | J52: =L52/$L$43 -> 0.00010961665 | K52: =_xlfn.XLOOKUP($A52,'rubros_id_opex (2)'!$B:$B,'rubros_id_opex (2)'!$A:$A) -> MANTENIMIENTO PREVENTIVO | L52: =SUMIFS('bbdd.5.final'!$Y:$Y,'bbdd.5.final'!$AA:$AA,Vista!I52,'bbdd.5.final'!$Z:$Z,$J$41,'bbdd.5.final'!$J:$J,"Opex") -> 551.62105 | M52: =M51+1 -> 9 | N52: =P52/$P$43 -> 0.0017869199 | O52: =_xlfn.XLOOKUP($A52,'rubros_id_opex (2)'!$B:$B,'rubros_id_opex (2)'!$A:$A) -> MANTENIMIENTO PREVENTIVO | P52: =SUMIFS('bbdd.5.final'!$Y:$Y,'bbdd.5.final'!$AA:$AA,Vista!M52,'bbdd.5.final'!$Z:$Z,$N$41,'bbdd.5.final'!$J:$J,"Opex") -> 9579.2771
A53: =A52+1 -> 10 | B53: =D53/$D$43 -> 0.076506213 | C53: =_xlfn.XLOOKUP($A53,'rubros_id_opex (2)'!$B:$B,'rubros_id_opex (2)'!$A:$A) -> PERSONAL | D53: =SUMIFS('bbdd.5.final'!$Y:$Y,'bbdd.5.final'!$AA:$AA,Vista!A53,'bbdd.5.final'!$Z:$Z,$B$41,'bbdd.5.final'!$J:$J,"Opex") -> 8285710.6 | E53: =E52+1 -> 10 | F53: =H53/$H$43 -> 0.41008469 | G53: =_xlfn.XLOOKUP($A53,'rubros_id_opex (2)'!$B:$B,'rubros_id_opex (2)'!$A:$A) -> PERSONAL | H53: =SUMIFS('bbdd.5.final'!$Y:$Y,'bbdd.5.final'!$AA:$AA,Vista!E53,'bbdd.5.final'!$Z:$Z,$F$41,'bbdd.5.final'!$J:$J,"Opex") -> 12923140 | I53: =I52+1 -> 10 | J53: =L53/$L$43 -> 0.96203805 | K53: =_xlfn.XLOOKUP($A53,'rubros_id_opex (2)'!$B:$B,'rubros_id_opex (2)'!$A:$A) -> PERSONAL | L53: =SUMIFS('bbdd.5.final'!$Y:$Y,'bbdd.5.final'!$AA:$AA,Vista!I53,'bbdd.5.final'!$Z:$Z,$J$41,'bbdd.5.final'!$J:$J,"Opex") -> 4841239.4 | M53: =M52+1 -> 10 | N53: =P53/$P$43 -> 0.84290252 | O53: =_xlfn.XLOOKUP($A53,'rubros_id_opex (2)'!$B:$B,'rubros_id_opex (2)'!$A:$A) -> PERSONAL | P53: =SUMIFS('bbdd.5.final'!$Y:$Y,'bbdd.5.final'!$AA:$AA,Vista!M53,'bbdd.5.final'!$Z:$Z,$N$41,'bbdd.5.final'!$J:$J,"Opex") -> 4518611.5
A54: =A53+1 -> 11 | B54: =D54/$D$43 -> 0.0019790304 | C54: =_xlfn.XLOOKUP($A54,'rubros_id_opex (2)'!$B:$B,'rubros_id_opex (2)'!$A:$A) -> REPARACIONES | D54: =SUMIFS('bbdd.5.final'!$Y:$Y,'bbdd.5.final'!$AA:$AA,Vista!A54,'bbdd.5.final'!$Z:$Z,$B$41,'bbdd.5.final'!$J:$J,"Opex") -> 214331.27 | E54: =E53+1 -> 11 | F54: =H54/$H$43 -> 0.0029509829 | G54: =_xlfn.XLOOKUP($A54,'rubros_id_opex (2)'!$B:$B,'rubros_id_opex (2)'!$A:$A) -> REPARACIONES | H54: =SUMIFS('bbdd.5.final'!$Y:$Y,'bbdd.5.final'!$AA:$AA,Vista!E54,'bbdd.5.final'!$Z:$Z,$F$41,'bbdd.5.final'!$J:$J,"Opex") -> 92995.345 | I54: =I53+1 -> 11 | J54: =L54/$L$43 -> 0.00053412202 | K54: =_xlfn.XLOOKUP($A54,'rubros_id_opex (2)'!$B:$B,'rubros_id_opex (2)'!$A:$A) -> REPARACIONES | L54: =SUMIFS('bbdd.5.final'!$Y:$Y,'bbdd.5.final'!$AA:$AA,Vista!I54,'bbdd.5.final'!$Z:$Z,$J$41,'bbdd.5.final'!$J:$J,"Opex") -> 2687.8486 | M54: =M53+1 -> 11 | N54: =P54/$P$43 -> 0.0087070102 | O54: =_xlfn.XLOOKUP($A54,'rubros_id_opex (2)'!$B:$B,'rubros_id_opex (2)'!$A:$A) -> REPARACIONES | P54: =SUMIFS('bbdd.5.final'!$Y:$Y,'bbdd.5.final'!$AA:$AA,Vista!M54,'bbdd.5.final'!$Z:$Z,$N$41,'bbdd.5.final'!$J:$J,"Opex") -> 46676.33
A55: =A54+1 -> 12 | B55: =D55/$D$43 -> 0.00041198955 | C55: =_xlfn.XLOOKUP($A55,'rubros_id_opex (2)'!$B:$B,'rubros_id_opex (2)'!$A:$A) -> REPOSICION | D55: =SUMIFS('bbdd.5.final'!$Y:$Y,'bbdd.5.final'!$AA:$AA,Vista!A55,'bbdd.5.final'!$Z:$Z,$B$41,'bbdd.5.final'!$J:$J,"Opex") -> 44618.94 | E55: =E54+1 -> 12 | F55: =H55/$H$43 -> 0.0015727669 | G55: =_xlfn.XLOOKUP($A55,'rubros_id_opex (2)'!$B:$B,'rubros_id_opex (2)'!$A:$A) -> REPOSICION | H55: =SUMIFS('bbdd.5.final'!$Y:$Y,'bbdd.5.final'!$AA:$AA,Vista!E55,'bbdd.5.final'!$Z:$Z,$F$41,'bbdd.5.final'!$J:$J,"Opex") -> 49563.145 | I55: =I54+1 -> 12 | J55: =L55/$L$43 -> 0.00011119217 | K55: =_xlfn.XLOOKUP($A55,'rubros_id_opex (2)'!$B:$B,'rubros_id_opex (2)'!$A:$A) -> REPOSICION | L55: =SUMIFS('bbdd.5.final'!$Y:$Y,'bbdd.5.final'!$AA:$AA,Vista!I55,'bbdd.5.final'!$Z:$Z,$J$41,'bbdd.5.final'!$J:$J,"Opex") -> 559.54951 | M55: =M54+1 -> 12 | N55: =P55/$P$43 -> 0.0018126033 | O55: =_xlfn.XLOOKUP($A55,'rubros_id_opex (2)'!$B:$B,'rubros_id_opex (2)'!$A:$A) -> REPOSICION | P55: =SUMIFS('bbdd.5.final'!$Y:$Y,'bbdd.5.final'!$AA:$AA,Vista!M55,'bbdd.5.final'!$Z:$Z,$N$41,'bbdd.5.final'!$J:$J,"Opex") -> 9716.9602
A56: =A55+1 -> 13 | B56: =D56/$D$43 -> 0.0074966439 | C56: =_xlfn.XLOOKUP($A56,'rubros_id_opex (2)'!$B:$B,'rubros_id_opex (2)'!$A:$A) -> SERVICIOS | D56: =SUMIFS('bbdd.5.final'!$Y:$Y,'bbdd.5.final'!$AA:$AA,Vista!A56,'bbdd.5.final'!$Z:$Z,$B$41,'bbdd.5.final'!$J:$J,"Opex") -> 811895.13 | E56: =E55+1 -> 13 | F56: =H56/$H$43 -> 0.091810943 | G56: =_xlfn.XLOOKUP($A56,'rubros_id_opex (2)'!$B:$B,'rubros_id_opex (2)'!$A:$A) -> SERVICIOS | H56: =SUMIFS('bbdd.5.final'!$Y:$Y,'bbdd.5.final'!$AA:$AA,Vista!E56,'bbdd.5.final'!$Z:$Z,$F$41,'bbdd.5.final'!$J:$J,"Opex") -> 2893270 | I56: =I55+1 -> 13 | J56: =L56/$L$43 -> 0.0020232749 | K56: =_xlfn.XLOOKUP($A56,'rubros_id_opex (2)'!$B:$B,'rubros_id_opex (2)'!$A:$A) -> SERVICIOS | L56: =SUMIFS('bbdd.5.final'!$Y:$Y,'bbdd.5.final'!$AA:$AA,Vista!I56,'bbdd.5.final'!$Z:$Z,$J$41,'bbdd.5.final'!$J:$J,"Opex") -> 10181.674 | M56: =M55+1 -> 13 | N56: =P56/$P$43 -> 0.032982491 | O56: =_xlfn.XLOOKUP($A56,'rubros_id_opex (2)'!$B:$B,'rubros_id_opex (2)'!$A:$A) -> SERVICIOS | P56: =SUMIFS('bbdd.5.final'!$Y:$Y,'bbdd.5.final'!$AA:$AA,Vista!M56,'bbdd.5.final'!$Z:$Z,$N$41,'bbdd.5.final'!$J:$J,"Opex") -> 176811.74
A57: =A56+1 -> 14 | B57: =D57/$D$43 -> 0.00014660937 | C57: =_xlfn.XLOOKUP($A57,'rubros_id_opex (2)'!$B:$B,'rubros_id_opex (2)'!$A:$A) -> COMERCIAL | D57: =SUMIFS('bbdd.5.final'!$Y:$Y,'bbdd.5.final'!$AA:$AA,Vista!A57,'bbdd.5.final'!$Z:$Z,$B$41,'bbdd.5.final'!$J:$J,"Opex") -> 15877.962 | E57: =E56+1 -> 14 | F57: =H57/$H$43 -> 0.00021861298 | G57: =_xlfn.XLOOKUP($A57,'rubros_id_opex (2)'!$B:$B,'rubros_id_opex (2)'!$A:$A) -> COMERCIAL | H57: =SUMIFS('bbdd.5.final'!$Y:$Y,'bbdd.5.final'!$AA:$AA,Vista!E57,'bbdd.5.final'!$Z:$Z,$F$41,'bbdd.5.final'!$J:$J,"Opex") -> 6889.2262 | I57: =I56+1 -> 14 | J57: =L57/$L$43 -> 3.9568512e-05 | K57: =_xlfn.XLOOKUP($A57,'rubros_id_opex (2)'!$B:$B,'rubros_id_opex (2)'!$A:$A) -> COMERCIAL | L57: =SUMIFS('bbdd.5.final'!$Y:$Y,'bbdd.5.final'!$AA:$AA,Vista!I57,'bbdd.5.final'!$Z:$Z,$J$41,'bbdd.5.final'!$J:$J,"Opex") -> 199.11961 | M57: =M56+1 -> 14 | N57: =P57/$P$43 -> 0.00064502759 | O57: =_xlfn.XLOOKUP($A57,'rubros_id_opex (2)'!$B:$B,'rubros_id_opex (2)'!$A:$A) -> COMERCIAL | P57: =SUMIFS('bbdd.5.final'!$Y:$Y,'bbdd.5.final'!$AA:$AA,Vista!M57,'bbdd.5.final'!$Z:$Z,$N$41,'bbdd.5.final'!$J:$J,"Opex") -> 3457.8483
B59: VENTAS | D59: =SUMIFS(BBDD_INGRESOS_FINAL!$O:$O,BBDD_INGRESOS_FINAL!$D:$D,B42) -> 1.151894e+08 | F59: VENTAS | H59: =SUMIFS(BBDD_INGRESOS_FINAL!$O:$O,BBDD_INGRESOS_FINAL!$D:$D,F42) -> 36666425 | J59: VENTAS | L59: =SUMIFS(BBDD_INGRESOS_FINAL!$O:$O,BBDD_INGRESOS_FINAL!$D:$D,J42) -> 0 | N59: VENTAS | P59: =SUMIFS(BBDD_INGRESOS_FINAL!$O:$O,BBDD_INGRESOS_FINAL!$D:$D,N42) -> 25207646
B61: UTILDAD | D61: =D59-D43 -> 6888257.8 | F61: UTILDAD | H61: =H59-H43 -> 5153079.8 | J61: UTILDAD | L61: =L59-L43 -> -5032274.4 | N61: UTILDAD | P61: =P59-P43 -> 19846870
B63: CAPEX | D63: =SUMIFS('bbdd.5.final'!$Y:$Y,'bbdd.5.final'!$J:$J,"Capex",'bbdd.5.final'!$Z:$Z,$B$41) -> 70477.593 | F63: CAPEX | H63: =SUMIFS('bbdd.5.final'!$Y:$Y,'bbdd.5.final'!$J:$J,"Capex",'bbdd.5.final'!$Z:$Z,$F$41) -> 34543156 | J63: CAPEX | L63: =SUMIFS('bbdd.5.final'!$Y:$Y,'bbdd.5.final'!$J:$J,"Capex",'bbdd.5.final'!$Z:$Z,$J$41) -> 883.83325 | N63: CAPEX | P63: =SUMIFS('bbdd.5.final'!$Y:$Y,'bbdd.5.final'!$J:$J,"Capex",'bbdd.5.final'!$Z:$Z,$N$41) -> 15348.369
O64: INVERSION
B65: DEUDA | D65: =SUMIFS('bbdd.5.final'!$Y:$Y,'bbdd.5.final'!$J:$J,"deuda",'bbdd.5.final'!$V:$V,B42) -> 0 | F65: DEUDA | H65: =SUMIFS('bbdd.5.final'!$Y:$Y,'bbdd.5.final'!$J:$J,"deuda",'bbdd.5.final'!$V:$V,F42) -> 0 | J65: DEUDA | L65: =SUMIFS('bbdd.5.final'!$Y:$Y,'bbdd.5.final'!$J:$J,"deuda",'bbdd.5.final'!$V:$V,J42) -> 0 | N65: DEUDA | P65: =SUMIFS('bbdd.5.final'!$Y:$Y,'bbdd.5.final'!$J:$J,"deuda",'bbdd.5.final'!$V:$V,N42) -> 0
B67: Flujo de Caja al Accionista | D67: =D61-D65-D63 -> 6817780.2 | F67: Flujo de Caja al Accionista | H67: =H61-H65-H63 -> -29390076 | J67: Flujo de Caja al Accionista | L67: =L61-L65-L63 -> -5033158.2 | N67: Flujo de Caja al Accionista | P67: =P61-P65-P63 -> 19831522
A69: id | B69: 9 | E69: id | F69: 5
B70: EXPORTACION
B71: OPEX | D71: =SUM(D72:D85) -> 2.562834e+09
A72: 1 | B72: =D72/D71 -> 0.0044561546 | C72: =_xlfn.XLOOKUP($E72,'rubros_id_opex (2)'!$B:$B,'rubros_id_opex (2)'!$A:$A) -> ENERGIA | D72: =SUMIFS('bbdd.5.final'!$Y:$Y,'bbdd.5.final'!$AA:$AA,Vista!E72,'bbdd.5.final'!$Z:$Z,$F$69,'bbdd.5.final'!$J:$J,"Opex") -> 11420385 | E72: 1 | I72: 1
A73: =A72+1 -> 2 | B73: =D73/$D$71 -> 0.00097383975 | C73: =_xlfn.XLOOKUP($E73,'rubros_id_opex (2)'!$B:$B,'rubros_id_opex (2)'!$A:$A) -> HABILITACIONES Y CERT | D73: =SUMIFS('bbdd.5.final'!$Y:$Y,'bbdd.5.final'!$AA:$AA,Vista!E73,'bbdd.5.final'!$Z:$Z,$F$69,'bbdd.5.final'!$J:$J,"Opex") -> 2495789.7 | E73: =E72+1 -> 2 | I73: =I72+1 -> 2
A74: =A73+1 -> 3 | B74: =D74/$D$71 -> 0.00068922491 | C74: =_xlfn.XLOOKUP($E74,'rubros_id_opex (2)'!$B:$B,'rubros_id_opex (2)'!$A:$A) -> HIGIENE Y SEGURIDAD | D74: =SUMIFS('bbdd.5.final'!$Y:$Y,'bbdd.5.final'!$AA:$AA,Vista!E74,'bbdd.5.final'!$Z:$Z,$F$69,'bbdd.5.final'!$J:$J,"Opex") -> 1766369.1 | E74: =E73+1 -> 3 | I74: =I73+1 -> 3
A75: =A74+1 -> 4 | B75: =D75/$D$71 -> 0.0019963439 | C75: =_xlfn.XLOOKUP($E75,'rubros_id_opex (2)'!$B:$B,'rubros_id_opex (2)'!$A:$A) -> IMPUESTOS | D75: =SUMIFS('bbdd.5.final'!$Y:$Y,'bbdd.5.final'!$AA:$AA,Vista!E75,'bbdd.5.final'!$Z:$Z,$F$69,'bbdd.5.final'!$J:$J,"Opex") -> 5116298 | E75: =E74+1 -> 4 | I75: =I74+1 -> 4
A76: =A75+1 -> 5 | B76: =D76/$D$71 -> 0.00054483587 | C76: =_xlfn.XLOOKUP($E76,'rubros_id_opex (2)'!$B:$B,'rubros_id_opex (2)'!$A:$A) -> INSUMOS | D76: =SUMIFS('bbdd.5.final'!$Y:$Y,'bbdd.5.final'!$AA:$AA,Vista!E76,'bbdd.5.final'!$Z:$Z,$F$69,'bbdd.5.final'!$J:$J,"Opex") -> 1396323.9 | E76: =E75+1 -> 5 | I76: =I75+1 -> 5
A77: =A76+1 -> 6 | B77: =D77/$D$71 -> 0 | C77: =_xlfn.XLOOKUP($E77,'rubros_id_opex (2)'!$B:$B,'rubros_id_opex (2)'!$A:$A) -> INVERSION | D77: =SUMIFS('bbdd.5.final'!$Y:$Y,'bbdd.5.final'!$AA:$AA,Vista!E77,'bbdd.5.final'!$Z:$Z,$F$69,'bbdd.5.final'!$J:$J,"Opex") -> 0 | E77: =E76+1 -> 6 | I77: =I76+1 -> 6
A78: =A77+1 -> 7 | B78: =D78/$D$71 -> 0.016103617 | C78: =_xlfn.XLOOKUP($E78,'rubros_id_opex (2)'!$B:$B,'rubros_id_opex (2)'!$A:$A) -> LOGISTICA | D78: =SUMIFS('bbdd.5.final'!$Y:$Y,'bbdd.5.final'!$AA:$AA,Vista!E78,'bbdd.5.final'!$Z:$Z,$F$69,'bbdd.5.final'!$J:$J,"Opex") -> 41270898 | E78: =E77+1 -> 7 | I78: =I77+1 -> 7
A79: =A78+1 -> 8 | B79: =D79/$D$71 -> 0.94708107 | C79: =_xlfn.XLOOKUP($E79,'rubros_id_opex (2)'!$B:$B,'rubros_id_opex (2)'!$A:$A) -> M.PRIMAS | D79: =SUMIFS('bbdd.5.final'!$Y:$Y,'bbdd.5.final'!$AA:$AA,Vista!E79,'bbdd.5.final'!$Z:$Z,$F$69,'bbdd.5.final'!$J:$J,"Opex") -> 2.4272116e+09 | E79: =E78+1 -> 8 | I79: =I78+1 -> 8
A80: =A79+1 -> 9 | B80: =D80/$D$71 -> 0.00038867492 | C80: =_xlfn.XLOOKUP($E80,'rubros_id_opex (2)'!$B:$B,'rubros_id_opex (2)'!$A:$A) -> MANTENIMIENTO PREVENTIVO | D80: =SUMIFS('bbdd.5.final'!$Y:$Y,'bbdd.5.final'!$AA:$AA,Vista!E80,'bbdd.5.final'!$Z:$Z,$F$69,'bbdd.5.final'!$J:$J,"Opex") -> 996109.31 | E80: =E79+1 -> 9 | I80: =I79+1 -> 9
A81: =A80+1 -> 10 | B81: =D81/$D$71 -> 0.0081853115 | C81: =_xlfn.XLOOKUP($E81,'rubros_id_opex (2)'!$B:$B,'rubros_id_opex (2)'!$A:$A) -> PERSONAL | D81: =SUMIFS('bbdd.5.final'!$Y:$Y,'bbdd.5.final'!$AA:$AA,Vista!E81,'bbdd.5.final'!$Z:$Z,$F$69,'bbdd.5.final'!$J:$J,"Opex") -> 20977595 | E81: =E80+1 -> 10 | I81: =I80+1 -> 10
A82: =A81+1 -> 11 | B82: =D82/$D$71 -> 0.0021995747 | C82: =_xlfn.XLOOKUP($E82,'rubros_id_opex (2)'!$B:$B,'rubros_id_opex (2)'!$A:$A) -> REPARACIONES | D82: =SUMIFS('bbdd.5.final'!$Y:$Y,'bbdd.5.final'!$AA:$AA,Vista!E82,'bbdd.5.final'!$Z:$Z,$F$69,'bbdd.5.final'!$J:$J,"Opex") -> 5637144.9 | E82: =E81+1 -> 11 | I82: =I81+1 -> 11
A83: =A82+1 -> 12 | B83: =D83/$D$71 -> 0.00063988142 | C83: =_xlfn.XLOOKUP($E83,'rubros_id_opex (2)'!$B:$B,'rubros_id_opex (2)'!$A:$A) -> REPOSICION | D83: =SUMIFS('bbdd.5.final'!$Y:$Y,'bbdd.5.final'!$AA:$AA,Vista!E83,'bbdd.5.final'!$Z:$Z,$F$69,'bbdd.5.final'!$J:$J,"Opex") -> 1639909.9 | E83: =E82+1 -> 12 | I83: =I82+1 -> 12
A84: =A83+1 -> 13 | B84: =D84/$D$71 -> 0.016601175 | C84: =_xlfn.XLOOKUP($E84,'rubros_id_opex (2)'!$B:$B,'rubros_id_opex (2)'!$A:$A) -> SERVICIOS | D84: =SUMIFS('bbdd.5.final'!$Y:$Y,'bbdd.5.final'!$AA:$AA,Vista!E84,'bbdd.5.final'!$Z:$Z,$F$69,'bbdd.5.final'!$J:$J,"Opex") -> 42546056 | E84: =E83+1 -> 13 | I84: =I83+1 -> 13
A85: =A84+1 -> 14 | B85: =D85/$D$71 -> 0.00014030066 | C85: =_xlfn.XLOOKUP($E85,'rubros_id_opex (2)'!$B:$B,'rubros_id_opex (2)'!$A:$A) -> COMERCIAL | D85: =SUMIFS('bbdd.5.final'!$Y:$Y,'bbdd.5.final'!$AA:$AA,Vista!E85,'bbdd.5.final'!$Z:$Z,$F$69,'bbdd.5.final'!$J:$J,"Opex") -> 359567.31 | E85: =E84+1 -> 14 | I85: =I84+1 -> 14
B88: VENTAS | D88: =SUMIFS(BBDD_INGRESOS_FINAL!$O:$O,BBDD_INGRESOS_FINAL!$D:$D,B70) -> 2.633974e+09
B90: UTILDAD | D90: =D88-D71 -> 71139922
B92: CAPEX | D92: =SUMIFS('bbdd.5.final'!$Y:$Y,'bbdd.5.final'!$J:$J,"Capex",'bbdd.5.final'!$Z:$Z,$F$69) -> 24811016
B94: DEUDA | D94: =SUMIFS('bbdd.5.final'!$Y:$Y,'bbdd.5.final'!$J:$J,"deuda",'bbdd.5.final'!$V:$V,B70) -> 0
B96: Flujo de Caja al Accionista | D96: =D90-D94-D92 -> 46328905
B109: CHECK
B111: PRODUCCION_UN | C111: =#REF!+D59+H59+L59+P59+P31+L31+H31+D31+D88 -> #REF!
B112: PRODUCCION_TOTAL | C112: =C6 -> 3.453388e+09
C113: =C111=C112 -> #REF!
B115: OPEX UN | C115: =D15+H15+L15+P15+P43+L43+H43+D43+#REF!+D71+L71 -> #REF!
B116: OPEX total | C116: =C7 -> 2.9779225e+09
C117: =MROUND(C116,10000)=MROUND(C115,10000) -> #REF!
B119: CAPEX_UN | C119: =D35+H35+L35+P35+P63+L63+H63+D63+#REF!+D92+L92 -> #REF!
B120: CAPEX_TOTAL | C120: =C9 -> 2.5523632e+08 | D120: =C119=C120 -> #REF!
B121: DEUDA_UN | C121: =D37+H37+L37+P37+P65+L65+H65+D65+#REF!+D94+L94 -> #REF!
B122: DEUDA_TOTAL | C122: =C10 -> 0 | D122: =C121=C122 -> #REF!
B126: UTILIDAD_TOTAL | C126: =C8 -> 4.7546546e+08
B127: UTILIDAD_UN | C127: =D33+H33+L33+P33+P61+L61+H61+D61+#REF!+D90+L90 -> #REF! | D127: =MROUND(C127,10000)=MROUND(C126,10000) -> #REF!
B130: Flujo_TOTAL | C130: =C11 -> 2.2022915e+08
B131: FLUJO_UN | C131: =D39+H39+L39+P39+P67+L67+H67+D67+#REF!+D96+L96 -> #REF! | D131: =MROUND(C131,10000)=MROUND(C130,10000) -> #REF!

Sheet val1
A1: VENTAS
A2: CEREAL & POLVILLO | B2: =Vista!P59 -> 25207646
A3: DISPOSICIÓN FINAL RESIDUOS SOLIDOS | B3: =Vista!D31 -> 5365216.3 | E3: Row Labels | F3: Sum of TOTAL
A4: DISPOSICIÓN FINAL RESIDUOS LIQUIDOS | B4: =Vista!$H$31 -> 1.712503e+08 | E4: BACHAS | F4: 1.151894e+08
A5: =Vista!J14 -> PILETAS | B5: =Vista!$L$31 -> 253547470 | E5: CEREAL & POLVILLO | F5: 25207646
A6: =Vista!N14 -> REACTORES | B6: =Vista!$P$31 -> 2.1218758e+08 | E6: DISPOSICIÓN FINAL RESIDUOS LIQUIDOS | F6: 1.712503e+08
A7: =Vista!B42 -> BACHAS | B7: =Vista!D59 -> 1.151894e+08 | E7: DISPOSICIÓN FINAL RESIDUOS SOLIDOS | F7: 5365216.3
A8: =Vista!F42 -> NFU | B8: =Vista!H59 -> 36666425 | E8: EXPORTACION | F8: 2.633974e+09
A9: =Vista!J42 -> COMPOST & FERTILIZANTES | B9: =Vista!L59 -> 0 | E9: NFU | F9: 36666425
A10: =Vista!#REF! -> #REF! | B10: =Vista!#REF! -> #REF! | E10: PILETAS | F10: 253547470
A11: =Vista!B70 -> EXPORTACION | B11: =Vista!D88 -> 2.633974e+09 | E11: REACTORES | F11: 2.1218758e+08
A12: SALES | B12: =GETPIVOTDATA("TOTAL",$E$3,"SECTOR","SALES") -> #REF! | E12: (blank)
A13: SUB-TOTAL | B13: =SUM(B2:B12) -> #REF! | E13: Grand Total | F13: 3.453388e+09
A15: TOTAL | B15: =GETPIVOTDATA("TOTAL",$E$3) -> 3.453388e+09
B18: =B15=B13 -> #REF!

Sheet Vista_R_sin_expo
B2: SIN EXPORTACIÓN
B3: TOTAL
B4: OPEX | D4: =SUM(D5:D18) -> 4.150885e+08
A5: 1 | B5: =D5/$D$4 -> 0.15890069 | C5: =_xlfn.XLOOKUP($A5,'rubros_id_opex (2)'!$B:$B,'rubros_id_opex (2)'!$A:$A) -> ENERGIA | D5: =SUMIFS('bbdd.5.final'!$Y:$Y,'bbdd.5.final'!$AA:$AA,A5,'bbdd.5.final'!$J:$J,"Opex",'bbdd.5.final'!$Z:$Z,"<>5") -> 65957848
A6: =A5+1 -> 2 | B6: =D6/$D$4 -> 0.00092561066 | C6: =_xlfn.XLOOKUP($A6,'rubros_id_opex (2)'!$B:$B,'rubros_id_opex (2)'!$A:$A) -> HABILITACIONES Y CERT | D6: =SUMIFS('bbdd.5.final'!$Y:$Y,'bbdd.5.final'!$AA:$AA,A6,'bbdd.5.final'!$J:$J,"Opex",'bbdd.5.final'!$Z:$Z,"<>5") -> 384210.34
A7: =A6+1 -> 3 | B7: =D7/$D$4 -> 0.0015412764 | C7: =_xlfn.XLOOKUP($A7,'rubros_id_opex (2)'!$B:$B,'rubros_id_opex (2)'!$A:$A) -> HIGIENE Y SEGURIDAD | D7: =SUMIFS('bbdd.5.final'!$Y:$Y,'bbdd.5.final'!$AA:$AA,A7,'bbdd.5.final'!$J:$J,"Opex",'bbdd.5.final'!$Z:$Z,"<>5") -> 639766.1
A8: =A7+1 -> 4 | B8: =D8/$D$4 -> 0.0080379865 | C8: =_xlfn.XLOOKUP($A8,'rubros_id_opex (2)'!$B:$B,'rubros_id_opex (2)'!$A:$A) -> IMPUESTOS | D8: =SUMIFS('bbdd.5.final'!$Y:$Y,'bbdd.5.final'!$AA:$AA,A8,'bbdd.5.final'!$J:$J,"Opex",'bbdd.5.final'!$Z:$Z,"<>5") -> 3336475.8
A9: =A8+1 -> 5 | B9: =D9/$D$4 -> 0.23742958 | C9: =_xlfn.XLOOKUP($A9,'rubros_id_opex (2)'!$B:$B,'rubros_id_opex (2)'!$A:$A) -> INSUMOS | D9: =SUMIFS('bbdd.5.final'!$Y:$Y,'bbdd.5.final'!$AA:$AA,A9,'bbdd.5.final'!$J:$J,"Opex",'bbdd.5.final'!$Z:$Z,"<>5") -> 98554291
A10: =A9+1 -> 6 | B10: =D10/$D$4 -> 0 | C10: =_xlfn.XLOOKUP($A10,'rubros_id_opex (2)'!$B:$B,'rubros_id_opex (2)'!$A:$A) -> INVERSION | D10: =SUMIFS('bbdd.5.final'!$Y:$Y,'bbdd.5.final'!$AA:$AA,A10,'bbdd.5.final'!$J:$J,"Opex",'bbdd.5.final'!$Z:$Z,"<>5") -> 0
A11: =A10+1 -> 7 | B11: =D11/$D$4 -> 0.0028300808 | C11: =_xlfn.XLOOKUP($A11,'rubros_id_opex (2)'!$B:$B,'rubros_id_opex (2)'!$A:$A) -> LOGISTICA | D11: =SUMIFS('bbdd.5.final'!$Y:$Y,'bbdd.5.final'!$AA:$AA,A11,'bbdd.5.final'!$J:$J,"Opex",'bbdd.5.final'!$Z:$Z,"<>5") -> 1174734
A12: =A11+1 -> 8 | B12: =D12/$D$4 -> 0.32214452 | C12: =_xlfn.XLOOKUP($A12,'rubros_id_opex (2)'!$B:$B,'rubros_id_opex (2)'!$A:$A) -> M.PRIMAS | D12: =SUMIFS('bbdd.5.final'!$Y:$Y,'bbdd.5.final'!$AA:$AA,A12,'bbdd.5.final'!$J:$J,"Opex",'bbdd.5.final'!$Z:$Z,"<>5") -> 1.3371849e+08
A13: =A12+1 -> 9 | B13: =D13/$D$4 -> 0.0014218145 | C13: =_xlfn.XLOOKUP($A13,'rubros_id_opex (2)'!$B:$B,'rubros_id_opex (2)'!$A:$A) -> MANTENIMIENTO PREVENTIVO | D13: =SUMIFS('bbdd.5.final'!$Y:$Y,'bbdd.5.final'!$AA:$AA,A13,'bbdd.5.final'!$J:$J,"Opex",'bbdd.5.final'!$Z:$Z,"<>5") -> 590178.87
A14: =A13+1 -> 10 | B14: =D14/$D$4 -> 0.18566161 | C14: =_xlfn.XLOOKUP($A14,'rubros_id_opex (2)'!$B:$B,'rubros_id_opex (2)'!$A:$A) -> PERSONAL | D14: =SUMIFS('bbdd.5.final'!$Y:$Y,'bbdd.5.final'!$AA:$AA,A14,'bbdd.5.final'!$J:$J,"Opex",'bbdd.5.final'!$Z:$Z,"<>5") -> 77065999
A15: =A14+1 -> 11 | B15: =D15/$D$4 -> 0.004620622 | C15: =_xlfn.XLOOKUP($A15,'rubros_id_opex (2)'!$B:$B,'rubros_id_opex (2)'!$A:$A) -> REPARACIONES | D15: =SUMIFS('bbdd.5.final'!$Y:$Y,'bbdd.5.final'!$AA:$AA,A15,'bbdd.5.final'!$J:$J,"Opex",'bbdd.5.final'!$Z:$Z,"<>5") -> 1917967.1
A16: =A15+1 -> 12 | B16: =D16/$D$4 -> 0.0045105285 | C16: =_xlfn.XLOOKUP($A16,'rubros_id_opex (2)'!$B:$B,'rubros_id_opex (2)'!$A:$A) -> REPOSICION | D16: =SUMIFS('bbdd.5.final'!$Y:$Y,'bbdd.5.final'!$AA:$AA,A16,'bbdd.5.final'!$J:$J,"Opex",'bbdd.5.final'!$Z:$Z,"<>5") -> 1872268.5
A17: =A16+1 -> 13 | B17: =D17/$D$4 -> 0.07166194 | C17: =_xlfn.XLOOKUP($A17,'rubros_id_opex (2)'!$B:$B,'rubros_id_opex (2)'!$A:$A) -> SERVICIOS | D17: =SUMIFS('bbdd.5.final'!$Y:$Y,'bbdd.5.final'!$AA:$AA,A17,'bbdd.5.final'!$J:$J,"Opex",'bbdd.5.final'!$Z:$Z,"<>5") -> 29746047
A18: =A17+1 -> 14 | B18: =D18/$D$4 -> 0.00031374678 | C18: =_xlfn.XLOOKUP($A18,'rubros_id_opex (2)'!$B:$B,'rubros_id_opex (2)'!$A:$A) -> COMERCIAL | D18: =SUMIFS('bbdd.5.final'!$Y:$Y,'bbdd.5.final'!$AA:$AA,A18,'bbdd.5.final'!$J:$J,"Opex",'bbdd.5.final'!$Z:$Z,"<>5") -> 130232.68
B20: VENTAS | D20: =SUMIFS(BBDD_INGRESOS_FINAL!$O:$O,BBDD_INGRESOS_FINAL!$R:$R,"<>5") -> 8.1941405e+08
B22: UTILDAD | D22: =D20-D4 -> 4.0432554e+08
B24: CAPEX | D24: =SUMIFS('bbdd.5.final'!$Y:$Y,'bbdd.5.final'!$J:$J,"Capex",'bbdd.5.final'!$Z:$Z,"<>5") -> 2.304253e+08
B26: DEUDA | D26: =SUMIFS('bbdd.5.final'!$Y:$Y,'bbdd.5.final'!$J:$J,"Deuda",'bbdd.5.final'!$Z:$Z,"<>5") -> 0
B28: Flujo de Caja al Accionista | D28: =D22-D24-D26 -> 1.7390024e+08
B31: VENTAS
B32: Row Labels | C32: Sum of TOTAL | D32: prc
B33: PILETAS | C33: 253547470 | D33: =C33/$C$40 -> 0.30942534
B34: REACTORES | C34: 2.1218758e+08 | D34: =C34/$C$40 -> 0.25895038
B35: DISPOSICIÓN FINAL RESIDUOS LIQUIDOS | C35: 1.712503e+08 | D35: =C35/$C$40 -> 0.20899118
B36: BACHAS | C36: 1.151894e+08 | D36: =C36/$C$40 -> 0.14057533
B37: NFU | C37: 36666425 | D37: =C37/$C$40 -> 0.044747128
B38: CEREAL & POLVILLO | C38: 25207646 | D38: =C38/$C$40 -> 0.030763014
B39: DISPOSICIÓN FINAL RESIDUOS SOLIDOS | C39: 5365216.3 | D39: =C39/$C$40 -> 0.0065476255
B40: Grand Total | C40: 8.1941405e+08
B44: COSTOS
B45: Row Labels | C45: Sum of MONTO_FINAL
B46: DISP. FINAL RESIDUOS LÍQUIDOS | C46: 2.5542369e+08 | D46: =C46/$C$54 -> 0.27538052
B47: REACTORES | C47: 2.5465884e+08 | D47: =C47/$C$54 -> 0.27455591
B48: BACHAS | C48: 1.30417e+08 | D48: =C48/$C$54 -> 0.14060678
B49: NFU | C49: 1.2746245e+08 | D49: =C49/$C$54 -> 0.13742138
B50: PILETAS | C50: 73655932 | D50: =C50/$C$54 -> 0.079410836
B51: DISP. FINAL RESIDUOS SÓLIDOS | C51: 46252965 | D51: =C51/$C$54 -> 0.049866813
B52: CEREAL & POLVILLO | C52: 24896303 | D52: =C52/$C$54 -> 0.026841507
B53: COMPOST & FERTILIZANTES | C53: 14762808 | D53: =C53/$C$54 -> 0.015916259
B54: Grand Total | C54: 9.2752999e+08 | D54: =C54/$C$54 -> 1

Sheet Vista_RUBRO
B2: CON EXPORTACIÓN INCLUÍDA
B3: TOTAL
B4: OPEX | D4: =SUM(D5:D18) -> 2.9779225e+09
A5: 1 | B5: =D5/$D$4 -> 0.025983964 | C5: =_xlfn.XLOOKUP($A5,'rubros_id_opex (2)'!$B:$B,'rubros_id_opex (2)'!$A:$A) -> ENERGIA | D5: =SUMIFS('bbdd.5.final'!$Y:$Y,'bbdd.5.final'!$AA:$AA,A5,'bbdd.5.final'!$J:$J,"Opex") -> 77378232
A6: =A5+1 -> 2 | B6: =D6/$D$4 -> 0.00096711716 | C6: =_xlfn.XLOOKUP($A6,'rubros_id_opex (2)'!$B:$B,'rubros_id_opex (2)'!$A:$A) -> HABILITACIONES Y CERT | D6: =SUMIFS('bbdd.5.final'!$Y:$Y,'bbdd.5.final'!$AA:$AA,A6,'bbdd.5.final'!$J:$J,"Opex") -> 2880000
A7: =A6+1 -> 3 | B7: =D7/$D$4 -> 0.00080799118 | C7: =_xlfn.XLOOKUP($A7,'rubros_id_opex (2)'!$B:$B,'rubros_id_opex (2)'!$A:$A) -> HIGIENE Y SEGURIDAD | D7: =SUMIFS('bbdd.5.final'!$Y:$Y,'bbdd.5.final'!$AA:$AA,A7,'bbdd.5.final'!$J:$J,"Opex") -> 2406135.1
A8: =A7+1 -> 4 | B8: =D8/$D$4 -> 0.0028384801 | C8: =_xlfn.XLOOKUP($A8,'rubros_id_opex (2)'!$B:$B,'rubros_id_opex (2)'!$A:$A) -> IMPUESTOS | D8: =SUMIFS('bbdd.5.final'!$Y:$Y,'bbdd.5.final'!$AA:$AA,A8,'bbdd.5.final'!$J:$J,"Opex") -> 8452773.8
A9: =A8+1 -> 5 | B9: =D9/$D$4 -> 0.033563873 | C9: =_xlfn.XLOOKUP($A9,'rubros_id_opex (2)'!$B:$B,'rubros_id_opex (2)'!$A:$A) -> INSUMOS | D9: =SUMIFS('bbdd.5.final'!$Y:$Y,'bbdd.5.final'!$AA:$AA,A9,'bbdd.5.final'!$J:$J,"Opex") -> 99950615
A10: =A9+1 -> 6 | B10: =D10/$D$4 -> 0 | C10: =_xlfn.XLOOKUP($A10,'rubros_id_opex (2)'!$B:$B,'rubros_id_opex (2)'!$A:$A) -> INVERSION | D10: =SUMIFS('bbdd.5.final'!$Y:$Y,'bbdd.5.final'!$AA:$AA,A10,'bbdd.5.final'!$J:$J,"Opex") -> 0
A11: =A10+1 -> 7 | B11: =D11/$D$4 -> 0.014253437 | C11: =_xlfn.XLOOKUP($A11,'rubros_id_opex (2)'!$B:$B,'rubros_id_opex (2)'!$A:$A) -> LOGISTICA | D11: =SUMIFS('bbdd.5.final'!$Y:$Y,'bbdd.5.final'!$AA:$AA,A11,'bbdd.5.final'!$J:$J,"Opex") -> 42445632
A12: =A11+1 -> 8 | B12: =D12/$D$4 -> 0.85997202 | C12: =_xlfn.XLOOKUP($A12,'rubros_id_opex (2)'!$B:$B,'rubros_id_opex (2)'!$A:$A) -> M.PRIMAS | D12: =SUMIFS('bbdd.5.final'!$Y:$Y,'bbdd.5.final'!$AA:$AA,A12,'bbdd.5.final'!$J:$J,"Opex") -> 2.5609301e+09
A13: =A12+1 -> 9 | B13: =D13/$D$4 -> 0.00053268282 | C13: =_xlfn.XLOOKUP($A13,'rubros_id_opex (2)'!$B:$B,'rubros_id_opex (2)'!$A:$A) -> MANTENIMIENTO PREVENTIVO | D13: =SUMIFS('bbdd.5.final'!$Y:$Y,'bbdd.5.final'!$AA:$AA,A13,'bbdd.5.final'!$J:$J,"Opex") -> 1586288.2
A14: =A13+1 -> 10 | B14: =D14/$D$4 -> 0.032923487 | C14: =_xlfn.XLOOKUP($A14,'rubros_id_opex (2)'!$B:$B,'rubros_id_opex (2)'!$A:$A) -> PERSONAL | D14: =SUMIFS('bbdd.5.final'!$Y:$Y,'bbdd.5.final'!$AA:$AA,A14,'bbdd.5.final'!$J:$J,"Opex") -> 98043594
A15: =A14+1 -> 11 | B15: =D15/$D$4 -> 0.0025370412 | C15: =_xlfn.XLOOKUP($A15,'rubros_id_opex (2)'!$B:$B,'rubros_id_opex (2)'!$A:$A) -> REPARACIONES | D15: =SUMIFS('bbdd.5.final'!$Y:$Y,'bbdd.5.final'!$AA:$AA,A15,'bbdd.5.final'!$J:$J,"Opex") -> 7555112
A16: =A15+1 -> 12 | B16: =D16/$D$4 -> 0.0011794056 | C16: =_xlfn.XLOOKUP($A16,'rubros_id_opex (2)'!$B:$B,'rubros_id_opex (2)'!$A:$A) -> REPOSICION | D16: =SUMIFS('bbdd.5.final'!$Y:$Y,'bbdd.5.final'!$AA:$AA,A16,'bbdd.5.final'!$J:$J,"Opex") -> 3512178.4
A17: =A16+1 -> 13 | B17: =D17/$D$4 -> 0.024276019 | C17: =_xlfn.XLOOKUP($A17,'rubros_id_opex (2)'!$B:$B,'rubros_id_opex (2)'!$A:$A) -> SERVICIOS | D17: =SUMIFS('bbdd.5.final'!$Y:$Y,'bbdd.5.final'!$AA:$AA,A17,'bbdd.5.final'!$J:$J,"Opex") -> 72292103
A18: =A17+1 -> 14 | B18: =D18/$D$4 -> 0.00016447708 | C18: =_xlfn.XLOOKUP($A18,'rubros_id_opex (2)'!$B:$B,'rubros_id_opex (2)'!$A:$A) -> COMERCIAL | D18: =SUMIFS('bbdd.5.final'!$Y:$Y,'bbdd.5.final'!$AA:$AA,A18,'bbdd.5.final'!$J:$J,"Opex") -> 489799.99
B20: VENTAS | D20: =SUM(BBDD_INGRESOS_FINAL!$O:$O) -> 3.453388e+09
B22: UTILDAD | D22: =D20-D4 -> 4.7546546e+08
B24: CAPEX | D24: =SUMIFS('bbdd.5.final'!$Y:$Y,'bbdd.5.final'!$J:$J,"Capex") -> 2.5523632e+08
B26: DEUDA | D26: =SUMIFS('bbdd.5.final'!$Y:$Y,'bbdd.5.final'!$J:$J,"Deuda") -> 0
B28: Flujo de Caja al Accionista | D28: =D22-D24-D26 -> 2.2022915e+08
B31: VENTAS
B32: Row Labels | C32: sectores_id.id_sector_2 | D32: Sum of TOTAL
B33: EXPORTACION | C33: 5 | D33: 2.633974e+09
B34: PILETAS | C34: 7 | D34: 253547470
B35: REACTORES | C35: 8 | D35: 2.1218758e+08
B36: DISPOSICIÓN FINAL RESIDUOS LIQUIDOS | C36: 3 | D36: 1.712503e+08
B37: BACHAS | C37: 1 | D37: 1.151894e+08
B38: NFU | C38: 6 | D38: 36666425
B39: CEREAL & POLVILLO | C39: 2 | D39: 25207646
B40: DISPOSICIÓN FINAL RESIDUOS SOLIDOS | C40: 4 | D40: 5365216.3
B41: Grand Total | C41: 8 | D41: 3.453388e+09
B43: Concepto | C43: OPEX
B44: COSTOS_OPEX
B45: Row Labels | C45: Max of id_sector | D45: Sum of monto_final2
B46: EXPORTACION | C46: 5 | D46: 2.6512766e+09
B47: REACTORES | C47: 8 | D47: 2.4140028e+08
B48: BACHAS | C48: 1 | D48: 1.3034652e+08
B49: NFU | C49: 6 | D49: 92849602
B50: PILETAS | C50: 7 | D50: 73340986
B51: DISP. FINAL RESIDUOS LÍQUIDOS | C51: 3 | D51: 73212356
B52: DISP. FINAL RESIDUOS SÓLIDOS | C52: 4 | D52: 46242369
B53: CEREAL & POLVILLO | C53: 2 | D53: 14848954
B54: COMPOST & FERTILIZANTES | C54: 10 | D54: 14761924
B55: GENERAL | C55: 0 | D55: 0
B56: TIERRAS FILTRANTES | C56: 9 | D56: 0
B57: Grand Total | C57: 10 | D57: 3.3382796e+09
B60: SECTOR | C60: id | D60: VENTAS | E60: COSTOS_OPEX | F60: UTILIDAD
B61: EXPORTACION | C61: =_xlfn.XLOOKUP(B61,$B$46:$B$55,$C$46:$C$55) -> 5 | D61: =_xlfn.XLOOKUP(C61,$C$33:$C$41,$D$33:$D$41) -> 2.633974e+09 | E61: =_xlfn.XLOOKUP(C61,$C$46:$C$55,$D$46:$D$55) -> 2.6512766e+09 | F61: =D61-E61 -> -17302656
B62: DISP. FINAL RESIDUOS LÍQUIDOS | C62: =_xlfn.XLOOKUP(B62,$B$46:$B$55,$C$46:$C$55) -> 3 | D62: =_xlfn.XLOOKUP(C62,$C$33:$C$41,$D$33:$D$41) -> 1.712503e+08 | E62: =_xlfn.XLOOKUP(C62,$C$46:$C$55,$D$46:$D$55) -> 73212356 | F62: =D62-E62 -> 98037948
B63: BACHAS | C63: =_xlfn.XLOOKUP(B63,$B$46:$B$55,$C$46:$C$55) -> 1 | D63: =_xlfn.XLOOKUP(C63,$C$33:$C$41,$D$33:$D$41) -> 1.151894e+08 | E63: =_xlfn.XLOOKUP(C63,$C$46:$C$55,$D$46:$D$55) -> 1.3034652e+08 | F63: =D63-E63 -> -15157121
B64: REACTORES | C64: =_xlfn.XLOOKUP(B64,$B$46:$B$55,$C$46:$C$55) -> 8 | D64: =_xlfn.XLOOKUP(C64,$C$33:$C$41,$D$33:$D$41) -> 2.1218758e+08 | E64: =_xlfn.XLOOKUP(C64,$C$46:$C$55,$D$46:$D$55) -> 2.4140028e+08 | F64: =D64-E64 -> -29212700
B65: NFU | C65: =_xlfn.XLOOKUP(B65,$B$46:$B$55,$C$46:$C$55) -> 6 | D65: =_xlfn.XLOOKUP(C65,$C$33:$C$41,$D$33:$D$41) -> 36666425 | E65: =_xlfn.XLOOKUP(C65,$C$46:$C$55,$D$46:$D$55) -> 92849602 | F65: =D65-E65 -> -56183177
B66: PILETAS | C66: =_xlfn.XLOOKUP(B66,$B$46:$B$55,$C$46:$C$55) -> 7 | D66: =_xlfn.XLOOKUP(C66,$C$33:$C$41,$D$33:$D$41) -> 253547470 | E66: =_xlfn.XLOOKUP(C66,$C$46:$C$55,$D$46:$D$55) -> 73340986 | F66: =D66-E66 -> 1.8020648e+08
B67: DISP. FINAL RESIDUOS SÓLIDOS | C67: =_xlfn.XLOOKUP(B67,$B$46:$B$55,$C$46:$C$55) -> 4 | D67: =_xlfn.XLOOKUP(C67,$C$33:$C$41,$D$33:$D$41) -> 5365216.3 | E67: =_xlfn.XLOOKUP(C67,$C$46:$C$55,$D$46:$D$55) -> 46242369 | F67: =D67-E67 -> -40877153
B68: COMPOST & FERTILIZANTES | C68: =_xlfn.XLOOKUP(B68,$B$46:$B$55,$C$46:$C$55) -> 10 | D68: =_xlfn.XLOOKUP(C68,$C$33:$C$41,$D$33:$D$41) -> #N/A | E68: =_xlfn.XLOOKUP(C68,$C$46:$C$55,$D$46:$D$55) -> 14761924 | F68: =D68-E68 -> #N/A
B69: CEREAL & POLVILLO | C69: =_xlfn.XLOOKUP(B69,$B$46:$B$55,$C$46:$C$55) -> 2 | D69: =_xlfn.XLOOKUP(C69,$C$33:$C$41,$D$33:$D$41) -> 25207646 | E69: =_xlfn.XLOOKUP(C69,$C$46:$C$55,$D$46:$D$55) -> 14848954 | F69: =D69-E69 -> 10358692
B70: TIERRAS FILTRANTES | C70: =_xlfn.XLOOKUP(B70,$B$46:$B$55,$C$46:$C$55) -> #N/A | D70: =_xlfn.XLOOKUP(C70,$C$33:$C$41,$D$33:$D$41,0) -> #N/A | E70: =_xlfn.XLOOKUP(C70,$C$46:$C$55,$D$46:$D$55) -> #N/A | F70: =D70-E70 -> #N/A

Sheet RRHH
C1: TOTAL 1+2 | D1: COMPONENTE
A2: ADMINISTRACION | B2: =_xlfn.CONCAT("RRHH-",A2) -> RRHH-ADMINISTRACION | C2: 67124149 | D2: 100% ADMINISTRACION - 100% DIRECTOR | E2: CC1
A3: INTENDENCIA | B3: =_xlfn.CONCAT("RRHH-",A3) -> RRHH-INTENDENCIA | C3: 9375237.7 | D3: 100% INTENDENCIA - 6,67% PRODUCCION | E3: CC1
A4: LABORATORIO | B4: =_xlfn.CONCAT("RRHH-",A4) -> RRHH-LABORATORIO | C4: 12249966 | D4: 100% LABORATORIO - 6,67% PRODUCCION | E4: CC1
A5: LOGISTICA | B5: =_xlfn.CONCAT("RRHH-",A5) -> RRHH-LOGISTICA | C5: 6459899.7 | D5: 75% LOGISTICA - 6,67% PRODUCCION | E5: CC1
A6: MANTENIMIENTO | B6: =_xlfn.CONCAT("RRHH-",A6) -> RRHH-MANTENIMIENTO | C6: 7742399.7 | D6: 100% MANTENIMIENTO - 6,67% PRODUCCION | E6: CC1
A7: NFU | B7: =_xlfn.CONCAT("RRHH-",A7) -> RRHH-NFU | C7: 29572095 | D7: 25% LOGISTICA - 100% CAT - 100% EXTERNO NFU - 6,67% PRODUCCION - 95% NFU | E7: CC7
A8: PORTERIA | B8: =_xlfn.CONCAT("RRHH-",A8) -> RRHH-PORTERIA | C8: 10797311 | D8: 100% PORTERIA - 6,67% PRODUCCION | E8: CC1
A9: COMPOST Y FERTILIZANTES | B9: =_xlfn.CONCAT("RRHH-",A9) -> RRHH-COMPOST Y FERTILIZANTES | C9: 1833599.1 | D9: 60% COMPOST Y FERTILIZANTES - 6,67% PRODUCCION | E9: CC14
A10: CEREAL Y POLVILLO | B10: =_xlfn.CONCAT("RRHH-",A10) -> RRHH-CEREAL Y POLVILLO | C10: 0 | D10: 0% CEREAL Y POLVILLO - 0% PRODUCCION | E10: NO
A11: TALLER MECANICO | B11: =_xlfn.CONCAT("RRHH-",A11) -> RRHH-TALLER MECANICO | C11: 6300478.7 | D11: 100% TALLER MECANICO - 6,67% PRODUCCION | E11: CC1
A12: TIERRAS FILTRANTES | B12: =_xlfn.CONCAT("RRHH-",A12) -> RRHH-TIERRAS FILTRANTES | C12: 0 | D12: 0% TIERRAS FILTRANTES - 0% PRODUCCION | E12: NO
A13: VIGILANCIA | B13: =_xlfn.CONCAT("RRHH-",A13) -> RRHH-VIGILANCIA | C13: 6294101.7 | D13: 100% VIGILANCIA - 6,67% PRODUCCION | E13: CC1
... A21: SALES | B21: =_xlfn.CONCAT("RRHH-",A21) -> RRHH-SALES | C21: 0 | D21: 0% SALES - 0% PRODUCCION | E21: NO

Sheet ref_rrhh
A1: Sector | B1: f/v | C1: d/i
A2: ADMINISTRACION | B2: Fijo | C2: Indirecto
A3: INTENDENCIA | B3: Fijo | C3: Indirecto
A4: REACTOR | B4: Variable | C4: Directo
A5: NFU | B5: Variable | C5: Directo
A6: DISPOSICION FINAL DE R. LIQUIDOS | B6: Variable | C6: Directo
A7: DIRECTOR | B7: Fijo | C7: Indirecto
A8: TALLER MECANICO | B8: Fijo | C8: Indirecto
A9: PRODUCCION | B9: Variable | C9: Directo
A10: CAT | B10: Variable | C10: Directo
A11: MANTENIMIENTO | B11: Fijo | C11: Indirecto
A12: PORTERIA | B12: Fijo | C12: Indirecto
... A17: COMPOST Y FERTILIZANTES | B17: Variable | C17: Directo

Sheet gastos_unificado.p0
A1: Fecha de Factura/Recibo | B1: Nombre de la empresa a mostrar en la factura | C1: Número | D1: Total con signo | E1: Líneas de factura/Etiqueta | F1: Líneas de factura/Cantidad | G1: Líneas de factura/Precio unitario | H1: Líneas de factura/Unidad de medida | I1: Líneas de factura/Producto | J1: Concepto | K1: Tipo de Gasto 1 | L1: Tipo de Gasto 2 | M1: CCO EMPRESA | N1: CCO - SECTOR | O1: Origen | P1: USD | Q1: SECTOR | R1: SUBRUBRO | S1: TC | T1: Total | U1: # LEGAJO | V1: LEG. | W1: CUIL
A2: 46111 | B2: WORMS 2 | C2: prod17 | D2: -2.0810686e+09 | E2: AFE (S) | F2: 1541.07 | G2: 945 | H2: TN | I2: MATERIA PRIMA | J2: OPEX | K2: VARIABLE | L2: DIRECTO | N2: CC11 | O2: gastos_produccion | P2: 1429 | Q2: EXPORTACION | R2: AFE (S)
A3: 46111 | B3: WORMS 2 | C3: prod15 | D3: -1.2849682e+08 | E3: AFE (G) | F3: 97.74 | G3: 920 | H3: TN | I3: MATERIA PRIMA | J3: OPEX | K3: VARIABLE | L3: DIRECTO | N3: CC11 | O3: gastos_produccion | P3: 1429 | Q3: EXPORTACION | R3: AFE (G)
A4: 46111 | B4: WORMS 2 | C4: prod23 | D4: -89426820 | E4: AG- C | F4: 83.44 | G4: 750 | H4: TN | I4: MATERIA PRIMA | J4: OPEX | K4: VARIABLE | L4: DIRECTO | N4: CC11 | O4: gastos_produccion | P4: 1429 | Q4: EXPORTACION | R4: AG- C
A5: 46111 | B5: EDUARDO SEMINARA - DENIS LUQUE | C5: prod13 | D5: -87306127 | E5: GLICERINA CRUDA | F5: 169.711 | G5: 360 | H5: TN | I5: INSUMOS | J5: OPEX | K5: VARIABLE | L5: DIRECTO | N5: CC5 | O5: gastos_produccion | P5: 1429 | Q5: REACTORES | R5: GLICERINA CRUDA
A6: 46111 | B6: WORMS 2 | C6: prod29 | D6: -80532152 | E6: ARE- B | F6: 67.09 | G6: 840 | H6: TN | I6: MATERIA PRIMA | J6: OPEX | K6: VARIABLE | L6: DIRECTO | N6: CC11 | O6: gastos_produccion | P6: 1429 | Q6: EXPORTACION | R6: ARE- B
A7: 46111 | B7: WORMS 1 | C7: prod26 | D7: -79981130 | E7: AG-D | F7: 111.94 | G7: 500 | H7: TN | I7: MATERIA PRIMA | J7: OPEX | K7: VARIABLE | L7: DIRECTO | N7: CC6 | O7: gastos_produccion | P7: 1429 | Q7: BACHAS | R7: AG-D
A8: 46100 | B8: Construcciones Industriales Y Portuarias S.A. | C8: FA-A 00003-00001298 | D8: -54208000 | E8: INVERSION Planta de efluentes | F8: 1 | G8: 44800000 | H8: UN | I8: INVERSION | J8: CAPEX | K8: VARIABLE | L8: INDIRECTO | N8: CC3 | O8: gastos_produccion | R8: PROYECTO 4
A9: 46093 | B9: Construcciones Industriales Y Portuarias S.A. | C9: FA-A 00003-00001295 | D9: -50700270 | E9: INVERSION Planta de efluentes Actualizacion | F9: 1 | G9: 41901050 | H9: UN | I9: INVERSION | J9: CAPEX | K9: VARIABLE | L9: INDIRECTO | N9: CC3 | O9: gastos_produccion | R9: PROYECTO 4
A10: 46111 | B10: WORMS 2 | C10: prod19 | D10: -47687159 | E10: AG- A | F10: 39.26 | G10: 850 | H10: TN | I10: MATERIA PRIMA | J10: OPEX | K10: VARIABLE | L10: DIRECTO | N10: CC11 | O10: gastos_produccion | P10: 1429 | Q10: EXPORTACION | R10: AG- A
A11: 46111 | B11: WORMS 1 | C11: prod25 | D11: -45305016 | E11: AG- C | F11: 42.272 | G11: 750 | H11: TN | I11: MATERIA PRIMA | J11: OPEX | K11: VARIABLE | L11: DIRECTO | N11: CC5 | O11: gastos_produccion | P11: 1429 | Q11: REACTORES | R11: AG- C
A12: 46111 | B12: LOGISTICA EXPORTACION | C12: FA-C 2-2026-3 | D12: -41270898 | E12: FOB | F12: 1038.915 | G12: 39725 | H12: TN | I12: LOGISTICA | J12: OPEX | K12: VARIABLE | L12: DIRECTO | N12: CC11 | O12: gastos_produccion | P12: 1 | Q12: EXPORTACION | R12: FOB
A13: 46085 | B13: Nation Limited S.A. | C13: FA-A 00001-00000285 | D13: -38586537 | E13: INVERSION Geomembrana Proy #6 | F13: 1 | G13: 31889700 | H13: UN | I13: INVERSION | J13: CAPEX | K13: VARIABLE | L13: DIRECTO | N13: CC3 | O13: gastos_produccion
A14: 46085 | B14: Nation Limited S.A. | C14: FA-A 00001-00000284 | D14: -38586537 | E14: INVERSION Geomembrana proy #6 | F14: 1 | G14: 31889700 | H14: UN | I14: INVERSION | J14: CAPEX | K14: VARIABLE | L14: DIRECTO | N14: CC3 | O14: gastos_produccion
A15: 46083 | B15: Gmc Valores Sociedad Anonima | C15: OCOM/2026/0183 | D15: -31500000 | E15: INVERSION exim | F15: 1 | G15: 31500000 | H15: UN | I15: INVERSION | J15: CAPEX | K15: VARIABLE | L15: DIRECTO | N15: CC7 | O15: gastos_produccion | R15: PROYECTO X
A16: 46111 | B16: ULTRAONIX SRL | C16: prod4 | D16: -29192969 | E16: FUEL OIL | F16: 46167.3 | G16: 632.33 | H16: KG | I16: ENERGIA | J16: OPEX | K16: VARIABLE | L16: DIRECTO | N16: CC5 | O16: gastos_produccion | P16: 1 | Q16: REACTORES | R16: FUEL OIL
A17: 46090 | B17: Empresa Provincial De La Energia De Santa Fe (W) | C17: FA-A 00069-00039909 | D17: -27731946 | E17: ENERGIA Luz | F17: 1 | G17: 20171433 | H17: UN | I17: ENERGIA | J17: OPEX | K17: VARIABLE | L17: DIRECTO | N17: CC14 | O17: gastos_produccion | R17: ENERGIA
A18: 46106 | B18: Electromecanica Dick Costantino S.A. | C18: FA-A 00004-00023210 | D18: -23215003 | E18: INVERSION Colocación de radares tanques ítem 1 | F18: 1 | G18: 23215002 | H18: UN | I18: INVERSION | J18: CAPEX | K18: VARIABLE | L18: INDIRECTO | N18: CC11 | O18: gastos_produccion | R18: PROYECTO N°
A19: 46111 | B19: COOPERATIVA DE TRABAJO COMERCIO EXTERIOR LIMITADA | C19: FA-C 2-2026-3 | D19: -22211090 | E19: SERVICIO DE DESPACHO | F19: 1828.6 | G19: 8.5 | H19: UN | I19: SERVICIOS | J19: OPEX | K19: VARIABLE | L19: DIRECTO | N19: CC11 | O19: gastos_produccion | P19: 1429 | R19: COMEX
A20: 46086 | B20: Hidalgo, Ruben Dario | C20: FA-A 00003-00000130 | D20: -14157000 | E20: SERVICIOS Trabajo realizado en campo con pala | F20: 60 | G20: 80000 | H20: UN | I20: SERVICIOS | J20: OPEX | K20: VARIABLE | L20: INDIRECTO | N20: CC3 | O20: gastos_produccion
A21: 46087 | B21: Quiroz, Maria Ines | C21: FA-C 00002-00000036 | D21: -13172300 | E21: INVERSION Servicios varios , Mantenimiento y Ampliación | F21: 1 | G21: 13172300 | H21: UN | I21: INVERSION | J21: CAPEX | K21: VARIABLE | L21: INDIRECTO | N21: CC5 | O21: gastos_produccion
A22: 46111 | B22: MARTINS, JOAQUIN | C22: prod8 | D22: -11011000 | E22: GASOIL G3 | F22: 4550 | G22: 2420 | H22: Lts | I22: ENERGIA | J22: OPEX | K22: VARIABLE | L22: DIRECTO | N22: CC1 | O22: gastos_produccion | P22: 1 | Q22: INTENDENCIA | R22: GASOIL G3
A23: 46111 | B23: WORMS 1 | C23: prod33 | D23: -7557266.5 | E23: FONDO TK | F23: 10.577 | G23: 500 | H23: TN | I23: MATERIA PRIMA | J23: OPEX | K23: VARIABLE | L23: DIRECTO | N23: CC6 | O23: gastos_produccion | P23: 1429 | Q23: BACHAS | R23: FONDO TK
A24: 46112 | B24: RRHH WORMS (NUEVO) | C24: JORGE BENJAMIN FERREYRA GRACES | D24: -6866469.7 | E24: DIRECCION | F24: 1 | G24: 6866469.7 | H24: # RRHH | I24: PERSONAL | J24: OPEX | K24: FIJO | L24: INDIRECTO | N24: CC16 | O24: rrhh_nuevo | T24: 6866469.7 | U24: 117 | V24: 117 | W24: 20337494014
A25: 46086 | B25: Hidalgo, Ruben Dario | C25: FA-A 00003-00000128 | D25: -6388800 | E25: SERVICIOS movimiento de suelo | F25: 1 | G25: 5280000 | H25: UN | I25: SERVICIOS | J25: OPEX | K25: VARIABLE | L25: INDIRECTO | N25: CC3 | O25: gastos_produccion
A26: 46111 | B26: TOTAL QUIMICA S.A. | C26: prod12 | D26: -5645419.8 | E26: SODA CAUSTICA | F26: 5867.2 | G26: 962.2 | H26: KG | I26: INSUMOS | J26: OPEX | K26: VARIABLE | L26: DIRECTO | N26: CC5 | O26: gastos_produccion | P26: 1 | Q26: REACTORES | R26: SODA CAUSTICA
A27: 46112 | B27: RRHH WORMS (NUEVO) | C27: PABLO ALFONSO PAGANI | D27: -5428026.1 | E27: PRODUCCION | F27: 1 | G27: 5428026.1 | H27: # RRHH | I27: PERSONAL | J27: OPEX | K27: FIJO | L27: DIRECTO | N27: CC28 | O27: rrhh_nuevo | T27: 5428026.1 | U27: 139 | V27: 139 | W27: 20127294853
A28: 46111 | B28: IMPUESTOS | C28: imp2 | D28: -5039229.7 | E28: IMPUESTOS | F28: 1 | G28: 5039229.7 | H28: UN | I28: IMPUESTOS | J28: OPEX | K28: VARIABLE | L28: INDIRECTO | N28: CC1 | O28: gastos_impuestos | R28: GASTOS BANCARIOS
A29: 46112 | B29: RRHH WORMS (NUEVO) | C29: CARLA JUDIT MAZZALI | D29: -4823227.7 | E29: ADMINISTRACION | F29: 1 | G29: 4823227.7 | H29: # RRHH | I29: PERSONAL | J29: OPEX | K29: FIJO | L29: INDIRECTO | N29: CC15 | O29: rrhh_nuevo | T29: 4823227.7 | U29: 216 | V29: 216 | W29: 27338810194
A30: 46111 | B30: TOTAL QUIMICA S.A. | C30: prod2 | D30: -4738755.8 | E30: ACIDO SULFÚRICO 70/80 | F30: 12224 | G30: 387.66 | H30: KG | I30: INSUMOS | J30: OPEX | K30: VARIABLE | L30: DIRECTO | N30: CC6 | O30: gastos_produccion | P30: 1 | Q30: BACHAS | R30: ACIDO SULFÚRICO 70/80
A31: 46112 | B31: RRHH WORMS (NUEVO) | C31: PABLO MAURICIO ZIMMERMAN | D31: -4693346 | E31: DIRECCION | F31: 1 | G31: 4693346 | H31: # RRHH | I31: PERSONAL | J31: OPEX | K31: FIJO | L31: INDIRECTO | N31: CC16 | O31: rrhh_nuevo | T31: 4693346 | U31: 125 | V31: 125 | W31: 20231231634
A32: 46111 | B32: ULTRAONIX SRL | C32: prod5 | D32: -4074324.8 | E32: FUEL OIL | F32: 6443.352 | G32: 632.33 | H32: KG | I32: ENERGIA | J32: OPEX | K32: VARIABLE | L32: DIRECTO | N32: CC6 | O32: gastos_produccion | P32: 1 | Q32: BACHAS | R32: FUEL OIL
A33: 46111 | B33: MARTINS, JOAQUIN | C33: prod10 | D33: -3444000 | E33: NAFTA | F33: 1680 | G33: 2050 | H33: Lts | I33: ENERGIA | J33: OPEX | K33: VARIABLE | L33: DIRECTO | N33: CC4 | O33: gastos_produccion | P33: 1 | Q33: PILETAS | R33: NAFTA
A34: 46112 | B34: RRHH WORMS (NUEVO) | C34: ANDRES CULOTA | D34: -3357574.7 | E34: ADMINISTRACION | F34: 1 | G34: 3357574.7 | H34: # RRHH | I34: PERSONAL | J34: OPEX | K34: FIJO | L34: INDIRECTO | N34: CC15 | O34: rrhh_nuevo | T34: 3357574.7 | U34: 219 | V34: 219 | W34: 20244797513
A35: 46086 | B35: Exportdeniv Internacional Sa | C35: FA-A 00002-00000626 | D35: -3012576.3 | E35: SERVICIOS Almacenaje cargas generales 2/26 | F35: 3585.12 | G35: 840.3 | H35: UN | I35: SERVICIOS | J35: CAPEX | K35: VARIABLE | L35: DIRECTO | N35: CC7 | O35: gastos_produccion
A36: 46084 | B36: Acosta, Roberto Maximiliano | C36: FA-C 00001-00000687 | D36: -2950000 | E36: SERVICIOS Servicio de limpieza Febrero 2026 | F36: 1 | G36: 2950000 | H36: UN | I36: SERVICIOS | J36: OPEX | K36: VARIABLE | L36: INDIRECTO | N36: CC1 | O36: gastos_produccion | Q36: INTENDENCIA | R36: LIMPIEZA
A37: 46084 | B37: Gonzalez, Delia | C37: FA-C 00001-00000015 | D37: -2950000 | E37: SERVICIOS Servicio de limpieza Febrero 2026 | F37: 1 | G37: 2950000 | H37: UN | I37: SERVICIOS | J37: OPEX | K37: VARIABLE | L37: INDIRECTO | N37: CC1 | O37: gastos_produccion | Q37: INTENDENCIA | R37: LIMPIEZA
A38: 46091 | B38: Zavalia Lagos, Marina | C38: FA-C 00002-00000086 | D38: -2850000 | E38: HONORARIOS Servicios profesionales Tomas Bollini Febrero 26 | F38: 1 | G38: 2850000 | H38: UN | I38: HONORARIOS | J38: OPEX | K38: VARIABLE | L38: INDIRECTO | N38: CC1 | O38: gastos_produccion | Q38: ADMINISTRACION | R38: LEGALES
A39: 46112 | B39: RRHH WORMS (NUEVO) | C39: CEBALLEZ MARIA EUGENIA | D39: -2640353.7 | E39: PRODUCCION | F39: 1 | G39: 2640353.7 | H39: # RRHH | I39: PERSONAL | J39: OPEX | K39: FIJO | L39: DIRECTO | N39: CC28 | O39: rrhh_nuevo | T39: 2640353.7 | U39: 29 | V39: 29 | W39: 27328978666
A40: 46091 | B40: Mil Propiedades Srl | C40: FA-A 00001-00000743 | D40: -2541000 | E40: SERVICIOS Alquiler Sauce viejo Baradero Coronda Timbues | F40: 4 | G40: 420000 | H40: UN | I40: SERVICIOS | J40: OPEX | K40: VARIABLE | L40: INDIRECTO | N40: CC7 | O40: gastos_produccion | R40: CAT'S
A41: 46112 | B41: RRHH WORMS (NUEVO) | C41: PABLO EMMANUEL DIAZ | D41: -2499379.3 | E41: NFU + DISPOSICION FINAL DE R. SOLIDOS | F41: 1 | G41: 2499379.3 | H41: # RRHH | I41: PERSONAL | J41: OPEX | K41: FIJO | L41: DIRECTO | N41: CC20 | O41: rrhh_nuevo | T41: 2499379.3 | U41: 112 | V41: 112 | W41: 20320730865
A42: 46112 | B42: RRHH WORMS (NUEVO) | C42: FERNANDO TISCORNIA | D42: -2485063.8 | E42: DIRECCION | F42: 1 | G42: 2485063.8 | H42: # RRHH | I42: PERSONAL | J42: OPEX | K42: FIJO | L42: INDIRECTO | N42: CC16 | O42: rrhh_nuevo | T42: 2485063.8 | U42: 119 | V42: 119 | W42: 20336552304
A43: 46082 | B43: Adhoc S.A.(W) | C43: FA-A 00003-00021811 | D43: -2281259 | E43: SERVICIOS Sistema contable | F43: 1 | G43: 1885338 | H43: UN | I43: SERVICIOS | J43: OPEX | K43: FIJO | L43: INDIRECTO | N43: CC1 | O43: gastos_produccion | Q43: ADMINISTRACION | R43: SISTEMA
A44: 46094 | B44: H.S.E. Ingenieria S R L | C44: FA-A 00003-00029654 | D44: -2153800 | E44: SERVICIOS Evaluacion impacto odorifico | F44: 1 | G44: 1780000 | H44: UN | I44: SERVICIOS | J44: OPEX | K44: VARIABLE | L44: INDIRECTO | N44: CC1 | O44: gastos_produccion | Q44: INTENDENCIA | R44: MEDIO AMBIENTE
A45: 46112 | B45: RRHH WORMS (NUEVO) | C45: PARDEL MAURO | D45: -2064817.8 | E45: PORTERIA | F45: 1 | G45: 2064817.8 | H45: # RRHH | I45: PERSONAL | J45: OPEX | K45: FIJO | L45: DIRECTO | N45: CC22 | O45: rrhh_nuevo | T45: 2064817.8 | U45: 25 | V45: 25 | W45: 23397537749
A46: 46112 | B46: RRHH WORMS (NUEVO) | C46: TULLIANI ROMINA | D46: -1768620.2 | E46: DISPOSICIÓN FINAL RESIDUOS LIQUIDOS + EXPORTACION | F46: 1 | G46: 1768620.2 | H46: # RRHH | I46: PERSONAL | J46: OPEX | K46: FIJO | L46: DIRECTO | N46: CC25 | O46: rrhh_nuevo | T46: 1768620.2 | U46: 239 | V46: 239 | W46: 27260352836
A47: 46112 | B47: RRHH WORMS (NUEVO) | C47: LISARDO MATIAS IVAN | D47: -1570631.8 | E47: REACTOR | F47: 1 | G47: 1570631.8 | H47: # RRHH | I47: PERSONAL | J47: OPEX | K47: FIJO | L47: DIRECTO | N47: CC5 | O47: rrhh_nuevo | T47: 1570631.8 | U47: 88 | V47: 88 | W47: 20400564818
A48: 46111 | B48: MARTINS, JOAQUIN | C48: prod7 | D48: -1472000 | E48: G2 | F48: 1000 | G48: 1472 | H48: Lts | I48: ENERGIA | J48: OPEX | K48: VARIABLE | L48: DIRECTO | N48: CC5 | O48: gastos_produccion | P48: 1 | Q48: REACTORES | R48: G2
A49: 46087 | B49: Fundacion Sistema B Argentina Para Promover Una Economia Sustentable | C49: FA-C 00004-00003161 | D49: -1445000 | E49: HABILITACIONES Y CERT Capacitación y concientización | F49: 1 | G49: 1445000 | H49: UN | I49: HABILITACIONES Y CERT | J49: OPEX | K49: VARIABLE | L49: INDIRECTO | N49: CC1 | O49: gastos_produccion | Q49: ADMINISTRACION | R49: SISTEMA
A50: 46091 | B50: Dragubitzky, Jose Luis | C50: FA-C 00010-00000107 | D50: -1435000 | E50: HABILITACIONES Y CERT gestión sistema de sustentabilidad Febrero 2026 | F50: 1 | G50: 1435000 | H50: UN | I50: HABILITACIONES Y CERT | J50: OPEX | K50: VARIABLE | L50: DIRECTO | N50: CC11 | O50: gastos_produccion | R50: ISCC
A51: 46108 | B51: Pierucci, Marcelo Nello | C51: FA-A 00004-00006613 | D51: -1417000 | E51: REPARACIONES Reparaciones desde el mes 08 al12 | F51: 1 | G51: 1171074.4 | H51: UN | I51: REPARACIONES | J51: OPEX | K51: VARIABLE | L51: INDIRECTO | N51: CC1 | O51: gastos_produccion | Q51: TALLER | R51: BIEN DE USO
A52: 46112 | B52: RRHH WORMS (NUEVO) | C52: ANDRES HONORES | D52: -1404307 | E52: REACTOR | F52: 1 | G52: 1404307 | H52: # RRHH | I52: PERSONAL | J52: OPEX | K52: FIJO | L52: DIRECTO | N52: CC5 | O52: rrhh_nuevo | T52: 1404307 | U52: 43 | V52: 43 | W52: 20372612615
A53: 46092 | B53: Silenzi, Cristian Emmanuel | C53: FA-A 00002-00001240 | D53: -1401180 | E53: REPARACIONES Cremallera hidráulica nueva mano de obra sacar y colocar . Entremos dirección Mitsubishi lbn962-Chata Matías Pérez Intendencia | F53: 1 | G53: 1158000 | H53: UN | I53: REPARACIONES | J53: OPEX | K53: VARIABLE | L53: INDIRECTO | N53: CC1 | O53: gastos_produccion | Q53: TALLER | R53: BIEN DE USO
A54: 46092 | B54: Picatto, Santiago | C54: FA-A 00002-00004669 | D54: -1366791.2 | E54: INSUMOS consumibles para laboratorio | F54: 1 | G54: 1065000 | H54: UN | I54: INSUMOS | J54: OPEX | K54: VARIABLE | L54: INDIRECTO | N54: CC1 | O54: gastos_produccion | Q54: LABORATORIO | R54: CONSUMIBLE
A55: 46111 | B55: IMPUESTOS | C55: imp1 | D55: -1338535.2 | E55: IMPUESTOS | F55: 1828.6 | G55: 0.5 | H55: UN | I55: IMPUESTOS | J55: OPEX | K55: VARIABLE | L55: DIRECTO | N55: CC11 | O55: gastos_impuestos | R55: GANANCIAS EXPORTACION | S55: 1464
A56: 46112 | B56: RRHH WORMS (NUEVO) | C56: IVAN DARIO ALVAREZ | D56: -1324135.6 | E56: ADMINISTRACION | F56: 1 | G56: 1324135.6 | H56: # RRHH | I56: PERSONAL | J56: OPEX | K56: FIJO | L56: INDIRECTO | N56: CC15 | O56: rrhh_nuevo | T56: 1324135.6 | U56: 72 | V56: 72 | W56: 20399514593
A57: 46112 | B57: RRHH WORMS (NUEVO) | C57: FABIANA MARISEL ZACARIA | D57: -1303056.7 | E57: ADMINISTRACION | F57: 1 | G57: 1303056.7 | H57: # RRHH | I57: PERSONAL | J57: OPEX | K57: FIJO | L57: INDIRECTO | N57: CC15 | O57: rrhh_nuevo | T57: 1303056.7 | U57: 227 | V57: 227 | W57: 27364438309
A58: 46112 | B58: RRHH WORMS (NUEVO) | C58: JORGE SEBASTIAN ACOSTA | D58: -1289287.6 | E58: BACHAS | F58: 1 | G58: 1289287.6 | H58: # RRHH | I58: PERSONAL | J58: OPEX | K58: FIJO | L58: DIRECTO | N58: CC6 | O58: rrhh_nuevo | T58: 1289287.6 | U58: 55 | V58: 55 | W58: 20340454368
A59: 46112 | B59: RRHH WORMS (NUEVO) | C59: GABRIEL GERARDO CORDOBA | D59: -1286619.5 | E59: ADMINISTRACION | F59: 1 | G59: 1286619.5 | H59: # RRHH | I59: PERSONAL | J59: OPEX | K59: FIJO | L59: INDIRECTO | N59: CC15 | O59: rrhh_nuevo | T59: 1286619.5 | U59: 184 | V59: 184 | W59: 20373340155
A60: 46112 | B60: RRHH WORMS (NUEVO) | C60: ERWIN CHIANEA | D60: -1268210.9 | E60: PRODUCCION | F60: 1 | G60: 1268210.9 | H60: # RRHH | I60: PERSONAL | J60: OPEX | K60: FIJO | L60: DIRECTO | N60: CC28 | O60: rrhh_nuevo | T60: 1268210.9 | U60: 221 | V60: 221 | W60: 20276307755
A61: 46091 | B61: Mollard, Martin Enrique | C61: FA-A 00004-00011678 | D61: -1208811.8 | E61: HIGIENE Y SEGURIDAD Guantes Rojos | F61: 150 | G61: 6660.12 | H61: UN | I61: HIGIENE Y SEGURIDAD | J61: OPEX | K61: VARIABLE | L61: DIRECTO | N61: CC1 | O61: gastos_produccion | R61: EPP
A62: 46112 | B62: RRHH WORMS (NUEVO) | C62: MONTENEGRO GUSTAVO DANIEL | D62: -1155262.9 | E62: INTENDENCIA | F62: 1 | G62: 1155262.9 | H62: # RRHH | I62: PERSONAL | J62: OPEX | K62: FIJO | L62: INDIRECTO | N62: CC27 | O62: rrhh_nuevo | T62: 1155262.9 | U62: 27 | V62: 27 | W62: 20278683762
A63: 46112 | B63: RRHH WORMS (NUEVO) | C63: MAXIMO GUSTAVO ENRIQUEZ | D63: -1128948.3 | E63: DISPOSICIÓN FINAL RESIDUOS LIQUIDOS + EXPORTACION | F63: 1 | G63: 1128948.3 | H63: # RRHH | I63: PERSONAL | J63: OPEX | K63: FIJO | L63: DIRECTO | N63: CC25 | O63: rrhh_nuevo | T63: 1128948.3 | U63: 15 | V63: 15 | W63: 20178981863
A64: 46090 | B64: Ambrogi, Raul | C64: FA-A 00009-00000417 | D64: -1128930 | E64: REPARACIONES Pedido de repuestos para el Massey | F64: 1 | G64: 933000 | H64: UN | I64: REPARACIONES | J64: OPEX | K64: VARIABLE | L64: DIRECTO | N64: CC1 | O64: gastos_produccion | Q64: TALLER | R64: BIEN DE USO
A65: 46112 | B65: RRHH WORMS (NUEVO) | C65: GUSTAVO GASTON BUSTAMANTE | D65: -1128307.7 | E65: INTENDENCIA | F65: 1 | G65: 1128307.7 | H65: # RRHH | I65: PERSONAL | J65: OPEX | K65: FIJO | L65: INDIRECTO | N65: CC27 | O65: rrhh_nuevo | T65: 1128307.7 | U65: 85 | V65: 85 | W65: 20497550050
A66: 46112 | B66: RRHH WORMS (NUEVO) | C66: ULISES BENIGNO BUSTAMANTE | D66: -1111149.2 | E66: PILETAS + BACHAS | F66: 1 | G66: 1111149.2 | H66: # RRHH | I66: PERSONAL | J66: OPEX | K66: FIJO | L66: DIRECTO | N66: CC21 | O66: rrhh_nuevo | T66: 1111149.2 | U66: 60 | V66: 60 | W66: 20479725277
A67: 46112 | B67: RRHH WORMS (NUEVO) | C67: BRIAN NICOLAS BERON | D67: -1099914.5 | E67: REACTOR | F67: 1 | G67: 1099914.5 | H67: # RRHH | I67: PERSONAL | J67: OPEX | K67: FIJO | L67: DIRECTO | N67: CC5 | O67: rrhh_nuevo | T67: 1099914.5 | U67: 220 | V67: 220 | W67: 20434276641
A68: 46112 | B68: RRHH WORMS (NUEVO) | C68: ANDREA ANALI DI PAOLO | D68: -1098479.4 | E68: ADMINISTRACION | F68: 1 | G68: 1098479.4 | H68: # RRHH | I68: PERSONAL | J68: OPEX | K68: FIJO | L68: INDIRECTO | N68: CC15 | O68: rrhh_nuevo | T68: 1098479.4 | U68: 235 | V68: 235 | W68: 27326483791
A69: 46112 | B69: RRHH WORMS (NUEVO) | C69: SEBASTIAN ERNESTO BAEZ | D69: -1094441.7 | E69: MANTENIMIENTO | F69: 1 | G69: 1094441.7 | H69: # RRHH | I69: PERSONAL | J69: OPEX | K69: FIJO | L69: DIRECTO | N69: CC19 | O69: rrhh_nuevo | T69: 1094441.7 | U69: 264 | V69: 264 | W69: 20372610043
A70: 46112 | B70: RRHH WORMS (NUEVO) | C70: ISOLA GIULIANA | D70: -1093875 | E70: ADMINISTRACION | F70: 1 | G70: 1093875 | H70: # RRHH | I70: PERSONAL | J70: OPEX | K70: FIJO | L70: INDIRECTO | N70: CC15 | O70: rrhh_nuevo | T70: 1093875 | U70: 120 | V70: 120 | W70: 27381344261
A71: 46112 | B71: RRHH WORMS (NUEVO) | C71: HECTOR OSCAR FERNANDEZ | D71: -1089034.3 | E71: VIGILANCIA | F71: 1 | G71: 1089034.3 | H71: # RRHH | I71: PERSONAL | J71: OPEX | K71: FIJO | L71: INDIRECTO | N71: CC29 | O71: rrhh_nuevo | T71: 1089034.3 | U71: 186 | V71: 186 | W71: 20180644068
A72: 46112 | B72: RRHH WORMS (NUEVO) | C72: JEREMIAS EDGARDO NAHUEL FERNANDEZ | D72: -1082821.2 | E72: BACHAS | F72: 1 | G72: 1082821.2 | H72: # RRHH | I72: PERSONAL | J72: OPEX | K72: FIJO | L72: DIRECTO | N72: CC6 | O72: rrhh_nuevo | T72: 1082821.2 | U72: 262 | V72: 262 | W72: 20468401968
A73: 46112 | B73: RRHH WORMS (NUEVO) | C73: BRIAN EZEQUIEL GROSSO | D73: -1080740.6 | E73: VIGILANCIA | F73: 1 | G73: 1080740.6 | H73: # RRHH | I73: PERSONAL | J73: OPEX | K73: FIJO | L73: INDIRECTO | N73: CC29 | O73: rrhh_nuevo | T73: 1080740.6 | U73: 191 | V73: 191 | W73: 20398270070
A74: 46112 | B74: RRHH WORMS (NUEVO) | C74: MARIA EDITH MATTAROLLO | D74: -1080319.8 | E74: PORTERIA | F74: 1 | G74: 1080319.8 | H74: # RRHH | I74: PERSONAL | J74: OPEX | K74: FIJO | L74: DIRECTO | N74: CC22 | O74: rrhh_nuevo | T74: 1080319.8 | U74: 200 | V74: 200 | W74: 27305902344
A75: 46112 | B75: RRHH WORMS (NUEVO) | C75: EDUARDO JAVIER PANZANELLA | D75: -1073056.3 | E75: PORTERIA | F75: 1 | G75: 1073056.3 | H75: # RRHH | I75: PERSONAL | J75: OPEX | K75: FIJO | L75: DIRECTO | N75: CC22 | O75: rrhh_nuevo | T75: 1073056.3 | U75: 4 | V75: 4 | W75: 20276685105
A76: 46083 | B76: Multinautica Rosario Srl | C76: FA-A 00004-00001694 | D76: -1050045 | E76: INVERSION bomba para regador intendencia | F76: 1 | G76: 867805.79 | H76: UN | I76: INVERSION | J76: CAPEX | K76: VARIABLE | L76: DIRECTO | N76: CC1 | O76: gastos_produccion | Q76: INTENDENCIA | R76: MANTENIMIENTO Y ORDEN
A77: 46112 | B77: RRHH WORMS (NUEVO) | C77: ALEJANDRO FABIAN ALVAREZ | D77: -1022001 | E77: PILETAS + BACHAS | F77: 1 | G77: 1022001 | H77: # RRHH | I77: PERSONAL | J77: OPEX | K77: FIJO | L77: DIRECTO | N77: CC21 | O77: rrhh_nuevo | T77: 1022001 | U77: 252 | V77: 252 | W77: 20324334255
A78: 46112 | B78: RRHH WORMS (NUEVO) | C78: JOSE RAMON MAIDANA | D78: -1012297.5 | E78: INTENDENCIA | F78: 1 | G78: 1012297.5 | H78: # RRHH | I78: PERSONAL | J78: OPEX | K78: FIJO | L78: INDIRECTO | N78: CC27 | O78: rrhh_nuevo | T78: 1012297.5 | U78: 1 | V78: 1 | W78: 23241749789
A79: 46112 | B79: RRHH WORMS (NUEVO) | C79: HORACIO RODRIGUEZ | D79: -1006372.2 | E79: TALLER MECANICO | F79: 1 | G79: 1006372.2 | H79: # RRHH | I79: PERSONAL | J79: OPEX | K79: FIJO | L79: DIRECTO | N79: CC23 | O79: rrhh_nuevo | T79: 1006372.2 | U79: 174 | V79: 174 | W79: 20245697822
A80: 46112 | B80: RRHH WORMS (NUEVO) | C80: ROLANDO CESAR ADRIAN REY | D80: -998597 | E80: LOGISTICA | F80: 1 | G80: 998597 | H80: # RRHH | I80: PERSONAL | J80: OPEX | K80: FIJO | L80: DIRECTO | N80: CC18 | O80: rrhh_nuevo | T80: 998597 | U80: 218 | V80: 218 | W80: 20240298253
A81: 46112 | B81: RRHH WORMS (NUEVO) | C81: GUSTAVO RAMON ALTAMIRANO | D81: -996409.64 | E81: DISPOSICIÓN FINAL RESIDUOS LIQUIDOS + EXPORTACION | F81: 1 | G81: 996409.64 | H81: # RRHH | I81: PERSONAL | J81: OPEX | K81: FIJO | L81: DIRECTO | N81: CC25 | O81: rrhh_nuevo | T81: 996409.64 | U81: 23 | V81: 23 | W81: 20221319282
A82: 46112 | B82: RRHH WORMS (NUEVO) | C82: LOPEZ CAMARGO BERLITZ BEATRIZ | D82: -993291.09 | E82: LABORATORIO | F82: 1 | G82: 993291.09 | H82: # RRHH | I82: PERSONAL | J82: OPEX | K82: FIJO | L82: DIRECTO | N82: CC17 | O82: rrhh_nuevo | T82: 993291.09 | U82: 34 | V82: 34 | W82: 27960560464
A83: 46112 | B83: RRHH WORMS (NUEVO) | C83: JUAN PABLO MARTINEZ | D83: -991075.49 | E83: MANTENIMIENTO | F83: 1 | G83: 991075.49 | H83: # RRHH | I83: PERSONAL | J83: OPEX | K83: FIJO | L83: DIRECTO | N83: CC19 | O83: rrhh_nuevo | T83: 991075.49 | U83: 231 | V83: 231 | W83: 20364438797
A84: 46112 | B84: RRHH WORMS (NUEVO) | C84: LEANDRO GABRIEL MUÑOZ | D84: -986404.35 | E84: DISPOSICIÓN FINAL RESIDUOS LIQUIDOS + EXPORTACION | F84: 1 | G84: 986404.35 | H84: # RRHH | I84: PERSONAL | J84: OPEX | K84: FIJO | L84: DIRECTO | N84: CC25 | O84: rrhh_nuevo | T84: 986404.35 | U84: 52 | V84: 52 | W84: 20406914284
A85: 46112 | B85: RRHH WORMS (NUEVO) | C85: CESAR IGNACIO PEREZ | D85: -959900.23 | E85: NFU + DISPOSICION FINAL DE R. SOLIDOS | F85: 1 | G85: 959900.23 | H85: # RRHH | I85: PERSONAL | J85: OPEX | K85: FIJO | L85: DIRECTO | N85: CC20 | O85: rrhh_nuevo | T85: 959900.23 | U85: 157 | V85: 157 | W85: 20432838626
A86: 46112 | B86: RRHH WORMS (NUEVO) | C86: FRANCO BRUNO AGUSTIN | D86: -955828.67 | E86: DISPOSICIÓN FINAL RESIDUOS LIQUIDOS + EXPORTACION | F86: 1 | G86: 955828.67 | H86: # RRHH | I86: PERSONAL | J86: OPEX | K86: FIJO | L86: DIRECTO | N86: CC25 | O86: rrhh_nuevo | T86: 955828.67 | U86: 189 | V86: 189 | W86: 20397536298
A87: 46112 | B87: RRHH WORMS (NUEVO) | C87: MAXIMILIANO ESEQUIEL BARRERA | D87: -945255.68 | E87: DISPOSICIÓN FINAL RESIDUOS LIQUIDOS + EXPORTACION | F87: 1 | G87: 945255.68 | H87: # RRHH | I87: PERSONAL | J87: OPEX | K87: FIJO | L87: DIRECTO | N87: CC25 | O87: rrhh_nuevo | T87: 945255.68 | U87: 164 | V87: 164 | W87: 20392493361
A88: 46112 | B88: RRHH WORMS (NUEVO) | C88: AYRTON RODRIGUEZ | D88: -939543.46 | E88: DISPOSICIÓN FINAL RESIDUOS LIQUIDOS + EXPORTACION | F88: 1 | G88: 939543.46 | H88: # RRHH | I88: PERSONAL | J88: OPEX | K88: FIJO | L88: DIRECTO | N88: CC25 | O88: rrhh_nuevo | T88: 939543.46 | U88: 196 | V88: 196 | W88: 20402767139
... A90: 46112 | B90: RRHH WORMS (NUEVO) | C90: FRANCISCO NICOLAS BRAVO | D90: -928418.48 | E90: DISPOSICIÓN FINAL RESIDUOS LIQUIDOS + EXPORTACION | F90: 1 | G90: 928418.48 | H90: # RRHH | I90: PERSONAL | J90: OPEX | K90: FIJO | L90: DIRECTO | N90: CC25 | O90: rrhh_nuevo | T90: 928418.48 | U90: 69 | V90: 69 | W90: 20400406104
A91: 46085 | B91: Telmex Argentina Sa | C91: FA-A 00070-00348134 | D91: -926025.46 | E91: SERVICIOS Internet | F91: 1 | G91: 765310.3 | H91: UN | I91: SERVICIOS | J91: OPEX | K91: VARIABLE | L91: INDIRECTO | N91: CC1 | O91: gastos_produccion | Q91: ADMINISTRACION | R91: SISTEMA
A92: 46112 | B92: RRHH WORMS (NUEVO) | C92: JUAN IGNACIO MARTINEZ | D92: -923683.11 | E92: DISPOSICIÓN FINAL RESIDUOS LIQUIDOS + EXPORTACION | F92: 1 | G92: 923683.11 | H92: # RRHH | I92: PERSONAL | J92: OPEX | K92: FIJO | L92: DIRECTO | N92: CC25 | O92: rrhh_nuevo | T92: 923683.11 | U92: 236 | V92: 236 | W92: 20448105556
A93: 46112 | B93: RRHH WORMS (NUEVO) | C93: MATIAS ROMAN PEREZ | D93: -923204.36 | E93: INTENDENCIA | F93: 1 | G93: 923204.36 | H93: # RRHH | I93: PERSONAL | J93: OPEX | K93: FIJO | L93: INDIRECTO | N93: CC27 | O93: rrhh_nuevo | T93: 923204.36 | U93: 3 | V93: 3 | W93: 20297717147
A94: 46112 | B94: RRHH WORMS (NUEVO) | C94: MATIAS LEONEL VIZCARRA | D94: -917721.28 | E94: MANTENIMIENTO | F94: 1 | G94: 917721.28 | H94: # RRHH | I94: PERSONAL | J94: OPEX | K94: FIJO | L94: DIRECTO | N94: CC19 | O94: rrhh_nuevo | T94: 917721.28 | U94: 261 | V94: 261 | W94: 23402678089
A95: 46112 | B95: RRHH WORMS (NUEVO) | C95: BRYAN EZEQUIEL OVANDO | D95: -908276.4 | E95: MANTENIMIENTO | F95: 1 | G95: 908276.4 | H95: # RRHH | I95: PERSONAL | J95: OPEX | K95: FIJO | L95: DIRECTO | N95: CC19 | O95: rrhh_nuevo | T95: 908276.4 | U95: 228 | V95: 228 | W95: 20381344704
A96: 46091 | B96: Telecom Argentina Sociedad Anonima | C96: FA-A 06364-09382912 | D96: -907182.26 | E96: SERVICIOS Telefonía móvil | F96: 1 | G96: 730426.5 | H96: UN | I96: SERVICIOS | J96: OPEX | K96: VARIABLE | L96: INDIRECTO | N96: CC1 | O96: gastos_produccion | Q96: ADMINISTRACION | R96: SISTEMA
A97: 46084 | B97: Estudio De Profesionales Sa | C97: FA-A 00002-00001547 | D97: -895400 | E97: HONORARIOS Estudio contable Servicios comunales | F97: 1 | G97: 740000 | H97: UN | I97: HONORARIOS | J97: OPEX | K97: FIJO | L97: INDIRECTO | M97: CC13 | O97: gastos_produccion | Q97: ADMINISTRACION | R97: CONTABLE
A98: 46084 | B98: Estudio De Profesionales Sa | C98: FA-A 00002-00001546 | D98: -895400 | E98: HONORARIOS Estudio contable | F98: 1 | G98: 740000 | H98: UN | I98: HONORARIOS | J98: OPEX | K98: FIJO | L98: INDIRECTO | N98: CC1 | O98: gastos_produccion | Q98: ADMINISTRACION | R98: CONTABLE
A99: 46112 | B99: RRHH WORMS (NUEVO) | C99: JESUS RODRIGO LOPEZ | D99: -894944.57 | E99: LOGISTICA | F99: 1 | G99: 894944.57 | H99: # RRHH | I99: PERSONAL | J99: OPEX | K99: FIJO | L99: DIRECTO | N99: CC18 | O99: rrhh_nuevo | T99: 894944.57 | U99: 199 | V99: 199 | W99: 20397537146
A100: 46112 | B100: RRHH WORMS (NUEVO) | C100: VAZQUEZ MATIAS EMANUEL | D100: -893215.88 | E100: PILETAS + BACHAS | F100: 1 | G100: 893215.88 | H100: # RRHH | I100: PERSONAL | J100: OPEX | K100: FIJO | L100: DIRECTO | N100: CC21 | O100: rrhh_nuevo | T100: 893215.88 | U100: 180 | V100: 180 | W100: 20395675673
A101: 46112 | B101: RRHH WORMS (NUEVO) | C101: JUAN PABLO MORENO | D101: -892762.22 | E101: COMPOST & FERTILIZANTES + DISPOSICION FINAL DE R. SOLIDOS | F101: 1 | G101: 892762.22 | H101: # RRHH | I101: PERSONAL | J101: OPEX | K101: FIJO | L101: DIRECTO | N101: CC24 | O101: rrhh_nuevo | T101: 892762.22 | U101: 249 | V101: 249 | W101: 20459511122
...

Sheet bbdd_total.p1
A1: Fecha de Factura/Recibo | B1: Nombre de la empresa a mostrar en la factura | C1: Número | D1: Total con signo | E1: Líneas de factura/Etiqueta | F1: Líneas de factura/Cantidad | G1: Líneas de factura/Precio unitario | H1: Líneas de factura/Unidad de medida | I1: Líneas de factura/Producto | J1: Concepto | K1: Tipo de Gasto 1 | L1: Tipo de Gasto 2 | M1: CCO EMPRESA | N1: CCO - SECTOR | O1: SECTOR_ODOO | P1: # SECTORES | Q1: LISTA_SECTORES | R1: prc_empresa
A2: 46111 | B2: WORMS 2 | C2: prod17 | D2: -2.0810686e+09 | E2: AFE (S) | F2: 1541.07 | G2: 945 | H2: TN | I2: MATERIA PRIMA | J2: OPEX | K2: VARIABLE | L2: DIRECTO | N2: CC11 | O2: gastos_produccion | P2: =_xlfn.XLOOKUP(bbdd3[[#This Row],[CCO - SECTOR]],'cco '!$A:$A,'cco '!F:F,"CCO NO DEFINIDO") -> 1 | Q2: =_xlfn.XLOOKUP(bbdd3[[#This Row],[CCO - SECTOR]],'cco '!$A:$A,'cco '!I:I,"CCO NO DEFINIDO") -> EXPORTACION | R2: =IF(ISBLANK(bbdd3[[#This Row],[CCO EMPRESA]]),1,_xlfn.XLOOKUP(bbdd3[[#This Row],[CCO EMPRESA]],'cco_worms_empresa'!$A:$A,'cco_worms_empresa'!$G:$G)) -> 1
A3: 46111 | B3: WORMS 2 | C3: prod15 | D3: -1.2849682e+08 | E3: AFE (G) | F3: 97.74 | G3: 920 | H3: TN | I3: MATERIA PRIMA | J3: OPEX | K3: VARIABLE | L3: DIRECTO | N3: CC11 | O3: gastos_produccion | P3: =_xlfn.XLOOKUP(bbdd3[[#This Row],[CCO - SECTOR]],'cco '!$A:$A,'cco '!F:F,"CCO NO DEFINIDO") -> 1 | Q3: =_xlfn.XLOOKUP(bbdd3[[#This Row],[CCO - SECTOR]],'cco '!$A:$A,'cco '!I:I,"CCO NO DEFINIDO") -> EXPORTACION | R3: =IF(ISBLANK(bbdd3[[#This Row],[CCO EMPRESA]]),1,_xlfn.XLOOKUP(bbdd3[[#This Row],[CCO EMPRESA]],'cco_worms_empresa'!$A:$A,'cco_worms_empresa'!$G:$G)) -> 1
A4: 46111 | B4: WORMS 2 | C4: prod23 | D4: -89426820 | E4: AG- C | F4: 83.44 | G4: 750 | H4: TN | I4: MATERIA PRIMA | J4: OPEX | K4: VARIABLE | L4: DIRECTO | N4: CC11 | O4: gastos_produccion | P4: =_xlfn.XLOOKUP(bbdd3[[#This Row],[CCO - SECTOR]],'cco '!$A:$A,'cco '!F:F,"CCO NO DEFINIDO") -> 1 | Q4: =_xlfn.XLOOKUP(bbdd3[[#This Row],[CCO - SECTOR]],'cco '!$A:$A,'cco '!I:I,"CCO NO DEFINIDO") -> EXPORTACION | R4: =IF(ISBLANK(bbdd3[[#This Row],[CCO EMPRESA]]),1,_xlfn.XLOOKUP(bbdd3[[#This Row],[CCO EMPRESA]],'cco_worms_empresa'!$A:$A,'cco_worms_empresa'!$G:$G)) -> 1
A5: 46111 | B5: EDUARDO SEMINARA - DENIS LUQUE | C5: prod13 | D5: -87306127 | E5: GLICERINA CRUDA | F5: 169.711 | G5: 360 | H5: TN | I5: INSUMOS | J5: OPEX | K5: VARIABLE | L5: DIRECTO | N5: CC5 | O5: gastos_produccion | P5: =_xlfn.XLOOKUP(bbdd3[[#This Row],[CCO - SECTOR]],'cco '!$A:$A,'cco '!F:F,"CCO NO DEFINIDO") -> 1 | Q5: =_xlfn.XLOOKUP(bbdd3[[#This Row],[CCO - SECTOR]],'cco '!$A:$A,'cco '!I:I,"CCO NO DEFINIDO") -> REACTORES | R5: =IF(ISBLANK(bbdd3[[#This Row],[CCO EMPRESA]]),1,_xlfn.XLOOKUP(bbdd3[[#This Row],[CCO EMPRESA]],'cco_worms_empresa'!$A:$A,'cco_worms_empresa'!$G:$G)) -> 1
A6: 46111 | B6: WORMS 2 | C6: prod29 | D6: -80532152 | E6: ARE- B | F6: 67.09 | G6: 840 | H6: TN | I6: MATERIA PRIMA | J6: OPEX | K6: VARIABLE | L6: DIRECTO | N6: CC11 | O6: gastos_produccion | P6: =_xlfn.XLOOKUP(bbdd3[[#This Row],[CCO - SECTOR]],'cco '!$A:$A,'cco '!F:F,"CCO NO DEFINIDO") -> 1 | Q6: =_xlfn.XLOOKUP(bbdd3[[#This Row],[CCO - SECTOR]],'cco '!$A:$A,'cco '!I:I,"CCO NO DEFINIDO") -> EXPORTACION | R6: =IF(ISBLANK(bbdd3[[#This Row],[CCO EMPRESA]]),1,_xlfn.XLOOKUP(bbdd3[[#This Row],[CCO EMPRESA]],'cco_worms_empresa'!$A:$A,'cco_worms_empresa'!$G:$G)) -> 1
A7: 46111 | B7: WORMS 1 | C7: prod26 | D7: -79981130 | E7: AG-D | F7: 111.94 | G7: 500 | H7: TN | I7: MATERIA PRIMA | J7: OPEX | K7: VARIABLE | L7: DIRECTO | N7: CC6 | O7: gastos_produccion | P7: =_xlfn.XLOOKUP(bbdd3[[#This Row],[CCO - SECTOR]],'cco '!$A:$A,'cco '!F:F,"CCO NO DEFINIDO") -> 1 | Q7: =_xlfn.XLOOKUP(bbdd3[[#This Row],[CCO - SECTOR]],'cco '!$A:$A,'cco '!I:I,"CCO NO DEFINIDO") -> BACHAS | R7: =IF(ISBLANK(bbdd3[[#This Row],[CCO EMPRESA]]),1,_xlfn.XLOOKUP(bbdd3[[#This Row],[CCO EMPRESA]],'cco_worms_empresa'!$A:$A,'cco_worms_empresa'!$G:$G)) -> 1
A8: 46100 | B8: Construcciones Industriales Y Portuarias S.A. | C8: FA-A 00003-00001298 | D8: -54208000 | E8: INVERSION Planta de efluentes | F8: 1 | G8: 44800000 | H8: UN | I8: INVERSION | J8: CAPEX | K8: VARIABLE | L8: INDIRECTO | N8: CC3 | O8: gastos_produccion | P8: =_xlfn.XLOOKUP(bbdd3[[#This Row],[CCO - SECTOR]],'cco '!$A:$A,'cco '!F:F,"CCO NO DEFINIDO") -> 1 | Q8: =_xlfn.XLOOKUP(bbdd3[[#This Row],[CCO - SECTOR]],'cco '!$A:$A,'cco '!I:I,"CCO NO DEFINIDO") -> DISPOSICIÓN FINAL RESIDUOS LIQUIDOS | R8: =IF(ISBLANK(bbdd3[[#This Row],[CCO EMPRESA]]),1,_xlfn.XLOOKUP(bbdd3[[#This Row],[CCO EMPRESA]],'cco_worms_empresa'!$A:$A,'cco_worms_empresa'!$G:$G)) -> 1
A9: 46093 | B9: Construcciones Industriales Y Portuarias S.A. | C9: FA-A 00003-00001295 | D9: -50700270 | E9: INVERSION Planta de efluentes Actualizacion | F9: 1 | G9: 41901050 | H9: UN | I9: INVERSION | J9: CAPEX | K9: VARIABLE | L9: INDIRECTO | N9: CC3 | O9: gastos_produccion | P9: =_xlfn.XLOOKUP(bbdd3[[#This Row],[CCO - SECTOR]],'cco '!$A:$A,'cco '!F:F,"CCO NO DEFINIDO") -> 1 | Q9: =_xlfn.XLOOKUP(bbdd3[[#This Row],[CCO - SECTOR]],'cco '!$A:$A,'cco '!I:I,"CCO NO DEFINIDO") -> DISPOSICIÓN FINAL RESIDUOS LIQUIDOS | R9: =IF(ISBLANK(bbdd3[[#This Row],[CCO EMPRESA]]),1,_xlfn.XLOOKUP(bbdd3[[#This Row],[CCO EMPRESA]],'cco_worms_empresa'!$A:$A,'cco_worms_empresa'!$G:$G)) -> 1
A10: 46111 | B10: WORMS 2 | C10: prod19 | D10: -47687159 | E10: AG- A | F10: 39.26 | G10: 850 | H10: TN | I10: MATERIA PRIMA | J10: OPEX | K10: VARIABLE | L10: DIRECTO | N10: CC11 | O10: gastos_produccion | P10: =_xlfn.XLOOKUP(bbdd3[[#This Row],[CCO - SECTOR]],'cco '!$A:$A,'cco '!F:F,"CCO NO DEFINIDO") -> 1 | Q10: =_xlfn.XLOOKUP(bbdd3[[#This Row],[CCO - SECTOR]],'cco '!$A:$A,'cco '!I:I,"CCO NO DEFINIDO") -> EXPORTACION | R10: =IF(ISBLANK(bbdd3[[#This Row],[CCO EMPRESA]]),1,_xlfn.XLOOKUP(bbdd3[[#This Row],[CCO EMPRESA]],'cco_worms_empresa'!$A:$A,'cco_worms_empresa'!$G:$G)) -> 1
A11: 46111 | B11: WORMS 1 | C11: prod25 | D11: -45305016 | E11: AG- C | F11: 42.272 | G11: 750 | H11: TN | I11: MATERIA PRIMA | J11: OPEX | K11: VARIABLE | L11: DIRECTO | N11: CC5 | O11: gastos_produccion | P11: =_xlfn.XLOOKUP(bbdd3[[#This Row],[CCO - SECTOR]],'cco '!$A:$A,'cco '!F:F,"CCO NO DEFINIDO") -> 1 | Q11: =_xlfn.XLOOKUP(bbdd3[[#This Row],[CCO - SECTOR]],'cco '!$A:$A,'cco '!I:I,"CCO NO DEFINIDO") -> REACTORES | R11: =IF(ISBLANK(bbdd3[[#This Row],[CCO EMPRESA]]),1,_xlfn.XLOOKUP(bbdd3[[#This Row],[CCO EMPRESA]],'cco_worms_empresa'!$A:$A,'cco_worms_empresa'!$G:$G)) -> 1
A12: 46111 | B12: LOGISTICA EXPORTACION | C12: FA-C 2-2026-3 | D12: -41270898 | E12: FOB | F12: 1038.915 | G12: 39725 | H12: TN | I12: LOGISTICA | J12: OPEX | K12: VARIABLE | L12: DIRECTO | N12: CC11 | O12: gastos_produccion | P12: =_xlfn.XLOOKUP(bbdd3[[#This Row],[CCO - SECTOR]],'cco '!$A:$A,'cco '!F:F,"CCO NO DEFINIDO") -> 1 | Q12: =_xlfn.XLOOKUP(bbdd3[[#This Row],[CCO - SECTOR]],'cco '!$A:$A,'cco '!I:I,"CCO NO DEFINIDO") -> EXPORTACION | R12: =IF(ISBLANK(bbdd3[[#This Row],[CCO EMPRESA]]),1,_xlfn.XLOOKUP(bbdd3[[#This Row],[CCO EMPRESA]],'cco_worms_empresa'!$A:$A,'cco_worms_empresa'!$G:$G)) -> 1
A13: 46085 | B13: Nation Limited S.A. | C13: FA-A 00001-00000285 | D13: -38586537 | E13: INVERSION Geomembrana Proy #6 | F13: 1 | G13: 31889700 | H13: UN | I13: INVERSION | J13: CAPEX | K13: VARIABLE | L13: DIRECTO | N13: CC3 | O13: gastos_produccion | P13: =_xlfn.XLOOKUP(bbdd3[[#This Row],[CCO - SECTOR]],'cco '!$A:$A,'cco '!F:F,"CCO NO DEFINIDO") -> 1 | Q13: =_xlfn.XLOOKUP(bbdd3[[#This Row],[CCO - SECTOR]],'cco '!$A:$A,'cco '!I:I,"CCO NO DEFINIDO") -> DISPOSICIÓN FINAL RESIDUOS LIQUIDOS | R13: =IF(ISBLANK(bbdd3[[#This Row],[CCO EMPRESA]]),1,_xlfn.XLOOKUP(bbdd3[[#This Row],[CCO EMPRESA]],'cco_worms_empresa'!$A:$A,'cco_worms_empresa'!$G:$G)) -> 1
... A96: 46091 | B96: Telecom Argentina Sociedad Anonima | C96: FA-A 06364-09382912 | D96: -907182.26 | E96: SERVICIOS Telefonía móvil | F96: 1 | G96: 730426.5 | H96: UN | I96: SERVICIOS | J96: OPEX | K96: VARIABLE | L96: INDIRECTO | N96: CC1 | O96: gastos_produccion | P96: =_xlfn.XLOOKUP(bbdd3[[#This Row],[CCO - SECTOR]],'cco '!$A:$A,'cco '!F:F,"CCO NO DEFINIDO") -> 10 | Q96: =_xlfn.XLOOKUP(bbdd3[[#This Row],[CCO - SECTOR]],'cco '!$A:$A,'cco '!I:I,"CCO NO DEFINIDO") -> BACHAS, CEREAL & POLVILLO, COMPOST & FERTILIZANTES, DISPOSICIÓN FINAL RESIDUOS LIQUIDOS, DISPOSICIÓN FINAL RESIDUOS SOLIDOS, EXPORTACION, NFU, PILETAS, REACTORES, TIERRAS FILTRANTES | R96: =IF(ISBLANK(bbdd3[[#This Row],[CCO EMPRESA]]),1,_xlfn.XLOOKUP(bbdd3[[#This Row],[CCO EMPRESA]],'cco_worms_empresa'!$A:$A,'cco_worms_empresa'!$G:$G)) -> 1
A97: 46084 | B97: Estudio De Profesionales Sa | C97: FA-A 00002-00001547 | D97: -895400 | E97: HONORARIOS Estudio contable Servicios comunales | F97: 1 | G97: 740000 | H97: UN | I97: HONORARIOS | J97: OPEX | K97: FIJO | L97: INDIRECTO | M97: CC13 | O97: gastos_produccion | P97: =_xlfn.XLOOKUP(bbdd3[[#This Row],[CCO - SECTOR]],'cco '!$A:$A,'cco '!F:F,"CCO NO DEFINIDO") -> 0 | Q97: =_xlfn.XLOOKUP(bbdd3[[#This Row],[CCO - SECTOR]],'cco '!$A:$A,'cco '!I:I,"CCO NO DEFINIDO") -> 0 | R97: =IF(ISBLANK(bbdd3[[#This Row],[CCO EMPRESA]]),1,_xlfn.XLOOKUP(bbdd3[[#This Row],[CCO EMPRESA]],'cco_worms_empresa'!$A:$A,'cco_worms_empresa'!$G:$G)) -> 0.7
A98: 46084 | B98: Estudio De Profesionales Sa | C98: FA-A 00002-00001546 | D98: -895400 | E98: HONORARIOS Estudio contable | F98: 1 | G98: 740000 | H98: UN | I98: HONORARIOS | J98: OPEX | K98: FIJO | L98: INDIRECTO | N98: CC1 | O98: gastos_produccion | P98: =_xlfn.XLOOKUP(bbdd3[[#This Row],[CCO - SECTOR]],'cco '!$A:$A,'cco '!F:F,"CCO NO DEFINIDO") -> 10 | Q98: =_xlfn.XLOOKUP(bbdd3[[#This Row],[CCO - SECTOR]],'cco '!$A:$A,'cco '!I:I,"CCO NO DEFINIDO") -> BACHAS, CEREAL & POLVILLO, COMPOST & FERTILIZANTES, DISPOSICIÓN FINAL RESIDUOS LIQUIDOS, DISPOSICIÓN FINAL RESIDUOS SOLIDOS, EXPORTACION, NFU, PILETAS, REACTORES, TIERRAS FILTRANTES | R98: =IF(ISBLANK(bbdd3[[#This Row],[CCO EMPRESA]]),1,_xlfn.XLOOKUP(bbdd3[[#This Row],[CCO EMPRESA]],'cco_worms_empresa'!$A:$A,'cco_worms_empresa'!$G:$G)) -> 1
A99: 46112 | B99: RRHH WORMS (NUEVO) | C99: JESUS RODRIGO LOPEZ | D99: -894944.57 | E99: LOGISTICA | F99: 1 | G99: 894944.57 | H99: # RRHH | I99: PERSONAL | J99: OPEX | K99: FIJO | L99: DIRECTO | N99: CC18 | O99: rrhh_nuevo | P99: =_xlfn.XLOOKUP(bbdd3[[#This Row],[CCO - SECTOR]],'cco '!$A:$A,'cco '!F:F,"CCO NO DEFINIDO") -> 5 | Q99: =_xlfn.XLOOKUP(bbdd3[[#This Row],[CCO - SECTOR]],'cco '!$A:$A,'cco '!I:I,"CCO NO DEFINIDO") -> DISPOSICION FINAL DE R. SOLIDOS, EXPORTACION, NFU, PILETAS, REACTORES | R99: =IF(ISBLANK(bbdd3[[#This Row],[CCO EMPRESA]]),1,_xlfn.XLOOKUP(bbdd3[[#This Row],[CCO EMPRESA]],'cco_worms_empresa'!$A:$A,'cco_worms_empresa'!$G:$G)) -> 1
A100: 46112 | B100: RRHH WORMS (NUEVO) | C100: VAZQUEZ MATIAS EMANUEL | D100: -893215.88 | E100: PILETAS + BACHAS | F100: 1 | G100: 893215.88 | H100: # RRHH | I100: PERSONAL | J100: OPEX | K100: FIJO | L100: DIRECTO | N100: CC21 | O100: rrhh_nuevo | P100: =_xlfn.XLOOKUP(bbdd3[[#This Row],[CCO - SECTOR]],'cco '!$A:$A,'cco '!F:F,"CCO NO DEFINIDO") -> 2 | Q100: =_xlfn.XLOOKUP(bbdd3[[#This Row],[CCO - SECTOR]],'cco '!$A:$A,'cco '!I:I,"CCO NO DEFINIDO") -> BACHAS, PILETAS | R100: =IF(ISBLANK(bbdd3[[#This Row],[CCO EMPRESA]]),1,_xlfn.XLOOKUP(bbdd3[[#This Row],[CCO EMPRESA]],'cco_worms_empresa'!$A:$A,'cco_worms_empresa'!$G:$G)) -> 1
A101: 46112 | B101: RRHH WORMS (NUEVO) | C101: JUAN PABLO MORENO | D101: -892762.22 | E101: COMPOST & FERTILIZANTES + DISPOSICION FINAL DE R. SOLIDOS | F101: 1 | G101: 892762.22 | H101: # RRHH | I101: PERSONAL | J101: OPEX | K101: FIJO | L101: DIRECTO | N101: CC24 | O101: rrhh_nuevo | P101: =_xlfn.XLOOKUP(bbdd3[[#This Row],[CCO - SECTOR]],'cco '!$A:$A,'cco '!F:F,"CCO NO DEFINIDO") -> 2 | Q101: =_xlfn.XLOOKUP(bbdd3[[#This Row],[CCO - SECTOR]],'cco '!$A:$A,'cco '!I:I,"CCO NO DEFINIDO") -> COMPOST Y FERTILIZANTES, DISPOSICION FINAL DE R. SOLIDOS | R101: =IF(ISBLANK(bbdd3[[#This Row],[CCO EMPRESA]]),1,_xlfn.XLOOKUP(bbdd3[[#This Row],[CCO EMPRESA]],'cco_worms_empresa'!$A:$A,'cco_worms_empresa'!$G:$G)) -> 1
A102: 46112 | B102: RRHH WORMS (NUEVO) | C102: CAMILO RAFAEL BORDON | D102: -888429.56 | E102: REACTOR | F102: 1 | G102: 888429.56 | H102: # RRHH | I102: PERSONAL | J102: OPEX | K102: FIJO | L102: DIRECTO | N102: CC5 | O102: rrhh_nuevo | P102: =_xlfn.XLOOKUP(bbdd3[[#This Row],[CCO - SECTOR]],'cco '!$A:$A,'cco '!F:F,"CCO NO DEFINIDO") -> 1 | Q102: =_xlfn.XLOOKUP(bbdd3[[#This Row],[CCO - SECTOR]],'cco '!$A:$A,'cco '!I:I,"CCO NO DEFINIDO") -> REACTORES | R102: =IF(ISBLANK(bbdd3[[#This Row],[CCO EMPRESA]]),1,_xlfn.XLOOKUP(bbdd3[[#This Row],[CCO EMPRESA]],'cco_worms_empresa'!$A:$A,'cco_worms_empresa'!$G:$G)) -> 1
A103: 46112 | B103: RRHH WORMS (NUEVO) | C103: GERMAN CLAUDIO POLLACCHI | D103: -885658.49 | E103: VIGILANCIA | F103: 1 | G103: 885658.49 | H103: # RRHH | I103: PERSONAL | J103: OPEX | K103: FIJO | L103: INDIRECTO | N103: CC29 | O103: rrhh_nuevo | P103: =_xlfn.XLOOKUP(bbdd3[[#This Row],[CCO - SECTOR]],'cco '!$A:$A,'cco '!F:F,"CCO NO DEFINIDO") -> 10 | Q103: =_xlfn.XLOOKUP(bbdd3[[#This Row],[CCO - SECTOR]],'cco '!$A:$A,'cco '!I:I,"CCO NO DEFINIDO") -> BACHAS, CEREAL Y POLVILLO, COMPOST Y FERTILIZANTES, DISPOSICION FINAL DE R. LIQUIDOS, DISPOSICION FINAL DE R. SOLIDOS, EXPORTACION, NFU, PILETAS, REACTORES, TIERRAS FILTRANTES | R103: =IF(ISBLANK(bbdd3[[#This Row],[CCO EMPRESA]]),1,_xlfn.XLOOKUP(bbdd3[[#This Row],[CCO EMPRESA]],'cco_worms_empresa'!$A:$A,'cco_worms_empresa'!$G:$G)) -> 1
A104: 46112 | B104: RRHH WORMS (NUEVO) | C104: HECTOR JOAQUIN BAEZ | D104: -877797.38 | E104: TALLER MECANICO | F104: 1 | G104: 877797.38 | H104: # RRHH | I104: PERSONAL | J104: OPEX | K104: FIJO | L104: DIRECTO | N104: CC23 | O104: rrhh_nuevo | P104: =_xlfn.XLOOKUP(bbdd3[[#This Row],[CCO - SECTOR]],'cco '!$A:$A,'cco '!F:F,"CCO NO DEFINIDO") -> 10 | Q104: =_xlfn.XLOOKUP(bbdd3[[#This Row],[CCO - SECTOR]],'cco '!$A:$A,'cco '!I:I,"CCO NO DEFINIDO") -> BACHAS, CEREAL Y POLVILLO, COMPOST Y FERTILIZANTES, DISPOSICION FINAL DE R. LIQUIDOS, DISPOSICION FINAL DE R. SOLIDOS, EXPORTACION, NFU, PILETAS, REACTORES, TIERRAS FILTRANTES | R104: =IF(ISBLANK(bbdd3[[#This Row],[CCO EMPRESA]]),1,_xlfn.XLOOKUP(bbdd3[[#This Row],[CCO EMPRESA]],'cco_worms_empresa'!$A:$A,'cco_worms_empresa'!$G:$G)) -> 1
A105: 46112 | B105: RRHH WORMS (NUEVO) | C105: JOAQUIN ESTEBAN CECCHI | D105: -875549.35 | E105: PRODUCCION | F105: 1 | G105: 875549.35 | H105: # RRHH | I105: PERSONAL | J105: OPEX | K105: FIJO | L105: DIRECTO | N105: CC28 | O105: rrhh_nuevo | P105: =_xlfn.XLOOKUP(bbdd3[[#This Row],[CCO - SECTOR]],'cco '!$A:$A,'cco '!F:F,"CCO NO DEFINIDO") -> 10 | Q105: =_xlfn.XLOOKUP(bbdd3[[#This Row],[CCO - SECTOR]],'cco '!$A:$A,'cco '!I:I,"CCO NO DEFINIDO") -> BACHAS, CEREAL & POLVILLO, COMPOST & FERTILIZANTES, DISPOSICIÓN FINAL RESIDUOS LIQUIDOS, DISPOSICIÓN FINAL RESIDUOS SOLIDOS, EXPORTACION, NFU, PILETAS, REACTORES, TIERRAS FILTRANTES | R105: =IF(ISBLANK(bbdd3[[#This Row],[CCO EMPRESA]]),1,_xlfn.XLOOKUP(bbdd3[[#This Row],[CCO EMPRESA]],'cco_worms_empresa'!$A:$A,'cco_worms_empresa'!$G:$G)) -> 1
A106: 46112 | B106: RRHH WORMS (NUEVO) | C106: VALENTIN DE AVELENDA | D106: -874663.9 | E106: DISPOSICIÓN FINAL RESIDUOS LIQUIDOS + EXPORTACION | F106: 1 | G106: 874663.9 | H106: # RRHH | I106: PERSONAL | J106: OPEX | K106: FIJO | L106: DIRECTO | N106: CC25 | O106: rrhh_nuevo | P106: =_xlfn.XLOOKUP(bbdd3[[#This Row],[CCO - SECTOR]],'cco '!$A:$A,'cco '!F:F,"CCO NO DEFINIDO") -> 2 | Q106: =_xlfn.XLOOKUP(bbdd3[[#This Row],[CCO - SECTOR]],'cco '!$A:$A,'cco '!I:I,"CCO NO DEFINIDO") -> DISPOSICION FINAL DE R. LIQUIDOS, EXPORTACION | R106: =IF(ISBLANK(bbdd3[[#This Row],[CCO EMPRESA]]),1,_xlfn.XLOOKUP(bbdd3[[#This Row],[CCO EMPRESA]],'cco_worms_empresa'!$A:$A,'cco_worms_empresa'!$G:$G)) -> 1
A107: 46112 | B107: RRHH WORMS (NUEVO) | C107: NUÑEZ ALAN OSVALDO | D107: -871867.94 | E107: PILETAS + BACHAS | F107: 1 | G107: 871867.94 | H107: # RRHH | I107: PERSONAL | J107: OPEX | K107: FIJO | L107: DIRECTO | N107: CC21 | O107: rrhh_nuevo | P107: =_xlfn.XLOOKUP(bbdd3[[#This Row],[CCO - SECTOR]],'cco '!$A:$A,'cco '!F:F,"CCO NO DEFINIDO") -> 2 | Q107: =_xlfn.XLOOKUP(bbdd3[[#This Row],[CCO - SECTOR]],'cco '!$A:$A,'cco '!I:I,"CCO NO DEFINIDO") -> BACHAS, PILETAS | R107: =IF(ISBLANK(bbdd3[[#This Row],[CCO EMPRESA]]),1,_xlfn.XLOOKUP(bbdd3[[#This Row],[CCO EMPRESA]],'cco_worms_empresa'!$A:$A,'cco_worms_empresa'!$G:$G)) -> 1
A108: 46093 | B108: Comercial Uritorco S. R. L. (w) | C108: FA-A 00001-00009009 | D108: -871775.04 | E108: REPOSICION | F108: 1 | G108: 124786.25 | H108: UN | I108: REPOSICION | J108: OPEX | K108: VARIABLE | L108: INDIRECTO | N108: CC1 | O108: gastos_produccion | P108: =_xlfn.XLOOKUP(bbdd3[[#This Row],[CCO - SECTOR]],'cco '!$A:$A,'cco '!F:F,"CCO NO DEFINIDO") -> 10 | Q108: =_xlfn.XLOOKUP(bbdd3[[#This Row],[CCO - SECTOR]],'cco '!$A:$A,'cco '!I:I,"CCO NO DEFINIDO") -> BACHAS, CEREAL & POLVILLO, COMPOST & FERTILIZANTES, DISPOSICIÓN FINAL RESIDUOS LIQUIDOS, DISPOSICIÓN FINAL RESIDUOS SOLIDOS, EXPORTACION, NFU, PILETAS, REACTORES, TIERRAS FILTRANTES | R108: =IF(ISBLANK(bbdd3[[#This Row],[CCO EMPRESA]]),1,_xlfn.XLOOKUP(bbdd3[[#This Row],[CCO EMPRESA]],'cco_worms_empresa'!$A:$A,'cco_worms_empresa'!$G:$G)) -> 1
A109: 46112 | B109: RRHH WORMS (NUEVO) | C109: VANINA ELIZABETH LARREY | D109: -868719.75 | E109: PORTERIA | F109: 1 | G109: 868719.75 | H109: # RRHH | I109: PERSONAL | J109: OPEX | K109: FIJO | L109: DIRECTO | N109: CC22 | O109: rrhh_nuevo | P109: =_xlfn.XLOOKUP(bbdd3[[#This Row],[CCO - SECTOR]],'cco '!$A:$A,'cco '!F:F,"CCO NO DEFINIDO") -> 7 | Q109: =_xlfn.XLOOKUP(bbdd3[[#This Row],[CCO - SECTOR]],'cco '!$A:$A,'cco '!I:I,"CCO NO DEFINIDO") -> BACHAS, COMPOST Y FERTILIZANTES, DISPOSICION FINAL DE R. LIQUIDOS, DISPOSICION FINAL DE R. SOLIDOS, EXPORTACION, NFU, REACTORES | R109: =IF(ISBLANK(bbdd3[[#This Row],[CCO EMPRESA]]),1,_xlfn.XLOOKUP(bbdd3[[#This Row],[CCO EMPRESA]],'cco_worms_empresa'!$A:$A,'cco_worms_empresa'!$G:$G)) -> 1
... A235: 46111 | B235: WORMS 1 | C235: prod31 | D235: 0 | E235: BORRA AN | F235: 0 | G235: 500 | H235: TN | I235: MATERIA PRIMA | J235: OPEX | K235: VARIABLE | L235: DIRECTO | N235: CC6 | O235: gastos_produccion | P235: =_xlfn.XLOOKUP(bbdd3[[#This Row],[CCO - SECTOR]],'cco '!$A:$A,'cco '!F:F,"CCO NO DEFINIDO") -> 1 | Q235: =_xlfn.XLOOKUP(bbdd3[[#This Row],[CCO - SECTOR]],'cco '!$A:$A,'cco '!I:I,"CCO NO DEFINIDO") -> BACHAS | R235: =IF(ISBLANK(bbdd3[[#This Row],[CCO EMPRESA]]),1,_xlfn.XLOOKUP(bbdd3[[#This Row],[CCO EMPRESA]],'cco_worms_empresa'!$A:$A,'cco_worms_empresa'!$G:$G)) -> 1
A236: 46111 | B236: WORMS 1 | C236: prod32 | D236: 0 | E236: ÁCIDO CITRICO | F236: 0 | H236: KG | I236: INSUMOS | J236: OPEX | K236: VARIABLE | L236: DIRECTO | N236: CC6 | O236: gastos_produccion | P236: =_xlfn.XLOOKUP(bbdd3[[#This Row],[CCO - SECTOR]],'cco '!$A:$A,'cco '!F:F,"CCO NO DEFINIDO") -> 1 | Q236: =_xlfn.XLOOKUP(bbdd3[[#This Row],[CCO - SECTOR]],'cco '!$A:$A,'cco '!I:I,"CCO NO DEFINIDO") -> BACHAS | R236: =IF(ISBLANK(bbdd3[[#This Row],[CCO EMPRESA]]),1,_xlfn.XLOOKUP(bbdd3[[#This Row],[CCO EMPRESA]],'cco_worms_empresa'!$A:$A,'cco_worms_empresa'!$G:$G)) -> 1
A237: 46111 | B237: WORMS 1 | C237: prod34 | D237: 0 | E237: BORRA A | F237: 20.48 | H237: KG | I237: MATERIA PRIMA | J237: OPEX | K237: VARIABLE | L237: DIRECTO | N237: CC6 | O237: gastos_produccion | P237: =_xlfn.XLOOKUP(bbdd3[[#This Row],[CCO - SECTOR]],'cco '!$A:$A,'cco '!F:F,"CCO NO DEFINIDO") -> 1 | Q237: =_xlfn.XLOOKUP(bbdd3[[#This Row],[CCO - SECTOR]],'cco '!$A:$A,'cco '!I:I,"CCO NO DEFINIDO") -> BACHAS | R237: =IF(ISBLANK(bbdd3[[#This Row],[CCO EMPRESA]]),1,_xlfn.XLOOKUP(bbdd3[[#This Row],[CCO EMPRESA]],'cco_worms_empresa'!$A:$A,'cco_worms_empresa'!$G:$G)) -> 1
A238: 46111 | B238: FCA | C238: FA-C 2-2026-3 | D238: 0 | E238: FCA | F238: 808.045 | G238: 0 | H238: TN | I238: LOGISTICA | J238: OPEX | K238: VARIABLE | L238: DIRECTO | N238: CC11 | O238: gastos_produccion | P238: =_xlfn.XLOOKUP(bbdd3[[#This Row],[CCO - SECTOR]],'cco '!$A:$A,'cco '!F:F,"CCO NO DEFINIDO") -> 1 | Q238: =_xlfn.XLOOKUP(bbdd3[[#This Row],[CCO - SECTOR]],'cco '!$A:$A,'cco '!I:I,"CCO NO DEFINIDO") -> EXPORTACION | R238: =IF(ISBLANK(bbdd3[[#This Row],[CCO EMPRESA]]),1,_xlfn.XLOOKUP(bbdd3[[#This Row],[CCO EMPRESA]],'cco_worms_empresa'!$A:$A,'cco_worms_empresa'!$G:$G)) -> 1
A239: 46112 | B239: RRHH WORMS (NUEVO) | C239: BELTRAMO, ANDRES | D239: 0 | E239: DISPOSICIÓN FINAL RESIDUOS SOLIDOS | F239: 1 | G239: 0 | H239: # RRHH | I239: PERSONAL | J239: OPEX | K239: FIJO | L239: DIRECTO | N239: CC2 | O239: rrhh_nuevo | P239: =_xlfn.XLOOKUP(bbdd3[[#This Row],[CCO - SECTOR]],'cco '!$A:$A,'cco '!F:F,"CCO NO DEFINIDO") -> 1 | Q239: =_xlfn.XLOOKUP(bbdd3[[#This Row],[CCO - SECTOR]],'cco '!$A:$A,'cco '!I:I,"CCO NO DEFINIDO") -> DISPOSICIÓN FINAL RESIDUOS SOLIDOS | R239: =IF(ISBLANK(bbdd3[[#This Row],[CCO EMPRESA]]),1,_xlfn.XLOOKUP(bbdd3[[#This Row],[CCO EMPRESA]],'cco_worms_empresa'!$A:$A,'cco_worms_empresa'!$G:$G)) -> 1
A240: 46112 | B240: RRHH WORMS (NUEVO) | C240: CENSABELLA, AMALIA | D240: 0 | E240: DISPOSICIÓN FINAL RESIDUOS LIQUIDOS | F240: 1 | G240: 0 | H240: # RRHH | I240: PERSONAL | J240: OPEX | K240: FIJO | L240: DIRECTO | N240: CC3 | O240: rrhh_nuevo | P240: =_xlfn.XLOOKUP(bbdd3[[#This Row],[CCO - SECTOR]],'cco '!$A:$A,'cco '!F:F,"CCO NO DEFINIDO") -> 1 | Q240: =_xlfn.XLOOKUP(bbdd3[[#This Row],[CCO - SECTOR]],'cco '!$A:$A,'cco '!I:I,"CCO NO DEFINIDO") -> DISPOSICIÓN FINAL RESIDUOS LIQUIDOS | R240: =IF(ISBLANK(bbdd3[[#This Row],[CCO EMPRESA]]),1,_xlfn.XLOOKUP(bbdd3[[#This Row],[CCO EMPRESA]],'cco_worms_empresa'!$A:$A,'cco_worms_empresa'!$G:$G)) -> 1
A241: 46112 | B241: RRHH WORMS (NUEVO) | C241: CUETO, DANIELA | D241: 0 | E241: ADMINISTRACION | F241: 1 | G241: 0 | H241: # RRHH | I241: PERSONAL | J241: OPEX | K241: FIJO | L241: DIRECTO | N241: CC15 | O241: rrhh_nuevo | P241: =_xlfn.XLOOKUP(bbdd3[[#This Row],[CCO - SECTOR]],'cco '!$A:$A,'cco '!F:F,"CCO NO DEFINIDO") -> 10 | Q241: =_xlfn.XLOOKUP(bbdd3[[#This Row],[CCO - SECTOR]],'cco '!$A:$A,'cco '!I:I,"CCO NO DEFINIDO") -> BACHAS, CEREAL Y POLVILLO, COMPOST Y FERTILIZANTES, DISPOSICION FINAL DE R. LIQUIDOS, DISPOSICION FINAL DE R. SOLIDOS, EXPORTACION, NFU, PILETAS, REACTORES, TIERRAS FILTRANTES | R241: =IF(ISBLANK(bbdd3[[#This Row],[CCO EMPRESA]]),1,_xlfn.XLOOKUP(bbdd3[[#This Row],[CCO EMPRESA]],'cco_worms_empresa'!$A:$A,'cco_worms_empresa'!$G:$G)) -> 1

Sheet Sheet1
A1: CCO - SECTOR | B1: # SECTORES
A2: CC11 | B2: 1
A3: CC5 | B3: 1
A4: CC6 | B4: 1
A5: CC3 | B5: 1
A6: CC7 | B6: 1
A7: CC4 | B7: 1
A8: CC2 | B8: 1
A9: CC9 | B9: 1
A10: CC8 | B10: 1
A11: CC20 | B11: 2
A12: CC25 | B12: 2
A13: CC21 | B13: 2
... A26: CC23 | B26: 10

Sheet aperturado_por_empresa.p2
A1: {=_xlfn._xlws.PY(0,0,bbdd3[])} -> 0 | B1: 1 | C1: 2 | D1: 3 | E1: 4 | F1: 5 | G1: 6 | H1: 7 | I1: 8 | J1: 9 | K1: 10 | L1: 11 | M1: 12 | N1: 13 | O1: 14 | P1: 15 | Q1: 16 | R1: 17 | S1: Total*prc (D×R) | T1: Cantidad*prc (F×R) | U1: APERTURADO POR EMPRESA
A2: 46111 | B2: WORMS 2 | C2: prod17 | D2: -2.0810686e+09 | E2: AFE (S) | F2: 1541.07 | G2: 945 | H2: TN | I2: MATERIA PRIMA | J2: OPEX | K2: VARIABLE | L2: DIRECTO | M2: 0 | N2: CC11 | O2: gastos_produccion | P2: 1 | Q2: EXPORTACION | R2: 1 | S2: -2.0810686e+09 | T2: 1541.07 | U2: APERTURADO POR EMPRESA
A3: 46111 | B3: WORMS 2 | C3: prod15 | D3: -1.2849682e+08 | E3: AFE (G) | F3: 97.74 | G3: 920 | H3: TN | I3: MATERIA PRIMA | J3: OPEX | K3: VARIABLE | L3: DIRECTO | M3: 0 | N3: CC11 | O3: gastos_produccion | P3: 1 | Q3: EXPORTACION | R3: 1 | S3: -1.2849682e+08 | T3: 97.74 | U3: APERTURADO POR EMPRESA
A4: 46111 | B4: WORMS 2 | C4: prod23 | D4: -89426820 | E4: AG- C | F4: 83.44 | G4: 750 | H4: TN | I4: MATERIA PRIMA | J4: OPEX | K4: VARIABLE | L4: DIRECTO | M4: 0 | N4: CC11 | O4: gastos_produccion | P4: 1 | Q4: EXPORTACION | R4: 1 | S4: -89426820 | T4: 83.44 | U4: APERTURADO POR EMPRESA
A5: 46111 | B5: EDUARDO SEMINARA - DENIS LUQUE | C5: prod13 | D5: -87306127 | E5: GLICERINA CRUDA | F5: 169.711 | G5: 360 | H5: TN | I5: INSUMOS | J5: OPEX | K5: VARIABLE | L5: DIRECTO | M5: 0 | N5: CC5 | O5: gastos_produccion | P5: 1 | Q5: REACTORES | R5: 1 | S5: -87306127 | T5: 169.711 | U5: APERTURADO POR EMPRESA
A6: 46111 | B6: WORMS 2 | C6: prod29 | D6: -80532152 | E6: ARE- B | F6: 67.09 | G6: 840 | H6: TN | I6: MATERIA PRIMA | J6: OPEX | K6: VARIABLE | L6: DIRECTO | M6: 0 | N6: CC11 | O6: gastos_produccion | P6: 1 | Q6: EXPORTACION | R6: 1 | S6: -80532152 | T6: 67.09 | U6: APERTURADO POR EMPRESA
A7: 46111 | B7: WORMS 1 | C7: prod26 | D7: -79981130 | E7: AG-D | F7: 111.94 | G7: 500 | H7: TN | I7: MATERIA PRIMA | J7: OPEX | K7: VARIABLE | L7: DIRECTO | M7: 0 | N7: CC6 | O7: gastos_produccion | P7: 1 | Q7: BACHAS | R7: 1 | S7: -79981130 | T7: 111.94 | U7: APERTURADO POR EMPRESA
A8: 46100 | B8: Construcciones Industriales Y Portuarias S.A. | C8: FA-A 00003-00001298 | D8: -54208000 | E8: INVERSION Planta de efluentes | F8: 1 | G8: 44800000 | H8: UN | I8: INVERSION | J8: CAPEX | K8: VARIABLE | L8: INDIRECTO | M8: 0 | N8: CC3 | O8: gastos_produccion | P8: 1 | Q8: DISPOSICIÓN FINAL RESIDUOS LIQUIDOS | R8: 1 | S8: -54208000 | T8: 1 | U8: APERTURADO POR EMPRESA
A9: 46093 | B9: Construcciones Industriales Y Portuarias S.A. | C9: FA-A 00003-00001295 | D9: -50700270 | E9: INVERSION Planta de efluentes Actualizacion | F9: 1 | G9: 41901050 | H9: UN | I9: INVERSION | J9: CAPEX | K9: VARIABLE | L9: INDIRECTO | M9: 0 | N9: CC3 | O9: gastos_produccion | P9: 1 | Q9: DISPOSICIÓN FINAL RESIDUOS LIQUIDOS | R9: 1 | S9: -50700270 | T9: 1 | U9: APERTURADO POR EMPRESA
A10: 46111 | B10: WORMS 2 | C10: prod19 | D10: -47687159 | E10: AG- A | F10: 39.26 | G10: 850 | H10: TN | I10: MATERIA PRIMA | J10: OPEX | K10: VARIABLE | L10: DIRECTO | M10: 0 | N10: CC11 | O10: gastos_produccion | P10: 1 | Q10: EXPORTACION | R10: 1 | S10: -47687159 | T10: 39.26 | U10: APERTURADO POR EMPRESA
A11: 46111 | B11: WORMS 1 | C11: prod25 | D11: -45305016 | E11: AG- C | F11: 42.272 | G11: 750 | H11: TN | I11: MATERIA PRIMA | J11: OPEX | K11: VARIABLE | L11: DIRECTO | M11: 0 | N11: CC5 | O11: gastos_produccion | P11: 1 | Q11: REACTORES | R11: 1 | S11: -45305016 | T11: 42.272 | U11: APERTURADO POR EMPRESA
A12: 46111 | B12: LOGISTICA EXPORTACION | C12: FA-C 2-2026-3 | D12: -41270898 | E12: FOB | F12: 1038.915 | G12: 39725 | H12: TN | I12: LOGISTICA | J12: OPEX | K12: VARIABLE | L12: DIRECTO | M12: 0 | N12: CC11 | O12: gastos_produccion | P12: 1 | Q12: EXPORTACION | R12: 1 | S12: -41270898 | T12: 1038.915 | U12: APERTURADO POR EMPRESA
A13: 46085 | B13: Nation Limited S.A. | C13: FA-A 00001-00000285 | D13: -38586537 | E13: INVERSION Geomembrana Proy #6 | F13: 1 | G13: 31889700 | H13: UN | I13: INVERSION | J13: CAPEX | K13: VARIABLE | L13: DIRECTO | M13: 0 | N13: CC3 | O13: gastos_produccion | P13: 1 | Q13: DISPOSICIÓN FINAL RESIDUOS LIQUIDOS | R13: 1 | S13: -38586537 | T13: 1 | U13: APERTURADO POR EMPRESA
... A96: 46091 | B96: Telecom Argentina Sociedad Anonima | C96: FA-A 06364-09382912 | D96: -907182.26 | E96: SERVICIOS Telefonía móvil | F96: 1 | G96: 730426.5 | H96: UN | I96: SERVICIOS | J96: OPEX | K96: VARIABLE | L96: INDIRECTO | M96: 0 | N96: CC1 | O96: gastos_produccion | P96: 10 | Q96: BACHAS, CEREAL & POLVILLO, COMPOST & FERTILIZANTES, DISPOSICIÓN FINAL RESIDUOS LIQUIDOS, DISPOSICIÓN FINAL RESIDUOS SOLIDOS, EXPORTACION, NFU, PILETAS, REACTORES, TIERRAS FILTRANTES | R96: 1 | S96: -907182.26 | T96: 1 | U96: APERTURADO POR EMPRESA
A97: 46084 | B97: Estudio De Profesionales Sa | C97: FA-A 00002-00001547 | D97: -895400 | E97: HONORARIOS Estudio contable Servicios comunales | F97: 1 | G97: 740000 | H97: UN | I97: HONORARIOS | J97: OPEX | K97: FIJO | L97: INDIRECTO | M97: CC13 | N97: 0 | O97: gastos_produccion | P97: 0 | Q97: 0 | R97: 0.7 | S97: -626780 | T97: 0.7 | U97: APERTURADO POR EMPRESA
A98: 46084 | B98: Estudio De Profesionales Sa | C98: FA-A 00002-00001546 | D98: -895400 | E98: HONORARIOS Estudio contable | F98: 1 | G98: 740000 | H98: UN | I98: HONORARIOS | J98: OPEX | K98: FIJO | L98: INDIRECTO | M98: 0 | N98: CC1 | O98: gastos_produccion | P98: 10 | Q98: BACHAS, CEREAL & POLVILLO, COMPOST & FERTILIZANTES, DISPOSICIÓN FINAL RESIDUOS LIQUIDOS, DISPOSICIÓN FINAL RESIDUOS SOLIDOS, EXPORTACION, NFU, PILETAS, REACTORES, TIERRAS FILTRANTES | R98: 1 | S98: -895400 | T98: 1 | U98: APERTURADO POR EMPRESA
A99: 46112 | B99: RRHH WORMS (NUEVO) | C99: JESUS RODRIGO LOPEZ | D99: -894944.57 | E99: LOGISTICA | F99: 1 | G99: 894944.57 | H99: # RRHH | I99: PERSONAL | J99: OPEX | K99: FIJO | L99: DIRECTO | M99: 0 | N99: CC18 | O99: rrhh_nuevo | P99: 5 | Q99: DISPOSICION FINAL DE R. SOLIDOS, EXPORTACION, NFU, PILETAS, REACTORES | R99: 1 | S99: -894944.57 | T99: 1 | U99: APERTURADO POR EMPRESA
A100: 46112 | B100: RRHH WORMS (NUEVO) | C100: VAZQUEZ MATIAS EMANUEL | D100: -893215.88 | E100: PILETAS + BACHAS | F100: 1 | G100: 893215.88 | H100: # RRHH | I100: PERSONAL | J100: OPEX | K100: FIJO | L100: DIRECTO | M100: 0 | N100: CC21 | O100: rrhh_nuevo | P100: 2 | Q100: BACHAS, PILETAS | R100: 1 | S100: -893215.88 | T100: 1 | U100: APERTURADO POR EMPRESA
A101: 46112 | B101: RRHH WORMS (NUEVO) | C101: JUAN PABLO MORENO | D101: -892762.22 | E101: COMPOST & FERTILIZANTES + DISPOSICION FINAL DE R. SOLIDOS | F101: 1 | G101: 892762.22 | H101: # RRHH | I101: PERSONAL | J101: OPEX | K101: FIJO | L101: DIRECTO | M101: 0 | N101: CC24 | O101: rrhh_nuevo | P101: 2 | Q101: COMPOST Y FERTILIZANTES, DISPOSICION FINAL DE R. SOLIDOS | R101: 1 | S101: -892762.22 | T101: 1 | U101: APERTURADO POR EMPRESA
A102: 46112 | B102: RRHH WORMS (NUEVO) | C102: CAMILO RAFAEL BORDON | D102: -888429.56 | E102: REACTOR | F102: 1 | G102: 888429.56 | H102: # RRHH | I102: PERSONAL | J102: OPEX | K102: FIJO | L102: DIRECTO | M102: 0 | N102: CC5 | O102: rrhh_nuevo | P102: 1 | Q102: REACTORES | R102: 1 | S102: -888429.56 | T102: 1 | U102: APERTURADO POR EMPRESA
A103: 46112 | B103: RRHH WORMS (NUEVO) | C103: GERMAN CLAUDIO POLLACCHI | D103: -885658.49 | E103: VIGILANCIA | F103: 1 | G103: 885658.49 | H103: # RRHH | I103: PERSONAL | J103: OPEX | K103: FIJO | L103: INDIRECTO | M103: 0 | N103: CC29 | O103: rrhh_nuevo | P103: 10 | Q103: BACHAS, CEREAL Y POLVILLO, COMPOST Y FERTILIZANTES, DISPOSICION FINAL DE R. LIQUIDOS, DISPOSICION FINAL DE R. SOLIDOS, EXPORTACION, NFU, PILETAS, REACTORES, TIERRAS FILTRANTES | R103: 1 | S103: -885658.49 | T103: 1 | U103: APERTURADO POR EMPRESA
A104: 46112 | B104: RRHH WORMS (NUEVO) | C104: HECTOR JOAQUIN BAEZ | D104: -877797.38 | E104: TALLER MECANICO | F104: 1 | G104: 877797.38 | H104: # RRHH | I104: PERSONAL | J104: OPEX | K104: FIJO | L104: DIRECTO | M104: 0 | N104: CC23 | O104: rrhh_nuevo | P104: 10 | Q104: BACHAS, CEREAL Y POLVILLO, COMPOST Y FERTILIZANTES, DISPOSICION FINAL DE R. LIQUIDOS, DISPOSICION FINAL DE R. SOLIDOS, EXPORTACION, NFU, PILETAS, REACTORES, TIERRAS FILTRANTES | R104: 1 | S104: -877797.38 | T104: 1 | U104: APERTURADO POR EMPRESA
A105: 46112 | B105: RRHH WORMS (NUEVO) | C105: JOAQUIN ESTEBAN CECCHI | D105: -875549.35 | E105: PRODUCCION | F105: 1 | G105: 875549.35 | H105: # RRHH | I105: PERSONAL | J105: OPEX | K105: FIJO | L105: DIRECTO | M105: 0 | N105: CC28 | O105: rrhh_nuevo | P105: 10 | Q105: BACHAS, CEREAL & POLVILLO, COMPOST & FERTILIZANTES, DISPOSICIÓN FINAL RESIDUOS LIQUIDOS, DISPOSICIÓN FINAL RESIDUOS SOLIDOS, EXPORTACION, NFU, PILETAS, REACTORES, TIERRAS FILTRANTES | R105: 1 | S105: -875549.35 | T105: 1 | U105: APERTURADO POR EMPRESA
A106: 46112 | B106: RRHH WORMS (NUEVO) | C106: VALENTIN DE AVELENDA | D106: -874663.9 | E106: DISPOSICIÓN FINAL RESIDUOS LIQUIDOS + EXPORTACION | F106: 1 | G106: 874663.9 | H106: # RRHH | I106: PERSONAL | J106: OPEX | K106: FIJO | L106: DIRECTO | M106: 0 | N106: CC25 | O106: rrhh_nuevo | P106: 2 | Q106: DISPOSICION FINAL DE R. LIQUIDOS, EXPORTACION | R106: 1 | S106: -874663.9 | T106: 1 | U106: APERTURADO POR EMPRESA
A107: 46112 | B107: RRHH WORMS (NUEVO) | C107: NUÑEZ ALAN OSVALDO | D107: -871867.94 | E107: PILETAS + BACHAS | F107: 1 | G107: 871867.94 | H107: # RRHH | I107: PERSONAL | J107: OPEX | K107: FIJO | L107: DIRECTO | M107: 0 | N107: CC21 | O107: rrhh_nuevo | P107: 2 | Q107: BACHAS, PILETAS | R107: 1 | S107: -871867.94 | T107: 1 | U107: APERTURADO POR EMPRESA
A108: 46093 | B108: Comercial Uritorco S. R. L. (w) | C108: FA-A 00001-00009009 | D108: -871775.04 | E108: REPOSICION | F108: 1 | G108: 124786.25 | H108: UN | I108: REPOSICION | J108: OPEX | K108: VARIABLE | L108: INDIRECTO | M108: 0 | N108: CC1 | O108: gastos_produccion | P108: 10 | Q108: BACHAS, CEREAL & POLVILLO, COMPOST & FERTILIZANTES, DISPOSICIÓN FINAL RESIDUOS LIQUIDOS, DISPOSICIÓN FINAL RESIDUOS SOLIDOS, EXPORTACION, NFU, PILETAS, REACTORES, TIERRAS FILTRANTES | R108: 1 | S108: -871775.04 | T108: 1 | U108: APERTURADO POR EMPRESA
A109: 46112 | B109: RRHH WORMS (NUEVO) | C109: VANINA ELIZABETH LARREY | D109: -868719.75 | E109: PORTERIA | F109: 1 | G109: 868719.75 | H109: # RRHH | I109: PERSONAL | J109: OPEX | K109: FIJO | L109: DIRECTO | M109: 0 | N109: CC22 | O109: rrhh_nuevo | P109: 7 | Q109: BACHAS, COMPOST Y FERTILIZANTES, DISPOSICION FINAL DE R. LIQUIDOS, DISPOSICION FINAL DE R. SOLIDOS, EXPORTACION, NFU, REACTORES | R109: 1 | S109: -868719.75 | T109: 1 | U109: APERTURADO POR EMPRESA
... A235: 46111 | B235: WORMS 1 | C235: prod31 | D235: 0 | E235: BORRA AN | F235: 0 | G235: 500 | H235: TN | I235: MATERIA PRIMA | J235: OPEX | K235: VARIABLE | L235: DIRECTO | M235: 0 | N235: CC6 | O235: gastos_produccion | P235: 1 | Q235: BACHAS | R235: 1 | S235: 0 | T235: 0 | U235: APERTURADO POR EMPRESA
A236: 46111 | B236: WORMS 1 | C236: prod32 | D236: 0 | E236: ÁCIDO CITRICO | F236: 0 | G236: #NUM! | H236: KG | I236: INSUMOS | J236: OPEX | K236: VARIABLE | L236: DIRECTO | M236: 0 | N236: CC6 | O236: gastos_produccion | P236: 1 | Q236: BACHAS | R236: 1 | S236: 0 | T236: 0 | U236: APERTURADO POR EMPRESA
A237: 46111 | B237: WORMS 1 | C237: prod34 | D237: 0 | E237: BORRA A | F237: 20.48 | G237: #NUM! | H237: KG | I237: MATERIA PRIMA | J237: OPEX | K237: VARIABLE | L237: DIRECTO | M237: 0 | N237: CC6 | O237: gastos_produccion | P237: 1 | Q237: BACHAS | R237: 1 | S237: 0 | T237: 20.48 | U237: APERTURADO POR EMPRESA
A238: 46111 | B238: FCA | C238: FA-C 2-2026-3 | D238: 0 | E238: FCA | F238: 808.045 | G238: 0 | H238: TN | I238: LOGISTICA | J238: OPEX | K238: VARIABLE | L238: DIRECTO | M238: 0 | N238: CC11 | O238: gastos_produccion | P238: 1 | Q238: EXPORTACION | R238: 1 | S238: 0 | T238: 808.045 | U238: APERTURADO POR EMPRESA
A239: 46112 | B239: RRHH WORMS (NUEVO) | C239: BELTRAMO, ANDRES | D239: 0 | E239: DISPOSICIÓN FINAL RESIDUOS SOLIDOS | F239: 1 | G239: 0 | H239: # RRHH | I239: PERSONAL | J239: OPEX | K239: FIJO | L239: DIRECTO | M239: 0 | N239: CC2 | O239: rrhh_nuevo | P239: 1 | Q239: DISPOSICIÓN FINAL RESIDUOS SOLIDOS | R239: 1 | S239: 0 | T239: 1 | U239: APERTURADO POR EMPRESA
A240: 46112 | B240: RRHH WORMS (NUEVO) | C240: CENSABELLA, AMALIA | D240: 0 | E240: DISPOSICIÓN FINAL RESIDUOS LIQUIDOS | F240: 1 | G240: 0 | H240: # RRHH | I240: PERSONAL | J240: OPEX | K240: FIJO | L240: DIRECTO | M240: 0 | N240: CC3 | O240: rrhh_nuevo | P240: 1 | Q240: DISPOSICIÓN FINAL RESIDUOS LIQUIDOS | R240: 1 | S240: 0 | T240: 1 | U240: APERTURADO POR EMPRESA
A241: 46112 | B241: RRHH WORMS (NUEVO) | C241: CUETO, DANIELA | D241: 0 | E241: ADMINISTRACION | F241: 1 | G241: 0 | H241: # RRHH | I241: PERSONAL | J241: OPEX | K241: FIJO | L241: DIRECTO | M241: 0 | N241: CC15 | O241: rrhh_nuevo | P241: 10 | Q241: BACHAS, CEREAL Y POLVILLO, COMPOST Y FERTILIZANTES, DISPOSICION FINAL DE R. LIQUIDOS, DISPOSICION FINAL DE R. SOLIDOS, EXPORTACION, NFU, PILETAS, REACTORES, TIERRAS FILTRANTES | R241: 1 | S241: 0 | T241: 1 | U241: APERTURADO POR EMPRESA

Sheet bbdd_ape.p3
A1: Fecha de Factura/Recibo | B1: Nombre de la empresa a mostrar en la factura | C1: Número | D1: Total con signo | E1: Líneas de factura/Etiqueta | F1: Líneas de factura/Cantidad | G1: Líneas de factura/Precio unitario | H1: Líneas de factura/Unidad de medida | I1: Líneas de factura/Producto | J1: Concepto | K1: Tipo de Gasto 1 | L1: Tipo de Gasto 2 | M1: CCO EMPRESA | N1: CCO - SECTOR | O1: SECTOR_ODOO | P1: # SECTORES | Q1: LISTA_SECTORES | R1: Column1 | S1: Column2 | T1: Column3 | U1: Column4
A2: 46111 | B2: WORMS 2 | C2: prod17 | D2: -2.0810686e+09 | E2: AFE (S) | F2: 1541.07 | G2: 945 | H2: TN | I2: MATERIA PRIMA | J2: OPEX | K2: VARIABLE | L2: DIRECTO | M2: 0 | N2: CC11 | O2: gastos_produccion | P2: 1 | Q2: EXPORTACION | R2: 1 | S2: -2.0810686e+09 | T2: 1541.07 | U2: APERTURADO POR EMPRESA
A3: 46111 | B3: WORMS 2 | C3: prod15 | D3: -1.2849682e+08 | E3: AFE (G) | F3: 97.74 | G3: 920 | H3: TN | I3: MATERIA PRIMA | J3: OPEX | K3: VARIABLE | L3: DIRECTO | M3: 0 | N3: CC11 | O3: gastos_produccion | P3: 1 | Q3: EXPORTACION | R3: 1 | S3: -1.2849682e+08 | T3: 97.74 | U3: APERTURADO POR EMPRESA
A4: 46111 | B4: WORMS 2 | C4: prod23 | D4: -89426820 | E4: AG- C | F4: 83.44 | G4: 750 | H4: TN | I4: MATERIA PRIMA | J4: OPEX | K4: VARIABLE | L4: DIRECTO | M4: 0 | N4: CC11 | O4: gastos_produccion | P4: 1 | Q4: EXPORTACION | R4: 1 | S4: -89426820 | T4: 83.44 | U4: APERTURADO POR EMPRESA
A5: 46111 | B5: EDUARDO SEMINARA - DENIS LUQUE | C5: prod13 | D5: -87306127 | E5: GLICERINA CRUDA | F5: 169.711 | G5: 360 | H5: TN | I5: INSUMOS | J5: OPEX | K5: VARIABLE | L5: DIRECTO | M5: 0 | N5: CC5 | O5: gastos_produccion | P5: 1 | Q5: REACTORES | R5: 1 | S5: -87306127 | T5: 169.711 | U5: APERTURADO POR EMPRESA
A6: 46111 | B6: WORMS 2 | C6: prod29 | D6: -80532152 | E6: ARE- B | F6: 67.09 | G6: 840 | H6: TN | I6: MATERIA PRIMA | J6: OPEX | K6: VARIABLE | L6: DIRECTO | M6: 0 | N6: CC11 | O6: gastos_produccion | P6: 1 | Q6: EXPORTACION | R6: 1 | S6: -80532152 | T6: 67.09 | U6: APERTURADO POR EMPRESA
A7: 46111 | B7: WORMS 1 | C7: prod26 | D7: -79981130 | E7: AG-D | F7: 111.94 | G7: 500 | H7: TN | I7: MATERIA PRIMA | J7: OPEX | K7: VARIABLE | L7: DIRECTO | M7: 0 | N7: CC6 | O7: gastos_produccion | P7: 1 | Q7: BACHAS | R7: 1 | S7: -79981130 | T7: 111.94 | U7: APERTURADO POR EMPRESA
A8: 46100 | B8: Construcciones Industriales Y Portuarias S.A. | C8: FA-A 00003-00001298 | D8: -54208000 | E8: INVERSION Planta de efluentes | F8: 1 | G8: 44800000 | H8: UN | I8: INVERSION | J8: CAPEX | K8: VARIABLE | L8: INDIRECTO | M8: 0 | N8: CC3 | O8: gastos_produccion | P8: 1 | Q8: DISPOSICIÓN FINAL RESIDUOS LIQUIDOS | R8: 1 | S8: -54208000 | T8: 1 | U8: APERTURADO POR EMPRESA
A9: 46093 | B9: Construcciones Industriales Y Portuarias S.A. | C9: FA-A 00003-00001295 | D9: -50700270 | E9: INVERSION Planta de efluentes Actualizacion | F9: 1 | G9: 41901050 | H9: UN | I9: INVERSION | J9: CAPEX | K9: VARIABLE | L9: INDIRECTO | M9: 0 | N9: CC3 | O9: gastos_produccion | P9: 1 | Q9: DISPOSICIÓN FINAL RESIDUOS LIQUIDOS | R9: 1 | S9: -50700270 | T9: 1 | U9: APERTURADO POR EMPRESA
A10: 46111 | B10: WORMS 2 | C10: prod19 | D10: -47687159 | E10: AG- A | F10: 39.26 | G10: 850 | H10: TN | I10: MATERIA PRIMA | J10: OPEX | K10: VARIABLE | L10: DIRECTO | M10: 0 | N10: CC11 | O10: gastos_produccion | P10: 1 | Q10: EXPORTACION | R10: 1 | S10: -47687159 | T10: 39.26 | U10: APERTURADO POR EMPRESA
A11: 46111 | B11: WORMS 1 | C11: prod25 | D11: -45305016 | E11: AG- C | F11: 42.272 | G11: 750 | H11: TN | I11: MATERIA PRIMA | J11: OPEX | K11: VARIABLE | L11: DIRECTO | M11: 0 | N11: CC5 | O11: gastos_produccion | P11: 1 | Q11: REACTORES | R11: 1 | S11: -45305016 | T11: 42.272 | U11: APERTURADO POR EMPRESA
A12: 46111 | B12: LOGISTICA EXPORTACION | C12: FA-C 2-2026-3 | D12: -41270898 | E12: FOB | F12: 1038.915 | G12: 39725 | H12: TN | I12: LOGISTICA | J12: OPEX | K12: VARIABLE | L12: DIRECTO | M12: 0 | N12: CC11 | O12: gastos_produccion | P12: 1 | Q12: EXPORTACION | R12: 1 | S12: -41270898 | T12: 1038.915 | U12: APERTURADO POR EMPRESA
A13: 46085 | B13: Nation Limited S.A. | C13: FA-A 00001-00000285 | D13: -38586537 | E13: INVERSION Geomembrana Proy #6 | F13: 1 | G13: 31889700 | H13: UN | I13: INVERSION | J13: CAPEX | K13: VARIABLE | L13: DIRECTO | M13: 0 | N13: CC3 | O13: gastos_produccion | P13: 1 | Q13: DISPOSICIÓN FINAL RESIDUOS LIQUIDOS | R13: 1 | S13: -38586537 | T13: 1 | U13: APERTURADO POR EMPRESA
... A96: 46091 | B96: Telecom Argentina Sociedad Anonima | C96: FA-A 06364-09382912 | D96: -907182.26 | E96: SERVICIOS Telefonía móvil | F96: 1 | G96: 730426.5 | H96: UN | I96: SERVICIOS | J96: OPEX | K96: VARIABLE | L96: INDIRECTO | M96: 0 | N96: CC1 | O96: gastos_produccion | P96: 10 | Q96: BACHAS, CEREAL & POLVILLO, COMPOST & FERTILIZANTES, DISPOSICIÓN FINAL RESIDUOS LIQUIDOS, DISPOSICIÓN FINAL RESIDUOS SOLIDOS, EXPORTACION, NFU, PILETAS, REACTORES, TIERRAS FILTRANTES | R96: 1 | S96: -907182.26 | T96: 1 | U96: APERTURADO POR EMPRESA
A97: 46084 | B97: Estudio De Profesionales Sa | C97: FA-A 00002-00001547 | D97: -895400 | E97: HONORARIOS Estudio contable Servicios comunales | F97: 1 | G97: 740000 | H97: UN | I97: HONORARIOS | J97: OPEX | K97: FIJO | L97: INDIRECTO | M97: CC13 | N97: 0 | O97: gastos_produccion | P97: 0 | Q97: 0 | R97: 0.7 | S97: -626780 | T97: 0.7 | U97: APERTURADO POR EMPRESA
A98: 46084 | B98: Estudio De Profesionales Sa | C98: FA-A 00002-00001546 | D98: -895400 | E98: HONORARIOS Estudio contable | F98: 1 | G98: 740000 | H98: UN | I98: HONORARIOS | J98: OPEX | K98: FIJO | L98: INDIRECTO | M98: 0 | N98: CC1 | O98: gastos_produccion | P98: 10 | Q98: BACHAS, CEREAL & POLVILLO, COMPOST & FERTILIZANTES, DISPOSICIÓN FINAL RESIDUOS LIQUIDOS, DISPOSICIÓN FINAL RESIDUOS SOLIDOS, EXPORTACION, NFU, PILETAS, REACTORES, TIERRAS FILTRANTES | R98: 1 | S98: -895400 | T98: 1 | U98: APERTURADO POR EMPRESA
A99: 46112 | B99: RRHH WORMS (NUEVO) | C99: JESUS RODRIGO LOPEZ | D99: -894944.57 | E99: LOGISTICA | F99: 1 | G99: 894944.57 | H99: # RRHH | I99: PERSONAL | J99: OPEX | K99: FIJO | L99: DIRECTO | M99: 0 | N99: CC18 | O99: rrhh_nuevo | P99: 5 | Q99: DISPOSICION FINAL DE R. SOLIDOS, EXPORTACION, NFU, PILETAS, REACTORES | R99: 1 | S99: -894944.57 | T99: 1 | U99: APERTURADO POR EMPRESA
A100: 46112 | B100: RRHH WORMS (NUEVO) | C100: VAZQUEZ MATIAS EMANUEL | D100: -893215.88 | E100: PILETAS + BACHAS | F100: 1 | G100: 893215.88 | H100: # RRHH | I100: PERSONAL | J100: OPEX | K100: FIJO | L100: DIRECTO | M100: 0 | N100: CC21 | O100: rrhh_nuevo | P100: 2 | Q100: BACHAS, PILETAS | R100: 1 | S100: -893215.88 | T100: 1 | U100: APERTURADO POR EMPRESA
A101: 46112 | B101: RRHH WORMS (NUEVO) | C101: JUAN PABLO MORENO | D101: -892762.22 | E101: COMPOST & FERTILIZANTES + DISPOSICION FINAL DE R. SOLIDOS | F101: 1 | G101: 892762.22 | H101: # RRHH | I101: PERSONAL | J101: OPEX | K101: FIJO | L101: DIRECTO | M101: 0 | N101: CC24 | O101: rrhh_nuevo | P101: 2 | Q101: COMPOST Y FERTILIZANTES, DISPOSICION FINAL DE R. SOLIDOS | R101: 1 | S101: -892762.22 | T101: 1 | U101: APERTURADO POR EMPRESA
A102: 46112 | B102: RRHH WORMS (NUEVO) | C102: CAMILO RAFAEL BORDON | D102: -888429.56 | E102: REACTOR | F102: 1 | G102: 888429.56 | H102: # RRHH | I102: PERSONAL | J102: OPEX | K102: FIJO | L102: DIRECTO | M102: 0 | N102: CC5 | O102: rrhh_nuevo | P102: 1 | Q102: REACTORES | R102: 1 | S102: -888429.56 | T102: 1 | U102: APERTURADO POR EMPRESA
A103: 46112 | B103: RRHH WORMS (NUEVO) | C103: GERMAN CLAUDIO POLLACCHI | D103: -885658.49 | E103: VIGILANCIA | F103: 1 | G103: 885658.49 | H103: # RRHH | I103: PERSONAL | J103: OPEX | K103: FIJO | L103: INDIRECTO | M103: 0 | N103: CC29 | O103: rrhh_nuevo | P103: 10 | Q103: BACHAS, CEREAL Y POLVILLO, COMPOST Y FERTILIZANTES, DISPOSICION FINAL DE R. LIQUIDOS, DISPOSICION FINAL DE R. SOLIDOS, EXPORTACION, NFU, PILETAS, REACTORES, TIERRAS FILTRANTES | R103: 1 | S103: -885658.49 | T103: 1 | U103: APERTURADO POR EMPRESA
A104: 46112 | B104: RRHH WORMS (NUEVO) | C104: HECTOR JOAQUIN BAEZ | D104: -877797.38 | E104: TALLER MECANICO | F104: 1 | G104: 877797.38 | H104: # RRHH | I104: PERSONAL | J104: OPEX | K104: FIJO | L104: DIRECTO | M104: 0 | N104: CC23 | O104: rrhh_nuevo | P104: 10 | Q104: BACHAS, CEREAL Y POLVILLO, COMPOST Y FERTILIZANTES, DISPOSICION FINAL DE R. LIQUIDOS, DISPOSICION FINAL DE R. SOLIDOS, EXPORTACION, NFU, PILETAS, REACTORES, TIERRAS FILTRANTES | R104: 1 | S104: -877797.38 | T104: 1 | U104: APERTURADO POR EMPRESA
A105: 46112 | B105: RRHH WORMS (NUEVO) | C105: JOAQUIN ESTEBAN CECCHI | D105: -875549.35 | E105: PRODUCCION | F105: 1 | G105: 875549.35 | H105: # RRHH | I105: PERSONAL | J105: OPEX | K105: FIJO | L105: DIRECTO | M105: 0 | N105: CC28 | O105: rrhh_nuevo | P105: 10 | Q105: BACHAS, CEREAL & POLVILLO, COMPOST & FERTILIZANTES, DISPOSICIÓN FINAL RESIDUOS LIQUIDOS, DISPOSICIÓN FINAL RESIDUOS SOLIDOS, EXPORTACION, NFU, PILETAS, REACTORES, TIERRAS FILTRANTES | R105: 1 | S105: -875549.35 | T105: 1 | U105: APERTURADO POR EMPRESA
A106: 46112 | B106: RRHH WORMS (NUEVO) | C106: VALENTIN DE AVELENDA | D106: -874663.9 | E106: DISPOSICIÓN FINAL RESIDUOS LIQUIDOS + EXPORTACION | F106: 1 | G106: 874663.9 | H106: # RRHH | I106: PERSONAL | J106: OPEX | K106: FIJO | L106: DIRECTO | M106: 0 | N106: CC25 | O106: rrhh_nuevo | P106: 2 | Q106: DISPOSICION FINAL DE R. LIQUIDOS, EXPORTACION | R106: 1 | S106: -874663.9 | T106: 1 | U106: APERTURADO POR EMPRESA
A107: 46112 | B107: RRHH WORMS (NUEVO) | C107: NUÑEZ ALAN OSVALDO | D107: -871867.94 | E107: PILETAS + BACHAS | F107: 1 | G107: 871867.94 | H107: # RRHH | I107: PERSONAL | J107: OPEX | K107: FIJO | L107: DIRECTO | M107: 0 | N107: CC21 | O107: rrhh_nuevo | P107: 2 | Q107: BACHAS, PILETAS | R107: 1 | S107: -871867.94 | T107: 1 | U107: APERTURADO POR EMPRESA
A108: 46093 | B108: Comercial Uritorco S. R. L. (w) | C108: FA-A 00001-00009009 | D108: -871775.04 | E108: REPOSICION | F108: 1 | G108: 124786.25 | H108: UN | I108: REPOSICION | J108: OPEX | K108: VARIABLE | L108: INDIRECTO | M108: 0 | N108: CC1 | O108: gastos_produccion | P108: 10 | Q108: BACHAS, CEREAL & POLVILLO, COMPOST & FERTILIZANTES, DISPOSICIÓN FINAL RESIDUOS LIQUIDOS, DISPOSICIÓN FINAL RESIDUOS SOLIDOS, EXPORTACION, NFU, PILETAS, REACTORES, TIERRAS FILTRANTES | R108: 1 | S108: -871775.04 | T108: 1 | U108: APERTURADO POR EMPRESA
A109: 46112 | B109: RRHH WORMS (NUEVO) | C109: VANINA ELIZABETH LARREY | D109: -868719.75 | E109: PORTERIA | F109: 1 | G109: 868719.75 | H109: # RRHH | I109: PERSONAL | J109: OPEX | K109: FIJO | L109: DIRECTO | M109: 0 | N109: CC22 | O109: rrhh_nuevo | P109: 7 | Q109: BACHAS, COMPOST Y FERTILIZANTES, DISPOSICION FINAL DE R. LIQUIDOS, DISPOSICION FINAL DE R. SOLIDOS, EXPORTACION, NFU, REACTORES | R109: 1 | S109: -868719.75 | T109: 1 | U109: APERTURADO POR EMPRESA
... A235: 46111 | B235: WORMS 1 | C235: prod31 | D235: 0 | E235: BORRA AN | F235: 0 | G235: 500 | H235: TN | I235: MATERIA PRIMA | J235: OPEX | K235: VARIABLE | L235: DIRECTO | M235: 0 | N235: CC6 | O235: gastos_produccion | P235: 1 | Q235: BACHAS | R235: 1 | S235: 0 | T235: 0 | U235: APERTURADO POR EMPRESA
A236: 46111 | B236: WORMS 1 | C236: prod32 | D236: 0 | E236: ÁCIDO CITRICO | F236: 0 | G236: #NUM! | H236: KG | I236: INSUMOS | J236: OPEX | K236: VARIABLE | L236: DIRECTO | M236: 0 | N236: CC6 | O236: gastos_produccion | P236: 1 | Q236: BACHAS | R236: 1 | S236: 0 | T236: 0 | U236: APERTURADO POR EMPRESA
A237: 46111 | B237: WORMS 1 | C237: prod34 | D237: 0 | E237: BORRA A | F237: 20.48 | G237: #NUM! | H237: KG | I237: MATERIA PRIMA | J237: OPEX | K237: VARIABLE | L237: DIRECTO | M237: 0 | N237: CC6 | O237: gastos_produccion | P237: 1 | Q237: BACHAS | R237: 1 | S237: 0 | T237: 20.48 | U237: APERTURADO POR EMPRESA
A238: 46111 | B238: FCA | C238: FA-C 2-2026-3 | D238: 0 | E238: FCA | F238: 808.045 | G238: 0 | H238: TN | I238: LOGISTICA | J238: OPEX | K238: VARIABLE | L238: DIRECTO | M238: 0 | N238: CC11 | O238: gastos_produccion | P238: 1 | Q238: EXPORTACION | R238: 1 | S238: 0 | T238: 808.045 | U238: APERTURADO POR EMPRESA
A239: 46112 | B239: RRHH WORMS (NUEVO) | C239: BELTRAMO, ANDRES | D239: 0 | E239: DISPOSICIÓN FINAL RESIDUOS SOLIDOS | F239: 1 | G239: 0 | H239: # RRHH | I239: PERSONAL | J239: OPEX | K239: FIJO | L239: DIRECTO | M239: 0 | N239: CC2 | O239: rrhh_nuevo | P239: 1 | Q239: DISPOSICIÓN FINAL RESIDUOS SOLIDOS | R239: 1 | S239: 0 | T239: 1 | U239: APERTURADO POR EMPRESA
A240: 46112 | B240: RRHH WORMS (NUEVO) | C240: CENSABELLA, AMALIA | D240: 0 | E240: DISPOSICIÓN FINAL RESIDUOS LIQUIDOS | F240: 1 | G240: 0 | H240: # RRHH | I240: PERSONAL | J240: OPEX | K240: FIJO | L240: DIRECTO | M240: 0 | N240: CC3 | O240: rrhh_nuevo | P240: 1 | Q240: DISPOSICIÓN FINAL RESIDUOS LIQUIDOS | R240: 1 | S240: 0 | T240: 1 | U240: APERTURADO POR EMPRESA
A241: 46112 | B241: RRHH WORMS (NUEVO) | C241: CUETO, DANIELA | D241: 0 | E241: ADMINISTRACION | F241: 1 | G241: 0 | H241: # RRHH | I241: PERSONAL | J241: OPEX | K241: FIJO | L241: DIRECTO | M241: 0 | N241: CC15 | O241: rrhh_nuevo | P241: 10 | Q241: BACHAS, CEREAL Y POLVILLO, COMPOST Y FERTILIZANTES, DISPOSICION FINAL DE R. LIQUIDOS, DISPOSICION FINAL DE R. SOLIDOS, EXPORTACION, NFU, PILETAS, REACTORES, TIERRAS FILTRANTES | R241: 1 | S241: 0 | T241: 1 | U241: APERTURADO POR EMPRESA

Sheet cco_bbdd_asignado.p4 
A1: {=_xlfn._xlws.PY(1,0,bbdd2[#All])} -> 0 | B1: 1 | C1: 2 | D1: 3 | E1: 4 | F1: 5 | G1: 6 | H1: 7 | I1: 8 | J1: 9 | K1: 10 | L1: 11 | M1: 12 | N1: 13 | O1: 14 | P1: 15 | Q1: 16 | R1: 17 | S1: 18 | T1: 19 | U1: 20 | V1: SECTOR APERTURADO
A2: Fecha de Factura/Recibo | B2: Nombre de la empresa a mostrar en la factura | C2: Número | D2: Total con signo | E2: Líneas de factura/Etiqueta | F2: Líneas de factura/Cantidad | G2: Líneas de factura/Precio unitario | H2: Líneas de factura/Unidad de medida | I2: Líneas de factura/Producto | J2: Concepto | K2: Tipo de Gasto 1 | L2: Tipo de Gasto 2 | M2: CCO EMPRESA | N2: CCO - SECTOR | O2: SECTOR_ODOO | P2: # SECTORES | Q2: LISTA_SECTORES | R2: Column1 | S2: Column2 | T2: Column3 | U2: Column4 | V2: LISTA_SECTORES
A3: 46111 | B3: WORMS 2 | C3: prod17 | D3: -2.0810686e+09 | E3: AFE (S) | F3: 1541.07 | G3: 945 | H3: TN | I3: MATERIA PRIMA | J3: OPEX | K3: VARIABLE | L3: DIRECTO | M3: 0 | N3: CC11 | O3: gastos_produccion | P3: 1 | Q3: EXPORTACION | R3: 1 | S3: -2.0810686e+09 | T3: 1541.07 | U3: APERTURADO POR EMPRESA | V3: EXPORTACION
A4: 46111 | B4: WORMS 2 | C4: prod15 | D4: -1.2849682e+08 | E4: AFE (G) | F4: 97.74 | G4: 920 | H4: TN | I4: MATERIA PRIMA | J4: OPEX | K4: VARIABLE | L4: DIRECTO | M4: 0 | N4: CC11 | O4: gastos_produccion | P4: 1 | Q4: EXPORTACION | R4: 1 | S4: -1.2849682e+08 | T4: 97.74 | U4: APERTURADO POR EMPRESA | V4: EXPORTACION
A5: 46111 | B5: WORMS 2 | C5: prod23 | D5: -89426820 | E5: AG- C | F5: 83.44 | G5: 750 | H5: TN | I5: MATERIA PRIMA | J5: OPEX | K5: VARIABLE | L5: DIRECTO | M5: 0 | N5: CC11 | O5: gastos_produccion | P5: 1 | Q5: EXPORTACION | R5: 1 | S5: -89426820 | T5: 83.44 | U5: APERTURADO POR EMPRESA | V5: EXPORTACION
A6: 46111 | B6: EDUARDO SEMINARA - DENIS LUQUE | C6: prod13 | D6: -87306127 | E6: GLICERINA CRUDA | F6: 169.711 | G6: 360 | H6: TN | I6: INSUMOS | J6: OPEX | K6: VARIABLE | L6: DIRECTO | M6: 0 | N6: CC5 | O6: gastos_produccion | P6: 1 | Q6: REACTORES | R6: 1 | S6: -87306127 | T6: 169.711 | U6: APERTURADO POR EMPRESA | V6: REACTORES
A7: 46111 | B7: WORMS 2 | C7: prod29 | D7: -80532152 | E7: ARE- B | F7: 67.09 | G7: 840 | H7: TN | I7: MATERIA PRIMA | J7: OPEX | K7: VARIABLE | L7: DIRECTO | M7: 0 | N7: CC11 | O7: gastos_produccion | P7: 1 | Q7: EXPORTACION | R7: 1 | S7: -80532152 | T7: 67.09 | U7: APERTURADO POR EMPRESA | V7: EXPORTACION
A8: 46111 | B8: WORMS 1 | C8: prod26 | D8: -79981130 | E8: AG-D | F8: 111.94 | G8: 500 | H8: TN | I8: MATERIA PRIMA | J8: OPEX | K8: VARIABLE | L8: DIRECTO | M8: 0 | N8: CC6 | O8: gastos_produccion | P8: 1 | Q8: BACHAS | R8: 1 | S8: -79981130 | T8: 111.94 | U8: APERTURADO POR EMPRESA | V8: BACHAS
A9: 46100 | B9: Construcciones Industriales Y Portuarias S.A. | C9: FA-A 00003-00001298 | D9: -54208000 | E9: INVERSION Planta de efluentes | F9: 1 | G9: 44800000 | H9: UN | I9: INVERSION | J9: CAPEX | K9: VARIABLE | L9: INDIRECTO | M9: 0 | N9: CC3 | O9: gastos_produccion | P9: 1 | Q9: DISPOSICIÓN FINAL RESIDUOS LIQUIDOS | R9: 1 | S9: -54208000 | T9: 1 | U9: APERTURADO POR EMPRESA | V9: DISPOSICIÓN FINAL RESIDUOS LIQUIDOS
A10: 46093 | B10: Construcciones Industriales Y Portuarias S.A. | C10: FA-A 00003-00001295 | D10: -50700270 | E10: INVERSION Planta de efluentes Actualizacion | F10: 1 | G10: 41901050 | H10: UN | I10: INVERSION | J10: CAPEX | K10: VARIABLE | L10: INDIRECTO | M10: 0 | N10: CC3 | O10: gastos_produccion | P10: 1 | Q10: DISPOSICIÓN FINAL RESIDUOS LIQUIDOS | R10: 1 | S10: -50700270 | T10: 1 | U10: APERTURADO POR EMPRESA | V10: DISPOSICIÓN FINAL RESIDUOS LIQUIDOS
A11: 46111 | B11: WORMS 2 | C11: prod19 | D11: -47687159 | E11: AG- A | F11: 39.26 | G11: 850 | H11: TN | I11: MATERIA PRIMA | J11: OPEX | K11: VARIABLE | L11: DIRECTO | M11: 0 | N11: CC11 | O11: gastos_produccion | P11: 1 | Q11: EXPORTACION | R11: 1 | S11: -47687159 | T11: 39.26 | U11: APERTURADO POR EMPRESA | V11: EXPORTACION
A12: 46111 | B12: WORMS 1 | C12: prod25 | D12: -45305016 | E12: AG- C | F12: 42.272 | G12: 750 | H12: TN | I12: MATERIA PRIMA | J12: OPEX | K12: VARIABLE | L12: DIRECTO | M12: 0 | N12: CC5 | O12: gastos_produccion | P12: 1 | Q12: REACTORES | R12: 1 | S12: -45305016 | T12: 42.272 | U12: APERTURADO POR EMPRESA | V12: REACTORES
A13: 46111 | B13: LOGISTICA EXPORTACION | C13: FA-C 2-2026-3 | D13: -41270898 | E13: FOB | F13: 1038.915 | G13: 39725 | H13: TN | I13: LOGISTICA | J13: OPEX | K13: VARIABLE | L13: DIRECTO | M13: 0 | N13: CC11 | O13: gastos_produccion | P13: 1 | Q13: EXPORTACION | R13: 1 | S13: -41270898 | T13: 1038.915 | U13: APERTURADO POR EMPRESA | V13: EXPORTACION
A14: 46085 | B14: Nation Limited S.A. | C14: FA-A 00001-00000285 | D14: -38586537 | E14: INVERSION Geomembrana Proy #6 | F14: 1 | G14: 31889700 | H14: UN | I14: INVERSION | J14: CAPEX | K14: VARIABLE | L14: DIRECTO | M14: 0 | N14: CC3 | O14: gastos_produccion | P14: 1 | Q14: DISPOSICIÓN FINAL RESIDUOS LIQUIDOS | R14: 1 | S14: -38586537 | T14: 1 | U14: APERTURADO POR EMPRESA | V14: DISPOSICIÓN FINAL RESIDUOS LIQUIDOS
... A495: 46091 | B495: Telecom Argentina Sociedad Anonima | C495: FA-A 06364-09382912 | D495: -907182.26 | E495: SERVICIOS Telefonía móvil | F495: 1 | G495: 730426.5 | H495: UN | I495: SERVICIOS | J495: OPEX | K495: VARIABLE | L495: INDIRECTO | M495: 0 | N495: CC1 | O495: gastos_produccion | P495: 10 | Q495: BACHAS, CEREAL & POLVILLO, COMPOST & FERTILIZANTES, DISPOSICIÓN FINAL RESIDUOS LIQUIDOS, DISPOSICIÓN FINAL RESIDUOS SOLIDOS, EXPORTACION, NFU, PILETAS, REACTORES, TIERRAS FILTRANTES | R495: 1 | S495: -907182.26 | T495: 1 | U495: APERTURADO POR EMPRESA | V495: TIERRAS FILTRANTES
A496: 46084 | B496: Estudio De Profesionales Sa | C496: FA-A 00002-00001547 | D496: -895400 | E496: HONORARIOS Estudio contable Servicios comunales | F496: 1 | G496: 740000 | H496: UN | I496: HONORARIOS | J496: OPEX | K496: FIJO | L496: INDIRECTO | M496: CC13 | N496: 0 | O496: gastos_produccion | P496: 0 | Q496: 0 | R496: 0.7 | S496: -626780 | T496: 0.7 | U496: APERTURADO POR EMPRESA | V496: 0
A497: 46084 | B497: Estudio De Profesionales Sa | C497: FA-A 00002-00001546 | D497: -895400 | E497: HONORARIOS Estudio contable | F497: 1 | G497: 740000 | H497: UN | I497: HONORARIOS | J497: OPEX | K497: FIJO | L497: INDIRECTO | M497: 0 | N497: CC1 | O497: gastos_produccion | P497: 10 | Q497: BACHAS, CEREAL & POLVILLO, COMPOST & FERTILIZANTES, DISPOSICIÓN FINAL RESIDUOS LIQUIDOS, DISPOSICIÓN FINAL RESIDUOS SOLIDOS, EXPORTACION, NFU, PILETAS, REACTORES, TIERRAS FILTRANTES | R497: 1 | S497: -895400 | T497: 1 | U497: APERTURADO POR EMPRESA | V497: BACHAS
A498: 46084 | B498: Estudio De Profesionales Sa | C498: FA-A 00002-00001546 | D498: -895400 | E498: HONORARIOS Estudio contable | F498: 1 | G498: 740000 | H498: UN | I498: HONORARIOS | J498: OPEX | K498: FIJO | L498: INDIRECTO | M498: 0 | N498: CC1 | O498: gastos_produccion | P498: 10 | Q498: BACHAS, CEREAL & POLVILLO, COMPOST & FERTILIZANTES, DISPOSICIÓN FINAL RESIDUOS LIQUIDOS, DISPOSICIÓN FINAL RESIDUOS SOLIDOS, EXPORTACION, NFU, PILETAS, REACTORES, TIERRAS FILTRANTES | R498: 1 | S498: -895400 | T498: 1 | U498: APERTURADO POR EMPRESA | V498: CEREAL & POLVILLO
A499: 46084 | B499: Estudio De Profesionales Sa | C499: FA-A 00002-00001546 | D499: -895400 | E499: HONORARIOS Estudio contable | F499: 1 | G499: 740000 | H499: UN | I499: HONORARIOS | J499: OPEX | K499: FIJO | L499: INDIRECTO | M499: 0 | N499: CC1 | O499: gastos_produccion | P499: 10 | Q499: BACHAS, CEREAL & POLVILLO, COMPOST & FERTILIZANTES, DISPOSICIÓN FINAL RESIDUOS LIQUIDOS, DISPOSICIÓN FINAL RESIDUOS SOLIDOS, EXPORTACION, NFU, PILETAS, REACTORES, TIERRAS FILTRANTES | R499: 1 | S499: -895400 | T499: 1 | U499: APERTURADO POR EMPRESA | V499: COMPOST & FERTILIZANTES
A500: 46084 | B500: Estudio De Profesionales Sa | C500: FA-A 00002-00001546 | D500: -895400 | E500: HONORARIOS Estudio contable | F500: 1 | G500: 740000 | H500: UN | I500: HONORARIOS | J500: OPEX | K500: FIJO | L500: INDIRECTO | M500: 0 | N500: CC1 | O500: gastos_produccion | P500: 10 | Q500: BACHAS, CEREAL & POLVILLO, COMPOST & FERTILIZANTES, DISPOSICIÓN FINAL RESIDUOS LIQUIDOS, DISPOSICIÓN FINAL RESIDUOS SOLIDOS, EXPORTACION, NFU, PILETAS, REACTORES, TIERRAS FILTRANTES | R500: 1 | S500: -895400 | T500: 1 | U500: APERTURADO POR EMPRESA | V500: DISPOSICIÓN FINAL RESIDUOS LIQUIDOS
A501: 46084 | B501: Estudio De Profesionales Sa | C501: FA-A 00002-00001546 | D501: -895400 | E501: HONORARIOS Estudio contable | F501: 1 | G501: 740000 | H501: UN | I501: HONORARIOS | J501: OPEX | K501: FIJO | L501: INDIRECTO | M501: 0 | N501: CC1 | O501: gastos_produccion | P501: 10 | Q501: BACHAS, CEREAL & POLVILLO, COMPOST & FERTILIZANTES, DISPOSICIÓN FINAL RESIDUOS LIQUIDOS, DISPOSICIÓN FINAL RESIDUOS SOLIDOS, EXPORTACION, NFU, PILETAS, REACTORES, TIERRAS FILTRANTES | R501: 1 | S501: -895400 | T501: 1 | U501: APERTURADO POR EMPRESA | V501: DISPOSICIÓN FINAL RESIDUOS SOLIDOS
A502: 46084 | B502: Estudio De Profesionales Sa | C502: FA-A 00002-00001546 | D502: -895400 | E502: HONORARIOS Estudio contable | F502: 1 | G502: 740000 | H502: UN | I502: HONORARIOS | J502: OPEX | K502: FIJO | L502: INDIRECTO | M502: 0 | N502: CC1 | O502: gastos_produccion | P502: 10 | Q502: BACHAS, CEREAL & POLVILLO, COMPOST & FERTILIZANTES, DISPOSICIÓN FINAL RESIDUOS LIQUIDOS, DISPOSICIÓN FINAL RESIDUOS SOLIDOS, EXPORTACION, NFU, PILETAS, REACTORES, TIERRAS FILTRANTES | R502: 1 | S502: -895400 | T502: 1 | U502: APERTURADO POR EMPRESA | V502: EXPORTACION
A503: 46084 | B503: Estudio De Profesionales Sa | C503: FA-A 00002-00001546 | D503: -895400 | E503: HONORARIOS Estudio contable | F503: 1 | G503: 740000 | H503: UN | I503: HONORARIOS | J503: OPEX | K503: FIJO | L503: INDIRECTO | M503: 0 | N503: CC1 | O503: gastos_produccion | P503: 10 | Q503: BACHAS, CEREAL & POLVILLO, COMPOST & FERTILIZANTES, DISPOSICIÓN FINAL RESIDUOS LIQUIDOS, DISPOSICIÓN FINAL RESIDUOS SOLIDOS, EXPORTACION, NFU, PILETAS, REACTORES, TIERRAS FILTRANTES | R503: 1 | S503: -895400 | T503: 1 | U503: APERTURADO POR EMPRESA | V503: NFU
A504: 46084 | B504: Estudio De Profesionales Sa | C504: FA-A 00002-00001546 | D504: -895400 | E504: HONORARIOS Estudio contable | F504: 1 | G504: 740000 | H504: UN | I504: HONORARIOS | J504: OPEX | K504: FIJO | L504: INDIRECTO | M504: 0 | N504: CC1 | O504: gastos_produccion | P504: 10 | Q504: BACHAS, CEREAL & POLVILLO, COMPOST & FERTILIZANTES, DISPOSICIÓN FINAL RESIDUOS LIQUIDOS, DISPOSICIÓN FINAL RESIDUOS SOLIDOS, EXPORTACION, NFU, PILETAS, REACTORES, TIERRAS FILTRANTES | R504: 1 | S504: -895400 | T504: 1 | U504: APERTURADO POR EMPRESA | V504: PILETAS
A505: 46084 | B505: Estudio De Profesionales Sa | C505: FA-A 00002-00001546 | D505: -895400 | E505: HONORARIOS Estudio contable | F505: 1 | G505: 740000 | H505: UN | I505: HONORARIOS | J505: OPEX | K505: FIJO | L505: INDIRECTO | M505: 0 | N505: CC1 | O505: gastos_produccion | P505: 10 | Q505: BACHAS, CEREAL & POLVILLO, COMPOST & FERTILIZANTES, DISPOSICIÓN FINAL RESIDUOS LIQUIDOS, DISPOSICIÓN FINAL RESIDUOS SOLIDOS, EXPORTACION, NFU, PILETAS, REACTORES, TIERRAS FILTRANTES | R505: 1 | S505: -895400 | T505: 1 | U505: APERTURADO POR EMPRESA | V505: REACTORES
A506: 46084 | B506: Estudio De Profesionales Sa | C506: FA-A 00002-00001546 | D506: -895400 | E506: HONORARIOS Estudio contable | F506: 1 | G506: 740000 | H506: UN | I506: HONORARIOS | J506: OPEX | K506: FIJO | L506: INDIRECTO | M506: 0 | N506: CC1 | O506: gastos_produccion | P506: 10 | Q506: BACHAS, CEREAL & POLVILLO, COMPOST & FERTILIZANTES, DISPOSICIÓN FINAL RESIDUOS LIQUIDOS, DISPOSICIÓN FINAL RESIDUOS SOLIDOS, EXPORTACION, NFU, PILETAS, REACTORES, TIERRAS FILTRANTES | R506: 1 | S506: -895400 | T506: 1 | U506: APERTURADO POR EMPRESA | V506: TIERRAS FILTRANTES
A507: 46112 | B507: RRHH WORMS (NUEVO) | C507: JESUS RODRIGO LOPEZ | D507: -894944.57 | E507: LOGISTICA | F507: 1 | G507: 894944.57 | H507: # RRHH | I507: PERSONAL | J507: OPEX | K507: FIJO | L507: DIRECTO | M507: 0 | N507: CC18 | O507: rrhh_nuevo | P507: 5 | Q507: DISPOSICION FINAL DE R. SOLIDOS, EXPORTACION, NFU, PILETAS, REACTORES | R507: 1 | S507: -894944.57 | T507: 1 | U507: APERTURADO POR EMPRESA | V507: DISPOSICION FINAL DE R. SOLIDOS
A508: 46112 | B508: RRHH WORMS (NUEVO) | C508: JESUS RODRIGO LOPEZ | D508: -894944.57 | E508: LOGISTICA | F508: 1 | G508: 894944.57 | H508: # RRHH | I508: PERSONAL | J508: OPEX | K508: FIJO | L508: DIRECTO | M508: 0 | N508: CC18 | O508: rrhh_nuevo | P508: 5 | Q508: DISPOSICION FINAL DE R. SOLIDOS, EXPORTACION, NFU, PILETAS, REACTORES | R508: 1 | S508: -894944.57 | T508: 1 | U508: APERTURADO POR EMPRESA | V508: EXPORTACION
... A1278: 46111 | B1278: WORMS 1 | C1278: prod31 | D1278: 0 | E1278: BORRA AN | F1278: 0 | G1278: 500 | H1278: TN | I1278: MATERIA PRIMA | J1278: OPEX | K1278: VARIABLE | L1278: DIRECTO | M1278: 0 | N1278: CC6 | O1278: gastos_produccion | P1278: 1 | Q1278: BACHAS | R1278: 1 | S1278: 0 | T1278: 0 | U1278: APERTURADO POR EMPRESA | V1278: BACHAS
A1279: 46111 | B1279: WORMS 1 | C1279: prod32 | D1279: 0 | E1279: ÁCIDO CITRICO | F1279: 0 | G1279: #NUM! | H1279: KG | I1279: INSUMOS | J1279: OPEX | K1279: VARIABLE | L1279: DIRECTO | M1279: 0 | N1279: CC6 | O1279: gastos_produccion | P1279: 1 | Q1279: BACHAS | R1279: 1 | S1279: 0 | T1279: 0 | U1279: APERTURADO POR EMPRESA | V1279: BACHAS
A1280: 46111 | B1280: WORMS 1 | C1280: prod34 | D1280: 0 | E1280: BORRA A | F1280: 20.48 | G1280: #NUM! | H1280: KG | I1280: MATERIA PRIMA | J1280: OPEX | K1280: VARIABLE | L1280: DIRECTO | M1280: 0 | N1280: CC6 | O1280: gastos_produccion | P1280: 1 | Q1280: BACHAS | R1280: 1 | S1280: 0 | T1280: 20.48 | U1280: APERTURADO POR EMPRESA | V1280: BACHAS
A1281: 46111 | B1281: FCA | C1281: FA-C 2-2026-3 | D1281: 0 | E1281: FCA | F1281: 808.045 | G1281: 0 | H1281: TN | I1281: LOGISTICA | J1281: OPEX | K1281: VARIABLE | L1281: DIRECTO | M1281: 0 | N1281: CC11 | O1281: gastos_produccion | P1281: 1 | Q1281: EXPORTACION | R1281: 1 | S1281: 0 | T1281: 808.045 | U1281: APERTURADO POR EMPRESA | V1281: EXPORTACION
A1282: 46112 | B1282: RRHH WORMS (NUEVO) | C1282: BELTRAMO, ANDRES | D1282: 0 | E1282: DISPOSICIÓN FINAL RESIDUOS SOLIDOS | F1282: 1 | G1282: 0 | H1282: # RRHH | I1282: PERSONAL | J1282: OPEX | K1282: FIJO | L1282: DIRECTO | M1282: 0 | N1282: CC2 | O1282: rrhh_nuevo | P1282: 1 | Q1282: DISPOSICIÓN FINAL RESIDUOS SOLIDOS | R1282: 1 | S1282: 0 | T1282: 1 | U1282: APERTURADO POR EMPRESA | V1282: DISPOSICIÓN FINAL RESIDUOS SOLIDOS
A1283: 46112 | B1283: RRHH WORMS (NUEVO) | C1283: CENSABELLA, AMALIA | D1283: 0 | E1283: DISPOSICIÓN FINAL RESIDUOS LIQUIDOS | F1283: 1 | G1283: 0 | H1283: # RRHH | I1283: PERSONAL | J1283: OPEX | K1283: FIJO | L1283: DIRECTO | M1283: 0 | N1283: CC3 | O1283: rrhh_nuevo | P1283: 1 | Q1283: DISPOSICIÓN FINAL RESIDUOS LIQUIDOS | R1283: 1 | S1283: 0 | T1283: 1 | U1283: APERTURADO POR EMPRESA | V1283: DISPOSICIÓN FINAL RESIDUOS LIQUIDOS
A1284: 46112 | B1284: RRHH WORMS (NUEVO) | C1284: CUETO, DANIELA | D1284: 0 | E1284: ADMINISTRACION | F1284: 1 | G1284: 0 | H1284: # RRHH | I1284: PERSONAL | J1284: OPEX | K1284: FIJO | L1284: DIRECTO | M1284: 0 | N1284: CC15 | O1284: rrhh_nuevo | P1284: 10 | Q1284: BACHAS, CEREAL Y POLVILLO, COMPOST Y FERTILIZANTES, DISPOSICION FINAL DE R. LIQUIDOS, DISPOSICION FINAL DE R. SOLIDOS, EXPORTACION, NFU, PILETAS, REACTORES, TIERRAS FILTRANTES | R1284: 1 | S1284: 0 | T1284: 1 | U1284: APERTURADO POR EMPRESA | V1284: BACHAS
A1285: 46112 | B1285: RRHH WORMS (NUEVO) | C1285: CUETO, DANIELA | D1285: 0 | E1285: ADMINISTRACION | F1285: 1 | G1285: 0 | H1285: # RRHH | I1285: PERSONAL | J1285: OPEX | K1285: FIJO | L1285: DIRECTO | M1285: 0 | N1285: CC15 | O1285: rrhh_nuevo | P1285: 10 | Q1285: BACHAS, CEREAL Y POLVILLO, COMPOST Y FERTILIZANTES, DISPOSICION FINAL DE R. LIQUIDOS, DISPOSICION FINAL DE R. SOLIDOS, EXPORTACION, NFU, PILETAS, REACTORES, TIERRAS FILTRANTES | R1285: 1 | S1285: 0 | T1285: 1 | U1285: APERTURADO POR EMPRESA | V1285: CEREAL Y POLVILLO
A1286: 46112 | B1286: RRHH WORMS (NUEVO) | C1286: CUETO, DANIELA | D1286: 0 | E1286: ADMINISTRACION | F1286: 1 | G1286: 0 | H1286: # RRHH | I1286: PERSONAL | J1286: OPEX | K1286: FIJO | L1286: DIRECTO | M1286: 0 | N1286: CC15 | O1286: rrhh_nuevo | P1286: 10 | Q1286: BACHAS, CEREAL Y POLVILLO, COMPOST Y FERTILIZANTES, DISPOSICION FINAL DE R. LIQUIDOS, DISPOSICION FINAL DE R. SOLIDOS, EXPORTACION, NFU, PILETAS, REACTORES, TIERRAS FILTRANTES | R1286: 1 | S1286: 0 | T1286: 1 | U1286: APERTURADO POR EMPRESA | V1286: COMPOST Y FERTILIZANTES
A1287: 46112 | B1287: RRHH WORMS (NUEVO) | C1287: CUETO, DANIELA | D1287: 0 | E1287: ADMINISTRACION | F1287: 1 | G1287: 0 | H1287: # RRHH | I1287: PERSONAL | J1287: OPEX | K1287: FIJO | L1287: DIRECTO | M1287: 0 | N1287: CC15 | O1287: rrhh_nuevo | P1287: 10 | Q1287: BACHAS, CEREAL Y POLVILLO, COMPOST Y FERTILIZANTES, DISPOSICION FINAL DE R. LIQUIDOS, DISPOSICION FINAL DE R. SOLIDOS, EXPORTACION, NFU, PILETAS, REACTORES, TIERRAS FILTRANTES | R1287: 1 | S1287: 0 | T1287: 1 | U1287: APERTURADO POR EMPRESA | V1287: DISPOSICION FINAL DE R. LIQUIDOS
A1288: 46112 | B1288: RRHH WORMS (NUEVO) | C1288: CUETO, DANIELA | D1288: 0 | E1288: ADMINISTRACION | F1288: 1 | G1288: 0 | H1288: # RRHH | I1288: PERSONAL | J1288: OPEX | K1288: FIJO | L1288: DIRECTO | M1288: 0 | N1288: CC15 | O1288: rrhh_nuevo | P1288: 10 | Q1288: BACHAS, CEREAL Y POLVILLO, COMPOST Y FERTILIZANTES, DISPOSICION FINAL DE R. LIQUIDOS, DISPOSICION FINAL DE R. SOLIDOS, EXPORTACION, NFU, PILETAS, REACTORES, TIERRAS FILTRANTES | R1288: 1 | S1288: 0 | T1288: 1 | U1288: APERTURADO POR EMPRESA | V1288: DISPOSICION FINAL DE R. SOLIDOS
A1289: 46112 | B1289: RRHH WORMS (NUEVO) | C1289: CUETO, DANIELA | D1289: 0 | E1289: ADMINISTRACION | F1289: 1 | G1289: 0 | H1289: # RRHH | I1289: PERSONAL | J1289: OPEX | K1289: FIJO | L1289: DIRECTO | M1289: 0 | N1289: CC15 | O1289: rrhh_nuevo | P1289: 10 | Q1289: BACHAS, CEREAL Y POLVILLO, COMPOST Y FERTILIZANTES, DISPOSICION FINAL DE R. LIQUIDOS, DISPOSICION FINAL DE R. SOLIDOS, EXPORTACION, NFU, PILETAS, REACTORES, TIERRAS FILTRANTES | R1289: 1 | S1289: 0 | T1289: 1 | U1289: APERTURADO POR EMPRESA | V1289: EXPORTACION
A1290: 46112 | B1290: RRHH WORMS (NUEVO) | C1290: CUETO, DANIELA | D1290: 0 | E1290: ADMINISTRACION | F1290: 1 | G1290: 0 | H1290: # RRHH | I1290: PERSONAL | J1290: OPEX | K1290: FIJO | L1290: DIRECTO | M1290: 0 | N1290: CC15 | O1290: rrhh_nuevo | P1290: 10 | Q1290: BACHAS, CEREAL Y POLVILLO, COMPOST Y FERTILIZANTES, DISPOSICION FINAL DE R. LIQUIDOS, DISPOSICION FINAL DE R. SOLIDOS, EXPORTACION, NFU, PILETAS, REACTORES, TIERRAS FILTRANTES | R1290: 1 | S1290: 0 | T1290: 1 | U1290: APERTURADO POR EMPRESA | V1290: NFU
A1291: 46112 | B1291: RRHH WORMS (NUEVO) | C1291: CUETO, DANIELA | D1291: 0 | E1291: ADMINISTRACION | F1291: 1 | G1291: 0 | H1291: # RRHH | I1291: PERSONAL | J1291: OPEX | K1291: FIJO | L1291: DIRECTO | M1291: 0 | N1291: CC15 | O1291: rrhh_nuevo | P1291: 10 | Q1291: BACHAS, CEREAL Y POLVILLO, COMPOST Y FERTILIZANTES, DISPOSICION FINAL DE R. LIQUIDOS, DISPOSICION FINAL DE R. SOLIDOS, EXPORTACION, NFU, PILETAS, REACTORES, TIERRAS FILTRANTES | R1291: 1 | S1291: 0 | T1291: 1 | U1291: APERTURADO POR EMPRESA | V1291: PILETAS
A1292: 46112 | B1292: RRHH WORMS (NUEVO) | C1292: CUETO, DANIELA | D1292: 0 | E1292: ADMINISTRACION | F1292: 1 | G1292: 0 | H1292: # RRHH | I1292: PERSONAL | J1292: OPEX | K1292: FIJO | L1292: DIRECTO | M1292: 0 | N1292: CC15 | O1292: rrhh_nuevo | P1292: 10 | Q1292: BACHAS, CEREAL Y POLVILLO, COMPOST Y FERTILIZANTES, DISPOSICION FINAL DE R. LIQUIDOS, DISPOSICION FINAL DE R. SOLIDOS, EXPORTACION, NFU, PILETAS, REACTORES, TIERRAS FILTRANTES | R1292: 1 | S1292: 0 | T1292: 1 | U1292: APERTURADO POR EMPRESA | V1292: REACTORES
A1293: 46112 | B1293: RRHH WORMS (NUEVO) | C1293: CUETO, DANIELA | D1293: 0 | E1293: ADMINISTRACION | F1293: 1 | G1293: 0 | H1293: # RRHH | I1293: PERSONAL | J1293: OPEX | K1293: FIJO | L1293: DIRECTO | M1293: 0 | N1293: CC15 | O1293: rrhh_nuevo | P1293: 10 | Q1293: BACHAS, CEREAL Y POLVILLO, COMPOST Y FERTILIZANTES, DISPOSICION FINAL DE R. LIQUIDOS, DISPOSICION FINAL DE R. SOLIDOS, EXPORTACION, NFU, PILETAS, REACTORES, TIERRAS FILTRANTES | R1293: 1 | S1293: 0 | T1293: 1 | U1293: APERTURADO POR EMPRESA | V1293: TIERRAS FILTRANTES
A1294: 0 | B1294: 0 | C1294: 0 | D1294: 0 | E1294: 0 | F1294: 0 | G1294: 0 | H1294: 0 | I1294: 0 | J1294: 0 | K1294: 0 | L1294: 0 | M1294: 0 | N1294: 0 | O1294: 0 | P1294: 0 | R1294: 0 | S1294: 0 | T1294: 0 | U1294: 0 | V1294: #NUM!
A1295: 0 | B1295: 0 | C1295: 0 | D1295: 0 | E1295: 0 | F1295: 0 | G1295: 0 | H1295: 0 | I1295: 0 | J1295: 0 | K1295: 0 | L1295: 0 | M1295: 0 | N1295: 0 | O1295: 0 | P1295: 0 | R1295: 0 | S1295: 0 | T1295: 0 | U1295: 0 | V1295: #NUM!
A1296: 0 | B1296: 0 | C1296: 0 | D1296: 0 | E1296: 0 | F1296: 0 | G1296: 0 | H1296: 0 | I1296: 0 | J1296: 0 | K1296: 0 | L1296: 0 | M1296: 0 | N1296: 0 | O1296: 0 | P1296: 0 | R1296: 0 | S1296: 0 | T1296: 0 | U1296: 0 | V1296: #NUM!
A1297: 0 | B1297: 0 | C1297: 0 | D1297: 0 | E1297: 0 | F1297: 0 | G1297: 0 | H1297: 0 | I1297: 0 | J1297: 0 | K1297: 0 | L1297: 0 | M1297: 0 | N1297: 0 | O1297: 0 | P1297: 0 | R1297: 0 | S1297: 0 | T1297: 0 | U1297: 0 | V1297: #NUM!
A1298: 0 | B1298: 0 | C1298: 0 | D1298: 0 | E1298: 0 | F1298: 0 | G1298: 0 | H1298: 0 | I1298: 0 | J1298: 0 | K1298: 0 | L1298: 0 | M1298: 0 | N1298: 0 | O1298: 0 | P1298: 0 | R1298: 0 | S1298: 0 | T1298: 0 | U1298: 0 | V1298: #NUM!
A1299: 0 | B1299: 0 | C1299: 0 | D1299: 0 | E1299: 0 | F1299: 0 | G1299: 0 | H1299: 0 | I1299: 0 | J1299: 0 | K1299: 0 | L1299: 0 | M1299: 0 | N1299: 0 | O1299: 0 | P1299: 0 | R1299: 0 | S1299: 0 | T1299: 0 | U1299: 0 | V1299: #NUM!
A1300: 0 | B1300: 0 | C1300: 0 | D1300: 0 | E1300: 0 | F1300: 0 | G1300: 0 | H1300: 0 | I1300: 0 | J1300: 0 | K1300: 0 | L1300: 0 | M1300: 0 | N1300: 0 | O1300: 0 | P1300: 0 | R1300: 0 | S1300: 0 | T1300: 0 | U1300: 0 | V1300: #NUM!
A1301: 0 | B1301: 0 | C1301: 0 | D1301: 0 | E1301: 0 | F1301: 0 | G1301: 0 | H1301: 0 | I1301: 0 | J1301: 0 | K1301: 0 | L1301: 0 | M1301: 0 | N1301: 0 | O1301: 0 | P1301: 0 | R1301: 0 | S1301: 0 | T1301: 0 | U1301: 0 | V1301: #NUM!
A1302: 0 | B1302: 0 | C1302: 0 | D1302: 0 | E1302: 0 | F1302: 0 | G1302: 0 | H1302: 0 | I1302: 0 | J1302: 0 | K1302: 0 | L1302: 0 | M1302: 0 | N1302: 0 | O1302: 0 | P1302: 0 | R1302: 0 | S1302: 0 | T1302: 0 | U1302: 0 | V1302: #NUM!
A1303: 0 | B1303: 0 | C1303: 0 | D1303: 0 | E1303: 0 | F1303: 0 | G1303: 0 | H1303: 0 | I1303: 0 | J1303: 0 | K1303: 0 | L1303: 0 | M1303: 0 | N1303: 0 | O1303: 0 | P1303: 0 | R1303: 0 | S1303: 0 | T1303: 0 | U1303: 0 | V1303: #NUM!
A1304: 0 | B1304: 0 | C1304: 0 | D1304: 0 | E1304: 0 | F1304: 0 | G1304: 0 | H1304: 0 | I1304: 0 | J1304: 0 | K1304: 0 | L1304: 0 | M1304: 0 | N1304: 0 | O1304: 0 | P1304: 0 | R1304: 0 | S1304: 0 | T1304: 0 | U1304: 0 | V1304: #NUM!
A1305: 0 | B1305: 0 | C1305: 0 | D1305: 0 | E1305: 0 | F1305: 0 | G1305: 0 | H1305: 0 | I1305: 0 | J1305: 0 | K1305: 0 | L1305: 0 | M1305: 0 | N1305: 0 | O1305: 0 | P1305: 0 | R1305: 0 | S1305: 0 | T1305: 0 | U1305: 0 | V1305: #NUM!
... A1400: 0 | B1400: 0 | C1400: 0 | D1400: 0 | E1400: 0 | F1400: 0 | G1400: 0 | H1400: 0 | I1400: 0 | J1400: 0 | K1400: 0 | L1400: 0 | M1400: 0 | N1400: 0 | O1400: 0 | P1400: 0 | R1400: 0 | S1400: 0 | T1400: 0 | U1400: 0 | V1400: #NUM!

Sheet bbdd.5.final
A1: Fecha de Factura/Recibo | B1: Nombre de la empresa a mostrar en la factura | C1: Número | D1: Total con signo | E1: Líneas de factura/Etiqueta | F1: Líneas de factura/Cantidad | G1: Líneas de factura/Precio unitario | H1: Líneas de factura/Unidad de medida | I1: Líneas de factura/Producto | J1: Concepto | K1: Tipo de Gasto 1 | L1: Tipo de Gasto 2 | M1: CCO EMPRESA | N1: CCO - SECTOR | O1: SECTOR_ODOO | P1: # SECTORES | Q1: LISTA_SECTORES | R1: CANTIDAD | S1: MONTO_FINAL | T1: CANTIDAD_APERTURADO | U1: Column4 | V1: SECTORES | W1: DC_COMUN | X1: prc_cco | Y1: monto_final2 | Z1: id_sector | AA1: id_rubro_opex | AB1: sector_final | AC1: rubro_final | AD1: monto_total_ampliado | AE1: dif
A2: 46111 | B2: WORMS 1 | C2: prod26 | D2: -79981130 | E2: AG-D | F2: 111.94 | G2: 500 | H2: TN | I2: MATERIA PRIMA | J2: OPEX | K2: VARIABLE | L2: DIRECTO | M2: 0 | N2: CC6 | O2: gastos_produccion | P2: 1 | Q2: BACHAS | R2: 1 | S2: -79981130 | T2: 111.94 | U2: APERTURADO POR EMPRESA | V2: BACHAS | W2: =_xlfn.CONCAT(N2,V2) -> CC6BACHAS | X2: =_xlfn.XLOOKUP(W2,'cco '!C:C,'cco '!D:D,0) -> 1 | Y2: =$X2*$S2*-1 -> 79981130 | Z2: =_xlfn.XLOOKUP(V2,sectores_id!A:A,sectores_id!B:B) -> 1 | AA2: =IF(J2="OPEX",_xlfn.XLOOKUP(I2,'rubros_id_opex (2)'!A:A,'rubros_id_opex (2)'!B:B,"RUBRO MC"),J2) -> 8 | AB2: =UPPER(_xlfn.XLOOKUP(Z2,sectores_id!B:B,sectores_id!A:A)) -> BACHAS | AC2: =_xlfn.XLOOKUP(AA2,'rubros_id_opex (2)'!B:B,'rubros_id_opex (2)'!A:A,gastos_final[[#This Row],[Líneas de factura/Producto]]) -> M.PRIMAS | AD2: =SUMIFS(Y:Y,C:C,gastos_final[[#This Row],[Número]]) -> 79981130 | AE2: =gastos_final[[#This Row],[MONTO_FINAL]]*-1-gastos_final[[#This Row],[monto_total_ampliado]] -> 0
A3: 46111 | B3: WORMS 1 | C3: prod33 | D3: -7557266.5 | E3: FONDO TK | F3: 10.577 | G3: 500 | H3: TN | I3: MATERIA PRIMA | J3: OPEX | K3: VARIABLE | L3: DIRECTO | M3: 0 | N3: CC6 | O3: gastos_produccion | P3: 1 | Q3: BACHAS | R3: 1 | S3: -7557266.5 | T3: 10.577 | U3: APERTURADO POR EMPRESA | V3: BACHAS | W3: =_xlfn.CONCAT(N3,V3) -> CC6BACHAS | X3: =_xlfn.XLOOKUP(W3,'cco '!C:C,'cco '!D:D,0) -> 1 | Y3: =$X3*$S3*-1 -> 7557266.5 | Z3: =_xlfn.XLOOKUP(V3,sectores_id!A:A,sectores_id!B:B) -> 1 | AA3: =IF(J3="OPEX",_xlfn.XLOOKUP(I3,'rubros_id_opex (2)'!A:A,'rubros_id_opex (2)'!B:B,"RUBRO MC"),J3) -> 8 | AB3: =UPPER(_xlfn.XLOOKUP(Z3,sectores_id!B:B,sectores_id!A:A)) -> BACHAS | AC3: =_xlfn.XLOOKUP(AA3,'rubros_id_opex (2)'!B:B,'rubros_id_opex (2)'!A:A,gastos_final[[#This Row],[Líneas de factura/Producto]]) -> M.PRIMAS | AD3: =SUMIFS(Y:Y,C:C,gastos_final[[#This Row],[Número]]) -> 7557266.5 | AE3: =gastos_final[[#This Row],[MONTO_FINAL]]*-1-gastos_final[[#This Row],[monto_total_ampliado]] -> 0
A4: 46111 | B4: TOTAL QUIMICA S.A. | C4: prod2 | D4: -4738755.8 | E4: ACIDO SULFÚRICO 70/80 | F4: 12224 | G4: 387.66 | H4: KG | I4: INSUMOS | J4: OPEX | K4: VARIABLE | L4: DIRECTO | M4: 0 | N4: CC6 | O4: gastos_produccion | P4: 1 | Q4: BACHAS | R4: 1 | S4: -4738755.8 | T4: 12224 | U4: APERTURADO POR EMPRESA | V4: BACHAS | W4: =_xlfn.CONCAT(N4,V4) -> CC6BACHAS | X4: =_xlfn.XLOOKUP(W4,'cco '!C:C,'cco '!D:D,0) -> 1 | Y4: =$X4*$S4*-1 -> 4738755.8 | Z4: =_xlfn.XLOOKUP(V4,sectores_id!A:A,sectores_id!B:B) -> 1 | AA4: =IF(J4="OPEX",_xlfn.XLOOKUP(I4,'rubros_id_opex (2)'!A:A,'rubros_id_opex (2)'!B:B,"RUBRO MC"),J4) -> 5 | AB4: =UPPER(_xlfn.XLOOKUP(Z4,sectores_id!B:B,sectores_id!A:A)) -> BACHAS | AC4: =_xlfn.XLOOKUP(AA4,'rubros_id_opex (2)'!B:B,'rubros_id_opex (2)'!A:A,gastos_final[[#This Row],[Líneas de factura/Producto]]) -> INSUMOS | AD4: =SUMIFS(Y:Y,C:C,gastos_final[[#This Row],[Número]]) -> 4738755.8 | AE4: =gastos_final[[#This Row],[MONTO_FINAL]]*-1-gastos_final[[#This Row],[monto_total_ampliado]] -> 0
A5: 46111 | B5: ULTRAONIX SRL | C5: prod5 | D5: -4074324.8 | E5: FUEL OIL | F5: 6443.352 | G5: 632.33 | H5: KG | I5: ENERGIA | J5: OPEX | K5: VARIABLE | L5: DIRECTO | M5: 0 | N5: CC6 | O5: gastos_produccion | P5: 1 | Q5: BACHAS | R5: 1 | S5: -4074324.8 | T5: 6443.352 | U5: APERTURADO POR EMPRESA | V5: BACHAS | W5: =_xlfn.CONCAT(N5,V5) -> CC6BACHAS | X5: =_xlfn.XLOOKUP(W5,'cco '!C:C,'cco '!D:D,0) -> 1 | Y5: =$X5*$S5*-1 -> 4074324.8 | Z5: =_xlfn.XLOOKUP(V5,sectores_id!A:A,sectores_id!B:B) -> 1 | AA5: =IF(J5="OPEX",_xlfn.XLOOKUP(I5,'rubros_id_opex (2)'!A:A,'rubros_id_opex (2)'!B:B,"RUBRO MC"),J5) -> 1 | AB5: =UPPER(_xlfn.XLOOKUP(Z5,sectores_id!B:B,sectores_id!A:A)) -> BACHAS | AC5: =_xlfn.XLOOKUP(AA5,'rubros_id_opex (2)'!B:B,'rubros_id_opex (2)'!A:A,gastos_final[[#This Row],[Líneas de factura/Producto]]) -> ENERGIA | AD5: =SUMIFS(Y:Y,C:C,gastos_final[[#This Row],[Número]]) -> 4074324.8 | AE5: =gastos_final[[#This Row],[MONTO_FINAL]]*-1-gastos_final[[#This Row],[monto_total_ampliado]] -> 0
A6: 46112 | B6: RRHH WORMS (NUEVO) | C6: JORGE SEBASTIAN ACOSTA | D6: -1289287.6 | E6: BACHAS | F6: 1 | G6: 1289287.6 | H6: # RRHH | I6: PERSONAL | J6: OPEX | K6: FIJO | L6: DIRECTO | M6: 0 | N6: CC6 | O6: rrhh_nuevo | P6: 1 | Q6: BACHAS | R6: 1 | S6: -1289287.6 | T6: 1 | U6: APERTURADO POR EMPRESA | V6: BACHAS | W6: =_xlfn.CONCAT(N6,V6) -> CC6BACHAS | X6: =_xlfn.XLOOKUP(W6,'cco '!C:C,'cco '!D:D,0) -> 1 | Y6: =$X6*$S6*-1 -> 1289287.6 | Z6: =_xlfn.XLOOKUP(V6,sectores_id!A:A,sectores_id!B:B) -> 1 | AA6: =IF(J6="OPEX",_xlfn.XLOOKUP(I6,'rubros_id_opex (2)'!A:A,'rubros_id_opex (2)'!B:B,"RUBRO MC"),J6) -> 10 | AB6: =UPPER(_xlfn.XLOOKUP(Z6,sectores_id!B:B,sectores_id!A:A)) -> BACHAS | AC6: =_xlfn.XLOOKUP(AA6,'rubros_id_opex (2)'!B:B,'rubros_id_opex (2)'!A:A,gastos_final[[#This Row],[Líneas de factura/Producto]]) -> PERSONAL | AD6: =SUMIFS(Y:Y,C:C,gastos_final[[#This Row],[Número]]) -> 1289287.6 | AE6: =gastos_final[[#This Row],[MONTO_FINAL]]*-1-gastos_final[[#This Row],[monto_total_ampliado]] -> 0
A7: 46112 | B7: RRHH WORMS (NUEVO) | C7: JEREMIAS EDGARDO NAHUEL FERNANDEZ | D7: -1082821.2 | E7: BACHAS | F7: 1 | G7: 1082821.2 | H7: # RRHH | I7: PERSONAL | J7: OPEX | K7: FIJO | L7: DIRECTO | M7: 0 | N7: CC6 | O7: rrhh_nuevo | P7: 1 | Q7: BACHAS | R7: 1 | S7: -1082821.2 | T7: 1 | U7: APERTURADO POR EMPRESA | V7: BACHAS | W7: =_xlfn.CONCAT(N7,V7) -> CC6BACHAS | X7: =_xlfn.XLOOKUP(W7,'cco '!C:C,'cco '!D:D,0) -> 1 | Y7: =$X7*$S7*-1 -> 1082821.2 | Z7: =_xlfn.XLOOKUP(V7,sectores_id!A:A,sectores_id!B:B) -> 1 | AA7: =IF(J7="OPEX",_xlfn.XLOOKUP(I7,'rubros_id_opex (2)'!A:A,'rubros_id_opex (2)'!B:B,"RUBRO MC"),J7) -> 10 | AB7: =UPPER(_xlfn.XLOOKUP(Z7,sectores_id!B:B,sectores_id!A:A)) -> BACHAS | AC7: =_xlfn.XLOOKUP(AA7,'rubros_id_opex (2)'!B:B,'rubros_id_opex (2)'!A:A,gastos_final[[#This Row],[Líneas de factura/Producto]]) -> PERSONAL | AD7: =SUMIFS(Y:Y,C:C,gastos_final[[#This Row],[Número]]) -> 1082821.2 | AE7: =gastos_final[[#This Row],[MONTO_FINAL]]*-1-gastos_final[[#This Row],[monto_total_ampliado]] -> 0
A8: 46111 | B8: MARTINS, JOAQUIN | C8: prod9 | D8: -215250 | E8: NAFTA | F8: 105 | G8: 2050 | H8: Lts | I8: ENERGIA | J8: OPEX | K8: VARIABLE | L8: DIRECTO | M8: 0 | N8: CC6 | O8: gastos_produccion | P8: 1 | Q8: BACHAS | R8: 1 | S8: -215250 | T8: 105 | U8: APERTURADO POR EMPRESA | V8: BACHAS | W8: =_xlfn.CONCAT(N8,V8) -> CC6BACHAS | X8: =_xlfn.XLOOKUP(W8,'cco '!C:C,'cco '!D:D,0) -> 1 | Y8: =$X8*$S8*-1 -> 215250 | Z8: =_xlfn.XLOOKUP(V8,sectores_id!A:A,sectores_id!B:B) -> 1 | AA8: =IF(J8="OPEX",_xlfn.XLOOKUP(I8,'rubros_id_opex (2)'!A:A,'rubros_id_opex (2)'!B:B,"RUBRO MC"),J8) -> 1 | AB8: =UPPER(_xlfn.XLOOKUP(Z8,sectores_id!B:B,sectores_id!A:A)) -> BACHAS | AC8: =_xlfn.XLOOKUP(AA8,'rubros_id_opex (2)'!B:B,'rubros_id_opex (2)'!A:A,gastos_final[[#This Row],[Líneas de factura/Producto]]) -> ENERGIA | AD8: =SUMIFS(Y:Y,C:C,gastos_final[[#This Row],[Número]]) -> 215250 | AE8: =gastos_final[[#This Row],[MONTO_FINAL]]*-1-gastos_final[[#This Row],[monto_total_ampliado]] -> 0
A9: 46111 | B9: SALINERA JAISAL S. A. | C9: prod3 | D9: -34485 | E9: CLORURO DE SODIO (SAL) | F9: 300 | G9: 114.95 | H9: KG | I9: INSUMOS | J9: OPEX | K9: VARIABLE | L9: DIRECTO | M9: 0 | N9: CC6 | O9: gastos_produccion | P9: 1 | Q9: BACHAS | R9: 1 | S9: -34485 | T9: 300 | U9: APERTURADO POR EMPRESA | V9: BACHAS | W9: =_xlfn.CONCAT(N9,V9) -> CC6BACHAS | X9: =_xlfn.XLOOKUP(W9,'cco '!C:C,'cco '!D:D,0) -> 1 | Y9: =$X9*$S9*-1 -> 34485 | Z9: =_xlfn.XLOOKUP(V9,sectores_id!A:A,sectores_id!B:B) -> 1 | AA9: =IF(J9="OPEX",_xlfn.XLOOKUP(I9,'rubros_id_opex (2)'!A:A,'rubros_id_opex (2)'!B:B,"RUBRO MC"),J9) -> 5 | AB9: =UPPER(_xlfn.XLOOKUP(Z9,sectores_id!B:B,sectores_id!A:A)) -> BACHAS | AC9: =_xlfn.XLOOKUP(AA9,'rubros_id_opex (2)'!B:B,'rubros_id_opex (2)'!A:A,gastos_final[[#This Row],[Líneas de factura/Producto]]) -> INSUMOS | AD9: =SUMIFS(Y:Y,C:C,gastos_final[[#This Row],[Número]]) -> 34485 | AE9: =gastos_final[[#This Row],[MONTO_FINAL]]*-1-gastos_final[[#This Row],[monto_total_ampliado]] -> 0
A10: 46111 | B10: TOTAL QUIMICA S.A. | C10: prod1 | D10: 0 | E10: ACIDO CLORHIDRICO | F10: 0 | G10: 464 | H10: KG | I10: INSUMOS | J10: OPEX | K10: VARIABLE | L10: DIRECTO | M10: 0 | N10: CC6 | O10: gastos_produccion | P10: 1 | Q10: BACHAS | R10: 1 | S10: 0 | T10: 0 | U10: APERTURADO POR EMPRESA | V10: BACHAS | W10: =_xlfn.CONCAT(N10,V10) -> CC6BACHAS | X10: =_xlfn.XLOOKUP(W10,'cco '!C:C,'cco '!D:D,0) -> 1 | Y10: =$X10*$S10*-1 -> 0 | Z10: =_xlfn.XLOOKUP(V10,sectores_id!A:A,sectores_id!B:B) -> 1 | AA10: =IF(J10="OPEX",_xlfn.XLOOKUP(I10,'rubros_id_opex (2)'!A:A,'rubros_id_opex (2)'!B:B,"RUBRO MC"),J10) -> 5 | AB10: =UPPER(_xlfn.XLOOKUP(Z10,sectores_id!B:B,sectores_id!A:A)) -> BACHAS | AC10: =_xlfn.XLOOKUP(AA10,'rubros_id_opex (2)'!B:B,'rubros_id_opex (2)'!A:A,gastos_final[[#This Row],[Líneas de factura/Producto]]) -> INSUMOS | AD10: =SUMIFS(Y:Y,C:C,gastos_final[[#This Row],[Número]]) -> 0 | AE10: =gastos_final[[#This Row],[MONTO_FINAL]]*-1-gastos_final[[#This Row],[monto_total_ampliado]] -> 0
A11: 46111 | B11: MARTINS, JOAQUIN | C11: prod6 | D11: 0 | E11: G2 | F11: 0 | G11: 1472 | H11: Lts | I11: ENERGIA | J11: OPEX | K11: VARIABLE | L11: DIRECTO | M11: 0 | N11: CC6 | O11: gastos_produccion | P11: 1 | Q11: BACHAS | R11: 1 | S11: 0 | T11: 0 | U11: APERTURADO POR EMPRESA | V11: BACHAS | W11: =_xlfn.CONCAT(N11,V11) -> CC6BACHAS | X11: =_xlfn.XLOOKUP(W11,'cco '!C:C,'cco '!D:D,0) -> 1 | Y11: =$X11*$S11*-1 -> 0 | Z11: =_xlfn.XLOOKUP(V11,sectores_id!A:A,sectores_id!B:B) -> 1 | AA11: =IF(J11="OPEX",_xlfn.XLOOKUP(I11,'rubros_id_opex (2)'!A:A,'rubros_id_opex (2)'!B:B,"RUBRO MC"),J11) -> 1 | AB11: =UPPER(_xlfn.XLOOKUP(Z11,sectores_id!B:B,sectores_id!A:A)) -> BACHAS | AC11: =_xlfn.XLOOKUP(AA11,'rubros_id_opex (2)'!B:B,'rubros_id_opex (2)'!A:A,gastos_final[[#This Row],[Líneas de factura/Producto]]) -> ENERGIA | AD11: =SUMIFS(Y:Y,C:C,gastos_final[[#This Row],[Número]]) -> 0 | AE11: =gastos_final[[#This Row],[MONTO_FINAL]]*-1-gastos_final[[#This Row],[monto_total_ampliado]] -> 0
A12: 46111 | B12: WORMS 1 | C12: prod31 | D12: 0 | E12: BORRA AN | F12: 0 | G12: 500 | H12: TN | I12: MATERIA PRIMA | J12: OPEX | K12: VARIABLE | L12: DIRECTO | M12: 0 | N12: CC6 | O12: gastos_produccion | P12: 1 | Q12: BACHAS | R12: 1 | S12: 0 | T12: 0 | U12: APERTURADO POR EMPRESA | V12: BACHAS | W12: =_xlfn.CONCAT(N12,V12) -> CC6BACHAS | X12: =_xlfn.XLOOKUP(W12,'cco '!C:C,'cco '!D:D,0) -> 1 | Y12: =$X12*$S12*-1 -> 0 | Z12: =_xlfn.XLOOKUP(V12,sectores_id!A:A,sectores_id!B:B) -> 1 | AA12: =IF(J12="OPEX",_xlfn.XLOOKUP(I12,'rubros_id_opex (2)'!A:A,'rubros_id_opex (2)'!B:B,"RUBRO MC"),J12) -> 8 | AB12: =UPPER(_xlfn.XLOOKUP(Z12,sectores_id!B:B,sectores_id!A:A)) -> BACHAS | AC12: =_xlfn.XLOOKUP(AA12,'rubros_id_opex (2)'!B:B,'rubros_id_opex (2)'!A:A,gastos_final[[#This Row],[Líneas de factura/Producto]]) -> M.PRIMAS | AD12: =SUMIFS(Y:Y,C:C,gastos_final[[#This Row],[Número]]) -> 0 | AE12: =gastos_final[[#This Row],[MONTO_FINAL]]*-1-gastos_final[[#This Row],[monto_total_ampliado]] -> 0
A13: 46111 | B13: WORMS 1 | C13: prod32 | D13: 0 | E13: ÁCIDO CITRICO | F13: 0 | G13: #NUM! | H13: KG | I13: INSUMOS | J13: OPEX | K13: VARIABLE | L13: DIRECTO | M13: 0 | N13: CC6 | O13: gastos_produccion | P13: 1 | Q13: BACHAS | R13: 1 | S13: 0 | T13: 0 | U13: APERTURADO POR EMPRESA | V13: BACHAS | W13: =_xlfn.CONCAT(N13,V13) -> CC6BACHAS | X13: =_xlfn.XLOOKUP(W13,'cco '!C:C,'cco '!D:D,0) -> 1 | Y13: =$X13*$S13*-1 -> 0 | Z13: =_xlfn.XLOOKUP(V13,sectores_id!A:A,sectores_id!B:B) -> 1 | AA13: =IF(J13="OPEX",_xlfn.XLOOKUP(I13,'rubros_id_opex (2)'!A:A,'rubros_id_opex (2)'!B:B,"RUBRO MC"),J13) -> 5 | AB13: =UPPER(_xlfn.XLOOKUP(Z13,sectores_id!B:B,sectores_id!A:A)) -> BACHAS | AC13: =_xlfn.XLOOKUP(AA13,'rubros_id_opex (2)'!B:B,'rubros_id_opex (2)'!A:A,gastos_final[[#This Row],[Líneas de factura/Producto]]) -> INSUMOS | AD13: =SUMIFS(Y:Y,C:C,gastos_final[[#This Row],[Número]]) -> 0 | AE13: =gastos_final[[#This Row],[MONTO_FINAL]]*-1-gastos_final[[#This Row],[monto_total_ampliado]] -> 0
A14: 46111 | B14: WORMS 1 | C14: prod34 | D14: 0 | E14: BORRA A | F14: 20.48 | G14: #NUM! | H14: KG | I14: MATERIA PRIMA | J14: OPEX | K14: VARIABLE | L14: DIRECTO | M14: 0 | N14: CC6 | O14: gastos_produccion | P14: 1 | Q14: BACHAS | R14: 1 | S14: 0 | T14: 20.48 | U14: APERTURADO POR EMPRESA | V14: BACHAS | W14: =_xlfn.CONCAT(N14,V14) -> CC6BACHAS | X14: =_xlfn.XLOOKUP(W14,'cco '!C:C,'cco '!D:D,0) -> 1 | Y14: =$X14*$S14*-1 -> 0 | Z14: =_xlfn.XLOOKUP(V14,sectores_id!A:A,sectores_id!B:B) -> 1 | AA14: =IF(J14="OPEX",_xlfn.XLOOKUP(I14,'rubros_id_opex (2)'!A:A,'rubros_id_opex (2)'!B:B,"RUBRO MC"),J14) -> 8 | AB14: =UPPER(_xlfn.XLOOKUP(Z14,sectores_id!B:B,sectores_id!A:A)) -> BACHAS | AC14: =_xlfn.XLOOKUP(AA14,'rubros_id_opex (2)'!B:B,'rubros_id_opex (2)'!A:A,gastos_final[[#This Row],[Líneas de factura/Producto]]) -> M.PRIMAS | AD14: =SUMIFS(Y:Y,C:C,gastos_final[[#This Row],[Número]]) -> 0 | AE14: =gastos_final[[#This Row],[MONTO_FINAL]]*-1-gastos_final[[#This Row],[monto_total_ampliado]] -> 0
A15: 46111 | B15: LOPEZ, JESUS RODRIGO | C15: FA-C 2-2026-3 | D15: -418000 | E15: LOGISTICA PUERT | F15: 22 | G15: 19000 | H15: UN | I15: LOGISTICA | J15: OPEX | K15: VARIABLE | L15: DIRECTO | M15: 0 | N15: CC9 | O15: gastos_produccion | P15: 1 | Q15: CEREAL & POLVILLO | R15: 1 | S15: -418000 | T15: 22 | U15: APERTURADO POR EMPRESA | V15: CEREAL & POLVILLO | W15: =_xlfn.CONCAT(N15,V15) -> CC9CEREAL & POLVILLO | X15: =_xlfn.XLOOKUP(W15,'cco '!C:C,'cco '!D:D,0) -> 1 | Y15: =$X15*$S15*-1 -> 418000 | Z15: =_xlfn.XLOOKUP(V15,sectores_id!A:A,sectores_id!B:B) -> 2 | AA15: =IF(J15="OPEX",_xlfn.XLOOKUP(I15,'rubros_id_opex (2)'!A:A,'rubros_id_opex (2)'!B:B,"RUBRO MC"),J15) -> 7 | AB15: =UPPER(_xlfn.XLOOKUP(Z15,sectores_id!B:B,sectores_id!A:A)) -> CEREAL & POLVILLO | AC15: =_xlfn.XLOOKUP(AA15,'rubros_id_opex (2)'!B:B,'rubros_id_opex (2)'!A:A,gastos_final[[#This Row],[Líneas de factura/Producto]]) -> LOGISTICA | AD15: =SUMIFS(Y:Y,C:C,gastos_final[[#This Row],[Número]]) -> 63902892 | AE15: =gastos_final[[#This Row],[MONTO_FINAL]]*-1-gastos_final[[#This Row],[monto_total_ampliado]] -> -63484892
A16: 46111 | B16: IMPUESTOS | C16: imp5 | D16: -166429.71 | E16: IMPUESTOS | F16: 1 | G16: 166429.71 | H16: UN | I16: IMPUESTOS | J16: OPEX | K16: VARIABLE | L16: INDIRECTO | M16: 0 | N16: CC8 | O16: gastos_impuestos | P16: 1 | Q16: COMPOST & FERTILIZANTES | R16: 1 | S16: -166429.71 | T16: 1 | U16: APERTURADO POR EMPRESA | V16: COMPOST & FERTILIZANTES | W16: =_xlfn.CONCAT(N16,V16) -> CC8COMPOST & FERTILIZANTES | X16: =_xlfn.XLOOKUP(W16,'cco '!C:C,'cco '!D:D,0) -> 1 | Y16: =$X16*$S16*-1 -> 166429.71 | Z16: =_xlfn.XLOOKUP(V16,sectores_id!A:A,sectores_id!B:B) -> 10 | AA16: =IF(J16="OPEX",_xlfn.XLOOKUP(I16,'rubros_id_opex (2)'!A:A,'rubros_id_opex (2)'!B:B,"RUBRO MC"),J16) -> 4 | AB16: =UPPER(_xlfn.XLOOKUP(Z16,sectores_id!B:B,sectores_id!A:A)) -> COMPOST & FERTILIZANTES | AC16: =_xlfn.XLOOKUP(AA16,'rubros_id_opex (2)'!B:B,'rubros_id_opex (2)'!A:A,gastos_final[[#This Row],[Líneas de factura/Producto]]) -> IMPUESTOS | AD16: =SUMIFS(Y:Y,C:C,gastos_final[[#This Row],[Número]]) -> 166429.71 | AE16: =gastos_final[[#This Row],[MONTO_FINAL]]*-1-gastos_final[[#This Row],[monto_total_ampliado]] -> 0
A17: 46090 | B17: Empresa Provincial De La Energia De Santa Fe (W) | C17: FA-A 00069-00039909 | D17: -27731946 | E17: ENERGIA Luz | F17: 1 | G17: 20171433 | H17: UN | I17: ENERGIA | J17: OPEX | K17: VARIABLE | L17: DIRECTO | M17: 0 | N17: CC14 | O17: gastos_produccion | P17: 10 | Q17: BACHAS, CEREAL & POLVILLO, COMPOST & FERTILIZANTES, DISPOSICIÓN FINAL RESIDUOS LIQUIDOS, DISPOSICIÓN FINAL RESIDUOS SOLIDOS, EXPORTACION, NFU, PILETAS, REACTORES, TIERRAS FILTRANTES | R17: 1 | S17: -27731946 | T17: 1 | U17: APERTURADO POR EMPRESA | V17: BACHAS | W17: =_xlfn.CONCAT(N17,V17) -> CC14BACHAS | X17: =_xlfn.XLOOKUP(W17,'cco '!C:C,'cco '!D:D,0) -> 0.056730377 | Y17: =$X17*$S17*-1 -> 1573243.7 | Z17: =_xlfn.XLOOKUP(V17,sectores_id!A:A,sectores_id!B:B) -> 1 | AA17: =IF(J17="OPEX",_xlfn.XLOOKUP(I17,'rubros_id_opex (2)'!A:A,'rubros_id_opex (2)'!B:B,"RUBRO MC"),J17) -> 1 | AB17: =UPPER(_xlfn.XLOOKUP(Z17,sectores_id!B:B,sectores_id!A:A)) -> BACHAS | AC17: =_xlfn.XLOOKUP(AA17,'rubros_id_opex (2)'!B:B,'rubros_id_opex (2)'!A:A,gastos_final[[#This Row],[Líneas de factura/Producto]]) -> ENERGIA | AD17: =SUMIFS(Y:Y,C:C,gastos_final[[#This Row],[Número]]) -> 27732939 | AE17: =gastos_final[[#This Row],[MONTO_FINAL]]*-1-gastos_final[[#This Row],[monto_total_ampliado]] -> -992.85646
A18: 46090 | B18: Empresa Provincial De La Energia De Santa Fe (W) | C18: FA-A 00069-00039909 | D18: -27731946 | E18: ENERGIA Luz | F18: 1 | G18: 20171433 | H18: UN | I18: ENERGIA | J18: OPEX | K18: VARIABLE | L18: DIRECTO | M18: 0 | N18: CC14 | O18: gastos_produccion | P18: 10 | Q18: BACHAS, CEREAL & POLVILLO, COMPOST & FERTILIZANTES, DISPOSICIÓN FINAL RESIDUOS LIQUIDOS, DISPOSICIÓN FINAL RESIDUOS SOLIDOS, EXPORTACION, NFU, PILETAS, REACTORES, TIERRAS FILTRANTES | R18: 1 | S18: -27731946 | T18: 1 | U18: APERTURADO POR EMPRESA | V18: CEREAL & POLVILLO | W18: =_xlfn.CONCAT(N18,V18) -> CC14CEREAL & POLVILLO | X18: =_xlfn.XLOOKUP(W18,'cco '!C:C,'cco '!D:D,0) -> 0.00083810181 | Y18: =$X18*$S18*-1 -> 23242.194 | Z18: =_xlfn.XLOOKUP(V18,sectores_id!A:A,sectores_id!B:B) -> 2 | AA18: =IF(J18="OPEX",_xlfn.XLOOKUP(I18,'rubros_id_opex (2)'!A:A,'rubros_id_opex (2)'!B:B,"RUBRO MC"),J18) -> 1 | AB18: =UPPER(_xlfn.XLOOKUP(Z18,sectores_id!B:B,sectores_id!A:A)) -> CEREAL & POLVILLO | AC18: =_xlfn.XLOOKUP(AA18,'rubros_id_opex (2)'!B:B,'rubros_id_opex (2)'!A:A,gastos_final[[#This Row],[Líneas de factura/Producto]]) -> ENERGIA | AD18: =SUMIFS(Y:Y,C:C,gastos_final[[#This Row],[Número]]) -> 27732939 | AE18: =gastos_final[[#This Row],[MONTO_FINAL]]*-1-gastos_final[[#This Row],[monto_total_ampliado]] -> -992.85646
