Workbook

Sheet costos_ampliados
A1: Actividades | B1: Estado | C1: Estado de pago | D1: Fecha de Factura/Recibo | E1: Fecha de vencimiento | F1: Importe sin impuestos con signo | G1: Nombre de la empresa a mostrar en la factura | H1: Número | I1: Referencia | J1: Total con signo | K1: Total en divisa con signo | L1: Importe adeudado | M1: Líneas de factura/Etiquetas | N1: Líneas de factura/Etiqueta | O1: Líneas de factura/Cantidad | P1: Líneas de factura/Precio unitario | Q1: Líneas de factura/Unidad de medida | R1: Apuntes contables/Líneas analíticas/Cuenta analítica | S1: Origen
B2: Publicado | C2: No pagadas | D2: 45900 | E2: 45907 | F2: -118800 | G2: Barrera, Adrian Jesus | H2: FA-C 00001-00000366 | J2: -118800 | K2: -118800 | L2: 118800 | N2: OC 0001-00001152: Gastos Operativos (C) Bidones de agua de 20 litros | O2: 33 | P2: 3600 | Q2: Unidad(es) | S2: OC 0001-00001152
B4: Publicado | C4: No pagadas | D4: 45900 | E4: 45930 | F4: -140842.95 | G4: Agroceres Pic Argentina S A | H4: FA-A 00008-00137653 | J4: -170419.97 | K4: -170419.97 | L4: 170419.97 | N4: DOSIS AGpic337 Roy | O4: 15 | P4: 9389.53 | Q4: Unidad(es)
B7: Publicado | C7: Pagado | D7: 45898 | E7: 45898 | F7: -2479500 | G7: Sueldos a pagar | H7: OC/2025/0131 | J7: -2479500 | K7: -2479500 | N7: ALBERTENGO GUIDO Pablos (ACUERDO) | O7: 1 | P7: 2479500
B9: Publicado | C9: Pagado | D9: 45898 | E9: 45898 | F9: -2137500 | G9: Sueldos a pagar | H9: OC/2025/0130 | J9: -2137500 | K9: -2137500 | N9: Albertengo Juan Ignacio(ACUERDO) | O9: 1 | P9: 2137500
B11: Publicado | C11: Pagado | D11: 45898 | E11: 45898 | F11: -1754639 | G11: Sueldos a pagar | H11: OC/2025/0129 | J11: -1754639 | K11: -1754639 | N11: Cristian Franco Emiliano Nicolas (ACUERDO) | O11: 1 | P11: 1754639
B13: Publicado | C13: Pagado | D13: 45898 | E13: 45898 | F13: -1459831.4 | G13: Sueldos a pagar | H13: OC/2025/0128 | J13: -1459831.4 | K13: -1459831.4 | N13: Cristian Franco Martin Andrés (ACUERDO) | O13: 1 | P13: 1459831.4
B15: Publicado | C15: Pagado | D15: 45898 | E15: 45898 | F15: -1302502 | G15: Sueldos a pagar | H15: OC/2025/0127 | J15: -1302502 | K15: -1302502 | N15: Cristian Joaquin Duran (ACUERDO) | O15: 1 | P15: 1302502
O16: 1 | P16: 0
B19: Publicado | C19: Pagado | D19: 45898 | E19: 45898 | F19: -200000 | G19: Sueldos a pagar | H19: OC/2025/0126 | J19: -200000 | K19: -200000 | N19: Cristian Leonardo Celaya (ACUERDO) | O19: 1 | P19: 200000
B21: Publicado | C21: No pagadas | D21: 45898 | E21: 45929 | F21: -3627176 | G21: Nutran S.R.L. | H21: FA-A 00002-00009786 | J21: -4388883 | K21: -4388883 | L21: 4388883 | N21: OC 0001-00000960: Fason(C) | O21: 1 | P21: 3627176 | Q21: Unidad(es) | S21: OC 0001-00000960
B24: Publicado | C24: Pagado | D24: 45898 | E24: 45912 | F24: -20774.4 | G24: Comercial Uritorco S. R. L. | H24: FA-A 00001-00006198 | J24: -25137.03 | K24: -25137.03 | N24: ALAMBRE RECOCIDO NEGRO 17=1.42XR ROLLO | O24: 1 | P24: 15580.8 | Q24: Unidad(es)
N25: ALAMBRE RECOCDIO NEGRO17=1.42X R ROLLO= 1KG | O25: 1 | P25: 5193.6 | Q25: Unidad(es)
B29: Publicado | C29: Pagado | D29: 45898 | E29: 45912 | F29: -66531.8 | G29: Comercial Uritorco S. R. L. | H29: FA-A 00001-00006197 | J29: -80503.48 | K29: -80503.48 | N29: AEROSOL AZUL 350ML.USO GENERAL TEK BOND | O29: 1 | P29: 33265.9 | Q29: Unidad(es)
N30: AEROSOL ROJO 350ML.ACRILICA TEK BOND | O30: 1 | P30: 33265.9 | Q30: Unidad(es)
B34: Publicado | C34: Pagado | D34: 45898 | E34: 45898 | F34: -90500.8 | G34: Pascual Materiales S. R. L. | H34: FA-A 00001-00000311 | J34: -109506.01 | K34: -109506.01 | N34: bolsas de cemento (hidroponia) | O34: 12 | P34: 4463.04 | Q34: Unidad(es)
N35: bolsas de cemento(recrea) | O35: 8 | P35: 4463.04 | Q35: Unidad(es)
N36: envió de mercaderia | O36: 1 | P36: 1240 | Q36: Unidad(es)
B41: Publicado | C41: Pagado | D41: 45897 | E41: 45897 | F41: -190449.86 | G41: ARCA | H41: OC/2025/0125 | J41: -190449.86 | K41: -190449.86 | O41: 1 | P41: 190449.86
B43: Publicado | C43: No pagadas | D43: 45897 | E43: 45912 | F43: -4500 | G43: Forconi, Marcos Roman | H43: FA-C 00001-00000305 | J43: -4500 | K43: -4500 | L43: 4500 | N43: diferencia aumento de septiembre | O43: 1 | P43: 4500 | Q43: Unidad(es)
B45: Publicado | C45: No pagadas | D45: 45897 | E45: 45912 | F45: -57999 | G45: Forconi, Marcos Roman | H45: FA-C 00001-00000290 | J45: -57999 | K45: -57999 | L45: 57999 | N45: Servicio mes de septiembre 2025 | O45: 1 | P45: 57999 | Q45: Unidad(es)
B47: Publicado | C47: Pagado | D47: 45897 | E47: 45897 | F47: -11172374 | G47: Topigs Norsvin Argentina S.R.L. | H47: FA-A 00011-00027677 | J47: -12345474 | K47: -12345474 | N47: abuelas cash gps plus genético | O47: 1 | P47: 11172374 | Q47: Unidad(es)
B50: Publicado | C50: Pagado | D50: 45896 | E50: 45896 | F50: -10539.86 | G50: Servicio Nacional De Sanidad Y Calidad Agroalimentaria Senasa | H50: OC/2025/0124 | J50: -10539.86 | K50: -10539.86 | N50: Gastos Operativos (C) | O50: 1 | P50: 10539.86 | Q50: Unidad(es)
B52: Publicado | C52: Pagado | D52: 45896 | E52: 45896 | F52: -1500000 | G52: Sueldos a pagar | H52: OC/2025/0123 | J52: -1500000 | K52: -1500000 | N52: Cristian Leonardo Celaya (ACUERDO) | O52: 1 | P52: 1500000 | S52: OC 0001-00001004
B54: Publicado | C54: Pagado | D54: 45895 | E54: 45895 | F54: -15711.62 | G54: Servicio Nacional De Sanidad Y Calidad Agroalimentaria Senasa | H54: OC/2025/0122 | J54: -15711.62 | K54: -15711.62 | N54: Gastos Operativos (C) | O54: 1 | P54: 15711.62 | Q54: Unidad(es)
B56: Publicado | C56: No pagadas | D56: 45896 | E56: 45958 | F56: -1200 | G56: Esperanza Distribuciones Srl | H56: FA-A 00026-00489583 | J56: -1452 | K56: -1452 | L56: 1452 | N56: gastos adm, de cheques | O56: 1 | P56: 1200 | Q56: Unidad(es)
B59: Publicado | C59: No pagadas | D59: 45896 | E59: 45911 | F59: -3352500 | G59: Arrieta, Fernando Gabriel | H59: FA-A 00003-00000285 | J59: -4056525 | K59: -4056525 | L59: 4056525 | N59: Flete, fecha : 04/08/2025 Calzim / Máximo paz kms:70 tipo: simple DTE: 29964925-29968915-CABEZAS: 85 CHOFER:GARFAGNOLI MATIAS | O59: 1 | P59: 415000 | Q59: Unidad(es)
N60: Flete-Fecha:07/08/2025 ARROYO SECO/MAXIMO PAZ KM: 70 TIPO:SOBLE dte:2199819957-2199820408-Cabezas:0 | O60: 1 | P60: 495000 | Q60: Unidad(es)
N61: Flete: Fceha_21/08/2025 Arroyo Seco /Maximo Paz kms:70 tipo:Simple DTE: 300861393 | O61: 1 | P61: 415000 | Q61: Unidad(es)
N62: LETE-fECHA:05/08/2025 Arroyo SEco /Máximo Paz kms: tipo: simple. Dte_2299721302-2299721426-2299721671 | O62: 1 | P62: 415000 | Q62: Unidad(es)
N63: Flete -Fecha:14/08/2025 Arroyo Seco/Maximo Paz kms: 70 Tipo: Doble DTE:300309143--cABEZAS:0 CHOFER: SCUOTRI OMAR | O63: 1 | P63: 495000 | Q63: Unidad(es)
N64: fLETE-fECHA:19/08/2025 aRROYO sECO/mAXIMO pAZ kms.70 tipo :chasis Dte:300795205 | O64: 1 | P64: 287500 | Q64: Unidad(es)
N65: Flete-Fecha:11/08/2025 Arroyo Seco/Maximo Paz KMs: 70 Tipo : Simple Dte: 2300127943-2300127606 cabezas:0 chofer ; scuotri Omar | O65: 1 | P65: 415000 | Q65: Unidad(es)
N66: Flete: Fecha:18/08/2025 Arroyo Seco/Maximo Paz Kms:70 Tipo: SIMPLEDTE:2300618057-2300617670-CABEZAS:0 CHOFER | O66: 1 | P66: 415000 | Q66: Unidad(es)
B76: Publicado | C76: Pagado | D76: 45896 | E76: 45910 | F76: -21409.9 | G76: Comercial Uritorco S. R. L. | H76: FA-A 00001-00006140 | J76: -25905.98 | K76: -25905.98 | N76: bulon whitwortk 5/16 x 1cincada taco metalico | O76: 1 | P76: 21409.9 | Q76: Unidad(es)
B79: Publicado | C79: Pagado | D79: 45896 | E79: 45910 | F79: -14355.27 | G79: Comercial Uritorco S. R. L. | H79: FA-A 00001-00000639 | J79: -17369.88 | K79: -17369.88 | N79: vaso magnetico hexag, disc diam segmentado(mantenimiento) | O79: 1 | P79: 14355.27 | Q79: Unidad(es)
B82: Publicado | C82: Pagado | D82: 45896 | E82: 45896 | F82: -36323.98 | G82: Pascual Materiales S. R. L. | H82: FA-A 00001-00000309 | J82: -43952.02 | K82: -43952.02 | N82: Cemento AVELLANEDA X 25KG DE MAYORISTA (RECRIA) | O82: 1 | P82: 36323.98 | Q82: Unidad(es)
B85: Publicado | C85: Pagado | D85: 45894 | E85: 45894 | F85: -332727.7 | G85: Administracion Provincial De Impuestos | H85: OC/2025/0119 | J85: -332727.7 | K85: -332727.7 | N85: SERVICIOS (C) | O85: 1 | P85: 332727.7 | Q85: Unidad(es)
B87: Publicado | C87: Pagado | D87: 45895 | E87: 45895 | F87: -266479.34 | G87: Pascual Materiales S. R. L. | H87: FA-A 00001-00000308 | J87: -322440 | K87: -322440 | N87: bolson de arena, piedras 6/19 x bolson, hieroo 10 por barra x 12mts, cemento avellaneda x 25 kg mayorista, servicio grua (hidroponía) | O87: 1 | P87: 266479.34 | Q87: Unidad(es)
B90: Publicado | C90: Pagado | D90: 45894 | E90: 45894 | F90: -12421.99 | G90: Servicio Nacional De Sanidad Y Calidad Agroalimentaria Senasa | H90: OC/2025/0121 | J90: -12421.99 | K90: -12421.99 | N90: Gastos Operativos (C) | O90: 1 | P90: 12421.99 | Q90: Unidad(es) | S90: OC 0001-00000985
B92: Publicado | C92: Pagado | D92: 45894 | E92: 45894 | F92: -342773.24 | G92: Administracion Provincial De Impuestos | H92: OC/2025/0120 | J92: -342773.24 | K92: -342773.24 | N92: SERVICIOS (C) | O92: 1 | P92: 342773.24 | Q92: Unidad(es)
B94: Publicado | C94: Pagado | D94: 45894 | E94: 45894 | F94: -4500000 | G94: Martinez, Marcelo Gregorio | H94: OC/2025/0118 | J94: -4500000 | K94: -4500000 | N94: SS de terceros (C) ALBAÑIL | O94: 1 | P94: 4500000 | Q94: Unidad(es)
B96: Publicado | C96: No pagadas | D96: 45894 | E96: 45894 | F96: -114000 | G96: La Delfina Sociedad Anonima Comercial Industrial Financiera Y Agropecuaria | H96: FA-A 00009-00021213 | J96: -137940 | K96: -137940 | L96: 137940 | N96: Alojamiento Capurro | O96: 1 | P96: 114000 | Q96: Unidad(es)
B99: Publicado | C99: No pagadas | D99: 45894 | E99: 45924 | F99: -381873.54 | G99: Agroceres Pic Argentina S A | H99: FA-A 00008-00137230 | J99: -462066.98 | K99: -462066.98 | L99: 462066.98 | N99: DOSIS AG1010 IU ABUELO VISTA | O99: 6 | P99: 63645.59 | Q99: Unidad(es)
B102: Publicado | C102: No pagadas | D102: 45894 | E102: 45924 | F102: -584967.53 | G102: Agroceres Pic Argentina S A | H102: FA-A 00008-00137202 | J102: -707810.71 | K102: -707810.71 | L102: 707810.71 | N102: DOSIS agpic337 ROY 1 | O102: 27 | P102: 8450.57 | Q102: Unidad(es)
N103: DOSIS agpic337IU roy I | O103: 38 | P103: 9389.53 | Q103: Unidad(es)
B107: Publicado | C107: No pagadas | D107: 45894 | E107: 45925 | F107: -27516738 | G107: Vetifarma S A | H107: FA-A 00004-00074070 | J107: -33295253 | K107: -33295253 | L107: 33295253 | N107: Tiamulina 10% | O107: 25 | P107: 10055.8 | Q107: Unidad(es)
N108: STARFEED LACTANCIA 4% REPRO | O108: 1000 | P108: 2246.8 | Q108: Unidad(es)
N109: STARFEED WEANING FASE 4 (6%) | O109: 2100 | P109: 3205.8 | Q109: Unidad(es)
N110: tiamulina 10% | O110: 25 | P110: 10055.8 | Q110: Unidad(es)
N111: MAXIMIX cerdas repc/fitasas | O111: 2015 | P111: 1274.1 | Q111: Unidad(es)
N112: CLORTETRACICLINA 20% | O112: 100 | P112: 11576.5 | Q112: Unidad(es)
N113: MYCOBINDER | O113: 50 | P113: 7302.1 | Q113: Unidad(es)
N114: ENERGY PROTEIN DRINK | O114: 9 | P114: 31016.8 | Q114: Unidad(es)
N115: FLORFENICOL 2% | O115: 250 | P115: 3973 | Q115: Unidad(es)
N116: ACIDO CITRICO | O116: 50 | P116: 2575.6 | Q116: Unidad(es)
N117: STARFEED FINISHING DESARROLLO | O117: 2600 | P117: 1972.8 | Q117: Unidad(es)
N118: STARFEED FINISHING TERMINACION | O118: 4400 | P118: 1685.1 | Q118: Unidad(es)
B132: Publicado | C132: No pagadas | D132: 45894 | E132: 45925 | F132: -7477460 | G132: Vetifarma S A | H132: FA-A 00004-00074069 | J132: -9047726.6 | K132: -9047726.6 | L132: 9047726.6 | N132: STARFEED WEANING FASE 4 (6%) | O132: 300 | P132: 1876.9 | Q132: Unidad(es)
N133: STARFEED FASE 1 | O133: 1550 | P133: 1835.8 | Q133: Unidad(es)
N134: STARFEED FASE 2 M | O134: 2750 | P134: 1479.6 | Q134: Unidad(es)
B139: Publicado | C139: No pagadas | D139: 45894 | E139: 45924 | F139: -3621800 | G139: Nutran S.R.L. | H139: FA-A 00002-00009757 | J139: -4382378 | K139: -4382378 | L139: 4382378 | N139: Fason(C) PREMIX CERDO DESARROLLO | O139: 2426 | P139: 350 | Q139: Unidad(es)
N140: Fason(C) PREMIX CERDO TERMINADOR MXX | O140: 1586 | P140: 350 | Q140: Unidad(es)
N141: Fason(C) PREMIX LACTANCIA | O141: 1024 | P141: 350 | Q141: Unidad(es)
N142: Fason(C) PREMIX FASE 4 | O142: 1101 | P142: 350 | Q142: Unidad(es)
N143: Fason(C) PREMIX GESTACION JAULA | O143: 1235 | P143: 350 | Q143: Unidad(es)
N144: Fason(C) TERMINADOR 2 | O144: 2976 | P144: 350 | Q144: Unidad(es)
B152: Publicado | C152: Pagado | D152: 45894 | E152: 45909 | F152: -37110.11 | G152: Comercial Uritorco S. R. L. | H152: FA-A 00001-00006079 | J152: -44903.23 | K152: -44903.23 | N152: taco metálico mr 10, alambre recorrido negro 17=1,42x r rollos, pluviómetro pvc 156 | O152: 1 | P152: 37110.11 | Q152: Unidad(es)
B155: Publicado | C155: Pagado | D155: 45894 | E155: 45894 | F155: -176269.65 | G155: Pascual Materiales S. R. L. | H155: FA-A 00001-00000306 | J155: -213286.28 | K155: -213286.28 | N155: 132 block m20 (hidroponía) | O155: 1 | P155: 176269.65 | Q155: Unidad(es)
B158: Publicado | C158: No pagadas | D158: 45891 | E158: 45951 | F158: -434593.38 | G158: Esperanza Distribuciones Srl | H158: FA-A 00026-00488575 | J158: -525857.99 | K158: -525857.99 | L158: 525857.99 | N158: desengrasante ramaj-gel raticida ultra blocks 1 kg | O158: 1 | P158: 434593.38 | Q158: Unidad(es)
B161: Publicado | C161: Pagado | D161: 45891 | E161: 45891 | F161: -310050 | G161: Nutrisan Granja S.R.L. | H161: FA-A 00005-00002354 | J161: -375160.5 | K161: -375160.5 | N161: Mantenimiento (C) lamparas infrared 250w | O161: 30 | P161: 10335 | Q161: Unidad(es)
B164: Publicado | C164: No pagadas | D164: 45890 | E164: 45940 | F164: -2446526 | G164: Drovet S A | H164: FA-A 00330-00174670 | J164: -2960296.5 | K164: -2960296.5 | L164: 2960296.5 | N164: Sanidad (C) gripork x 50ds | O164: 4 | P164: 49280 | Q164: Unidad(es)
N165: Sanidad (C) hipra suis glasser x 50 ds | O165: 54 | P165: 40989 | Q165: Unidad(es)
N166: Sanidad (C) servicio cadena frio | O166: 1 | P166: 36000 | Q166: Unidad(es)
B171: Publicado | C171: Pagado Parcialmente | D171: 45890 | E171: 45950 | F171: -644579.92 | G171: Esperanza Distribuciones Srl | H171: FA-A 00032-00100698 | J171: -779941.7 | K171: -779941.7 | L171: 462128.54 | N171: kobra curabic tulatromax oxitocina roborante ventabiotic aguja toallita desinfectaste guantes de tactos | O171: 1 | P171: 644579.92 | Q171: Unidad(es)
B174: Publicado | C174: No pagadas | D174: 45890 | E174: 45920 | F174: -338022.8 | G174: Agroceres Pic Argentina S A | H174: FA-A 00008-00136952 | J174: -409007.59 | K174: -409007.59 | L174: 409007.59 | N174: DOSIS agpic337 ROY 1 | O174: 40 | P174: 8450.57 | Q174: Unidad(es)
B177: Publicado | C177: Pagado | D177: 45890 | E177: 45890 | F177: -18843 | G177: Pascual Materiales S. R. L. | H177: FA-A 00001-00000300 | J177: -22800.03 | K177: -22800.03 | N177: BOL,SON DE ARENA (hidroponía pozo) | O177: 1 | P177: 18843 | Q177: Unidad(es)
B180: Publicado | C180: Pagado | D180: 45889 | E180: 45889 | F180: -27554.22 | G180: Servicio Nacional De Sanidad Y Calidad Agroalimentaria Senasa | H180: OC/2025/0117 | J180: -27554.22 | K180: -27554.22 | N180: Gastos Operativos (C) | O180: 1 | P180: 27554.22 | Q180: Unidad(es)
B182: Publicado | C182: No pagadas | D182: 45889 | E182: 45949 | F182: -3097534.6 | G182: Trt S.A. | H182: FA-A 00012-00530282 | J182: -3769699.6 | K182: -3769699.6 | L182: 3769699.6 | N182: overcox, overferr, metaxona, ,, , hoja para bisturi , hilo lino ,guante latex , guante latex desc, | O182: 1 | P182: 3097534.6 | Q182: Unidad(es)
B186: Publicado | C186: No pagadas | D186: 45889 | E186: 45903 | F186: -2951468 | G186: La Quinta Eventos S.R.L. | H186: FA-A 00005-00003378 | J186: -3571276.3 | K186: -3571276.3 | L186: 3571276.3 | N186: viandas primera quincena agosto | O186: 1 | P186: 2951468 | Q186: Unidad(es)
B189: Publicado | C189: No pagadas | D189: 45889 | E189: 45904 | F189: -3061085.8 | G189: Eliceche, Adrian Alberto | H189: FA-A 00002-00001742 | J189: -3703913.9 | K189: -3703913.9 | L189: 3703913.9 | N189: Honorarios profesionales correspondiente a los contratos nro 86493 y nro 86498 | O189: 1 | P189: 3061085.8 | Q189: Unidad(es)
B192: Publicado | C192: Pagado | D192: 45889 | E192: 45903 | F192: -26996.28 | G192: Comercial Uritorco S. R. L. | H192: FA-A 00001-00006023 | J192: -32665.5 | K192: -32665.5 | N192: candado sekur arco mediano nª 50 | O192: 1 | P192: 26996.28 | Q192: Unidad(es)
B195: Publicado | C195: Pagado | D195: 45888 | E195: 45888 | F195: -12421.99 | G195: Servicio Nacional De Sanidad Y Calidad Agroalimentaria Senasa | H195: OC/2025/0116 | J195: -12421.99 | K195: -12421.99 | N195: Gastos Operativos (C) | O195: 1 | P195: 12421.99 | Q195: Unidad(es)
B197: Publicado | C197: No pagadas | D197: 45888 | E197: 45888 | F197: -114000 | G197: La Delfina Sociedad Anonima Comercial Industrial Financiera Y Agropecuaria | H197: FA-A 00009-00021154 | J197: -137940 | K197: -137940 | L197: 137940 | N197: Alojamiento Capurro | O197: 1 | P197: 114000 | Q197: Unidad(es)
B200: Publicado | C200: Pagado | D200: 45887 | E200: 45887 | F200: -369.87 | G200: Servicio Nacional De Sanidad Y Calidad Agroalimentaria Senasa | H200: OC/2025/0115 | J200: -369.87 | K200: -369.87 | N200: Gastos Operativos (C) | O200: 1 | P200: 369.87 | Q200: Unidad(es)
B202: Publicado | C202: No pagadas | D202: 45887 | E202: 45917 | F202: -356802.14 | G202: Agroceres Pic Argentina S A | H202: FA-A 00008-00136751 | J202: -431730.59 | K202: -431730.59 | L202: 431730.59 | N202: DOSIS agpic337 ROY 1 | O202: 38 | P202: 9389.53 | Q202: Unidad(es)
B205: Publicado | C205: Pagado Parcialmente | D205: 45887 | E205: 45917 | F205: -5325522 | G205: Nutran S.R.L. | H205: FA-A 00002-00009746 | J205: -6443881.6 | K205: -6443881.6 | L205: 526478.96 | N205: Fason(C) PREMIX CERDO DESARROLLO | O205: 3034 | P205: 350 | Q205: Unidad(es)
N206: Fason(C) PREMIX CERDO TERMINADOR MXX | O206: 3112 | P206: 350 | Q206: Unidad(es)
N207: Fason(C) PREMIX CACHORRA 150 A 210 MXX | O207: 304 | P207: 350 | Q207: Unidad(es)
N208: Fason(C) PREMIX LACTANCIA | O208: 1103 | P208: 350 | Q208: Unidad(es)
N209: Fason(C) SERVICIO EMBOLSADO | O209: 594 | P209: 288 | Q209: Unidad(es)
N210: Fason(C) PREMIX FASE 3 STA | O210: 594 | P210: 350 | Q210: Unidad(es)
N211: Fason(C) PREMIX FASE 4 STA | O211: 1006 | P211: 350 | Q211: Unidad(es)
N212: Fason(C) PREMIX GESTACIONAL JAULA | O212: 1728 | P212: 350 | Q212: Unidad(es)
N213: Fason(C) PREMIX CERDO TERMINADOR 2 EXP | O213: 3846 | P213: 350 | Q213: Unidad(es)
B224: Publicado | C224: No pagadas | D224: 45884 | E224: 45914 | F224: -5571980.2 | G224: Vetifarma S A | H224: FA-A 00004-00073996 | J224: -6742096 | K224: -6742096 | L224: 6742096 | N224: STARFEED FASE 1 M | O224: 600 | P224: 1755.4 | Q224: Unidad(es)
N225: MAXIMIX CERDAS REP C/FITASAS | O225: 1054 | P225: 1218.3 | Q225: Unidad(es)
N226: STARFEED LACTANCIA 4% REPRO | O226: 220 | P226: 2148.4 | Q226: Unidad(es)
N227: STARFEED WEANING FASE 4 (6%) | O227: 500 | P227: 3065.4 | Q227: Unidad(es)
N228: MAXIMIX CTO Y TERM | O228: 570 | P228: 1205.2 | Q228: Unidad(es)
...

Sheet facturacion
A1: Asiento | B1: Partner | C1: Provincia de entrega | D1: Fecha de factura | E1: Producto | F1: Apunte contable/Líneas analíticas/Cuenta analítica | G1: Cantidad producto | H1: Precio unitario | I1: Total libre de impuestos | J1: Total (CC)
A2: LCDP-A 00009-00002010 | B2: Gapre S R L | C2: Santa Fe (AR) | D2: 45898 | E2: CERDAS | G2: 2081 | H2: 1330 | I2: 2767730 | J2: 3058341.6
A3: LCDP-A 00009-00002009 | B3: Gapre S R L | C3: Santa Fe (AR) | D3: 45898 | E3: PORCINOS | G3: 3446 | H3: 1822.26 | I3: 6279508 | J3: 6938856.3
A4: LCDP-A 00009-00002008 | B4: Gapre S R L | C4: Santa Fe (AR) | D4: 45897 | E4: PORCINOS | G4: 13142 | H4: 1838.41 | I4: 24160384 | J4: 26697225
A5: LCDP-A 00002-00000172 | B5: Gaspari, Leonardo Sergio | C5: Santa Fe (AR) | D5: 45897 | E5: PORCINOS | G5: 3324 | H5: 1330 | I5: 4420920 | J5: 4885116.6
A6: LCDP-A 00009-00002006 | B6: Gapre S R L | C6: Santa Fe (AR) | D6: 45895 | E6: PORCINOS | G6: 5433 | H6: 1890.56 | I6: 10271412 | J6: 11349911
A7: LCDP-A 00009-00002007 | B7: Gapre S R L | C7: Santa Fe (AR) | D7: 45895 | E7: PORCINOS | G7: 4004 | H7: 1876.27 | I7: 7512585.1 | J7: 8301406.5
A8: LCDP-A 00009-00002003 | B8: Gapre S R L | C8: Santa Fe (AR) | D8: 45894 | E8: PORCINOS | G8: 3358 | H8: 1891.51 | I8: 6351690.6 | J8: 7018618.1
A9: LCDP-A 00009-00002002 | B9: Gapre S R L | C9: Santa Fe (AR) | D9: 45894 | E9: CERDAS | G9: 1079 | H9: 1330 | I9: 1435070 | J9: 1585752.4
A10: LCDP-A 00009-00002001 | B10: Gapre S R L | C10: Santa Fe (AR) | D10: 45894 | E10: CERDAS | G10: 2403 | H10: 1330 | I10: 3195990 | J10: 3531569
A11: LCDP-A 00002-00000169 | B11: Gaspari, Leonardo Sergio | C11: Santa Fe (AR) | D11: 45890 | E11: PORCINOS | G11: 3090 | H11: 1450 | I11: 4480500 | J11: 4950952.5
A12: LCDP-A 00009-00002000 | B12: Gapre S R L | C12: Santa Fe (AR) | D12: 45890 | E12: PORCINOS | G12: 13908 | H12: 1798.36 | I12: 25011591 | J12: 27637808
A13: LCDP-A 00002-00000170 | B13: Gaspari, Leonardo Sergio | C13: Santa Fe (AR) | D13: 45890 | E13: PORCINOS | G13: 3831 | H13: 1550 | I13: 5938050 | J13: 6561545.2
... A32: LCDP-A 00009-00001981 | B32: Gapre S R L | C32: Santa Fe (AR) | D32: 45873 | E32: PORCINOS | G32: 10823 | H32: 1754.26 | I32: 18986356 | J32: 20979923

Sheet Vista_RUBRO
B2: TOTAL CALZIM
B3: VENTAS | C3: =SUM(venta_nico!F:F) -> 3.8425232e+08
B4: OPEX | C4: =D11 -> 3.3910724e+08
B5: UTILIDAD | C5: =C3-C4 -> 45145074
B6: CAPEX | C6: =SUMIFS(union_gastos!$D:$D,union_gastos!$J:$J,B6) -> 0
B7: DEUDA | C7: =SUMIFS(union_gastos!$D:$D,union_gastos!$J:$J,B7)*-1 -> 225721.37
B8: Flujo de Caja al Accionista | C8: =C5-C6-C7 -> 44919352
B11: OPEX | D11: =SUM(D12:D22) -> 3.3910724e+08
B12: 2 | C12: NUTRICIÓN | D12: =SUMIFS(union_gastos!$D:$D,union_gastos!$J:$J,"OPEX",union_gastos!$P:$P,Vista_RUBRO!C12)*-1 -> 2.0105721e+08 | E12: =D12/$D$11 -> 0.59290156
B13: 9 | C13: PERSONAL | D13: =SUMIFS(union_gastos!$D:$D,union_gastos!$J:$J,"OPEX",union_gastos!$P:$P,Vista_RUBRO!C13) -> 49609364 | E13: =D13/$D$11 -> 0.14629403
B14: 1 | C14: SANIDAD | D14: =SUMIFS(union_gastos!$D:$D,union_gastos!$J:$J,"OPEX",union_gastos!$P:$P,Vista_RUBRO!C14)*-1 -> 23353554 | E14: =D14/$D$11 -> 0.068867753
B15: 7 | C15: GENÉTICA | D15: =SUMIFS(union_gastos!$D:$D,union_gastos!$J:$J,"OPEX",union_gastos!$P:$P,Vista_RUBRO!C15)*-1 -> 8511805.7 | E15: =D15/$D$11 -> 0.025100631
B16: 10 | C16: FLETES | D16: =SUMIFS(union_gastos!$D:$D,union_gastos!$J:$J,"OPEX",union_gastos!$P:$P,Vista_RUBRO!C16)*-1 -> 6921200 | E16: =D16/$D$11 -> 0.020410062
B17: 3 | C17: ENERGÍA | D17: =SUMIFS(union_gastos!$D:$D,union_gastos!$J:$J,"OPEX",union_gastos!$P:$P,Vista_RUBRO!C17)*-1 -> 12284042 | E17: =D17/$D$11 -> 0.036224651
B18: 8 | C18: MANTENIMIENTO | D18: =SUMIFS(union_gastos!$D:$D,union_gastos!$J:$J,"OPEX",union_gastos!$P:$P,Vista_RUBRO!C18)*-1 -> 5755846.3 | E18: =D18/$D$11 -> 0.016973528
B19: 6 | C19: GASTOS OPERATIVOS | D19: =SUMIFS(union_gastos!$D:$D,union_gastos!$J:$J,"OPEX",union_gastos!$P:$P,Vista_RUBRO!C19)*-1 -> 23312174 | E19: =D19/$D$11 -> 0.068745728
B20: 5 | C20: IMPUESTOS | D20: =SUMIFS(union_gastos!$D:$D,union_gastos!$J:$J,"OPEX",union_gastos!$P:$P,Vista_RUBRO!C20)*-1 -> 6008871.6 | E20: =D20/$D$11 -> 0.017719679
B21: 11 | C21: HONORARIOS | D21: =SUMIFS(union_gastos!$D:$D,union_gastos!$J:$J,"OPEX",union_gastos!$P:$P,Vista_RUBRO!C21)*-1 -> 2293173.5 | E21: =D21/$D$11 -> 0.0067623844
C22: SERVICIOS | D22: =SUMIFS(union_gastos!$D:$D,union_gastos!$J:$J,"OPEX",union_gastos!$P:$P,Vista_RUBRO!C22)*-1 -> 0 | E22: =D22/$D$11 -> 0
B24: VENTAS POR FACTURAS | D24: =C3 -> 3.8425232e+08
B26: RESULTADO NETO | D26: =D22-D11 -> -3.3910724e+08
B27: MARGEN BRUTO | D27: =D29/D24 -> 0.1174881
B29: UTILDAD OPERATIVA | D29: =D24-D11 -> 45145074
B31: DEUDA | D31: =SUMIFS('BD Gastos_DICIEMBRE'!$V:$V,'BD Gastos_DICIEMBRE'!$Z:$Z,1,'BD Gastos_DICIEMBRE'!A:A,1) -> 0
B32: CAPEX | D32: =SUMIFS('BD Gastos_DICIEMBRE'!$V:$V,'BD Gastos_DICIEMBRE'!$AA:$AA,1,'BD Gastos_DICIEMBRE'!A:A,1) -> 0
B34: Flujo de Caja al Accionista | D34: =D29-D31-D32 -> 45145074

Sheet costos
A1: Asiento | B1: Partner | C1: Provincia de entrega | D1: Fecha de factura | E1: Producto | F1: Cantidad producto | G1: Precio unitario | H1: Total libre de impuestos | I1: Total (CC) | J1: Estado de factura
A2: FA-C 00001-00000366 | B2: Barrera, Adrian Jesus | C2: Santa Fe (AR) | D2: 45900 | E2: Gastos Operativos (C) | F2: -33 | G2: 3600 | H2: -118800 | I2: -118800 | J2: Abierto
A3: FA-A 00008-00137653 | B3: Agroceres Pic Argentina S A | C3: Ciudad Autónoma de Buenos Aires (AR) | D3: 45900 | E3: Genetica (C) | F3: -15 | G3: 9389.53 | H3: -140842.95 | I3: -170419.97 | J3: Abierto
A4: OC/2025/0128 | B4: Sueldos a pagar | D4: 45898 | F4: -1 | G4: 1459831.4 | H4: -1459831.4 | I4: -1459831.4 | J4: Abierto
A5: OC/2025/0130 | B5: Sueldos a pagar | D5: 45898 | F5: -1 | G5: 2137500 | H5: -2137500 | I5: -2137500 | J5: Abierto
A6: OC/2025/0129 | B6: Sueldos a pagar | D6: 45898 | F6: -1 | G6: 1754639 | H6: -1754639 | I6: -1754639 | J6: Abierto
A7: OC/2025/0126 | B7: Sueldos a pagar | D7: 45898 | F7: -1 | G7: 200000 | H7: -200000 | I7: -200000 | J7: Abierto
A8: FA-A 00001-00006197 | B8: Comercial Uritorco S. R. L. | C8: Santa Fe (AR) | D8: 45898 | E8: Reparaciones y repuestos (C) | F8: -1 | G8: 33265.9 | H8: -33265.9 | I8: -40251.74 | J8: Abierto
A9: FA-A 00001-00006197 | B9: Comercial Uritorco S. R. L. | C9: Santa Fe (AR) | D9: 45898 | E9: Reparaciones y repuestos (C) | F9: -1 | G9: 33265.9 | H9: -33265.9 | I9: -40251.74 | J9: Abierto
A10: FA-A 00001-00006198 | B10: Comercial Uritorco S. R. L. | C10: Santa Fe (AR) | D10: 45898 | E10: Reparaciones y repuestos (C) | F10: -1 | G10: 15580.8 | H10: -15580.8 | I10: -18852.77 | J10: Abierto
A11: FA-A 00001-00006198 | B11: Comercial Uritorco S. R. L. | C11: Santa Fe (AR) | D11: 45898 | E11: Reparaciones y repuestos (C) | F11: -1 | G11: 5193.6 | H11: -5193.6 | I11: -6284.26 | J11: Abierto
A12: OC/2025/0127 | B12: Sueldos a pagar | D12: 45898 | F12: -1 | G12: 1302502 | H12: -1302502 | I12: -1302502 | J12: Abierto
A13: FA-A 00001-00000311 | B13: Pascual Materiales S. R. L. | C13: Santa Fe (AR) | D13: 45898 | E13: Mantenimiento (C) | F13: -1 | G13: 1240 | H13: -1240 | I13: -1500.4 | J13: Abierto
A14: FA-A 00001-00000311 | B14: Pascual Materiales S. R. L. | C14: Santa Fe (AR) | D14: 45898 | E14: Mantenimiento (C) | F14: -8 | G14: 4463.04 | H14: -35704.32 | I14: -43202.23 | J14: Abierto
A15: OC/2025/0127 | B15: Sueldos a pagar | D15: 45898 | F15: -1 | J15: Abierto
A16: FA-A 00001-00000311 | B16: Pascual Materiales S. R. L. | C16: Santa Fe (AR) | D16: 45898 | E16: Mantenimiento (C) | F16: -12 | G16: 4463.04 | H16: -53556.48 | I16: -64803.34 | J16: Abierto
A17: OC/2025/0131 | B17: Sueldos a pagar | D17: 45898 | F17: -1 | G17: 2479500 | H17: -2479500 | I17: -2479500 | J17: Abierto
A18: FA-A 00011-00027677 | B18: Topigs Norsvin Argentina S.R.L. | C18: Ciudad Autónoma de Buenos Aires (AR) | D18: 45897 | E18: Genetica (C) | F18: -1 | G18: 11172374 | H18: -11172374 | I18: -12345474 | J18: Abierto
A19: FA-C 00001-00000305 | B19: Forconi, Marcos Roman | C19: Santa Fe (AR) | D19: 45897 | E19: SS de terceros (C) | F19: -1 | G19: 4500 | H19: -4500 | I19: -4500 | J19: Abierto
A20: FA-C 00001-00000290 | B20: Forconi, Marcos Roman | C20: Santa Fe (AR) | D20: 45897 | E20: SS de terceros (C) | F20: -1 | G20: 57999 | H20: -57999 | I20: -57999 | J20: Abierto
A21: OC/2025/0125 | B21: ARCA | D21: 45897 | F21: -1 | G21: 190449.86 | H21: -190449.86 | I21: -190449.86 | J21: Abierto
A22: OC/2025/0124 | B22: Servicio Nacional De Sanidad Y Calidad Agroalimentaria Senasa | C22: Ciudad Autónoma de Buenos Aires (AR) | D22: 45896 | E22: Gastos Operativos (C) | F22: -1 | G22: 10539.86 | H22: -10539.86 | I22: -10539.86 | J22: Abierto
A23: FA-A 00003-00000285 | B23: Arrieta, Fernando Gabriel | C23: Santa Fe (AR) | D23: 45896 | E23: Fletes (C) | F23: -1 | G23: 495000 | H23: -495000 | I23: -598950 | J23: Abierto
A24: FA-A 00003-00000285 | B24: Arrieta, Fernando Gabriel | C24: Santa Fe (AR) | D24: 45896 | E24: Fletes (C) | F24: -1 | G24: 415000 | H24: -415000 | I24: -502150 | J24: Abierto
A25: FA-A 00003-00000285 | B25: Arrieta, Fernando Gabriel | C25: Santa Fe (AR) | D25: 45896 | E25: Fletes (C) | F25: -1 | G25: 415000 | H25: -415000 | I25: -502150 | J25: Abierto
A26: FA-A 00003-00000285 | B26: Arrieta, Fernando Gabriel | C26: Santa Fe (AR) | D26: 45896 | E26: Fletes (C) | F26: -1 | G26: 495000 | H26: -495000 | I26: -598950 | J26: Abierto
A27: FA-A 00003-00000285 | B27: Arrieta, Fernando Gabriel | C27: Santa Fe (AR) | D27: 45896 | E27: Fletes (C) | F27: -1 | G27: 415000 | H27: -415000 | I27: -502150 | J27: Abierto
A28: FA-A 00003-00000285 | B28: Arrieta, Fernando Gabriel | C28: Santa Fe (AR) | D28: 45896 | E28: Fletes (C) | F28: -1 | G28: 415000 | H28: -415000 | I28: -502150 | J28: Abierto
A29: OC/2025/0123 | B29: Sueldos a pagar | D29: 45896 | F29: -1 | G29: 1500000 | H29: -1500000 | I29: -1500000 | J29: Abierto
A30: NC-A 00011-00010896 (Reversión de: FA-A 00011-00050785) | B30: Rosario Agro Industrial Srl | C30: Santa Fe (AR) | D30: 45896 | E30: Mantenimiento (C) | F30: 1 | G30: 72865 | H30: 72865 | I30: 88166.65 | J30: Abierto
A31: FA-A 00001-00000309 | B31: Pascual Materiales S. R. L. | C31: Santa Fe (AR) | D31: 45896 | E31: Mantenimiento (C) | F31: -1 | G31: 36323.98 | H31: -36323.98 | I31: -43952.02 | J31: Abierto
A32: FA-A 00001-00006140 | B32: Comercial Uritorco S. R. L. | C32: Santa Fe (AR) | D32: 45896 | E32: Reparaciones y repuestos (C) | F32: -1 | G32: 21409.9 | H32: -21409.9 | I32: -25905.98 | J32: Abierto
A33: FA-A 00001-00000639 | B33: Comercial Uritorco S. R. L. | C33: Santa Fe (AR) | D33: 45896 | E33: Reparaciones y repuestos (C) | F33: -1 | G33: 14355.27 | H33: -14355.27 | I33: -17369.88 | J33: Abierto
A34: FA-A 00026-00489583 | B34: Esperanza Distribuciones Srl | C34: Santa Fe (AR) | D34: 45896 | E34: Sanidad (C) | F34: -1 | G34: 1200 | H34: -1200 | I34: -1452 | J34: Abierto
A35: FA-A 00003-00000285 | B35: Arrieta, Fernando Gabriel | C35: Santa Fe (AR) | D35: 45896 | E35: Fletes (C) | F35: -1 | G35: 287500 | H35: -287500 | I35: -347875 | J35: Abierto
A36: FA-A 00003-00000285 | B36: Arrieta, Fernando Gabriel | C36: Santa Fe (AR) | D36: 45896 | E36: Fletes (C) | F36: -1 | G36: 415000 | H36: -415000 | I36: -502150 | J36: Abierto
A37: FA-A 00001-00000308 | B37: Pascual Materiales S. R. L. | C37: Santa Fe (AR) | D37: 45895 | E37: Mantenimiento (C) | F37: -1 | G37: 266479.34 | H37: -266479.34 | I37: -322440 | J37: Abierto
A38: OC/2025/0122 | B38: Servicio Nacional De Sanidad Y Calidad Agroalimentaria Senasa | C38: Ciudad Autónoma de Buenos Aires (AR) | D38: 45895 | E38: Gastos Operativos (C) | F38: -1 | G38: 15711.62 | H38: -15711.62 | I38: -15711.62 | J38: Abierto
A39: FA-A 00001-00006079 | B39: Comercial Uritorco S. R. L. | C39: Santa Fe (AR) | D39: 45894 | E39: Reparaciones y repuestos (C) | F39: -1 | G39: 37110.11 | H39: -37110.11 | I39: -44903.23 | J39: Abierto
A40: FA-A 00001-00000306 | B40: Pascual Materiales S. R. L. | C40: Santa Fe (AR) | D40: 45894 | E40: Mantenimiento (C) | F40: -1 | G40: 176269.65 | H40: -176269.65 | I40: -213286.28 | J40: Abierto
A41: FA-A 00009-00021213 | B41: La Delfina Sociedad Anonima Comercial Industrial Financiera Y Agropecuaria | C41: Santa Fe (AR) | D41: 45894 | E41: Gastos Operativos (C) | F41: -1 | G41: 114000 | H41: -114000 | I41: -137940 | J41: Abierto
... A101: FA-A 00004-00073996 | B101: Vetifarma S A | C101: Buenos Aires (AR) | D101: 45884 | E101: Alimento para Animales (C) | F101: -450 | G101: 1205.2 | H101: -542340 | I101: -656231.4 | J101: Abierto
A102: OC/2025/0113 | B102: ARCA | D102: 45883 | F102: -1 | G102: 1965214.3 | H102: -1965214.3 | I102: -1965214.3 | J102: Abierto
A103: OC/2025/0112 | B103: ARCA | D103: 45883 | F103: -1 | G103: 2827302.5 | H103: -2827302.5 | I103: -2827302.5 | J103: Abierto
A104: OC/2025/0114 | B104: ARCA | D104: 45883 | F104: -1 | G104: 2650283.6 | H104: -2650283.6 | I104: -2650283.6 | J104: Abierto
A105: OC/2025/0111 | B105: ARCA | D105: 45883 | F105: -1 | G105: 598371.58 | H105: -598371.58 | I105: -598371.58 | J105: Abierto
A106: OC/2025/0110 | B106: Servicio Nacional De Sanidad Y Calidad Agroalimentaria Senasa | C106: Ciudad Autónoma de Buenos Aires (AR) | D106: 45882 | E106: Gastos Operativos (C) | F106: -1 | G106: 15940.74 | H106: -15940.74 | I106: -15940.74 | J106: Abierto
A107: FA-A 00001-00000292 | B107: Pascual Materiales S. R. L. | C107: Santa Fe (AR) | D107: 45881 | E107: Mantenimiento (C) | F107: -1 | G107: 499217.77 | H107: -499217.77 | I107: -604053.5 | J107: Abierto
A108: OC/2025/0109 | B108: Servicio Nacional De Sanidad Y Calidad Agroalimentaria Senasa | C108: Ciudad Autónoma de Buenos Aires (AR) | D108: 45881 | E108: Gastos Operativos (C) | F108: -1 | G108: 11014.49 | H108: -11014.49 | I108: -11014.49 | J108: Abierto
A109: FA-A 00002-00003941 | B109: Bordalt Ivan Y Carpinetti Barbara Ss | C109: Santa Fe (AR) | D109: 45881 | E109: Articulos de limpieza (C) | F109: -1 | G109: 43041.35 | H109: -43041.35 | I109: -52080.03 | J109: Abierto
A110: FA-A 00001-00005926 | B110: Comercial Uritorco S. R. L. | C110: Santa Fe (AR) | D110: 45880 | E110: Reparaciones y repuestos (C) | F110: -1 | G110: 132070.36 | H110: -132070.36 | I110: -159805.14 | J110: Abierto
A111: FA-A 00001-00005926 | B111: Comercial Uritorco S. R. L. | C111: Santa Fe (AR) | D111: 45880 | E111: Reparaciones y repuestos (C) | F111: -1 | G111: 6300 | H111: -6300 | I111: -6961.5 | J111: Abierto
A112: FA-A 00008-00136293 | B112: Agroceres Pic Argentina S A | C112: Ciudad Autónoma de Buenos Aires (AR) | D112: 45880 | E112: Genetica (C) | F112: -39 | G112: 8450.57 | H112: -329572.23 | I112: -398782.4 | J112: Abierto
A113: FA-A 00008-00136293 | B113: Agroceres Pic Argentina S A | C113: Ciudad Autónoma de Buenos Aires (AR) | D113: 45880 | E113: Genetica (C) | F113: -20 | G113: 9389.53 | H113: -187790.6 | I113: -227226.63 | J113: Abierto
A114: FA-A 00330-00172625 | B114: Drovet S A | C114: Santa Fe (AR) | D114: 45880 | E114: Sanidad (C) | F114: -26 | G114: 61617.19 | H114: -1602046.9 | I114: -1938476.8 | J114: Abierto
A115: FA-A 00330-00172625 | B115: Drovet S A | C115: Santa Fe (AR) | D115: 45880 | E115: Sanidad (C) | F115: -32 | G115: 30747.73 | H115: -983927.36 | I115: -1190552.1 | J115: Abierto
A116: FA-A 00330-00172625 | B116: Drovet S A | C116: Santa Fe (AR) | D116: 45880 | E116: Sanidad (C) | F116: -9 | G116: 32590.07 | H116: -293310.63 | I116: -354905.86 | J116: Abierto
A117: OC/2025/0107 | B117: Sueldos a pagar | D117: 45880 | F117: -1 | G117: 6581093 | H117: -6581093 | I117: -6581093 | J117: Abierto
A118: OC/2025/0108 | B118: Servicio Nacional De Sanidad Y Calidad Agroalimentaria Senasa | C118: Ciudad Autónoma de Buenos Aires (AR) | D118: 45880 | E118: Gastos Operativos (C) | F118: -1 | G118: 12421.99 | H118: -12421.99 | I118: -12421.99 | J118: Abierto
A119: FA-A 00330-00172589 | B119: Drovet S A | C119: Santa Fe (AR) | D119: 45880 | E119: Sanidad (C) | F119: -1 | G119: 2419722.6 | H119: -2419722.6 | I119: -2927864.4 | J119: Abierto
A120: FA-A 00004-00019973 | B120: Agroceres Pic Argentina S A | C120: Ciudad Autónoma de Buenos Aires (AR) | D120: 45880 | E120: Genetica (C) | F120: -1 | G120: 1879407 | H120: -1879407 | I120: -2274082.5 | J120: Abierto
A121: FA-A 00009-00210769 | B121: La Delfina Sociedad Anonima Comercial Industrial Financiera Y Agropecuaria | C121: Santa Fe (AR) | D121: 45880 | E121: Gastos Operativos (C) | F121: -1 | G121: 114000 | H121: -114000 | I121: -137940 | J121: Abierto
A122: FA-A 00008-00136322 | B122: Agroceres Pic Argentina S A | C122: Ciudad Autónoma de Buenos Aires (AR) | D122: 45880 | E122: Genetica (C) | F122: -6 | G122: 63645.59 | H122: -381873.54 | I122: -462066.98 | J122: Abierto
A123: FA-A 00005-00089191 | B123: Establecimiento Do#A Teresa S R L | C123: Santa Fe (AR) | D123: 45880 | E123: Alquiler (C) | F123: -1 | G123: 4269240 | H123: -4269240 | I123: -4269240 | J123: Abierto
A124: FA-A 00004-00019972 | B124: Agroceres Pic Argentina S A | C124: Ciudad Autónoma de Buenos Aires (AR) | D124: 45880 | E124: Genetica (C) | F124: -1 | G124: 1853644.6 | H124: -1853644.6 | I124: -2242909.9 | J124: Abierto
A125: FA-A 00003-00000046 | B125: Rojas, Juan Manuel | C125: Santa Fe (AR) | D125: 45878 | E125: Honorarios Veterinario (C) | F125: -1 | G125: 2300000 | H125: -2300000 | I125: -2783000 | J125: Abierto
A126: FA-A 00002-00009721 | B126: Nutran S.R.L. | C126: Santa Fe (AR) | D126: 45878 | E126: Fason(C) | F126: -1 | G126: 3711050 | H126: -3711050 | I126: -4490370.5 | J126: Abierto
A127: OC/2025/0106 | B127: Sueldos a pagar | D127: 45877 | F127: -1 | G127: 373517 | H127: -373517 | I127: -373517 | J127: Abierto
A128: FA-A 00001-00000303 | B128: Bongiovanni, Juan Pablo | C128: Santa Fe (AR) | D128: 45877 | E128: Mantenimiento e Instalaciones (C) | F128: -1 | G128: 179250 | H128: -179250 | I128: -216892.5 | J128: Abierto
A129: OC/2025/0104 | B129: Sueldos a pagar | D129: 45877 | F129: -1 | G129: 856116 | H129: -856116 | I129: -856116 | J129: Abierto
A130: OC/2025/0105 | B130: Sueldos a pagar | D130: 45877 | F130: -1 | G130: 515224 | H130: -515224 | I130: -515224 | J130: Abierto
A131: FA-C 00003-00001726 | B131: Chiminello, Vanina | C131: Buenos Aires (AR) | D131: 45876 | E131: Honorarios Veterinario (C) | F131: -1 | G131: 349000 | H131: -349000 | I131: -349000 | J131: Abierto
A132: NC-A 00002-00000274 (Reversión de: FA-A 00002-00007631) | B132: Alvarez, Maria Milagros | C132: Santa Fe (AR) | D132: 45876 | E132: Reparaciones y repuestos (C) | F132: 1 | G132: 121880.22 | H132: 121880.22 | I132: 147475.07 | J132: Abierto
A133: FA-A 00008-00136043 | B133: Agroceres Pic Argentina S A | C133: Ciudad Autónoma de Buenos Aires (AR) | D133: 45876 | E133: Genetica (C) | F133: -48 | G133: 9389.53 | H133: -450697.44 | I133: -545343.9 | J133: Abierto
A134: FA-A 00008-00136043 | B134: Agroceres Pic Argentina S A | C134: Ciudad Autónoma de Buenos Aires (AR) | D134: 45876 | E134: Genetica (C) | F134: -36 | G134: 8450.57 | H134: -304220.52 | I134: -368106.83 | J134: Abierto
A135: OC/2025/0103 | B135: Servicio Nacional De Sanidad Y Calidad Agroalimentaria Senasa | C135: Ciudad Autónoma de Buenos Aires (AR) | D135: 45875 | E135: Gastos Operativos (C) | F135: -1 | G135: 15940.74 | H135: -15940.74 | I135: -15940.74 | J135: Abierto
A136: FA-C 00001-00000012 | B136: Matteo, Marcelo Mario | C136: Santa Fe (AR) | D136: 45875 | E136: SS de terceros (C) | F136: -1 | G136: 1819116 | H136: -1819116 | I136: -1819116 | J136: Abierto
A137: FA-A 00002-00006667 | B137: Bater S.R.L. | C137: Santa Fe (AR) | D137: 45874 | E137: Alquiler (C) | F137: -1 | G137: 89000 | H137: -89000 | I137: -107690 | J137: Abierto
A138: OC/2025/0102 | B138: Servicio Nacional De Sanidad Y Calidad Agroalimentaria Senasa | C138: Ciudad Autónoma de Buenos Aires (AR) | D138: 45874 | E138: Gastos Operativos (C) | F138: -1 | G138: 9976.86 | H138: -9976.86 | I138: -9976.86 | J138: Abierto
A139: FA-A 00003-00000251 | B139: Arrieta, Fernando Gabriel | C139: Santa Fe (AR) | D139: 45873 | E139: Fletes (C) | F139: -1 | G139: 415000 | H139: -415000 | I139: -502150 | J139: Abierto
A140: FA-A 00003-00000251 | B140: Arrieta, Fernando Gabriel | C140: Santa Fe (AR) | D140: 45873 | E140: Fletes (C) | F140: -1 | G140: 415000 | H140: -415000 | I140: -502150 | J140: Abierto
A141: FA-A 00003-00000251 | B141: Arrieta, Fernando Gabriel | C141: Santa Fe (AR) | D141: 45873 | E141: Fletes (C) | F141: -1 | G141: 495000 | H141: -495000 | I141: -598950 | J141: Abierto
A142: FA-A 00003-00000251 | B142: Arrieta, Fernando Gabriel | C142: Santa Fe (AR) | D142: 45873 | E142: Fletes (C) | F142: -1 | G142: 495000 | H142: -495000 | I142: -598950 | J142: Abierto
... A156: FA-C 00001-00000011 | B156: Donda, Ruben Estelio | C156: Santa Fe (AR) | D156: 45870 | E156: SS de terceros (C) | F156: -1 | G156: 1500000 | H156: -1500000 | I156: -1500000 | J156: Abierto
B157: Vagnoni | E157: Rollos | F157: -100 | G157: 45000 | H157: -4500000 | I157: -4500000

Sheet BBDD_PROVEEDORES_FINAL
A1: ID | B1: PROVEEDOR | C1: CANAL | D1: CONCEPTO | E1: TIPO 1 (DIRECTO/INDIRECTO) | F1: TIPO 2 (FIJO/VARIABLE) | G1: RUBRO | H1: AREA | I1: UN | J1: CUIT | K1: ESTADO | L1: METODO_DE_PAGO | M1: CUIT2 | N1: Nombre Fantasia | O1: Teléfono | P1: Mail | Q1: Contacto | R1: Direccion | S1: Observaciones | T1: Canal de pago | U1: ESTADO2 | V1: PDP | W1: INTERESES MORATORIO MENSUAL | X1: Total_con_signo_2025 | Y1: Crédito máximo asignado | Z1: Base Aine
A2: 30684082627 | B2: Vetifarma S A | C2: 1 | D2: OPEX | E2: DIRECTO | F2: VARIABLE | H2: PORCINOS | I2: GRAL | J2: 30684082627 | K2: ACTIVO | L2: TRANSF | M2: 30684082627 | N2: Vetifarma S A | O2: +54 9 221 617-6065 | P2: vetifarma@vetifarma.com.ar | T2: 1 | U2: ACTIVO | V2: 2 | W2: 0 | X2: 1.3358374e+09 | Y2: 46900000
A3: 30707140514 | B3: Nutran S.R.L. | C3: 1 | D3: OPEX | E3: DIRECTO | F3: VARIABLE | H3: PORCINOS | I3: GRAL | J3: 30707140514 | K3: ACTIVO | L3: TRANSF | M3: 30707140514 | N3: Nutran S.R.L. | O3: +54 9 3469 69-3367 | P3: nutransrl@gmail.com | T3: 1 | U3: ACTIVO | V3: 2 | W3: 0 | X3: 6.3956659e+08 | Y3: 12400000
A4: 30716107309 | B4: Agroindustrial Cosanic S.R.L. | C4: 1 | D4: OPEX | E4: INDIRECTO | F4: VARIABLE | H4: PORCINOS | I4: GRAL | J4: 30716107309 | K4: ACTIVO | L4: TRANSF | M4: 30716107309 | N4: Agroindustrial Cosanic S.R.L. | O4: +54 9 2266 46-4650 | P4: admin1.agroindustrial@grupocosanic.com | T4: 1 | U4: ACTIVO | V4: 2 | W4: 0 | X4: 5.4080364e+08 | Y4: 54100000
A5: 30586988359 | B5: Drovet S A | C5: 1 | D5: OPEX | E5: DIRECTO | F5: VARIABLE | H5: PORCINOS | I5: GRAL | J5: 30586988359 | K5: ACTIVO | L5: TRANSF | M5: 30586988359 | N5: Drovet S A | O5: +54 9 341 311-8981 | T5: 1 | U5: ACTIVO | V5: 2 | W5: 0 | X5: 4.4233435e+08 | Y5: 4100000
A6: a_000006 | B6: Sueldos a pagar | C6: 1 | D6: OPEX | E6: DIRECTO | F6: FIJO | H6: PORCINOS | I6: GRAL | K6: ACTIVO | L6: TRANSF | N6: Sueldos a pagar | T6: 1 | U6: ACTIVO | V6: 1 | W6: 0 | X6: 4.1250728e+08 | Y6: 11500000
A7: 30663202657 | B7: Agroceres Pic Argentina S A | C7: 1 | D7: OPEX | E7: DIRECTO | F7: VARIABLE | H7: PORCINOS | I7: GRAL | J7: 30663202657 | K7: ACTIVO | L7: TRANSF | M7: 30663202657 | N7: Agroceres Pic Argentina S A | O7: +54 11 6658-6406 | P7: administracion@agroceres.com. | T7: 1 | U7: ACTIVO | V7: 2 | W7: 0 | X7: 2.9507223e+08 | Y7: 3100000
A8: 23175073779 | B8: Arrieta, Fernando Gabriel | C8: 1 | D8: OPEX | E8: DIRECTO | F8: VARIABLE | H8: PORCINOS | I8: GRAL | J8: 23175073779 | K8: ACTIVO | L8: TRANSF | M8: 23175073779 | N8: Arrieta, Fernando Gabriel | O8: +54 9 3402 65-9154 | T8: 1 | U8: ACTIVO | V8: 2 | W8: 0 | X8: 2.6441406e+08 | Y8: 9800000
A9: a_000079 | B9: Sueldos ok | C9: 1 | D9: OPEX | E9: INDIRECTO | F9: FIJO | H9: PORCINOS | I9: GRAL | K9: ACTIVO | L9: TRANSF | N9: Sueldos ok | T9: 1 | U9: ACTIVO | V9: 1 | W9: 0 | X9: 222416675 | Y9: 74100000
A10: 20305330516 | B10: Colella, Santiago Nicolas | C10: 1 | D10: OPEX | E10: INDIRECTO | F10: VARIABLE | H10: PORCINOS | I10: GRAL | J10: 20305330516 | K10: ACTIVO | L10: TRANSF | M10: 20305330516 | N10: Colella, Santiago Nicolas | T10: 1 | U10: ACTIVO | V10: 2 | W10: 0 | X10: 155685895 | Y10: 51900000
A11: 30713986808 | B11: La Quinta Eventos S.R.L. | C11: 1 | D11: OPEX | E11: DIRECTO | F11: VARIABLE | H11: PORCINOS | I11: GRAL | J11: 30713986808 | K11: ACTIVO | L11: TRANSF | M11: 30713986808 | N11: La Quinta Eventos S.R.L. | O11: +54 9 3402 50-5858 | T11: 1 | U11: ACTIVO | V11: 3 | W11: 0 | X11: 1.3675182e+08 | Y11: 6500000
A12: 30714259012 | B12: SAN AGUSTIN CEREALES | C12: 1 | D12: OPEX | E12: DIRECTO | F12: VARIABLE | H12: PORCINOS | I12: GRAL | J12: 30714259012 | K12: ACTIVO | L12: TRANSF | M12: 30714259012 | N12: SAN AGUSTIN CEREALES | T12: 1 | U12: ACTIVO | V12: 2 | W12: 0 | X12: 1.1006013e+08 | Y12: 110100000
A13: 30545788167 | B13: Empresa Provincial De La Energia De Santa Fe | C13: 1 | D13: OPEX | E13: DIRECTO | F13: VARIABLE | H13: PORCINOS | I13: GRAL | J13: 30545788167 | K13: ACTIVO | L13: TRANSF | M13: 30545788167 | N13: Empresa Provincial De La Energia De Santa Fe | T13: 1 | U13: ACTIVO | V13: 2 | W13: 0 | X13: 1.0926222e+08 | Y13: 7300000
A14: 30710882564 | B14: Topigs Norsvin Argentina S.R.L. | C14: 1 | D14: OPEX | E14: DIRECTO | F14: VARIABLE | H14: PORCINOS | I14: GRAL | J14: 30710882564 | K14: ACTIVO | L14: TRANSF | M14: 30710882564 | N14: Topigs Norsvin Argentina S.R.L. | T14: 1 | U14: ACTIVO | V14: 2 | W14: 0 | X14: 99028637 | Y14: 19800000
A15: 30709181714 | B15: Jacycec S.R.L. | C15: 1 | D15: OPEX | E15: INDIRECTO | F15: VARIABLE | H15: PORCINOS | I15: GRAL | J15: 30709181714 | K15: ACTIVO | L15: TRANSF | M15: 30709181714 | N15: Jacycec S.R.L. | T15: 1 | U15: ACTIVO | V15: 2 | W15: 0 | X15: 89096426 | Y15: 17800000
A16: 30708982713 | B16: Los Rolleros S. R. L. | C16: 1 | D16: OPEX | E16: INDIRECTO | F16: VARIABLE | H16: PORCINOS | I16: GRAL | J16: 30708982713 | K16: ACTIVO | L16: TRANSF | M16: 30708982713 | N16: Los Rolleros S. R. L. | T16: 1 | U16: ACTIVO | V16: 2 | W16: 0 | X16: 65096730 | Y16: 13000000
A17: 30619484807 | B17: Esperanza Distribuciones Srl | C17: 1 | D17: OPEX | E17: INDIRECTO | F17: VARIABLE | H17: PORCINOS | I17: GRAL | J17: 30619484807 | K17: ACTIVO | L17: TRANSF | M17: 30619484807 | N17: Esperanza Distribuciones Srl | O17: +54 9 3496 57-7789 | T17: 1 | U17: ACTIVO | V17: 2 | W17: 0 | X17: 54410645 | Y17: 2000000
A18: 20247725238 | B18: Rojas, Juan Manuel | C18: 1 | D18: OPEX | E18: INDIRECTO | F18: VARIABLE | H18: PORCINOS | I18: GRAL | J18: 20247725238 | K18: ACTIVO | L18: TRANSF | M18: 20247725238 | N18: Rojas, Juan Manuel | O18: +54 9 341 687-3022 | T18: 1 | U18: ACTIVO | V18: 2 | W18: 0 | X18: 45556500 | Y18: 4600000
A19: 27059351899 | B19: Sacco, Alicia Iris | C19: 1 | D19: OPEX | E19: INDIRECTO | F19: VARIABLE | H19: PORCINOS | I19: GRAL | J19: 27059351899 | K19: ACTIVO | L19: TRANSF | M19: 27059351899 | N19: Sacco, Alicia Iris | T19: 1 | U19: ACTIVO | V19: 3 | W19: 0 | X19: 42275888 | Y19: 84600000
A20: 30711239991 | B20: Tfin Sa | C20: 1 | D20: OPEX | E20: INDIRECTO | F20: VARIABLE | H20: PORCINOS | I20: GRAL | J20: 30711239991 | K20: ACTIVO | L20: TRANSF | M20: 30711239991 | N20: Tfin Sa | P20: franciscoa@tfinancial.com.ar | T20: 1 | U20: ACTIVO | V20: 1 | W20: 0 | X20: 40384888 | Y20: 3200000
A21: 30622309730 | B21: Rosario Insumos Agropecuarios Sa | C21: 1 | D21: OPEX | E21: INDIRECTO | F21: VARIABLE | H21: PORCINOS | I21: GRAL | J21: 30622309730 | K21: ACTIVO | L21: TRANSF | M21: 30622309730 | N21: Rosario Insumos Agropecuarios Sa | T21: 1 | U21: ACTIVO | V21: 3 | W21: 0 | X21: 36686441 | Y21: 10500000
A22: 30685484303 | B22: Establecimiento Do#A Teresa S R L | C22: 1 | D22: OPEX | E22: INDIRECTO | F22: VARIABLE | H22: PORCINOS | I22: GRAL | J22: 30685484303 | K22: ACTIVO | L22: TRANSF | M22: 30685484303 | N22: Establecimiento Do#A Teresa S R L | T22: 1 | U22: ACTIVO | V22: 3 | W22: 0 | X22: 35956055 | Y22: 6500000
A23: 20241865070 | B23: Eliceche, Adrian Alberto | C23: 1 | D23: OPEX | E23: INDIRECTO | F23: VARIABLE | H23: PORCINOS | I23: GRAL | J23: 20241865070 | K23: ACTIVO | L23: TRANSF | M23: 20241865070 | N23: Eliceche, Adrian Alberto | T23: 1 | U23: ACTIVO | V23: 3 | W23: 0 | X23: 33946281 | Y23: 8500000
A24: 30717713431 | B24: Don Vitto Wa-La S.A.S. | C24: 1 | D24: OPEX | E24: INDIRECTO | F24: VARIABLE | H24: PORCINOS | I24: GRAL | J24: 30717713431 | K24: ACTIVO | L24: TRANSF | M24: 30717713431 | N24: Don Vitto Wa-La S.A.S. | T24: 1 | U24: ACTIVO | V24: 3 | W24: 0 | X24: 31000000 | Y24: 31000000
A25: 20227667592 | B25: D Angela, Sergio | C25: 1 | D25: OPEX | E25: INDIRECTO | F25: VARIABLE | H25: PORCINOS | I25: GRAL | J25: 20227667592 | K25: ACTIVO | L25: TRANSF | M25: 20227667592 | N25: D Angela, Sergio | O25: +54 9 341 505-5497 | T25: 1 | U25: ACTIVO | V25: 3 | W25: 0 | X25: 30748919 | Y25: 7700000
A26: 30718209222 | B26: Grupo Nodo Gestion Ambiental S.R.L. | C26: 1 | D26: OPEX | E26: INDIRECTO | F26: VARIABLE | H26: PORCINOS | I26: GRAL | J26: 30718209222 | K26: ACTIVO | L26: TRANSF | M26: 30718209222 | N26: Grupo Nodo Gestion Ambiental S.R.L. | O26: +54 9 221 643-0789 | T26: 1 | U26: ACTIVO | V26: 3 | W26: 0 | X26: 29678727 | Y26: 3100000
A27: 30716299852 | B27: Special Commodity Srl | C27: 1 | D27: OPEX | E27: INDIRECTO | F27: VARIABLE | H27: PORCINOS | I27: GRAL | J27: 30716299852 | K27: ACTIVO | L27: TRANSF | M27: 30716299852 | N27: Special Commodity Srl | T27: 1 | U27: ACTIVO | V27: 3 | W27: 0 | X27: 28881955 | Y27: 28900000
A28: 30500049460 | B28: Sancor Cooperativa De Seguros Limitada | C28: 1 | D28: OPEX | E28: INDIRECTO | F28: VARIABLE | H28: PORCINOS | I28: GRAL | J28: 30500049460 | K28: ACTIVO | L28: TRANSF | M28: 30500049460 | N28: Sancor Cooperativa De Seguros Limitada | O28: +54 3462 55-5654 | T28: 1 | U28: ACTIVO | V28: 3 | W28: 0 | X28: 26306820 | Y28: 52600000
A29: 30500049460 | B29: Sancor Cooperativa De Seguros Limitada | C29: 1 | D29: OPEX | E29: INDIRECTO | F29: VARIABLE | H29: PORCINOS | I29: GRAL | J29: 30500049460 | K29: ACTIVO | L29: TRANSF | M29: 30500049460 | N29: Sancor Cooperativa De Seguros Limitada | O29: +54 3462 55-5654 | T29: 1 | U29: ACTIVO | V29: 3 | W29: 0 | X29: 26306820 | Y29: 52600000
A30: 33715110909 | B30: Estudio De Profesionales Sa | C30: 1 | D30: OPEX | E30: INDIRECTO | F30: VARIABLE | H30: PORCINOS | I30: GRAL | J30: 33715110909 | K30: ACTIVO | L30: TRANSF | M30: 33715110909 | N30: Estudio De Profesionales Sa | O30: +54 9 341 657-5087 | T30: 1 | U30: ACTIVO | V30: 3 | W30: 0 | X30: 25913438 | Y30: 2100000
A31: a_000020 | B31: ARCA | C31: 1 | D31: OPEX | E31: INDIRECTO | F31: VARIABLE | H31: PORCINOS | I31: GRAL | K31: ACTIVO | L31: TRANSF | N31: ARCA | T31: 1 | U31: ACTIVO | V31: 4 | W31: 0 | X31: 23783407 | Y31: 3000000
A32: 20172586776 | B32: Cesaretti, Fernando Rene | C32: 1 | D32: OPEX | E32: INDIRECTO | F32: VARIABLE | H32: PORCINOS | I32: GRAL | J32: 20172586776 | K32: ACTIVO | L32: TRANSF | M32: 20172586776 | N32: Cesaretti, Fernando Rene | T32: 1 | U32: ACTIVO | V32: 4 | W32: 0 | X32: 22912729 | Y32: 7600000
A33: 30500001735 | B33: Banco De Galicia Y Buenos Aires S A U | C33: 1 | D33: OPEX | E33: INDIRECTO | F33: VARIABLE | H33: PORCINOS | I33: GRAL | J33: 30500001735 | K33: ACTIVO | L33: TRANSF | M33: 30500001735 | N33: Banco De Galicia Y Buenos Aires S A U | T33: 1 | U33: ACTIVO | V33: 4 | W33: 0 | X33: 21264640 | Y33: 21300000
A34: 20287965444 | B34: Perez, Rodrigo Alejandro | C34: 1 | D34: OPEX | E34: INDIRECTO | F34: VARIABLE | H34: PORCINOS | I34: GRAL | J34: 20287965444 | K34: ACTIVO | L34: TRANSF | M34: 20287965444 | N34: Perez, Rodrigo Alejandro | T34: 1 | U34: ACTIVO | V34: 4 | W34: 0 | X34: 20463053 | Y34: 20500000
A35: 20173241985 | B35: Matteo, Marcelo Mario | C35: 1 | D35: OPEX | E35: INDIRECTO | F35: VARIABLE | H35: PORCINOS | I35: GRAL | J35: 20173241985 | K35: ACTIVO | L35: TRANSF | M35: 20173241985 | N35: Matteo, Marcelo Mario | T35: 1 | U35: ACTIVO | V35: 4 | W35: 0 | X35: 18140297 | Y35: 3000000
A36: 33707409369 | B36: Afe Sociedad Civil | C36: 1 | D36: OPEX | E36: INDIRECTO | F36: VARIABLE | H36: PORCINOS | I36: GRAL | J36: 33707409369 | K36: ACTIVO | L36: TRANSF | M36: 33707409369 | N36: Afe Sociedad Civil | O36: +54 9 341 657-5087 | T36: 1 | U36: ACTIVO | V36: 4 | W36: 0 | X36: 16413582 | Y36: 1200000
A37: 20123698372 | B37: Donda, Ruben Estelio | C37: 1 | D37: OPEX | E37: INDIRECTO | F37: VARIABLE | H37: PORCINOS | I37: GRAL | J37: 20123698372 | K37: ACTIVO | L37: TRANSF | M37: 20123698372 | N37: Donda, Ruben Estelio | T37: 1 | U37: ACTIVO | V37: 4 | W37: 0 | X37: 14100000 | Y37: 3100000
A38: 30670799758 | B38: Grantec Sa | C38: 1 | D38: OPEX | E38: INDIRECTO | F38: VARIABLE | H38: PORCINOS | I38: GRAL | J38: 30670799758 | K38: ACTIVO | L38: TRANSF | M38: 30670799758 | N38: Grantec Sa | O38: +54 9 3442 55-3871 | T38: 1 | U38: ACTIVO | V38: 4 | W38: 0 | X38: 13897098 | Y38: 9300000
A39: 20345257595 | B39: Ventura, Agustin | C39: 1 | D39: OPEX | E39: INDIRECTO | F39: VARIABLE | H39: PORCINOS | I39: GRAL | J39: 20345257595 | K39: ACTIVO | L39: TRANSF | M39: 20345257595 | N39: Ventura, Agustin | T39: 1 | U39: ACTIVO | V39: 4 | W39: 0 | X39: 13812500 | Y39: 13800000
A40: 20233291073 | B40: Bieule, Cesar | C40: 1 | D40: OPEX | E40: INDIRECTO | F40: VARIABLE | H40: PORCINOS | I40: GRAL | J40: 20233291073 | K40: ACTIVO | L40: TRANSF | M40: 20233291073 | N40: Bieule, Cesar | T40: 1 | U40: ACTIVO | V40: 4 | W40: 0 | X40: 13310000 | Y40: 6700000
A41: 30714462241 | B41: Establecimiento Don Miguel Kobila S.R.L. | C41: 1 | D41: OPEX | E41: INDIRECTO | F41: VARIABLE | H41: PORCINOS | I41: GRAL | J41: 30714462241 | K41: ACTIVO | L41: TRANSF | M41: 30714462241 | N41: Establecimiento Don Miguel Kobila S.R.L. | T41: 1 | U41: ACTIVO | V41: 4 | W41: 0 | X41: 12305200 | Y41: 6200000
A42: 20251250856 | B42: Martinez, Marcelo Gregorio | C42: 1 | D42: OPEX | E42: INDIRECTO | F42: VARIABLE | H42: PORCINOS | I42: GRAL | J42: 20251250856 | K42: ACTIVO | L42: TRANSF | M42: 20251250856 | N42: Martinez, Marcelo Gregorio | O42: +54 9 3402 54-1063 | T42: 1 | U42: ACTIVO | V42: 4 | W42: 0 | X42: 12276000 | Y42: 4100000
A43: 20251250856 | B43: Martinez, Marcelo Gregorio | C43: 1 | D43: OPEX | E43: INDIRECTO | F43: VARIABLE | H43: PORCINOS | I43: GRAL | J43: 20251250856 | K43: ACTIVO | L43: TRANSF | M43: 20251250856 | N43: Martinez, Marcelo Gregorio | T43: 1 | U43: ACTIVO | V43: 4 | W43: 0 | X43: 12276000 | Y43: 4100000
A44: 27310444508 | B44: Andreoli, Maria Laura | C44: 1 | D44: OPEX | E44: INDIRECTO | F44: VARIABLE | H44: PORCINOS | I44: GRAL | J44: 27310444508 | K44: ACTIVO | L44: TRANSF | M44: 27310444508 | N44: Andreoli, Maria Laura | T44: 1 | U44: ACTIVO | V44: 4 | W44: 0 | X44: 11572281 | Y44: 1400000
A45: 30717027260 | B45: El Laboral Srl | C45: 1 | D45: OPEX | E45: INDIRECTO | F45: VARIABLE | H45: PORCINOS | I45: GRAL | J45: 30717027260 | K45: ACTIVO | L45: TRANSF | M45: 30717027260 | N45: El Laboral Srl | O45: +54 9 341 275-1524 | T45: 1 | U45: ACTIVO | V45: 4 | W45: 0 | X45: 10983042 | Y45: 5500000
A46: 30712111131 | B46: Trt S.A. | C46: 1 | D46: OPEX | E46: INDIRECTO | F46: VARIABLE | H46: PORCINOS | I46: GRAL | J46: 30712111131 | K46: ACTIVO | L46: TRANSF | M46: 30712111131 | N46: Trt S.A. | T46: 1 | U46: ACTIVO | V46: 4 | W46: 0 | X46: 10472041 | Y46: 4200000
A47: 30708809914 | B47: Argentina Essential Services Srl | C47: 1 | D47: OPEX | E47: INDIRECTO | F47: VARIABLE | H47: PORCINOS | I47: GRAL | J47: 30708809914 | K47: ACTIVO | L47: TRANSF | M47: 30708809914 | N47: Argentina Essential Services Srl | T47: 1 | U47: ACTIVO | V47: 4 | W47: 0 | X47: 10000000 | Y47: 20000000
A48: 30715137395 | B48: Electric Litoral S.R.L. | C48: 1 | D48: OPEX | E48: INDIRECTO | F48: VARIABLE | H48: PORCINOS | I48: GRAL | J48: 30715137395 | K48: ACTIVO | L48: TRANSF | M48: 30715137395 | N48: Electric Litoral S.R.L. | O48: +54 9 341 327-2802 | T48: 1 | U48: ACTIVO | V48: 4 | W48: 0 | X48: 9971721.1 | Y48: 1800000
A49: 30715801740 | B49: Danej S.A. | C49: 1 | D49: OPEX | E49: INDIRECTO | F49: VARIABLE | H49: PORCINOS | I49: GRAL | J49: 30715801740 | K49: ACTIVO | L49: TRANSF | M49: 30715801740 | N49: Danej S.A. | T49: 1 | U49: ACTIVO | V49: 4 | W49: 0 | X49: 9693310 | Y49: 3900000
A50: a_000493 | B50: T190111 | C50: 1 | D50: OPEX | E50: INDIRECTO | F50: VARIABLE | H50: PORCINOS | I50: GRAL | K50: ACTIVO | L50: TRANSF | N50: T190111 | T50: 1 | U50: ACTIVO | V50: 4 | W50: 0 | X50: 9560561.7 | Y50: 6400000
A51: 30718643992 | B51: Pascual Materiales S. R. L. | C51: 1 | D51: OPEX | E51: INDIRECTO | F51: VARIABLE | H51: PORCINOS | I51: GRAL | J51: 30718643992 | K51: ACTIVO | L51: TRANSF | M51: 30718643992 | N51: Pascual Materiales S. R. L. | O51: +54 9 341 307-4888 | T51: 1 | U51: ACTIVO | V51: 4 | W51: 0 | X51: 9076806.6 | Y51: 1000000
A52: 30718643992 | B52: Pascual Materiales S. R. L. | C52: 1 | D52: OPEX | E52: INDIRECTO | F52: VARIABLE | H52: PORCINOS | I52: GRAL | J52: 30718643992 | K52: ACTIVO | L52: TRANSF | M52: 30718643992 | N52: Pascual Materiales S. R. L. | T52: 1 | U52: ACTIVO | V52: 4 | W52: 0 | X52: 9076806.6 | Y52: 1000000
A53: 30709282049 | B53: Tecnogran S R L(C) | C53: 1 | D53: OPEX | E53: INDIRECTO | F53: VARIABLE | H53: PORCINOS | I53: GRAL | J53: 30709282049 | K53: ACTIVO | L53: TRANSF | M53: 30709282049 | N53: Tecnogran S R L(C) | T53: 1 | U53: ACTIVO | V53: 4 | W53: 0 | X53: 8034439.2 | Y53: 1800000
A54: 20145093881 | B54: Alvarez, Alejandro Dario | C54: 1 | D54: OPEX | E54: INDIRECTO | F54: VARIABLE | H54: PORCINOS | I54: GRAL | J54: 20145093881 | K54: ACTIVO | L54: TRANSF | M54: 20145093881 | N54: Alvarez, Alejandro Dario | O54: +54 9 341 595-4372 | T54: 1 | U54: ACTIVO | V54: 4 | W54: 0 | X54: 7816450 | Y54: 800000
A55: 24271349846 | B55: Chiminello, Vanina | C55: 1 | D55: OPEX | E55: INDIRECTO | F55: VARIABLE | H55: PORCINOS | I55: GRAL | J55: 24271349846 | K55: ACTIVO | L55: TRANSF | M55: 24271349846 | N55: Chiminello, Vanina | O55: +54 9 236 430-1023 | T55: 1 | U55: ACTIVO | V55: 4 | W55: 0 | X55: 7641000 | Y55: 800000
A56: 30-53510190-2 | B56: Molino Argentino S A I C A G E I | C56: 1 | D56: OPEX | E56: INDIRECTO | F56: VARIABLE | H56: PORCINOS | I56: GRAL | J56: 30-53510190-2 | K56: ACTIVO | L56: TRANSF | M56: 30-53510190-2 | N56: Molino Argentino S A I C A G E I | T56: 1 | U56: ACTIVO | V56: 4 | W56: 0 | X56: 6948458 | Y56: 2000000
A57: a_000075 | B57: ART a Pagar | C57: 1 | D57: OPEX | E57: INDIRECTO | F57: VARIABLE | H57: PORCINOS | I57: GRAL | K57: ACTIVO | L57: TRANSF | N57: ART a Pagar | T57: 1 | U57: ACTIVO | V57: 4 | W57: 0 | X57: 6773880.8 | Y57: 3400000
A58: 27134134580 | B58: Ciarniello, Claudia Maria | C58: 1 | D58: OPEX | E58: INDIRECTO | F58: VARIABLE | H58: PORCINOS | I58: GRAL | J58: 27134134580 | K58: ACTIVO | L58: TRANSF | M58: 27134134580 | N58: Ciarniello, Claudia Maria | O58: +54 9 3402 41-8806 | T58: 1 | U58: ACTIVO | V58: 4 | W58: 0 | X58: 6684793.6 | Y58: 800000
A59: a_000543 | B59: Plan AFIP S719696 | C59: 1 | D59: OPEX | E59: INDIRECTO | F59: VARIABLE | H59: PORCINOS | I59: GRAL | K59: ACTIVO | L59: TRANSF | N59: Plan AFIP S719696 | T59: 1 | U59: ACTIVO | V59: 4 | W59: 0 | X59: 6667448.4 | Y59: 6700000
A60: 30715950525 | B60: Mil Propiedades Srl. | C60: 1 | D60: OPEX | E60: INDIRECTO | F60: VARIABLE | H60: PORCINOS | I60: GRAL | J60: 30715950525 | K60: ACTIVO | L60: TRANSF | M60: 30715950525 | N60: Mil Propiedades Srl. | O60: +54 9 341 560-0660 | T60: 1 | U60: ACTIVO | V60: 4 | W60: 0 | X60: 6618700 | Y60: 700000
A61: 30717384810 | B61: Biotrader Sudamericana | C61: 1 | D61: OPEX | E61: INDIRECTO | F61: VARIABLE | H61: PORCINOS | I61: GRAL | J61: 30717384810 | K61: ACTIVO | L61: TRANSF | M61: 30717384810 | N61: Biotrader Sudamericana | T61: 1 | U61: ACTIVO | V61: 4 | W61: 0 | X61: 6298997.2 | Y61: 12600000
A62: 30717384810 | B62: Biotrader Sudamericana | C62: 1 | D62: OPEX | E62: INDIRECTO | F62: VARIABLE | H62: PORCINOS | I62: GRAL | J62: 30717384810 | K62: ACTIVO | L62: TRANSF | M62: 30717384810 | N62: Biotrader Sudamericana | T62: 1 | U62: ACTIVO | V62: 4 | W62: 0 | X62: 6298997.2 | Y62: 12600000
A63: 30715164457 | B63: Traverso Juan Y Traverso Guido | C63: 1 | D63: OPEX | E63: INDIRECTO | F63: VARIABLE | H63: PORCINOS | I63: GRAL | J63: 30715164457 | K63: ACTIVO | L63: TRANSF | M63: 30715164457 | N63: Traverso Juan Y Traverso Guido | T63: 1 | U63: ACTIVO | V63: 4 | W63: 0 | X63: 6011200 | Y63: 6000000
A64: 30-50853272-1 | B64: La Delfina Sociedad Anonima Comercial Industrial Financiera Y Agropecuaria | C64: 1 | D64: OPEX | E64: INDIRECTO | F64: VARIABLE | H64: PORCINOS | I64: GRAL | J64: 30-50853272-1 | K64: ACTIVO | L64: TRANSF | M64: 30-50853272-1 | N64: La Delfina Sociedad Anonima Comercial Industrial Financiera Y Agropecuaria | O64: +54 341 532-1444 | T64: 1 | U64: ACTIVO | V64: 4 | W64: 0 | X64: 5962880 | Y64: 200000
A65: 23230131139 | B65: Grimaldi, Gerardo Daniel | C65: 1 | D65: OPEX | E65: INDIRECTO | F65: VARIABLE | H65: PORCINOS | I65: GRAL | J65: 23230131139 | K65: ACTIVO | L65: TRANSF | M65: 23230131139 | N65: Grimaldi, Gerardo Daniel | T65: 1 | U65: ACTIVO | V65: 4 | W65: 0 | X65: 5764067.8 | Y65: 3800000
A66: 30718385292 | B66: Comercial Uritorco S. R. L. | C66: 1 | D66: OPEX | E66: INDIRECTO | F66: VARIABLE | H66: PORCINOS | I66: GRAL | J66: 30718385292 | K66: ACTIVO | L66: TRANSF | M66: 30718385292 | N66: Comercial Uritorco S. R. L. | T66: 1 | U66: ACTIVO | V66: 4 | W66: 0 | X66: 5733862.3 | Y66: 300000
A67: a_000273 | B67: Ganancias Ret ART 79 | C67: 1 | D67: OPEX | E67: INDIRECTO | F67: VARIABLE | H67: PORCINOS | I67: GRAL | K67: ACTIVO | L67: TRANSF | N67: Ganancias Ret ART 79 | T67: 1 | U67: ACTIVO | V67: 4 | W67: 0 | X67: 5704653.1 | Y67: 11400000
A68: 30715364731 | B68: Bordalt Ivan Y Carpinetti Barbara Ss | C68: 1 | D68: OPEX | E68: INDIRECTO | F68: VARIABLE | H68: PORCINOS | I68: GRAL | J68: 30715364731 | K68: ACTIVO | L68: TRANSF | M68: 30715364731 | N68: Bordalt Ivan Y Carpinetti Barbara Ss | O68: +54 9 3402 48-0840 | P68: ibbclimpieza@gmail.com | T68: 1 | U68: ACTIVO | V68: 4 | W68: 0 | X68: 4895015 | Y68: 800000
A69: 20339632392 | B69: Biscayart, Santiago | C69: 1 | D69: OPEX | E69: INDIRECTO | F69: VARIABLE | H69: PORCINOS | I69: GRAL | J69: 20339632392 | K69: ACTIVO | L69: TRANSF | M69: 20339632392 | N69: Biscayart, Santiago | T69: 1 | U69: ACTIVO | V69: 4 | W69: 0 | X69: 4890820 | Y69: 9800000
A70: a_000298 | B70: S827842 | C70: 1 | D70: OPEX | E70: INDIRECTO | F70: VARIABLE | H70: PORCINOS | I70: GRAL | K70: ACTIVO | L70: TRANSF | N70: S827842 | T70: 1 | U70: ACTIVO | V70: 4 | W70: 0 | X70: 4799271 | Y70: 1600000
A71: 30707097937 | B71: H.S.E. Ingenieria S R L | C71: 1 | D71: OPEX | E71: INDIRECTO | F71: VARIABLE | H71: PORCINOS | I71: GRAL | J71: 30707097937 | K71: ACTIVO | L71: TRANSF | M71: 30707097937 | N71: H.S.E. Ingenieria S R L | O71: +54 9 341 354-9683 | T71: 1 | U71: ACTIVO | V71: 4 | W71: 0 | X71: 4740207.7 | Y71: 1900000
A72: 30707097937 | B72: H.S.E. Ingenieria S R L | C72: 1 | D72: OPEX | E72: INDIRECTO | F72: VARIABLE | H72: PORCINOS | I72: GRAL | J72: 30707097937 | K72: ACTIVO | L72: TRANSF | M72: 30707097937 | N72: H.S.E. Ingenieria S R L | T72: 1 | U72: ACTIVO | V72: 4 | W72: 0 | X72: 4740207.7 | Y72: 1900000
A73: 27210110718 | B73: Silva, Nora Alejandra | C73: 1 | D73: OPEX | E73: INDIRECTO | F73: VARIABLE | H73: PORCINOS | I73: GRAL | J73: 27210110718 | K73: ACTIVO | L73: TRANSF | M73: 27210110718 | N73: Silva, Nora Alejandra | O73: +54 9 341 309-3968 | T73: 1 | U73: ACTIVO | V73: 4 | W73: 0 | X73: 4667000 | Y73: 800000
A74: 30714896632 | B74: Bater S.R.L. | C74: 1 | D74: OPEX | E74: INDIRECTO | F74: VARIABLE | H74: PORCINOS | I74: GRAL | J74: 30714896632 | K74: ACTIVO | L74: TRANSF | M74: 30714896632 | N74: Bater S.R.L. | T74: 1 | U74: ACTIVO | V74: 4 | W74: 0 | X74: 4285892.6 | Y74: 400000
A75: 20343814500 | B75: Parla, Ivan Andres | C75: 1 | D75: OPEX | E75: INDIRECTO | F75: VARIABLE | H75: PORCINOS | I75: GRAL | J75: 20343814500 | K75: ACTIVO | L75: TRANSF | M75: 20343814500 | N75: Parla, Ivan Andres | T75: 1 | U75: ACTIVO | V75: 4 | W75: 0 | X75: 4182438.5 | Y75: 1000000
A76: 33716457929 | B76: Pick Sas | C76: 1 | D76: OPEX | E76: INDIRECTO | F76: VARIABLE | H76: PORCINOS | I76: GRAL | J76: 33716457929 | K76: ACTIVO | L76: TRANSF | M76: 33716457929 | N76: Pick Sas | T76: 1 | U76: ACTIVO | V76: 4 | W76: 0 | X76: 4127229 | Y76: 400000
A77: 20372640104 | B77: Ruzzi, Emiliano Ramon | C77: 1 | D77: OPEX | E77: INDIRECTO | F77: VARIABLE | H77: PORCINOS | I77: GRAL | J77: 20372640104 | K77: ACTIVO | L77: TRANSF | M77: 20372640104 | N77: Ruzzi, Emiliano Ramon | O77: +54 9 3402 41-8235 | T77: 1 | U77: ACTIVO | V77: 4 | W77: 0 | X77: 3969457 | Y77: 1300000
A78: a_000497 | B78: T312066 | C78: 1 | D78: OPEX | E78: INDIRECTO | F78: VARIABLE | H78: PORCINOS | I78: GRAL | K78: ACTIVO | L78: TRANSF | N78: T312066 | T78: 1 | U78: ACTIVO | V78: 4 | W78: 0 | X78: 3656904.7 | Y78: 2400000
A79: 30680892276 | B79: Union Emergencias Regionales S A Acion | C79: 1 | D79: OPEX | E79: INDIRECTO | F79: VARIABLE | H79: PORCINOS | I79: GRAL | J79: 30680892276 | K79: ACTIVO | L79: TRANSF | M79: 30680892276 | N79: Union Emergencias Regionales S A Acion | O79: +54 3402 56-0748 | T79: 1 | U79: ACTIVO | V79: 4 | W79: 0 | X79: 3600392.8 | Y79: 400000
A80: 30680892276 | B80: Union Emergencias Regionales S A Acion | C80: 1 | D80: OPEX | E80: INDIRECTO | F80: VARIABLE | H80: PORCINOS | I80: GRAL | J80: 30680892276 | K80: ACTIVO | L80: TRANSF | M80: 30680892276 | N80: Union Emergencias Regionales S A Acion | T80: 1 | U80: ACTIVO | V80: 4 | W80: 0 | X80: 3600392.8 | Y80: 400000
A81: a_001332 | B81: Contribuciones Obra Social | C81: 1 | D81: OPEX | E81: INDIRECTO | F81: VARIABLE | H81: PORCINOS | I81: GRAL | K81: ACTIVO | L81: TRANSF | N81: Contribuciones Obra Social | T81: 1 | U81: ACTIVO | V81: 4 | W81: 0 | X81: 3440696.6 | Y81: 6900000
A82: 30717396479 | B82: Bertex S. R. L. | C82: 1 | D82: OPEX | E82: INDIRECTO | F82: VARIABLE | H82: PORCINOS | I82: GRAL | J82: 30717396479 | K82: ACTIVO | L82: TRANSF | M82: 30717396479 | N82: Bertex S. R. L. | O82: +54 9 3402 41-8736 | P82: eugenio@mbertex.com | T82: 1 | U82: ACTIVO | V82: 4 | W82: 0 | X82: 3397355.8 | Y82: 6800000
A83: a_000071 | B83: Contribuciones Obra Social a pagar | C83: 1 | D83: OPEX | E83: INDIRECTO | F83: VARIABLE | H83: PORCINOS | I83: GRAL | K83: ACTIVO | L83: TRANSF | N83: Contribuciones Obra Social a pagar | T83: 1 | U83: ACTIVO | V83: 4 | W83: 0 | X83: 3337986.5 | Y83: 6700000
A84: 30628044623 | B84: Pedro Lopez S A | C84: 1 | D84: OPEX | E84: INDIRECTO | F84: VARIABLE | H84: PORCINOS | I84: GRAL | J84: 30628044623 | K84: ACTIVO | L84: TRANSF | M84: 30628044623 | N84: Pedro Lopez S A | T84: 1 | U84: ACTIVO | V84: 4 | W84: 0 | X84: 3173830 | Y84: 3200000
A85: 30718385292 | B85: Comercial Uritorco S. R. L.- | C85: 1 | D85: OPEX | E85: INDIRECTO | F85: VARIABLE | H85: PORCINOS | I85: GRAL | J85: 30718385292 | K85: ACTIVO | L85: TRANSF | M85: 30718385292 | N85: Comercial Uritorco S. R. L.- | T85: 1 | U85: ACTIVO | V85: 4 | W85: 0 | X85: 3001090.7 | Y85: 200000
A86: 30717700402 | B86: Nardi Emanuel Oscar Y Nardi Rodrigo Nahuel S. Cap I Secc Iv | C86: 1 | D86: OPEX | E86: INDIRECTO | F86: VARIABLE | H86: PORCINOS | I86: GRAL | J86: 30717700402 | K86: ACTIVO | L86: TRANSF | M86: 30717700402 | N86: Nardi Emanuel Oscar Y Nardi Rodrigo Nahuel S. Cap I Secc Iv | O86: +54 9 341 582-8083 | T86: 1 | U86: ACTIVO | V86: 4 | W86: 0 | X86: 2887544 | Y86: 1400000
A87: 23060699569 | B87: Marcantoni, Ruben Enrique | C87: 1 | D87: OPEX | E87: INDIRECTO | F87: VARIABLE | H87: PORCINOS | I87: GRAL | J87: 23060699569 | K87: ACTIVO | L87: TRANSF | M87: 23060699569 | N87: Marcantoni, Ruben Enrique | T87: 1 | U87: ACTIVO | V87: 4 | W87: 0 | X87: 2865846 | Y87: 2900000
A88: 30640079378 | B88: Gomerias Neumen S A | C88: 1 | D88: OPEX | E88: INDIRECTO | F88: VARIABLE | H88: PORCINOS | I88: GRAL | J88: 30640079378 | K88: ACTIVO | L88: TRANSF | M88: 30640079378 | N88: Gomerias Neumen S A | T88: 1 | U88: ACTIVO | V88: 4 | W88: 0 | X88: 2594660.8 | Y88: 5200000
A89: 20297925947 | B89: Barrera, Adrian Jesus | C89: 1 | D89: OPEX | E89: INDIRECTO | F89: VARIABLE | H89: PORCINOS | I89: GRAL | J89: 20297925947 | K89: ACTIVO | L89: TRANSF | M89: 20297925947 | N89: Barrera, Adrian Jesus | O89: +54 9 3402 52-1799 | T89: 1 | U89: ACTIVO | V89: 4 | W89: 0 | X89: 2578800 | Y89: 300000
A90: 20290013934 | B90: Albertengo, Guido Pablo | C90: 1 | D90: OPEX | E90: INDIRECTO | F90: VARIABLE | H90: PORCINOS | I90: GRAL | J90: 20290013934 | K90: ACTIVO | L90: TRANSF | M90: 20290013934 | N90: Albertengo, Guido Pablo | T90: 1 | U90: ACTIVO | V90: 4 | W90: 0 | X90: 2349000 | Y90: 4700000
A91: 20305903184 | B91: Guillermo Andres, Iocco | C91: 1 | D91: OPEX | E91: INDIRECTO | F91: VARIABLE | H91: PORCINOS | I91: GRAL | J91: 20305903184 | K91: ACTIVO | L91: TRANSF | M91: 20305903184 | N91: Guillermo Andres, Iocco | T91: 1 | U91: ACTIVO | V91: 4 | W91: 0 | X91: 2135674.2 | Y91: 400000
A92: a_000498 | B92: T312079 | C92: 1 | D92: OPEX | E92: INDIRECTO | F92: VARIABLE | H92: PORCINOS | I92: GRAL | K92: ACTIVO | L92: TRANSF | N92: T312079 | T92: 1 | U92: ACTIVO | V92: 4 | W92: 0 | X92: 2128884.7 | Y92: 1400000
A93: a_000278 | B93: Plan AFIP N963638 | C93: 1 | D93: OPEX | E93: INDIRECTO | F93: VARIABLE | H93: PORCINOS | I93: GRAL | K93: ACTIVO | L93: TRANSF | N93: Plan AFIP N963638 | T93: 1 | U93: ACTIVO | V93: 4 | W93: 0 | X93: 2128613.9 | Y93: 500000
A94: 30711336911 | B94: Argelec Centro S.R.L. | C94: 1 | D94: OPEX | E94: INDIRECTO | F94: VARIABLE | H94: PORCINOS | I94: GRAL | J94: 30711336911 | K94: ACTIVO | L94: TRANSF | M94: 30711336911 | N94: Argelec Centro S.R.L. | T94: 1 | U94: ACTIVO | V94: 4 | W94: 0 | X94: 2085544.9 | Y94: 1000000
A95: 23280588709 | B95: Albertengo, Juan Ignacio | C95: 1 | D95: OPEX | E95: INDIRECTO | F95: VARIABLE | H95: PORCINOS | I95: GRAL | J95: 23280588709 | K95: ACTIVO | L95: TRANSF | M95: 23280588709 | N95: Albertengo, Juan Ignacio | T95: 1 | U95: ACTIVO | V95: 4 | W95: 0 | X95: 2025000 | Y95: 4100000
A96: a_001481 | B96: Plan AFIP R341057 | C96: 1 | D96: OPEX | E96: INDIRECTO | F96: VARIABLE | H96: PORCINOS | I96: GRAL | K96: ACTIVO | L96: TRANSF | N96: Plan AFIP R341057 | T96: 1 | U96: ACTIVO | V96: 4 | W96: 0 | X96: 1994506.5 | Y96: 4000000
A97: 20-21417084-2 | B97: Gaspari, Leonardo Sergio | C97: 1 | D97: OPEX | E97: INDIRECTO | F97: VARIABLE | H97: PORCINOS | I97: GRAL | J97: 20-21417084-2 | K97: ACTIVO | L97: TRANSF | M97: 20-21417084-2 | N97: Gaspari, Leonardo Sergio | O97: +54 9 3462 51-6747 | P97: leo-gaspari@hotmail.com | T97: 1 | U97: ACTIVO | V97: 4 | W97: 0 | X97: 1966314.4 | Y97: 3900000
A98: 20372610817 | B98: Bongiovanni, Juan Pablo | C98: 1 | D98: OPEX | E98: INDIRECTO | F98: VARIABLE | H98: PORCINOS | I98: GRAL | J98: 20372610817 | K98: ACTIVO | L98: TRANSF | M98: 20372610817 | N98: Bongiovanni, Juan Pablo | O98: +54 9 341 227-9805 | T98: 1 | U98: ACTIVO | V98: 4 | W98: 0 | X98: 1916762.2 | Y98: 1000000
A99: 27283146540 | B99: Martinez, Marcela Silvana | C99: 1 | D99: OPEX | E99: INDIRECTO | F99: VARIABLE | H99: PORCINOS | I99: GRAL | J99: 27283146540 | K99: ACTIVO | L99: TRANSF | M99: 27283146540 | N99: Martinez, Marcela Silvana | O99: +54 9 341 657-5087 | T99: 1 | U99: ACTIVO | V99: 4 | W99: 0 | X99: 1813000 | Y99: 200000
A100: 27283146540 | B100: Martinez, Marcela Silvana | C100: 1 | D100: OPEX | E100: INDIRECTO | F100: VARIABLE | H100: PORCINOS | I100: GRAL | J100: 27283146540 | K100: ACTIVO | L100: TRANSF | M100: 27283146540 | N100: Martinez, Marcela Silvana | T100: 1 | U100: ACTIVO | V100: 4 | W100: 0 | X100: 1813000 | Y100: 200000
...

Sheet union_gastos
A1: Fecha de Factura/Recibo | B1: Nombre de la empresa a mostrar en la factura | C1: Número | D1: Total con signo | E1: Líneas de factura/Etiqueta | F1: Líneas de factura/Cantidad | G1: Líneas de factura/Precio unitario | H1: Líneas de factura/Unidad de medida | I1: Líneas de factura/Producto | J1: Concepto | K1: Tipo de Gasto 1 | L1: Tipo de Gasto 2 | M1: CCO - SECTOR | N1: origen | O1: rubro_id | P1: rubro_final
A2: 46112 | B2: Alimento | C2: nico_2 | D2: -1.7861696e+08 | E2: calculo_alimentos_total | F2: 432780 | G2: 412.72 | H2: KG | I2: Nutrición | J2: OPEX | K2: VARIABLE | L2: DIRECTO | N2: nutri&rrhh | O2: =_xlfn.XLOOKUP(union_gastos[[#This Row],[Líneas de factura/Producto]],'concepto_id'!A:A,'concepto_id'!B:B) -> 1 | P2: =_xlfn.XLOOKUP(union_gastos[[#This Row],[rubro_id]],rubros!B:B,rubros!A:A) -> NUTRICIÓN
A3: 46112 | B3: Nutran | C3: nico_1 | D3: -21985644 | E3: fason_calculo_alimentos_1 | F3: 423330 | G3: 47 | H3: KG | I3: Nutrición | J3: OPEX | K3: VARIABLE | L3: DIRECTO | N3: nutri&rrhh | O3: =_xlfn.XLOOKUP(union_gastos[[#This Row],[Líneas de factura/Producto]],'concepto_id'!A:A,'concepto_id'!B:B) -> 1 | P3: =_xlfn.XLOOKUP(union_gastos[[#This Row],[rubro_id]],rubros!B:B,rubros!A:A) -> NUTRICIÓN
A4: 46090 | B4: Empresa Provincial De La Energia De Santa Fe | C4: FA-A 00069-00039924 | D4: -12284042 | E4: Energia (C) | F4: 1 | G4: 8313807.3 | H4: Unidad(es) | I4: Energia (C) | J4: OPEX | K4: VARIABLE | L4: DIRECTO | N4: gastos_facturas | O4: =_xlfn.XLOOKUP(union_gastos[[#This Row],[Líneas de factura/Producto]],'concepto_id'!A:A,'concepto_id'!B:B) -> 11 | P4: =_xlfn.XLOOKUP(union_gastos[[#This Row],[rubro_id]],rubros!B:B,rubros!A:A) -> ENERGÍA
A5: 46104 | B5: Trt S.A. | C5: FA-A 00012-00058059 | D5: -4849392.4 | E5: Sanidad (C) IMPROVAC X 125 DS | F5: 20 | G5: 183017.71 | H5: Unidad(es) | I5: Sanidad (C) | J5: OPEX | K5: VARIABLE | L5: DIRECTO | N5: gastos_facturas | O5: =_xlfn.XLOOKUP(union_gastos[[#This Row],[Líneas de factura/Producto]],'concepto_id'!A:A,'concepto_id'!B:B) -> 3 | P5: =_xlfn.XLOOKUP(union_gastos[[#This Row],[rubro_id]],rubros!B:B,rubros!A:A) -> SANIDAD
A6: 46108 | B6: ARCA 931 | C6: OC/2026/0149 | D6: -4772839.3 | E6: IMPUESTO (C) Obra Social Diciembre | F6: 1 | G6: 4772839.3 | H6: Unidad(es) | I6: IMPUESTO (C) | J6: OPEX | K6: VARIABLE | L6: INDIRECTO | N6: gastos_facturas | O6: =_xlfn.XLOOKUP(union_gastos[[#This Row],[Líneas de factura/Producto]],'concepto_id'!A:A,'concepto_id'!B:B) -> 8 | P6: =_xlfn.XLOOKUP(union_gastos[[#This Row],[rubro_id]],rubros!B:B,rubros!A:A) -> IMPUESTOS
A7: 46091 | B7: Establecimiento Do#A Teresa S R L | C7: FA-A 00005-00008597 | D7: -4673960 | E7: Gastos Operativos (C) Gastos Operativos (C) Alquiler mes Marzo Campo Tonfoni | F7: 2000 | G7: 2278.48 | H7: Unidad(es) | I7: Gastos Operativos (C) | J7: OPEX | K7: FIJO | L7: INDIRECTO | N7: gastos_facturas | O7: =_xlfn.XLOOKUP(union_gastos[[#This Row],[Líneas de factura/Producto]],'concepto_id'!A:A,'concepto_id'!B:B) -> 7 | P7: =_xlfn.XLOOKUP(union_gastos[[#This Row],[rubro_id]],rubros!B:B,rubros!A:A) -> GASTOS OPERATIVOS
A8: 46094 | B8: Drovet S A | C8: FA-A 00330-00214077 | D8: -3748727.7 | E8: Sanidad (C) Porcilis pcv | F8: 26 | G8: 65042.2 | H8: Unidad(es) | I8: Sanidad (C) | J8: OPEX | K8: VARIABLE | L8: DIRECTO | N8: gastos_facturas | O8: =_xlfn.XLOOKUP(union_gastos[[#This Row],[Líneas de factura/Producto]],'concepto_id'!A:A,'concepto_id'!B:B) -> 3 | P8: =_xlfn.XLOOKUP(union_gastos[[#This Row],[rubro_id]],rubros!B:B,rubros!A:A) -> SANIDAD
A9: 46083 | B9: Arrieta, Fernando Gabriel | C9: FA-A 00003-00000538 | D9: -3460600 | E9: Fletes (C) DOBLE 02/02 / 09/02 | F9: 2 | G9: 550000 | H9: Unidad(es) | I9: Fletes (C) | J9: OPEX | K9: VARIABLE | L9: INDIRECTO | N9: gastos_facturas | O9: =_xlfn.XLOOKUP(union_gastos[[#This Row],[Líneas de factura/Producto]],'concepto_id'!A:A,'concepto_id'!B:B) -> 5 | P9: =_xlfn.XLOOKUP(union_gastos[[#This Row],[rubro_id]],rubros!B:B,rubros!A:A) -> FLETES
A10: 46092 | B10: Drovet S A | C10: FA-A 00330-00013592 | D10: -3042226.4 | E10: Sanidad (C) coglapix x 50 ds | F10: 44 | G10: 47926 | H10: Unidad(es) | I10: Sanidad (C) | J10: OPEX | K10: VARIABLE | L10: DIRECTO | N10: gastos_facturas | O10: =_xlfn.XLOOKUP(union_gastos[[#This Row],[Líneas de factura/Producto]],'concepto_id'!A:A,'concepto_id'!B:B) -> 3 | P10: =_xlfn.XLOOKUP(union_gastos[[#This Row],[rubro_id]],rubros!B:B,rubros!A:A) -> SANIDAD
A11: 46097 | B11: Trt S.A. | C11: FA-A 00012-00057855 | D11: -3010390.4 | E11: Sanidad (C) HYOGEN | F11: 54 | G11: 45807.7 | H11: Unidad(es) | I11: Sanidad (C) | J11: OPEX | K11: VARIABLE | L11: DIRECTO | N11: gastos_facturas | O11: =_xlfn.XLOOKUP(union_gastos[[#This Row],[Líneas de factura/Producto]],'concepto_id'!A:A,'concepto_id'!B:B) -> 3 | P11: =_xlfn.XLOOKUP(union_gastos[[#This Row],[rubro_id]],rubros!B:B,rubros!A:A) -> SANIDAD
A12: 46092 | B12: Drovet S A | C12: FA-A 00330-00213643 | D12: -2889639 | E12: Sanidad (C) Hypra suis glasser x 50 DS | F12: 54 | G12: 43307.45 | H12: Unidad(es) | I12: Sanidad (C) | J12: OPEX | K12: VARIABLE | L12: DIRECTO | N12: gastos_facturas | O12: =_xlfn.XLOOKUP(union_gastos[[#This Row],[Líneas de factura/Producto]],'concepto_id'!A:A,'concepto_id'!B:B) -> 3 | P12: =_xlfn.XLOOKUP(union_gastos[[#This Row],[rubro_id]],rubros!B:B,rubros!A:A) -> SANIDAD
A13: 46094 | B13: Agroceres Pic Argentina S A | C13: FA-A 00004-00021027 | D13: -2494688.1 | E13: Genetica (C) Royalty lechón destetado macho | F13: 1110 | G13: 1846.73 | H13: Unidad(es) | I13: Genetica (C) | J13: OPEX | K13: VARIABLE | L13: DIRECTO | N13: gastos_facturas | O13: =_xlfn.XLOOKUP(union_gastos[[#This Row],[Líneas de factura/Producto]],'concepto_id'!A:A,'concepto_id'!B:B) -> 4 | P13: =_xlfn.XLOOKUP(union_gastos[[#This Row],[rubro_id]],rubros!B:B,rubros!A:A) -> GENÉTICA
... A110: 46112 | B110: HABERES | C110: remu | D110: 49609364 | E110: planilla de andres | F110: 23 | G110: -2156928.9 | H110: #RRHH | I110: Personal | J110: OPEX | K110: OPEX | L110: FIJO | N110: nutri&rrhh | O110: =_xlfn.XLOOKUP(union_gastos[[#This Row],[Líneas de factura/Producto]],'concepto_id'!A:A,'concepto_id'!B:B) -> 2 | P110: =_xlfn.XLOOKUP(union_gastos[[#This Row],[rubro_id]],rubros!B:B,rubros!A:A) -> PERSONAL

Sheet concepto_id
A1: CONCEPTO | B1: ID | C1: Column3 | D1: Column4 | E1: Column5 | F1: Column6 | G1: Column7 | H1: Column8
A2: Honorarios (C) | B2: 9
A3: IMPUESTO (C) | B3: 8
A4: Genetica (C) | B4: 4
A5: Mantenimiento (C) | B5: 6
A6: Fletes (C) | B6: 5
A7: SERVICIOS (C) | B7: 10
A8: NUTRICION | B8: 1
A9: Sanidad (C) | B9: 3
A10: PERSONAL (C) | B10: 2
A11: rrhh_andy1 | B11: 2
A12: rrhh_andy2 | B12: 2
A13: rrhh_andy3 | B13: 2
... A93: Reparaciones y repuestos (C) | B93: 6

Sheet facturas_ingresos
A1: Actividades | B1: Estado | C1: Estado de pago | D1: Fecha de Factura/Recibo | E1: Fecha de vencimiento | F1: Importe sin impuestos con signo | G1: Nombre de la empresa a mostrar en la factura | H1: Número | I1: Referencia | J1: Total con signo | K1: Total en divisa con signo | L1: Importe adeudado | M1: Líneas de factura/Etiquetas | N1: Líneas de factura/Etiqueta | O1: Líneas de factura/Cantidad | P1: Líneas de factura/Precio unitario | Q1: Líneas de factura/Unidad de medida | R1: Apuntes contables/Líneas analíticas/Cuenta analítica | S1: Origen | T1: Líneas de factura/Producto
B2: Publicado | C2: No pagadas | D2: 46022 | E2: 46028 | F2: 1933516 | G2: Worms Argentina S.A ok | H2: FA-M 00001-00000041 | J2: 2339554.4 | K2: 2339554.4 | L2: 2339554.4 | N2: Efluentes solidos (cama profunda)recibidos durante el mes de diciembre 2025 | O2: 93860 | P2: 20.6 | Q2: Unidad(es) | T2: Efluentes solidos (cama profunda)
B3: Publicado | C3: No pagadas | D3: 46022 | E3: 46028 | F3: 33616589 | G3: Worms Argentina S.A ok | H3: FA-M 00001-00000040 | J3: 40676072 | K3: 40676072 | L3: 40676072 | N3: Efluentes liquidos (biol)recibidos durante el mes de diciembre 2025 | O3: 174080 | P3: 193.11 | Q3: Unidad(es) | T3: Efluentes liquidos (biol)
B4: Publicado | C4: Pagado | D4: 46021 | E4: 46041 | F4: 6313300 | G4: Gaspari, Leonardo Sergio | H4: LCDP-A 00002-00000207 | J4: 6976196.5 | K4: 6976196.5 | N4: PORCINOS | O4: 4354 | P4: 1450 | Q4: kg | S4: OV 0001-00001266 | T4: PORCINOS
B5: Publicado | C5: No pagadas | D5: 46021 | E5: 46052 | F5: 5250055.7 | G5: De La Fuente Florencia | H5: FA-M 00001-00000039 | J5: 5801311.6 | K5: 5801311.6 | L5: 5801311.6 | N5: KG DE CARNE CAPON PORCINOS PORCINOS | O5: 3031 | P5: 1732.12 | Q5: Unidad(es) | S5: OV 0001-00001273 | T5: KG DE CARNE CAPON PORCINOS
B6: Publicado | C6: Revertido | D6: 46020 | E6: 46021 | F6: 1792744.2 | G6: Gonzalez Maximiliano Eduardo | H6: ND-M 00001-00000001 | J6: 1980982.3 | K6: 1980982.3 | N6: KG DE CARNE CAPON PORCINOS PORCINOS | O6: 1035 | P6: 1732.12 | Q6: Unidad(es) | T6: KG DE CARNE CAPON PORCINOS
B7: Publicado | C7: No pagadas | D7: 46020 | E7: 46038 | F7: 5267150 | G7: Gapre S R L | H7: LCDP-A 00009-00002095 | J7: 5820200.8 | K7: 5820200.8 | L7: 5820200.8 | N7: PORCINOS | O7: 3725 | P7: 1414 | Q7: kg | S7: OV 0001-00001148 | T7: PORCINOS
B8: Publicado | C8: Pagado | D8: 46020 | E8: 46039 | F8: 3970891.6 | G8: Pura Raza S.A.S. | H8: FA-M 00001-00000038 | J8: 4387835.3 | K8: 4387835.3 | N8: KG DE CARNE CAPON PORCINOS PORCINOS | O8: 1965 | P8: 2020.81 | Q8: Unidad(es) | S8: OV 0001-00001242 | T8: KG DE CARNE CAPON PORCINOS
B9: Publicado | C9: Pagado | D9: 46020 | E9: 46039 | F9: 7720058.8 | G9: Rovetto, Carlos Alberto | H9: FA-M 00001-00000037 | J9: 8530665 | K9: 8530665 | N9: KG DE CARNE CAPON PORCINOS PORCINOS | O9: 4457 | P9: 1732.12 | Q9: Unidad(es) | S9: OV 0001-00001241 | T9: KG DE CARNE CAPON PORCINOS
B10: Publicado | C10: Revertido | D10: 46020 | E10: 46025 | F10: 1792744.2 | G10: Gonzalez Maximiliano Eduardo | H10: FA-M 00001-00000035 | J10: 1980982.3 | K10: 1980982.3 | N10: KG DE CARNE CAPON PORCINOS PORCINOS | O10: 1035 | P10: 1732.12 | Q10: Unidad(es) | S10: OV 0001-00001239 | T10: KG DE CARNE CAPON PORCINOS
B11: Publicado | C11: Pagado Parcialmente | D11: 46020 | E11: 46041 | F11: 8638082.4 | G11: Rovetto, Carlos Alberto | H11: FA-M 00001-00000034 | J11: 9545081.1 | K11: 9545081.1 | L11: 9361337.8 | N11: KG DE CARNE CAPON PORCINOS PORCINOS | O11: 4987 | P11: 1732.12 | Q11: Unidad(es) | S11: OV 0001-00001237 | T11: KG DE CARNE CAPON PORCINOS
B12: Publicado | C12: Pagado | D12: 46020 | E12: 46039 | F12: 3730415.3 | G12: Pura Raza S.A.S. | H12: FA-M 00001-00000033 | J12: 4122108.9 | K12: 4122108.9 | N12: KG DE CARNE CAPON PORCINOS PORCINOS | O12: 1846 | P12: 2020.81 | Q12: Unidad(es) | S12: OV 0001-00001238 | T12: KG DE CARNE CAPON PORCINOS
B13: Publicado | C13: Pagado | D13: 46018 | E13: 46025 | F13: 788114.6 | G13: RATONE PAOLA | H13: FA-M 00001-00000036 | J13: 870866.63 | K13: 870866.63 | N13: KG DE CARNE CAPON PORCINOS PORCINOS | O13: 455 | P13: 1732.12 | Q13: Unidad(es) | S13: OV 0001-00001240 | T13: KG DE CARNE CAPON PORCINOS
B14: Publicado | C14: No pagadas | D14: 46013 | E14: 46031 | F14: 14205044 | G14: Gapre S R L | H14: LCDP-A 00009-00002094 | J14: 15696574 | K14: 15696574 | L14: 15696574 | N14: PORCINOS | O14: 10046 | P14: 1414 | Q14: kg | S14: OV 0001-00001236 | T14: PORCINOS
B15: Publicado | C15: No pagadas | D15: 46013 | E15: 46031 | F15: 1888538.4 | G15: Gapre S R L | H15: LCDP-A 00009-00002093 | J15: 2086834.9 | K15: 2086834.9 | L15: 2086834.9 | N15: CERDAS | O15: 1908 | P15: 989.8 | Q15: kg | S15: OV 0001-00001235 | T15: CERDAS
B16: Publicado | C16: No pagadas | D16: 46013 | E16: 46031 | F16: 5344920 | G16: Gapre S R L | H16: LCDP-A 00009-00002092 | J16: 5906136.6 | K16: 5906136.6 | L16: 5906136.6 | N16: PORCINOS | O16: 3780 | P16: 1414 | Q16: kg | S16: OV 0001-00001234 | T16: PORCINOS
B17: Publicado | C17: Pagado Parcialmente | D17: 46013 | E17: 46031 | F17: 14654696 | G17: Gapre S R L | H17: LCDP-A 00009-00002091 | J17: 16193439 | K17: 16193439 | L17: 3388083.5 | N17: PORCINOS | O17: 10364 | P17: 1414 | Q17: kg | S17: OV 0001-00001233 | T17: PORCINOS
B18: Publicado | C18: Pagado | D18: 46013 | E18: 46024 | F18: 18181212 | G18: Gapre S R L | H18: LCDP-A 00009-00002090 | J18: 20090239 | K18: 20090239 | N18: PORCINOS | O18: 12858 | P18: 1414 | Q18: kg | S18: OV 0001-00001232 | T18: PORCINOS
B19: Publicado | C19: Pagado | D19: 46013 | E19: 46013 | F19: 6403200 | G19: Gaspari, Leonardo Sergio | H19: LCDP-A 00002-00000205 | J19: 7075536 | K19: 7075536 | N19: PORCINOS | O19: 4416 | P19: 1450 | Q19: kg | S19: OV 0001-00001226 | T19: PORCINOS
B20: Publicado | C20: Pagado | D20: 46009 | E20: 46022 | F20: 935635.03 | G20: DIAMBRI FEDERICO | H20: FA-M 00001-00000032 | J20: 1033876.7 | K20: 1033876.7 | N20: KG DE CARNE CAPON PORCINOS PORCINOS | O20: 463 | P20: 2020.81 | Q20: Unidad(es) | S20: OV 0001-00001217 | T20: KG DE CARNE CAPON PORCINOS
B21: Publicado | C21: Pagado | D21: 46008 | E21: 46036 | F21: 4080015.4 | G21: Pura Raza S.A.S. | H21: FA-M 00001-00000031 | J21: 4508417 | K21: 4508417 | N21: KG DE CARNE CAPON PORCINOS PORCINOS | O21: 2019 | P21: 2020.81 | Q21: Unidad(es) | S21: OV 0001-00001211 | T21: KG DE CARNE CAPON PORCINOS
B22: Publicado | C22: Pagado | D22: 46008 | E22: 46029 | F22: 4077994.6 | G22: Pura Raza S.A.S. | H22: FA-M 00001-00000030 | J22: 4506184 | K22: 4506184 | N22: KG DE CARNE CAPON PORCINOS PORCINOS | O22: 2018 | P22: 2020.81 | Q22: Unidad(es) | S22: OV 0001-00001210 | T22: KG DE CARNE CAPON PORCINOS
B23: Publicado | C23: Pagado | D23: 46008 | E23: 46028 | F23: 8284730 | G23: Rovetto, Carlos Alberto | H23: FA-M 00001-00000029 | J23: 9154626.6 | K23: 9154626.6 | N23: KG DE CARNE CAPON PORCINOS PORCINOS | O23: 4783 | P23: 1732.12 | Q23: Unidad(es) | S23: OV 0001-00001203 | T23: KG DE CARNE CAPON PORCINOS
B24: Publicado | C24: No pagadas | D24: 46008 | E24: 46032 | F24: 4905363.8 | G24: SANVIRO S.A | H24: FA-M 00001-00000028 | J24: 5420427 | K24: 5420427 | L24: 5420427 | N24: KG DE CARNE CAPON PORCINOS PORCINOS | O24: 2832 | P24: 1732.12 | Q24: Unidad(es) | S24: OV 0001-00000999 | T24: KG DE CARNE CAPON PORCINOS
B25: Publicado | C25: Pagado Parcialmente | D25: 46008 | E25: 46025 | F25: 4903631.7 | G25: SANVIRO S.A | H25: FA-M 00001-00000027 | J25: 5418513 | K25: 5418513 | L25: 4947329.1 | N25: KG DE CARNE CAPON PORCINOS PORCINOS | O25: 2831 | P25: 1732.12 | Q25: Unidad(es) | S25: OV 0001-00000998 | T25: KG DE CARNE CAPON PORCINOS
B26: Publicado | C26: Pagado | D26: 46008 | E26: 46018 | F26: 5139200 | G26: SANVIRO S.A | H26: FA-M 00001-00000026 | J26: 5678816 | K26: 5678816 | N26: KG DE CARNE CAPON PORCINOS PORCINOS | O26: 2967 | P26: 1732.12 | Q26: Unidad(es) | S26: OV 0001-00000997 | T26: KG DE CARNE CAPON PORCINOS
B27: Publicado | C27: Pagado | D27: 46007 | E27: 46024 | F27: 10846794 | G27: Gapre S R L | H27: LCDP-A 00009-00002089 | J27: 11985707 | K27: 11985707 | N27: PORCINOS | O27: 7671 | P27: 1414 | Q27: kg | S27: OV 0001-00001231 | T27: PORCINOS
B28: Publicado | C28: Pagado | D28: 46006 | E28: 46024 | F28: 11242714 | G28: Gapre S R L | H28: LCDP-A 00009-00002088 | J28: 12423199 | K28: 12423199 | N28: PORCINOS | O28: 7951 | P28: 1414 | Q28: kg | S28: OV 0001-00001147 | T28: PORCINOS
B29: Publicado | C29: Pagado | D29: 46006 | E29: 46017 | F29: 2577439.2 | G29: Gapre S R L | H29: LCDP-A 00009-00002087 | J29: 2848070.3 | K29: 2848070.3 | N29: CERDAS | O29: 2604 | P29: 989.8 | Q29: kg | S29: OV 0001-00001223 | T29: CERDAS
B30: Publicado | C30: Pagado | D30: 46006 | E30: 46017 | F30: 470155 | G30: Gapre S R L | H30: LCDP-A 00009-00002086 | J30: 519521.28 | K30: 519521.28 | N30: CERDAS | O30: 475 | P30: 989.8 | Q30: kg | S30: OV 0001-00001222 | T30: CERDAS
B31: Publicado | C31: Pagado | D31: 46006 | E31: 46017 | F31: 11234230 | G31: Gapre S R L | H31: LCDP-A 00009-00002085 | J31: 12413824 | K31: 12413824 | N31: PORCINOS | O31: 7945 | P31: 1414 | Q31: kg | S31: OV 0001-00001146 | T31: PORCINOS
B32: Publicado | C32: Pagado | D32: 46004 | E32: 46010 | F32: 4292500 | G32: Livolti, Maria | H32: LCDP-A 00001-00000788 | J32: 4743212.5 | K32: 4743212.5 | N32: PORCINOS | O32: 2125 | P32: 2020 | Q32: kg | S32: OV 0001-00001216 | T32: PORCINOS
B33: Publicado | C33: Pagado | D33: 46003 | E33: 46024 | F33: 8631154 | G33: Rovetto, Carlos Alberto | H33: FA-M 00001-00000025 | J33: 9537425.1 | K33: 9537425.1 | N33: KG DE CARNE CAPON PORCINOS PORCINOS | O33: 4983 | P33: 1732.12 | Q33: Unidad(es) | S33: OV 0001-00001184 | T33: KG DE CARNE CAPON PORCINOS
B34: Publicado | C34: Pagado | D34: 46002 | E34: 46017 | F34: 193920 | G34: Gapre S R L | H34: LCDP-A 00009-00002084 | J34: 214281.6 | K34: 214281.6 | N34: PORCINOS | O34: 160 | P34: 1212 | Q34: kg | S34: OV 0001-00001206 | T34: PORCINOS
B35: Publicado | C35: Pagado | D35: 46000 | E35: 46016 | F35: 16481988 | G35: Gapre S R L | H35: LCDP-A 00009-00002083 | J35: 18212597 | K35: 18212597 | N35: PORCINOS | O35: 13599 | P35: 1212 | Q35: kg | S35: OV 0001-00001205 | T35: PORCINOS
B36: Publicado | C36: No pagadas | D36: 46000 | E36: 46002 | F36: 2081549.4 | G36: Cooperativa Agricola Ganadera Aaron Castellanos Ltda De Esperanza | H36: LCDP-A 00004-00000247 | J36: 2300112.1 | K36: 2300112.1 | L36: 2300112.1 | N36: CERDAS | O36: 2103 | P36: 989.8 | Q36: kg | T36: CERDAS
B37: Publicado | C37: Revertido | D37: 46000 | E37: 46002 | F37: 2973642 | G37: Cooperativa Agricola Ganadera Aaron Castellanos Ltda De Esperanza | H37: LCDP-A 00004-00000245 | J37: 3285874.4 | K37: 3285874.4 | N37: CERDAS | O37: 2103 | P37: 1414 | Q37: kg | T37: CERDAS
B38: Publicado | C38: Pagado | D38: 46000 | E38: 46015 | F38: 3898142.5 | G38: Pura Raza S.A.S. | H38: FA-M 00001-00000024 | J38: 4307447.5 | K38: 4307447.5 | N38: KG DE CARNE CAPON PORCINOS PORCINOS | O38: 1929 | P38: 2020.81 | Q38: Unidad(es) | S38: OV 0001-00001177 | T38: KG DE CARNE CAPON PORCINOS
B39: Publicado | C39: Pagado | D39: 46000 | E39: 46020 | F39: 8535887.4 | G39: Rovetto, Carlos Alberto | H39: FA-M 00001-00000023 | J39: 9432155.5 | K39: 9432155.5 | N39: KG DE CARNE CAPON PORCINOS PORCINOS | O39: 4928 | P39: 1732.12 | Q39: Unidad(es) | S39: OV 0001-00001175 | T39: KG DE CARNE CAPON PORCINOS
B40: Publicado | C40: Pagado | D40: 46000 | E40: 46013 | F40: 2691714.5 | G40: Rovetto, Carlos Alberto | H40: FA-M 00001-00000022 | J40: 2974344.5 | K40: 2974344.5 | N40: KG DE CARNE CAPON PORCINOS PORCINOS | O40: 1554 | P40: 1732.12 | Q40: Unidad(es) | S40: OV 0001-00001174 | T40: KG DE CARNE CAPON PORCINOS
B41: Publicado | C41: Pagado | D41: 45999 | E41: 46017 | F41: 10614696 | G41: Gapre S R L | H41: LCDP-A 00009-00002082 | J41: 11729239 | K41: 11729239 | N41: KG DE CARNE CAPON PORCINOS PORCINOS | O41: 8758 | P41: 1212 | Q41: Unidad(es) | S41: OV 0001-00001204 | T41: KG DE CARNE CAPON PORCINOS
B42: Publicado | C42: Pagado | D42: 45999 | E42: 46010 | F42: 13508952 | G42: Gapre S R L | H42: LCDP-A 00009-00002081 | J42: 14927392 | K42: 14927392 | N42: PORCINOS | O42: 11146 | P42: 1212 | Q42: kg | S42: OV 0001-00001145 | T42: PORCINOS
B43: Publicado | C43: Pagado | D43: 45993 | E43: 46010 | F43: 385416 | G43: Gapre S R L | H43: LCDP-A 00009-00002080 | J43: 425884.68 | K43: 425884.68 | N43: PORCINOS | O43: 318 | P43: 1212 | Q43: kg | S43: OV 0001-00001181 | T43: PORCINOS
B44: Publicado | C44: Pagado | D44: 45993 | E44: 46010 | F44: 15354828 | G44: Gapre S R L | H44: LCDP-A 00009-00002079 | J44: 16967085 | K44: 16967085 | N44: PORCINOS | O44: 12669 | P44: 1212 | Q44: kg | S44: OV 0001-00001180 | T44: PORCINOS
B45: Publicado | C45: Pagado | D45: 45993 | E45: 46002 | F45: 3765280 | G45: Livolti, Maria | H45: LCDP-A 00001-00000784 | J45: 4160634.4 | K45: 4160634.4 | N45: PORCINOS | O45: 1864 | P45: 2020 | Q45: kg | S45: OV 0001-00001178 | T45: PORCINOS
B46: Publicado | C46: Pagado | D46: 45992 | E46: 46010 | F46: 10271700 | G46: Gapre S R L | H46: LCDP-A 00009-00002078 | J46: 11350228 | K46: 11350228 | N46: PORCINOS | O46: 8475 | P46: 1212 | Q46: kg | S46: OV 0001-00001179 | T46: PORCINOS
B47: Publicado | C47: Pagado | D47: 45992 | E47: 46003 | F47: 11947896 | G47: Gapre S R L | H47: LCDP-A 00009-00002077 | J47: 13202425 | K47: 13202425 | N47: PORCINOS | O47: 9858 | P47: 1212 | Q47: kg | S47: OV 0001-00000882 | T47: PORCINOS

Sheet venta_nico
A1: FACTURACION | B1: Cantidades | C1: kg_promedio | D1: Precio promedio | E1: Final +IVA | F1: Subtotal
A2: CAPON | B2: 1280 | C2: 114.36 | D2: 2427.63 | E2: 2592.95 | F2: =B2*C2*E2 -> 3.795581e+08
A3: CHANCHA | B3: 11 | C3: 263.4 | D3: 1510.79 | E3: 1620.15 | F3: =B3*C3*E3 -> 4694222.6

Sheet rubros
A1: RUBRO | B1: ID
A2: NUTRICIÓN | B2: 1
A3: PERSONAL | B3: 2
A4: SANIDAD | B4: 3
A5: GENÉTICA | B5: 4
A6: FLETES | B6: 5
A7: ENERGÍA | B7: 11
A8: MANTENIMIENTO | B8: 6
A9: GASTOS OPERATIVOS | B9: 7
A10: IMPUESTOS | B10: 8
A11: HONORARIOS | B11: 9
A12: SERVICIOS | B12: 10

Sheet nutri&rrhh
A1: Fecha de Factura/Recibo | B1: Nombre de la empresa a mostrar en la factura | C1: Número | D1: Total con signo | E1: Líneas de factura/Etiqueta | F1: Líneas de factura/Cantidad | G1: Líneas de factura/Precio unitario | H1: Líneas de factura/Unidad de medida | I1: Líneas de factura/Producto | J1: Concepto | K1: Tipo de Gasto 1 | L1: Tipo de Gasto 2 | M1: CCO - SECTOR
A2: 46112 | B2: Nutran | C2: nico_1 | D2: -21985644 | E2: fason_calculo_alimentos_1 | F2: 423330 | G2: 47 | H2: KG | I2: Nutrición | J2: OPEX | K2: VARIABLE | L2: DIRECTO
A3: 46112 | B3: Alimento | C3: nico_2 | D3: -1.7861696e+08 | E3: calculo_alimentos_total | F3: 432780 | G3: 412.72 | H3: KG | I3: Nutrición | J3: OPEX | K3: VARIABLE | L3: DIRECTO
A4: 46112 | B4: Nutran | C4: nico_3 | D4: -454608 | E4: embolsado_calculo_alimentos_3 | F4: 15785 | G4: 28.8 | H4: KG | I4: Nutrición | J4: OPEX | K4: OPEX | L4: VARIABLE
A5: 46112 | B5: HABERES | C5: remu | D5: 49609364 | E5: planilla de andres | F5: 23 | G5: -2156928.9 | H5: #RRHH | I5: Personal | J5: OPEX | K5: OPEX | L5: FIJO

Sheet gastos_facturas
A1: Fecha de Factura/Recibo | B1: Nombre de la empresa a mostrar en la factura | C1: Número | D1: Total con signo | E1: Líneas de factura/Etiqueta | F1: Líneas de factura/Cantidad | G1: Líneas de factura/Precio unitario | H1: Líneas de factura/Unidad de medida | I1: Líneas de factura/Producto | J1: Concepto | K1: Tipo de Gasto 1 | L1: Tipo de Gasto 2 | M1: CCO - SECTOR
A2: 46112 | B2: Servicio Nacional De Sanidad Y Calidad Agroalimentaria Senasa | C2: OC/2026/0155 | D2: -21642.72 | E2: IMPUESTO (C) | F2: 1 | G2: 21642.72 | H2: Unidad(es) | I2: IMPUESTO (C) | J2: OPEX | K2: FIJO | L2: DIRECTO
A3: 46112 | B3: Correa, Natalia Erica | C3: OC/2026/0152 | D3: -51343.54 | E3: Honorarios (C) | F3: 1 | G3: 51343.54 | H3: Unidad(es) | I3: Honorarios (C) | J3: OPEX | K3: VARIABLE | L3: INDIRECTO
A4: 46112 | B4: Barrera, Adrian Jesus | C4: FA-C 00001-00000437 | D4: -225600 | E4: Gastos Operativos (C) | F4: 47 | G4: 4800 | H4: Unidad(es) | I4: Gastos Operativos (C) | J4: OPEX | K4: VARIABLE | L4: INDIRECTO
A5: 46112 | B5: Esperanza Distribuciones Srl | C5: FA-A 00026-00530141 | D5: -127060.24 | E5: Sanidad (C) Despadac | F5: 1 | G5: 105008.46 | H5: Unidad(es) | I5: Sanidad (C) | J5: OPEX | K5: VARIABLE | L5: DIRECTO
A6: 46112 | B6: Agroceres Pic Argentina S A | C6: FA-A 00008-00151527 | D6: -913335.72 | E6: Genetica (C) Dosis AGPIC337 IU ROY I | F6: 62 | G6: 10264.94 | H6: Unidad(es) | I6: Genetica (C) | J6: OPEX | K6: VARIABLE | L6: DIRECTO | U6: Genetica (C)
A7: 46112 | B7: Agroceres Pic Argentina S A | C7: FA-A 00008-00015564 | D7: -279170.81 | E7: Genetica (C) DOSIS AG1020 ABUELO VISTA | F7: 3 | G7: 76906.56 | H7: Unidad(es) | I7: Genetica (C) | J7: OPEX | K7: VARIABLE | L7: DIRECTO
A8: 46112 | B8: Comercial Uritorco S. R. L. | C8: FA-A 00001-00009311 | D8: -293208.43 | E8: Mantenimiento (C) Espiga c/rosca, espig.dob., piton cincado, taco universal, teflon , poliet, espiga , aerosol rojo, azul, verde, alambre recocido negro | F8: 1 | G8: 242321.02 | H8: Unidad(es) | I8: Mantenimiento (C) | J8: OPEX | K8: VARIABLE | L8: INDIRECTO
A9: 46111 | B9: Topigs Norsvin Argentina S.R.L. | C9: FA-A 00011-00034214 | D9: -265043.43 | E9: Genetica (C) Semen Linea TLLL Pedido correspondientess del 16 al 22 de marzo | F9: 96 | G9: 2281.71 | H9: Unidad(es) | I9: Genetica (C) | J9: OPEX | K9: VARIABLE | L9: DIRECTO
A10: 46111 | B10: Agroceres Pic Argentina S A | C10: FA-A 00008-00151320 | D10: -513577.89 | E10: Genetica (C) Dosis AGPIC337 IU ROY I | F10: 30 | G10: 10264.94 | H10: Unidad(es) | I10: Genetica (C) | J10: OPEX | K10: VARIABLE | L10: DIRECTO
A11: 46111 | B11: Bca Distribuciones Sa | C11: FA-A 00001-00005944 | D11: -303732.45 | E11: Mantenimiento (C) TEE EPOXI HH 1/2 | F11: 20 | G11: 1520.5179 | H11: Unidad(es) | I11: Mantenimiento (C) | J11: OPEX | K11: VARIABLE | L11: INDIRECTO
A12: 46109 | B12: Trt S.A. | C12: FA-A 00012-00058283 | D12: -839050 | E12: Sanidad (C) cheque nª 57879404 | F12: 1 | G12: 839050 | H12: Unidad(es) | I12: Sanidad (C) | J12: OPEX | K12: VARIABLE | L12: DIRECTO
A13: 46108 | B13: Servicio Nacional De Sanidad Y Calidad Agroalimentaria Senasa | C13: OC/2026/0151 | D13: -22857.09 | E13: IMPUESTO (C) | F13: 1 | G13: 22857.09 | H13: Unidad(es) | I13: IMPUESTO (C) | J13: OPEX | K13: FIJO | L13: DIRECTO
A14: 46108 | B14: Asociacion Empleados De Comercio De Rosario | C14: OC/2026/0150 | D14: -522382.82 | E14: Gastos Operativos (C) Requerimiento | F14: 1 | G14: 522382.82 | H14: Unidad(es) | I14: Gastos Operativos (C) | J14: OPEX | K14: VARIABLE | L14: INDIRECTO
A15: 46108 | B15: ARCA 931 | C15: OC/2026/0149 | D15: -4772839.3 | E15: IMPUESTO (C) Obra Social Diciembre | F15: 1 | G15: 4772839.3 | H15: Unidad(es) | I15: IMPUESTO (C) | J15: OPEX | K15: VARIABLE | L15: INDIRECTO
A16: 46108 | B16: Carrizo, Juan Mario | C16: FA-C 00001-00000217 | D16: -520000 | E16: Mantenimiento (C) reparación de bomba sumergible (Bomba quemada de worms) | F16: 1 | G16: 520000 | H16: Unidad(es) | I16: Mantenimiento (C) | J16: OPEX | K16: VARIABLE | L16: DIRECTO
A17: 46108 | B17: Seproa S.R.L. | C17: FA-A 00004-00006273 | D17: -104544 | E17: Gastos Operativos (C) | F17: 20 | G17: 4320 | H17: Unidad(es) | I17: Gastos Operativos (C) | J17: OPEX | K17: VARIABLE | L17: DIRECTO
A18: 46107 | B18: Servicio Nacional De Sanidad Y Calidad Agroalimentaria Senasa | C18: OC/2026/0148 | D18: -10785.37 | E18: IMPUESTO (C) | F18: 1 | G18: 10785.37 | H18: Unidad(es) | I18: IMPUESTO (C) | J18: OPEX | K18: FIJO | L18: DIRECTO
... A106: 46082 | B106: Pick Sas | C106: FA-A 00002-00027498 | D106: -337305.65 | E106: Gastos Operativos (C) | F106: 1 | G106: 278765 | H106: Unidad(es) | I106: Gastos Operativos (C) | J106: OPEX | K106: FIJO | L106: INDIRECTO

Sheet BD Gastos_DICIEMBRE
A1: VALIDO | B1: id_factura | C1: FECHA CARGA | D1: # ID GASTO | E1: CANAL | F1: CONCEPTO | G1: TIPO 1 (DIRECTO/INDIRECTO) | H1: TIPO 2 (FIJO/VARIABLE) | I1: RUBRO | J1: AREA | K1: UN | L1: PRODUCTO | M1: PROVEEDOR | N1: DESCRIPCION | O1: UM | P1: Q | Q1: P | R1: MONEDA | S1: SUBTOTAL | T1: T.C | U1: IVA | V1: TOTAL | W1: COMENTARIO | X1: id_rubro | Y1: rubro_final | Z1: deuda_ok | AA1: capex_ok | AB1: opex_ok
A2: 1 | B2: nico_1 | C2: 45992 | D2: =B2 -> nico_1 | E2: 1 | F2: OPEX | G2: DIRECTO | H2: VARIABLE | I2: Nutrición | J2: PORCINOS | K2: PORCINOS | M2: Nutran | N2: fason_calculo_alimentos_1 | O2: kg | P2: 502888 | Q2: 35 | R2: ARS | S2: =P2*Q2 -> 17601080 | T2: 1 | U2: 0 | V2: =S2 -> 17601080 | X2: =_xlfn.XLOOKUP(I2,id_rubro!A:A,id_rubro!B:B) -> 2 | Y2: =_xlfn.XLOOKUP(X2,id_rubro!B:B,id_rubro!C:C) -> Nutrición | Z2: =IF(TRIM(F2)="DEUDA",1,0) -> 0 | AA2: =IF(TRIM($F2)="capex",1,0) -> 0 | AB2: =IF(TRIM($F2)="opex",1,0) -> 1
A3: 1 | B3: nico_2 | C3: 45992 | D3: =B3 -> nico_2 | E3: 2 | F3: OPEX | G3: DIRECTO | H3: VARIABLE | I3: Nutrición | J3: PORCINOS | K3: PORCINOS | M3: Alimento | N3: calculo_alimentos_2 | O3: kg | P3: 510488 | Q3: 353.49 | R3: ARS | S3: =P3*Q3 -> 1.804524e+08 | T3: 1 | U3: 0 | V3: =S3 -> 1.804524e+08 | X3: =_xlfn.XLOOKUP(I3,id_rubro!A:A,id_rubro!B:B) -> 2 | Y3: =_xlfn.XLOOKUP(X3,id_rubro!B:B,id_rubro!C:C) -> Nutrición | Z3: =IF(TRIM(F3)="DEUDA",1,0) -> 0 | AA3: =IF(TRIM($F3)="capex",1,0) -> 0 | AB3: =IF(TRIM($F3)="opex",1,0) -> 1
A4: 1 | B4: nico_3 | C4: 45992 | D4: =B4 -> nico_3 | E4: 1 | F4: OPEX | G4: DIRECTO | H4: VARIABLE | I4: Nutrición | M4: Nutran | N4: embolsado_calculo_alimentos_3 | O4: kg | P4: 10355 | Q4: 29 | R4: ARS | S4: =P4*Q4 -> 300295 | T4: 1 | U4: 0 | V4: =S4 -> 300295 | X4: =_xlfn.XLOOKUP(I4,id_rubro!A:A,id_rubro!B:B) -> 2 | Y4: =_xlfn.XLOOKUP(X4,id_rubro!B:B,id_rubro!C:C) -> Nutrición | Z4: =IF(TRIM(F4)="DEUDA",1,0) -> 0 | AA4: =IF(TRIM($F4)="capex",1,0) -> 0 | AB4: =IF(TRIM($F4)="opex",1,0) -> 1
A5: 0 | B5: c2_1 | C5: 45992 | D5: c2_2 | E5: 2 | F5: OPEX | G5: DIRECTO | H5: FIJO | I5: Personal | J5: PORCINOS | K5: PORCINOS | L5: Mariano santos | M5: NA | N5: alquiler | O5: Unidad(es) | P5: 1 | Q5: 560000 | R5: ARS | S5: =Q5 -> 560000 | T5: 1 | U5: 0 | V5: =S5 -> 560000 | X5: =_xlfn.XLOOKUP(I5,id_rubro!A:A,id_rubro!B:B) -> 9 | Y5: =_xlfn.XLOOKUP(X5,id_rubro!B:B,id_rubro!C:C) -> Personal | Z5: =IF(TRIM(F5)="DEUDA",1,0) -> 0 | AA5: =IF(TRIM($F5)="capex",1,0) -> 0 | AB5: =IF(TRIM($F5)="opex",1,0) -> 1
A6: 0 | B6: c2_2 | C6: 45992 | D6: c2_2 | E6: 2 | F6: OPEX | G6: DIRECTO | H6: FIJO | I6: Personal | J6: PORCINOS | K6: PORCINOS | L6: Mariano santos | M6: NA | N6: sueldo 2 | O6: Unidad(es) | P6: 1 | Q6: 287000 | R6: ARS | S6: =Q6 -> 287000 | T6: 1 | U6: 0 | V6: =S6 -> 287000 | X6: =_xlfn.XLOOKUP(I6,id_rubro!A:A,id_rubro!B:B) -> 9 | Y6: =_xlfn.XLOOKUP(X6,id_rubro!B:B,id_rubro!C:C) -> Personal | Z6: =IF(TRIM(F6)="DEUDA",1,0) -> 0 | AA6: =IF(TRIM($F6)="capex",1,0) -> 0 | AB6: =IF(TRIM($F6)="opex",1,0) -> 1
A7: 1 | B7: c2_3 | C7: 45992 | D7: c2_3 | E7: 2 | F7: OPEX | G7: DIRECTO | H7: FIJO | I7: Personal | J7: PORCINOS | K7: PORCINOS | L7: Capurro Nicolas | M7: NA | N7: viaticos | O7: Unidad(es) | P7: 1 | Q7: 216000 | R7: ARS | S7: =P7*Q7 -> 216000 | T7: 1 | U7: 0 | V7: =S7 -> 216000 | X7: =_xlfn.XLOOKUP(I7,id_rubro!A:A,id_rubro!B:B) -> 9 | Y7: =_xlfn.XLOOKUP(X7,id_rubro!B:B,id_rubro!C:C) -> Personal | Z7: =IF(TRIM(F7)="DEUDA",1,0) -> 0 | AA7: =IF(TRIM($F7)="capex",1,0) -> 0 | AB7: =IF(TRIM($F7)="opex",1,0) -> 1
A8: 1 | B8: remu | C8: 45992 | D8: remu | E8: 1 | F8: OPEX | G8: DIRECTO | H8: FIJO | I8: Personal | J8: PORCINOS | K8: PORCINOS | M8: HABERES | N8: planilla de andres | O8: UN | P8: 23 | Q8: 0 | R8: ARS | S8: 52929850 | T8: 1 | U8: =IFERROR(V8/S8-1,0) -> 0 | V8: =S8 -> 52929850 | X8: =_xlfn.XLOOKUP(I8,id_rubro!A:A,id_rubro!B:B) -> 9 | Y8: =_xlfn.XLOOKUP(X8,id_rubro!B:B,id_rubro!C:C) -> Personal | Z8: =IF(TRIM(F8)="DEUDA",1,0) -> 0 | AA8: =IF(TRIM($F8)="capex",1,0) -> 0 | AB8: =IF(TRIM($F8)="opex",1,0) -> 1
A9: 1 | B9: BBDD IMPUESTOS | C9: 45901 | D9: BBDD_IMPUESTOS | E9: 1 | F9: OPEX | G9: INDIRECTO | H9: FIJO | I9: Impuestos | M9: Banco Bica | N9: Gastos Bancarios | O9: UN | P9: 1 | Q9: 1006934 | R9: ARS | S9: =Q9 -> 1006934 | T9: 1 | U9: 0 | V9: 1006934 | X9: =_xlfn.XLOOKUP(I9,id_rubro!A:A,id_rubro!B:B) -> 11 | Y9: =_xlfn.XLOOKUP(X9,id_rubro!B:B,id_rubro!C:C) -> Impuestos | Z9: =IF(TRIM(F9)="DEUDA",1,0) -> 0 | AA9: =IF(TRIM($F9)="capex",1,0) -> 0 | AB9: =IF(TRIM($F9)="opex",1,0) -> 1
A10: 1 | B10: BBDD IMPUESTOS | C10: 45901 | D10: BBDD_IMPUESTOS | E10: 1 | F10: OPEX | G10: INDIRECTO | H10: FIJO | I10: Impuestos | M10: ARCA | N10: IB | O10: UN | P10: 1 | Q10: 4999769.6 | R10: ARS | S10: =Q10 -> 4999769.6 | T10: 1 | U10: 0 | V10: 4999769.6 | X10: =_xlfn.XLOOKUP(I10,id_rubro!A:A,id_rubro!B:B) -> 11 | Y10: =_xlfn.XLOOKUP(X10,id_rubro!B:B,id_rubro!C:C) -> Impuestos | Z10: =IF(TRIM(F10)="DEUDA",1,0) -> 0 | AA10: =IF(TRIM($F10)="capex",1,0) -> 0 | AB10: =IF(TRIM($F10)="opex",1,0) -> 1
A11: 1 | B11: BBDD IMPUESTOS | C11: 45901 | D11: BBDD_IMPUESTOS | E11: 1 | F11: OPEX | G11: INDIRECTO | H11: FIJO | I11: Impuestos | M11: Municipalidad Arroyo seco | N11: DREI | O11: UN | P11: 1 | Q11: 2025348 | R11: ARS | S11: =Q11 -> 2025348 | T11: 1 | U11: 0 | V11: 2025348 | X11: =_xlfn.XLOOKUP(I11,id_rubro!A:A,id_rubro!B:B) -> 11 | Y11: =_xlfn.XLOOKUP(X11,id_rubro!B:B,id_rubro!C:C) -> Impuestos | Z11: =IF(TRIM(F11)="DEUDA",1,0) -> 0 | AA11: =IF(TRIM($F11)="capex",1,0) -> 0 | AB11: =IF(TRIM($F11)="opex",1,0) -> 1
A12: 1 | B12: BBDD IMPUESTOS | C12: 45901 | D12: BBDD_IMPUESTOS | E12: 1 | F12: OPEX | G12: INDIRECTO | H12: FIJO | I12: Impuestos | M12: UATRE | N12: SINDICATOS CARNE | O12: UN | P12: 1 | Q12: 548875.69 | R12: ARS | S12: =Q12 -> 548875.69 | T12: 1 | U12: 0 | V12: 548876 | X12: =_xlfn.XLOOKUP(I12,id_rubro!A:A,id_rubro!B:B) -> 11 | Y12: =_xlfn.XLOOKUP(X12,id_rubro!B:B,id_rubro!C:C) -> Impuestos | Z12: =IF(TRIM(F12)="DEUDA",1,0) -> 0 | AA12: =IF(TRIM($F12)="capex",1,0) -> 0 | AB12: =IF(TRIM($F12)="opex",1,0) -> 1
A13: 1 | B13: BBDD IMPUESTOS | C13: 45901 | D13: BBDD_IMPUESTOS | E13: 1 | F13: OPEX | G13: INDIRECTO | H13: FIJO | I13: Impuestos | M13: AEC/INACAP | N13: SINDICATOS COMERCIO | O13: UN | P13: 1 | Q13: 160037.18 | R13: ARS | S13: =Q13 -> 160037.18 | T13: 1 | U13: 0 | V13: 160037.18 | X13: =_xlfn.XLOOKUP(I13,id_rubro!A:A,id_rubro!B:B) -> 11 | Y13: =_xlfn.XLOOKUP(X13,id_rubro!B:B,id_rubro!C:C) -> Impuestos | Z13: =IF(TRIM(F13)="DEUDA",1,0) -> 0 | AA13: =IF(TRIM($F13)="capex",1,0) -> 0 | AB13: =IF(TRIM($F13)="opex",1,0) -> 1

Sheet id_rubro
A1: raw | B1: id | C1: rubro_fina
B2: 1 | C2: Servicios
A3: Alimento para Animales (C) | B3: 2 | C3: Nutrición
A4: Alquiler (C) | B4: 1 | C4: Servicios
A5: Energia (C) | B5: 3 | C5: Energía
A6: Fason(C) | B6: 4 | C6: Fasón
A7: Fletes (C) | B7: 1 | C7: Servicios
A8: Gastos Medicos (C) | B8: 5 | C8: Gastos Médicos
A9: Gastos Operativos (C) | B9: 6 | C9: Gastos Operativos
A10: Genetica (C) | B10: 7 | C10: Genética
A11: Honorario Contador (C) | B11: 1 | C11: Servicios
A12: Honorarios Ingenieros (C) | B12: 1 | C12: Servicios
A13: Honorarios Veterinario (C) | B13: 1 | C13: Servicios
A14: Mantenimiento (C) | B14: 8 | C14: Mentenimiento
... A25: Acuerdo PigBank | B25: 12 | C25: Deuda
