Workbook

Sheet lote_todos
A1: LOTE | B1: >=0 | C1: Mortandad-SITIO 2 | G1: CALZIM
C2: Mortandad-SITIO 3 | D2: =SUMIFS(produccion!G:G,produccion!$A:$A,B1) -> -0.094058413
B5: TOTALES | F5: FIJO/VARIABLE | J5: DIRECTO/INDERECTO
B6: VENTAS SITIO 3 | C6: =D55 -> 3.0382462e+08 | F6: VENTAS | G6: =C6 -> 3.0382462e+08 | J6: VENTAS | K6: =G6 -> 3.0382462e+08
B7: OPEX | C7: =SUMIFS(BBDD_GASTOS_FINAL!$Z:$Z,BBDD_GASTOS_FINAL!$V:$V,lote_todos!$B$1,BBDD_GASTOS_FINAL!$J:$J,"OPEX")*-1 -> 2.5052749e+08 | F7: Fijo | G7: =SUMIFS(BBDD_GASTOS_FINAL!$Z:$Z,BBDD_GASTOS_FINAL!$V:$V,lote_todos!$B$1,BBDD_GASTOS_FINAL!$J:$J,"OPEX",BBDD_GASTOS_FINAL!$K:$K,lote_todos!F7)*-1 -> 5405487.4 | J7: DIRECTO | K7: =SUMIFS(BBDD_GASTOS_FINAL!$Z:$Z,BBDD_GASTOS_FINAL!$V:$V,lote_todos!$B$1,BBDD_GASTOS_FINAL!$J:$J,"OPEX",BBDD_GASTOS_FINAL!$L:$L,lote_todos!J7)*-1 -> 25488574
B8: UTILIDAD | C8: =C6-C7 -> 53297135 | F8: Variable | G8: =SUMIFS(BBDD_GASTOS_FINAL!$Z:$Z,BBDD_GASTOS_FINAL!$V:$V,lote_todos!$B$1,BBDD_GASTOS_FINAL!$J:$J,"OPEX",BBDD_GASTOS_FINAL!$K:$K,lote_todos!F8)*-1 -> 44585205 | J8: INDIRECTO | K8: =SUMIFS(BBDD_GASTOS_FINAL!$Z:$Z,BBDD_GASTOS_FINAL!$V:$V,lote_todos!$B$1,BBDD_GASTOS_FINAL!$J:$J,"OPEX",BBDD_GASTOS_FINAL!$L:$L,lote_todos!J8)*-1 -> 24502119
B9: CAPEX | C9: =SUMIFS(BBDD_GASTOS_FINAL!$Y:$Y,BBDD_GASTOS_FINAL!$J:$J,lote_todos!B9) -> 0
B10: DEUDA | C10: =SUMIFS(BBDD_GASTOS_FINAL!$Z:$Z,BBDD_GASTOS_FINAL!$J:$J,lote_todos!B10)*-1 -> 221959.33
B11: Flujo de Caja al Accionista | C11: =C6-C7-C9-C10 -> 53075176 | F11: Flujo de Caja al Accionista | G11: =G6-G7-G8 -> 2.5383393e+08 | J11: Flujo de Caja al Accionista | K11: =K6-K7-K8 -> 2.5383393e+08
A13: id | B13: 4 | E13: id | F13: 3 | I13: id | J13: 7 | M13: id
B14: GESTACIÓN | F14: MATERNIDAD | J14: SITIO 2
B15: OPEX | D15: =SUM(D16:D26) -> 47491108 | F15: OPEX | H15: =SUM(H16:H26) -> 36382907 | J15: OPEX | L15: =SUM(L16:L26) -> 36382907 | M15: 1
A16: 1 | B16: =D16/$D$15 -> 0.30685958 | C16: NUTRICIÓN | D16: =SUMIFS(BBDD_GASTOS_FINAL!$Z:$Z,BBDD_GASTOS_FINAL!$V:$V,$B$1,BBDD_GASTOS_FINAL!$W:$W,$B$14,BBDD_GASTOS_FINAL!$AC:$AC,lote_todos!$C16)*-1 -> 14573101 | E16: 1 | F16: =H16/$H$15 -> 0.20759624 | G16: NUTRICIÓN | H16: =SUMIFS(BBDD_GASTOS_FINAL!$Z:$Z,BBDD_GASTOS_FINAL!$V:$V,$B$1,BBDD_GASTOS_FINAL!$W:$W,$F$14,BBDD_GASTOS_FINAL!$AC:$AC,$G16)*-1 -> 7552954.8 | I16: 1 | J16: =L16/$L$15 -> 0.20759624 | K16: NUTRICIÓN | L16: =SUMIFS(BBDD_GASTOS_FINAL!$Z:$Z,BBDD_GASTOS_FINAL!$V:$V,$B$1,BBDD_GASTOS_FINAL!$W:$W,$F$14,BBDD_GASTOS_FINAL!$AC:$AC,$G16)*-1 -> 7552954.8 | M16: 1
A17: =A16+1 -> 2 | B17: =D17/$D$15 -> 0.33888286 | C17: PERSONAL | D17: =SUMIFS(BBDD_GASTOS_FINAL!$Z:$Z,BBDD_GASTOS_FINAL!$V:$V,$B$1,BBDD_GASTOS_FINAL!$W:$W,$B$14,BBDD_GASTOS_FINAL!AC:AC,lote_todos!$C17)*-1 -> 16093922 | E17: 2 | F17: =H17/$H$15 -> 0.42865634 | G17: PERSONAL | H17: =SUMIFS(BBDD_GASTOS_FINAL!$Z:$Z,BBDD_GASTOS_FINAL!$V:$V,$B$1,BBDD_GASTOS_FINAL!$W:$W,$F$14,BBDD_GASTOS_FINAL!$AC:$AC,$G17)*-1 -> 15595764 | I17: =I16+1 -> 2 | J17: =L17/$L$15 -> 0.42865634 | K17: PERSONAL | L17: =SUMIFS(BBDD_GASTOS_FINAL!$Z:$Z,BBDD_GASTOS_FINAL!$V:$V,$B$1,BBDD_GASTOS_FINAL!$W:$W,$F$14,BBDD_GASTOS_FINAL!$AC:$AC,$G17)*-1 -> 15595764 | M17: =M16+1 -> 2
A18: =A17+1 -> 3 | B18: =D18/$D$15 -> 0.0086120867 | C18: SANIDAD | D18: =SUMIFS(BBDD_GASTOS_FINAL!$Z:$Z,BBDD_GASTOS_FINAL!$V:$V,$B$1,BBDD_GASTOS_FINAL!$W:$W,$B$14,BBDD_GASTOS_FINAL!AC:AC,lote_todos!$C18)*-1 -> 408997.54 | E18: 3 | F18: =H18/$H$15 -> 0.013095908 | G18: SANIDAD | H18: =SUMIFS(BBDD_GASTOS_FINAL!$Z:$Z,BBDD_GASTOS_FINAL!$V:$V,$B$1,BBDD_GASTOS_FINAL!$W:$W,$F$14,BBDD_GASTOS_FINAL!$AC:$AC,$G18)*-1 -> 476467.21 | I18: =I17+12 -> 14 | J18: =L18/$L$15 -> 0.013095908 | K18: SANIDAD | L18: =SUMIFS(BBDD_GASTOS_FINAL!$Z:$Z,BBDD_GASTOS_FINAL!$V:$V,$B$1,BBDD_GASTOS_FINAL!$W:$W,$F$14,BBDD_GASTOS_FINAL!$AC:$AC,$G18)*-1 -> 476467.21 | M18: =M17+1 -> 3
A19: =A18+1 -> 4 | B19: =D19/$D$15 -> 0.11752701 | C19: GENÉTICA | D19: =SUMIFS(BBDD_GASTOS_FINAL!$Z:$Z,BBDD_GASTOS_FINAL!$V:$V,$B$1,BBDD_GASTOS_FINAL!$W:$W,$B$14,BBDD_GASTOS_FINAL!AC:AC,lote_todos!$C19)*-1 -> 5581488 | E19: 4 | F19: =H19/$H$15 -> 0 | G19: GENÉTICA | H19: =SUMIFS(BBDD_GASTOS_FINAL!$Z:$Z,BBDD_GASTOS_FINAL!$V:$V,$B$1,BBDD_GASTOS_FINAL!$W:$W,$F$14,BBDD_GASTOS_FINAL!$AC:$AC,$G19)*-1 -> 0 | I19: =I18+1 -> 15 | J19: =L19/$L$15 -> 0 | K19: GENÉTICA | L19: =SUMIFS(BBDD_GASTOS_FINAL!$Z:$Z,BBDD_GASTOS_FINAL!$V:$V,$B$1,BBDD_GASTOS_FINAL!$W:$W,$F$14,BBDD_GASTOS_FINAL!$AC:$AC,$G19)*-1 -> 0 | M19: =M18+1 -> 4
A20: =A19+1 -> 5 | B20: =D20/$D$15 -> 0 | C20: FLETES | D20: =SUMIFS(BBDD_GASTOS_FINAL!$Z:$Z,BBDD_GASTOS_FINAL!$V:$V,$B$1,BBDD_GASTOS_FINAL!$W:$W,$B$14,BBDD_GASTOS_FINAL!AC:AC,lote_todos!$C20)*-1 -> 0 | E20: 5 | F20: =H20/$H$15 -> 0 | G20: FLETES | H20: =SUMIFS(BBDD_GASTOS_FINAL!$Z:$Z,BBDD_GASTOS_FINAL!$V:$V,$B$1,BBDD_GASTOS_FINAL!$W:$W,$F$14,BBDD_GASTOS_FINAL!$AC:$AC,$G20)*-1 -> 0 | I20: =I19+1 -> 16 | J20: =L20/$L$15 -> 0 | K20: FLETES | L20: =SUMIFS(BBDD_GASTOS_FINAL!$Z:$Z,BBDD_GASTOS_FINAL!$V:$V,$B$1,BBDD_GASTOS_FINAL!$W:$W,$F$14,BBDD_GASTOS_FINAL!$AC:$AC,$G20)*-1 -> 0 | M20: =M19+1 -> 5
A21: =A20+1 -> 6 | B21: =D21/$D$15 -> 0.063587202 | C21: ENERGÍA | D21: =SUMIFS(BBDD_GASTOS_FINAL!$Z:$Z,BBDD_GASTOS_FINAL!$V:$V,$B$1,BBDD_GASTOS_FINAL!$W:$W,$B$14,BBDD_GASTOS_FINAL!AC:AC,lote_todos!$C21)*-1 -> 3019826.7 | E21: 6 | F21: =H21/$H$15 -> 0.083001248 | G21: ENERGÍA | H21: =SUMIFS(BBDD_GASTOS_FINAL!$Z:$Z,BBDD_GASTOS_FINAL!$V:$V,$B$1,BBDD_GASTOS_FINAL!$W:$W,$F$14,BBDD_GASTOS_FINAL!$AC:$AC,$G21)*-1 -> 3019826.7 | I21: =I20+1 -> 17 | J21: =L21/$L$15 -> 0.083001248 | K21: ENERGÍA | L21: =SUMIFS(BBDD_GASTOS_FINAL!$Z:$Z,BBDD_GASTOS_FINAL!$V:$V,$B$1,BBDD_GASTOS_FINAL!$W:$W,$F$14,BBDD_GASTOS_FINAL!$AC:$AC,$G21)*-1 -> 3019826.7 | M21: =M20+1 -> 6
A22: =A21+1 -> 7 | B22: =D22/$D$15 -> 0 | C22: MENTENIMIENTO | D22: =SUMIFS(BBDD_GASTOS_FINAL!$Z:$Z,BBDD_GASTOS_FINAL!$V:$V,$B$1,BBDD_GASTOS_FINAL!$W:$W,$B$14,BBDD_GASTOS_FINAL!AC:AC,lote_todos!$C22)*-1 -> 0 | E22: 7 | F22: =H22/$H$15 -> 0 | G22: MENTENIMIENTO | H22: =SUMIFS(BBDD_GASTOS_FINAL!$Z:$Z,BBDD_GASTOS_FINAL!$V:$V,$B$1,BBDD_GASTOS_FINAL!$W:$W,$F$14,BBDD_GASTOS_FINAL!$AC:$AC,$G22)*-1 -> 0 | I22: =I21+1 -> 18 | J22: =L22/$L$15 -> 0 | K22: MENTENIMIENTO | L22: =SUMIFS(BBDD_GASTOS_FINAL!$Z:$Z,BBDD_GASTOS_FINAL!$V:$V,$B$1,BBDD_GASTOS_FINAL!$W:$W,$F$14,BBDD_GASTOS_FINAL!$AC:$AC,$G22)*-1 -> 0 | M22: =M21+1 -> 7
A23: =A22+1 -> 8 | B23: =D23/$D$15 -> 0.11336253 | C23: GASTOS OPERATIVOS | D23: =SUMIFS(BBDD_GASTOS_FINAL!$Z:$Z,BBDD_GASTOS_FINAL!$V:$V,$B$1,BBDD_GASTOS_FINAL!$W:$W,$B$14,BBDD_GASTOS_FINAL!AC:AC,lote_todos!$C23)*-1 -> 5383712.4 | E23: 8 | F23: =H23/$H$15 -> 0.14611924 | G23: GASTOS OPERATIVOS | H23: =SUMIFS(BBDD_GASTOS_FINAL!$Z:$Z,BBDD_GASTOS_FINAL!$V:$V,$B$1,BBDD_GASTOS_FINAL!$W:$W,$F$14,BBDD_GASTOS_FINAL!$AC:$AC,$G23)*-1 -> 5316242.7 | I23: =I22+1 -> 19 | J23: =L23/$L$15 -> 0.14611924 | K23: GASTOS OPERATIVOS | L23: =SUMIFS(BBDD_GASTOS_FINAL!$Z:$Z,BBDD_GASTOS_FINAL!$V:$V,$B$1,BBDD_GASTOS_FINAL!$W:$W,$F$14,BBDD_GASTOS_FINAL!$AC:$AC,$G23)*-1 -> 5316242.7 | M23: =M22+1 -> 8
A24: =A23+1 -> 9 | B24: =D24/$D$15 -> 0.037984074 | C24: IMPUESTOS | D24: =SUMIFS(BBDD_GASTOS_FINAL!$Z:$Z,BBDD_GASTOS_FINAL!$V:$V,$B$1,BBDD_GASTOS_FINAL!$W:$W,$B$14,BBDD_GASTOS_FINAL!AC:AC,lote_todos!$C24)*-1 -> 1803905.8 | E24: 9 | F24: =H24/$H$15 -> 0.10432091 | G24: IMPUESTOS | H24: =SUMIFS(BBDD_GASTOS_FINAL!$Z:$Z,BBDD_GASTOS_FINAL!$V:$V,$B$1,BBDD_GASTOS_FINAL!$W:$W,$F$14,BBDD_GASTOS_FINAL!$AC:$AC,$G24)*-1 -> 3795497.8 | I24: =I23+1 -> 20 | J24: =L24/$L$15 -> 0.10432091 | K24: IMPUESTOS | L24: =SUMIFS(BBDD_GASTOS_FINAL!$Z:$Z,BBDD_GASTOS_FINAL!$V:$V,$B$1,BBDD_GASTOS_FINAL!$W:$W,$F$14,BBDD_GASTOS_FINAL!$AC:$AC,$G24)*-1 -> 3795497.8 | M24: =M23+1 -> 9
A25: =A24+1 -> 10 | B25: =D25/$D$15 -> 0.013184659 | C25: HONORARIOS | D25: =SUMIFS(BBDD_GASTOS_FINAL!$Z:$Z,BBDD_GASTOS_FINAL!$V:$V,$B$1,BBDD_GASTOS_FINAL!$W:$W,$B$14,BBDD_GASTOS_FINAL!AC:AC,lote_todos!$C25)*-1 -> 626154.04 | E25: 10 | F25: =H25/$H$15 -> 0.017210116 | G25: HONORARIOS | H25: =SUMIFS(BBDD_GASTOS_FINAL!$Z:$Z,BBDD_GASTOS_FINAL!$V:$V,$B$1,BBDD_GASTOS_FINAL!$W:$W,$F$14,BBDD_GASTOS_FINAL!$AC:$AC,$G25)*-1 -> 626154.04 | I25: =I24+1 -> 21 | J25: =L25/$L$15 -> 0.017210116 | K25: HONORARIOS | L25: =SUMIFS(BBDD_GASTOS_FINAL!$Z:$Z,BBDD_GASTOS_FINAL!$V:$V,$B$1,BBDD_GASTOS_FINAL!$W:$W,$F$14,BBDD_GASTOS_FINAL!$AC:$AC,$G25)*-1 -> 626154.04 | M25: =M24+1 -> 10
B26: =D26/$D$15 -> 0 | C26: SERVICIOS | D26: =SUMIFS(BBDD_GASTOS_FINAL!$Z:$Z,BBDD_GASTOS_FINAL!$V:$V,$B$1,BBDD_GASTOS_FINAL!$W:$W,$B$14,BBDD_GASTOS_FINAL!AC:AC,lote_todos!$C26)*-1 -> 0 | F26: =H26/$H$15 -> 0 | G26: SERVICIOS | H26: =SUMIFS(BBDD_GASTOS_FINAL!$Z:$Z,BBDD_GASTOS_FINAL!$V:$V,$B$1,BBDD_GASTOS_FINAL!$W:$W,$F$14,BBDD_GASTOS_FINAL!$AC:$AC,$G26)*-1 -> 0 | J26: =L26/$L$15 -> 0 | K26: OTROS | L26: =SUMIFS(BBDD_GASTOS_FINAL!$Z:$Z,BBDD_GASTOS_FINAL!$V:$V,$B$1,BBDD_GASTOS_FINAL!$W:$W,$F$14,BBDD_GASTOS_FINAL!$AC:$AC,$G26)*-1 -> 0
F28: COMPRAS EN GESTACION | H28: =D15 -> 47491108 | J28: COMPRAS EN MATERNIDAD | L28: =H29 -> 48462460
B29: VENTAS | D29: =SUMIFS(produccion!$H:$H,produccion!$A:$A,lote_todos!$B$1,produccion!$B:$B,lote_todos!B14) -> 0 | F29: VENTAS | H29: =SUMIFS(produccion!$H:$H,produccion!$A:$A,lote_todos!$B$1,produccion!$B:$B,lote_todos!F14) -> 48462460 | J29: VENTAS | L29: =SUMIFS(produccion!$H:$H,produccion!$A:$A,lote_todos!$B$1,produccion!$B:$B,lote_todos!J14) -> 94822882
B31: UTILDAD | D31: =D29-D15-D28 -> -47491108 | F31: UTILDAD | H31: =H29-H15-H28 -> -35411555 | J31: UTILDAD | L31: =L29-L15-L28 -> 9977515.2
B33: CAPEX | D33: =SUMIFS(BBDD_GASTOS_FINAL!$Y:$Y,BBDD_GASTOS_FINAL!$J:$J,"Capex",BBDD_GASTOS_FINAL!$Z:$Z,$B$13) -> 0 | F33: CAPEX | H33: =SUMIFS(BBDD_GASTOS_FINAL!$Y:$Y,BBDD_GASTOS_FINAL!$J:$J,"Capex",BBDD_GASTOS_FINAL!$Z:$Z,$F$13) -> 0 | J33: CAPEX | L33: =SUMIFS(BBDD_GASTOS_FINAL!$Y:$Y,BBDD_GASTOS_FINAL!$J:$J,"Capex",BBDD_GASTOS_FINAL!$Z:$Z,$J$13) -> 0
B35: DEUDA | D35: =SUMIFS(BBDD_GASTOS_FINAL!$Y:$Y,BBDD_GASTOS_FINAL!$J:$J,"Deuda",BBDD_GASTOS_FINAL!$V:$V,B14) -> 0 | F35: DEUDA | H35: =SUMIFS(BBDD_GASTOS_FINAL!$Y:$Y,BBDD_GASTOS_FINAL!$J:$J,"Deuda",BBDD_GASTOS_FINAL!$V:$V,F14) -> 0 | J35: DEUDA | L35: =SUMIFS(BBDD_GASTOS_FINAL!$Y:$Y,BBDD_GASTOS_FINAL!$J:$J,"deuda",BBDD_GASTOS_FINAL!$V:$V,J14) -> 0
B37: Flujo de Caja al Accionista | D37: =D31-D35-D33 -> -47491108 | F37: Flujo de Caja al Accionista | H37: =H31-H35-H33 -> -35411555 | J37: Flujo de Caja al Accionista | L37: =L31-L35-L33 -> 9977515.2
F38: Margen de utilidad | H38: =H31/H29 -> -0.73070072 | J38: Margen de utilidad | L38: =L31/L29 -> 0.10522265
A39: id | B39: 1 | M39: id
B40: SITIO 3
B41: OPEX | D41: =SUM(D42:D52) -> 1.1888009e+08
A42: 1 | B42: =D42/$D$41 -> 0.75354893 | C42: NUTRICIÓN | D42: =SUMIFS(BBDD_GASTOS_FINAL!$Z:$Z,BBDD_GASTOS_FINAL!$V:$V,$B$1,BBDD_GASTOS_FINAL!$W:$W,$B$40,BBDD_GASTOS_FINAL!$AC:$AC,lote_todos!$C42)*-1 -> 89581964
A43: =A42+1 -> 2 | B43: =D43/$D$41 -> 0.094630505 | C43: PERSONAL | D43: =SUMIFS(BBDD_GASTOS_FINAL!$Z:$Z,BBDD_GASTOS_FINAL!$V:$V,$B$1,BBDD_GASTOS_FINAL!$W:$W,$B$40,BBDD_GASTOS_FINAL!AC:AC,lote_todos!$C43)*-1 -> 11249683
A44: =A43+1 -> 3 | B44: =D44/$D$41 -> 0.0036378494 | C44: SANIDAD | D44: =SUMIFS(BBDD_GASTOS_FINAL!$Z:$Z,BBDD_GASTOS_FINAL!$V:$V,$B$1,BBDD_GASTOS_FINAL!$W:$W,$B$40,BBDD_GASTOS_FINAL!AC:AC,lote_todos!$C44)*-1 -> 432467.86
A45: =A44+1 -> 4 | B45: =D45/$D$41 -> 0 | C45: GENÉTICA | D45: =SUMIFS(BBDD_GASTOS_FINAL!$Z:$Z,BBDD_GASTOS_FINAL!$V:$V,$B$1,BBDD_GASTOS_FINAL!$W:$W,$B$40,BBDD_GASTOS_FINAL!AC:AC,lote_todos!$C45)*-1 -> 0
A46: =A45+1 -> 5 | B46: =D46/$D$41 -> 0.057249672 | C46: FLETES | D46: =SUMIFS(BBDD_GASTOS_FINAL!$Z:$Z,BBDD_GASTOS_FINAL!$V:$V,$B$1,BBDD_GASTOS_FINAL!$W:$W,$B$40,BBDD_GASTOS_FINAL!AC:AC,lote_todos!$C46)*-1 -> 6805846.2
A47: =A46+1 -> 6 | B47: =D47/$D$41 -> 0.025402291 | C47: ENERGÍA | D47: =SUMIFS(BBDD_GASTOS_FINAL!$Z:$Z,BBDD_GASTOS_FINAL!$V:$V,$B$1,BBDD_GASTOS_FINAL!$W:$W,$B$40,BBDD_GASTOS_FINAL!AC:AC,lote_todos!$C47)*-1 -> 3019826.7
A48: =A47+1 -> 7 | B48: =D48/$D$41 -> 0 | C48: MENTENIMIENTO | D48: =SUMIFS(BBDD_GASTOS_FINAL!$Z:$Z,BBDD_GASTOS_FINAL!$V:$V,$B$1,BBDD_GASTOS_FINAL!$W:$W,$B$40,BBDD_GASTOS_FINAL!AC:AC,lote_todos!$C48)*-1 -> 0
A49: =A48+1 -> 8 | B49: =D49/$D$41 -> 0.045036398 | C49: GASTOS OPERATIVOS | D49: =SUMIFS(BBDD_GASTOS_FINAL!$Z:$Z,BBDD_GASTOS_FINAL!$V:$V,$B$1,BBDD_GASTOS_FINAL!$W:$W,$B$40,BBDD_GASTOS_FINAL!AC:AC,lote_todos!$C49)*-1 -> 5353931.1
A50: =A49+1 -> 9 | B50: =D50/$D$41 -> 0.015174162 | C50: IMPUESTOS | D50: =SUMIFS(BBDD_GASTOS_FINAL!$Z:$Z,BBDD_GASTOS_FINAL!$V:$V,$B$1,BBDD_GASTOS_FINAL!$W:$W,$B$40,BBDD_GASTOS_FINAL!AC:AC,lote_todos!$C50)*-1 -> 1803905.8
A51: =A50+1 -> 10 | B51: =D51/$D$41 -> 0.005320193 | C51: HONORARIOS | D51: =SUMIFS(BBDD_GASTOS_FINAL!$Z:$Z,BBDD_GASTOS_FINAL!$V:$V,$B$1,BBDD_GASTOS_FINAL!$W:$W,$B$40,BBDD_GASTOS_FINAL!AC:AC,lote_todos!$C51)*-1 -> 632465.02
B52: =D52/$D$41 -> 0 | C52: SERVICIOS | D52: =SUMIFS(BBDD_GASTOS_FINAL!$Z:$Z,BBDD_GASTOS_FINAL!$V:$V,$B$1,BBDD_GASTOS_FINAL!$W:$W,$B$40,BBDD_GASTOS_FINAL!AC:AC,lote_todos!$C52)*-1 -> 0
B54: COMPRAS EN SITIO 2 | D54: =L29 -> 94822882
B55: VENTAS | D55: =SUMIFS(produccion!$H:$H,produccion!$A:$A,lote_todos!$B$1,produccion!$B:$B,lote_todos!B40) -> 3.0382462e+08
B57: UTILDAD | D57: =D55-D41-D54 -> 90121649
B59: CAPEX | D59: =SUMIFS(BBDD_GASTOS_FINAL!$Y:$Y,BBDD_GASTOS_FINAL!$J:$J,"Capex",BBDD_GASTOS_FINAL!$Z:$Z,$B$39) -> 0
B61: DEUDA | D61: =SUMIFS(BBDD_GASTOS_FINAL!$Y:$Y,BBDD_GASTOS_FINAL!$J:$J,"deuda",BBDD_GASTOS_FINAL!$V:$V,B40) -> 0
B63: Flujo de Caja al Accionista | D63: =D57-D61-D59 -> 90121649
B64: Margen de utilidad | D64: =D57/D55 -> 0.29662392
A65: id | B65: 9 | E65: id
A66: LOTE | B66: =B1 -> >=0
A67: TOTAL | B67: <> & ""
B68: OPEX | D68: =SUM(D69:D79) -> 2.450974e+08
B69: =D69/$D$68 -> 0.54133505 | C69: NUTRICIÓN | D69: =SUMIFS(BBDD_GASTOS_FINAL!$Z:$Z,BBDD_GASTOS_FINAL!$V:$V,$B$1,BBDD_GASTOS_FINAL!$W:$W,$B$67,BBDD_GASTOS_FINAL!$AC:$AC,lote_todos!$C69)*-1 -> 1.3267981e+08
B70: =D70/$D$68 -> 0.21587706 | C70: PERSONAL | D70: =SUMIFS(BBDD_GASTOS_FINAL!$Z:$Z,BBDD_GASTOS_FINAL!$V:$V,$B$1,BBDD_GASTOS_FINAL!$W:$W,$B$67,BBDD_GASTOS_FINAL!$AC:$AC,lote_todos!$C70)*-1 -> 52910906
B71: =D71/$D$68 -> 0.0073478504 | C71: SANIDAD | D71: =SUMIFS(BBDD_GASTOS_FINAL!$Z:$Z,BBDD_GASTOS_FINAL!$V:$V,$B$1,BBDD_GASTOS_FINAL!$W:$W,$B$67,BBDD_GASTOS_FINAL!$AC:$AC,lote_todos!$C71)*-1 -> 1800939
B72: =D72/$D$68 -> 0.02277253 | C72: GENÉTICA | D72: =SUMIFS(BBDD_GASTOS_FINAL!$Z:$Z,BBDD_GASTOS_FINAL!$V:$V,$B$1,BBDD_GASTOS_FINAL!$W:$W,$B$67,BBDD_GASTOS_FINAL!$AC:$AC,lote_todos!$C72)*-1 -> 5581488
B73: =D73/$D$68 -> 0.027767925 | C73: FLETES | D73: =SUMIFS(BBDD_GASTOS_FINAL!$Z:$Z,BBDD_GASTOS_FINAL!$V:$V,$B$1,BBDD_GASTOS_FINAL!$W:$W,$B$67,BBDD_GASTOS_FINAL!$AC:$AC,lote_todos!$C73)*-1 -> 6805846.2
B74: =D74/$D$68 -> 0.0492837 | C74: ENERGÍA | D74: =SUMIFS(BBDD_GASTOS_FINAL!$Z:$Z,BBDD_GASTOS_FINAL!$V:$V,$B$1,BBDD_GASTOS_FINAL!$W:$W,$B$67,BBDD_GASTOS_FINAL!$AC:$AC,lote_todos!$C74)*-1 -> 12079307
B75: =D75/$D$68 -> 0 | C75: MENTENIMIENTO | D75: =SUMIFS(BBDD_GASTOS_FINAL!$Z:$Z,BBDD_GASTOS_FINAL!$V:$V,$B$1,BBDD_GASTOS_FINAL!$W:$W,$B$67,BBDD_GASTOS_FINAL!$AC:$AC,lote_todos!$C75)*-1 -> 0
B76: =D76/$D$68 -> 0.087137923 | C76: GASTOS OPERATIVOS | D76: =SUMIFS(BBDD_GASTOS_FINAL!$Z:$Z,BBDD_GASTOS_FINAL!$V:$V,$B$1,BBDD_GASTOS_FINAL!$W:$W,$B$67,BBDD_GASTOS_FINAL!$AC:$AC,lote_todos!$C76)*-1 -> 21357279
B77: =D77/$D$68 -> 0.038207606 | C77: IMPUESTOS | D77: =SUMIFS(BBDD_GASTOS_FINAL!$Z:$Z,BBDD_GASTOS_FINAL!$V:$V,$B$1,BBDD_GASTOS_FINAL!$W:$W,$B$67,BBDD_GASTOS_FINAL!$AC:$AC,lote_todos!$C77)*-1 -> 9364584.9
B78: =D78/$D$68 -> 0.010270358 | C78: HONORARIOS | D78: =SUMIFS(BBDD_GASTOS_FINAL!$Z:$Z,BBDD_GASTOS_FINAL!$V:$V,$B$1,BBDD_GASTOS_FINAL!$W:$W,$B$67,BBDD_GASTOS_FINAL!$AC:$AC,lote_todos!$C78)*-1 -> 2517238.1
B79: =D79/$D$68 -> 0 | C79: SERVICIOS | D79: =SUMIFS(BBDD_GASTOS_FINAL!$Z:$Z,BBDD_GASTOS_FINAL!$V:$V,$B$1,BBDD_GASTOS_FINAL!$W:$W,$B$67,BBDD_GASTOS_FINAL!$AC:$AC,lote_todos!$C79)*-1 -> 0
B81: VENTAS | D81: =C6 -> 3.0382462e+08
B83: UTILDAD | D83: =D81-D68 -> 58727219
B85: CAPEX | D85: =SUMIFS(BBDD_GASTOS_FINAL!$Y:$Y,BBDD_GASTOS_FINAL!$J:$J,"Capex",BBDD_GASTOS_FINAL!$Z:$Z,$B$39) -> 0
B87: DEUDA | D87: =SUMIFS(BBDD_GASTOS_FINAL!$Y:$Y,BBDD_GASTOS_FINAL!$J:$J,"deuda",BBDD_GASTOS_FINAL!$V:$V,B67) -> 2
B89: Flujo de Caja al Accionista | D89: =D83-D87-D85 -> 58727217
B90: OPEX UN | C90: =D15+H15+L15+P15+P41+L41+H41+D41+#REF!+#REF!+#REF! -> #REF!
B91: OPEX total | C91: =C7 -> 2.5052749e+08
C92: =MROUND(C91,10000)=MROUND(C90,10000) -> #REF!
B94: CAPEX_UN | C94: =D33+H33+L33+P33+P59+L59+H59+D59+D67+H67+L67 -> 0
B95: CAPEX_TOTAL | C95: =C9 -> 0 | D95: =C94=C95 -> TRUE
B96: DEUDA_UN | C96: =D35+H35+L35+P35+P61+L61+H61+D61+D69+H69+L69 -> 1.3267981e+08
B97: DEUDA_TOTAL | C97: =C10 -> 221959.33 | D97: =C96=C97 -> FALSE
B101: UTILIDAD_TOTAL | C101: =C8 -> 53297135
B102: UTILIDAD_UN | C102: =D31+H31+L31+P31+P57+L57+H57+D57+#REF!+#REF!+#REF! -> #REF! | D102: =MROUND(C102,10000)=MROUND(C101,10000) -> #REF!
B105: Flujo_TOTAL | C105: =C11 -> 53075176
B106: FLUJO_UN | C106: =D37+H37+L37+P37+P63+L63+H63+D63+D71+H71+L71 -> 18997440 | D106: =MROUND(C106,10000)=MROUND(C105,10000) -> FALSE
B107: Margen de utilidad | D107: =D83/D81 -> 0.19329315

Sheet lote_I
A1: LOTE | B1: 3925 | C1: Mortandad-SITIO 2 | G1: CALZIM
C2: Mortandad-SITIO 3 | D2: =SUMIFS(produccion!G:G,produccion!$A:$A,B1) -> -0.053422371
B5: TOTALES | F5: FIJO/VARIABLE | J5: DIRECTO/INDERECTO
B6: VENTAS SITIO 3 | C6: =D55 -> 1.5626228e+08 | F6: VENTAS | G6: =C6 -> 1.5626228e+08 | J6: VENTAS | K6: =G6 -> 1.5626228e+08
B7: OPEX | C7: =SUMIFS(BBDD_GASTOS_FINAL!$Z:$Z,BBDD_GASTOS_FINAL!$V:$V,lote_I!$B$1,BBDD_GASTOS_FINAL!$J:$J,"OPEX")*-1 -> 1.288857e+08 | F7: Fijo | G7: =SUMIFS(BBDD_GASTOS_FINAL!$Z:$Z,BBDD_GASTOS_FINAL!$V:$V,lote_I!$B$1,BBDD_GASTOS_FINAL!$J:$J,"OPEX",BBDD_GASTOS_FINAL!$K:$K,lote_I!F7)*-1 -> 2702743.5 | J7: DIRECTO | K7: =SUMIFS(BBDD_GASTOS_FINAL!$Z:$Z,BBDD_GASTOS_FINAL!$V:$V,lote_I!$B$1,BBDD_GASTOS_FINAL!$J:$J,"OPEX",BBDD_GASTOS_FINAL!$L:$L,lote_I!J7)*-1 -> 12744286
B8: UTILIDAD | C8: =C6-C7 -> 27376584 | F8: Variable | G8: =SUMIFS(BBDD_GASTOS_FINAL!$Z:$Z,BBDD_GASTOS_FINAL!$V:$V,lote_I!$B$1,BBDD_GASTOS_FINAL!$J:$J,"OPEX",BBDD_GASTOS_FINAL!$K:$K,lote_todos!F8)*-1 -> 22292601 | J8: INDIRECTO | K8: =SUMIFS(BBDD_GASTOS_FINAL!$Z:$Z,BBDD_GASTOS_FINAL!$V:$V,lote_I!$B$1,BBDD_GASTOS_FINAL!$J:$J,"OPEX",BBDD_GASTOS_FINAL!$L:$L,lote_I!J8)*-1 -> 12251059
B9: CAPEX | C9: =SUMIFS(BBDD_GASTOS_FINAL!$Y:$Y,BBDD_GASTOS_FINAL!$J:$J,lote_I!B9) -> 0
B10: DEUDA | C10: =SUMIFS(BBDD_GASTOS_FINAL!$Z:$Z,BBDD_GASTOS_FINAL!$J:$J,lote_I!B10,BBDD_GASTOS_FINAL!$V:$V,$B$1)*-1 -> 110979.66
B11: Flujo de Caja al Accionista | C11: =C6-C7-C9-C10 -> 27265604 | F11: Flujo de Caja al Accionista | G11: =G6-G7-G8 -> 1.3126694e+08 | J11: Flujo de Caja al Accionista | K11: =K6-K7-K8 -> 1.3126694e+08
A13: id | B13: 4 | E13: id | F13: 3 | I13: id | J13: 7 | M13: id
B14: GESTACIÓN | F14: MATERNIDAD | J14: SITIO 2
B15: OPEX | D15: =SUM(D16:D26) -> 23745553 | F15: OPEX | H15: =SUM(H16:H26) -> 20889733 | J15: OPEX | L15: =SUM(L16:L26) -> 20889733 | M15: 1
A16: 1 | B16: =D16/$D$15 -> 0.30685959 | C16: NUTRICIÓN | D16: =SUMIFS(BBDD_GASTOS_FINAL!$Z:$Z,BBDD_GASTOS_FINAL!$V:$V,$B$1,BBDD_GASTOS_FINAL!$W:$W,$B$14,BBDD_GASTOS_FINAL!$AC:$AC,lote_I!$C16)*-1 -> 7286550.6 | E16: 1 | F16: =H16/$H$15 -> 0.30994928 | G16: NUTRICIÓN | H16: =SUMIFS(BBDD_GASTOS_FINAL!$Z:$Z,BBDD_GASTOS_FINAL!$V:$V,$B$1,BBDD_GASTOS_FINAL!$W:$W,$F$14,BBDD_GASTOS_FINAL!$AC:$AC,$G16)*-1 -> 6474757.6 | I16: 1 | J16: =L16/$L$15 -> 0.30994928 | K16: NUTRICIÓN | L16: =SUMIFS(BBDD_GASTOS_FINAL!$Z:$Z,BBDD_GASTOS_FINAL!$V:$V,$B$1,BBDD_GASTOS_FINAL!$W:$W,$F$14,BBDD_GASTOS_FINAL!$AC:$AC,$G16)*-1 -> 6474757.6 | M16: 1
A17: =A16+1 -> 2 | B17: =D17/$D$15 -> 0.33888285 | C17: PERSONAL | D17: =SUMIFS(BBDD_GASTOS_FINAL!$Z:$Z,BBDD_GASTOS_FINAL!$V:$V,$B$1,BBDD_GASTOS_FINAL!$W:$W,$B$14,BBDD_GASTOS_FINAL!AC:AC,lote_I!$C17)*-1 -> 8046960.7 | E17: 2 | F17: =H17/$H$15 -> 0.37328775 | G17: PERSONAL | H17: =SUMIFS(BBDD_GASTOS_FINAL!$Z:$Z,BBDD_GASTOS_FINAL!$V:$V,$B$1,BBDD_GASTOS_FINAL!$W:$W,$F$14,BBDD_GASTOS_FINAL!$AC:$AC,$G17)*-1 -> 7797881.3 | I17: =I16+1 -> 2 | J17: =L17/$L$15 -> 0.37328775 | K17: PERSONAL | L17: =SUMIFS(BBDD_GASTOS_FINAL!$Z:$Z,BBDD_GASTOS_FINAL!$V:$V,$B$1,BBDD_GASTOS_FINAL!$W:$W,$F$14,BBDD_GASTOS_FINAL!$AC:$AC,$G17)*-1 -> 7797881.3 | M17: =M16+1 -> 2
A18: =A17+1 -> 3 | B18: =D18/$D$15 -> 0.0085376736 | C18: SANIDAD | D18: =SUMIFS(BBDD_GASTOS_FINAL!$Z:$Z,BBDD_GASTOS_FINAL!$V:$V,$B$1,BBDD_GASTOS_FINAL!$W:$W,$B$14,BBDD_GASTOS_FINAL!AC:AC,lote_I!$C18)*-1 -> 202731.78 | E18: 3 | F18: =H18/$H$15 -> 0.0048034225 | G18: SANIDAD | H18: =SUMIFS(BBDD_GASTOS_FINAL!$Z:$Z,BBDD_GASTOS_FINAL!$V:$V,$B$1,BBDD_GASTOS_FINAL!$W:$W,$F$14,BBDD_GASTOS_FINAL!$AC:$AC,$G18)*-1 -> 100342.21 | I18: =I17+12 -> 14 | J18: =L18/$L$15 -> 0.0048034225 | K18: SANIDAD | L18: =SUMIFS(BBDD_GASTOS_FINAL!$Z:$Z,BBDD_GASTOS_FINAL!$V:$V,$B$1,BBDD_GASTOS_FINAL!$W:$W,$F$14,BBDD_GASTOS_FINAL!$AC:$AC,$G18)*-1 -> 100342.21 | M18: =M17+1 -> 3
A19: =A18+1 -> 4 | B19: =D19/$D$15 -> 0.11752702 | C19: GENÉTICA | D19: =SUMIFS(BBDD_GASTOS_FINAL!$Z:$Z,BBDD_GASTOS_FINAL!$V:$V,$B$1,BBDD_GASTOS_FINAL!$W:$W,$B$14,BBDD_GASTOS_FINAL!AC:AC,lote_I!$C19)*-1 -> 2790744 | E19: 4 | F19: =H19/$H$15 -> 0 | G19: GENÉTICA | H19: =SUMIFS(BBDD_GASTOS_FINAL!$Z:$Z,BBDD_GASTOS_FINAL!$V:$V,$B$1,BBDD_GASTOS_FINAL!$W:$W,$F$14,BBDD_GASTOS_FINAL!$AC:$AC,$G19)*-1 -> 0 | I19: =I18+1 -> 15 | J19: =L19/$L$15 -> 0 | K19: GENÉTICA | L19: =SUMIFS(BBDD_GASTOS_FINAL!$Z:$Z,BBDD_GASTOS_FINAL!$V:$V,$B$1,BBDD_GASTOS_FINAL!$W:$W,$F$14,BBDD_GASTOS_FINAL!$AC:$AC,$G19)*-1 -> 0 | M19: =M18+1 -> 4
A20: =A19+1 -> 5 | B20: =D20/$D$15 -> 0 | C20: FLETES | D20: =SUMIFS(BBDD_GASTOS_FINAL!$Z:$Z,BBDD_GASTOS_FINAL!$V:$V,$B$1,BBDD_GASTOS_FINAL!$W:$W,$B$14,BBDD_GASTOS_FINAL!AC:AC,lote_I!$C20)*-1 -> 0 | E20: 5 | F20: =H20/$H$15 -> 0 | G20: FLETES | H20: =SUMIFS(BBDD_GASTOS_FINAL!$Z:$Z,BBDD_GASTOS_FINAL!$V:$V,$B$1,BBDD_GASTOS_FINAL!$W:$W,$F$14,BBDD_GASTOS_FINAL!$AC:$AC,$G20)*-1 -> 0 | I20: =I19+1 -> 16 | J20: =L20/$L$15 -> 0 | K20: FLETES | L20: =SUMIFS(BBDD_GASTOS_FINAL!$Z:$Z,BBDD_GASTOS_FINAL!$V:$V,$B$1,BBDD_GASTOS_FINAL!$W:$W,$F$14,BBDD_GASTOS_FINAL!$AC:$AC,$G20)*-1 -> 0 | M20: =M19+1 -> 5
A21: =A20+1 -> 6 | B21: =D21/$D$15 -> 0.0635872 | C21: ENERGÍA | D21: =SUMIFS(BBDD_GASTOS_FINAL!$Z:$Z,BBDD_GASTOS_FINAL!$V:$V,$B$1,BBDD_GASTOS_FINAL!$W:$W,$B$14,BBDD_GASTOS_FINAL!AC:AC,lote_I!$C21)*-1 -> 1509913.2 | E21: 6 | F21: =H21/$H$15 -> 0.072280161 | G21: ENERGÍA | H21: =SUMIFS(BBDD_GASTOS_FINAL!$Z:$Z,BBDD_GASTOS_FINAL!$V:$V,$B$1,BBDD_GASTOS_FINAL!$W:$W,$F$14,BBDD_GASTOS_FINAL!$AC:$AC,$G21)*-1 -> 1509913.2 | I21: =I20+1 -> 17 | J21: =L21/$L$15 -> 0.072280161 | K21: ENERGÍA | L21: =SUMIFS(BBDD_GASTOS_FINAL!$Z:$Z,BBDD_GASTOS_FINAL!$V:$V,$B$1,BBDD_GASTOS_FINAL!$W:$W,$F$14,BBDD_GASTOS_FINAL!$AC:$AC,$G21)*-1 -> 1509913.2 | M21: =M20+1 -> 6
A22: =A21+1 -> 7 | B22: =D22/$D$15 -> 0 | C22: MENTENIMIENTO | D22: =SUMIFS(BBDD_GASTOS_FINAL!$Z:$Z,BBDD_GASTOS_FINAL!$V:$V,$B$1,BBDD_GASTOS_FINAL!$W:$W,$B$14,BBDD_GASTOS_FINAL!AC:AC,lote_I!$C22)*-1 -> 0 | E22: 7 | F22: =H22/$H$15 -> 0 | G22: MENTENIMIENTO | H22: =SUMIFS(BBDD_GASTOS_FINAL!$Z:$Z,BBDD_GASTOS_FINAL!$V:$V,$B$1,BBDD_GASTOS_FINAL!$W:$W,$F$14,BBDD_GASTOS_FINAL!$AC:$AC,$G22)*-1 -> 0 | I22: =I21+1 -> 18 | J22: =L22/$L$15 -> 0 | K22: MENTENIMIENTO | L22: =SUMIFS(BBDD_GASTOS_FINAL!$Z:$Z,BBDD_GASTOS_FINAL!$V:$V,$B$1,BBDD_GASTOS_FINAL!$W:$W,$F$14,BBDD_GASTOS_FINAL!$AC:$AC,$G22)*-1 -> 0 | M22: =M21+1 -> 7
A23: =A22+1 -> 8 | B23: =D23/$D$15 -> 0.11356983 | C23: GASTOS OPERATIVOS | D23: =SUMIFS(BBDD_GASTOS_FINAL!$Z:$Z,BBDD_GASTOS_FINAL!$V:$V,$B$1,BBDD_GASTOS_FINAL!$W:$W,$B$14,BBDD_GASTOS_FINAL!AC:AC,lote_I!$C23)*-1 -> 2696778.5 | E23: 8 | F23: =H23/$H$15 -> 0.13399731 | G23: GASTOS OPERATIVOS | H23: =SUMIFS(BBDD_GASTOS_FINAL!$Z:$Z,BBDD_GASTOS_FINAL!$V:$V,$B$1,BBDD_GASTOS_FINAL!$W:$W,$F$14,BBDD_GASTOS_FINAL!$AC:$AC,$G23)*-1 -> 2799168 | I23: =I22+1 -> 19 | J23: =L23/$L$15 -> 0.13399731 | K23: GASTOS OPERATIVOS | L23: =SUMIFS(BBDD_GASTOS_FINAL!$Z:$Z,BBDD_GASTOS_FINAL!$V:$V,$B$1,BBDD_GASTOS_FINAL!$W:$W,$F$14,BBDD_GASTOS_FINAL!$AC:$AC,$G23)*-1 -> 2799168 | M23: =M22+1 -> 8
A24: =A23+1 -> 9 | B24: =D24/$D$15 -> 0.037984074 | C24: IMPUESTOS | D24: =SUMIFS(BBDD_GASTOS_FINAL!$Z:$Z,BBDD_GASTOS_FINAL!$V:$V,$B$1,BBDD_GASTOS_FINAL!$W:$W,$B$14,BBDD_GASTOS_FINAL!AC:AC,lote_I!$C24)*-1 -> 901952.84 | E24: 9 | F24: =H24/$H$15 -> 0.090846007 | G24: IMPUESTOS | H24: =SUMIFS(BBDD_GASTOS_FINAL!$Z:$Z,BBDD_GASTOS_FINAL!$V:$V,$B$1,BBDD_GASTOS_FINAL!$W:$W,$F$14,BBDD_GASTOS_FINAL!$AC:$AC,$G24)*-1 -> 1897748.8 | I24: =I23+1 -> 20 | J24: =L24/$L$15 -> 0.090846007 | K24: IMPUESTOS | L24: =SUMIFS(BBDD_GASTOS_FINAL!$Z:$Z,BBDD_GASTOS_FINAL!$V:$V,$B$1,BBDD_GASTOS_FINAL!$W:$W,$F$14,BBDD_GASTOS_FINAL!$AC:$AC,$G24)*-1 -> 1897748.8 | M24: =M23+1 -> 9
A25: =A24+1 -> 10 | B25: =D25/$D$15 -> 0.013051771 | C25: HONORARIOS | D25: =SUMIFS(BBDD_GASTOS_FINAL!$Z:$Z,BBDD_GASTOS_FINAL!$V:$V,$B$1,BBDD_GASTOS_FINAL!$W:$W,$B$14,BBDD_GASTOS_FINAL!AC:AC,lote_I!$C25)*-1 -> 309921.52 | E25: 10 | F25: =H25/$H$15 -> 0.014836069 | G25: HONORARIOS | H25: =SUMIFS(BBDD_GASTOS_FINAL!$Z:$Z,BBDD_GASTOS_FINAL!$V:$V,$B$1,BBDD_GASTOS_FINAL!$W:$W,$F$14,BBDD_GASTOS_FINAL!$AC:$AC,$G25)*-1 -> 309921.52 | I25: =I24+1 -> 21 | J25: =L25/$L$15 -> 0.014836069 | K25: HONORARIOS | L25: =SUMIFS(BBDD_GASTOS_FINAL!$Z:$Z,BBDD_GASTOS_FINAL!$V:$V,$B$1,BBDD_GASTOS_FINAL!$W:$W,$F$14,BBDD_GASTOS_FINAL!$AC:$AC,$G25)*-1 -> 309921.52 | M25: =M24+1 -> 10
B26: =D26/$D$15 -> 0 | C26: SERVICIOS | D26: =SUMIFS(BBDD_GASTOS_FINAL!$Z:$Z,BBDD_GASTOS_FINAL!$V:$V,$B$1,BBDD_GASTOS_FINAL!$W:$W,$B$14,BBDD_GASTOS_FINAL!AC:AC,lote_I!$C26)*-1 -> 0 | F26: =H26/$H$15 -> 0 | G26: SERVICIOS | H26: =SUMIFS(BBDD_GASTOS_FINAL!$Z:$Z,BBDD_GASTOS_FINAL!$V:$V,$B$1,BBDD_GASTOS_FINAL!$W:$W,$F$14,BBDD_GASTOS_FINAL!$AC:$AC,$G26)*-1 -> 0 | J26: =L26/$L$15 -> 0 | K26: OTROS | L26: =SUMIFS(BBDD_GASTOS_FINAL!$Z:$Z,BBDD_GASTOS_FINAL!$V:$V,$B$1,BBDD_GASTOS_FINAL!$W:$W,$F$14,BBDD_GASTOS_FINAL!$AC:$AC,$G26)*-1 -> 0
F28: COMPRAS EN GESTACION | H28: =D15 -> 23745553 | J28: COMPRAS EN MATERNIDAD | L28: =H29 -> 24295372
B29: VENTAS | D29: =SUMIFS(produccion!$H:$H,produccion!$A:$A,lote_I!$B$1,produccion!$B:$B,lote_I!B14) -> 0 | F29: VENTAS | H29: =SUMIFS(produccion!$H:$H,produccion!$A:$A,lote_I!$B$1,produccion!$B:$B,lote_I!F14) -> 24295372 | J29: VENTAS | L29: =SUMIFS(produccion!$H:$H,produccion!$A:$A,lote_I!$B$1,produccion!$B:$B,lote_I!J14) -> 50061904
B31: UTILDAD | D31: =D29-D15-D28 -> -23745553 | F31: UTILDAD | H31: =H29-H15-H28 -> -20339914 | J31: UTILDAD | L31: =L29-L15-L28 -> 4876799.3
B33: CAPEX | D33: =SUMIFS(BBDD_GASTOS_FINAL!$Y:$Y,BBDD_GASTOS_FINAL!$J:$J,"Capex",BBDD_GASTOS_FINAL!$Z:$Z,$B$13) -> 0 | F33: CAPEX | H33: =SUMIFS(BBDD_GASTOS_FINAL!$Y:$Y,BBDD_GASTOS_FINAL!$J:$J,"Capex",BBDD_GASTOS_FINAL!$Z:$Z,$F$13) -> 0 | J33: CAPEX | L33: =SUMIFS(BBDD_GASTOS_FINAL!$Y:$Y,BBDD_GASTOS_FINAL!$J:$J,"Capex",BBDD_GASTOS_FINAL!$Z:$Z,$J$13) -> 0
B35: DEUDA | D35: =SUMIFS(BBDD_GASTOS_FINAL!$Y:$Y,BBDD_GASTOS_FINAL!$J:$J,"Deuda",BBDD_GASTOS_FINAL!$V:$V,B14) -> 0 | F35: DEUDA | H35: =SUMIFS(BBDD_GASTOS_FINAL!$Y:$Y,BBDD_GASTOS_FINAL!$J:$J,"Deuda",BBDD_GASTOS_FINAL!$V:$V,F14) -> 0 | J35: DEUDA | L35: =SUMIFS(BBDD_GASTOS_FINAL!$Y:$Y,BBDD_GASTOS_FINAL!$J:$J,"deuda",BBDD_GASTOS_FINAL!$V:$V,J14) -> 0
B37: Flujo de Caja al Accionista | D37: =D31-D35-D33 -> -23745553 | F37: Flujo de Caja al Accionista | H37: =H31-H35-H33 -> -20339914 | J37: Flujo de Caja al Accionista | L37: =L31-L35-L33 -> 4876799.3
F38: Margen de utilidad | H38: =H31/H29 -> -0.83719292 | J38: Margen de utilidad | L38: =L31/L29 -> 0.097415377
A39: id | B39: 1 | M39: id
B40: SITIO 3
B41: OPEX | D41: =SUM(D42:D52) -> 59931142
A42: 1 | B42: =D42/$D$41 -> 0.75556845 | C42: NUTRICIÓN | D42: =SUMIFS(BBDD_GASTOS_FINAL!$Z:$Z,BBDD_GASTOS_FINAL!$V:$V,$B$1,BBDD_GASTOS_FINAL!$W:$W,$B$40,BBDD_GASTOS_FINAL!$AC:$AC,lote_I!$C42)*-1 -> 45282080
A43: =A42+1 -> 2 | B43: =D43/$D$41 -> 0.093855064 | C43: PERSONAL | D43: =SUMIFS(BBDD_GASTOS_FINAL!$Z:$Z,BBDD_GASTOS_FINAL!$V:$V,$B$1,BBDD_GASTOS_FINAL!$W:$W,$B$40,BBDD_GASTOS_FINAL!AC:AC,lote_I!$C43)*-1 -> 5624841.1
A44: =A43+1 -> 3 | B44: =D44/$D$41 -> 0.0026403766 | C44: SANIDAD | D44: =SUMIFS(BBDD_GASTOS_FINAL!$Z:$Z,BBDD_GASTOS_FINAL!$V:$V,$B$1,BBDD_GASTOS_FINAL!$W:$W,$B$40,BBDD_GASTOS_FINAL!AC:AC,lote_I!$C44)*-1 -> 158240.78
A45: =A44+1 -> 4 | B45: =D45/$D$41 -> 0 | C45: GENÉTICA | D45: =SUMIFS(BBDD_GASTOS_FINAL!$Z:$Z,BBDD_GASTOS_FINAL!$V:$V,$B$1,BBDD_GASTOS_FINAL!$W:$W,$B$40,BBDD_GASTOS_FINAL!AC:AC,lote_I!$C45)*-1 -> 0
A46: =A45+1 -> 5 | B46: =D46/$D$41 -> 0.056780545 | C46: FLETES | D46: =SUMIFS(BBDD_GASTOS_FINAL!$Z:$Z,BBDD_GASTOS_FINAL!$V:$V,$B$1,BBDD_GASTOS_FINAL!$W:$W,$B$40,BBDD_GASTOS_FINAL!AC:AC,lote_I!$C46)*-1 -> 3402922.9
A47: =A46+1 -> 6 | B47: =D47/$D$41 -> 0.025194134 | C47: ENERGÍA | D47: =SUMIFS(BBDD_GASTOS_FINAL!$Z:$Z,BBDD_GASTOS_FINAL!$V:$V,$B$1,BBDD_GASTOS_FINAL!$W:$W,$B$40,BBDD_GASTOS_FINAL!AC:AC,lote_I!$C47)*-1 -> 1509913.2
A48: =A47+1 -> 7 | B48: =D48/$D$41 -> 0 | C48: MENTENIMIENTO | D48: =SUMIFS(BBDD_GASTOS_FINAL!$Z:$Z,BBDD_GASTOS_FINAL!$V:$V,$B$1,BBDD_GASTOS_FINAL!$W:$W,$B$40,BBDD_GASTOS_FINAL!AC:AC,lote_I!$C48)*-1 -> 0
A49: =A48+1 -> 8 | B49: =D49/$D$41 -> 0.045635014 | C49: GASTOS OPERATIVOS | D49: =SUMIFS(BBDD_GASTOS_FINAL!$Z:$Z,BBDD_GASTOS_FINAL!$V:$V,$B$1,BBDD_GASTOS_FINAL!$W:$W,$B$40,BBDD_GASTOS_FINAL!AC:AC,lote_I!$C49)*-1 -> 2734958.5
A50: =A49+1 -> 9 | B50: =D50/$D$41 -> 0.015049819 | C50: IMPUESTOS | D50: =SUMIFS(BBDD_GASTOS_FINAL!$Z:$Z,BBDD_GASTOS_FINAL!$V:$V,$B$1,BBDD_GASTOS_FINAL!$W:$W,$B$40,BBDD_GASTOS_FINAL!AC:AC,lote_I!$C50)*-1 -> 901952.84
A51: =A50+1 -> 10 | B51: =D51/$D$41 -> 0.0052765971 | C51: HONORARIOS | D51: =SUMIFS(BBDD_GASTOS_FINAL!$Z:$Z,BBDD_GASTOS_FINAL!$V:$V,$B$1,BBDD_GASTOS_FINAL!$W:$W,$B$40,BBDD_GASTOS_FINAL!AC:AC,lote_I!$C51)*-1 -> 316232.49
B52: =D52/$D$41 -> 0 | C52: SERVICIOS | D52: =SUMIFS(BBDD_GASTOS_FINAL!$Z:$Z,BBDD_GASTOS_FINAL!$V:$V,$B$1,BBDD_GASTOS_FINAL!$W:$W,$B$40,BBDD_GASTOS_FINAL!AC:AC,lote_I!$C52)*-1 -> 0
B54: COMPRAS EN SITIO 2 | D54: =L29 -> 50061904
B55: VENTAS | D55: =SUMIFS(produccion!$H:$H,produccion!$A:$A,lote_I!$B$1,produccion!$B:$B,lote_I!B40) -> 1.5626228e+08
B57: UTILDAD | D57: =D55-D41-D54 -> 46269238
B59: CAPEX | D59: =SUMIFS(BBDD_GASTOS_FINAL!$Y:$Y,BBDD_GASTOS_FINAL!$J:$J,"Capex",BBDD_GASTOS_FINAL!$Z:$Z,$B$39) -> 0
B61: DEUDA | D61: =SUMIFS(BBDD_GASTOS_FINAL!$Y:$Y,BBDD_GASTOS_FINAL!$J:$J,"deuda",BBDD_GASTOS_FINAL!$V:$V,B40) -> 0
B63: Flujo de Caja al Accionista | D63: =D57-D61-D59 -> 46269238
B64: Margen de utilidad | D64: =D57/D55 -> 0.29609985
A65: id | B65: 9 | E65: id
A66: LOTE | B66: =B1 -> 3925
A67: TOTAL | B67: <> & ""
B68: OPEX | D68: =SUM(D69:D79) -> 1.2617066e+08
B69: =D69/$D$68 -> 0.55450189 | C69: NUTRICIÓN | D69: =SUMIFS(BBDD_GASTOS_FINAL!$Z:$Z,BBDD_GASTOS_FINAL!$V:$V,$B$1,BBDD_GASTOS_FINAL!$W:$W,$B$67,BBDD_GASTOS_FINAL!$AC:$AC,lote_I!$C69)*-1 -> 69961868
B70: =D70/$D$68 -> 0.2096799 | C70: PERSONAL | D70: =SUMIFS(BBDD_GASTOS_FINAL!$Z:$Z,BBDD_GASTOS_FINAL!$V:$V,$B$1,BBDD_GASTOS_FINAL!$W:$W,$B$67,BBDD_GASTOS_FINAL!$AC:$AC,lote_I!$C70)*-1 -> 26455451
B71: =D71/$D$68 -> 0.0044015465 | C71: SANIDAD | D71: =SUMIFS(BBDD_GASTOS_FINAL!$Z:$Z,BBDD_GASTOS_FINAL!$V:$V,$B$1,BBDD_GASTOS_FINAL!$W:$W,$B$67,BBDD_GASTOS_FINAL!$AC:$AC,lote_I!$C71)*-1 -> 555346.02
B72: =D72/$D$68 -> 0.022118803 | C72: GENÉTICA | D72: =SUMIFS(BBDD_GASTOS_FINAL!$Z:$Z,BBDD_GASTOS_FINAL!$V:$V,$B$1,BBDD_GASTOS_FINAL!$W:$W,$B$67,BBDD_GASTOS_FINAL!$AC:$AC,lote_I!$C72)*-1 -> 2790744
B73: =D73/$D$68 -> 0.026970794 | C73: FLETES | D73: =SUMIFS(BBDD_GASTOS_FINAL!$Z:$Z,BBDD_GASTOS_FINAL!$V:$V,$B$1,BBDD_GASTOS_FINAL!$W:$W,$B$67,BBDD_GASTOS_FINAL!$AC:$AC,lote_I!$C73)*-1 -> 3402922.9
B74: =D74/$D$68 -> 0.047868919 | C74: ENERGÍA | D74: =SUMIFS(BBDD_GASTOS_FINAL!$Z:$Z,BBDD_GASTOS_FINAL!$V:$V,$B$1,BBDD_GASTOS_FINAL!$W:$W,$B$67,BBDD_GASTOS_FINAL!$AC:$AC,lote_I!$C74)*-1 -> 6039653
B75: =D75/$D$68 -> 0 | C75: MENTENIMIENTO | D75: =SUMIFS(BBDD_GASTOS_FINAL!$Z:$Z,BBDD_GASTOS_FINAL!$V:$V,$B$1,BBDD_GASTOS_FINAL!$W:$W,$B$67,BBDD_GASTOS_FINAL!$AC:$AC,lote_I!$C75)*-1 -> 0
B76: =D76/$D$68 -> 0.087421855 | C76: GASTOS OPERATIVOS | D76: =SUMIFS(BBDD_GASTOS_FINAL!$Z:$Z,BBDD_GASTOS_FINAL!$V:$V,$B$1,BBDD_GASTOS_FINAL!$W:$W,$B$67,BBDD_GASTOS_FINAL!$AC:$AC,lote_I!$C76)*-1 -> 11030073
B77: =D77/$D$68 -> 0.037110785 | C77: IMPUESTOS | D77: =SUMIFS(BBDD_GASTOS_FINAL!$Z:$Z,BBDD_GASTOS_FINAL!$V:$V,$B$1,BBDD_GASTOS_FINAL!$W:$W,$B$67,BBDD_GASTOS_FINAL!$AC:$AC,lote_I!$C77)*-1 -> 4682292.2
B78: =D78/$D$68 -> 0.009925509 | C78: HONORARIOS | D78: =SUMIFS(BBDD_GASTOS_FINAL!$Z:$Z,BBDD_GASTOS_FINAL!$V:$V,$B$1,BBDD_GASTOS_FINAL!$W:$W,$B$67,BBDD_GASTOS_FINAL!$AC:$AC,lote_I!$C78)*-1 -> 1252308
B79: =D79/$D$68 -> 0 | C79: SERVICIOS | D79: =SUMIFS(BBDD_GASTOS_FINAL!$Z:$Z,BBDD_GASTOS_FINAL!$V:$V,$B$1,BBDD_GASTOS_FINAL!$W:$W,$B$67,BBDD_GASTOS_FINAL!$AC:$AC,lote_I!$C79)*-1 -> 0
B81: VENTAS | D81: =C6 -> 1.5626228e+08
B83: UTILDAD | D83: =D81-D68 -> 30091626
B85: CAPEX | D85: =SUMIFS(BBDD_GASTOS_FINAL!$Y:$Y,BBDD_GASTOS_FINAL!$J:$J,"Capex",BBDD_GASTOS_FINAL!$Z:$Z,$B$39) -> 0
B87: DEUDA | D87: =SUMIFS(BBDD_GASTOS_FINAL!$Y:$Y,BBDD_GASTOS_FINAL!$J:$J,"deuda",BBDD_GASTOS_FINAL!$V:$V,B67) -> 2
B89: Flujo de Caja al Accionista | D89: =D83-D87-D85 -> 30091624
B90: OPEX UN | C90: =D15+H15+L15+P15+P41+L41+H41+D41+#REF!+#REF!+#REF! -> #REF!
B91: OPEX total | C91: =C7 -> 1.288857e+08
C92: =MROUND(C91,10000)=MROUND(C90,10000) -> #REF!
B94: CAPEX_UN | C94: =D33+H33+L33+P33+P59+L59+H59+D59+D67+H67+L67 -> 0
B95: CAPEX_TOTAL | C95: =C9 -> 0 | D95: =C94=C95 -> TRUE
B96: DEUDA_UN | C96: =D35+H35+L35+P35+P61+L61+H61+D61+D69+H69+L69 -> 69961868
B97: DEUDA_TOTAL | C97: =C10 -> 110979.66 | D97: =C96=C97 -> FALSE
B101: UTILIDAD_TOTAL | C101: =C8 -> 27376584
B102: UTILIDAD_UN | C102: =D31+H31+L31+P31+P57+L57+H57+D57+#REF!+#REF!+#REF! -> #REF! | D102: =MROUND(C102,10000)=MROUND(C101,10000) -> #REF!
B105: Flujo_TOTAL | C105: =C11 -> 27265604
B106: FLUJO_UN | C106: =D37+H37+L37+P37+P63+L63+H63+D63+D71+H71+L71 -> 7615916.8 | D106: =MROUND(C106,10000)=MROUND(C105,10000) -> FALSE
B107: Margen de utilidad | D107: =D83/D81 -> 0.19257127

Sheet lote_II
A1: LOTE | B1: 3725 | C1: Mortandad-SITIO 2 | G1: CALZIM
C2: Mortandad-SITIO 3 | D2: =SUMIFS(produccion!G:G,produccion!$A:$A,B1) -> -0.040636042
B5: TOTALES | F5: FIJO/VARIABLE | J5: DIRECTO/INDERECTO
B6: VENTAS SITIO 3 | C6: =D55 -> 1.4756234e+08 | F6: VENTAS | G6: =C6 -> 1.4756234e+08 | J6: VENTAS | K6: =G6 -> 1.4756234e+08
B7: OPEX | C7: =SUMIFS(BBDD_GASTOS_FINAL!$Z:$Z,BBDD_GASTOS_FINAL!$V:$V,lote_II!$B$1,BBDD_GASTOS_FINAL!$J:$J,"OPEX")*-1 -> 1.2164178e+08 | F7: Fijo | G7: =SUMIFS(BBDD_GASTOS_FINAL!$Z:$Z,BBDD_GASTOS_FINAL!$V:$V,lote_II!$B$1,BBDD_GASTOS_FINAL!$J:$J,"OPEX",BBDD_GASTOS_FINAL!$K:$K,lote_II!F7)*-1 -> 2702743.9 | J7: DIRECTO | K7: =SUMIFS(BBDD_GASTOS_FINAL!$Z:$Z,BBDD_GASTOS_FINAL!$V:$V,lote_II!$B$1,BBDD_GASTOS_FINAL!$J:$J,"OPEX",BBDD_GASTOS_FINAL!$L:$L,lote_II!J7)*-1 -> 12744288
B8: UTILIDAD | C8: =C6-C7 -> 25920551 | F8: Variable | G8: =SUMIFS(BBDD_GASTOS_FINAL!$Z:$Z,BBDD_GASTOS_FINAL!$V:$V,lote_II!$B$1,BBDD_GASTOS_FINAL!$J:$J,"OPEX",BBDD_GASTOS_FINAL!$K:$K,lote_II!F8)*-1 -> 22292604 | J8: INDIRECTO | K8: =SUMIFS(BBDD_GASTOS_FINAL!$Z:$Z,BBDD_GASTOS_FINAL!$V:$V,lote_II!$B$1,BBDD_GASTOS_FINAL!$J:$J,"OPEX",BBDD_GASTOS_FINAL!$L:$L,lote_II!J8)*-1 -> 12251060
B9: CAPEX | C9: =SUMIFS(BBDD_GASTOS_FINAL!$Y:$Y,BBDD_GASTOS_FINAL!$J:$J,lote_II!B9) -> 0
B10: DEUDA | C10: =SUMIFS(BBDD_GASTOS_FINAL!$Z:$Z,BBDD_GASTOS_FINAL!$J:$J,lote_II!B10,BBDD_GASTOS_FINAL!$V:$V,lote_II!$B$1)*-1 -> 110979.67
B11: Flujo de Caja al Accionista | C11: =C6-C7-C9-C10 -> 25809571 | F11: Flujo de Caja al Accionista | G11: =G6-G7-G8 -> 1.2256699e+08 | J11: Flujo de Caja al Accionista | K11: =K6-K7-K8 -> 1.2256699e+08
A13: id | B13: 4 | E13: id | F13: 3 | I13: id | J13: 7 | M13: id
B14: GESTACIÓN | F14: MATERNIDAD | J14: SITIO 2
B15: OPEX | D15: =SUM(D16:D26) -> 23745555 | F15: OPEX | H15: =SUM(H16:H26) -> 15493174 | J15: OPEX | L15: =SUM(L16:L26) -> 15493174 | M15: 1
A16: 1 | B16: =D16/$D$15 -> 0.30685956 | C16: NUTRICIÓN | D16: =SUMIFS(BBDD_GASTOS_FINAL!$Z:$Z,BBDD_GASTOS_FINAL!$V:$V,$B$1,BBDD_GASTOS_FINAL!$W:$W,$B$14,BBDD_GASTOS_FINAL!$AC:$AC,lote_II!$C16)*-1 -> 7286550.6 | E16: 1 | F16: =H16/$H$15 -> 0.069591757 | G16: NUTRICIÓN | H16: =SUMIFS(BBDD_GASTOS_FINAL!$Z:$Z,BBDD_GASTOS_FINAL!$V:$V,$B$1,BBDD_GASTOS_FINAL!$W:$W,$F$14,BBDD_GASTOS_FINAL!$AC:$AC,$G16)*-1 -> 1078197.2 | I16: 1 | J16: =L16/$L$15 -> 0.069591757 | K16: NUTRICIÓN | L16: =SUMIFS(BBDD_GASTOS_FINAL!$Z:$Z,BBDD_GASTOS_FINAL!$V:$V,$B$1,BBDD_GASTOS_FINAL!$W:$W,$F$14,BBDD_GASTOS_FINAL!$AC:$AC,$G16)*-1 -> 1078197.2 | M16: 1
A17: =A16+1 -> 2 | B17: =D17/$D$15 -> 0.33888287 | C17: PERSONAL | D17: =SUMIFS(BBDD_GASTOS_FINAL!$Z:$Z,BBDD_GASTOS_FINAL!$V:$V,$B$1,BBDD_GASTOS_FINAL!$W:$W,$B$14,BBDD_GASTOS_FINAL!AC:AC,lote_II!$C17)*-1 -> 8046961.7 | E17: 2 | F17: =H17/$H$15 -> 0.50331083 | G17: PERSONAL | H17: =SUMIFS(BBDD_GASTOS_FINAL!$Z:$Z,BBDD_GASTOS_FINAL!$V:$V,$B$1,BBDD_GASTOS_FINAL!$W:$W,$F$14,BBDD_GASTOS_FINAL!$AC:$AC,$G17)*-1 -> 7797882.3 | I17: =I16+1 -> 2 | J17: =L17/$L$15 -> 0.50331083 | K17: PERSONAL | L17: =SUMIFS(BBDD_GASTOS_FINAL!$Z:$Z,BBDD_GASTOS_FINAL!$V:$V,$B$1,BBDD_GASTOS_FINAL!$W:$W,$F$14,BBDD_GASTOS_FINAL!$AC:$AC,$G17)*-1 -> 7797882.3 | M17: =M16+1 -> 2
A18: =A17+1 -> 3 | B18: =D18/$D$15 -> 0.0086864998 | C18: SANIDAD | D18: =SUMIFS(BBDD_GASTOS_FINAL!$Z:$Z,BBDD_GASTOS_FINAL!$V:$V,$B$1,BBDD_GASTOS_FINAL!$W:$W,$B$14,BBDD_GASTOS_FINAL!AC:AC,lote_II!$C18)*-1 -> 206265.76 | E18: 3 | F18: =H18/$H$15 -> 0.02427682 | G18: SANIDAD | H18: =SUMIFS(BBDD_GASTOS_FINAL!$Z:$Z,BBDD_GASTOS_FINAL!$V:$V,$B$1,BBDD_GASTOS_FINAL!$W:$W,$F$14,BBDD_GASTOS_FINAL!$AC:$AC,$G18)*-1 -> 376124.99 | I18: =I17+12 -> 14 | J18: =L18/$L$15 -> 0.02427682 | K18: SANIDAD | L18: =SUMIFS(BBDD_GASTOS_FINAL!$Z:$Z,BBDD_GASTOS_FINAL!$V:$V,$B$1,BBDD_GASTOS_FINAL!$W:$W,$F$14,BBDD_GASTOS_FINAL!$AC:$AC,$G18)*-1 -> 376124.99 | M18: =M17+1 -> 3
A19: =A18+1 -> 4 | B19: =D19/$D$15 -> 0.11752701 | C19: GENÉTICA | D19: =SUMIFS(BBDD_GASTOS_FINAL!$Z:$Z,BBDD_GASTOS_FINAL!$V:$V,$B$1,BBDD_GASTOS_FINAL!$W:$W,$B$14,BBDD_GASTOS_FINAL!AC:AC,lote_II!$C19)*-1 -> 2790744 | E19: 4 | F19: =H19/$H$15 -> 0 | G19: GENÉTICA | H19: =SUMIFS(BBDD_GASTOS_FINAL!$Z:$Z,BBDD_GASTOS_FINAL!$V:$V,$B$1,BBDD_GASTOS_FINAL!$W:$W,$F$14,BBDD_GASTOS_FINAL!$AC:$AC,$G19)*-1 -> 0 | I19: =I18+1 -> 15 | J19: =L19/$L$15 -> 0 | K19: GENÉTICA | L19: =SUMIFS(BBDD_GASTOS_FINAL!$Z:$Z,BBDD_GASTOS_FINAL!$V:$V,$B$1,BBDD_GASTOS_FINAL!$W:$W,$F$14,BBDD_GASTOS_FINAL!$AC:$AC,$G19)*-1 -> 0 | M19: =M18+1 -> 4
A20: =A19+1 -> 5 | B20: =D20/$D$15 -> 0 | C20: FLETES | D20: =SUMIFS(BBDD_GASTOS_FINAL!$Z:$Z,BBDD_GASTOS_FINAL!$V:$V,$B$1,BBDD_GASTOS_FINAL!$W:$W,$B$14,BBDD_GASTOS_FINAL!AC:AC,lote_II!$C20)*-1 -> 0 | E20: 5 | F20: =H20/$H$15 -> 0 | G20: FLETES | H20: =SUMIFS(BBDD_GASTOS_FINAL!$Z:$Z,BBDD_GASTOS_FINAL!$V:$V,$B$1,BBDD_GASTOS_FINAL!$W:$W,$F$14,BBDD_GASTOS_FINAL!$AC:$AC,$G20)*-1 -> 0 | I20: =I19+1 -> 16 | J20: =L20/$L$15 -> 0 | K20: FLETES | L20: =SUMIFS(BBDD_GASTOS_FINAL!$Z:$Z,BBDD_GASTOS_FINAL!$V:$V,$B$1,BBDD_GASTOS_FINAL!$W:$W,$F$14,BBDD_GASTOS_FINAL!$AC:$AC,$G20)*-1 -> 0 | M20: =M19+1 -> 5
A21: =A20+1 -> 6 | B21: =D21/$D$15 -> 0.063587204 | C21: ENERGÍA | D21: =SUMIFS(BBDD_GASTOS_FINAL!$Z:$Z,BBDD_GASTOS_FINAL!$V:$V,$B$1,BBDD_GASTOS_FINAL!$W:$W,$B$14,BBDD_GASTOS_FINAL!AC:AC,lote_II!$C21)*-1 -> 1509913.4 | E21: 6 | F21: =H21/$H$15 -> 0.097456688 | G21: ENERGÍA | H21: =SUMIFS(BBDD_GASTOS_FINAL!$Z:$Z,BBDD_GASTOS_FINAL!$V:$V,$B$1,BBDD_GASTOS_FINAL!$W:$W,$F$14,BBDD_GASTOS_FINAL!$AC:$AC,$G21)*-1 -> 1509913.4 | I21: =I20+1 -> 17 | J21: =L21/$L$15 -> 0.097456688 | K21: ENERGÍA | L21: =SUMIFS(BBDD_GASTOS_FINAL!$Z:$Z,BBDD_GASTOS_FINAL!$V:$V,$B$1,BBDD_GASTOS_FINAL!$W:$W,$F$14,BBDD_GASTOS_FINAL!$AC:$AC,$G21)*-1 -> 1509913.4 | M21: =M20+1 -> 6
A22: =A21+1 -> 7 | B22: =D22/$D$15 -> 0 | C22: MENTENIMIENTO | D22: =SUMIFS(BBDD_GASTOS_FINAL!$Z:$Z,BBDD_GASTOS_FINAL!$V:$V,$B$1,BBDD_GASTOS_FINAL!$W:$W,$B$14,BBDD_GASTOS_FINAL!AC:AC,lote_II!$C22)*-1 -> 0 | E22: 7 | F22: =H22/$H$15 -> 0 | G22: MENTENIMIENTO | H22: =SUMIFS(BBDD_GASTOS_FINAL!$Z:$Z,BBDD_GASTOS_FINAL!$V:$V,$B$1,BBDD_GASTOS_FINAL!$W:$W,$F$14,BBDD_GASTOS_FINAL!$AC:$AC,$G22)*-1 -> 0 | I22: =I21+1 -> 18 | J22: =L22/$L$15 -> 0 | K22: MENTENIMIENTO | L22: =SUMIFS(BBDD_GASTOS_FINAL!$Z:$Z,BBDD_GASTOS_FINAL!$V:$V,$B$1,BBDD_GASTOS_FINAL!$W:$W,$F$14,BBDD_GASTOS_FINAL!$AC:$AC,$G22)*-1 -> 0 | M22: =M21+1 -> 7
A23: =A22+1 -> 8 | B23: =D23/$D$15 -> 0.11315524 | C23: GASTOS OPERATIVOS | D23: =SUMIFS(BBDD_GASTOS_FINAL!$Z:$Z,BBDD_GASTOS_FINAL!$V:$V,$B$1,BBDD_GASTOS_FINAL!$W:$W,$B$14,BBDD_GASTOS_FINAL!AC:AC,lote_II!$C23)*-1 -> 2686933.9 | E23: 8 | F23: =H23/$H$15 -> 0.16246346 | G23: GASTOS OPERATIVOS | H23: =SUMIFS(BBDD_GASTOS_FINAL!$Z:$Z,BBDD_GASTOS_FINAL!$V:$V,$B$1,BBDD_GASTOS_FINAL!$W:$W,$F$14,BBDD_GASTOS_FINAL!$AC:$AC,$G23)*-1 -> 2517074.6 | I23: =I22+1 -> 19 | J23: =L23/$L$15 -> 0.16246346 | K23: GASTOS OPERATIVOS | L23: =SUMIFS(BBDD_GASTOS_FINAL!$Z:$Z,BBDD_GASTOS_FINAL!$V:$V,$B$1,BBDD_GASTOS_FINAL!$W:$W,$F$14,BBDD_GASTOS_FINAL!$AC:$AC,$G23)*-1 -> 2517074.6 | M23: =M22+1 -> 8
A24: =A23+1 -> 9 | B24: =D24/$D$15 -> 0.037984075 | C24: IMPUESTOS | D24: =SUMIFS(BBDD_GASTOS_FINAL!$Z:$Z,BBDD_GASTOS_FINAL!$V:$V,$B$1,BBDD_GASTOS_FINAL!$W:$W,$B$14,BBDD_GASTOS_FINAL!AC:AC,lote_II!$C24)*-1 -> 901952.95 | E24: 9 | F24: =H24/$H$15 -> 0.12248936 | G24: IMPUESTOS | H24: =SUMIFS(BBDD_GASTOS_FINAL!$Z:$Z,BBDD_GASTOS_FINAL!$V:$V,$B$1,BBDD_GASTOS_FINAL!$W:$W,$F$14,BBDD_GASTOS_FINAL!$AC:$AC,$G24)*-1 -> 1897749 | I24: =I23+1 -> 20 | J24: =L24/$L$15 -> 0.12248936 | K24: IMPUESTOS | L24: =SUMIFS(BBDD_GASTOS_FINAL!$Z:$Z,BBDD_GASTOS_FINAL!$V:$V,$B$1,BBDD_GASTOS_FINAL!$W:$W,$F$14,BBDD_GASTOS_FINAL!$AC:$AC,$G24)*-1 -> 1897749 | M24: =M23+1 -> 9
A25: =A24+1 -> 10 | B25: =D25/$D$15 -> 0.013317546 | C25: HONORARIOS | D25: =SUMIFS(BBDD_GASTOS_FINAL!$Z:$Z,BBDD_GASTOS_FINAL!$V:$V,$B$1,BBDD_GASTOS_FINAL!$W:$W,$B$14,BBDD_GASTOS_FINAL!AC:AC,lote_II!$C25)*-1 -> 316232.53 | E25: 10 | F25: =H25/$H$15 -> 0.020411087 | G25: HONORARIOS | H25: =SUMIFS(BBDD_GASTOS_FINAL!$Z:$Z,BBDD_GASTOS_FINAL!$V:$V,$B$1,BBDD_GASTOS_FINAL!$W:$W,$F$14,BBDD_GASTOS_FINAL!$AC:$AC,$G25)*-1 -> 316232.53 | I25: =I24+1 -> 21 | J25: =L25/$L$15 -> 0.020411087 | K25: HONORARIOS | L25: =SUMIFS(BBDD_GASTOS_FINAL!$Z:$Z,BBDD_GASTOS_FINAL!$V:$V,$B$1,BBDD_GASTOS_FINAL!$W:$W,$F$14,BBDD_GASTOS_FINAL!$AC:$AC,$G25)*-1 -> 316232.53 | M25: =M24+1 -> 10
B26: =D26/$D$15 -> 0 | C26: SERVICIOS | D26: =SUMIFS(BBDD_GASTOS_FINAL!$Z:$Z,BBDD_GASTOS_FINAL!$V:$V,$B$1,BBDD_GASTOS_FINAL!$W:$W,$B$14,BBDD_GASTOS_FINAL!AC:AC,lote_II!$C26)*-1 -> 0 | F26: =H26/$H$15 -> 0 | G26: SERVICIOS | H26: =SUMIFS(BBDD_GASTOS_FINAL!$Z:$Z,BBDD_GASTOS_FINAL!$V:$V,$B$1,BBDD_GASTOS_FINAL!$W:$W,$F$14,BBDD_GASTOS_FINAL!$AC:$AC,$G26)*-1 -> 0 | J26: =L26/$L$15 -> 0 | K26: OTROS | L26: =SUMIFS(BBDD_GASTOS_FINAL!$Z:$Z,BBDD_GASTOS_FINAL!$V:$V,$B$1,BBDD_GASTOS_FINAL!$W:$W,$F$14,BBDD_GASTOS_FINAL!$AC:$AC,$G26)*-1 -> 0
F28: COMPRAS EN GESTACION | H28: =D15 -> 23745555 | J28: COMPRAS EN MATERNIDAD | L28: =H29 -> 24167088
B29: VENTAS | D29: =SUMIFS(produccion!$H:$H,produccion!$A:$A,lote_II!$B$1,produccion!$B:$B,lote_II!B14) -> 0 | F29: VENTAS | H29: =SUMIFS(produccion!$H:$H,produccion!$A:$A,lote_II!$B$1,produccion!$B:$B,lote_II!F14) -> 24167088 | J29: VENTAS | L29: =SUMIFS(produccion!$H:$H,produccion!$A:$A,lote_II!$B$1,produccion!$B:$B,lote_II!J14) -> 44760978
B31: UTILDAD | D31: =D29-D15-D28 -> -23745555 | F31: UTILDAD | H31: =H29-H15-H28 -> -15071641 | J31: UTILDAD | L31: =L29-L15-L28 -> 5100715.9
B33: CAPEX | D33: =SUMIFS(BBDD_GASTOS_FINAL!$Y:$Y,BBDD_GASTOS_FINAL!$J:$J,"Capex",BBDD_GASTOS_FINAL!$Z:$Z,$B$13) -> 0 | F33: CAPEX | H33: =SUMIFS(BBDD_GASTOS_FINAL!$Y:$Y,BBDD_GASTOS_FINAL!$J:$J,"Capex",BBDD_GASTOS_FINAL!$Z:$Z,$F$13) -> 0 | J33: CAPEX | L33: =SUMIFS(BBDD_GASTOS_FINAL!$Y:$Y,BBDD_GASTOS_FINAL!$J:$J,"Capex",BBDD_GASTOS_FINAL!$Z:$Z,$J$13) -> 0
B35: DEUDA | D35: =SUMIFS(BBDD_GASTOS_FINAL!$Y:$Y,BBDD_GASTOS_FINAL!$J:$J,"Deuda",BBDD_GASTOS_FINAL!$V:$V,B14) -> 0 | F35: DEUDA | H35: =SUMIFS(BBDD_GASTOS_FINAL!$Y:$Y,BBDD_GASTOS_FINAL!$J:$J,"Deuda",BBDD_GASTOS_FINAL!$V:$V,F14) -> 0 | J35: DEUDA | L35: =SUMIFS(BBDD_GASTOS_FINAL!$Y:$Y,BBDD_GASTOS_FINAL!$J:$J,"deuda",BBDD_GASTOS_FINAL!$V:$V,J14) -> 0
B37: Flujo de Caja al Accionista | D37: =D31-D35-D33 -> -23745555 | F37: Flujo de Caja al Accionista | H37: =H31-H35-H33 -> -15071641 | J37: Flujo de Caja al Accionista | L37: =L31-L35-L33 -> 5100715.9
F38: Margen de utilidad | H38: =H31/H29 -> -0.62364324 | J38: Margen de utilidad | L38: =L31/L29 -> 0.11395452
A39: id | B39: 1 | M39: id
B40: SITIO 3
B41: OPEX | D41: =SUM(D42:D52) -> 58948948
A42: 1 | B42: =D42/$D$41 -> 0.75149576 | C42: NUTRICIÓN | D42: =SUMIFS(BBDD_GASTOS_FINAL!$Z:$Z,BBDD_GASTOS_FINAL!$V:$V,$B$1,BBDD_GASTOS_FINAL!$W:$W,$B$40,BBDD_GASTOS_FINAL!$AC:$AC,lote_II!$C42)*-1 -> 44299884
A43: =A42+1 -> 2 | B43: =D43/$D$41 -> 0.095418867 | C43: PERSONAL | D43: =SUMIFS(BBDD_GASTOS_FINAL!$Z:$Z,BBDD_GASTOS_FINAL!$V:$V,$B$1,BBDD_GASTOS_FINAL!$W:$W,$B$40,BBDD_GASTOS_FINAL!AC:AC,lote_II!$C43)*-1 -> 5624841.8
A44: =A43+1 -> 3 | B44: =D44/$D$41 -> 0.0046519419 | C44: SANIDAD | D44: =SUMIFS(BBDD_GASTOS_FINAL!$Z:$Z,BBDD_GASTOS_FINAL!$V:$V,$B$1,BBDD_GASTOS_FINAL!$W:$W,$B$40,BBDD_GASTOS_FINAL!AC:AC,lote_II!$C44)*-1 -> 274227.08
A45: =A44+1 -> 4 | B45: =D45/$D$41 -> 0 | C45: GENÉTICA | D45: =SUMIFS(BBDD_GASTOS_FINAL!$Z:$Z,BBDD_GASTOS_FINAL!$V:$V,$B$1,BBDD_GASTOS_FINAL!$W:$W,$B$40,BBDD_GASTOS_FINAL!AC:AC,lote_II!$C45)*-1 -> 0
A46: =A45+1 -> 5 | B46: =D46/$D$41 -> 0.057726616 | C46: FLETES | D46: =SUMIFS(BBDD_GASTOS_FINAL!$Z:$Z,BBDD_GASTOS_FINAL!$V:$V,$B$1,BBDD_GASTOS_FINAL!$W:$W,$B$40,BBDD_GASTOS_FINAL!AC:AC,lote_II!$C46)*-1 -> 3402923.3
A47: =A46+1 -> 6 | B47: =D47/$D$41 -> 0.025613917 | C47: ENERGÍA | D47: =SUMIFS(BBDD_GASTOS_FINAL!$Z:$Z,BBDD_GASTOS_FINAL!$V:$V,$B$1,BBDD_GASTOS_FINAL!$W:$W,$B$40,BBDD_GASTOS_FINAL!AC:AC,lote_II!$C47)*-1 -> 1509913.4
A48: =A47+1 -> 7 | B48: =D48/$D$41 -> 0 | C48: MENTENIMIENTO | D48: =SUMIFS(BBDD_GASTOS_FINAL!$Z:$Z,BBDD_GASTOS_FINAL!$V:$V,$B$1,BBDD_GASTOS_FINAL!$W:$W,$B$40,BBDD_GASTOS_FINAL!AC:AC,lote_II!$C48)*-1 -> 0
A49: =A48+1 -> 8 | B49: =D49/$D$41 -> 0.044427808 | C49: GASTOS OPERATIVOS | D49: =SUMIFS(BBDD_GASTOS_FINAL!$Z:$Z,BBDD_GASTOS_FINAL!$V:$V,$B$1,BBDD_GASTOS_FINAL!$W:$W,$B$40,BBDD_GASTOS_FINAL!AC:AC,lote_II!$C49)*-1 -> 2618972.6
A50: =A49+1 -> 9 | B50: =D50/$D$41 -> 0.015300578 | C50: IMPUESTOS | D50: =SUMIFS(BBDD_GASTOS_FINAL!$Z:$Z,BBDD_GASTOS_FINAL!$V:$V,$B$1,BBDD_GASTOS_FINAL!$W:$W,$B$40,BBDD_GASTOS_FINAL!AC:AC,lote_II!$C50)*-1 -> 901952.95
A51: =A50+1 -> 10 | B51: =D51/$D$41 -> 0.0053645153 | C51: HONORARIOS | D51: =SUMIFS(BBDD_GASTOS_FINAL!$Z:$Z,BBDD_GASTOS_FINAL!$V:$V,$B$1,BBDD_GASTOS_FINAL!$W:$W,$B$40,BBDD_GASTOS_FINAL!AC:AC,lote_II!$C51)*-1 -> 316232.53
B52: =D52/$D$41 -> 0 | C52: SERVICIOS | D52: =SUMIFS(BBDD_GASTOS_FINAL!$Z:$Z,BBDD_GASTOS_FINAL!$V:$V,$B$1,BBDD_GASTOS_FINAL!$W:$W,$B$40,BBDD_GASTOS_FINAL!AC:AC,lote_II!$C52)*-1 -> 0
B54: COMPRAS EN SITIO 2 | D54: =L29 -> 44760978
B55: VENTAS | D55: =SUMIFS(produccion!$H:$H,produccion!$A:$A,lote_II!$B$1,produccion!$B:$B,lote_II!B40) -> 1.4756234e+08
B57: UTILDAD | D57: =D55-D41-D54 -> 43852410
B59: CAPEX | D59: =SUMIFS(BBDD_GASTOS_FINAL!$Y:$Y,BBDD_GASTOS_FINAL!$J:$J,"Capex",BBDD_GASTOS_FINAL!$Z:$Z,$B$39) -> 0
B61: DEUDA | D61: =SUMIFS(BBDD_GASTOS_FINAL!$Y:$Y,BBDD_GASTOS_FINAL!$J:$J,"deuda",BBDD_GASTOS_FINAL!$V:$V,B40) -> 0
B63: Flujo de Caja al Accionista | D63: =D57-D61-D59 -> 43852410
B64: Margen de utilidad | D64: =D57/D55 -> 0.29717888
A65: id | B65: 9 | E65: id
A66: LOTE | B66: =B1 -> 3725
A67: TOTAL | B67: <> & ""
B68: OPEX | D68: =SUM(D69:D79) -> 1.1892674e+08
B69: =D69/$D$68 -> 0.52736621 | C69: NUTRICIÓN | D69: =SUMIFS(BBDD_GASTOS_FINAL!$Z:$Z,BBDD_GASTOS_FINAL!$V:$V,$B$1,BBDD_GASTOS_FINAL!$W:$W,$B$67,BBDD_GASTOS_FINAL!$AC:$AC,lote_II!$C69)*-1 -> 62717946
B70: =D70/$D$68 -> 0.22245169 | C70: PERSONAL | D70: =SUMIFS(BBDD_GASTOS_FINAL!$Z:$Z,BBDD_GASTOS_FINAL!$V:$V,$B$1,BBDD_GASTOS_FINAL!$W:$W,$B$67,BBDD_GASTOS_FINAL!$AC:$AC,lote_II!$C70)*-1 -> 26455454
B71: =D71/$D$68 -> 0.010473616 | C71: SANIDAD | D71: =SUMIFS(BBDD_GASTOS_FINAL!$Z:$Z,BBDD_GASTOS_FINAL!$V:$V,$B$1,BBDD_GASTOS_FINAL!$W:$W,$B$67,BBDD_GASTOS_FINAL!$AC:$AC,lote_II!$C71)*-1 -> 1245593
B72: =D72/$D$68 -> 0.023466076 | C72: GENÉTICA | D72: =SUMIFS(BBDD_GASTOS_FINAL!$Z:$Z,BBDD_GASTOS_FINAL!$V:$V,$B$1,BBDD_GASTOS_FINAL!$W:$W,$B$67,BBDD_GASTOS_FINAL!$AC:$AC,lote_II!$C72)*-1 -> 2790744
B73: =D73/$D$68 -> 0.028613609 | C73: FLETES | D73: =SUMIFS(BBDD_GASTOS_FINAL!$Z:$Z,BBDD_GASTOS_FINAL!$V:$V,$B$1,BBDD_GASTOS_FINAL!$W:$W,$B$67,BBDD_GASTOS_FINAL!$AC:$AC,lote_II!$C73)*-1 -> 3402923.3
B74: =D74/$D$68 -> 0.050784656 | C74: ENERGÍA | D74: =SUMIFS(BBDD_GASTOS_FINAL!$Z:$Z,BBDD_GASTOS_FINAL!$V:$V,$B$1,BBDD_GASTOS_FINAL!$W:$W,$B$67,BBDD_GASTOS_FINAL!$AC:$AC,lote_II!$C74)*-1 -> 6039653.7
B75: =D75/$D$68 -> 0 | C75: MENTENIMIENTO | D75: =SUMIFS(BBDD_GASTOS_FINAL!$Z:$Z,BBDD_GASTOS_FINAL!$V:$V,$B$1,BBDD_GASTOS_FINAL!$W:$W,$B$67,BBDD_GASTOS_FINAL!$AC:$AC,lote_II!$C75)*-1 -> 0
B76: =D76/$D$68 -> 0.086836697 | C76: GASTOS OPERATIVOS | D76: =SUMIFS(BBDD_GASTOS_FINAL!$Z:$Z,BBDD_GASTOS_FINAL!$V:$V,$B$1,BBDD_GASTOS_FINAL!$W:$W,$B$67,BBDD_GASTOS_FINAL!$AC:$AC,lote_II!$C76)*-1 -> 10327206
B77: =D77/$D$68 -> 0.039371235 | C77: IMPUESTOS | D77: =SUMIFS(BBDD_GASTOS_FINAL!$Z:$Z,BBDD_GASTOS_FINAL!$V:$V,$B$1,BBDD_GASTOS_FINAL!$W:$W,$B$67,BBDD_GASTOS_FINAL!$AC:$AC,lote_II!$C77)*-1 -> 4682292.7
B78: =D78/$D$68 -> 0.010636213 | C78: HONORARIOS | D78: =SUMIFS(BBDD_GASTOS_FINAL!$Z:$Z,BBDD_GASTOS_FINAL!$V:$V,$B$1,BBDD_GASTOS_FINAL!$W:$W,$B$67,BBDD_GASTOS_FINAL!$AC:$AC,lote_II!$C78)*-1 -> 1264930.1
B79: =D79/$D$68 -> 0 | C79: SERVICIOS | D79: =SUMIFS(BBDD_GASTOS_FINAL!$Z:$Z,BBDD_GASTOS_FINAL!$V:$V,$B$1,BBDD_GASTOS_FINAL!$W:$W,$B$67,BBDD_GASTOS_FINAL!$AC:$AC,lote_II!$C79)*-1 -> 0
B81: VENTAS | D81: =C6 -> 1.4756234e+08
B83: UTILDAD | D83: =D81-D68 -> 28635593
B85: CAPEX | D85: =SUMIFS(BBDD_GASTOS_FINAL!$Y:$Y,BBDD_GASTOS_FINAL!$J:$J,"Capex",BBDD_GASTOS_FINAL!$Z:$Z,$B$39) -> 0
B87: DEUDA | D87: =SUMIFS(BBDD_GASTOS_FINAL!$Y:$Y,BBDD_GASTOS_FINAL!$J:$J,"deuda",BBDD_GASTOS_FINAL!$V:$V,B67) -> 2
B89: Flujo de Caja al Accionista | D89: =D83-D87-D85 -> 28635591
B90: OPEX UN | C90: =D15+H15+L15+P15+P41+L41+H41+D41+#REF!+#REF!+#REF! -> #REF!
B91: OPEX total | C91: =C7 -> 1.2164178e+08
C92: =MROUND(C91,10000)=MROUND(C90,10000) -> #REF!
B94: CAPEX_UN | C94: =D33+H33+L33+P33+P59+L59+H59+D59+D67+H67+L67 -> 0
B95: CAPEX_TOTAL | C95: =C9 -> 0 | D95: =C94=C95 -> TRUE
B96: DEUDA_UN | C96: =D35+H35+L35+P35+P61+L61+H61+D61+D69+H69+L69 -> 62717946
B97: DEUDA_TOTAL | C97: =C10 -> 110979.67 | D97: =C96=C97 -> FALSE
B101: UTILIDAD_TOTAL | C101: =C8 -> 25920551
B102: UTILIDAD_UN | C102: =D31+H31+L31+P31+P57+L57+H57+D57+#REF!+#REF!+#REF! -> #REF! | D102: =MROUND(C102,10000)=MROUND(C101,10000) -> #REF!
B105: Flujo_TOTAL | C105: =C11 -> 25809571
B106: FLUJO_UN | C106: =D37+H37+L37+P37+P63+L63+H63+D63+D71+H71+L71 -> 11381523 | D106: =MROUND(C106,10000)=MROUND(C105,10000) -> FALSE
B107: Margen de utilidad | D107: =D83/D81 -> 0.1940576

Sheet RRHH
C1: TOTAL 1+2 | D1: COMPONENTE
A2: ADMINISTRACION | B2: =_xlfn.CONCAT("RRHH-",A2) -> RRHH-ADMINISTRACION | C2: 67124149 | D2: 100% ADMINISTRACION - 100% DIRECTOR | E2: CC1
A3: INTENDENCIA | B3: =_xlfn.CONCAT("RRHH-",A3) -> RRHH-INTENDENCIA | C3: 9375237.7 | D3: 100% INTENDENCIA - 6,67% PRODUCCION | E3: CC1
A4: LABORATORIO | B4: =_xlfn.CONCAT("RRHH-",A4) -> RRHH-LABORATORIO | C4: 12249966 | D4: 100% LABORATORIO - 6,67% PRODUCCION | E4: CC1
A5: LOGISTICA | B5: =_xlfn.CONCAT("RRHH-",A5) -> RRHH-LOGISTICA | C5: 6459899.7 | D5: 75% LOGISTICA - 6,67% PRODUCCION | E5: CC1
A6: MANTENIMIENTO | B6: =_xlfn.CONCAT("RRHH-",A6) -> RRHH-MANTENIMIENTO | C6: 7742399.7 | D6: 100% MANTENIMIENTO - 6,67% PRODUCCION | E6: CC1
A7: NFU | B7: =_xlfn.CONCAT("RRHH-",A7) -> RRHH-NFU | C7: 29572095 | D7: 25% LOGISTICA - 100% CAT - 100% EXTERNO NFU - 6,67% PRODUCCION - 95% NFU | E7: CC7
A8: PORTERIA | B8: =_xlfn.CONCAT("RRHH-",A8) -> RRHH-PORTERIA | C8: 10797311 | D8: 100% PORTERIA - 6,67% PRODUCCION | E8: CC1
A9: COMPOST Y FERTILIZANTES | B9: =_xlfn.CONCAT("RRHH-",A9) -> RRHH-COMPOST Y FERTILIZANTES | C9: 1833599.1 | D9: 60% COMPOST Y FERTILIZANTES - 6,67% PRODUCCION | E9: CC14
A10: CEREAL Y POLVILLO | B10: =_xlfn.CONCAT("RRHH-",A10) -> RRHH-CEREAL Y POLVILLO | C10: 0 | D10: 0% CEREAL Y POLVILLO - 0% PRODUCCION | E10: NO
A11: TALLER MECANICO | B11: =_xlfn.CONCAT("RRHH-",A11) -> RRHH-TALLER MECANICO | C11: 6300478.7 | D11: 100% TALLER MECANICO - 6,67% PRODUCCION | E11: CC1
A12: TIERRAS FILTRANTES | B12: =_xlfn.CONCAT("RRHH-",A12) -> RRHH-TIERRAS FILTRANTES | C12: 0 | D12: 0% TIERRAS FILTRANTES - 0% PRODUCCION | E12: NO
A13: VIGILANCIA | B13: =_xlfn.CONCAT("RRHH-",A13) -> RRHH-VIGILANCIA | C13: 6294101.7 | D13: 100% VIGILANCIA - 6,67% PRODUCCION | E13: CC1
... A21: SALES | B21: =_xlfn.CONCAT("RRHH-",A21) -> RRHH-SALES | C21: 0 | D21: 0% SALES - 0% PRODUCCION | E21: NO

Sheet ref_rrhh
A1: Sector | B1: f/v | C1: d/i
A2: ADMINISTRACION | B2: Fijo | C2: Indirecto
A3: INTENDENCIA | B3: Fijo | C3: Indirecto
A4: REACTOR | B4: Variable | C4: Directo
A5: NFU | B5: Variable | C5: Directo
A6: DISPOSICION FINAL DE R. LIQUIDOS | B6: Variable | C6: Directo
A7: DIRECTOR | B7: Fijo | C7: Indirecto
A8: TALLER MECANICO | B8: Fijo | C8: Indirecto
A9: PRODUCCION | B9: Variable | C9: Directo
A10: CAT | B10: Variable | C10: Directo
A11: MANTENIMIENTO | B11: Fijo | C11: Indirecto
A12: PORTERIA | B12: Fijo | C12: Indirecto
... A17: COMPOST Y FERTILIZANTES | B17: Variable | C17: Directo

Sheet aperturado_por_empresa.p2
A1: {=_xlfn._xlws.PY(0,0,#REF!)} -> #REF!

Sheet bbdd_ape.p3
A1: Fecha de Factura/Recibo | B1: Nombre de la empresa a mostrar en la factura | C1: Número | D1: Total con signo | E1: Líneas de factura/Etiqueta | F1: Líneas de factura/Cantidad | G1: Líneas de factura/Precio unitario | H1: Líneas de factura/Unidad de medida | I1: Líneas de factura/Producto | J1: Concepto | K1: Tipo de Gasto 1 | L1: Tipo de Gasto 2 | M1: CCO EMPRESA | N1: CCO - SECTOR | O1: SECTOR_ODOO | P1: # SECTORES | Q1: LISTA_SECTORES | R1: Column1 | S1: Column2 | T1: Column3 | U1: Column4
A2: 45958 | B2: H.S.E. Ingenieria S R L | C2: FA-A 00003-00027849 | D2: -3315400 | E2: OC 0001-00001756: SERVICIOS Monitoreo | F2: 1 | G2: 2740000 | H2: UN | I2: SERVICIOS | J2: OPEX | K2: VARIABLE | L2: INDIRECTO | M2: 0 | N2: CC1 | O2: #NUM! | P2: 10 | Q2: BACHAS, CEREAL & POLVILLO, COMPOST & FERTILIZANTES, DISPOSICIÓN FINAL RESIDUOS LIQUIDOS, DISPOSICIÓN FINAL RESIDUOS SOLIDOS, EXPORTACION, NFU, PILETAS, REACTORES, TIERRAS FILTRANTES | R2: 1 | S2: -3315400 | T2: 1 | U2: APERTURADO POR EMPRESA
A3: 45933 | B3: Alvarez, Alejandro Dario | C3: FA-C 00002-00000250 | D3: -509644 | E3: OC 0001-00001364: HIGIENE Y SEGURIDAD Servicio de asesoramiento para la gestión ambiental en el cumplimiento de la normativa vigente para la provincia de Santa Fe. Servicio de higiene y seguridad de trabajo con cumplimiento de actividades s/Resol. SRT 905/15- MES 09/2025 | F3: 1 | G3: 509644 | H3: UN | I3: HIGIENE Y SEGURIDAD | J3: OPEX | K3: FIJO | L3: DIRECTO | M3: 0 | N3: CC1 | O3: #NUM! | P3: 10 | Q3: BACHAS, CEREAL & POLVILLO, COMPOST & FERTILIZANTES, DISPOSICIÓN FINAL RESIDUOS LIQUIDOS, DISPOSICIÓN FINAL RESIDUOS SOLIDOS, EXPORTACION, NFU, PILETAS, REACTORES, TIERRAS FILTRANTES | R3: 1 | S3: -509644 | T3: 1 | U3: APERTURADO POR EMPRESA
A4: 45931 | B4: Quiroz, Maria Ines | C4: FA-C 00002-00000031 | D4: -2097200 | E4: OC 0001-00001801: PERSONAL horas soldador | F4: 1 | G4: 2097200 | H4: UN | I4: PERSONAL | J4: OPEX | K4: FIJO | L4: INDIRECTO | M4: 0 | N4: CC1 | O4: #NUM! | P4: 10 | Q4: BACHAS, CEREAL & POLVILLO, COMPOST & FERTILIZANTES, DISPOSICIÓN FINAL RESIDUOS LIQUIDOS, DISPOSICIÓN FINAL RESIDUOS SOLIDOS, EXPORTACION, NFU, PILETAS, REACTORES, TIERRAS FILTRANTES | R4: 1 | S4: -2097200 | T4: 1 | U4: APERTURADO POR EMPRESA
A5: 45947 | B5: Lopez, Jesus Rodrigo | C5: OCOM/2025/0470 | D5: -180000 | E5: OC 0001-00001345: LOGISTICA puerto | F5: 1 | G5: 180000 | H5: UN | I5: LOGISTICA | J5: OPEX | K5: VARIABLE | L5: DIRECTO | M5: 0 | N5: CC9 | O5: #NUM! | P5: 1 | Q5: CEREAL & POLVILLO | R5: 1 | S5: -180000 | T5: 1 | U5: APERTURADO POR EMPRESA
A6: 45938 | B6: Lopez, Jesus Rodrigo | C6: OCOM/2025/0458 | D6: -180000 | E6: OC 0001-00001804: LOGISTICA | F6: 1 | G6: 180000 | H6: UN | I6: LOGISTICA | J6: OPEX | K6: VARIABLE | L6: DIRECTO | M6: 0 | N6: CC9 | O6: #NUM! | P6: 1 | Q6: CEREAL & POLVILLO | R6: 1 | S6: -180000 | T6: 1 | U6: APERTURADO POR EMPRESA
A7: 45931 | B7: Lopez, Jesus Rodrigo | C7: OCOM/2025/0443 | D7: -156000 | E7: OC 0001-00000944: LOGISTICA | F7: 1 | G7: 156000 | H7: UN | I7: LOGISTICA | J7: OPEX | K7: VARIABLE | L7: DIRECTO | M7: 0 | N7: CC9 | O7: #NUM! | P7: 1 | Q7: CEREAL & POLVILLO | R7: 1 | S7: -156000 | T7: 1 | U7: APERTURADO POR EMPRESA
A8: 45950 | B8: Area Abierta S.A. | C8: FA-A 00001-00001146 | D8: -798367.68 | E8: OC 0001-00001924: REPOSICION paño zda luz 6.50 2.50 mm 4 x1,60 metros (NFU) | F8: 1 | G8: 659808 | H8: UN | I8: REPOSICION | J8: OPEX | K8: VARIABLE | L8: DIRECTO | M8: 0 | N8: CC7 | O8: #NUM! | P8: 2 | Q8: NFU | R8: 1 | S8: -798367.68 | T8: 1 | U8: APERTURADO POR EMPRESA
A9: 45958 | B9: Bernis, Carlos Oscar | C9: FA-A 00006-00000175 | D9: -968000 | E9: OC 0001-00002255: LOGISTICA Viaje realizado fecha 28/10 | F9: 1 | G9: 800000 | H9: UN | I9: LOGISTICA | J9: OPEX | K9: VARIABLE | L9: DIRECTO | M9: 0 | N9: CC7 | O9: #NUM! | P9: 2 | Q9: NFU | R9: 1 | S9: -968000 | T9: 1 | U9: APERTURADO POR EMPRESA
A10: 45952 | B10: Bernis, Carlos Oscar | C10: FA-A 00006-00000174 | D10: -968000 | E10: OC 0001-00002218: LOGISTICA Viaje realizado fecha 20-10 worms - Parque industrial guernica | F10: 1 | G10: 800000 | H10: UN | I10: LOGISTICA | J10: OPEX | K10: VARIABLE | L10: DIRECTO | M10: 0 | N10: CC7 | O10: #NUM! | P10: 2 | Q10: NFU | R10: 1 | S10: -968000 | T10: 1 | U10: APERTURADO POR EMPRESA
A11: 45939 | B11: Bernis, Carlos Oscar | C11: FA-A 00006-00000171 | D11: -302500 | E11: OC 0001-00001836: LOGISTICA Viaje: 4 de septiembre origen: lujan worms con cubiertas en desuso . Destino :worms | F11: 1 | G11: 250000 | H11: UN | I11: LOGISTICA | J11: OPEX | K11: VARIABLE | L11: DIRECTO | M11: 0 | N11: CC7 | O11: #NUM! | P11: 2 | Q11: NFU | R11: 1 | S11: -302500 | T11: 1 | U11: APERTURADO POR EMPRESA
A12: 45939 | B12: Bernis, Carlos Oscar | C12: FA-A 00006-00000170 | D12: -968000 | E12: OC 0001-00002228: LOGISTICA Viaje realizado fecha 8/10 neumáticos | F12: 1 | G12: 800000 | H12: UN | I12: LOGISTICA | J12: OPEX | K12: VARIABLE | L12: DIRECTO | M12: 0 | N12: CC7 | O12: #NUM! | P12: 2 | Q12: NFU | R12: 1 | S12: -968000 | T12: 1 | U12: APERTURADO POR EMPRESA
A13: 45958 | B13: Comercial Uritorco S. R. L. (w) | C13: FA-A 00001-00007089 | D13: -66182.16 | E13: OC 0001-00002229: REPOSICION Adaptador 3/4 | F13: 2 | G13: 19578.51 | H13: UN | I13: REPOSICION | J13: OPEX | K13: VARIABLE | L13: INDIRECTO | M13: 0 | N13: CC7 | O13: #NUM! | P13: 2 | Q13: NFU | R13: 1 | S13: -66182.16 | T13: 2 | U13: APERTURADO POR EMPRESA
... A77: 45932 | B77: Acosta, Roberto Maximiliano | C77: FA-C 00001-00000616 | D77: -4632990 | E77: OC 0001-00001709: SERVICIOS de limpieza +ipc julio y agosto 3,8% | F77: 1 | G77: 4632990 | H77: UN | I77: SERVICIOS | J77: OPEX | K77: VARIABLE | L77: INDIRECTO | M77: 0 | N77: CC1 | O77: #NUM! | P77: 10 | Q77: BACHAS, CEREAL & POLVILLO, COMPOST & FERTILIZANTES, DISPOSICIÓN FINAL RESIDUOS LIQUIDOS, DISPOSICIÓN FINAL RESIDUOS SOLIDOS, EXPORTACION, NFU, PILETAS, REACTORES, TIERRAS FILTRANTES | R77: 1 | S77: -4632990 | T77: 1 | U77: APERTURADO POR EMPRESA
A78: 45931 | B78: Adhoc S.A. | C78: FA-A 00003-00019779 | D78: -2004596.6 | E78: OC 0001-00001367: SERVICIOS Sistema contable | F78: 1 | G78: 1656691.4 | H78: UN | I78: SERVICIOS | J78: OPEX | K78: FIJO | L78: INDIRECTO | M78: CC13 | N78: CC1 | O78: #NUM! | P78: 10 | Q78: BACHAS, CEREAL & POLVILLO, COMPOST & FERTILIZANTES, DISPOSICIÓN FINAL RESIDUOS LIQUIDOS, DISPOSICIÓN FINAL RESIDUOS SOLIDOS, EXPORTACION, NFU, PILETAS, REACTORES, TIERRAS FILTRANTES | R78: 0.7 | S78: -1403217.6 | T78: 0.7 | U78: APERTURADO POR EMPRESA
A79: 45950 | B79: American Express Argentina S. A. | C79: OCOM/2025/0472 | D79: -344000.85 | E79: OC 0001-00001936: PERSONAL | F79: 1 | G79: 344000.85 | H79: UN | I79: PERSONAL | J79: OPEX | K79: VARIABLE | L79: INDIRECTO | M79: 0 | N79: CC1 | O79: #NUM! | P79: 10 | Q79: BACHAS, CEREAL & POLVILLO, COMPOST & FERTILIZANTES, DISPOSICIÓN FINAL RESIDUOS LIQUIDOS, DISPOSICIÓN FINAL RESIDUOS SOLIDOS, EXPORTACION, NFU, PILETAS, REACTORES, TIERRAS FILTRANTES | R79: 1 | S79: -344000.85 | T79: 1 | U79: APERTURADO POR EMPRESA
A80: 45949 | B80: Amx Argentina Sociedad Anonima | C80: FA-A 01331-01351660 | D80: -40348.6 | E80: OC 0001-00002225: SERVICIOS Servicio Móvil | F80: 1 | G80: 10605 | H80: UN | I80: SERVICIOS | J80: OPEX | K80: VARIABLE | L80: INDIRECTO | M80: 0 | N80: CC1 | O80: #NUM! | P80: 10 | Q80: BACHAS, CEREAL & POLVILLO, COMPOST & FERTILIZANTES, DISPOSICIÓN FINAL RESIDUOS LIQUIDOS, DISPOSICIÓN FINAL RESIDUOS SOLIDOS, EXPORTACION, NFU, PILETAS, REACTORES, TIERRAS FILTRANTES | R80: 1 | S80: -40348.6 | T80: 1 | U80: APERTURADO POR EMPRESA
A81: 45931 | B81: Aranda, Marisa Isabel | C81: FA-C 00005-00000212 | D81: -720000 | E81: OC 0001-00001711: SERVICIOS servicio de parquización | F81: 9 | G81: 80000 | H81: UN | I81: SERVICIOS | J81: OPEX | K81: VARIABLE | L81: INDIRECTO | M81: 0 | N81: CC1 | O81: #NUM! | P81: 10 | Q81: BACHAS, CEREAL & POLVILLO, COMPOST & FERTILIZANTES, DISPOSICIÓN FINAL RESIDUOS LIQUIDOS, DISPOSICIÓN FINAL RESIDUOS SOLIDOS, EXPORTACION, NFU, PILETAS, REACTORES, TIERRAS FILTRANTES | R81: 1 | S81: -720000 | T81: 9 | U81: APERTURADO POR EMPRESA
A82: 45952 | B82: ARCA | C82: OCOM/2025/0481 | D82: -3840846 | E82: OC 0001-00002049: IMPUESTOS anticipo | F82: 1 | G82: 3840846 | H82: UN | I82: IMPUESTOS | J82: OPEX | K82: VARIABLE | L82: INDIRECTO | M82: 0 | N82: CC1 | O82: #NUM! | P82: 10 | Q82: BACHAS, CEREAL & POLVILLO, COMPOST & FERTILIZANTES, DISPOSICIÓN FINAL RESIDUOS LIQUIDOS, DISPOSICIÓN FINAL RESIDUOS SOLIDOS, EXPORTACION, NFU, PILETAS, REACTORES, TIERRAS FILTRANTES | R82: 1 | S82: -3840846 | T82: 1 | U82: APERTURADO POR EMPRESA
A83: 45952 | B83: ARCA | C83: OCOM/2025/0479 | D83: -1311921.2 | E83: OC 0001-00002043: IMPUESTOS Multa suse | F83: 1 | G83: 1311921.2 | H83: UN | I83: IMPUESTOS | J83: DEUDA | K83: VARIABLE | L83: INDIRECTO | M83: 0 | N83: CC1 | O83: #NUM! | P83: 10 | Q83: BACHAS, CEREAL & POLVILLO, COMPOST & FERTILIZANTES, DISPOSICIÓN FINAL RESIDUOS LIQUIDOS, DISPOSICIÓN FINAL RESIDUOS SOLIDOS, EXPORTACION, NFU, PILETAS, REACTORES, TIERRAS FILTRANTES | R83: 1 | S83: -1311921.2 | T83: 1 | U83: APERTURADO POR EMPRESA
A84: 45946 | B84: ARCA | C84: OCOM/2025/0466 | D84: -552778.24 | E84: OC 0001-00001904: HONORARIOS Didomenico | F84: 1 | G84: 552778.24 | H84: UN | I84: HONORARIOS | J84: DEUDA | K84: VARIABLE | L84: INDIRECTO | M84: 0 | N84: CC1 | O84: #NUM! | P84: 10 | Q84: BACHAS, CEREAL & POLVILLO, COMPOST & FERTILIZANTES, DISPOSICIÓN FINAL RESIDUOS LIQUIDOS, DISPOSICIÓN FINAL RESIDUOS SOLIDOS, EXPORTACION, NFU, PILETAS, REACTORES, TIERRAS FILTRANTES | R84: 1 | S84: -552778.24 | T84: 1 | U84: APERTURADO POR EMPRESA
A85: 45946 | B85: ARCA | C85: OCOM/2025/0464 | D85: -15235035 | E85: OC 0001-00001869: IMPUESTOS Deuda, Planes de pago | F85: 1 | G85: 15235035 | H85: UN | I85: IMPUESTOS | J85: DEUDA | K85: VARIABLE | L85: INDIRECTO | M85: 0 | N85: CC1 | O85: #NUM! | P85: 10 | Q85: BACHAS, CEREAL & POLVILLO, COMPOST & FERTILIZANTES, DISPOSICIÓN FINAL RESIDUOS LIQUIDOS, DISPOSICIÓN FINAL RESIDUOS SOLIDOS, EXPORTACION, NFU, PILETAS, REACTORES, TIERRAS FILTRANTES | R85: 1 | S85: -15235035 | T85: 1 | U85: APERTURADO POR EMPRESA
A86: 45954 | B86: Asociacion Empleados De Comercio De Rosario | C86: OCOM/2025/0504 | D86: -1383181 | E86: OC 0001-00002124: SERVICIOS | F86: 1 | G86: 1383181 | H86: UN | I86: SERVICIOS | J86: DEUDA | K86: VARIABLE | L86: INDIRECTO | M86: 0 | N86: CC1 | O86: #NUM! | P86: 10 | Q86: BACHAS, CEREAL & POLVILLO, COMPOST & FERTILIZANTES, DISPOSICIÓN FINAL RESIDUOS LIQUIDOS, DISPOSICIÓN FINAL RESIDUOS SOLIDOS, EXPORTACION, NFU, PILETAS, REACTORES, TIERRAS FILTRANTES | R86: 1 | S86: -1383181 | T86: 1 | U86: APERTURADO POR EMPRESA
A87: 45951 | B87: Asociacion Mutual 23 De Setiembre | C87: OCOM/2025/0477 | D87: -10000000 | E87: OC 0001-00002032: SERVICIOS mutual | F87: 1 | G87: 10000000 | H87: UN | I87: SERVICIOS | J87: DEUDA | K87: VARIABLE | L87: INDIRECTO | M87: 0 | N87: CC1 | O87: #NUM! | P87: 10 | Q87: BACHAS, CEREAL & POLVILLO, COMPOST & FERTILIZANTES, DISPOSICIÓN FINAL RESIDUOS LIQUIDOS, DISPOSICIÓN FINAL RESIDUOS SOLIDOS, EXPORTACION, NFU, PILETAS, REACTORES, TIERRAS FILTRANTES | R87: 1 | S87: -10000000 | T87: 1 | U87: APERTURADO POR EMPRESA
A88: 45931 | B88: Berardi, Alberto Jose - | C88: FA-C 00005-00000184 | D88: -560000 | E88: OC 0001-00001696: SERVICIOS Abono mensual | F88: 1 | G88: 560000 | H88: UN | I88: SERVICIOS | J88: OPEX | K88: VARIABLE | L88: INDIRECTO | M88: 0 | N88: CC1 | O88: #NUM! | P88: 10 | Q88: BACHAS, CEREAL & POLVILLO, COMPOST & FERTILIZANTES, DISPOSICIÓN FINAL RESIDUOS LIQUIDOS, DISPOSICIÓN FINAL RESIDUOS SOLIDOS, EXPORTACION, NFU, PILETAS, REACTORES, TIERRAS FILTRANTES | R88: 1 | S88: -560000 | T88: 1 | U88: APERTURADO POR EMPRESA
A89: 45943 | B89: Bollini, Tomas Maria | C89: OCOM/2025/0461 | D89: -114000 | E89: OC 0001-00001835: PERSONAL CARTA DOCUMENTO | F89: 1 | G89: 114000 | H89: UN | I89: PERSONAL | J89: OPEX | K89: VARIABLE | L89: INDIRECTO | M89: 0 | N89: CC1 | O89: #NUM! | P89: 10 | Q89: BACHAS, CEREAL & POLVILLO, COMPOST & FERTILIZANTES, DISPOSICIÓN FINAL RESIDUOS LIQUIDOS, DISPOSICIÓN FINAL RESIDUOS SOLIDOS, EXPORTACION, NFU, PILETAS, REACTORES, TIERRAS FILTRANTES | R89: 1 | S89: -114000 | T89: 1 | U89: APERTURADO POR EMPRESA
A90: 45937 | B90: Castelli, Guillermo Alejandro | C90: OCOM/2025/0457 | D90: -1500000 | E90: OC 0001-00001799: PERSONAL personal, acuerdo. | F90: 1 | G90: 1500000 | H90: UN | I90: PERSONAL | J90: DEUDA | K90: VARIABLE | L90: INDIRECTO | M90: 0 | N90: CC1 | O90: #NUM! | P90: 10 | Q90: BACHAS, CEREAL & POLVILLO, COMPOST & FERTILIZANTES, DISPOSICIÓN FINAL RESIDUOS LIQUIDOS, DISPOSICIÓN FINAL RESIDUOS SOLIDOS, EXPORTACION, NFU, PILETAS, REACTORES, TIERRAS FILTRANTES | R90: 1 | S90: -1500000 | T90: 1 | U90: APERTURADO POR EMPRESA
... A152: 45961 | B152: PROVEEDOR | C152: MT-0004 | D152: -3029264148 | E152: AFE (S) | F152: 2236.94 | G152: 925 | H152: TN | I152: MATERIA PRIMA | J152: OPEX | K152: VARIABLE | L152: DIRECTO | M152: 0 | N152: CC11 | O152: #NUM! | P152: 1 | Q152: EXPORTACION | R152: 1 | S152: -3029264148 | T152: 2236.94 | U152: APERTURADO POR EMPRESA
A153: 45961 | B153: PILETAS | C153: MT-0005 | D153: 0 | E153: AG- A | F153: #NUM! | G153: 850 | H153: TN | I153: MATERIA PRIMA | J153: OPEX | K153: VARIABLE | L153: DIRECTO | M153: 0 | N153: CC11 | O153: #NUM! | P153: 1 | Q153: EXPORTACION | R153: 1 | S153: 0 | T153: #NUM! | U153: APERTURADO POR EMPRESA
A154: 45961 | B154: PILETAS | C154: MT-0006 | D154: -24537811 | E154: AG- B | F154: 20.44 | G154: 820 | H154: TN | I154: MATERIA PRIMA | J154: OPEX | K154: VARIABLE | L154: DIRECTO | M154: 0 | N154: CC11 | O154: #NUM! | P154: 1 | Q154: EXPORTACION | R154: 1 | S154: -24537811 | T154: 20.44 | U154: APERTURADO POR EMPRESA
A155: 45961 | B155: PILETAS | C155: MT-0007 | D155: -12127190 | E155: AG- C | F155: 15.34 | G155: 540 | H155: TN | I155: MATERIA PRIMA | J155: OPEX | K155: VARIABLE | L155: DIRECTO | M155: 0 | N155: CC11 | O155: #NUM! | P155: 1 | Q155: EXPORTACION | R155: 1 | S155: -12127190 | T155: 15.34 | U155: APERTURADO POR EMPRESA
A156: 45961 | B156: REACTORES | C156: MT-0008 | D156: 0 | E156: ARE- A | F156: #NUM! | G156: 820 | H156: TN | I156: MATERIA PRIMA | J156: OPEX | K156: VARIABLE | L156: DIRECTO | M156: 0 | N156: CC11 | O156: #NUM! | P156: 1 | Q156: EXPORTACION | R156: 1 | S156: 0 | T156: #NUM! | U156: APERTURADO POR EMPRESA
A157: 45961 | B157: REACTORES | C157: MT-0009 | D157: 0 | E157: ARE- B | F157: #NUM! | G157: 820 | H157: TN | I157: MATERIA PRIMA | J157: OPEX | K157: VARIABLE | L157: DIRECTO | M157: 0 | N157: CC11 | O157: #NUM! | P157: 1 | Q157: EXPORTACION | R157: 1 | S157: 0 | T157: #NUM! | U157: APERTURADO POR EMPRESA
A158: 45961 | B158: REACTORES -PZ | C158: MT-0010 | D158: -246338496 | E158: ARE- A | F158: 205.2 | G158: 820 | H158: TN | I158: MATERIA PRIMA | J158: OPEX | K158: VARIABLE | L158: DIRECTO | M158: 0 | N158: NO | O158: #NUM! | P158: 1 | Q158: ANULADO | R158: 1 | S158: -246338496 | T158: 205.2 | U158: APERTURADO POR EMPRESA
A159: 45961 | B159: REACTORES - PZ | C159: MT-0011 | D159: 0 | E159: ARE- B | F159: #NUM! | G159: 820 | H159: TN | I159: MATERIA PRIMA | J159: OPEX | K159: VARIABLE | L159: DIRECTO | M159: 0 | N159: NO | O159: #NUM! | P159: 1 | Q159: ANULADO | R159: 1 | S159: 0 | T159: #NUM! | U159: APERTURADO POR EMPRESA
A160: 45961 | B160: WORMS 2 | C160: MT-0012 | D160: -154255824 | E160: AG- A | F160: 123.96 | G160: 850 | H160: TN | I160: MATERIA PRIMA | J160: OPEX | K160: VARIABLE | L160: DIRECTO | M160: 0 | N160: NO | O160: #NUM! | P160: 1 | Q160: ANULADO | R160: 1 | S160: -154255824 | T160: 123.96 | U160: APERTURADO POR EMPRESA
A161: 45961 | B161: WORMS 2 | C161: MT-0013 | D161: 0 | E161: AG- B | F161: #NUM! | G161: 820 | H161: TN | I161: MATERIA PRIMA | J161: OPEX | K161: VARIABLE | L161: DIRECTO | M161: 0 | N161: NO | O161: #NUM! | P161: 1 | Q161: ANULADO | R161: 1 | S161: 0 | T161: #NUM! | U161: APERTURADO POR EMPRESA
A162: 45961 | B162: WORMS 2 | C162: MT-0014 | D162: -8300880 | E162: AG- C | F162: 10.5 | G162: 540 | H162: TN | I162: MATERIA PRIMA | J162: OPEX | K162: VARIABLE | L162: DIRECTO | M162: 0 | N162: NO | O162: #NUM! | P162: 1 | Q162: ANULADO | R162: 1 | S162: -8300880 | T162: 10.5 | U162: APERTURADO POR EMPRESA
A163: 45961 | B163: PZ ( BORRA + PROVEEDOR) | C163: MT-0021 | D163: -91072512 | E163: AG- C | F163: 115.2 | G163: 540 | H163: TN | I163: MATERIA PRIMA | J163: OPEX | K163: VARIABLE | L163: DIRECTO | M163: 0 | N163: NO | O163: #NUM! | P163: 1 | Q163: ANULADO | R163: 1 | S163: -91072512 | T163: 115.2 | U163: APERTURADO POR EMPRESA
A164: 45961 | B164: PILETAS | C164: MT-0022 | D164: 0 | E164: AG- C | F164: #NUM! | G164: 540 | H164: TN | I164: MATERIA PRIMA | J164: OPEX | K164: VARIABLE | L164: DIRECTO | M164: 0 | N164: CC5 | O164: #NUM! | P164: 1 | Q164: REACTORES | R164: 1 | S164: 0 | T164: #NUM! | U164: APERTURADO POR EMPRESA
A165: 45961 | B165: PROVEEDOR | C165: MT-0023 | D165: -1.6548757e+08 | E165: AG - E | F165: 124.32 | G165: 909.25 | H165: TN | I165: MATERIA PRIMA | J165: OPEX | K165: VARIABLE | L165: DIRECTO | M165: 0 | N165: CC11 | O165: #NUM! | P165: 1 | Q165: EXPORTACION | R165: 1 | S165: -1.6548757e+08 | T165: 124.32 | U165: APERTURADO POR EMPRESA
A166: 45961 | B166: WORMS 2 | C166: MT-0024 | D166: 0 | E166: SEBO C - 2da | F166: #NUM! | G166: #NUM! | H166: TN | I166: MATERIA PRIMA | J166: OPEX | K166: VARIABLE | L166: DIRECTO | M166: 0 | N166: NO | O166: #NUM! | P166: 1 | Q166: ANULADO | R166: 1 | S166: 0 | T166: #NUM! | U166: APERTURADO POR EMPRESA
A167: 45961 | B167: WORMS 2 | C167: MT-0025 | D167: 0 | E167: BORRA A VEGETAL | F167: 126.22 | G167: #NUM! | H167: TN | I167: MATERIA PRIMA | J167: OPEX | K167: VARIABLE | L167: DIRECTO | M167: 0 | N167: NO | O167: #NUM! | P167: 1 | Q167: ANULADO | R167: 1 | S167: 0 | T167: 126.22 | U167: APERTURADO POR EMPRESA
A168: 45961 | B168: WORMS 2 | C168: MT-0026 | D168: 0 | E168: FONDO TK | F168: 22.2 | G168: #NUM! | H168: TN | I168: MATERIA PRIMA | J168: OPEX | K168: VARIABLE | L168: DIRECTO | M168: 0 | N168: NO | O168: #NUM! | P168: 1 | Q168: ANULADO | R168: 1 | S168: 0 | T168: 22.2 | U168: APERTURADO POR EMPRESA
A169: 45961 | B169: WORMS 2 | C169: MT-0027 | D169: 0 | E169: BORRA ANIMAL | F169: 34.1 | G169: #NUM! | H169: TN | I169: MATERIA PRIMA | J169: OPEX | K169: VARIABLE | L169: DIRECTO | M169: 0 | N169: NO | O169: #NUM! | P169: 1 | Q169: ANULADO | R169: 1 | S169: 0 | T169: 34.1 | U169: APERTURADO POR EMPRESA
A170: 45961 | B170: PROVEEDOR | C170: MT-0028 | D170: 0 | E170: BORRA PESCADO | F170: 86.28 | G170: #NUM! | H170: TN | I170: MATERIA PRIMA | J170: OPEX | K170: VARIABLE | L170: DIRECTO | M170: 0 | N170: NO | O170: #NUM! | P170: 1 | Q170: ANULADO | R170: 1 | S170: 0 | T170: 86.28 | U170: APERTURADO POR EMPRESA
A171: 45961 | B171: PILETAS | C171: MT-0029 | D171: -26088480 | E171: EMULSION | F171: 35.64 | G171: 500 | H171: TN | I171: MATERIA PRIMA | J171: OPEX | K171: VARIABLE | L171: DIRECTO | M171: 0 | N171: CC4 | O171: #NUM! | P171: 1 | Q171: PILETAS | R171: 1 | S171: -26088480 | T171: 35.64 | U171: APERTURADO POR EMPRESA
A172: 45961 | B172: PILETAS | C172: MT-0030 | D172: 0 | E172: AG-D | F172: 82.26 | G172: #NUM! | H172: TN | I172: MATERIA PRIMA | J172: 0 | K172: 0 | L172: 0 | M172: 0 | N172: 0 | O172: #NUM! | P172: 0 | Q172: 0 | R172: 1 | S172: 0 | T172: 82.26 | U172: APERTURADO POR EMPRESA
A173: 45961 | B173: Martins, Joaquin | C173: AD-0001 | D173: 0 | E173: ENERGIA GASOIL G3 | F173: #NUM! | G173: 1754 | H173: Lts | I173: ENERGIA | J173: OPEX | K173: VARIABLE | L173: DIRECTO | M173: 0 | N173: CC1 | O173: #NUM! | P173: CCO NO DEFINIDO | Q173: CCO NO DEFINIDO | R173: 1 | S173: 0 | T173: #NUM! | U173: APERTURADO POR EMPRESA
A174: 45961 | B174: Martins, Joaquin | C174: AD-0001 | D174: -2679040 | E174: ENERGIA G2 | F174: 1820 | G174: 1472 | H174: Lts | I174: ENERGIA | J174: OPEX | K174: VARIABLE | L174: DIRECTO | M174: 0 | N174: CC6 | O174: #NUM! | P174: 1 | Q174: BACHAS | R174: 1 | S174: -2679040 | T174: 1820 | U174: APERTURADO POR EMPRESA
A175: 45961 | B175: Martins, Joaquin | C175: AD-0001 | D175: 0 | E175: ENERGIA G2 | F175: 0 | G175: 1472 | H175: Lts | I175: ENERGIA | J175: OPEX | K175: VARIABLE | L175: DIRECTO | M175: 0 | N175: CC5 | O175: #NUM! | P175: 1 | Q175: REACTORES | R175: 1 | S175: 0 | T175: 0 | U175: APERTURADO POR EMPRESA
A176: 45961 | B176: Martins, Joaquin | C176: AD-0001 | D176: -149500 | E176: ENERGIA Nafta | F176: 100 | G176: 1495 | H176: Lts | I176: ENERGIA | J176: OPEX | K176: VARIABLE | L176: DIRECTO | M176: 0 | N176: CC6 | O176: #NUM! | P176: 1 | Q176: BACHAS | R176: 1 | S176: -149500 | T176: 100 | U176: APERTURADO POR EMPRESA
A177: 45961 | B177: Martins, Joaquin | C177: AD-0001 | D177: -1644500 | E177: ENERGIA Nafta | F177: 1100 | G177: 1495 | H177: Lts | I177: ENERGIA | J177: OPEX | K177: VARIABLE | L177: DIRECTO | M177: 0 | N177: CC4 | O177: #NUM! | P177: 1 | Q177: PILETAS | R177: 1 | S177: -1644500 | T177: 1100 | U177: APERTURADO POR EMPRESA
A178: 45961 | B178: Martins, Joaquin | C178: AD-0001 | D178: -448500 | E178: ENERGIA Nafta | F178: 300 | G178: 1495 | H178: Lts | I178: ENERGIA | J178: OPEX | K178: VARIABLE | L178: DIRECTO | M178: 0 | N178: CC3 | O178: #NUM! | P178: 1 | Q178: DISPOSICIÓN FINAL RESIDUOS LIQUIDOS | R178: 1 | S178: -448500 | T178: 300 | U178: APERTURADO POR EMPRESA
A179: 45961 | B179: Ultraonix Srl | C179: AD-0001 | D179: -14998192 | E179: ENERGIA Fuel Oil | F179: 24400 | G179: 614.68 | H179: KG | I179: ENERGIA | J179: OPEX | K179: VARIABLE | L179: DIRECTO | M179: 0 | N179: CC5 | O179: #NUM! | P179: 1 | Q179: REACTORES | R179: 1 | S179: -14998192 | T179: 24400 | U179: APERTURADO POR EMPRESA
A180: 45961 | B180: Ultraonix Srl | C180: AD-0001 | D180: -5224780 | E180: ENERGIA Fuel Oil | F180: 8500 | G180: 614.68 | H180: KG | I180: ENERGIA | J180: OPEX | K180: VARIABLE | L180: DIRECTO | M180: 0 | N180: CC6 | O180: #NUM! | P180: 1 | Q180: BACHAS | R180: 1 | S180: -5224780 | T180: 8500 | U180: APERTURADO POR EMPRESA
A181: 45961 | B181: Total Quimica S.A. | C181: AD-0001 | D181: -7342440.6 | E181: INSUMOS Acido Sulfúrico 70/80 | F181: 19860 | G181: 369.71 | H181: KG | I181: INSUMOS | J181: OPEX | K181: VARIABLE | L181: DIRECTO | M181: 0 | N181: CC6 | O181: #NUM! | P181: 1 | Q181: BACHAS | R181: 1 | S181: -7342440.6 | T181: 19860 | U181: APERTURADO POR EMPRESA
A182: 45961 | B182: Total Quimica S.A. | C182: AD-0001 | D182: -547520 | E182: INSUMOS Acido Clorhidrico | F182: 1180 | G182: 464 | H182: KG | I182: INSUMOS | J182: OPEX | K182: VARIABLE | L182: DIRECTO | M182: 0 | N182: CC6 | O182: #NUM! | P182: 1 | Q182: BACHAS | R182: 1 | S182: -547520 | T182: 1180 | U182: APERTURADO POR EMPRESA
A183: 45961 | B183: Total Quimica S.A. | C183: AD-0001 | D183: -691147.5 | E183: INSUMOS Soda Caustica | F183: 750 | G183: 921.53 | H183: KG | I183: INSUMOS | J183: OPEX | K183: VARIABLE | L183: DIRECTO | M183: 0 | N183: CC5 | O183: #NUM! | P183: 1 | Q183: REACTORES | R183: 1 | S183: -691147.5 | T183: 750 | U183: APERTURADO POR EMPRESA
A184: 45961 | B184: Salinera Jaisal S. A. | C184: AD-0001 | D184: -59774 | E184: INSUMOS Cloruro de Sodio (SAL) | F184: 520 | G184: 114.95 | H184: KG | I184: INSUMOS | J184: OPEX | K184: VARIABLE | L184: DIRECTO | M184: 0 | N184: CC6 | O184: #NUM! | P184: 1 | Q184: BACHAS | R184: 1 | S184: -59774 | T184: 520 | U184: APERTURADO POR EMPRESA
A185: 45961 | B185: Cremer Y Asociados Sociedad Anonima | C185: AD-0001 | D185: -11525588 | E185: INSUMOS Glicerina cruda | F185: 28.75 | G185: 400890 | H185: TN | I185: INSUMOS | J185: OPEX | K185: VARIABLE | L185: DIRECTO | M185: 0 | N185: CC5 | O185: #NUM! | P185: 1 | Q185: REACTORES | R185: 1 | S185: -11525588 | T185: 28.75 | U185: APERTURADO POR EMPRESA
A186: 45961 | B186: Meri-mar SRL | C186: AD-0001 | D186: 0 | E186: LOGISTICA | F186: 97.4 | G186: 19500 | H186: TN | I186: SERVICIOS | J186: OPEX | K186: VARIABLE | L186: DIRECTO | M186: 0 | N186: CC11 | O186: #NUM! | P186: 1 | Q186: EXPORTACION | R186: 1 | S186: 0 | T186: 97.4 | U186: APERTURADO POR EMPRESA
A187: 45961 | B187: Mercomar SA | C187: AD-0001 | D187: 0 | E187: LOGISTICA | F187: 852.25 | G187: 19500 | H187: TN | I187: SERVICIOS | J187: 0 | K187: 0 | L187: 0 | M187: 0 | N187: 0 | O187: #NUM! | P187: 0 | Q187: 0 | R187: 1 | S187: 0 | T187: 852.25 | U187: APERTURADO POR EMPRESA
A188: 45961 | B188: Transportes Padilla Sociedad Anonima | C188: AD-0001 | D188: 0 | E188: LOGISTICA | F188: 876.6 | G188: #NUM! | H188: TN | I188: SERVICIOS | J188: OPEX | K188: VARIABLE | L188: DIRECTO | M188: 0 | N188: CC11 | O188: #NUM! | P188: 1 | Q188: EXPORTACION | R188: 1 | S188: 0 | T188: 876.6 | U188: APERTURADO POR EMPRESA
A189: 45961 | B189: Cronos Soluciones Sustentables Sa | C189: AD-0001 | D189: -11261875 | E189: LOGISTICA | F189: 608.75 | G189: 18500 | H189: TN | I189: LOGISTICA | J189: OPEX | K189: VARIABLE | L189: DIRECTO | M189: 0 | N189: NO | O189: #NUM! | P189: 1 | Q189: ANULADO | R189: 1 | S189: -11261875 | T189: 608.75 | U189: APERTURADO POR EMPRESA
A190: 45961 | B190: Transporte Automotor El Loco Srl | C190: AD-0001 | D190: 0 | E190: LOGISTICA | F190: 97.4 | G190: #NUM! | H190: TN | I190: LOGISTICA | J190: OPEX | K190: VARIABLE | L190: DIRECTO | M190: 0 | N190: NO | O190: #NUM! | P190: 1 | Q190: ANULADO | R190: 1 | S190: 0 | T190: 97.4 | U190: APERTURADO POR EMPRESA
A191: 45961 | B191: Energia Del Sur Srl | C191: AD-0001 | D191: -1461000 | E191: LOGISTICA | F191: 97.4 | G191: 15000 | H191: TN | I191: LOGISTICA | J191: OPEX | K191: VARIABLE | L191: DIRECTO | M191: 0 | N191: NO | O191: #NUM! | P191: 1 | Q191: ANULADO | R191: 1 | S191: -1461000 | T191: 97.4 | U191: APERTURADO POR EMPRESA
A192: 45961 | B192: Duport Sociedad De Responsabilidad Limitada | C192: AD-0001 | D192: 0 | E192: LOGISTICA | F192: 194.8 | G192: #NUM! | H192: TN | I192: LOGISTICA | J192: OPEX | K192: VARIABLE | L192: DIRECTO | M192: 0 | N192: NO | O192: #NUM! | P192: 1 | Q192: ANULADO | R192: 1 | S192: 0 | T192: 194.8 | U192: APERTURADO POR EMPRESA
A193: 45931 | B193: GANANCIAS EXPORTACION | C193: AD_10-2025 | D193: -2067241.2 | E193: IMPUESTOS | F193: 2824.1 | G193: 0.5 | H193: UN | I193: IMPUESTOS | J193: OPEX | K193: VARIABLE | L193: DIRECTO | M193: 0 | N193: CC11 | O193: #NUM! | P193: 1 | Q193: EXPORTACION | R193: 1 | S193: -2067241.2 | T193: 2824.1 | U193: APERTURADO POR EMPRESA
A194: 45960 | B194: GASTOS BANCARIOS | C194: OCOM/2025/10 | D194: -6924925.3 | E194: IMPUESTOS | F194: 1 | G194: 6924925.3 | H194: UN | I194: IMPUESTOS | J194: OPEX | K194: VARIABLE | L194: INDIRECTO | M194: 0 | N194: CC1 | O194: #NUM! | P194: CCO NO DEFINIDO | Q194: CCO NO DEFINIDO | R194: 1 | S194: -6924925.3 | T194: 1 | U194: APERTURADO POR EMPRESA
A195: 45960 | B195: IB | C195: OCOM/2025/10 | D195: -32811.49 | E195: IMPUESTOS | F195: 1 | G195: 32811.49 | H195: UN | I195: IMPUESTOS | J195: OPEX | K195: VARIABLE | L195: INDIRECTO | M195: 0 | N195: CC1 | O195: #NUM! | P195: 10 | Q195: BACHAS, CEREAL & POLVILLO, COMPOST & FERTILIZANTES, DISPOSICIÓN FINAL RESIDUOS LIQUIDOS, DISPOSICIÓN FINAL RESIDUOS SOLIDOS, EXPORTACION, NFU, PILETAS, REACTORES, TIERRAS FILTRANTES | R195: 1 | S195: -32811.49 | T195: 1 | U195: APERTURADO POR EMPRESA
A196: 45960 | B196: DREI DISPOSICIÓN FINAL RESIDUOS LIQUIDOS | C196: OCOM/2025/10 | D196: -656141 | E196: IMPUESTOS | F196: 1 | G196: 656141 | H196: UN | I196: IMPUESTOS | J196: OPEX | K196: VARIABLE | L196: INDIRECTO | M196: 0 | N196: CC3 | O196: #NUM! | P196: 1 | Q196: DISPOSICIÓN FINAL RESIDUOS LIQUIDOS | R196: 1 | S196: -656141 | T196: 1 | U196: APERTURADO POR EMPRESA
A197: 45960 | B197: DREI COMPOST & FERTILIZANTES | C197: OCOM/2025/10 | D197: -485805 | E197: IMPUESTOS | F197: 1 | G197: 485805 | H197: UN | I197: IMPUESTOS | J197: OPEX | K197: VARIABLE | L197: INDIRECTO | M197: 0 | N197: CC8 | O197: #NUM! | P197: 1 | Q197: COMPOST & FERTILIZANTES | R197: 1 | S197: -485805 | T197: 1 | U197: APERTURADO POR EMPRESA
A198: 45960 | B198: DREI PILETAS | C198: OCOM/2025/10 | D198: -374523 | E198: IMPUESTOS | F198: 1 | G198: 374523 | H198: UN | I198: IMPUESTOS | J198: OPEX | K198: VARIABLE | L198: INDIRECTO | M198: 0 | N198: CC4 | O198: #NUM! | P198: 1 | Q198: PILETAS | R198: 1 | S198: -374523 | T198: 1 | U198: APERTURADO POR EMPRESA
A199: 45960 | B199: DREI NFU | C199: OCOM/2025/10 | D199: -386033 | E199: IMPUESTOS | F199: 1 | G199: 386033 | H199: UN | I199: IMPUESTOS | J199: OPEX | K199: VARIABLE | L199: INDIRECTO | M199: 0 | N199: CC7 | O199: #NUM! | P199: 2 | Q199: NFU | R199: 1 | S199: -386033 | T199: 1 | U199: APERTURADO POR EMPRESA
A200: 45931 | B200: WORMS-RRHH | C200: MAIDANA, JOSE RAMON | D200: -2078949.5 | E200: INTENDENCIA | F200: 1 | G200: 2078949.5 | H200: #RRHH | I200: PERSONAL | J200: Opex | K200: Fijo | L200: Indirecto | M200: 0 | N200: CC27 | O200: #NUM! | P200: 10 | Q200: BACHAS, CEREAL Y POLVILLO, COMPOST Y FERTILIZANTES, DISPOSICION FINAL DE R. LIQUIDOS, DISPOSICION FINAL DE R. SOLIDOS, EXPORTACION, NFU, PILETAS, REACTORES, TIERRAS FILTRANTES | R200: 1 | S200: -2078949.5 | T200: 1 | U200: APERTURADO POR EMPRESA
A201: 45931 | B201: WORMS-RRHH | C201: PEREZ, MATIAS ROMAN | D201: -5104642.3 | E201: INTENDENCIA | F201: 1 | G201: 5104642.3 | H201: #RRHH | I201: PERSONAL | J201: Opex | K201: Fijo | L201: Indirecto | M201: 0 | N201: CC27 | O201: #NUM! | P201: 10 | Q201: BACHAS, CEREAL Y POLVILLO, COMPOST Y FERTILIZANTES, DISPOSICION FINAL DE R. LIQUIDOS, DISPOSICION FINAL DE R. SOLIDOS, EXPORTACION, NFU, PILETAS, REACTORES, TIERRAS FILTRANTES | R201: 1 | S201: -5104642.3 | T201: 1 | U201: APERTURADO POR EMPRESA
A202: 45931 | B202: WORMS-RRHH | C202: PANZANELLA, EDUARDO JAVIER | D202: -2117008.3 | E202: PORTERIA | F202: 1 | G202: 2117008.3 | H202: #RRHH | I202: PERSONAL | J202: Opex | K202: Fijo | L202: Indirecto | M202: 0 | N202: CC22 | O202: #NUM! | P202: 7 | Q202: BACHAS, COMPOST Y FERTILIZANTES, DISPOSICION FINAL DE R. LIQUIDOS, DISPOSICION FINAL DE R. SOLIDOS, EXPORTACION, NFU, REACTORES | R202: 1 | S202: -2117008.3 | T202: 1 | U202: APERTURADO POR EMPRESA
A203: 45931 | B203: WORMS-RRHH | C203: ENRIQUEZ, MAXIMO GUSTAVO | D203: -2067002 | E203: DISPOSICION FINAL DE R. LIQUIDOS | F203: 1 | G203: 2067002 | H203: #RRHH | I203: PERSONAL | J203: Opex | K203: Variable | L203: Directo | M203: 0 | N203: CC25 | O203: #NUM! | P203: 2 | Q203: DISPOSICION FINAL DE R. LIQUIDOS, EXPORTACION | R203: 1 | S203: -2067002 | T203: 1 | U203: APERTURADO POR EMPRESA
A204: 45931 | B204: WORMS-RRHH | C204: PORCU, MIGUEL ANGEL | D204: -1085682.2 | E204: PILETAS | F204: 1 | G204: 1085682.2 | H204: #RRHH | I204: PERSONAL | J204: Opex | K204: Variable | L204: Directo | M204: 0 | N204: CC21 | O204: #NUM! | P204: 2 | Q204: BACHAS, PILETAS | R204: 1 | S204: -1085682.2 | T204: 1 | U204: APERTURADO POR EMPRESA
A205: 45931 | B205: WORMS-RRHH | C205: PETERS CORZO, JOSE LUIS | D205: -2513045.7 | E205: LABORATORIO | F205: 1 | G205: 2513045.7 | H205: #RRHH | I205: PERSONAL | J205: Opex | K205: Fijo | L205: Indirecto | M205: 0 | N205: CC17 | O205: #NUM! | P205: 6 | Q205: BACHAS, DISPOSICION FINAL DE R. LIQUIDOS, EXPORTACION, NFU, PILETAS, REACTORES | R205: 1 | S205: -2513045.7 | T205: 1 | U205: APERTURADO POR EMPRESA
A206: 45931 | B206: WORMS-RRHH | C206: ALTAMIRANO, GUSTAVO | D206: -2156572.8 | E206: NFU | F206: 1 | G206: 2156572.8 | H206: #RRHH | I206: PERSONAL | J206: Opex | K206: Variable | L206: Directo | M206: 0 | N206: CC20 | O206: #NUM! | P206: 2 | Q206: DISPOSICION FINAL DE R. SOLIDOS, NFU | R206: 1 | S206: -2156572.8 | T206: 1 | U206: APERTURADO POR EMPRESA
... A302: 45931 | B302: WORMS-RRHH | C302: ADROVER, JUAN HORACIO | D302: -1876296.3 | E302: TALLER MECANICO | F302: 15 | G302: 1876296.3 | H302: #RRHH | I302: PERSONAL | J302: Opex | K302: Fijo | L302: Indirecto | M302: 0 | N302: CC23 | O302: #NUM! | P302: 10 | Q302: BACHAS, CEREAL Y POLVILLO, COMPOST Y FERTILIZANTES, DISPOSICION FINAL DE R. LIQUIDOS, DISPOSICION FINAL DE R. SOLIDOS, EXPORTACION, NFU, PILETAS, REACTORES, TIERRAS FILTRANTES | R302: 1 | S302: -1876296.3 | T302: 15 | U302: APERTURADO POR EMPRESA

Sheet cco_bbdd_asignado.p4 
A1: {=_xlfn._xlws.PY(1,0,bbdd2[#All])} -> 0 | B1: 1 | C1: 2 | D1: 3 | E1: 4 | F1: 5 | G1: 6 | H1: 7 | I1: 8 | J1: 9 | K1: 10 | L1: 11 | M1: 12 | N1: 13 | O1: 14 | P1: 15 | Q1: 16 | R1: 17 | S1: 18 | T1: 19 | U1: 20 | V1: SECTOR APERTURADO
A2: Fecha de Factura/Recibo | B2: Nombre de la empresa a mostrar en la factura | C2: Número | D2: Total con signo | E2: Líneas de factura/Etiqueta | F2: Líneas de factura/Cantidad | G2: Líneas de factura/Precio unitario | H2: Líneas de factura/Unidad de medida | I2: Líneas de factura/Producto | J2: Concepto | K2: Tipo de Gasto 1 | L2: Tipo de Gasto 2 | M2: CCO EMPRESA | N2: CCO - SECTOR | O2: SECTOR_ODOO | P2: # SECTORES | Q2: LISTA_SECTORES | R2: Column1 | S2: Column2 | T2: Column3 | U2: Column4 | V2: LISTA_SECTORES
A3: 45958 | B3: H.S.E. Ingenieria S R L | C3: FA-A 00003-00027849 | D3: -3315400 | E3: OC 0001-00001756: SERVICIOS Monitoreo | F3: 1 | G3: 2740000 | H3: UN | I3: SERVICIOS | J3: OPEX | K3: VARIABLE | L3: INDIRECTO | M3: 0 | N3: CC1 | O3: #NUM! | P3: 10 | Q3: BACHAS, CEREAL & POLVILLO, COMPOST & FERTILIZANTES, DISPOSICIÓN FINAL RESIDUOS LIQUIDOS, DISPOSICIÓN FINAL RESIDUOS SOLIDOS, EXPORTACION, NFU, PILETAS, REACTORES, TIERRAS FILTRANTES | R3: 1 | S3: -3315400 | T3: 1 | U3: APERTURADO POR EMPRESA | V3: BACHAS
A4: 45958 | B4: H.S.E. Ingenieria S R L | C4: FA-A 00003-00027849 | D4: -3315400 | E4: OC 0001-00001756: SERVICIOS Monitoreo | F4: 1 | G4: 2740000 | H4: UN | I4: SERVICIOS | J4: OPEX | K4: VARIABLE | L4: INDIRECTO | M4: 0 | N4: CC1 | O4: #NUM! | P4: 10 | Q4: BACHAS, CEREAL & POLVILLO, COMPOST & FERTILIZANTES, DISPOSICIÓN FINAL RESIDUOS LIQUIDOS, DISPOSICIÓN FINAL RESIDUOS SOLIDOS, EXPORTACION, NFU, PILETAS, REACTORES, TIERRAS FILTRANTES | R4: 1 | S4: -3315400 | T4: 1 | U4: APERTURADO POR EMPRESA | V4: CEREAL & POLVILLO
A5: 45958 | B5: H.S.E. Ingenieria S R L | C5: FA-A 00003-00027849 | D5: -3315400 | E5: OC 0001-00001756: SERVICIOS Monitoreo | F5: 1 | G5: 2740000 | H5: UN | I5: SERVICIOS | J5: OPEX | K5: VARIABLE | L5: INDIRECTO | M5: 0 | N5: CC1 | O5: #NUM! | P5: 10 | Q5: BACHAS, CEREAL & POLVILLO, COMPOST & FERTILIZANTES, DISPOSICIÓN FINAL RESIDUOS LIQUIDOS, DISPOSICIÓN FINAL RESIDUOS SOLIDOS, EXPORTACION, NFU, PILETAS, REACTORES, TIERRAS FILTRANTES | R5: 1 | S5: -3315400 | T5: 1 | U5: APERTURADO POR EMPRESA | V5: COMPOST & FERTILIZANTES
A6: 45958 | B6: H.S.E. Ingenieria S R L | C6: FA-A 00003-00027849 | D6: -3315400 | E6: OC 0001-00001756: SERVICIOS Monitoreo | F6: 1 | G6: 2740000 | H6: UN | I6: SERVICIOS | J6: OPEX | K6: VARIABLE | L6: INDIRECTO | M6: 0 | N6: CC1 | O6: #NUM! | P6: 10 | Q6: BACHAS, CEREAL & POLVILLO, COMPOST & FERTILIZANTES, DISPOSICIÓN FINAL RESIDUOS LIQUIDOS, DISPOSICIÓN FINAL RESIDUOS SOLIDOS, EXPORTACION, NFU, PILETAS, REACTORES, TIERRAS FILTRANTES | R6: 1 | S6: -3315400 | T6: 1 | U6: APERTURADO POR EMPRESA | V6: DISPOSICIÓN FINAL RESIDUOS LIQUIDOS
A7: 45958 | B7: H.S.E. Ingenieria S R L | C7: FA-A 00003-00027849 | D7: -3315400 | E7: OC 0001-00001756: SERVICIOS Monitoreo | F7: 1 | G7: 2740000 | H7: UN | I7: SERVICIOS | J7: OPEX | K7: VARIABLE | L7: INDIRECTO | M7: 0 | N7: CC1 | O7: #NUM! | P7: 10 | Q7: BACHAS, CEREAL & POLVILLO, COMPOST & FERTILIZANTES, DISPOSICIÓN FINAL RESIDUOS LIQUIDOS, DISPOSICIÓN FINAL RESIDUOS SOLIDOS, EXPORTACION, NFU, PILETAS, REACTORES, TIERRAS FILTRANTES | R7: 1 | S7: -3315400 | T7: 1 | U7: APERTURADO POR EMPRESA | V7: DISPOSICIÓN FINAL RESIDUOS SOLIDOS
A8: 45958 | B8: H.S.E. Ingenieria S R L | C8: FA-A 00003-00027849 | D8: -3315400 | E8: OC 0001-00001756: SERVICIOS Monitoreo | F8: 1 | G8: 2740000 | H8: UN | I8: SERVICIOS | J8: OPEX | K8: VARIABLE | L8: INDIRECTO | M8: 0 | N8: CC1 | O8: #NUM! | P8: 10 | Q8: BACHAS, CEREAL & POLVILLO, COMPOST & FERTILIZANTES, DISPOSICIÓN FINAL RESIDUOS LIQUIDOS, DISPOSICIÓN FINAL RESIDUOS SOLIDOS, EXPORTACION, NFU, PILETAS, REACTORES, TIERRAS FILTRANTES | R8: 1 | S8: -3315400 | T8: 1 | U8: APERTURADO POR EMPRESA | V8: EXPORTACION
A9: 45958 | B9: H.S.E. Ingenieria S R L | C9: FA-A 00003-00027849 | D9: -3315400 | E9: OC 0001-00001756: SERVICIOS Monitoreo | F9: 1 | G9: 2740000 | H9: UN | I9: SERVICIOS | J9: OPEX | K9: VARIABLE | L9: INDIRECTO | M9: 0 | N9: CC1 | O9: #NUM! | P9: 10 | Q9: BACHAS, CEREAL & POLVILLO, COMPOST & FERTILIZANTES, DISPOSICIÓN FINAL RESIDUOS LIQUIDOS, DISPOSICIÓN FINAL RESIDUOS SOLIDOS, EXPORTACION, NFU, PILETAS, REACTORES, TIERRAS FILTRANTES | R9: 1 | S9: -3315400 | T9: 1 | U9: APERTURADO POR EMPRESA | V9: NFU
A10: 45958 | B10: H.S.E. Ingenieria S R L | C10: FA-A 00003-00027849 | D10: -3315400 | E10: OC 0001-00001756: SERVICIOS Monitoreo | F10: 1 | G10: 2740000 | H10: UN | I10: SERVICIOS | J10: OPEX | K10: VARIABLE | L10: INDIRECTO | M10: 0 | N10: CC1 | O10: #NUM! | P10: 10 | Q10: BACHAS, CEREAL & POLVILLO, COMPOST & FERTILIZANTES, DISPOSICIÓN FINAL RESIDUOS LIQUIDOS, DISPOSICIÓN FINAL RESIDUOS SOLIDOS, EXPORTACION, NFU, PILETAS, REACTORES, TIERRAS FILTRANTES | R10: 1 | S10: -3315400 | T10: 1 | U10: APERTURADO POR EMPRESA | V10: PILETAS
A11: 45958 | B11: H.S.E. Ingenieria S R L | C11: FA-A 00003-00027849 | D11: -3315400 | E11: OC 0001-00001756: SERVICIOS Monitoreo | F11: 1 | G11: 2740000 | H11: UN | I11: SERVICIOS | J11: OPEX | K11: VARIABLE | L11: INDIRECTO | M11: 0 | N11: CC1 | O11: #NUM! | P11: 10 | Q11: BACHAS, CEREAL & POLVILLO, COMPOST & FERTILIZANTES, DISPOSICIÓN FINAL RESIDUOS LIQUIDOS, DISPOSICIÓN FINAL RESIDUOS SOLIDOS, EXPORTACION, NFU, PILETAS, REACTORES, TIERRAS FILTRANTES | R11: 1 | S11: -3315400 | T11: 1 | U11: APERTURADO POR EMPRESA | V11: REACTORES
A12: 45958 | B12: H.S.E. Ingenieria S R L | C12: FA-A 00003-00027849 | D12: -3315400 | E12: OC 0001-00001756: SERVICIOS Monitoreo | F12: 1 | G12: 2740000 | H12: UN | I12: SERVICIOS | J12: OPEX | K12: VARIABLE | L12: INDIRECTO | M12: 0 | N12: CC1 | O12: #NUM! | P12: 10 | Q12: BACHAS, CEREAL & POLVILLO, COMPOST & FERTILIZANTES, DISPOSICIÓN FINAL RESIDUOS LIQUIDOS, DISPOSICIÓN FINAL RESIDUOS SOLIDOS, EXPORTACION, NFU, PILETAS, REACTORES, TIERRAS FILTRANTES | R12: 1 | S12: -3315400 | T12: 1 | U12: APERTURADO POR EMPRESA | V12: TIERRAS FILTRANTES
A13: 45933 | B13: Alvarez, Alejandro Dario | C13: FA-C 00002-00000250 | D13: -509644 | E13: OC 0001-00001364: HIGIENE Y SEGURIDAD Servicio de asesoramiento para la gestión ambiental en el cumplimiento de la normativa vigente para la provincia de Santa Fe. Servicio de higiene y seguridad de trabajo con cumplimiento de actividades s/Resol. SRT 905/15- MES 09/2025 | F13: 1 | G13: 509644 | H13: UN | I13: HIGIENE Y SEGURIDAD | J13: OPEX | K13: FIJO | L13: DIRECTO | M13: 0 | N13: CC1 | O13: #NUM! | P13: 10 | Q13: BACHAS, CEREAL & POLVILLO, COMPOST & FERTILIZANTES, DISPOSICIÓN FINAL RESIDUOS LIQUIDOS, DISPOSICIÓN FINAL RESIDUOS SOLIDOS, EXPORTACION, NFU, PILETAS, REACTORES, TIERRAS FILTRANTES | R13: 1 | S13: -509644 | T13: 1 | U13: APERTURADO POR EMPRESA | V13: BACHAS
A14: 45933 | B14: Alvarez, Alejandro Dario | C14: FA-C 00002-00000250 | D14: -509644 | E14: OC 0001-00001364: HIGIENE Y SEGURIDAD Servicio de asesoramiento para la gestión ambiental en el cumplimiento de la normativa vigente para la provincia de Santa Fe. Servicio de higiene y seguridad de trabajo con cumplimiento de actividades s/Resol. SRT 905/15- MES 09/2025 | F14: 1 | G14: 509644 | H14: UN | I14: HIGIENE Y SEGURIDAD | J14: OPEX | K14: FIJO | L14: DIRECTO | M14: 0 | N14: CC1 | O14: #NUM! | P14: 10 | Q14: BACHAS, CEREAL & POLVILLO, COMPOST & FERTILIZANTES, DISPOSICIÓN FINAL RESIDUOS LIQUIDOS, DISPOSICIÓN FINAL RESIDUOS SOLIDOS, EXPORTACION, NFU, PILETAS, REACTORES, TIERRAS FILTRANTES | R14: 1 | S14: -509644 | T14: 1 | U14: APERTURADO POR EMPRESA | V14: CEREAL & POLVILLO
... A141: 45932 | B141: Acosta, Roberto Maximiliano | C141: FA-C 00001-00000616 | D141: -4632990 | E141: OC 0001-00001709: SERVICIOS de limpieza +ipc julio y agosto 3,8% | F141: 1 | G141: 4632990 | H141: UN | I141: SERVICIOS | J141: OPEX | K141: VARIABLE | L141: INDIRECTO | M141: 0 | N141: CC1 | O141: #NUM! | P141: 10 | Q141: BACHAS, CEREAL & POLVILLO, COMPOST & FERTILIZANTES, DISPOSICIÓN FINAL RESIDUOS LIQUIDOS, DISPOSICIÓN FINAL RESIDUOS SOLIDOS, EXPORTACION, NFU, PILETAS, REACTORES, TIERRAS FILTRANTES | R141: 1 | S141: -4632990 | T141: 1 | U141: APERTURADO POR EMPRESA | V141: TIERRAS FILTRANTES
A142: 45931 | B142: Adhoc S.A. | C142: FA-A 00003-00019779 | D142: -2004596.6 | E142: OC 0001-00001367: SERVICIOS Sistema contable | F142: 1 | G142: 1656691.4 | H142: UN | I142: SERVICIOS | J142: OPEX | K142: FIJO | L142: INDIRECTO | M142: CC13 | N142: CC1 | O142: #NUM! | P142: 10 | Q142: BACHAS, CEREAL & POLVILLO, COMPOST & FERTILIZANTES, DISPOSICIÓN FINAL RESIDUOS LIQUIDOS, DISPOSICIÓN FINAL RESIDUOS SOLIDOS, EXPORTACION, NFU, PILETAS, REACTORES, TIERRAS FILTRANTES | R142: 0.7 | S142: -1403217.6 | T142: 0.7 | U142: APERTURADO POR EMPRESA | V142: BACHAS
A143: 45931 | B143: Adhoc S.A. | C143: FA-A 00003-00019779 | D143: -2004596.6 | E143: OC 0001-00001367: SERVICIOS Sistema contable | F143: 1 | G143: 1656691.4 | H143: UN | I143: SERVICIOS | J143: OPEX | K143: FIJO | L143: INDIRECTO | M143: CC13 | N143: CC1 | O143: #NUM! | P143: 10 | Q143: BACHAS, CEREAL & POLVILLO, COMPOST & FERTILIZANTES, DISPOSICIÓN FINAL RESIDUOS LIQUIDOS, DISPOSICIÓN FINAL RESIDUOS SOLIDOS, EXPORTACION, NFU, PILETAS, REACTORES, TIERRAS FILTRANTES | R143: 0.7 | S143: -1403217.6 | T143: 0.7 | U143: APERTURADO POR EMPRESA | V143: CEREAL & POLVILLO
A144: 45931 | B144: Adhoc S.A. | C144: FA-A 00003-00019779 | D144: -2004596.6 | E144: OC 0001-00001367: SERVICIOS Sistema contable | F144: 1 | G144: 1656691.4 | H144: UN | I144: SERVICIOS | J144: OPEX | K144: FIJO | L144: INDIRECTO | M144: CC13 | N144: CC1 | O144: #NUM! | P144: 10 | Q144: BACHAS, CEREAL & POLVILLO, COMPOST & FERTILIZANTES, DISPOSICIÓN FINAL RESIDUOS LIQUIDOS, DISPOSICIÓN FINAL RESIDUOS SOLIDOS, EXPORTACION, NFU, PILETAS, REACTORES, TIERRAS FILTRANTES | R144: 0.7 | S144: -1403217.6 | T144: 0.7 | U144: APERTURADO POR EMPRESA | V144: COMPOST & FERTILIZANTES
A145: 45931 | B145: Adhoc S.A. | C145: FA-A 00003-00019779 | D145: -2004596.6 | E145: OC 0001-00001367: SERVICIOS Sistema contable | F145: 1 | G145: 1656691.4 | H145: UN | I145: SERVICIOS | J145: OPEX | K145: FIJO | L145: INDIRECTO | M145: CC13 | N145: CC1 | O145: #NUM! | P145: 10 | Q145: BACHAS, CEREAL & POLVILLO, COMPOST & FERTILIZANTES, DISPOSICIÓN FINAL RESIDUOS LIQUIDOS, DISPOSICIÓN FINAL RESIDUOS SOLIDOS, EXPORTACION, NFU, PILETAS, REACTORES, TIERRAS FILTRANTES | R145: 0.7 | S145: -1403217.6 | T145: 0.7 | U145: APERTURADO POR EMPRESA | V145: DISPOSICIÓN FINAL RESIDUOS LIQUIDOS
A146: 45931 | B146: Adhoc S.A. | C146: FA-A 00003-00019779 | D146: -2004596.6 | E146: OC 0001-00001367: SERVICIOS Sistema contable | F146: 1 | G146: 1656691.4 | H146: UN | I146: SERVICIOS | J146: OPEX | K146: FIJO | L146: INDIRECTO | M146: CC13 | N146: CC1 | O146: #NUM! | P146: 10 | Q146: BACHAS, CEREAL & POLVILLO, COMPOST & FERTILIZANTES, DISPOSICIÓN FINAL RESIDUOS LIQUIDOS, DISPOSICIÓN FINAL RESIDUOS SOLIDOS, EXPORTACION, NFU, PILETAS, REACTORES, TIERRAS FILTRANTES | R146: 0.7 | S146: -1403217.6 | T146: 0.7 | U146: APERTURADO POR EMPRESA | V146: DISPOSICIÓN FINAL RESIDUOS SOLIDOS
A147: 45931 | B147: Adhoc S.A. | C147: FA-A 00003-00019779 | D147: -2004596.6 | E147: OC 0001-00001367: SERVICIOS Sistema contable | F147: 1 | G147: 1656691.4 | H147: UN | I147: SERVICIOS | J147: OPEX | K147: FIJO | L147: INDIRECTO | M147: CC13 | N147: CC1 | O147: #NUM! | P147: 10 | Q147: BACHAS, CEREAL & POLVILLO, COMPOST & FERTILIZANTES, DISPOSICIÓN FINAL RESIDUOS LIQUIDOS, DISPOSICIÓN FINAL RESIDUOS SOLIDOS, EXPORTACION, NFU, PILETAS, REACTORES, TIERRAS FILTRANTES | R147: 0.7 | S147: -1403217.6 | T147: 0.7 | U147: APERTURADO POR EMPRESA | V147: EXPORTACION
A148: 45931 | B148: Adhoc S.A. | C148: FA-A 00003-00019779 | D148: -2004596.6 | E148: OC 0001-00001367: SERVICIOS Sistema contable | F148: 1 | G148: 1656691.4 | H148: UN | I148: SERVICIOS | J148: OPEX | K148: FIJO | L148: INDIRECTO | M148: CC13 | N148: CC1 | O148: #NUM! | P148: 10 | Q148: BACHAS, CEREAL & POLVILLO, COMPOST & FERTILIZANTES, DISPOSICIÓN FINAL RESIDUOS LIQUIDOS, DISPOSICIÓN FINAL RESIDUOS SOLIDOS, EXPORTACION, NFU, PILETAS, REACTORES, TIERRAS FILTRANTES | R148: 0.7 | S148: -1403217.6 | T148: 0.7 | U148: APERTURADO POR EMPRESA | V148: NFU
A149: 45931 | B149: Adhoc S.A. | C149: FA-A 00003-00019779 | D149: -2004596.6 | E149: OC 0001-00001367: SERVICIOS Sistema contable | F149: 1 | G149: 1656691.4 | H149: UN | I149: SERVICIOS | J149: OPEX | K149: FIJO | L149: INDIRECTO | M149: CC13 | N149: CC1 | O149: #NUM! | P149: 10 | Q149: BACHAS, CEREAL & POLVILLO, COMPOST & FERTILIZANTES, DISPOSICIÓN FINAL RESIDUOS LIQUIDOS, DISPOSICIÓN FINAL RESIDUOS SOLIDOS, EXPORTACION, NFU, PILETAS, REACTORES, TIERRAS FILTRANTES | R149: 0.7 | S149: -1403217.6 | T149: 0.7 | U149: APERTURADO POR EMPRESA | V149: PILETAS
A150: 45931 | B150: Adhoc S.A. | C150: FA-A 00003-00019779 | D150: -2004596.6 | E150: OC 0001-00001367: SERVICIOS Sistema contable | F150: 1 | G150: 1656691.4 | H150: UN | I150: SERVICIOS | J150: OPEX | K150: FIJO | L150: INDIRECTO | M150: CC13 | N150: CC1 | O150: #NUM! | P150: 10 | Q150: BACHAS, CEREAL & POLVILLO, COMPOST & FERTILIZANTES, DISPOSICIÓN FINAL RESIDUOS LIQUIDOS, DISPOSICIÓN FINAL RESIDUOS SOLIDOS, EXPORTACION, NFU, PILETAS, REACTORES, TIERRAS FILTRANTES | R150: 0.7 | S150: -1403217.6 | T150: 0.7 | U150: APERTURADO POR EMPRESA | V150: REACTORES
A151: 45931 | B151: Adhoc S.A. | C151: FA-A 00003-00019779 | D151: -2004596.6 | E151: OC 0001-00001367: SERVICIOS Sistema contable | F151: 1 | G151: 1656691.4 | H151: UN | I151: SERVICIOS | J151: OPEX | K151: FIJO | L151: INDIRECTO | M151: CC13 | N151: CC1 | O151: #NUM! | P151: 10 | Q151: BACHAS, CEREAL & POLVILLO, COMPOST & FERTILIZANTES, DISPOSICIÓN FINAL RESIDUOS LIQUIDOS, DISPOSICIÓN FINAL RESIDUOS SOLIDOS, EXPORTACION, NFU, PILETAS, REACTORES, TIERRAS FILTRANTES | R151: 0.7 | S151: -1403217.6 | T151: 0.7 | U151: APERTURADO POR EMPRESA | V151: TIERRAS FILTRANTES
A152: 45950 | B152: American Express Argentina S. A. | C152: OCOM/2025/0472 | D152: -344000.85 | E152: OC 0001-00001936: PERSONAL | F152: 1 | G152: 344000.85 | H152: UN | I152: PERSONAL | J152: OPEX | K152: VARIABLE | L152: INDIRECTO | M152: 0 | N152: CC1 | O152: #NUM! | P152: 10 | Q152: BACHAS, CEREAL & POLVILLO, COMPOST & FERTILIZANTES, DISPOSICIÓN FINAL RESIDUOS LIQUIDOS, DISPOSICIÓN FINAL RESIDUOS SOLIDOS, EXPORTACION, NFU, PILETAS, REACTORES, TIERRAS FILTRANTES | R152: 1 | S152: -344000.85 | T152: 1 | U152: APERTURADO POR EMPRESA | V152: BACHAS
A153: 45950 | B153: American Express Argentina S. A. | C153: OCOM/2025/0472 | D153: -344000.85 | E153: OC 0001-00001936: PERSONAL | F153: 1 | G153: 344000.85 | H153: UN | I153: PERSONAL | J153: OPEX | K153: VARIABLE | L153: INDIRECTO | M153: 0 | N153: CC1 | O153: #NUM! | P153: 10 | Q153: BACHAS, CEREAL & POLVILLO, COMPOST & FERTILIZANTES, DISPOSICIÓN FINAL RESIDUOS LIQUIDOS, DISPOSICIÓN FINAL RESIDUOS SOLIDOS, EXPORTACION, NFU, PILETAS, REACTORES, TIERRAS FILTRANTES | R153: 1 | S153: -344000.85 | T153: 1 | U153: APERTURADO POR EMPRESA | V153: CEREAL & POLVILLO
A154: 45950 | B154: American Express Argentina S. A. | C154: OCOM/2025/0472 | D154: -344000.85 | E154: OC 0001-00001936: PERSONAL | F154: 1 | G154: 344000.85 | H154: UN | I154: PERSONAL | J154: OPEX | K154: VARIABLE | L154: INDIRECTO | M154: 0 | N154: CC1 | O154: #NUM! | P154: 10 | Q154: BACHAS, CEREAL & POLVILLO, COMPOST & FERTILIZANTES, DISPOSICIÓN FINAL RESIDUOS LIQUIDOS, DISPOSICIÓN FINAL RESIDUOS SOLIDOS, EXPORTACION, NFU, PILETAS, REACTORES, TIERRAS FILTRANTES | R154: 1 | S154: -344000.85 | T154: 1 | U154: APERTURADO POR EMPRESA | V154: COMPOST & FERTILIZANTES
A155: 45950 | B155: American Express Argentina S. A. | C155: OCOM/2025/0472 | D155: -344000.85 | E155: OC 0001-00001936: PERSONAL | F155: 1 | G155: 344000.85 | H155: UN | I155: PERSONAL | J155: OPEX | K155: VARIABLE | L155: INDIRECTO | M155: 0 | N155: CC1 | O155: #NUM! | P155: 10 | Q155: BACHAS, CEREAL & POLVILLO, COMPOST & FERTILIZANTES, DISPOSICIÓN FINAL RESIDUOS LIQUIDOS, DISPOSICIÓN FINAL RESIDUOS SOLIDOS, EXPORTACION, NFU, PILETAS, REACTORES, TIERRAS FILTRANTES | R155: 1 | S155: -344000.85 | T155: 1 | U155: APERTURADO POR EMPRESA | V155: DISPOSICIÓN FINAL RESIDUOS LIQUIDOS
A156: 45950 | B156: American Express Argentina S. A. | C156: OCOM/2025/0472 | D156: -344000.85 | E156: OC 0001-00001936: PERSONAL | F156: 1 | G156: 344000.85 | H156: UN | I156: PERSONAL | J156: OPEX | K156: VARIABLE | L156: INDIRECTO | M156: 0 | N156: CC1 | O156: #NUM! | P156: 10 | Q156: BACHAS, CEREAL & POLVILLO, COMPOST & FERTILIZANTES, DISPOSICIÓN FINAL RESIDUOS LIQUIDOS, DISPOSICIÓN FINAL RESIDUOS SOLIDOS, EXPORTACION, NFU, PILETAS, REACTORES, TIERRAS FILTRANTES | R156: 1 | S156: -344000.85 | T156: 1 | U156: APERTURADO POR EMPRESA | V156: DISPOSICIÓN FINAL RESIDUOS SOLIDOS
A157: 45950 | B157: American Express Argentina S. A. | C157: OCOM/2025/0472 | D157: -344000.85 | E157: OC 0001-00001936: PERSONAL | F157: 1 | G157: 344000.85 | H157: UN | I157: PERSONAL | J157: OPEX | K157: VARIABLE | L157: INDIRECTO | M157: 0 | N157: CC1 | O157: #NUM! | P157: 10 | Q157: BACHAS, CEREAL & POLVILLO, COMPOST & FERTILIZANTES, DISPOSICIÓN FINAL RESIDUOS LIQUIDOS, DISPOSICIÓN FINAL RESIDUOS SOLIDOS, EXPORTACION, NFU, PILETAS, REACTORES, TIERRAS FILTRANTES | R157: 1 | S157: -344000.85 | T157: 1 | U157: APERTURADO POR EMPRESA | V157: EXPORTACION
A158: 45950 | B158: American Express Argentina S. A. | C158: OCOM/2025/0472 | D158: -344000.85 | E158: OC 0001-00001936: PERSONAL | F158: 1 | G158: 344000.85 | H158: UN | I158: PERSONAL | J158: OPEX | K158: VARIABLE | L158: INDIRECTO | M158: 0 | N158: CC1 | O158: #NUM! | P158: 10 | Q158: BACHAS, CEREAL & POLVILLO, COMPOST & FERTILIZANTES, DISPOSICIÓN FINAL RESIDUOS LIQUIDOS, DISPOSICIÓN FINAL RESIDUOS SOLIDOS, EXPORTACION, NFU, PILETAS, REACTORES, TIERRAS FILTRANTES | R158: 1 | S158: -344000.85 | T158: 1 | U158: APERTURADO POR EMPRESA | V158: NFU
A159: 45950 | B159: American Express Argentina S. A. | C159: OCOM/2025/0472 | D159: -344000.85 | E159: OC 0001-00001936: PERSONAL | F159: 1 | G159: 344000.85 | H159: UN | I159: PERSONAL | J159: OPEX | K159: VARIABLE | L159: INDIRECTO | M159: 0 | N159: CC1 | O159: #NUM! | P159: 10 | Q159: BACHAS, CEREAL & POLVILLO, COMPOST & FERTILIZANTES, DISPOSICIÓN FINAL RESIDUOS LIQUIDOS, DISPOSICIÓN FINAL RESIDUOS SOLIDOS, EXPORTACION, NFU, PILETAS, REACTORES, TIERRAS FILTRANTES | R159: 1 | S159: -344000.85 | T159: 1 | U159: APERTURADO POR EMPRESA | V159: PILETAS
A160: 45950 | B160: American Express Argentina S. A. | C160: OCOM/2025/0472 | D160: -344000.85 | E160: OC 0001-00001936: PERSONAL | F160: 1 | G160: 344000.85 | H160: UN | I160: PERSONAL | J160: OPEX | K160: VARIABLE | L160: INDIRECTO | M160: 0 | N160: CC1 | O160: #NUM! | P160: 10 | Q160: BACHAS, CEREAL & POLVILLO, COMPOST & FERTILIZANTES, DISPOSICIÓN FINAL RESIDUOS LIQUIDOS, DISPOSICIÓN FINAL RESIDUOS SOLIDOS, EXPORTACION, NFU, PILETAS, REACTORES, TIERRAS FILTRANTES | R160: 1 | S160: -344000.85 | T160: 1 | U160: APERTURADO POR EMPRESA | V160: REACTORES
A161: 45950 | B161: American Express Argentina S. A. | C161: OCOM/2025/0472 | D161: -344000.85 | E161: OC 0001-00001936: PERSONAL | F161: 1 | G161: 344000.85 | H161: UN | I161: PERSONAL | J161: OPEX | K161: VARIABLE | L161: INDIRECTO | M161: 0 | N161: CC1 | O161: #NUM! | P161: 10 | Q161: BACHAS, CEREAL & POLVILLO, COMPOST & FERTILIZANTES, DISPOSICIÓN FINAL RESIDUOS LIQUIDOS, DISPOSICIÓN FINAL RESIDUOS SOLIDOS, EXPORTACION, NFU, PILETAS, REACTORES, TIERRAS FILTRANTES | R161: 1 | S161: -344000.85 | T161: 1 | U161: APERTURADO POR EMPRESA | V161: TIERRAS FILTRANTES
A162: 45949 | B162: Amx Argentina Sociedad Anonima | C162: FA-A 01331-01351660 | D162: -40348.6 | E162: OC 0001-00002225: SERVICIOS Servicio Móvil | F162: 1 | G162: 10605 | H162: UN | I162: SERVICIOS | J162: OPEX | K162: VARIABLE | L162: INDIRECTO | M162: 0 | N162: CC1 | O162: #NUM! | P162: 10 | Q162: BACHAS, CEREAL & POLVILLO, COMPOST & FERTILIZANTES, DISPOSICIÓN FINAL RESIDUOS LIQUIDOS, DISPOSICIÓN FINAL RESIDUOS SOLIDOS, EXPORTACION, NFU, PILETAS, REACTORES, TIERRAS FILTRANTES | R162: 1 | S162: -40348.6 | T162: 1 | U162: APERTURADO POR EMPRESA | V162: BACHAS
A163: 45949 | B163: Amx Argentina Sociedad Anonima | C163: FA-A 01331-01351660 | D163: -40348.6 | E163: OC 0001-00002225: SERVICIOS Servicio Móvil | F163: 1 | G163: 10605 | H163: UN | I163: SERVICIOS | J163: OPEX | K163: VARIABLE | L163: INDIRECTO | M163: 0 | N163: CC1 | O163: #NUM! | P163: 10 | Q163: BACHAS, CEREAL & POLVILLO, COMPOST & FERTILIZANTES, DISPOSICIÓN FINAL RESIDUOS LIQUIDOS, DISPOSICIÓN FINAL RESIDUOS SOLIDOS, EXPORTACION, NFU, PILETAS, REACTORES, TIERRAS FILTRANTES | R163: 1 | S163: -40348.6 | T163: 1 | U163: APERTURADO POR EMPRESA | V163: CEREAL & POLVILLO
... A855: 45961 | B855: PROVEEDOR | C855: MT-0004 | D855: -3029264148 | E855: AFE (S) | F855: 2236.94 | G855: 925 | H855: TN | I855: MATERIA PRIMA | J855: OPEX | K855: VARIABLE | L855: DIRECTO | M855: 0 | N855: CC11 | O855: #NUM! | P855: 1 | Q855: EXPORTACION | R855: 1 | S855: -3029264148 | T855: 2236.94 | U855: APERTURADO POR EMPRESA | V855: EXPORTACION
A856: 45961 | B856: PILETAS | C856: MT-0005 | D856: 0 | E856: AG- A | F856: #NUM! | G856: 850 | H856: TN | I856: MATERIA PRIMA | J856: OPEX | K856: VARIABLE | L856: DIRECTO | M856: 0 | N856: CC11 | O856: #NUM! | P856: 1 | Q856: EXPORTACION | R856: 1 | S856: 0 | T856: #NUM! | U856: APERTURADO POR EMPRESA | V856: EXPORTACION
A857: 45961 | B857: PILETAS | C857: MT-0006 | D857: -24537811 | E857: AG- B | F857: 20.44 | G857: 820 | H857: TN | I857: MATERIA PRIMA | J857: OPEX | K857: VARIABLE | L857: DIRECTO | M857: 0 | N857: CC11 | O857: #NUM! | P857: 1 | Q857: EXPORTACION | R857: 1 | S857: -24537811 | T857: 20.44 | U857: APERTURADO POR EMPRESA | V857: EXPORTACION
A858: 45961 | B858: PILETAS | C858: MT-0007 | D858: -12127190 | E858: AG- C | F858: 15.34 | G858: 540 | H858: TN | I858: MATERIA PRIMA | J858: OPEX | K858: VARIABLE | L858: DIRECTO | M858: 0 | N858: CC11 | O858: #NUM! | P858: 1 | Q858: EXPORTACION | R858: 1 | S858: -12127190 | T858: 15.34 | U858: APERTURADO POR EMPRESA | V858: EXPORTACION
A859: 45961 | B859: REACTORES | C859: MT-0008 | D859: 0 | E859: ARE- A | F859: #NUM! | G859: 820 | H859: TN | I859: MATERIA PRIMA | J859: OPEX | K859: VARIABLE | L859: DIRECTO | M859: 0 | N859: CC11 | O859: #NUM! | P859: 1 | Q859: EXPORTACION | R859: 1 | S859: 0 | T859: #NUM! | U859: APERTURADO POR EMPRESA | V859: EXPORTACION
A860: 45961 | B860: REACTORES | C860: MT-0009 | D860: 0 | E860: ARE- B | F860: #NUM! | G860: 820 | H860: TN | I860: MATERIA PRIMA | J860: OPEX | K860: VARIABLE | L860: DIRECTO | M860: 0 | N860: CC11 | O860: #NUM! | P860: 1 | Q860: EXPORTACION | R860: 1 | S860: 0 | T860: #NUM! | U860: APERTURADO POR EMPRESA | V860: EXPORTACION
A861: 45961 | B861: REACTORES -PZ | C861: MT-0010 | D861: -246338496 | E861: ARE- A | F861: 205.2 | G861: 820 | H861: TN | I861: MATERIA PRIMA | J861: OPEX | K861: VARIABLE | L861: DIRECTO | M861: 0 | N861: NO | O861: #NUM! | P861: 1 | Q861: ANULADO | R861: 1 | S861: -246338496 | T861: 205.2 | U861: APERTURADO POR EMPRESA | V861: ANULADO
A862: 45961 | B862: REACTORES - PZ | C862: MT-0011 | D862: 0 | E862: ARE- B | F862: #NUM! | G862: 820 | H862: TN | I862: MATERIA PRIMA | J862: OPEX | K862: VARIABLE | L862: DIRECTO | M862: 0 | N862: NO | O862: #NUM! | P862: 1 | Q862: ANULADO | R862: 1 | S862: 0 | T862: #NUM! | U862: APERTURADO POR EMPRESA | V862: ANULADO
A863: 45961 | B863: WORMS 2 | C863: MT-0012 | D863: -154255824 | E863: AG- A | F863: 123.96 | G863: 850 | H863: TN | I863: MATERIA PRIMA | J863: OPEX | K863: VARIABLE | L863: DIRECTO | M863: 0 | N863: NO | O863: #NUM! | P863: 1 | Q863: ANULADO | R863: 1 | S863: -154255824 | T863: 123.96 | U863: APERTURADO POR EMPRESA | V863: ANULADO
A864: 45961 | B864: WORMS 2 | C864: MT-0013 | D864: 0 | E864: AG- B | F864: #NUM! | G864: 820 | H864: TN | I864: MATERIA PRIMA | J864: OPEX | K864: VARIABLE | L864: DIRECTO | M864: 0 | N864: NO | O864: #NUM! | P864: 1 | Q864: ANULADO | R864: 1 | S864: 0 | T864: #NUM! | U864: APERTURADO POR EMPRESA | V864: ANULADO
A865: 45961 | B865: WORMS 2 | C865: MT-0014 | D865: -8300880 | E865: AG- C | F865: 10.5 | G865: 540 | H865: TN | I865: MATERIA PRIMA | J865: OPEX | K865: VARIABLE | L865: DIRECTO | M865: 0 | N865: NO | O865: #NUM! | P865: 1 | Q865: ANULADO | R865: 1 | S865: -8300880 | T865: 10.5 | U865: APERTURADO POR EMPRESA | V865: ANULADO
A866: 45961 | B866: PZ ( BORRA + PROVEEDOR) | C866: MT-0021 | D866: -91072512 | E866: AG- C | F866: 115.2 | G866: 540 | H866: TN | I866: MATERIA PRIMA | J866: OPEX | K866: VARIABLE | L866: DIRECTO | M866: 0 | N866: NO | O866: #NUM! | P866: 1 | Q866: ANULADO | R866: 1 | S866: -91072512 | T866: 115.2 | U866: APERTURADO POR EMPRESA | V866: ANULADO
A867: 45961 | B867: PILETAS | C867: MT-0022 | D867: 0 | E867: AG- C | F867: #NUM! | G867: 540 | H867: TN | I867: MATERIA PRIMA | J867: OPEX | K867: VARIABLE | L867: DIRECTO | M867: 0 | N867: CC5 | O867: #NUM! | P867: 1 | Q867: REACTORES | R867: 1 | S867: 0 | T867: #NUM! | U867: APERTURADO POR EMPRESA | V867: REACTORES
A868: 45961 | B868: PROVEEDOR | C868: MT-0023 | D868: -1.6548757e+08 | E868: AG - E | F868: 124.32 | G868: 909.25 | H868: TN | I868: MATERIA PRIMA | J868: OPEX | K868: VARIABLE | L868: DIRECTO | M868: 0 | N868: CC11 | O868: #NUM! | P868: 1 | Q868: EXPORTACION | R868: 1 | S868: -1.6548757e+08 | T868: 124.32 | U868: APERTURADO POR EMPRESA | V868: EXPORTACION
A869: 45961 | B869: WORMS 2 | C869: MT-0024 | D869: 0 | E869: SEBO C - 2da | F869: #NUM! | G869: #NUM! | H869: TN | I869: MATERIA PRIMA | J869: OPEX | K869: VARIABLE | L869: DIRECTO | M869: 0 | N869: NO | O869: #NUM! | P869: 1 | Q869: ANULADO | R869: 1 | S869: 0 | T869: #NUM! | U869: APERTURADO POR EMPRESA | V869: ANULADO
A870: 45961 | B870: WORMS 2 | C870: MT-0025 | D870: 0 | E870: BORRA A VEGETAL | F870: 126.22 | G870: #NUM! | H870: TN | I870: MATERIA PRIMA | J870: OPEX | K870: VARIABLE | L870: DIRECTO | M870: 0 | N870: NO | O870: #NUM! | P870: 1 | Q870: ANULADO | R870: 1 | S870: 0 | T870: 126.22 | U870: APERTURADO POR EMPRESA | V870: ANULADO
A871: 45961 | B871: WORMS 2 | C871: MT-0026 | D871: 0 | E871: FONDO TK | F871: 22.2 | G871: #NUM! | H871: TN | I871: MATERIA PRIMA | J871: OPEX | K871: VARIABLE | L871: DIRECTO | M871: 0 | N871: NO | O871: #NUM! | P871: 1 | Q871: ANULADO | R871: 1 | S871: 0 | T871: 22.2 | U871: APERTURADO POR EMPRESA | V871: ANULADO
A872: 45961 | B872: WORMS 2 | C872: MT-0027 | D872: 0 | E872: BORRA ANIMAL | F872: 34.1 | G872: #NUM! | H872: TN | I872: MATERIA PRIMA | J872: OPEX | K872: VARIABLE | L872: DIRECTO | M872: 0 | N872: NO | O872: #NUM! | P872: 1 | Q872: ANULADO | R872: 1 | S872: 0 | T872: 34.1 | U872: APERTURADO POR EMPRESA | V872: ANULADO
A873: 45961 | B873: PROVEEDOR | C873: MT-0028 | D873: 0 | E873: BORRA PESCADO | F873: 86.28 | G873: #NUM! | H873: TN | I873: MATERIA PRIMA | J873: OPEX | K873: VARIABLE | L873: DIRECTO | M873: 0 | N873: NO | O873: #NUM! | P873: 1 | Q873: ANULADO | R873: 1 | S873: 0 | T873: 86.28 | U873: APERTURADO POR EMPRESA | V873: ANULADO
A874: 45961 | B874: PILETAS | C874: MT-0029 | D874: -26088480 | E874: EMULSION | F874: 35.64 | G874: 500 | H874: TN | I874: MATERIA PRIMA | J874: OPEX | K874: VARIABLE | L874: DIRECTO | M874: 0 | N874: CC4 | O874: #NUM! | P874: 1 | Q874: PILETAS | R874: 1 | S874: -26088480 | T874: 35.64 | U874: APERTURADO POR EMPRESA | V874: PILETAS
A875: 45961 | B875: PILETAS | C875: MT-0030 | D875: 0 | E875: AG-D | F875: 82.26 | G875: #NUM! | H875: TN | I875: MATERIA PRIMA | J875: 0 | K875: 0 | L875: 0 | M875: 0 | N875: 0 | O875: #NUM! | P875: 0 | Q875: 0 | R875: 1 | S875: 0 | T875: 82.26 | U875: APERTURADO POR EMPRESA | V875: 0
A876: 45961 | B876: Martins, Joaquin | C876: AD-0001 | D876: 0 | E876: ENERGIA GASOIL G3 | F876: #NUM! | G876: 1754 | H876: Lts | I876: ENERGIA | J876: OPEX | K876: VARIABLE | L876: DIRECTO | M876: 0 | N876: CC1 | O876: #NUM! | P876: CCO NO DEFINIDO | Q876: CCO NO DEFINIDO | R876: 1 | S876: 0 | T876: #NUM! | U876: APERTURADO POR EMPRESA | V876: CCO NO DEFINIDO
A877: 45961 | B877: Martins, Joaquin | C877: AD-0001 | D877: -2679040 | E877: ENERGIA G2 | F877: 1820 | G877: 1472 | H877: Lts | I877: ENERGIA | J877: OPEX | K877: VARIABLE | L877: DIRECTO | M877: 0 | N877: CC6 | O877: #NUM! | P877: 1 | Q877: BACHAS | R877: 1 | S877: -2679040 | T877: 1820 | U877: APERTURADO POR EMPRESA | V877: BACHAS
A878: 45961 | B878: Martins, Joaquin | C878: AD-0001 | D878: 0 | E878: ENERGIA G2 | F878: 0 | G878: 1472 | H878: Lts | I878: ENERGIA | J878: OPEX | K878: VARIABLE | L878: DIRECTO | M878: 0 | N878: CC5 | O878: #NUM! | P878: 1 | Q878: REACTORES | R878: 1 | S878: 0 | T878: 0 | U878: APERTURADO POR EMPRESA | V878: REACTORES
A879: 45961 | B879: Martins, Joaquin | C879: AD-0001 | D879: -149500 | E879: ENERGIA Nafta | F879: 100 | G879: 1495 | H879: Lts | I879: ENERGIA | J879: OPEX | K879: VARIABLE | L879: DIRECTO | M879: 0 | N879: CC6 | O879: #NUM! | P879: 1 | Q879: BACHAS | R879: 1 | S879: -149500 | T879: 100 | U879: APERTURADO POR EMPRESA | V879: BACHAS
A880: 45961 | B880: Martins, Joaquin | C880: AD-0001 | D880: -1644500 | E880: ENERGIA Nafta | F880: 1100 | G880: 1495 | H880: Lts | I880: ENERGIA | J880: OPEX | K880: VARIABLE | L880: DIRECTO | M880: 0 | N880: CC4 | O880: #NUM! | P880: 1 | Q880: PILETAS | R880: 1 | S880: -1644500 | T880: 1100 | U880: APERTURADO POR EMPRESA | V880: PILETAS
A881: 45961 | B881: Martins, Joaquin | C881: AD-0001 | D881: -448500 | E881: ENERGIA Nafta | F881: 300 | G881: 1495 | H881: Lts | I881: ENERGIA | J881: OPEX | K881: VARIABLE | L881: DIRECTO | M881: 0 | N881: CC3 | O881: #NUM! | P881: 1 | Q881: DISPOSICIÓN FINAL RESIDUOS LIQUIDOS | R881: 1 | S881: -448500 | T881: 300 | U881: APERTURADO POR EMPRESA | V881: DISPOSICIÓN FINAL RESIDUOS LIQUIDOS
A882: 45961 | B882: Ultraonix Srl | C882: AD-0001 | D882: -14998192 | E882: ENERGIA Fuel Oil | F882: 24400 | G882: 614.68 | H882: KG | I882: ENERGIA | J882: OPEX | K882: VARIABLE | L882: DIRECTO | M882: 0 | N882: CC5 | O882: #NUM! | P882: 1 | Q882: REACTORES | R882: 1 | S882: -14998192 | T882: 24400 | U882: APERTURADO POR EMPRESA | V882: REACTORES
A883: 45961 | B883: Ultraonix Srl | C883: AD-0001 | D883: -5224780 | E883: ENERGIA Fuel Oil | F883: 8500 | G883: 614.68 | H883: KG | I883: ENERGIA | J883: OPEX | K883: VARIABLE | L883: DIRECTO | M883: 0 | N883: CC6 | O883: #NUM! | P883: 1 | Q883: BACHAS | R883: 1 | S883: -5224780 | T883: 8500 | U883: APERTURADO POR EMPRESA | V883: BACHAS
A884: 45961 | B884: Total Quimica S.A. | C884: AD-0001 | D884: -7342440.6 | E884: INSUMOS Acido Sulfúrico 70/80 | F884: 19860 | G884: 369.71 | H884: KG | I884: INSUMOS | J884: OPEX | K884: VARIABLE | L884: DIRECTO | M884: 0 | N884: CC6 | O884: #NUM! | P884: 1 | Q884: BACHAS | R884: 1 | S884: -7342440.6 | T884: 19860 | U884: APERTURADO POR EMPRESA | V884: BACHAS
A885: 45961 | B885: Total Quimica S.A. | C885: AD-0001 | D885: -547520 | E885: INSUMOS Acido Clorhidrico | F885: 1180 | G885: 464 | H885: KG | I885: INSUMOS | J885: OPEX | K885: VARIABLE | L885: DIRECTO | M885: 0 | N885: CC6 | O885: #NUM! | P885: 1 | Q885: BACHAS | R885: 1 | S885: -547520 | T885: 1180 | U885: APERTURADO POR EMPRESA | V885: BACHAS
A886: 45961 | B886: Total Quimica S.A. | C886: AD-0001 | D886: -691147.5 | E886: INSUMOS Soda Caustica | F886: 750 | G886: 921.53 | H886: KG | I886: INSUMOS | J886: OPEX | K886: VARIABLE | L886: DIRECTO | M886: 0 | N886: CC5 | O886: #NUM! | P886: 1 | Q886: REACTORES | R886: 1 | S886: -691147.5 | T886: 750 | U886: APERTURADO POR EMPRESA | V886: REACTORES
A887: 45961 | B887: Salinera Jaisal S. A. | C887: AD-0001 | D887: -59774 | E887: INSUMOS Cloruro de Sodio (SAL) | F887: 520 | G887: 114.95 | H887: KG | I887: INSUMOS | J887: OPEX | K887: VARIABLE | L887: DIRECTO | M887: 0 | N887: CC6 | O887: #NUM! | P887: 1 | Q887: BACHAS | R887: 1 | S887: -59774 | T887: 520 | U887: APERTURADO POR EMPRESA | V887: BACHAS
A888: 45961 | B888: Cremer Y Asociados Sociedad Anonima | C888: AD-0001 | D888: -11525588 | E888: INSUMOS Glicerina cruda | F888: 28.75 | G888: 400890 | H888: TN | I888: INSUMOS | J888: OPEX | K888: VARIABLE | L888: DIRECTO | M888: 0 | N888: CC5 | O888: #NUM! | P888: 1 | Q888: REACTORES | R888: 1 | S888: -11525588 | T888: 28.75 | U888: APERTURADO POR EMPRESA | V888: REACTORES
A889: 45961 | B889: Meri-mar SRL | C889: AD-0001 | D889: 0 | E889: LOGISTICA | F889: 97.4 | G889: 19500 | H889: TN | I889: SERVICIOS | J889: OPEX | K889: VARIABLE | L889: DIRECTO | M889: 0 | N889: CC11 | O889: #NUM! | P889: 1 | Q889: EXPORTACION | R889: 1 | S889: 0 | T889: 97.4 | U889: APERTURADO POR EMPRESA | V889: EXPORTACION
A890: 45961 | B890: Mercomar SA | C890: AD-0001 | D890: 0 | E890: LOGISTICA | F890: 852.25 | G890: 19500 | H890: TN | I890: SERVICIOS | J890: 0 | K890: 0 | L890: 0 | M890: 0 | N890: 0 | O890: #NUM! | P890: 0 | Q890: 0 | R890: 1 | S890: 0 | T890: 852.25 | U890: APERTURADO POR EMPRESA | V890: 0
A891: 45961 | B891: Transportes Padilla Sociedad Anonima | C891: AD-0001 | D891: 0 | E891: LOGISTICA | F891: 876.6 | G891: #NUM! | H891: TN | I891: SERVICIOS | J891: OPEX | K891: VARIABLE | L891: DIRECTO | M891: 0 | N891: CC11 | O891: #NUM! | P891: 1 | Q891: EXPORTACION | R891: 1 | S891: 0 | T891: 876.6 | U891: APERTURADO POR EMPRESA | V891: EXPORTACION
A892: 45961 | B892: Cronos Soluciones Sustentables Sa | C892: AD-0001 | D892: -11261875 | E892: LOGISTICA | F892: 608.75 | G892: 18500 | H892: TN | I892: LOGISTICA | J892: OPEX | K892: VARIABLE | L892: DIRECTO | M892: 0 | N892: NO | O892: #NUM! | P892: 1 | Q892: ANULADO | R892: 1 | S892: -11261875 | T892: 608.75 | U892: APERTURADO POR EMPRESA | V892: ANULADO
A893: 45961 | B893: Transporte Automotor El Loco Srl | C893: AD-0001 | D893: 0 | E893: LOGISTICA | F893: 97.4 | G893: #NUM! | H893: TN | I893: LOGISTICA | J893: OPEX | K893: VARIABLE | L893: DIRECTO | M893: 0 | N893: NO | O893: #NUM! | P893: 1 | Q893: ANULADO | R893: 1 | S893: 0 | T893: 97.4 | U893: APERTURADO POR EMPRESA | V893: ANULADO
A894: 45961 | B894: Energia Del Sur Srl | C894: AD-0001 | D894: -1461000 | E894: LOGISTICA | F894: 97.4 | G894: 15000 | H894: TN | I894: LOGISTICA | J894: OPEX | K894: VARIABLE | L894: DIRECTO | M894: 0 | N894: NO | O894: #NUM! | P894: 1 | Q894: ANULADO | R894: 1 | S894: -1461000 | T894: 97.4 | U894: APERTURADO POR EMPRESA | V894: ANULADO
A895: 45961 | B895: Duport Sociedad De Responsabilidad Limitada | C895: AD-0001 | D895: 0 | E895: LOGISTICA | F895: 194.8 | G895: #NUM! | H895: TN | I895: LOGISTICA | J895: OPEX | K895: VARIABLE | L895: DIRECTO | M895: 0 | N895: NO | O895: #NUM! | P895: 1 | Q895: ANULADO | R895: 1 | S895: 0 | T895: 194.8 | U895: APERTURADO POR EMPRESA | V895: ANULADO
A896: 45931 | B896: GANANCIAS EXPORTACION | C896: AD_10-2025 | D896: -2067241.2 | E896: IMPUESTOS | F896: 2824.1 | G896: 0.5 | H896: UN | I896: IMPUESTOS | J896: OPEX | K896: VARIABLE | L896: DIRECTO | M896: 0 | N896: CC11 | O896: #NUM! | P896: 1 | Q896: EXPORTACION | R896: 1 | S896: -2067241.2 | T896: 2824.1 | U896: APERTURADO POR EMPRESA | V896: EXPORTACION
A897: 45960 | B897: GASTOS BANCARIOS | C897: OCOM/2025/10 | D897: -6924925.3 | E897: IMPUESTOS | F897: 1 | G897: 6924925.3 | H897: UN | I897: IMPUESTOS | J897: OPEX | K897: VARIABLE | L897: INDIRECTO | M897: 0 | N897: CC1 | O897: #NUM! | P897: CCO NO DEFINIDO | Q897: CCO NO DEFINIDO | R897: 1 | S897: -6924925.3 | T897: 1 | U897: APERTURADO POR EMPRESA | V897: CCO NO DEFINIDO
A898: 45960 | B898: IB | C898: OCOM/2025/10 | D898: -32811.49 | E898: IMPUESTOS | F898: 1 | G898: 32811.49 | H898: UN | I898: IMPUESTOS | J898: OPEX | K898: VARIABLE | L898: INDIRECTO | M898: 0 | N898: CC1 | O898: #NUM! | P898: 10 | Q898: BACHAS, CEREAL & POLVILLO, COMPOST & FERTILIZANTES, DISPOSICIÓN FINAL RESIDUOS LIQUIDOS, DISPOSICIÓN FINAL RESIDUOS SOLIDOS, EXPORTACION, NFU, PILETAS, REACTORES, TIERRAS FILTRANTES | R898: 1 | S898: -32811.49 | T898: 1 | U898: APERTURADO POR EMPRESA | V898: BACHAS
A899: 45960 | B899: IB | C899: OCOM/2025/10 | D899: -32811.49 | E899: IMPUESTOS | F899: 1 | G899: 32811.49 | H899: UN | I899: IMPUESTOS | J899: OPEX | K899: VARIABLE | L899: INDIRECTO | M899: 0 | N899: CC1 | O899: #NUM! | P899: 10 | Q899: BACHAS, CEREAL & POLVILLO, COMPOST & FERTILIZANTES, DISPOSICIÓN FINAL RESIDUOS LIQUIDOS, DISPOSICIÓN FINAL RESIDUOS SOLIDOS, EXPORTACION, NFU, PILETAS, REACTORES, TIERRAS FILTRANTES | R899: 1 | S899: -32811.49 | T899: 1 | U899: APERTURADO POR EMPRESA | V899: CEREAL & POLVILLO
A900: 45960 | B900: IB | C900: OCOM/2025/10 | D900: -32811.49 | E900: IMPUESTOS | F900: 1 | G900: 32811.49 | H900: UN | I900: IMPUESTOS | J900: OPEX | K900: VARIABLE | L900: INDIRECTO | M900: 0 | N900: CC1 | O900: #NUM! | P900: 10 | Q900: BACHAS, CEREAL & POLVILLO, COMPOST & FERTILIZANTES, DISPOSICIÓN FINAL RESIDUOS LIQUIDOS, DISPOSICIÓN FINAL RESIDUOS SOLIDOS, EXPORTACION, NFU, PILETAS, REACTORES, TIERRAS FILTRANTES | R900: 1 | S900: -32811.49 | T900: 1 | U900: APERTURADO POR EMPRESA | V900: COMPOST & FERTILIZANTES
A901: 45960 | B901: IB | C901: OCOM/2025/10 | D901: -32811.49 | E901: IMPUESTOS | F901: 1 | G901: 32811.49 | H901: UN | I901: IMPUESTOS | J901: OPEX | K901: VARIABLE | L901: INDIRECTO | M901: 0 | N901: CC1 | O901: #NUM! | P901: 10 | Q901: BACHAS, CEREAL & POLVILLO, COMPOST & FERTILIZANTES, DISPOSICIÓN FINAL RESIDUOS LIQUIDOS, DISPOSICIÓN FINAL RESIDUOS SOLIDOS, EXPORTACION, NFU, PILETAS, REACTORES, TIERRAS FILTRANTES | R901: 1 | S901: -32811.49 | T901: 1 | U901: APERTURADO POR EMPRESA | V901: DISPOSICIÓN FINAL RESIDUOS LIQUIDOS
A902: 45960 | B902: IB | C902: OCOM/2025/10 | D902: -32811.49 | E902: IMPUESTOS | F902: 1 | G902: 32811.49 | H902: UN | I902: IMPUESTOS | J902: OPEX | K902: VARIABLE | L902: INDIRECTO | M902: 0 | N902: CC1 | O902: #NUM! | P902: 10 | Q902: BACHAS, CEREAL & POLVILLO, COMPOST & FERTILIZANTES, DISPOSICIÓN FINAL RESIDUOS LIQUIDOS, DISPOSICIÓN FINAL RESIDUOS SOLIDOS, EXPORTACION, NFU, PILETAS, REACTORES, TIERRAS FILTRANTES | R902: 1 | S902: -32811.49 | T902: 1 | U902: APERTURADO POR EMPRESA | V902: DISPOSICIÓN FINAL RESIDUOS SOLIDOS
A903: 45960 | B903: IB | C903: OCOM/2025/10 | D903: -32811.49 | E903: IMPUESTOS | F903: 1 | G903: 32811.49 | H903: UN | I903: IMPUESTOS | J903: OPEX | K903: VARIABLE | L903: INDIRECTO | M903: 0 | N903: CC1 | O903: #NUM! | P903: 10 | Q903: BACHAS, CEREAL & POLVILLO, COMPOST & FERTILIZANTES, DISPOSICIÓN FINAL RESIDUOS LIQUIDOS, DISPOSICIÓN FINAL RESIDUOS SOLIDOS, EXPORTACION, NFU, PILETAS, REACTORES, TIERRAS FILTRANTES | R903: 1 | S903: -32811.49 | T903: 1 | U903: APERTURADO POR EMPRESA | V903: EXPORTACION
A904: 45960 | B904: IB | C904: OCOM/2025/10 | D904: -32811.49 | E904: IMPUESTOS | F904: 1 | G904: 32811.49 | H904: UN | I904: IMPUESTOS | J904: OPEX | K904: VARIABLE | L904: INDIRECTO | M904: 0 | N904: CC1 | O904: #NUM! | P904: 10 | Q904: BACHAS, CEREAL & POLVILLO, COMPOST & FERTILIZANTES, DISPOSICIÓN FINAL RESIDUOS LIQUIDOS, DISPOSICIÓN FINAL RESIDUOS SOLIDOS, EXPORTACION, NFU, PILETAS, REACTORES, TIERRAS FILTRANTES | R904: 1 | S904: -32811.49 | T904: 1 | U904: APERTURADO POR EMPRESA | V904: NFU
A905: 45960 | B905: IB | C905: OCOM/2025/10 | D905: -32811.49 | E905: IMPUESTOS | F905: 1 | G905: 32811.49 | H905: UN | I905: IMPUESTOS | J905: OPEX | K905: VARIABLE | L905: INDIRECTO | M905: 0 | N905: CC1 | O905: #NUM! | P905: 10 | Q905: BACHAS, CEREAL & POLVILLO, COMPOST & FERTILIZANTES, DISPOSICIÓN FINAL RESIDUOS LIQUIDOS, DISPOSICIÓN FINAL RESIDUOS SOLIDOS, EXPORTACION, NFU, PILETAS, REACTORES, TIERRAS FILTRANTES | R905: 1 | S905: -32811.49 | T905: 1 | U905: APERTURADO POR EMPRESA | V905: PILETAS
A906: 45960 | B906: IB | C906: OCOM/2025/10 | D906: -32811.49 | E906: IMPUESTOS | F906: 1 | G906: 32811.49 | H906: UN | I906: IMPUESTOS | J906: OPEX | K906: VARIABLE | L906: INDIRECTO | M906: 0 | N906: CC1 | O906: #NUM! | P906: 10 | Q906: BACHAS, CEREAL & POLVILLO, COMPOST & FERTILIZANTES, DISPOSICIÓN FINAL RESIDUOS LIQUIDOS, DISPOSICIÓN FINAL RESIDUOS SOLIDOS, EXPORTACION, NFU, PILETAS, REACTORES, TIERRAS FILTRANTES | R906: 1 | S906: -32811.49 | T906: 1 | U906: APERTURADO POR EMPRESA | V906: REACTORES
A907: 45960 | B907: IB | C907: OCOM/2025/10 | D907: -32811.49 | E907: IMPUESTOS | F907: 1 | G907: 32811.49 | H907: UN | I907: IMPUESTOS | J907: OPEX | K907: VARIABLE | L907: INDIRECTO | M907: 0 | N907: CC1 | O907: #NUM! | P907: 10 | Q907: BACHAS, CEREAL & POLVILLO, COMPOST & FERTILIZANTES, DISPOSICIÓN FINAL RESIDUOS LIQUIDOS, DISPOSICIÓN FINAL RESIDUOS SOLIDOS, EXPORTACION, NFU, PILETAS, REACTORES, TIERRAS FILTRANTES | R907: 1 | S907: -32811.49 | T907: 1 | U907: APERTURADO POR EMPRESA | V907: TIERRAS FILTRANTES
A908: 45960 | B908: DREI DISPOSICIÓN FINAL RESIDUOS LIQUIDOS | C908: OCOM/2025/10 | D908: -656141 | E908: IMPUESTOS | F908: 1 | G908: 656141 | H908: UN | I908: IMPUESTOS | J908: OPEX | K908: VARIABLE | L908: INDIRECTO | M908: 0 | N908: CC3 | O908: #NUM! | P908: 1 | Q908: DISPOSICIÓN FINAL RESIDUOS LIQUIDOS | R908: 1 | S908: -656141 | T908: 1 | U908: APERTURADO POR EMPRESA | V908: DISPOSICIÓN FINAL RESIDUOS LIQUIDOS
A909: 45960 | B909: DREI COMPOST & FERTILIZANTES | C909: OCOM/2025/10 | D909: -485805 | E909: IMPUESTOS | F909: 1 | G909: 485805 | H909: UN | I909: IMPUESTOS | J909: OPEX | K909: VARIABLE | L909: INDIRECTO | M909: 0 | N909: CC8 | O909: #NUM! | P909: 1 | Q909: COMPOST & FERTILIZANTES | R909: 1 | S909: -485805 | T909: 1 | U909: APERTURADO POR EMPRESA | V909: COMPOST & FERTILIZANTES
... A1522: 45931 | B1522: WORMS-RRHH | C1522: ADROVER, JUAN HORACIO | D1522: -1876296.3 | E1522: TALLER MECANICO | F1522: 15 | G1522: 1876296.3 | H1522: #RRHH | I1522: PERSONAL | J1522: Opex | K1522: Fijo | L1522: Indirecto | M1522: 0 | N1522: CC23 | O1522: #NUM! | P1522: 10 | Q1522: BACHAS, CEREAL Y POLVILLO, COMPOST Y FERTILIZANTES, DISPOSICION FINAL DE R. LIQUIDOS, DISPOSICION FINAL DE R. SOLIDOS, EXPORTACION, NFU, PILETAS, REACTORES, TIERRAS FILTRANTES | R1522: 1 | S1522: -1876296.3 | T1522: 15 | U1522: APERTURADO POR EMPRESA | V1522: TIERRAS FILTRANTES

Sheet ingresos_ingresos
A1: FECHA CARGA | B1: CANAL | C1: AREA | D1: SECTOR | E1: PRODUCTO | F1: CLIENTE | G1: DESCRIPCION | H1: UM | I1: Q | J1: PRECIO | K1: MONEDA | L1: SUBTOTAL | M1: T.C | N1: IVA | O1: TOTAL | P1: Fuente
A2: 45931 | B2: 1 | C2: RECEPCION DE RESIDUOS SOLIDOS | D2: COMPOST_Y_FERTILIZANTES | E2: DESCARTE SEMILLAS | F2: TECNORED ENERGIA S.A. | H2: TN | I2: 184.94 | J2: 6 | K2: USD | L2: 1611197.3 | M2: 1452 | N2: 0.21 | O2: 1949548.7
A3: 45931 | B3: 1 | C3: RECEPCION DE RESIDUOS SOLIDOS | D3: DISP FINAL RESIDUOS SOLIDOS | E3: CERTIFICADO DISP FINAL SOLIDOS | G3: NFU | H3: KG | I3: 7920 | J3: 70 | K3: ARS | L3: 554400 | M3: 0 | N3: 0.21 | O3: 670824
A4: 45931 | B4: 1 | C4: RECEPCION DE RESIDUOS SOLIDOS | D4: DISP FINAL RESIDUOS SOLIDOS | E4: TIERRA TOSCA | F4: Aceitera Lonatte SRL | H4: TN | I4: 133.24
A5: 45931 | B5: 1 | C5: RECEPCION DE RESIDUOS SOLIDOS | D5: DISP FINAL RESIDUOS SOLIDOS | E5: CERTIFICADO DISP FINAL SOLIDOS | F5: Boortmalt | H5: TN | I5: 64.66 | J5: 3000 | K5: ARS | L5: 193980 | M5: 1 | N5: 0.21 | O5: 234715.8
A6: 45931 | B6: 1 | C6: RECEPCION DE RESIDUOS SOLIDOS | D6: DISP FINAL RESIDUOS SOLIDOS | E6: CERTIFICADO DISP FINAL SOLIDOS | F6: Bunge Argentina S A - San Jeronimo Sud | H6: TN | I6: 46.66 | J6: 4.93 | K6: USD | L6: 334009.08 | M6: 1452 | N6: 0.21 | O6: 404150.98
A7: 45931 | B7: 1 | C7: RECEPCION DE RESIDUOS SOLIDOS | D7: DISP FINAL RESIDUOS SOLIDOS | E7: SEMILLAS | F7: Bunge Argentina S A - San Jeronimo Sud | H7: TN | I7: 583.72 | J7: 0 | K7: 0
A8: 45931 | B8: 1 | C8: RECEPCION DE RESIDUOS SOLIDOS | D8: DISP FINAL RESIDUOS SOLIDOS | E8: CERTIFICADO DISP FINAL SOLIDOS | F8: Quickfood S.A. | H8: TN | I8: 145.56 | J8: 1140 | K8: ARS | L8: 165938.4 | M8: 1 | N8: 0.21 | O8: 200785.46
A9: 45931 | B9: 1 | C9: RECEPCION DE RESIDUOS SOLIDOS | D9: DISP FINAL RESIDUOS SOLIDOS | E9: CERTIFICADO DISP FINAL SOLIDOS | F9: Unilever de Argentina S.A. | H9: TN | I9: 31 | J9: 6500 | K9: ARS | L9: 201500 | M9: 1 | N9: 0.21 | O9: 243815
A10: 45931 | B10: 1 | C10: RECEPCION DE RESIDUOS SOLIDOS | D10: DISP FINAL RESIDUOS SOLIDOS | E10: CERTIFICADO DISP FINAL SOLIDOS | F10: Adm Agro S.R.L. - Arroyo Seco | H10: TN | I10: 38.62 | J10: 1600 | K10: ARS | L10: 61792 | M10: 1 | N10: 0.21 | O10: 74768.32
A11: 45931 | B11: 1 | C11: RECEPCION DE RESIDUOS SOLIDOS | D11: DISP FINAL RESIDUOS SOLIDOS | E11: CERTIFICADO DISP FINAL SOLIDOS | F11: Bunge Argentina S A - Puerto Gral San Martín | H11: TN | I11: 370.59 | J11: 0 | K11: ARS | L11: 0 | M11: 1 | N11: 0.21 | O11: 0
A12: 45931 | B12: 1 | C12: RECEPCION DE RESIDUOS SOLIDOS | D12: DISP FINAL RESIDUOS SOLIDOS | E12: CERTIFICADO DISP FINAL SOLIDOS | F12: Cargill - Alvear | H12: TN | I12: 14.94 | J12: 1305 | K12: ARS | L12: 19496.7 | M12: 1 | N12: 0.21 | O12: 23591.007
A13: 45931 | B13: 1 | C13: RECEPCION DE RESIDUOS SOLIDOS | D13: DISP FINAL RESIDUOS SOLIDOS | E13: CERTIFICADO DISP FINAL SOLIDOS | F13: Cargill - VGG | H13: TN | I13: 82.32 | J13: 1305 | K13: ARS | L13: 107427.6 | M13: 1 | N13: 0.21 | O13: 129987.4
A14: 45931 | B14: 1 | C14: RECEPCION DE RESIDUOS SOLIDOS | D14: DISP FINAL RESIDUOS SOLIDOS | E14: CERTIFICADO DISP FINAL SOLIDOS | F14: LDC Argentina S.A. - Lagos | H14: TN | I14: 43.74 | J14: 0 | K14: ARS | L14: 0 | M14: 1 | N14: 0.21 | O14: 0
A15: 45931 | B15: 1 | C15: RECEPCION DE RESIDUOS SOLIDOS | D15: DISP FINAL RESIDUOS SOLIDOS | E15: CERTIFICADO DISP FINAL SOLIDOS | F15: Molinos Rio De La Plata S.A. | H15: TN | I15: 37.33 | J15: 1760 | K15: ARS | L15: 65700.8 | M15: 1 | N15: 0.21 | O15: 79497.968
A16: 45931 | B16: 2 | C16: RECEPCION DE RESIDUOS SOLIDOS | D16: CEREAL & POLVILLO | E16: BARRIDO | F16: Alvarez Daniel Fabian | H16: TN | I16: 386.6 | J16: 40000 | K16: ARS | L16: 15464000 | M16: 1 | N16: 0 | O16: 15464000
A17: 45931 | B17: 2 | C17: RECEPCION DE RESIDUOS SOLIDOS | D17: CEREAL & POLVILLO | E17: BARRIDO | F17: Aquilino Pruzzo | H17: TN | I17: 19.12 | J17: 45000 | K17: ARS | L17: 860400 | M17: 1 | N17: 0 | O17: 860400
A18: 45931 | B18: 2 | C18: RECEPCION DE RESIDUOS SOLIDOS | D18: CEREAL & POLVILLO | E18: BARRIDO | F18: Batistelli | H18: TN | I18: 60.38 | J18: 30000 | K18: ARS | L18: 1811400 | M18: 1 | N18: 0 | O18: 1811400
A19: 45931 | B19: 2 | C19: RECEPCION DE RESIDUOS SOLIDOS | D19: CEREAL & POLVILLO | E19: BARRIDO | F19: Pascual | H19: TN | I19: 28 | J19: 40000 | K19: ARS | L19: 1120000 | M19: 1 | N19: 0 | O19: 1120000
... A22: 45931 | B22: 1 | C22: RECEPCION DE RESIDUOS LIQUIDOS | D22: DISP FINAL RESIDUOS LIQUIDOS | E22: CERTIFICADO DISP FINAL LIQUIDOS | F22: Bio Nogoya S.A. | H22: TN | I22: 281.86 | J22: 1770 | K22: ARS | L22: 498892.2 | M22: 1 | N22: 0.21 | O22: 603659.56
A23: 45931 | B23: 2 | C23: RECEPCION DE RESIDUOS LIQUIDOS | D23: DISP FINAL RESIDUOS LIQUIDOS | E23: CERTIFICADO DISP FINAL LIQUIDOS | F23: CREMER - CRONOS | H23: TN | I23: 176.32
A24: 45931 | B24: 2 | C24: RECEPCION DE RESIDUOS LIQUIDOS | D24: DISP FINAL RESIDUOS LIQUIDOS | E24: CERTIFICADO DISP FINAL LIQUIDOS | F24: DESIDERIO ZERIAL | H24: TN | I24: 50.74
A25: 45931 | B25: 1 | C25: RECEPCION DE RESIDUOS LIQUIDOS | D25: DISP FINAL RESIDUOS LIQUIDOS | E25: CERTIFICADO DISP FINAL LIQUIDOS | F25: Duport S.R.L. | H25: TN | I25: 3358.68 | J25: 5000 | K25: ARS | L25: 16793400 | M25: 1 | N25: 0.21 | O25: 20320014
A26: 45931 | B26: 1 | C26: RECEPCION DE RESIDUOS SOLIDOS | D26: DISP FINAL RESIDUOS SOLIDOS | E26: CERTIFICADO DISP FINAL SOLIDOS | F26: Emsade | H26: TN | I26: 65.48 | J26: 11500 | K26: ARS | L26: 753020 | M26: 1 | N26: 0.21 | O26: 911154.2
A27: 45931 | B27: 1 | C27: RECEPCION DE RESIDUOS LIQUIDOS | D27: DISP FINAL RESIDUOS LIQUIDOS | E27: CERTIFICADO DISP FINAL LIQUIDOS | F27: ERA S.A. | H27: TN | I27: 112.7 | J27: 7.5 | K27: USD | L27: 1227303 | M27: 1452 | N27: 0.21 | O27: 1485036.6
A28: 45931 | B28: 1 | C28: RECEPCION DE RESIDUOS LIQUIDOS | D28: DISP FINAL RESIDUOS LIQUIDOS | E28: CERTIFICADO DISP FINAL LIQUIDOS | F28: Geo S.R.L. | H28: TN | I28: 1727.49 | J28: 7.5 | K28: USD | L28: 18812366 | M28: 1452 | N28: 0.21 | O28: 22762963
A29: 45931 | B29: 1 | C29: RECEPCION DE RESIDUOS LIQUIDOS | D29: DISP FINAL RESIDUOS LIQUIDOS | E29: CERTIFICADO DISP FINAL LIQUIDOS | F29: Glardon Anibal Mauricio | H29: TN | I29: 221.04 | J29: 3937 | K29: ARS | L29: 870234.48 | M29: 1 | N29: 0.21 | O29: 1052983.7
A30: 45931 | B30: 1 | C30: RECEPCION DE RESIDUOS LIQUIDOS | D30: DISP FINAL RESIDUOS LIQUIDOS | E30: CERTIFICADO DISP FINAL LIQUIDOS | F30: Glycopharma S.A. | H30: TN | I30: 766.64 | J30: 1770 | K30: ARS | L30: 1356952.8 | M30: 1 | N30: 0.21 | O30: 1641912.9
A31: 45931 | B31: 1 | C31: RECEPCION DE RESIDUOS LIQUIDOS | D31: DISP FINAL RESIDUOS LIQUIDOS | E31: CERTIFICADO DISP FINAL LIQUIDOS | F31: Inagro S.R.L. | H31: TN | I31: 3835.94 | J31: 4.5 | K31: USD | L31: 25064032 | M31: 1452 | N31: 0.21 | O31: 30327479
A32: 45931 | B32: 1 | C32: RECEPCION DE RESIDUOS LIQUIDOS | D32: DISP FINAL RESIDUOS LIQUIDOS | E32: CERTIFICADO DISP FINAL LIQUIDOS | F32: Patagonia Bioenergía S.A. | H32: TN | I32: 98.44 | J32: 11120 | K32: ARS | L32: 1094652.8 | M32: 1 | N32: 0.21 | O32: 1324529.9
A33: 45931 | B33: 1 | C33: RECEPCION DE RESIDUOS LIQUIDOS | D33: DISP FINAL RESIDUOS LIQUIDOS | E33: CERTIFICADO DISP FINAL LIQUIDOS | F33: Renopack S.A. | H33: TN | I33: 8.43 | J33: 4380 | K33: ARS | L33: 36923.4 | M33: 1 | N33: 0.21 | O33: 44677.314
A34: 45931 | B34: 1 | C34: RECEPCION DE RESIDUOS LIQUIDOS | D34: DISP FINAL RESIDUOS LIQUIDOS | E34: CERTIFICADO DISP FINAL LIQUIDOS | F34: Renova S.A. | H34: TN | I34: 563.7 | J34: 11120 | K34: ARS | L34: 6268344 | M34: 1 | N34: 0.21 | O34: 7584696.2
A35: 45931 | B35: 1 | C35: RECEPCION DE RESIDUOS LIQUIDOS | D35: DISP FINAL RESIDUOS LIQUIDOS | E35: CERTIFICADO DISP FINAL LIQUIDOS | F35: Rosario Bio Energy S.A. | H35: TN | I35: 304.18 | J35: 6800 | K35: ARS | L35: 2068424 | M35: 1 | N35: 0.21 | O35: 2502793
A36: 45931 | B36: 1 | C36: RECEPCION DE RESIDUOS LIQUIDOS | D36: DISP FINAL RESIDUOS LIQUIDOS | E36: CERTIFICADO DISP FINAL LIQUIDOS | F36: Santa Fe Aceites S.R.L. | H36: TN | I36: 3937.74 | J36: 3937 | K36: ARS | L36: 15502882 | M36: 1 | N36: 0.21 | O36: 18758488
... A50: 45931 | B50: 1 | C50: TRATAMIENTO DE RESIDUOS SOLIDOS | D50: COMPOST_Y_FERTILIZANTES | E50: COMPOST | F50: Zamparo | H50: KG | I50: 3840 | J50: 91.79 | K50: ARS | L50: 352473.6 | M50: 1 | N50: 0.21 | O50: 426493.06

Sheet ingresos_produccion
A1: FECHA CARGA | B1: CANAL | C1: AREA | D1: SECTOR | E1: PRODUCTO | F1: CLIENTE | G1: DESCRIPCION | H1: UM | I1: Q | J1: PRECIO | K1: MONEDA | L1: SUBTOTAL | M1: T.C | N1: IVA | O1: TOTAL | P1: Fuente
A2: 45961 | B2: 1 | C2: EXPORTACION | D2: EXPORTACION | E2: AG - E | F2: PARAGUAY LOGISTIC | G2: EGRESOS | H2: TN | I2: 0 | J2: 172 | K2: USD | L2: 0 | M2: 1464 | N2: 0 | O2: 0
A3: 45961 | B3: 1 | C3: EXPORTACION | D3: EXPORTACION | E3: AG - E | F3: EGNITRADE | G3: EGRESOS | H3: TN | I3: 2824.1 | J3: 1072 | K3: USD | L3: 3027830.6 | M3: 1464 | N3: 0 | O3: 4.432744e+09 | P3: 116 cam
A4: 45961 | B4: 1 | C4: EXPORTACION | D4: EXPORTACION | E4: ARE (AN) | F4: SWIFT | G4: EGRESOS | H4: TN | I4: 58.48 | J4: 760 | K4: USD | L4: 44444.8 | M4: 1464 | N4: 0 | O4: 65067187 | P4: 2 CAM
A5: 45961 | B5: 1 | C5: EXPORTACION | D5: EXPORTACION | E5: ARE (AN)/SEBO 2DA A | F5: MILO | G5: EGRESOS | H5: TN | I5: 74.8 | K5: USD | L5: 0 | M5: 1464 | N5: 0 | O5: 0 | P5: 4 CAM
A6: 45961 | B6: 1 | C6: TRATAMIENTO DE RESIDUOS LIQUIDOS | D6: REACTORES | E6: ARE(V) - B | F6: MILO | G6: EGRESOS | H6: TN | I6: 193.86 | J6: 83 | K6: USD | L6: 16090.38 | M6: 1464 | N6: 0 | O6: 23556316 | P6: 8 CAM
A7: 45961 | B7: 2 | C7: TRATAMIENTO DE RESIDUOS LIQUIDOS | D7: REACTORES | E7: ARE (V) -A | F7: WORMS | G7: PRODUCCION | H7: TN | J7: 820 | K7: USD | L7: 0 | M7: 1464 | N7: 0 | O7: 0
A8: 45961 | B8: 2 | C8: TRATAMIENTO DE RESIDUOS LIQUIDOS | D8: REACTORES | E8: ARE (V) -B | F8: WORMS | G8: PRODUCCION | H8: TN | I8: 83 | J8: 820 | K8: USD | L8: 68060 | M8: 1464 | N8: 0 | O8: 99639840
A9: 45961 | B9: 2 | C9: TRATAMIENTO DE RESIDUOS LIQUIDOS | D9: REACTORES | E9: ARE (V) -A | F9: WORMS 2 | G9: FASON | H9: TN | J9: 90 | K9: USD | L9: 0 | M9: 1464 | N9: 0 | O9: 0
A10: 45961 | B10: 2 | C10: TRATAMIENTO DE RESIDUOS LIQUIDOS | D10: REACTORES | E10: ARE (V) -B | F10: WORMS 2 | G10: FASON | H10: TN | J10: 90 | K10: USD | L10: 0 | M10: 1464 | N10: 0 | O10: 0
A11: 45961 | B11: 2 | C11: TRATAMIENTO DE RESIDUOS LIQUIDOS | D11: REACTORES | E11: ARE (AN) | F11: WORMS 2 | G11: FASON | H11: TN | J11: 90 | K11: USD | L11: 0 | M11: 1464 | N11: 0 | O11: 0
A12: 45961 | B12: 2 | C12: TRATAMIENTO DE RESIDUOS LIQUIDOS | D12: REACTORES | E12: ARE (AN) | F12: WORMS | G12: PRODUCCION | H12: TN | J12: 760 | K12: USD | L12: 0 | M12: 1464 | N12: 0 | O12: 0
A13: 45961 | B13: 1 | C13: TRATAMIENTO DE RESIDUOS LIQUIDOS | D13: PILETAS | E13: AG - C | F13: BAHIA | G13: EGRESOS | H13: TN | I13: 29.5 | J13: 740 | K13: USD | L13: 21830 | M13: 1464 | N13: 0 | O13: 31959120 | P13: 1 CAM
A14: 45961 | B14: 1 | C14: TRATAMIENTO DE RESIDUOS LIQUIDOS | D14: PILETAS | E14: AG - C | F14: STA FE ACEITES | G14: EGRESOS | H14: TN | I14: 26.84 | J14: 740 | K14: USD | L14: 19861.6 | M14: 1464 | N14: 0 | O14: 29077382 | P14: 1 CAM
A15: 45961 | B15: 2 | C15: TRATAMIENTO DE RESIDUOS LIQUIDOS | D15: PILETAS | E15: AG - A | F15: WORMS | G15: RECUPERADO AG DE PILETAS | H15: TN | I15: 0 | J15: 850 | K15: USD | L15: 0 | M15: 1464 | N15: 0 | O15: 0
A16: 45961 | B16: 2 | C16: TRATAMIENTO DE RESIDUOS LIQUIDOS | D16: PILETAS | E16: AG - B | F16: WORMS | G16: RECUPERADO AG DE PILETAS | H16: TN | I16: 32.16 | J16: 820 | K16: USD | L16: 26371.2 | M16: 1464 | N16: 0 | O16: 38607437
A17: 45961 | B17: 2 | C17: TRATAMIENTO DE RESIDUOS LIQUIDOS | D17: PILETAS | E17: AG - C | F17: WORMS | G17: RECUPERADO AG DE PILETAS | H17: TN | I17: 461.12 | J17: 740 | K17: USD | L17: 341228.8 | M17: 1464 | N17: 0 | O17: 4.9955896e+08
A18: 45961 | B18: 2 | C18: TRATAMIENTO DE RESIDUOS LIQUIDOS | D18: PILETAS | E18: AG - D | F18: WORMS | G18: RECUPERADO AG DE PILETAS | H18: TN | I18: 44.49 | J18: 500 | K18: USD | L18: 22245 | M18: 1464 | N18: 0 | O18: 32566680
A19: 45961 | B19: 2 | C19: TRATAMIENTO DE RESIDUOS LIQUIDOS | D19: PILETAS | E19: EMULSION | F19: WORMS | G19: RECUPERADO EMUL DE PILETAS | H19: TN | I19: 50.26 | J19: 500 | K19: USD | L19: 25130 | M19: 1464 | N19: 0 | O19: 36790320
A20: 45961 | B20: 1 | C20: TRATAMIENTO DE RESIDUOS LIQUIDOS | D20: BACHAS | E20: AG (PES) | F20: DABID ABBIAD | G20: EGRESOS | H20: TN | I20: 25.96 | K20: USD | L20: 0 | M20: 1464 | N20: 0 | O20: 0 | P20: 1 CAM
A21: 45961 | B21: 2 | C21: TRATAMIENTO DE RESIDUOS LIQUIDOS | D21: BACHAS | E21: AG - C | F21: WORMS | G21: PRODUCCION | H21: TN | I21: 80.96 | J21: 740 | K21: USD | L21: 59910.4 | M21: 1464 | N21: 0 | O21: 87708826
A22: 45961 | B22: 2 | C22: TRATAMIENTO DE RESIDUOS LIQUIDOS | D22: BACHAS | E22: AG - C | F22: WORMS 2 | G22: FASON DE BORRAS DE TERCEROS | H22: TN | I22: 31.6 | J22: 740 | K22: USD | L22: 23384 | M22: 1464 | N22: 0 | O22: 34234176
A23: 45961 | B23: 2 | C23: TRATAMIENTO DE RESIDUOS LIQUIDOS | D23: BACHAS | E23: SEBO 2DA - C | F23: WORMS 2 | G23: FASON DE BORRAS DE TERCEROS | H23: TN | I23: 7.1 | K23: USD | L23: 0 | M23: 1464 | N23: 0 | O23: 0
A24: 45961 | B24: 2 | C24: TRATAMIENTO DE RESIDUOS LIQUIDOS | D24: BACHAS | E24: ACEITE PESCADO | F24: WORMS | G24: PRODUCCION | H24: TN | I24: 9.14 | K24: USD | L24: 0 | M24: 1464 | N24: 0 | O24: 0
A25: 45961 | B25: 2 | C25: TRATAMIENTO DE RESIDUOS LIQUIDOS | D25: BACHAS | E25: ACEITE PESCADO | F25: D ABIAD | G25: FASON DE BORRAS DE TERCEROS | H25: TN | I25: 41.18 | K25: USD | L25: 0 | M25: 1464 | N25: 0 | O25: 0
A26: 45961 | B26: 1 | C26: TRATAMIENTO DE RESIDUOS SOLIDOS | D26: NFU | E26: GRANULADO DE CAUCHO 1 - P1 | F26: WORMS | G26: PRODUCCION | H26: TN | I26: 47.08 | J26: 850 | K26: USD | L26: 40018 | M26: 1464 | N26: 0 | O26: 58586352
A27: 45961 | B27: 1 | C27: TRATAMIENTO DE RESIDUOS SOLIDOS | D27: NFU | E27: GRANULADO DE CAUCHO 2- P1 | F27: WORMS | G27: PRODUCCION | H27: TN | I27: 76.4 | J27: 650 | K27: USD | L27: 49660 | M27: 1464 | N27: 0 | O27: 72702240
A28: 45961 | B28: 1 | C28: TRATAMIENTO DE RESIDUOS SOLIDOS | D28: NFU | E28: GRANULADO DE CAUCHO 3 - P1 | F28: WORMS | G28: PRODUCCION | H28: TN | I28: 87.52 | J28: 450 | K28: USD | L28: 39384 | M28: 1464 | N28: 0 | O28: 57658176
A29: 45961 | B29: 1 | C29: TRATAMIENTO DE RESIDUOS SOLIDOS | D29: NFU | E29: ACERO | F29: WORMS | G29: PRODUCCION | H29: TN | I29: 110.7 | J29: 90000 | K29: ARG | L29: 9963000 | M29: 1464 | N29: 0 | O29: 14585832000
A30: 45961 | B30: 2 | C30: TRATAMIENTO DE RESIDUOS LIQUIDOS | D30: SALES | E30: GLICERINA -FE | F30: WORMS | G30: PRODUCCION | H30: TN | K30: USD | L30: 0 | M30: 1464 | N30: 0 | O30: 0

Sheet gastos_rrhh
A1: Fecha de Factura/Recibo | B1: Nombre de la empresa a mostrar en la factura | C1: Número | D1: Total con signo | E1: Líneas de factura/Etiqueta | F1: Líneas de factura/Cantidad | G1: Líneas de factura/Precio unitario | H1: Líneas de factura/Unidad de medida | I1: Líneas de factura/Producto | J1: Concepto | K1: Tipo de Gasto 1 | L1: Tipo de Gasto 2 | M1: CCO EMPRESA | N1: CCO - SECTOR
A2: 45931 | B2: WORMS-RRHH | C2: MAIDANA, JOSE RAMON | D2: -2078949.5 | E2: INTENDENCIA | F2: 1 | G2: 2078949.5 | H2: #RRHH | I2: PERSONAL | J2: Opex | K2: Fijo | L2: Indirecto | N2: CC27
A3: 45931 | B3: WORMS-RRHH | C3: PEREZ, MATIAS ROMAN | D3: -5104642.3 | E3: INTENDENCIA | F3: 1 | G3: 5104642.3 | H3: #RRHH | I3: PERSONAL | J3: Opex | K3: Fijo | L3: Indirecto | N3: CC27
A4: 45931 | B4: WORMS-RRHH | C4: PANZANELLA, EDUARDO JAVIER | D4: -2117008.3 | E4: PORTERIA | F4: 1 | G4: 2117008.3 | H4: #RRHH | I4: PERSONAL | J4: Opex | K4: Fijo | L4: Indirecto | N4: CC22
A5: 45931 | B5: WORMS-RRHH | C5: ENRIQUEZ, MAXIMO GUSTAVO | D5: -2067002 | E5: DISPOSICION FINAL DE R. LIQUIDOS | F5: 1 | G5: 2067002 | H5: #RRHH | I5: PERSONAL | J5: Opex | K5: Variable | L5: Directo | N5: CC25
A6: 45931 | B6: WORMS-RRHH | C6: PORCU, MIGUEL ANGEL | D6: -1085682.2 | E6: PILETAS | F6: 1 | G6: 1085682.2 | H6: #RRHH | I6: PERSONAL | J6: Opex | K6: Variable | L6: Directo | N6: CC21
A7: 45931 | B7: WORMS-RRHH | C7: PETERS CORZO, JOSE LUIS | D7: -2513045.7 | E7: LABORATORIO | F7: 1 | G7: 2513045.7 | H7: #RRHH | I7: PERSONAL | J7: Opex | K7: Fijo | L7: Indirecto | N7: CC17
A8: 45931 | B8: WORMS-RRHH | C8: ALTAMIRANO, GUSTAVO | D8: -2156572.8 | E8: NFU | F8: 1 | G8: 2156572.8 | H8: #RRHH | I8: PERSONAL | J8: Opex | K8: Variable | L8: Directo | N8: CC20
A9: 45931 | B9: WORMS-RRHH | C9: MARTINEZ, FRANCO ALBERTO | D9: -1290098.8 | E9: CAT | F9: 1 | G9: 1290098.8 | H9: #RRHH | I9: PERSONAL | J9: Opex | K9: Variable | L9: Directo | N9: CC7
A10: 45931 | B10: WORMS-RRHH | C10: PARDEL, MAURO | D10: -2430242.5 | E10: PORTERIA | F10: 1 | G10: 2430242.5 | H10: #RRHH | I10: PERSONAL | J10: Opex | K10: Fijo | L10: Indirecto | N10: CC22
A11: 45931 | B11: WORMS-RRHH | C11: MONTENEGRO, GUSTAVO | D11: -2174118.9 | E11: INTENDENCIA | F11: 1 | G11: 2174118.9 | H11: #RRHH | I11: PERSONAL | J11: Opex | K11: Fijo | L11: Indirecto | N11: CC27
A12: 45931 | B12: WORMS-RRHH | C12: CEBALLEZ, MARIA EUGENIA | D12: -5514943.3 | E12: PRODUCCION | F12: 1 | G12: 5514943.3 | H12: #RRHH | I12: PERSONAL | J12: Opex | K12: Fijo | L12: Indirecto | N12: CC28
A13: 45931 | B13: WORMS-RRHH | C13: LOPEZ CAMARGO BERLITZ, BEATRIZ | D13: -2756590.4 | E13: LABORATORIO | F13: 1 | G13: 2756590.4 | H13: #RRHH | I13: PERSONAL | J13: Opex | K13: Fijo | L13: Indirecto | N13: CC17
... A104: 45931 | B104: WORMS-RRHH | C104: ADROVER, JUAN HORACIO | D104: -1876296.3 | E104: TALLER MECANICO | F104: 15 | G104: 1876296.3 | H104: #RRHH | I104: PERSONAL | J104: Opex | K104: Fijo | L104: Indirecto | N104: CC23

Sheet gastos_impuestos
A1: Fecha de Factura/Recibo | B1: Nombre de la empresa a mostrar en la factura | C1: Número | D1: Total con signo | E1: Líneas de factura/Etiqueta | F1: Líneas de factura/Cantidad | G1: Líneas de factura/Precio unitario | H1: Líneas de factura/Unidad de medida | I1: Líneas de factura/Producto | J1: Concepto | K1: Tipo de Gasto 1 | L1: Tipo de Gasto 2 | M1: CCO EMPRESA | N1: CCO - SECTOR | O1: TC
A2: 45931 | B2: GANANCIAS EXPORTACION | C2: AD_10-2025 | D2: -2067241.2 | E2: IMPUESTOS | F2: 2824.1 | G2: 0.5 | H2: UN | I2: IMPUESTOS | J2: OPEX | K2: VARIABLE | L2: DIRECTO | N2: CC11 | O2: 1464
A3: 45960 | B3: GASTOS BANCARIOS | C3: OCOM/2025/10 | D3: -6924925.3 | E3: IMPUESTOS | F3: 1 | G3: 6924925.3 | H3: UN | I3: IMPUESTOS | J3: OPEX | K3: VARIABLE | L3: INDIRECTO | N3: CC1
A4: 45960 | B4: IB | C4: OCOM/2025/10 | D4: -32811.49 | E4: IMPUESTOS | F4: 1 | G4: 32811.49 | H4: UN | I4: IMPUESTOS | J4: OPEX | K4: VARIABLE | L4: INDIRECTO | N4: CC1
A5: 45960 | B5: DREI DISPOSICIÓN FINAL RESIDUOS LIQUIDOS | C5: OCOM/2025/10 | D5: -656141 | E5: IMPUESTOS | F5: 1 | G5: 656141 | H5: UN | I5: IMPUESTOS | J5: OPEX | K5: VARIABLE | L5: INDIRECTO | N5: CC3
A6: 45960 | B6: DREI COMPOST & FERTILIZANTES | C6: OCOM/2025/10 | D6: -485805 | E6: IMPUESTOS | F6: 1 | G6: 485805 | H6: UN | I6: IMPUESTOS | J6: OPEX | K6: VARIABLE | L6: INDIRECTO | N6: CC8
A7: 45960 | B7: DREI PILETAS | C7: OCOM/2025/10 | D7: -374523 | E7: IMPUESTOS | F7: 1 | G7: 374523 | H7: UN | I7: IMPUESTOS | J7: OPEX | K7: VARIABLE | L7: INDIRECTO | N7: CC4
A8: 45960 | B8: DREI NFU | C8: OCOM/2025/10 | D8: -386033 | E8: IMPUESTOS | F8: 1 | G8: 386033 | H8: UN | I8: IMPUESTOS | J8: OPEX | K8: VARIABLE | L8: INDIRECTO | N8: CC7

Sheet gastos_produccion
A1: Fecha de Factura/Recibo | B1: Nombre de la empresa a mostrar en la factura | C1: Número | D1: Total con signo | E1: Líneas de factura/Etiqueta | F1: Líneas de factura/Cantidad | G1: Líneas de factura/Precio unitario | H1: Líneas de factura/Unidad de medida | I1: Líneas de factura/Producto | J1: Concepto | K1: Tipo de Gasto 1 | L1: Tipo de Gasto 2 | M1: CCO EMPRESA | N1: CCO - SECTOR | O1: USD | P1: SECTOR | Q1: Column17 | R1: Column18
A2: 45961 | B2: WORMS 2 | C2: MT-0001 | D2: -90094560 | E2: AFE (AL) | F2: 72.4 | G2: 850 | H2: TN | I2: MATERIA PRIMA | J2: OPEX | K2: VARIABLE | L2: DIRECTO | N2: CC11 | O2: 1464 | P2: EXPORTACION
A3: 45961 | B3: WORMS 2 | C3: MT-0002 | D3: -5861856 | E3: AFE (G) | F3: 4.4 | G3: 910 | H3: TN | I3: MATERIA PRIMA | J3: OPEX | K3: VARIABLE | L3: DIRECTO | N3: CC11 | O3: 1464 | P3: EXPORTACION
A4: 45961 | B4: WORMS 2 | C4: MT-0003 | D4: -59830752 | E4: AFE (P) | F4: 60.1 | G4: 680 | H4: TN | I4: MATERIA PRIMA | J4: OPEX | K4: VARIABLE | L4: DIRECTO | N4: CC11 | O4: 1464 | P4: EXPORTACION
A5: 45961 | B5: WORMS 2 | C5: MT-0004 | D5: -3029264148 | E5: AFE (S) | F5: 2236.94 | G5: 925 | H5: TN | I5: MATERIA PRIMA | J5: OPEX | K5: VARIABLE | L5: DIRECTO | N5: CC11 | O5: 1464 | P5: EXPORTACION
A6: 45961 | B6: WORMS 1 | C6: MT-0005 | D6: 0 | E6: AG- A | G6: 850 | H6: TN | I6: MATERIA PRIMA | J6: OPEX | K6: VARIABLE | L6: DIRECTO | N6: CC11 | O6: 1464 | P6: EXPORTACION
A7: 45961 | B7: WORMS 1 | C7: MT-0006 | D7: -24537811 | E7: AG- B | F7: 20.44 | G7: 820 | H7: TN | I7: MATERIA PRIMA | J7: OPEX | K7: VARIABLE | L7: DIRECTO | N7: CC11 | O7: 1464 | P7: EXPORTACION
A8: 45961 | B8: WORMS 1 | C8: MT-0007 | D8: -12127190 | E8: AG- C | F8: 15.34 | G8: 540 | H8: TN | I8: MATERIA PRIMA | J8: OPEX | K8: VARIABLE | L8: DIRECTO | N8: CC11 | O8: 1464 | P8: EXPORTACION
A9: 45961 | B9: WORMS 1 | C9: MT-0008 | D9: 0 | E9: ARE- A | G9: 820 | H9: TN | I9: MATERIA PRIMA | J9: OPEX | K9: VARIABLE | L9: DIRECTO | N9: CC11 | O9: 1464 | P9: EXPORTACION
A10: 45961 | B10: WORMS 1 | C10: MT-0009 | D10: 0 | E10: ARE- B | G10: 820 | H10: TN | I10: MATERIA PRIMA | J10: OPEX | K10: VARIABLE | L10: DIRECTO | N10: CC11 | O10: 1464 | P10: EXPORTACION
A11: 45961 | B11: WORMS 2 | C11: MT-0010 | D11: -246338496 | E11: ARE- A | F11: 205.2 | G11: 820 | H11: TN | I11: MATERIA PRIMA | J11: OPEX | K11: VARIABLE | L11: DIRECTO | N11: CC11 | O11: 1464 | P11: EXPORTACION
A12: 45961 | B12: WORMS 2 | C12: MT-0011 | D12: 0 | E12: ARE- B | G12: 820 | H12: TN | I12: MATERIA PRIMA | J12: OPEX | K12: VARIABLE | L12: DIRECTO | N12: CC11 | O12: 1464 | P12: EXPORTACION
A13: 45961 | B13: WORMS 2 | C13: MT-0012 | D13: -117570912 | E13: AG- A | F13: 94.48 | G13: 850 | H13: TN | I13: MATERIA PRIMA | J13: OPEX | K13: VARIABLE | L13: DIRECTO | N13: CC11 | O13: 1464 | P13: EXPORTACION
A14: 45961 | B14: WORMS 2 | C14: MT-0013 | D14: 0 | E14: AG- B | G14: 820 | H14: TN | I14: MATERIA PRIMA | J14: OPEX | K14: VARIABLE | L14: DIRECTO | N14: CC11 | O14: 1464 | P14: EXPORTACION
A15: 45961 | B15: WORMS 2 | C15: MT-0014 | D15: -8300880 | E15: AG- C | F15: 10.5 | G15: 540 | H15: TN | I15: MATERIA PRIMA | J15: OPEX | K15: VARIABLE | L15: DIRECTO | N15: CC11 | O15: 1464 | P15: EXPORTACION
A16: 45961 | B16: WORMS 2 | C16: MT-0021 | D16: -91072512 | E16: AG- C | F16: 115.2 | G16: 540 | H16: TN | I16: MATERIA PRIMA | J16: OPEX | K16: VARIABLE | L16: DIRECTO | N16: CC5 | O16: 1464 | P16: REACTORES
A17: 45961 | B17: WORMS 1 | C17: MT-0022 | D17: 0 | E17: AG- C | G17: 540 | H17: TN | I17: MATERIA PRIMA | J17: OPEX | K17: VARIABLE | L17: DIRECTO | N17: CC5 | O17: 1464 | P17: REACTORES
A18: 45961 | B18: WORMS 2 | C18: MT-0023 | D18: -1.6548757e+08 | E18: AG - E | F18: 124.32 | G18: 909.25 | H18: TN | I18: MATERIA PRIMA | J18: OPEX | K18: VARIABLE | L18: DIRECTO | N18: CC11 | O18: 1464 | P18: EXPORTACION
A19: 45961 | B19: WORMS 2 | C19: MT-0024 | D19: 0 | E19: SEBO C - 2da | G19: 760 | H19: TN | I19: MATERIA PRIMA | J19: OPEX | K19: VARIABLE | L19: DIRECTO | N19: CC5 | O19: 1464 | P19: REACTORES
A20: 45961 | B20: WORMS 2 | C20: MT-0025 | D20: 0 | E20: BORRA A VEGETAL | F20: 126.22 | H20: TN | I20: MATERIA PRIMA | J20: OPEX | K20: VARIABLE | L20: DIRECTO | N20: CC6 | O20: 1464 | P20: BACHAS
A21: 45961 | B21: WORMS 2 | C21: MT-0026 | D21: 0 | E21: FONDO TK | F21: 22.2 | H21: TN | I21: MATERIA PRIMA | J21: OPEX | K21: VARIABLE | L21: DIRECTO | N21: CC6 | O21: 1464 | P21: BACHAS
A22: 45961 | B22: WORMS 2 | C22: MT-0027 | D22: 0 | E22: BORRA ANIMAL | F22: 34.1 | H22: TN | I22: MATERIA PRIMA | J22: OPEX | K22: VARIABLE | L22: DIRECTO | N22: CC6 | O22: 1464 | P22: BACHAS
A23: 45961 | B23: WORMS 2 | C23: MT-0028 | D23: 0 | E23: BORRA PESCADO | F23: 86.28 | H23: TN | I23: MATERIA PRIMA | J23: OPEX | K23: VARIABLE | L23: DIRECTO | N23: CC6 | O23: 1464 | P23: BACHAS
A24: 45961 | B24: WORMS 1 | C24: MT-0029 | D24: -26088480 | E24: EMULSION | F24: 35.64 | G24: 500 | H24: TN | I24: MATERIA PRIMA | J24: OPEX | K24: VARIABLE | L24: DIRECTO | N24: CC6 | O24: 1464 | P24: BACHAS
A25: 45961 | B25: WORMS 1 | C25: MT-0030 | D25: -60214320 | E25: AG-D | F25: 82.26 | G25: 500 | H25: TN | I25: MATERIA PRIMA | J25: OPEX | K25: VARIABLE | L25: DIRECTO | N25: CC6 | O25: 1464 | P25: BACHAS
A26: 45961 | B26: Martins, Joaquin | C26: AD-0001 | D26: 0 | E26: ENERGIA GASOIL G3 | G26: 1754 | H26: Lts | I26: ENERGIA | J26: OPEX | K26: VARIABLE | L26: DIRECTO | N26: CC1 | O26: 1 | P26: GENERAL
A27: 45961 | B27: Martins, Joaquin | C27: AD-0001 | D27: -2679040 | E27: ENERGIA G2 | F27: 1820 | G27: 1472 | H27: Lts | I27: ENERGIA | J27: OPEX | K27: VARIABLE | L27: DIRECTO | N27: CC6 | O27: 1 | P27: BACHAS
A28: 45961 | B28: Martins, Joaquin | C28: AD-0001 | D28: 0 | E28: ENERGIA G2 | F28: 0 | G28: 1472 | H28: Lts | I28: ENERGIA | J28: OPEX | K28: VARIABLE | L28: DIRECTO | N28: CC5 | O28: 1 | P28: REACTORES
A29: 45961 | B29: Martins, Joaquin | C29: AD-0001 | D29: -149500 | E29: ENERGIA Nafta | F29: 100 | G29: 1495 | H29: Lts | I29: ENERGIA | J29: OPEX | K29: VARIABLE | L29: DIRECTO | N29: CC6 | O29: 1 | P29: BACHAS
A30: 45961 | B30: Martins, Joaquin | C30: AD-0001 | D30: -1644500 | E30: ENERGIA Nafta | F30: 1100 | G30: 1495 | H30: Lts | I30: ENERGIA | J30: OPEX | K30: VARIABLE | L30: DIRECTO | N30: CC4 | O30: 1 | P30: PILETAS
A31: 45961 | B31: Martins, Joaquin | C31: AD-0001 | D31: -448500 | E31: ENERGIA Nafta | F31: 300 | G31: 1495 | H31: Lts | I31: ENERGIA | J31: OPEX | K31: VARIABLE | L31: DIRECTO | N31: CC3 | O31: 1 | P31: DISP FINAL RESIDUOS LIQUIDOS
A32: 45961 | B32: Ultraonix Srl | C32: AD-0001 | D32: -17241774 | E32: ENERGIA Fuel Oil | F32: 28050 | G32: 614.68 | H32: KG | I32: ENERGIA | J32: OPEX | K32: VARIABLE | L32: DIRECTO | N32: CC5 | O32: 1 | P32: REACTORES
A33: 45961 | B33: Ultraonix Srl | C33: AD-0001 | D33: -5808726 | E33: ENERGIA Fuel Oil | F33: 9450 | G33: 614.68 | H33: KG | I33: ENERGIA | J33: OPEX | K33: VARIABLE | L33: DIRECTO | N33: CC6 | O33: 1 | P33: BACHAS
A34: 45961 | B34: Total Quimica S.A. | C34: AD-0001 | D34: -7342440.6 | E34: INSUMOS Acido Sulfúrico 70/80 | F34: 19860 | G34: 369.71 | H34: KG | I34: INSUMOS | J34: OPEX | K34: VARIABLE | L34: DIRECTO | N34: CC6 | O34: 1 | P34: BACHAS
A35: 45961 | B35: Total Quimica S.A. | C35: AD-0001 | D35: -547520 | E35: INSUMOS Acido Clorhidrico | F35: 1180 | G35: 464 | H35: KG | I35: INSUMOS | J35: OPEX | K35: VARIABLE | L35: DIRECTO | N35: CC6 | O35: 1 | P35: BACHAS
A36: 45961 | B36: Total Quimica S.A. | C36: AD-0001 | D36: -691147.5 | E36: INSUMOS Soda Caustica | F36: 750 | G36: 921.53 | H36: KG | I36: INSUMOS | J36: OPEX | K36: VARIABLE | L36: DIRECTO | N36: CC5 | O36: 1 | P36: REACTORES
A37: 45961 | B37: Salinera Jaisal S. A. | C37: AD-0001 | D37: -59774 | E37: INSUMOS Cloruro de Sodio (SAL) | F37: 520 | G37: 114.95 | H37: KG | I37: INSUMOS | J37: OPEX | K37: VARIABLE | L37: DIRECTO | N37: CC6 | O37: 1 | P37: BACHAS
A38: 45961 | B38: Cremer Y Asociados Sociedad Anonima | C38: AD-0001 | D38: -11525588 | E38: INSUMOS Glicerina cruda | F38: 28.75 | G38: 400890 | H38: TN | I38: INSUMOS | J38: OPEX | K38: VARIABLE | L38: DIRECTO | N38: CC5 | O38: 1 | P38: REACTORES
... A40: 45961 | B40: Mercomar SA | C40: AD-0001 | D40: 0 | E40: LOGISTICA | F40: 852.25 | G40: 0 | H40: TN | I40: SERVICIOS | J40: OPEX | K40: VARIABLE | L40: DIRECTO | N40: CC11 | O40: 0 | P40: EXPORTACION
A41: 45961 | B41: Transportes Padilla Sociedad Anonima | C41: AD-0001 | D41: -27700560 | E41: LOGISTICA | F41: 876.6 | G41: 31600 | H41: TN | I41: SERVICIOS | J41: OPEX | K41: VARIABLE | L41: DIRECTO | N41: CC11 | O41: 1 | P41: EXPORTACION | R41: 220
A42: 45961 | B42: Cronos Soluciones Sustentables Sa | C42: AD-0001 | D42: -11261875 | E42: LOGISTICA | F42: 608.75 | G42: 18500 | H42: TN | I42: LOGISTICA | J42: OPEX | K42: VARIABLE | L42: DIRECTO | N42: CC11 | O42: 1 | P42: EXPORTACION
A43: 45961 | B43: Transporte Automotor El Loco Srl | C43: AD-0001 | D43: -1850600 | E43: LOGISTICA | F43: 97.4 | G43: 19000 | H43: TN | I43: LOGISTICA | J43: OPEX | K43: VARIABLE | L43: DIRECTO | N43: CC11 | O43: 1 | P43: EXPORTACION
A44: 45961 | B44: Energia Del Sur Srl | C44: AD-0001 | D44: -1461000 | E44: LOGISTICA | F44: 97.4 | G44: 15000 | H44: TN | I44: LOGISTICA | J44: OPEX | K44: VARIABLE | L44: DIRECTO | N44: CC11 | O44: 1 | P44: EXPORTACION
A45: 45961 | B45: Duport Sociedad De Responsabilidad Limitada | C45: AD-0001 | D45: -3798600 | E45: LOGISTICA | F45: 194.8 | G45: 19500 | H45: TN | I45: LOGISTICA | J45: OPEX | K45: VARIABLE | L45: DIRECTO | N45: CC11 | O45: 1 | P45: EXPORTACION
A46: 45961 | B46: Cooperativa De Trabajo Comercio Exterior Limitada | C46: AD-0001 | D46: -35141856 | E46: LOGISTICA | F46: 2824 | G46: 8.5 | H46: TN | I46: LOGISTICA | J46: OPEX | K46: VARIABLE | L46: DIRECTO | N46: CC11 | O46: 1464 | P46: EXPORTACION
A47: 45961 | B47: Exolgan Sociedad Anonima | C47: AD-0001 | D47: -21109140 | E47: LOGISTICA | F47: 36 | G47: 586365 | H47: UN | I47: SERVICIOS | J47: OPEX | K47: VARIABLE | L47: DIRECTO | N47: CC11 | O47: 1 | P47: EXPORTACION
A48: 45961 | B48: Pigini, Norberto Omar Marino | C48: AD-0001 | D48: -6030000 | E48: LOGISTICA | F48: 9 | G48: 670000 | H48: UN | I48: LOGISTICA | J48: OPEX | K48: VARIABLE | L48: DIRECTO | N48: CC7 | O48: 1 | P48: NFU
A49: 45961 | B49: Bernis, Carlos Oscar | C49: AD-0001 | D49: -4000000 | E49: LOGISTICA | F49: 5 | G49: 800000 | H49: UN | I49: LOGISTICA | J49: OPEX | K49: VARIABLE | L49: DIRECTO | N49: CC7 | O49: 1 | P49: NFU
A50: 45961 | B50: Bunge Argentina S A | C50: AD-0001 | D50: -97514 | E50: MATERIA PRIMA | F50: 975140 | G50: 0.1 | H50: UN | I50: MATERIA PRIMA | J50: OPEX | K50: VARIABLE | L50: DIRECTO | N50: CC2 | O50: 1 | P50: DISPOSICIÓN FINAL RESIDUOS SOLIDOS
A51: 45961 | B51: WORMS 2 | D51: 0 | E51: AFE (SG) | F51: 173.32 | H51: TN | I51: MATERIA PRIMA | J51: OPEX | K51: VARIABLE | L51: DIRECTO | N51: NO | O51: 1464 | P51: REACTORES
A52: 45961 | B52: WORMS 2 | D52: 0 | E52: AFE (P) | F52: 18.36 | H52: TN | I52: MATERIA PRIMA | J52: OPEX | K52: VARIABLE | L52: DIRECTO | N52: NO | O52: 1464 | P52: REACTORES

Sheet gastos_facturas
A1: Fecha de Factura/Recibo | B1: Nombre de la empresa a mostrar en la factura | C1: Número | D1: Total con signo | E1: Líneas de factura/Etiqueta | F1: Líneas de factura/Cantidad | G1: Líneas de factura/Precio unitario | H1: Líneas de factura/Unidad de medida | I1: Líneas de factura/Producto | J1: Concepto | K1: Tipo de Gasto 1 | L1: Tipo de Gasto 2 | M1: CCO EMPRESA | N1: CCO - SECTOR | O1: Column15
A2: 45958 | B2: H.S.E. Ingenieria S R L | C2: FA-A 00003-00027849 | D2: -3315400 | E2: OC 0001-00001756: SERVICIOS Monitoreo | F2: 1 | G2: 2740000 | H2: UN | I2: SERVICIOS | J2: OPEX | K2: VARIABLE | L2: INDIRECTO | N2: CC1
A3: 45933 | B3: Alvarez, Alejandro Dario | C3: FA-C 00002-00000250 | D3: -509644 | E3: OC 0001-00001364: HIGIENE Y SEGURIDAD Servicio de asesoramiento para la gestión ambiental en el cumplimiento de la normativa vigente para la provincia de Santa Fe. Servicio de higiene y seguridad de trabajo con cumplimiento de actividades s/Resol. SRT 905/15- MES 09/2025 | F3: 1 | G3: 509644 | H3: UN | I3: HIGIENE Y SEGURIDAD | J3: OPEX | K3: FIJO | L3: DIRECTO | N3: CC1
A4: 45931 | B4: Quiroz, Maria Ines | C4: FA-C 00002-00000031 | D4: -2097200 | E4: OC 0001-00001801: PERSONAL horas soldador | F4: 1 | G4: 2097200 | H4: UN | I4: PERSONAL | J4: OPEX | K4: FIJO | L4: INDIRECTO | N4: CC1
A5: 45947 | B5: Lopez, Jesus Rodrigo | C5: OCOM/2025/0470 | D5: -180000 | E5: OC 0001-00001345: LOGISTICA puerto | F5: 1 | G5: 180000 | H5: UN | I5: LOGISTICA | J5: OPEX | K5: VARIABLE | L5: DIRECTO | N5: CC9
A6: 45938 | B6: Lopez, Jesus Rodrigo | C6: OCOM/2025/0458 | D6: -180000 | E6: OC 0001-00001804: LOGISTICA | F6: 1 | G6: 180000 | H6: UN | I6: LOGISTICA | J6: OPEX | K6: VARIABLE | L6: DIRECTO | N6: CC9
A7: 45931 | B7: Lopez, Jesus Rodrigo | C7: OCOM/2025/0443 | D7: -156000 | E7: OC 0001-00000944: LOGISTICA | F7: 1 | G7: 156000 | H7: UN | I7: LOGISTICA | J7: OPEX | K7: VARIABLE | L7: DIRECTO | N7: CC9
A8: 45950 | B8: Area Abierta S.A. | C8: FA-A 00001-00001146 | D8: -798367.68 | E8: OC 0001-00001924: REPOSICION paño zda luz 6.50 2.50 mm 4 x1,60 metros (NFU) | F8: 1 | G8: 659808 | H8: UN | I8: REPOSICION | J8: OPEX | K8: VARIABLE | L8: DIRECTO | N8: CC7
A9: 45958 | B9: Bernis, Carlos Oscar | C9: FA-A 00006-00000175 | D9: -968000 | E9: OC 0001-00002255: LOGISTICA Viaje realizado fecha 28/10 | F9: 1 | G9: 800000 | H9: UN | I9: LOGISTICA | J9: OPEX | K9: VARIABLE | L9: DIRECTO | N9: CC7
A10: 45952 | B10: Bernis, Carlos Oscar | C10: FA-A 00006-00000174 | D10: -968000 | E10: OC 0001-00002218: LOGISTICA Viaje realizado fecha 20-10 worms - Parque industrial guernica | F10: 1 | G10: 800000 | H10: UN | I10: LOGISTICA | J10: OPEX | K10: VARIABLE | L10: DIRECTO | N10: CC7
A11: 45939 | B11: Bernis, Carlos Oscar | C11: FA-A 00006-00000171 | D11: -302500 | E11: OC 0001-00001836: LOGISTICA Viaje: 4 de septiembre origen: lujan worms con cubiertas en desuso . Destino :worms | F11: 1 | G11: 250000 | H11: UN | I11: LOGISTICA | J11: OPEX | K11: VARIABLE | L11: DIRECTO | N11: CC7
A12: 45939 | B12: Bernis, Carlos Oscar | C12: FA-A 00006-00000170 | D12: -968000 | E12: OC 0001-00002228: LOGISTICA Viaje realizado fecha 8/10 neumáticos | F12: 1 | G12: 800000 | H12: UN | I12: LOGISTICA | J12: OPEX | K12: VARIABLE | L12: DIRECTO | N12: CC7
A13: 45958 | B13: Comercial Uritorco S. R. L. (w) | C13: FA-A 00001-00007089 | D13: -66182.16 | E13: OC 0001-00002229: REPOSICION Adaptador 3/4 | F13: 2 | G13: 19578.51 | H13: UN | I13: REPOSICION | J13: OPEX | K13: VARIABLE | L13: INDIRECTO | N13: CC7
... A77: 45932 | B77: Acosta, Roberto Maximiliano | C77: FA-C 00001-00000616 | D77: -4632990 | E77: OC 0001-00001709: SERVICIOS de limpieza +ipc julio y agosto 3,8% | F77: 1 | G77: 4632990 | H77: UN | I77: SERVICIOS | J77: OPEX | K77: VARIABLE | L77: INDIRECTO | N77: CC1
A78: 45931 | B78: Adhoc S.A. | C78: FA-A 00003-00019779 | D78: -2004596.6 | E78: OC 0001-00001367: SERVICIOS Sistema contable | F78: 1 | G78: 1656691.4 | H78: UN | I78: SERVICIOS | J78: OPEX | K78: FIJO | L78: INDIRECTO | M78: CC13 | N78: CC1
A79: 45950 | B79: American Express Argentina S. A. | C79: OCOM/2025/0472 | D79: -344000.85 | E79: OC 0001-00001936: PERSONAL | F79: 1 | G79: 344000.85 | H79: UN | I79: PERSONAL | J79: OPEX | K79: VARIABLE | L79: INDIRECTO | N79: CC1
A80: 45949 | B80: Amx Argentina Sociedad Anonima | C80: FA-A 01331-01351660 | D80: -40348.6 | E80: OC 0001-00002225: SERVICIOS Servicio Móvil | F80: 1 | G80: 10605 | H80: UN | I80: SERVICIOS | J80: OPEX | K80: VARIABLE | L80: INDIRECTO | N80: CC1
A81: 45931 | B81: Aranda, Marisa Isabel | C81: FA-C 00005-00000212 | D81: -720000 | E81: OC 0001-00001711: SERVICIOS servicio de parquización | F81: 9 | G81: 80000 | H81: UN | I81: SERVICIOS | J81: OPEX | K81: VARIABLE | L81: INDIRECTO | N81: CC1
A82: 45952 | B82: ARCA | C82: OCOM/2025/0481 | D82: -3840846 | E82: OC 0001-00002049: IMPUESTOS anticipo | F82: 1 | G82: 3840846 | H82: UN | I82: IMPUESTOS | J82: OPEX | K82: VARIABLE | L82: INDIRECTO | N82: CC1
A83: 45952 | B83: ARCA | C83: OCOM/2025/0479 | D83: -1311921.2 | E83: OC 0001-00002043: IMPUESTOS Multa suse | F83: 1 | G83: 1311921.2 | H83: UN | I83: IMPUESTOS | J83: DEUDA | K83: VARIABLE | L83: INDIRECTO | N83: CC1
A84: 45946 | B84: ARCA | C84: OCOM/2025/0466 | D84: -552778.24 | E84: OC 0001-00001904: HONORARIOS Didomenico | F84: 1 | G84: 552778.24 | H84: UN | I84: HONORARIOS | J84: DEUDA | K84: VARIABLE | L84: INDIRECTO | N84: CC1
A85: 45946 | B85: ARCA | C85: OCOM/2025/0464 | D85: -15235035 | E85: OC 0001-00001869: IMPUESTOS Deuda, Planes de pago | F85: 1 | G85: 15235035 | H85: UN | I85: IMPUESTOS | J85: DEUDA | K85: VARIABLE | L85: INDIRECTO | N85: CC1
A86: 45954 | B86: Asociacion Empleados De Comercio De Rosario | C86: OCOM/2025/0504 | D86: -1383181 | E86: OC 0001-00002124: SERVICIOS | F86: 1 | G86: 1383181 | H86: UN | I86: SERVICIOS | J86: DEUDA | K86: VARIABLE | L86: INDIRECTO | N86: CC1
A87: 45951 | B87: Asociacion Mutual 23 De Setiembre | C87: OCOM/2025/0477 | D87: -10000000 | E87: OC 0001-00002032: SERVICIOS mutual | F87: 1 | G87: 10000000 | H87: UN | I87: SERVICIOS | J87: DEUDA | K87: VARIABLE | L87: INDIRECTO | N87: CC1
A88: 45931 | B88: Berardi, Alberto Jose - | C88: FA-C 00005-00000184 | D88: -560000 | E88: OC 0001-00001696: SERVICIOS Abono mensual | F88: 1 | G88: 560000 | H88: UN | I88: SERVICIOS | J88: OPEX | K88: VARIABLE | L88: INDIRECTO | N88: CC1
A89: 45943 | B89: Bollini, Tomas Maria | C89: OCOM/2025/0461 | D89: -114000 | E89: OC 0001-00001835: PERSONAL CARTA DOCUMENTO | F89: 1 | G89: 114000 | H89: UN | I89: PERSONAL | J89: OPEX | K89: VARIABLE | L89: INDIRECTO | N89: CC1
A90: 45937 | B90: Castelli, Guillermo Alejandro | C90: OCOM/2025/0457 | D90: -1500000 | E90: OC 0001-00001799: PERSONAL personal, acuerdo. | F90: 1 | G90: 1500000 | H90: UN | I90: PERSONAL | J90: DEUDA | K90: VARIABLE | L90: INDIRECTO | N90: CC1
... A148: 45931 | B148: Union Emergencias Regionales S A Acion | C148: FA-A 00005-00015075 | D148: -468967.64 | E148: OC 0001-00001362: SERVICIOS Amas Octubre 2025 | F148: 1 | G148: 424405.1 | H148: UN | I148: SERVICIOS | J148: OPEX | K148: VARIABLE | L148: INDIRECTO | N148: CC1

Sheet BBDD_GASTOS_FINAL
A1: Fecha de Factura/Recibo | B1: Nombre de la empresa a mostrar en la factura | C1: Número | D1: Total con signo | E1: Líneas de factura/Etiqueta | F1: Líneas de factura/Cantidad | G1: Líneas de factura/Precio unitario | H1: Líneas de factura/Unidad de medida | I1: RUBRO | J1: Concepto | K1: Tipo de Gasto 1 | L1: Tipo de Gasto 2 | M1: CCO LOTE | N1: CCO - SECTOR | O1: Column15 | P1: lote | Q1: Origen | R1: LOTES | S1: prc_lote | T1: etapas | U1: prc_etapa | V1: lote_desglosado | W1: etapa_desglosada | X1: peso_lote | Y1: peso_etapa | Z1: Total_desglosado | AA1: Cantidad_desglosada | AB1: rubro_id | AC1: rubro_final
A2: 46112 | B2: Servicio Nacional De Sanidad Y Calidad Agroalimentaria Senasa | C2: OC/2026/0155 | D2: -21642.72 | E2: IMPUESTO (C) | F2: 1 | G2: 21642.72 | H2: Unidad(es) | I2: IMPUESTO (C) | J2: OPEX | K2: FIJO | L2: DIRECTO | M2: CCC _mar26 | N2: NO | O2: 0 | P2: 0 | Q2: facturas_final | R2: {3725,3925} | S2: {0.49166666,0.4916666} | T2: NOSECOMPUTA | U2: {0} | V2: 3725 | W2: NOSECOMPUTA | X2: 0.49166666 | Y2: 0 | Z2: 0 | AA2: 0 | AB2: =_xlfn.XLOOKUP(I2,'rubros_id_opex '!A:A,'rubros_id_opex '!B:B) -> 8 | AC2: =_xlfn.XLOOKUP(AB2,'rubros_unicos'!B:B,'rubros_unicos'!A:A) -> IMPUESTOS
A3: 46112 | B3: Servicio Nacional De Sanidad Y Calidad Agroalimentaria Senasa | C3: OC/2026/0155 | D3: -21642.72 | E3: IMPUESTO (C) | F3: 1 | G3: 21642.72 | H3: Unidad(es) | I3: IMPUESTO (C) | J3: OPEX | K3: FIJO | L3: DIRECTO | M3: CCC _mar26 | N3: NO | O3: 0 | P3: 0 | Q3: facturas_final | R3: {3725,3925} | S3: {0.49166666,0.4916666} | T3: NOSECOMPUTA | U3: {0} | V3: 3925 | W3: NOSECOMPUTA | X3: 0.4916666 | Y3: 0 | Z3: 0 | AA3: 0 | AB3: =_xlfn.XLOOKUP(I3,'rubros_id_opex '!A:A,'rubros_id_opex '!B:B) -> 8 | AC3: =_xlfn.XLOOKUP(AB3,'rubros_unicos'!B:B,'rubros_unicos'!A:A) -> IMPUESTOS
A4: 46112 | B4: ARCA | C4: OC/2026/0153 | D4: -279565.72 | E4: Honorarios (C) | F4: 1 | G4: 279565.72 | H4: Unidad(es) | I4: Honorarios (C) | J4: OPEX | K4: VARIABLE | L4: INDIRECTO | M4: CCC _mar26 | N4: CC1 | O4: 0 | P4: 0 | Q4: facturas_final | R4: {3725,3925} | S4: {0.49166666,0.4916666} | T4: GESTACIÓN , MATERNIDAD, SITIO 2, SITIO 3 | U4: {0.25,0.25,0.25,0.25} | V4: 3725 | W4: GESTACIÓN | X4: 0.49166666 | Y4: 0.25 | Z4: -34363.286 | AA4: 0.12291666 | AB4: =_xlfn.XLOOKUP(I4,'rubros_id_opex '!A:A,'rubros_id_opex '!B:B) -> 9 | AC4: =_xlfn.XLOOKUP(AB4,'rubros_unicos'!B:B,'rubros_unicos'!A:A) -> HONORARIOS
A5: 46112 | B5: ARCA | C5: OC/2026/0153 | D5: -279565.72 | E5: Honorarios (C) | F5: 1 | G5: 279565.72 | H5: Unidad(es) | I5: Honorarios (C) | J5: OPEX | K5: VARIABLE | L5: INDIRECTO | M5: CCC _mar26 | N5: CC1 | O5: 0 | P5: 0 | Q5: facturas_final | R5: {3725,3925} | S5: {0.49166666,0.4916666} | T5: GESTACIÓN , MATERNIDAD, SITIO 2, SITIO 3 | U5: {0.25,0.25,0.25,0.25} | V5: 3725 | W5: MATERNIDAD | X5: 0.49166666 | Y5: 0.25 | Z5: -34363.286 | AA5: 0.12291666 | AB5: =_xlfn.XLOOKUP(I5,'rubros_id_opex '!A:A,'rubros_id_opex '!B:B) -> 9 | AC5: =_xlfn.XLOOKUP(AB5,'rubros_unicos'!B:B,'rubros_unicos'!A:A) -> HONORARIOS
A6: 46112 | B6: ARCA | C6: OC/2026/0153 | D6: -279565.72 | E6: Honorarios (C) | F6: 1 | G6: 279565.72 | H6: Unidad(es) | I6: Honorarios (C) | J6: OPEX | K6: VARIABLE | L6: INDIRECTO | M6: CCC _mar26 | N6: CC1 | O6: 0 | P6: 0 | Q6: facturas_final | R6: {3725,3925} | S6: {0.49166666,0.4916666} | T6: GESTACIÓN , MATERNIDAD, SITIO 2, SITIO 3 | U6: {0.25,0.25,0.25,0.25} | V6: 3725 | W6: SITIO 2 | X6: 0.49166666 | Y6: 0.25 | Z6: -34363.286 | AA6: 0.12291666 | AB6: =_xlfn.XLOOKUP(I6,'rubros_id_opex '!A:A,'rubros_id_opex '!B:B) -> 9 | AC6: =_xlfn.XLOOKUP(AB6,'rubros_unicos'!B:B,'rubros_unicos'!A:A) -> HONORARIOS
A7: 46112 | B7: ARCA | C7: OC/2026/0153 | D7: -279565.72 | E7: Honorarios (C) | F7: 1 | G7: 279565.72 | H7: Unidad(es) | I7: Honorarios (C) | J7: OPEX | K7: VARIABLE | L7: INDIRECTO | M7: CCC _mar26 | N7: CC1 | O7: 0 | P7: 0 | Q7: facturas_final | R7: {3725,3925} | S7: {0.49166666,0.4916666} | T7: GESTACIÓN , MATERNIDAD, SITIO 2, SITIO 3 | U7: {0.25,0.25,0.25,0.25} | V7: 3725 | W7: SITIO 3 | X7: 0.49166666 | Y7: 0.25 | Z7: -34363.286 | AA7: 0.12291666 | AB7: =_xlfn.XLOOKUP(I7,'rubros_id_opex '!A:A,'rubros_id_opex '!B:B) -> 9 | AC7: =_xlfn.XLOOKUP(AB7,'rubros_unicos'!B:B,'rubros_unicos'!A:A) -> HONORARIOS
A8: 46112 | B8: ARCA | C8: OC/2026/0153 | D8: -279565.72 | E8: Honorarios (C) | F8: 1 | G8: 279565.72 | H8: Unidad(es) | I8: Honorarios (C) | J8: OPEX | K8: VARIABLE | L8: INDIRECTO | M8: CCC _mar26 | N8: CC1 | O8: 0 | P8: 0 | Q8: facturas_final | R8: {3725,3925} | S8: {0.49166666,0.4916666} | T8: GESTACIÓN , MATERNIDAD, SITIO 2, SITIO 3 | U8: {0.25,0.25,0.25,0.25} | V8: 3925 | W8: GESTACIÓN | X8: 0.4916666 | Y8: 0.25 | Z8: -34363.282 | AA8: 0.12291665 | AB8: =_xlfn.XLOOKUP(I8,'rubros_id_opex '!A:A,'rubros_id_opex '!B:B) -> 9 | AC8: =_xlfn.XLOOKUP(AB8,'rubros_unicos'!B:B,'rubros_unicos'!A:A) -> HONORARIOS
A9: 46112 | B9: ARCA | C9: OC/2026/0153 | D9: -279565.72 | E9: Honorarios (C) | F9: 1 | G9: 279565.72 | H9: Unidad(es) | I9: Honorarios (C) | J9: OPEX | K9: VARIABLE | L9: INDIRECTO | M9: CCC _mar26 | N9: CC1 | O9: 0 | P9: 0 | Q9: facturas_final | R9: {3725,3925} | S9: {0.49166666,0.4916666} | T9: GESTACIÓN , MATERNIDAD, SITIO 2, SITIO 3 | U9: {0.25,0.25,0.25,0.25} | V9: 3925 | W9: MATERNIDAD | X9: 0.4916666 | Y9: 0.25 | Z9: -34363.282 | AA9: 0.12291665 | AB9: =_xlfn.XLOOKUP(I9,'rubros_id_opex '!A:A,'rubros_id_opex '!B:B) -> 9 | AC9: =_xlfn.XLOOKUP(AB9,'rubros_unicos'!B:B,'rubros_unicos'!A:A) -> HONORARIOS
A10: 46112 | B10: ARCA | C10: OC/2026/0153 | D10: -279565.72 | E10: Honorarios (C) | F10: 1 | G10: 279565.72 | H10: Unidad(es) | I10: Honorarios (C) | J10: OPEX | K10: VARIABLE | L10: INDIRECTO | M10: CCC _mar26 | N10: CC1 | O10: 0 | P10: 0 | Q10: facturas_final | R10: {3725,3925} | S10: {0.49166666,0.4916666} | T10: GESTACIÓN , MATERNIDAD, SITIO 2, SITIO 3 | U10: {0.25,0.25,0.25,0.25} | V10: 3925 | W10: SITIO 2 | X10: 0.4916666 | Y10: 0.25 | Z10: -34363.282 | AA10: 0.12291665 | AB10: =_xlfn.XLOOKUP(I10,'rubros_id_opex '!A:A,'rubros_id_opex '!B:B) -> 9 | AC10: =_xlfn.XLOOKUP(AB10,'rubros_unicos'!B:B,'rubros_unicos'!A:A) -> HONORARIOS
A11: 46112 | B11: ARCA | C11: OC/2026/0153 | D11: -279565.72 | E11: Honorarios (C) | F11: 1 | G11: 279565.72 | H11: Unidad(es) | I11: Honorarios (C) | J11: OPEX | K11: VARIABLE | L11: INDIRECTO | M11: CCC _mar26 | N11: CC1 | O11: 0 | P11: 0 | Q11: facturas_final | R11: {3725,3925} | S11: {0.49166666,0.4916666} | T11: GESTACIÓN , MATERNIDAD, SITIO 2, SITIO 3 | U11: {0.25,0.25,0.25,0.25} | V11: 3925 | W11: SITIO 3 | X11: 0.4916666 | Y11: 0.25 | Z11: -34363.282 | AA11: 0.12291665 | AB11: =_xlfn.XLOOKUP(I11,'rubros_id_opex '!A:A,'rubros_id_opex '!B:B) -> 9 | AC11: =_xlfn.XLOOKUP(AB11,'rubros_unicos'!B:B,'rubros_unicos'!A:A) -> HONORARIOS
A12: 46112 | B12: Correa, Natalia Erica | C12: OC/2026/0152 | D12: -51343.54 | E12: Honorarios (C) | F12: 1 | G12: 51343.54 | H12: Unidad(es) | I12: Honorarios (C) | J12: OPEX | K12: VARIABLE | L12: INDIRECTO | M12: CCC _mar26 | N12: CC1 | O12: 0 | P12: 0 | Q12: facturas_final | R12: {3725,3925} | S12: {0.49166666,0.4916666} | T12: GESTACIÓN , MATERNIDAD, SITIO 2, SITIO 3 | U12: {0.25,0.25,0.25,0.25} | V12: 3725 | W12: GESTACIÓN | X12: 0.49166666 | Y12: 0.25 | Z12: -6310.9767 | AA12: 0.12291666 | AB12: =_xlfn.XLOOKUP(I12,'rubros_id_opex '!A:A,'rubros_id_opex '!B:B) -> 9 | AC12: =_xlfn.XLOOKUP(AB12,'rubros_unicos'!B:B,'rubros_unicos'!A:A) -> HONORARIOS
A13: 46112 | B13: Correa, Natalia Erica | C13: OC/2026/0152 | D13: -51343.54 | E13: Honorarios (C) | F13: 1 | G13: 51343.54 | H13: Unidad(es) | I13: Honorarios (C) | J13: OPEX | K13: VARIABLE | L13: INDIRECTO | M13: CCC _mar26 | N13: CC1 | O13: 0 | P13: 0 | Q13: facturas_final | R13: {3725,3925} | S13: {0.49166666,0.4916666} | T13: GESTACIÓN , MATERNIDAD, SITIO 2, SITIO 3 | U13: {0.25,0.25,0.25,0.25} | V13: 3725 | W13: MATERNIDAD | X13: 0.49166666 | Y13: 0.25 | Z13: -6310.9767 | AA13: 0.12291666 | AB13: =_xlfn.XLOOKUP(I13,'rubros_id_opex '!A:A,'rubros_id_opex '!B:B) -> 9 | AC13: =_xlfn.XLOOKUP(AB13,'rubros_unicos'!B:B,'rubros_unicos'!A:A) -> HONORARIOS
... A15: 46112 | B15: Correa, Natalia Erica | C15: OC/2026/0152 | D15: -51343.54 | E15: Honorarios (C) | F15: 1 | G15: 51343.54 | H15: Unidad(es) | I15: Honorarios (C) | J15: OPEX | K15: VARIABLE | L15: INDIRECTO | M15: CCC _mar26 | N15: CC1 | O15: 0 | P15: 0 | Q15: facturas_final | R15: {3725,3925} | S15: {0.49166666,0.4916666} | T15: GESTACIÓN , MATERNIDAD, SITIO 2, SITIO 3 | U15: {0.25,0.25,0.25,0.25} | V15: 3725 | W15: SITIO 3 | X15: 0.49166666 | Y15: 0.25 | Z15: -6310.9767 | AA15: 0.12291666 | AB15: =_xlfn.XLOOKUP(I15,'rubros_id_opex '!A:A,'rubros_id_opex '!B:B) -> 9 | AC15: =_xlfn.XLOOKUP(AB15,'rubros_unicos'!B:B,'rubros_unicos'!A:A) -> HONORARIOS
A16: 46112 | B16: Correa, Natalia Erica | C16: OC/2026/0152 | D16: -51343.54 | E16: Honorarios (C) | F16: 1 | G16: 51343.54 | H16: Unidad(es) | I16: Honorarios (C) | J16: OPEX | K16: VARIABLE | L16: INDIRECTO | M16: CCC _mar26 | N16: CC1 | O16: 0 | P16: 0 | Q16: facturas_final | R16: {3725,3925} | S16: {0.49166666,0.4916666} | T16: GESTACIÓN , MATERNIDAD, SITIO 2, SITIO 3 | U16: {0.25,0.25,0.25,0.25} | V16: 3925 | W16: GESTACIÓN | X16: 0.4916666 | Y16: 0.25 | Z16: -6310.9759 | AA16: 0.12291665 | AB16: 3 | AC16: =_xlfn.XLOOKUP(AB16,'rubros_unicos'!B:B,'rubros_unicos'!A:A) -> SANIDAD
A17: 46112 | B17: Correa, Natalia Erica | C17: OC/2026/0152 | D17: -51343.54 | E17: Honorarios (C) | F17: 1 | G17: 51343.54 | H17: Unidad(es) | I17: Honorarios (C) | J17: OPEX | K17: VARIABLE | L17: INDIRECTO | M17: CCC _mar26 | N17: CC1 | O17: 0 | P17: 0 | Q17: facturas_final | R17: {3725,3925} | S17: {0.49166666,0.4916666} | T17: GESTACIÓN , MATERNIDAD, SITIO 2, SITIO 3 | U17: {0.25,0.25,0.25,0.25} | V17: 3925 | W17: MATERNIDAD | X17: 0.4916666 | Y17: 0.25 | Z17: -6310.9759 | AA17: 0.12291665 | AB17: 3 | AC17: =_xlfn.XLOOKUP(AB17,'rubros_unicos'!B:B,'rubros_unicos'!A:A) -> SANIDAD
A18: 46112 | B18: Correa, Natalia Erica | C18: OC/2026/0152 | D18: -51343.54 | E18: Honorarios (C) | F18: 1 | G18: 51343.54 | H18: Unidad(es) | I18: Honorarios (C) | J18: OPEX | K18: VARIABLE | L18: INDIRECTO | M18: CCC _mar26 | N18: CC1 | O18: 0 | P18: 0 | Q18: facturas_final | R18: {3725,3925} | S18: {0.49166666,0.4916666} | T18: GESTACIÓN , MATERNIDAD, SITIO 2, SITIO 3 | U18: {0.25,0.25,0.25,0.25} | V18: 3925 | W18: SITIO 2 | X18: 0.4916666 | Y18: 0.25 | Z18: -6310.9759 | AA18: 0.12291665 | AB18: =_xlfn.XLOOKUP(I18,'rubros_id_opex '!A:A,'rubros_id_opex '!B:B) -> 9 | AC18: =_xlfn.XLOOKUP(AB18,'rubros_unicos'!B:B,'rubros_unicos'!A:A) -> HONORARIOS
A19: 46112 | B19: Correa, Natalia Erica | C19: OC/2026/0152 | D19: -51343.54 | E19: Honorarios (C) | F19: 1 | G19: 51343.54 | H19: Unidad(es) | I19: Honorarios (C) | J19: OPEX | K19: VARIABLE | L19: INDIRECTO | M19: CCC _mar26 | N19: CC1 | O19: 0 | P19: 0 | Q19: facturas_final | R19: {3725,3925} | S19: {0.49166666,0.4916666} | T19: GESTACIÓN , MATERNIDAD, SITIO 2, SITIO 3 | U19: {0.25,0.25,0.25,0.25} | V19: 3925 | W19: SITIO 3 | X19: 0.4916666 | Y19: 0.25 | Z19: -6310.9759 | AA19: 0.12291665 | AB19: =_xlfn.XLOOKUP(I19,'rubros_id_opex '!A:A,'rubros_id_opex '!B:B) -> 9 | AC19: =_xlfn.XLOOKUP(AB19,'rubros_unicos'!B:B,'rubros_unicos'!A:A) -> HONORARIOS
A20: 46112 | B20: Barrera, Adrian Jesus | C20: FA-C 00001-00000437 | D20: -225600 | E20: Gastos Operativos (C) | F20: 47 | G20: 4800 | H20: Unidad(es) | I20: Gastos Operativos (C) | J20: OPEX | K20: VARIABLE | L20: INDIRECTO | M20: CCC _mar26 | N20: CC1 | O20: 0 | P20: 0 | Q20: facturas_final | R20: {3725,3925} | S20: {0.49166666,0.4916666} | T20: GESTACIÓN , MATERNIDAD, SITIO 2, SITIO 3 | U20: {0.25,0.25,0.25,0.25} | V20: 3725 | W20: GESTACIÓN | X20: 0.49166666 | Y20: 0.25 | Z20: -27730 | AA20: 5.7770833 | AB20: =_xlfn.XLOOKUP(I20,'rubros_id_opex '!A:A,'rubros_id_opex '!B:B) -> 7 | AC20: =_xlfn.XLOOKUP(AB20,'rubros_unicos'!B:B,'rubros_unicos'!A:A) -> GASTOS OPERATIVOS
A21: 46112 | B21: Barrera, Adrian Jesus | C21: FA-C 00001-00000437 | D21: -225600 | E21: Gastos Operativos (C) | F21: 47 | G21: 4800 | H21: Unidad(es) | I21: Gastos Operativos (C) | J21: OPEX | K21: VARIABLE | L21: INDIRECTO | M21: CCC _mar26 | N21: CC1 | O21: 0 | P21: 0 | Q21: facturas_final | R21: {3725,3925} | S21: {0.49166666,0.4916666} | T21: GESTACIÓN , MATERNIDAD, SITIO 2, SITIO 3 | U21: {0.25,0.25,0.25,0.25} | V21: 3725 | W21: MATERNIDAD | X21: 0.49166666 | Y21: 0.25 | Z21: -27730 | AA21: 5.7770833 | AB21: =_xlfn.XLOOKUP(I21,'rubros_id_opex '!A:A,'rubros_id_opex '!B:B) -> 7 | AC21: =_xlfn.XLOOKUP(AB21,'rubros_unicos'!B:B,'rubros_unicos'!A:A) -> GASTOS OPERATIVOS
A22: 46112 | B22: Barrera, Adrian Jesus | C22: FA-C 00001-00000437 | D22: -225600 | E22: Gastos Operativos (C) | F22: 47 | G22: 4800 | H22: Unidad(es) | I22: Gastos Operativos (C) | J22: OPEX | K22: VARIABLE | L22: INDIRECTO | M22: CCC _mar26 | N22: CC1 | O22: 0 | P22: 0 | Q22: facturas_final | R22: {3725,3925} | S22: {0.49166666,0.4916666} | T22: GESTACIÓN , MATERNIDAD, SITIO 2, SITIO 3 | U22: {0.25,0.25,0.25,0.25} | V22: 3725 | W22: SITIO 2 | X22: 0.49166666 | Y22: 0.25 | Z22: -27730 | AA22: 5.7770833 | AB22: =_xlfn.XLOOKUP(I22,'rubros_id_opex '!A:A,'rubros_id_opex '!B:B) -> 7 | AC22: =_xlfn.XLOOKUP(AB22,'rubros_unicos'!B:B,'rubros_unicos'!A:A) -> GASTOS OPERATIVOS
A23: 46112 | B23: Barrera, Adrian Jesus | C23: FA-C 00001-00000437 | D23: -225600 | E23: Gastos Operativos (C) | F23: 47 | G23: 4800 | H23: Unidad(es) | I23: Gastos Operativos (C) | J23: OPEX | K23: VARIABLE | L23: INDIRECTO | M23: CCC _mar26 | N23: CC1 | O23: 0 | P23: 0 | Q23: facturas_final | R23: {3725,3925} | S23: {0.49166666,0.4916666} | T23: GESTACIÓN , MATERNIDAD, SITIO 2, SITIO 3 | U23: {0.25,0.25,0.25,0.25} | V23: 3725 | W23: SITIO 3 | X23: 0.49166666 | Y23: 0.25 | Z23: -27730 | AA23: 5.7770833 | AB23: =_xlfn.XLOOKUP(I23,'rubros_id_opex '!A:A,'rubros_id_opex '!B:B) -> 7 | AC23: =_xlfn.XLOOKUP(AB23,'rubros_unicos'!B:B,'rubros_unicos'!A:A) -> GASTOS OPERATIVOS
A24: 46112 | B24: Barrera, Adrian Jesus | C24: FA-C 00001-00000437 | D24: -225600 | E24: Gastos Operativos (C) | F24: 47 | G24: 4800 | H24: Unidad(es) | I24: Gastos Operativos (C) | J24: OPEX | K24: VARIABLE | L24: INDIRECTO | M24: CCC _mar26 | N24: CC1 | O24: 0 | P24: 0 | Q24: facturas_final | R24: {3725,3925} | S24: {0.49166666,0.4916666} | T24: GESTACIÓN , MATERNIDAD, SITIO 2, SITIO 3 | U24: {0.25,0.25,0.25,0.25} | V24: 3925 | W24: GESTACIÓN | X24: 0.4916666 | Y24: 0.25 | Z24: -27729.996 | AA24: 5.7770826 | AB24: =_xlfn.XLOOKUP(I24,'rubros_id_opex '!A:A,'rubros_id_opex '!B:B) -> 7 | AC24: =_xlfn.XLOOKUP(AB24,'rubros_unicos'!B:B,'rubros_unicos'!A:A) -> GASTOS OPERATIVOS
A25: 46112 | B25: Barrera, Adrian Jesus | C25: FA-C 00001-00000437 | D25: -225600 | E25: Gastos Operativos (C) | F25: 47 | G25: 4800 | H25: Unidad(es) | I25: Gastos Operativos (C) | J25: OPEX | K25: VARIABLE | L25: INDIRECTO | M25: CCC _mar26 | N25: CC1 | O25: 0 | P25: 0 | Q25: facturas_final | R25: {3725,3925} | S25: {0.49166666,0.4916666} | T25: GESTACIÓN , MATERNIDAD, SITIO 2, SITIO 3 | U25: {0.25,0.25,0.25,0.25} | V25: 3925 | W25: MATERNIDAD | X25: 0.4916666 | Y25: 0.25 | Z25: -27729.996 | AA25: 5.7770826 | AB25: =_xlfn.XLOOKUP(I25,'rubros_id_opex '!A:A,'rubros_id_opex '!B:B) -> 7 | AC25: =_xlfn.XLOOKUP(AB25,'rubros_unicos'!B:B,'rubros_unicos'!A:A) -> GASTOS OPERATIVOS
A26: 46112 | B26: Barrera, Adrian Jesus | C26: FA-C 00001-00000437 | D26: -225600 | E26: Gastos Operativos (C) | F26: 47 | G26: 4800 | H26: Unidad(es) | I26: Gastos Operativos (C) | J26: OPEX | K26: VARIABLE | L26: INDIRECTO | M26: CCC _mar26 | N26: CC1 | O26: 0 | P26: 0 | Q26: facturas_final | R26: {3725,3925} | S26: {0.49166666,0.4916666} | T26: GESTACIÓN , MATERNIDAD, SITIO 2, SITIO 3 | U26: {0.25,0.25,0.25,0.25} | V26: 3925 | W26: SITIO 2 | X26: 0.4916666 | Y26: 0.25 | Z26: -27729.996 | AA26: 5.7770826 | AB26: =_xlfn.XLOOKUP(I26,'rubros_id_opex '!A:A,'rubros_id_opex '!B:B) -> 7 | AC26: =_xlfn.XLOOKUP(AB26,'rubros_unicos'!B:B,'rubros_unicos'!A:A) -> GASTOS OPERATIVOS
A27: 46112 | B27: Barrera, Adrian Jesus | C27: FA-C 00001-00000437 | D27: -225600 | E27: Gastos Operativos (C) | F27: 47 | G27: 4800 | H27: Unidad(es) | I27: Gastos Operativos (C) | J27: OPEX | K27: VARIABLE | L27: INDIRECTO | M27: CCC _mar26 | N27: CC1 | O27: 0 | P27: 0 | Q27: facturas_final | R27: {3725,3925} | S27: {0.49166666,0.4916666} | T27: GESTACIÓN , MATERNIDAD, SITIO 2, SITIO 3 | U27: {0.25,0.25,0.25,0.25} | V27: 3925 | W27: SITIO 3 | X27: 0.4916666 | Y27: 0.25 | Z27: -27729.996 | AA27: 5.7770826 | AB27: =_xlfn.XLOOKUP(I27,'rubros_id_opex '!A:A,'rubros_id_opex '!B:B) -> 7 | AC27: =_xlfn.XLOOKUP(AB27,'rubros_unicos'!B:B,'rubros_unicos'!A:A) -> GASTOS OPERATIVOS
A28: 46112 | B28: Esperanza Distribuciones Srl | C28: FA-A 00026-00530141 | D28: -127060.24 | E28: Sanidad (C) Despadac | F28: 1 | G28: 105008.46 | H28: Unidad(es) | I28: Sanidad (C) | J28: OPEX | K28: VARIABLE | L28: DIRECTO | M28: CCC _mar26 | N28: NO | O28: 0 | P28: 0 | Q28: facturas_final | R28: {3725,3925} | S28: {0.49166666,0.4916666} | T28: NOSECOMPUTA | U28: {0} | V28: 3725 | W28: NOSECOMPUTA | X28: 0.49166666 | Y28: 0 | Z28: 0 | AA28: 0 | AB28: =_xlfn.XLOOKUP(I28,'rubros_id_opex '!A:A,'rubros_id_opex '!B:B) -> 3 | AC28: =_xlfn.XLOOKUP(AB28,'rubros_unicos'!B:B,'rubros_unicos'!A:A) -> SANIDAD
A29: 46112 | B29: Esperanza Distribuciones Srl | C29: FA-A 00026-00530141 | D29: -127060.24 | E29: Sanidad (C) Despadac | F29: 1 | G29: 105008.46 | H29: Unidad(es) | I29: Sanidad (C) | J29: OPEX | K29: VARIABLE | L29: DIRECTO | M29: CCC _mar26 | N29: NO | O29: 0 | P29: 0 | Q29: facturas_final | R29: {3725,3925} | S29: {0.49166666,0.4916666} | T29: NOSECOMPUTA | U29: {0} | V29: 3925 | W29: NOSECOMPUTA | X29: 0.4916666 | Y29: 0 | Z29: 0 | AA29: 0 | AB29: =_xlfn.XLOOKUP(I29,'rubros_id_opex '!A:A,'rubros_id_opex '!B:B) -> 3 | AC29: =_xlfn.XLOOKUP(AB29,'rubros_unicos'!B:B,'rubros_unicos'!A:A) -> SANIDAD
... A64: 46108 | B64: Asociacion Empleados De Comercio De Rosario | C64: OC/2026/0150 | D64: -522382.82 | E64: Gastos Operativos (C) Requerimiento | F64: 1 | G64: 522382.82 | H64: Unidad(es) | I64: Gastos Operativos (C) | J64: OPEX | K64: VARIABLE | L64: INDIRECTO | M64: CCC _mar26 | N64: CC1 | O64: 0 | P64: 0 | Q64: facturas_final | R64: {3725,3925} | S64: {0.49166666,0.4916666} | T64: GESTACIÓN , MATERNIDAD, SITIO 2, SITIO 3 | U64: {0.25,0.25,0.25,0.25} | V64: 3925 | W64: SITIO 2 | X64: 0.4916666 | Y64: 0.25 | Z64: -64209.546 | AA64: 0.12291665 | AB64: =_xlfn.XLOOKUP(I64,'rubros_id_opex '!A:A,'rubros_id_opex '!B:B) -> 7 | AC64: =_xlfn.XLOOKUP(AB64,'rubros_unicos'!B:B,'rubros_unicos'!A:A) -> GASTOS OPERATIVOS
A65: 46108 | B65: Asociacion Empleados De Comercio De Rosario | C65: OC/2026/0150 | D65: -522382.82 | E65: Gastos Operativos (C) Requerimiento | F65: 1 | G65: 522382.82 | H65: Unidad(es) | I65: Gastos Operativos (C) | J65: OPEX | K65: VARIABLE | L65: INDIRECTO | M65: CCC _mar26 | N65: CC1 | O65: 0 | P65: 0 | Q65: facturas_final | R65: {3725,3925} | S65: {0.49166666,0.4916666} | T65: GESTACIÓN , MATERNIDAD, SITIO 2, SITIO 3 | U65: {0.25,0.25,0.25,0.25} | V65: 3925 | W65: SITIO 3 | X65: 0.4916666 | Y65: 0.25 | Z65: -64209.546 | AA65: 0.12291665 | AB65: 3 | AC65: =_xlfn.XLOOKUP(AB65,'rubros_unicos'!B:B,'rubros_unicos'!A:A) -> SANIDAD
A66: 46108 | B66: ARCA 931 | C66: OC/2026/0149 | D66: -4772839.3 | E66: IMPUESTO (C) Obra Social Diciembre | F66: 1 | G66: 4772839.3 | H66: Unidad(es) | I66: IMPUESTO (C) | J66: OPEX | K66: VARIABLE | L66: INDIRECTO | M66: CCC _mar26 | N66: NO | O66: 0 | P66: 0 | Q66: facturas_final | R66: {3725,3925} | S66: {0.49166666,0.4916666} | T66: NOSECOMPUTA | U66: {0} | V66: 3725 | W66: NOSECOMPUTA | X66: 0.49166666 | Y66: 0 | Z66: 0 | AA66: 0 | AB66: =_xlfn.XLOOKUP(I66,'rubros_id_opex '!A:A,'rubros_id_opex '!B:B) -> 8 | AC66: =_xlfn.XLOOKUP(AB66,'rubros_unicos'!B:B,'rubros_unicos'!A:A) -> IMPUESTOS
A67: 46108 | B67: ARCA 931 | C67: OC/2026/0149 | D67: -4772839.3 | E67: IMPUESTO (C) Obra Social Diciembre | F67: 1 | G67: 4772839.3 | H67: Unidad(es) | I67: IMPUESTO (C) | J67: OPEX | K67: VARIABLE | L67: INDIRECTO | M67: CCC _mar26 | N67: NO | O67: 0 | P67: 0 | Q67: facturas_final | R67: {3725,3925} | S67: {0.49166666,0.4916666} | T67: NOSECOMPUTA | U67: {0} | V67: 3925 | W67: NOSECOMPUTA | X67: 0.4916666 | Y67: 0 | Z67: 0 | AA67: 0 | AB67: =_xlfn.XLOOKUP(I67,'rubros_id_opex '!A:A,'rubros_id_opex '!B:B) -> 8 | AC67: =_xlfn.XLOOKUP(AB67,'rubros_unicos'!B:B,'rubros_unicos'!A:A) -> IMPUESTOS
A68: 46108 | B68: Carrizo, Juan Mario | C68: FA-C 00001-00000217 | D68: -520000 | E68: Mantenimiento (C) reparación de bomba sumergible (Bomba quemada de worms) | F68: 1 | G68: 520000 | H68: Unidad(es) | I68: Mantenimiento (C) | J68: OPEX | K68: VARIABLE | L68: DIRECTO | M68: CCC _mar26 | N68: CC1 | O68: 0 | P68: 0 | Q68: facturas_final | R68: {3725,3925} | S68: {0.49166666,0.4916666} | T68: GESTACIÓN , MATERNIDAD, SITIO 2, SITIO 3 | U68: {0.25,0.25,0.25,0.25} | V68: 3725 | W68: GESTACIÓN | X68: 0.49166666 | Y68: 0.25 | Z68: -63916.666 | AA68: 0.12291666 | AB68: =_xlfn.XLOOKUP(I68,'rubros_id_opex '!A:A,'rubros_id_opex '!B:B) -> 6 | AC68: =_xlfn.XLOOKUP(AB68,'rubros_unicos'!B:B,'rubros_unicos'!A:A) -> MANTENIMIENTO
A69: 46108 | B69: Carrizo, Juan Mario | C69: FA-C 00001-00000217 | D69: -520000 | E69: Mantenimiento (C) reparación de bomba sumergible (Bomba quemada de worms) | F69: 1 | G69: 520000 | H69: Unidad(es) | I69: Mantenimiento (C) | J69: OPEX | K69: VARIABLE | L69: DIRECTO | M69: CCC _mar26 | N69: CC1 | O69: 0 | P69: 0 | Q69: facturas_final | R69: {3725,3925} | S69: {0.49166666,0.4916666} | T69: GESTACIÓN , MATERNIDAD, SITIO 2, SITIO 3 | U69: {0.25,0.25,0.25,0.25} | V69: 3725 | W69: MATERNIDAD | X69: 0.49166666 | Y69: 0.25 | Z69: -63916.666 | AA69: 0.12291666 | AB69: =_xlfn.XLOOKUP(I69,'rubros_id_opex '!A:A,'rubros_id_opex '!B:B) -> 6 | AC69: =_xlfn.XLOOKUP(AB69,'rubros_unicos'!B:B,'rubros_unicos'!A:A) -> MANTENIMIENTO
A70: 46108 | B70: Carrizo, Juan Mario | C70: FA-C 00001-00000217 | D70: -520000 | E70: Mantenimiento (C) reparación de bomba sumergible (Bomba quemada de worms) | F70: 1 | G70: 520000 | H70: Unidad(es) | I70: Mantenimiento (C) | J70: OPEX | K70: VARIABLE | L70: DIRECTO | M70: CCC _mar26 | N70: CC1 | O70: 0 | P70: 0 | Q70: facturas_final | R70: {3725,3925} | S70: {0.49166666,0.4916666} | T70: GESTACIÓN , MATERNIDAD, SITIO 2, SITIO 3 | U70: {0.25,0.25,0.25,0.25} | V70: 3725 | W70: SITIO 2 | X70: 0.49166666 | Y70: 0.25 | Z70: -63916.666 | AA70: 0.12291666 | AB70: =_xlfn.XLOOKUP(I70,'rubros_id_opex '!A:A,'rubros_id_opex '!B:B) -> 6 | AC70: =_xlfn.XLOOKUP(AB70,'rubros_unicos'!B:B,'rubros_unicos'!A:A) -> MANTENIMIENTO
A71: 46108 | B71: Carrizo, Juan Mario | C71: FA-C 00001-00000217 | D71: -520000 | E71: Mantenimiento (C) reparación de bomba sumergible (Bomba quemada de worms) | F71: 1 | G71: 520000 | H71: Unidad(es) | I71: Mantenimiento (C) | J71: OPEX | K71: VARIABLE | L71: DIRECTO | M71: CCC _mar26 | N71: CC1 | O71: 0 | P71: 0 | Q71: facturas_final | R71: {3725,3925} | S71: {0.49166666,0.4916666} | T71: GESTACIÓN , MATERNIDAD, SITIO 2, SITIO 3 | U71: {0.25,0.25,0.25,0.25} | V71: 3725 | W71: SITIO 3 | X71: 0.49166666 | Y71: 0.25 | Z71: -63916.666 | AA71: 0.12291666 | AB71: =_xlfn.XLOOKUP(I71,'rubros_id_opex '!A:A,'rubros_id_opex '!B:B) -> 6 | AC71: =_xlfn.XLOOKUP(AB71,'rubros_unicos'!B:B,'rubros_unicos'!A:A) -> MANTENIMIENTO
A72: 46108 | B72: Carrizo, Juan Mario | C72: FA-C 00001-00000217 | D72: -520000 | E72: Mantenimiento (C) reparación de bomba sumergible (Bomba quemada de worms) | F72: 1 | G72: 520000 | H72: Unidad(es) | I72: Mantenimiento (C) | J72: OPEX | K72: VARIABLE | L72: DIRECTO | M72: CCC _mar26 | N72: CC1 | O72: 0 | P72: 0 | Q72: facturas_final | R72: {3725,3925} | S72: {0.49166666,0.4916666} | T72: GESTACIÓN , MATERNIDAD, SITIO 2, SITIO 3 | U72: {0.25,0.25,0.25,0.25} | V72: 3925 | W72: GESTACIÓN | X72: 0.4916666 | Y72: 0.25 | Z72: -63916.658 | AA72: 0.12291665 | AB72: =_xlfn.XLOOKUP(I72,'rubros_id_opex '!A:A,'rubros_id_opex '!B:B) -> 6 | AC72: =_xlfn.XLOOKUP(AB72,'rubros_unicos'!B:B,'rubros_unicos'!A:A) -> MANTENIMIENTO
A73: 46108 | B73: Carrizo, Juan Mario | C73: FA-C 00001-00000217 | D73: -520000 | E73: Mantenimiento (C) reparación de bomba sumergible (Bomba quemada de worms) | F73: 1 | G73: 520000 | H73: Unidad(es) | I73: Mantenimiento (C) | J73: OPEX | K73: VARIABLE | L73: DIRECTO | M73: CCC _mar26 | N73: CC1 | O73: 0 | P73: 0 | Q73: facturas_final | R73: {3725,3925} | S73: {0.49166666,0.4916666} | T73: GESTACIÓN , MATERNIDAD, SITIO 2, SITIO 3 | U73: {0.25,0.25,0.25,0.25} | V73: 3925 | W73: MATERNIDAD | X73: 0.4916666 | Y73: 0.25 | Z73: -63916.658 | AA73: 0.12291665 | AB73: =_xlfn.XLOOKUP(I73,'rubros_id_opex '!A:A,'rubros_id_opex '!B:B) -> 6 | AC73: =_xlfn.XLOOKUP(AB73,'rubros_unicos'!B:B,'rubros_unicos'!A:A) -> MANTENIMIENTO
A74: 46108 | B74: Carrizo, Juan Mario | C74: FA-C 00001-00000217 | D74: -520000 | E74: Mantenimiento (C) reparación de bomba sumergible (Bomba quemada de worms) | F74: 1 | G74: 520000 | H74: Unidad(es) | I74: Mantenimiento (C) | J74: OPEX | K74: VARIABLE | L74: DIRECTO | M74: CCC _mar26 | N74: CC1 | O74: 0 | P74: 0 | Q74: facturas_final | R74: {3725,3925} | S74: {0.49166666,0.4916666} | T74: GESTACIÓN , MATERNIDAD, SITIO 2, SITIO 3 | U74: {0.25,0.25,0.25,0.25} | V74: 3925 | W74: SITIO 2 | X74: 0.4916666 | Y74: 0.25 | Z74: -63916.658 | AA74: 0.12291665 | AB74: =_xlfn.XLOOKUP(I74,'rubros_id_opex '!A:A,'rubros_id_opex '!B:B) -> 6 | AC74: =_xlfn.XLOOKUP(AB74,'rubros_unicos'!B:B,'rubros_unicos'!A:A) -> MANTENIMIENTO
A75: 46108 | B75: Carrizo, Juan Mario | C75: FA-C 00001-00000217 | D75: -520000 | E75: Mantenimiento (C) reparación de bomba sumergible (Bomba quemada de worms) | F75: 1 | G75: 520000 | H75: Unidad(es) | I75: Mantenimiento (C) | J75: OPEX | K75: VARIABLE | L75: DIRECTO | M75: CCC _mar26 | N75: CC1 | O75: 0 | P75: 0 | Q75: facturas_final | R75: {3725,3925} | S75: {0.49166666,0.4916666} | T75: GESTACIÓN , MATERNIDAD, SITIO 2, SITIO 3 | U75: {0.25,0.25,0.25,0.25} | V75: 3925 | W75: SITIO 3 | X75: 0.4916666 | Y75: 0.25 | Z75: -63916.658 | AA75: 0.12291665 | AB75: =_xlfn.XLOOKUP(I75,'rubros_id_opex '!A:A,'rubros_id_opex '!B:B) -> 6 | AC75: =_xlfn.XLOOKUP(AB75,'rubros_unicos'!B:B,'rubros_unicos'!A:A) -> MANTENIMIENTO
A76: 46108 | B76: Seproa S.R.L. | C76: FA-A 00004-00006273 | D76: -104544 | E76: Gastos Operativos (C) | F76: 20 | G76: 4320 | H76: Unidad(es) | I76: Gastos Operativos (C) | J76: OPEX | K76: VARIABLE | L76: DIRECTO | M76: CCC _mar26 | N76: CC1 | O76: 0 | P76: 0 | Q76: facturas_final | R76: {3725,3925} | S76: {0.49166666,0.4916666} | T76: GESTACIÓN , MATERNIDAD, SITIO 2, SITIO 3 | U76: {0.25,0.25,0.25,0.25} | V76: 3725 | W76: GESTACIÓN | X76: 0.49166666 | Y76: 0.25 | Z76: -12850.2 | AA76: 2.4583333 | AB76: =_xlfn.XLOOKUP(I76,'rubros_id_opex '!A:A,'rubros_id_opex '!B:B) -> 7 | AC76: =_xlfn.XLOOKUP(AB76,'rubros_unicos'!B:B,'rubros_unicos'!A:A) -> GASTOS OPERATIVOS
A77: 46108 | B77: Seproa S.R.L. | C77: FA-A 00004-00006273 | D77: -104544 | E77: Gastos Operativos (C) | F77: 20 | G77: 4320 | H77: Unidad(es) | I77: Gastos Operativos (C) | J77: OPEX | K77: VARIABLE | L77: DIRECTO | M77: CCC _mar26 | N77: CC1 | O77: 0 | P77: 0 | Q77: facturas_final | R77: {3725,3925} | S77: {0.49166666,0.4916666} | T77: GESTACIÓN , MATERNIDAD, SITIO 2, SITIO 3 | U77: {0.25,0.25,0.25,0.25} | V77: 3725 | W77: MATERNIDAD | X77: 0.49166666 | Y77: 0.25 | Z77: -12850.2 | AA77: 2.4583333 | AB77: =_xlfn.XLOOKUP(I77,'rubros_id_opex '!A:A,'rubros_id_opex '!B:B) -> 7 | AC77: =_xlfn.XLOOKUP(AB77,'rubros_unicos'!B:B,'rubros_unicos'!A:A) -> GASTOS OPERATIVOS
A78: 46108 | B78: Seproa S.R.L. | C78: FA-A 00004-00006273 | D78: -104544 | E78: Gastos Operativos (C) | F78: 20 | G78: 4320 | H78: Unidad(es) | I78: Gastos Operativos (C) | J78: OPEX | K78: VARIABLE | L78: DIRECTO | M78: CCC _mar26 | N78: CC1 | O78: 0 | P78: 0 | Q78: facturas_final | R78: {3725,3925} | S78: {0.49166666,0.4916666} | T78: GESTACIÓN , MATERNIDAD, SITIO 2, SITIO 3 | U78: {0.25,0.25,0.25,0.25} | V78: 3725 | W78: SITIO 2 | X78: 0.49166666 | Y78: 0.25 | Z78: -12850.2 | AA78: 2.4583333 | AB78: 3 | AC78: =_xlfn.XLOOKUP(AB78,'rubros_unicos'!B:B,'rubros_unicos'!A:A) -> SANIDAD
A79: 46108 | B79: Seproa S.R.L. | C79: FA-A 00004-00006273 | D79: -104544 | E79: Gastos Operativos (C) | F79: 20 | G79: 4320 | H79: Unidad(es) | I79: Gastos Operativos (C) | J79: OPEX | K79: VARIABLE | L79: DIRECTO | M79: CCC _mar26 | N79: CC1 | O79: 0 | P79: 0 | Q79: facturas_final | R79: {3725,3925} | S79: {0.49166666,0.4916666} | T79: GESTACIÓN , MATERNIDAD, SITIO 2, SITIO 3 | U79: {0.25,0.25,0.25,0.25} | V79: 3725 | W79: SITIO 3 | X79: 0.49166666 | Y79: 0.25 | Z79: -12850.2 | AA79: 2.4583333 | AB79: =_xlfn.XLOOKUP(I79,'rubros_id_opex '!A:A,'rubros_id_opex '!B:B) -> 7 | AC79: =_xlfn.XLOOKUP(AB79,'rubros_unicos'!B:B,'rubros_unicos'!A:A) -> GASTOS OPERATIVOS
A80: 46108 | B80: Seproa S.R.L. | C80: FA-A 00004-00006273 | D80: -104544 | E80: Gastos Operativos (C) | F80: 20 | G80: 4320 | H80: Unidad(es) | I80: Gastos Operativos (C) | J80: OPEX | K80: VARIABLE | L80: DIRECTO | M80: CCC _mar26 | N80: CC1 | O80: 0 | P80: 0 | Q80: facturas_final | R80: {3725,3925} | S80: {0.49166666,0.4916666} | T80: GESTACIÓN , MATERNIDAD, SITIO 2, SITIO 3 | U80: {0.25,0.25,0.25,0.25} | V80: 3925 | W80: GESTACIÓN | X80: 0.4916666 | Y80: 0.25 | Z80: -12850.198 | AA80: 2.458333 | AB80: =_xlfn.XLOOKUP(I80,'rubros_id_opex '!A:A,'rubros_id_opex '!B:B) -> 7 | AC80: =_xlfn.XLOOKUP(AB80,'rubros_unicos'!B:B,'rubros_unicos'!A:A) -> GASTOS OPERATIVOS
A81: 46108 | B81: Seproa S.R.L. | C81: FA-A 00004-00006273 | D81: -104544 | E81: Gastos Operativos (C) | F81: 20 | G81: 4320 | H81: Unidad(es) | I81: Gastos Operativos (C) | J81: OPEX | K81: VARIABLE | L81: DIRECTO | M81: CCC _mar26 | N81: CC1 | O81: 0 | P81: 0 | Q81: facturas_final | R81: {3725,3925} | S81: {0.49166666,0.4916666} | T81: GESTACIÓN , MATERNIDAD, SITIO 2, SITIO 3 | U81: {0.25,0.25,0.25,0.25} | V81: 3925 | W81: MATERNIDAD | X81: 0.4916666 | Y81: 0.25 | Z81: -12850.198 | AA81: 2.458333 | AB81: =_xlfn.XLOOKUP(I81,'rubros_id_opex '!A:A,'rubros_id_opex '!B:B) -> 7 | AC81: =_xlfn.XLOOKUP(AB81,'rubros_unicos'!B:B,'rubros_unicos'!A:A) -> GASTOS OPERATIVOS
A82: 46108 | B82: Seproa S.R.L. | C82: FA-A 00004-00006273 | D82: -104544 | E82: Gastos Operativos (C) | F82: 20 | G82: 4320 | H82: Unidad(es) | I82: Gastos Operativos (C) | J82: OPEX | K82: VARIABLE | L82: DIRECTO | M82: CCC _mar26 | N82: CC1 | O82: 0 | P82: 0 | Q82: facturas_final | R82: {3725,3925} | S82: {0.49166666,0.4916666} | T82: GESTACIÓN , MATERNIDAD, SITIO 2, SITIO 3 | U82: {0.25,0.25,0.25,0.25} | V82: 3925 | W82: SITIO 2 | X82: 0.4916666 | Y82: 0.25 | Z82: -12850.198 | AA82: 2.458333 | AB82: =_xlfn.XLOOKUP(I82,'rubros_id_opex '!A:A,'rubros_id_opex '!B:B) -> 7 | AC82: =_xlfn.XLOOKUP(AB82,'rubros_unicos'!B:B,'rubros_unicos'!A:A) -> GASTOS OPERATIVOS
A83: 46108 | B83: Seproa S.R.L. | C83: FA-A 00004-00006273 | D83: -104544 | E83: Gastos Operativos (C) | F83: 20 | G83: 4320 | H83: Unidad(es) | I83: Gastos Operativos (C) | J83: OPEX | K83: VARIABLE | L83: DIRECTO | M83: CCC _mar26 | N83: CC1 | O83: 0 | P83: 0 | Q83: facturas_final | R83: {3725,3925} | S83: {0.49166666,0.4916666} | T83: GESTACIÓN , MATERNIDAD, SITIO 2, SITIO 3 | U83: {0.25,0.25,0.25,0.25} | V83: 3925 | W83: SITIO 3 | X83: 0.4916666 | Y83: 0.25 | Z83: -12850.198 | AA83: 2.458333 | AB83: =_xlfn.XLOOKUP(I83,'rubros_id_opex '!A:A,'rubros_id_opex '!B:B) -> 7 | AC83: =_xlfn.XLOOKUP(AB83,'rubros_unicos'!B:B,'rubros_unicos'!A:A) -> GASTOS OPERATIVOS
A84: 46107 | B84: Servicio Nacional De Sanidad Y Calidad Agroalimentaria Senasa | C84: OC/2026/0148 | D84: -10785.37 | E84: IMPUESTO (C) | F84: 1 | G84: 10785.37 | H84: Unidad(es) | I84: IMPUESTO (C) | J84: OPEX | K84: FIJO | L84: DIRECTO | M84: CCC _mar26 | N84: NO | O84: 0 | P84: 0 | Q84: facturas_final | R84: {3725,3925} | S84: {0.49166666,0.4916666} | T84: NOSECOMPUTA | U84: {0} | V84: 3725 | W84: NOSECOMPUTA | X84: 0.49166666 | Y84: 0 | Z84: 0 | AA84: 0 | AB84: =_xlfn.XLOOKUP(I84,'rubros_id_opex '!A:A,'rubros_id_opex '!B:B) -> 8 | AC84: =_xlfn.XLOOKUP(AB84,'rubros_unicos'!B:B,'rubros_unicos'!A:A) -> IMPUESTOS
A85: 46107 | B85: Servicio Nacional De Sanidad Y Calidad Agroalimentaria Senasa | C85: OC/2026/0148 | D85: -10785.37 | E85: IMPUESTO (C) | F85: 1 | G85: 10785.37 | H85: Unidad(es) | I85: IMPUESTO (C) | J85: OPEX | K85: FIJO | L85: DIRECTO | M85: CCC _mar26 | N85: NO | O85: 0 | P85: 0 | Q85: facturas_final | R85: {3725,3925} | S85: {0.49166666,0.4916666} | T85: NOSECOMPUTA | U85: {0} | V85: 3925 | W85: NOSECOMPUTA | X85: 0.4916666 | Y85: 0 | Z85: 0 | AA85: 0 | AB85: =_xlfn.XLOOKUP(I85,'rubros_id_opex '!A:A,'rubros_id_opex '!B:B) -> 8 | AC85: =_xlfn.XLOOKUP(AB85,'rubros_unicos'!B:B,'rubros_unicos'!A:A) -> IMPUESTOS
A86: 46107 | B86: ARCA | C86: OC/2026/0146 | D86: -99904 | E86: IMPUESTO (C) vep para liquidación 0314301035 | F86: 1 | G86: 53520 | H86: Unidad(es) | I86: IMPUESTO (C) | J86: OPEX | K86: VARIABLE | L86: INDIRECTO | M86: CCC _mar26 | N86: NO | O86: 0 | P86: 0 | Q86: facturas_final | R86: {3725,3925} | S86: {0.49166666,0.4916666} | T86: NOSECOMPUTA | U86: {0} | V86: 3725 | W86: NOSECOMPUTA | X86: 0.49166666 | Y86: 0 | Z86: 0 | AA86: 0 | AB86: =_xlfn.XLOOKUP(I86,'rubros_id_opex '!A:A,'rubros_id_opex '!B:B) -> 8 | AC86: =_xlfn.XLOOKUP(AB86,'rubros_unicos'!B:B,'rubros_unicos'!A:A) -> IMPUESTOS
A87: 46107 | B87: ARCA | C87: OC/2026/0146 | D87: -99904 | E87: IMPUESTO (C) vep para liquidación 0314301035 | F87: 1 | G87: 53520 | H87: Unidad(es) | I87: IMPUESTO (C) | J87: OPEX | K87: VARIABLE | L87: INDIRECTO | M87: CCC _mar26 | N87: NO | O87: 0 | P87: 0 | Q87: facturas_final | R87: {3725,3925} | S87: {0.49166666,0.4916666} | T87: NOSECOMPUTA | U87: {0} | V87: 3925 | W87: NOSECOMPUTA | X87: 0.4916666 | Y87: 0 | Z87: 0 | AA87: 0 | AB87: =_xlfn.XLOOKUP(I87,'rubros_id_opex '!A:A,'rubros_id_opex '!B:B) -> 8 | AC87: =_xlfn.XLOOKUP(AB87,'rubros_unicos'!B:B,'rubros_unicos'!A:A) -> IMPUESTOS
A88: 46107 | B88: Trt S.A. | C88: FA-A 00012-00058166 | D88: -31264.73 | E88: Sanidad (C) Guantes de nitrilo | F88: 7 | G88: 3670 | H88: Unidad(es) | I88: Sanidad (C) | J88: OPEX | K88: VARIABLE | L88: DIRECTO | M88: CCC _mar26 | N88: NO | O88: 0 | P88: 0 | Q88: facturas_final | R88: {3725,3925} | S88: {0.49166666,0.4916666} | T88: NOSECOMPUTA | U88: {0} | V88: 3725 | W88: NOSECOMPUTA | X88: 0.49166666 | Y88: 0 | Z88: 0 | AA88: 0 | AB88: =_xlfn.XLOOKUP(I88,'rubros_id_opex '!A:A,'rubros_id_opex '!B:B) -> 3 | AC88: =_xlfn.XLOOKUP(AB88,'rubros_unicos'!B:B,'rubros_unicos'!A:A) -> SANIDAD
