Workbook

Sheet lote_todos
A1: LOTE | B1: >=0 | C1: Mortandad-SITIO 2 | G1: CALZIM
C2: Mortandad-SITIO 3 | D2: =SUMIFS(produccion!G:G,produccion!$A:$A,B1) -> -0.10922097
B5: TOTALES | F5: FIJO/VARIABLE | J5: DIRECTO/INDERECTO
B6: VENTAS SITIO 3 | C6: =D55 -> 2.9089607e+08 | F6: VENTAS | G6: =C6 -> 2.9089607e+08 | J6: VENTAS | K6: =G6 -> 2.9089607e+08
B7: OPEX | C7: =SUMIFS(BBDD_GASTOS_FINAL!$Z:$Z,BBDD_GASTOS_FINAL!$V:$V,lote_todos!$B$1,BBDD_GASTOS_FINAL!$J:$J,"OPEX")*-1 -> 2.4220987e+08 | F7: Fijo | G7: =SUMIFS(BBDD_GASTOS_FINAL!$Z:$Z,BBDD_GASTOS_FINAL!$V:$V,lote_todos!$B$1,BBDD_GASTOS_FINAL!$J:$J,"OPEX",BBDD_GASTOS_FINAL!$K:$K,lote_todos!F7)*-1 -> 57882220 | J7: DIRECTO | K7: =SUMIFS(BBDD_GASTOS_FINAL!$Z:$Z,BBDD_GASTOS_FINAL!$V:$V,lote_todos!$B$1,BBDD_GASTOS_FINAL!$J:$J,"OPEX",BBDD_GASTOS_FINAL!$L:$L,lote_todos!J7)*-1 -> 1.8432765e+08
B8: UTILIDAD | C8: =C6-C7 -> 48686199 | F8: Variable | G8: =SUMIFS(BBDD_GASTOS_FINAL!$Z:$Z,BBDD_GASTOS_FINAL!$V:$V,lote_todos!$B$1,BBDD_GASTOS_FINAL!$J:$J,"OPEX",BBDD_GASTOS_FINAL!$K:$K,lote_todos!F8)*-1 -> 1.8432765e+08 | J8: INDIRECTO | K8: =SUMIFS(BBDD_GASTOS_FINAL!$Z:$Z,BBDD_GASTOS_FINAL!$V:$V,lote_todos!$B$1,BBDD_GASTOS_FINAL!$J:$J,"OPEX",BBDD_GASTOS_FINAL!$L:$L,lote_todos!J8)*-1 -> 57882220
B9: CAPEX | C9: =SUMIFS(BBDD_GASTOS_FINAL!$Y:$Y,BBDD_GASTOS_FINAL!$J:$J,lote_todos!B9) -> 0
B10: DEUDA | C10: =SUMIFS(BBDD_GASTOS_FINAL!$Y:$Y,BBDD_GASTOS_FINAL!$J:$J,lote_todos!B10) -> 0
B11: Flujo de Caja al Accionista | C11: =C6-C7-C9-C10 -> 48686199 | F11: Flujo de Caja al Accionista | G11: =G6-G7-G8 -> 48686199 | J11: Flujo de Caja al Accionista | K11: =K6-K7-K8 -> 48686199
A13: id | B13: 4 | E13: id | F13: 3 | I13: id | J13: 7 | M13: id
B14: GESTACIÓN | F14: MATERNIDAD | J14: SITIO 2
B15: OPEX | D15: =SUM(D16:D26) -> 42027260 | F15: OPEX | H15: =SUM(H16:H26) -> 38468397 | J15: OPEX | L15: =SUM(L16:L26) -> 38468397 | M15: 1
A16: 1 | B16: =D16/$D$15 -> 0.45344634 | C16: NUTRICIÓN | D16: =SUMIFS(BBDD_GASTOS_FINAL!$Z:$Z,BBDD_GASTOS_FINAL!$V:$V,$B$1,BBDD_GASTOS_FINAL!$W:$W,$B$14,BBDD_GASTOS_FINAL!$AC:$AC,lote_todos!$C16)*-1 -> 19057107 | E16: 1 | F16: =H16/$H$15 -> 0.32717862 | G16: NUTRICIÓN | H16: =SUMIFS(BBDD_GASTOS_FINAL!$Z:$Z,BBDD_GASTOS_FINAL!$V:$V,$B$1,BBDD_GASTOS_FINAL!$W:$W,$F$14,BBDD_GASTOS_FINAL!$AC:$AC,$G16)*-1 -> 12586037 | I16: 1 | J16: =L16/$L$15 -> 0.32717862 | K16: NUTRICIÓN | L16: =SUMIFS(BBDD_GASTOS_FINAL!$Z:$Z,BBDD_GASTOS_FINAL!$V:$V,$B$1,BBDD_GASTOS_FINAL!$W:$W,$F$14,BBDD_GASTOS_FINAL!$AC:$AC,$G16)*-1 -> 12586037 | M16: 1
A17: =A16+1 -> 2 | B17: =D17/$D$15 -> 0.24396498 | C17: PERSONAL | D17: =SUMIFS(BBDD_GASTOS_FINAL!$Z:$Z,BBDD_GASTOS_FINAL!$V:$V,$B$1,BBDD_GASTOS_FINAL!$W:$W,$B$14,BBDD_GASTOS_FINAL!AC:AC,lote_todos!$C17)*-1 -> 10253180 | E17: 2 | F17: =H17/$H$15 -> 0.45367868 | G17: PERSONAL | H17: =SUMIFS(BBDD_GASTOS_FINAL!$Z:$Z,BBDD_GASTOS_FINAL!$V:$V,$B$1,BBDD_GASTOS_FINAL!$W:$W,$F$14,BBDD_GASTOS_FINAL!$AC:$AC,$G17)*-1 -> 17452292 | I17: =I16+1 -> 2 | J17: =L17/$L$15 -> 0.45367868 | K17: PERSONAL | L17: =SUMIFS(BBDD_GASTOS_FINAL!$Z:$Z,BBDD_GASTOS_FINAL!$V:$V,$B$1,BBDD_GASTOS_FINAL!$W:$W,$F$14,BBDD_GASTOS_FINAL!$AC:$AC,$G17)*-1 -> 17452292 | M17: =M16+1 -> 2
A18: =A17+1 -> 3 | B18: =D18/$D$15 -> 0.028461913 | C18: SANIDAD | D18: =SUMIFS(BBDD_GASTOS_FINAL!$Z:$Z,BBDD_GASTOS_FINAL!$V:$V,$B$1,BBDD_GASTOS_FINAL!$W:$W,$B$14,BBDD_GASTOS_FINAL!AC:AC,lote_todos!$C18)*-1 -> 1196176.2 | E18: 3 | F18: =H18/$H$15 -> 0.018338364 | G18: SANIDAD | H18: =SUMIFS(BBDD_GASTOS_FINAL!$Z:$Z,BBDD_GASTOS_FINAL!$V:$V,$B$1,BBDD_GASTOS_FINAL!$W:$W,$F$14,BBDD_GASTOS_FINAL!$AC:$AC,$G18)*-1 -> 705447.48 | I18: =I17+12 -> 14 | J18: =L18/$L$15 -> 0.018338364 | K18: SANIDAD | L18: =SUMIFS(BBDD_GASTOS_FINAL!$Z:$Z,BBDD_GASTOS_FINAL!$V:$V,$B$1,BBDD_GASTOS_FINAL!$W:$W,$F$14,BBDD_GASTOS_FINAL!$AC:$AC,$G18)*-1 -> 705447.48 | M18: =M17+1 -> 3
A19: =A18+1 -> 4 | B19: =D19/$D$15 -> 0.13771462 | C19: GENÉTICA | D19: =SUMIFS(BBDD_GASTOS_FINAL!$Z:$Z,BBDD_GASTOS_FINAL!$V:$V,$B$1,BBDD_GASTOS_FINAL!$W:$W,$B$14,BBDD_GASTOS_FINAL!AC:AC,lote_todos!$C19)*-1 -> 5787768 | E19: 4 | F19: =H19/$H$15 -> 0 | G19: GENÉTICA | H19: =SUMIFS(BBDD_GASTOS_FINAL!$Z:$Z,BBDD_GASTOS_FINAL!$V:$V,$B$1,BBDD_GASTOS_FINAL!$W:$W,$F$14,BBDD_GASTOS_FINAL!$AC:$AC,$G19)*-1 -> 0 | I19: =I18+1 -> 15 | J19: =L19/$L$15 -> 0 | K19: GENÉTICA | L19: =SUMIFS(BBDD_GASTOS_FINAL!$Z:$Z,BBDD_GASTOS_FINAL!$V:$V,$B$1,BBDD_GASTOS_FINAL!$W:$W,$F$14,BBDD_GASTOS_FINAL!$AC:$AC,$G19)*-1 -> 0 | M19: =M18+1 -> 4
A20: =A19+1 -> 5 | B20: =D20/$D$15 -> 0 | C20: FLETES | D20: =SUMIFS(BBDD_GASTOS_FINAL!$Z:$Z,BBDD_GASTOS_FINAL!$V:$V,$B$1,BBDD_GASTOS_FINAL!$W:$W,$B$14,BBDD_GASTOS_FINAL!AC:AC,lote_todos!$C20)*-1 -> 0 | E20: 5 | F20: =H20/$H$15 -> 0 | G20: FLETES | H20: =SUMIFS(BBDD_GASTOS_FINAL!$Z:$Z,BBDD_GASTOS_FINAL!$V:$V,$B$1,BBDD_GASTOS_FINAL!$W:$W,$F$14,BBDD_GASTOS_FINAL!$AC:$AC,$G20)*-1 -> 0 | I20: =I19+1 -> 16 | J20: =L20/$L$15 -> 0 | K20: FLETES | L20: =SUMIFS(BBDD_GASTOS_FINAL!$Z:$Z,BBDD_GASTOS_FINAL!$V:$V,$B$1,BBDD_GASTOS_FINAL!$W:$W,$F$14,BBDD_GASTOS_FINAL!$AC:$AC,$G20)*-1 -> 0 | M20: =M19+1 -> 5
A21: =A20+1 -> 6 | B21: =D21/$D$15 -> 0 | C21: ENERGÍA | D21: =SUMIFS(BBDD_GASTOS_FINAL!$Z:$Z,BBDD_GASTOS_FINAL!$V:$V,$B$1,BBDD_GASTOS_FINAL!$W:$W,$B$14,BBDD_GASTOS_FINAL!AC:AC,lote_todos!$C21)*-1 -> 0 | E21: 6 | F21: =H21/$H$15 -> 0 | G21: ENERGÍA | H21: =SUMIFS(BBDD_GASTOS_FINAL!$Z:$Z,BBDD_GASTOS_FINAL!$V:$V,$B$1,BBDD_GASTOS_FINAL!$W:$W,$F$14,BBDD_GASTOS_FINAL!$AC:$AC,$G21)*-1 -> 0 | I21: =I20+1 -> 17 | J21: =L21/$L$15 -> 0 | K21: ENERGÍA | L21: =SUMIFS(BBDD_GASTOS_FINAL!$Z:$Z,BBDD_GASTOS_FINAL!$V:$V,$B$1,BBDD_GASTOS_FINAL!$W:$W,$F$14,BBDD_GASTOS_FINAL!$AC:$AC,$G21)*-1 -> 0 | M21: =M20+1 -> 6
A22: =A21+1 -> 7 | B22: =D22/$D$15 -> 0 | C22: MENTENIMIENTO | D22: =SUMIFS(BBDD_GASTOS_FINAL!$Z:$Z,BBDD_GASTOS_FINAL!$V:$V,$B$1,BBDD_GASTOS_FINAL!$W:$W,$B$14,BBDD_GASTOS_FINAL!AC:AC,lote_todos!$C22)*-1 -> 0 | E22: 7 | F22: =H22/$H$15 -> 0 | G22: MENTENIMIENTO | H22: =SUMIFS(BBDD_GASTOS_FINAL!$Z:$Z,BBDD_GASTOS_FINAL!$V:$V,$B$1,BBDD_GASTOS_FINAL!$W:$W,$F$14,BBDD_GASTOS_FINAL!$AC:$AC,$G22)*-1 -> 0 | I22: =I21+1 -> 18 | J22: =L22/$L$15 -> 0 | K22: MENTENIMIENTO | L22: =SUMIFS(BBDD_GASTOS_FINAL!$Z:$Z,BBDD_GASTOS_FINAL!$V:$V,$B$1,BBDD_GASTOS_FINAL!$W:$W,$F$14,BBDD_GASTOS_FINAL!$AC:$AC,$G22)*-1 -> 0 | M22: =M21+1 -> 7
A23: =A22+1 -> 8 | B23: =D23/$D$15 -> 0.073084317 | C23: GASTOS OPERATIVOS | D23: =SUMIFS(BBDD_GASTOS_FINAL!$Z:$Z,BBDD_GASTOS_FINAL!$V:$V,$B$1,BBDD_GASTOS_FINAL!$W:$W,$B$14,BBDD_GASTOS_FINAL!AC:AC,lote_todos!$C23)*-1 -> 3071533.6 | E23: 8 | F23: =H23/$H$15 -> 0.079845634 | G23: GASTOS OPERATIVOS | H23: =SUMIFS(BBDD_GASTOS_FINAL!$Z:$Z,BBDD_GASTOS_FINAL!$V:$V,$B$1,BBDD_GASTOS_FINAL!$W:$W,$F$14,BBDD_GASTOS_FINAL!$AC:$AC,$G23)*-1 -> 3071533.6 | I23: =I22+1 -> 19 | J23: =L23/$L$15 -> 0.079845634 | K23: GASTOS OPERATIVOS | L23: =SUMIFS(BBDD_GASTOS_FINAL!$Z:$Z,BBDD_GASTOS_FINAL!$V:$V,$B$1,BBDD_GASTOS_FINAL!$W:$W,$F$14,BBDD_GASTOS_FINAL!$AC:$AC,$G23)*-1 -> 3071533.6 | M23: =M22+1 -> 8
A24: =A23+1 -> 9 | B24: =D24/$D$15 -> 0.042922279 | C24: IMPUESTOS | D24: =SUMIFS(BBDD_GASTOS_FINAL!$Z:$Z,BBDD_GASTOS_FINAL!$V:$V,$B$1,BBDD_GASTOS_FINAL!$W:$W,$B$14,BBDD_GASTOS_FINAL!AC:AC,lote_todos!$C24)*-1 -> 1803905.8 | E24: 9 | F24: =H24/$H$15 -> 0.098665348 | G24: IMPUESTOS | H24: =SUMIFS(BBDD_GASTOS_FINAL!$Z:$Z,BBDD_GASTOS_FINAL!$V:$V,$B$1,BBDD_GASTOS_FINAL!$W:$W,$F$14,BBDD_GASTOS_FINAL!$AC:$AC,$G24)*-1 -> 3795497.8 | I24: =I23+1 -> 20 | J24: =L24/$L$15 -> 0.098665348 | K24: IMPUESTOS | L24: =SUMIFS(BBDD_GASTOS_FINAL!$Z:$Z,BBDD_GASTOS_FINAL!$V:$V,$B$1,BBDD_GASTOS_FINAL!$W:$W,$F$14,BBDD_GASTOS_FINAL!$AC:$AC,$G24)*-1 -> 3795497.8 | M24: =M23+1 -> 9
A25: =A24+1 -> 10 | B25: =D25/$D$15 -> 0.020405554 | C25: HONORARIOS | D25: =SUMIFS(BBDD_GASTOS_FINAL!$Z:$Z,BBDD_GASTOS_FINAL!$V:$V,$B$1,BBDD_GASTOS_FINAL!$W:$W,$B$14,BBDD_GASTOS_FINAL!AC:AC,lote_todos!$C25)*-1 -> 857589.52 | E25: 10 | F25: =H25/$H$15 -> 0.022293352 | G25: HONORARIOS | H25: =SUMIFS(BBDD_GASTOS_FINAL!$Z:$Z,BBDD_GASTOS_FINAL!$V:$V,$B$1,BBDD_GASTOS_FINAL!$W:$W,$F$14,BBDD_GASTOS_FINAL!$AC:$AC,$G25)*-1 -> 857589.52 | I25: =I24+1 -> 21 | J25: =L25/$L$15 -> 0.022293352 | K25: HONORARIOS | L25: =SUMIFS(BBDD_GASTOS_FINAL!$Z:$Z,BBDD_GASTOS_FINAL!$V:$V,$B$1,BBDD_GASTOS_FINAL!$W:$W,$F$14,BBDD_GASTOS_FINAL!$AC:$AC,$G25)*-1 -> 857589.52 | M25: =M24+1 -> 10
B26: =D26/$D$15 -> 0 | C26: SERVICIOS | D26: =SUMIFS(BBDD_GASTOS_FINAL!$Z:$Z,BBDD_GASTOS_FINAL!$V:$V,$B$1,BBDD_GASTOS_FINAL!$W:$W,$B$14,BBDD_GASTOS_FINAL!AC:AC,lote_todos!$C26)*-1 -> 0 | F26: =H26/$H$15 -> 0 | G26: SERVICIOS | H26: =SUMIFS(BBDD_GASTOS_FINAL!$Z:$Z,BBDD_GASTOS_FINAL!$V:$V,$B$1,BBDD_GASTOS_FINAL!$W:$W,$F$14,BBDD_GASTOS_FINAL!$AC:$AC,$G26)*-1 -> 0 | J26: =L26/$L$15 -> 0 | K26: OTROS | L26: =SUMIFS(BBDD_GASTOS_FINAL!$Z:$Z,BBDD_GASTOS_FINAL!$V:$V,$B$1,BBDD_GASTOS_FINAL!$W:$W,$F$14,BBDD_GASTOS_FINAL!$AC:$AC,$G26)*-1 -> 0
F28: COMPRAS EN GESTACION | H28: =D15 -> 42027260 | J28: COMPRAS EN MATERNIDAD | L28: =H29 -> 55488352
B29: VENTAS | D29: =SUMIFS(produccion!$H:$H,produccion!$A:$A,lote_todos!$B$1,produccion!$B:$B,lote_todos!B14) -> 0 | F29: VENTAS | H29: =SUMIFS(produccion!$H:$H,produccion!$A:$A,lote_todos!$B$1,produccion!$B:$B,lote_todos!F14) -> 55488352 | J29: VENTAS | L29: =SUMIFS(produccion!$H:$H,produccion!$A:$A,lote_todos!$B$1,produccion!$B:$B,lote_todos!J14) -> 1.0141986e+08
B31: UTILDAD | D31: =D29-D15-D28 -> -42027260 | F31: UTILDAD | H31: =H29-H15-H28 -> -25007306 | J31: UTILDAD | L31: =L29-L15-L28 -> 7463113.8
B33: CAPEX | D33: =SUMIFS(BBDD_GASTOS_FINAL!$Y:$Y,BBDD_GASTOS_FINAL!$J:$J,"Capex",BBDD_GASTOS_FINAL!$Z:$Z,$B$13) -> 0 | F33: CAPEX | H33: =SUMIFS(BBDD_GASTOS_FINAL!$Y:$Y,BBDD_GASTOS_FINAL!$J:$J,"Capex",BBDD_GASTOS_FINAL!$Z:$Z,$F$13) -> 0 | J33: CAPEX | L33: =SUMIFS(BBDD_GASTOS_FINAL!$Y:$Y,BBDD_GASTOS_FINAL!$J:$J,"Capex",BBDD_GASTOS_FINAL!$Z:$Z,$J$13) -> 0
B35: DEUDA | D35: =SUMIFS(BBDD_GASTOS_FINAL!$Y:$Y,BBDD_GASTOS_FINAL!$J:$J,"Deuda",BBDD_GASTOS_FINAL!$V:$V,B14) -> 0 | F35: DEUDA | H35: =SUMIFS(BBDD_GASTOS_FINAL!$Y:$Y,BBDD_GASTOS_FINAL!$J:$J,"Deuda",BBDD_GASTOS_FINAL!$V:$V,F14) -> 0 | J35: DEUDA | L35: =SUMIFS(BBDD_GASTOS_FINAL!$Y:$Y,BBDD_GASTOS_FINAL!$J:$J,"deuda",BBDD_GASTOS_FINAL!$V:$V,J14) -> 0
B37: Flujo de Caja al Accionista | D37: =D31-D35-D33 -> -42027260 | F37: Flujo de Caja al Accionista | H37: =H31-H35-H33 -> -25007306 | J37: Flujo de Caja al Accionista | L37: =L31-L35-L33 -> 7463113.8
F38: Margen de utilidad | H38: =H31/H29 -> -0.45067667 | J38: Margen de utilidad | L38: =L31/L29 -> 0.073586313
A39: id | B39: 1 | M39: id
B40: SITIO 3
B41: OPEX | D41: =SUM(D42:D52) -> 1.2527843e+08
A42: 1 | B42: =D42/$D$41 -> 0.84455914 | C42: NUTRICIÓN | D42: =SUMIFS(BBDD_GASTOS_FINAL!$Z:$Z,BBDD_GASTOS_FINAL!$V:$V,$B$1,BBDD_GASTOS_FINAL!$W:$W,$B$40,BBDD_GASTOS_FINAL!$AC:$AC,lote_todos!$C42)*-1 -> 1.0580504e+08
A43: =A42+1 -> 2 | B43: =D43/$D$41 -> 0.075202595 | C43: PERSONAL | D43: =SUMIFS(BBDD_GASTOS_FINAL!$Z:$Z,BBDD_GASTOS_FINAL!$V:$V,$B$1,BBDD_GASTOS_FINAL!$W:$W,$B$40,BBDD_GASTOS_FINAL!AC:AC,lote_todos!$C43)*-1 -> 9421263
A44: =A43+1 -> 3 | B44: =D44/$D$41 -> 0 | C44: SANIDAD | D44: =SUMIFS(BBDD_GASTOS_FINAL!$Z:$Z,BBDD_GASTOS_FINAL!$V:$V,$B$1,BBDD_GASTOS_FINAL!$W:$W,$B$40,BBDD_GASTOS_FINAL!AC:AC,lote_todos!$C44)*-1 -> 0
A45: =A44+1 -> 4 | B45: =D45/$D$41 -> 0 | C45: GENÉTICA | D45: =SUMIFS(BBDD_GASTOS_FINAL!$Z:$Z,BBDD_GASTOS_FINAL!$V:$V,$B$1,BBDD_GASTOS_FINAL!$W:$W,$B$40,BBDD_GASTOS_FINAL!AC:AC,lote_todos!$C45)*-1 -> 0
A46: =A45+1 -> 5 | B46: =D46/$D$41 -> 0.034475965 | C46: FLETES | D46: =SUMIFS(BBDD_GASTOS_FINAL!$Z:$Z,BBDD_GASTOS_FINAL!$V:$V,$B$1,BBDD_GASTOS_FINAL!$W:$W,$B$40,BBDD_GASTOS_FINAL!AC:AC,lote_todos!$C46)*-1 -> 4319094.7
A47: =A46+1 -> 6 | B47: =D47/$D$41 -> 0 | C47: ENERGÍA | D47: =SUMIFS(BBDD_GASTOS_FINAL!$Z:$Z,BBDD_GASTOS_FINAL!$V:$V,$B$1,BBDD_GASTOS_FINAL!$W:$W,$B$40,BBDD_GASTOS_FINAL!AC:AC,lote_todos!$C47)*-1 -> 0
A48: =A47+1 -> 7 | B48: =D48/$D$41 -> 0 | C48: MENTENIMIENTO | D48: =SUMIFS(BBDD_GASTOS_FINAL!$Z:$Z,BBDD_GASTOS_FINAL!$V:$V,$B$1,BBDD_GASTOS_FINAL!$W:$W,$B$40,BBDD_GASTOS_FINAL!AC:AC,lote_todos!$C48)*-1 -> 0
A49: =A48+1 -> 8 | B49: =D49/$D$41 -> 0.024517657 | C49: GASTOS OPERATIVOS | D49: =SUMIFS(BBDD_GASTOS_FINAL!$Z:$Z,BBDD_GASTOS_FINAL!$V:$V,$B$1,BBDD_GASTOS_FINAL!$W:$W,$B$40,BBDD_GASTOS_FINAL!AC:AC,lote_todos!$C49)*-1 -> 3071533.6
A50: =A49+1 -> 9 | B50: =D50/$D$41 -> 0.014399173 | C50: IMPUESTOS | D50: =SUMIFS(BBDD_GASTOS_FINAL!$Z:$Z,BBDD_GASTOS_FINAL!$V:$V,$B$1,BBDD_GASTOS_FINAL!$W:$W,$B$40,BBDD_GASTOS_FINAL!AC:AC,lote_todos!$C50)*-1 -> 1803905.8
A51: =A50+1 -> 10 | B51: =D51/$D$41 -> 0.0068454683 | C51: HONORARIOS | D51: =SUMIFS(BBDD_GASTOS_FINAL!$Z:$Z,BBDD_GASTOS_FINAL!$V:$V,$B$1,BBDD_GASTOS_FINAL!$W:$W,$B$40,BBDD_GASTOS_FINAL!AC:AC,lote_todos!$C51)*-1 -> 857589.52
B52: =D52/$D$41 -> 0 | C52: SERVICIOS | D52: =SUMIFS(BBDD_GASTOS_FINAL!$Z:$Z,BBDD_GASTOS_FINAL!$V:$V,$B$1,BBDD_GASTOS_FINAL!$W:$W,$B$40,BBDD_GASTOS_FINAL!AC:AC,lote_todos!$C52)*-1 -> 0
B54: COMPRAS EN SITIO 2 | D54: =L29 -> 1.0141986e+08
B55: VENTAS | D55: =SUMIFS(produccion!$H:$H,produccion!$A:$A,lote_todos!$B$1,produccion!$B:$B,lote_todos!B40) -> 2.9089607e+08
B57: UTILDAD | D57: =D55-D41-D54 -> 64197773
B59: CAPEX | D59: =SUMIFS(BBDD_GASTOS_FINAL!$Y:$Y,BBDD_GASTOS_FINAL!$J:$J,"Capex",BBDD_GASTOS_FINAL!$Z:$Z,$B$39) -> 0
B61: DEUDA | D61: =SUMIFS(BBDD_GASTOS_FINAL!$Y:$Y,BBDD_GASTOS_FINAL!$J:$J,"deuda",BBDD_GASTOS_FINAL!$V:$V,B40) -> 0
B63: Flujo de Caja al Accionista | D63: =D57-D61-D59 -> 64197773
B64: Margen de utilidad | D64: =D57/D55 -> 0.22068973
A65: id | B65: 9 | E65: id
A66: LOTE | B66: =B1 -> >=0
A67: TOTAL | B67: <> & ""
B68: OPEX | D68: =SUM(D69:D79) -> 2.4235303e+08
B69: =D69/$D$68 -> 0.63939177 | C69: NUTRICIÓN | D69: =SUMIFS(BBDD_GASTOS_FINAL!$Z:$Z,BBDD_GASTOS_FINAL!$V:$V,$B$1,BBDD_GASTOS_FINAL!$W:$W,$B$67,BBDD_GASTOS_FINAL!$AC:$AC,lote_todos!$C69)*-1 -> 1.5495853e+08
B70: =D70/$D$68 -> 0.18695505 | C70: PERSONAL | D70: =SUMIFS(BBDD_GASTOS_FINAL!$Z:$Z,BBDD_GASTOS_FINAL!$V:$V,$B$1,BBDD_GASTOS_FINAL!$W:$W,$B$67,BBDD_GASTOS_FINAL!$AC:$AC,lote_todos!$C70)*-1 -> 45309123
B71: =D71/$D$68 -> 0.028784942 | C71: SANIDAD | D71: =SUMIFS(BBDD_GASTOS_FINAL!$Z:$Z,BBDD_GASTOS_FINAL!$V:$V,$B$1,BBDD_GASTOS_FINAL!$W:$W,$B$67,BBDD_GASTOS_FINAL!$AC:$AC,lote_todos!$C71)*-1 -> 6976117.9
B72: =D72/$D$68 -> 0.023881558 | C72: GENÉTICA | D72: =SUMIFS(BBDD_GASTOS_FINAL!$Z:$Z,BBDD_GASTOS_FINAL!$V:$V,$B$1,BBDD_GASTOS_FINAL!$W:$W,$B$67,BBDD_GASTOS_FINAL!$AC:$AC,lote_todos!$C72)*-1 -> 5787768
B73: =D73/$D$68 -> 0.017821501 | C73: FLETES | D73: =SUMIFS(BBDD_GASTOS_FINAL!$Z:$Z,BBDD_GASTOS_FINAL!$V:$V,$B$1,BBDD_GASTOS_FINAL!$W:$W,$B$67,BBDD_GASTOS_FINAL!$AC:$AC,lote_todos!$C73)*-1 -> 4319094.7
B74: =D74/$D$68 -> 0 | C74: ENERGÍA | D74: =SUMIFS(BBDD_GASTOS_FINAL!$Z:$Z,BBDD_GASTOS_FINAL!$V:$V,$B$1,BBDD_GASTOS_FINAL!$W:$W,$B$67,BBDD_GASTOS_FINAL!$AC:$AC,lote_todos!$C74)*-1 -> 0
B75: =D75/$D$68 -> 0 | C75: MENTENIMIENTO | D75: =SUMIFS(BBDD_GASTOS_FINAL!$Z:$Z,BBDD_GASTOS_FINAL!$V:$V,$B$1,BBDD_GASTOS_FINAL!$W:$W,$B$67,BBDD_GASTOS_FINAL!$AC:$AC,lote_todos!$C75)*-1 -> 0
B76: =D76/$D$68 -> 0.050695197 | C76: GASTOS OPERATIVOS | D76: =SUMIFS(BBDD_GASTOS_FINAL!$Z:$Z,BBDD_GASTOS_FINAL!$V:$V,$B$1,BBDD_GASTOS_FINAL!$W:$W,$B$67,BBDD_GASTOS_FINAL!$AC:$AC,lote_todos!$C76)*-1 -> 12286134
B77: =D77/$D$68 -> 0.038315593 | C77: IMPUESTOS | D77: =SUMIFS(BBDD_GASTOS_FINAL!$Z:$Z,BBDD_GASTOS_FINAL!$V:$V,$B$1,BBDD_GASTOS_FINAL!$W:$W,$B$67,BBDD_GASTOS_FINAL!$AC:$AC,lote_todos!$C77)*-1 -> 9285900.1
B78: =D78/$D$68 -> 0.014154385 | C78: HONORARIOS | D78: =SUMIFS(BBDD_GASTOS_FINAL!$Z:$Z,BBDD_GASTOS_FINAL!$V:$V,$B$1,BBDD_GASTOS_FINAL!$W:$W,$B$67,BBDD_GASTOS_FINAL!$AC:$AC,lote_todos!$C78)*-1 -> 3430358.1
B79: =D79/$D$68 -> 0 | C79: SERVICIOS | D79: =SUMIFS(BBDD_GASTOS_FINAL!$Z:$Z,BBDD_GASTOS_FINAL!$V:$V,$B$1,BBDD_GASTOS_FINAL!$W:$W,$B$67,BBDD_GASTOS_FINAL!$AC:$AC,lote_todos!$C79)*-1 -> 0
B81: VENTAS | D81: =C6 -> 2.9089607e+08
B83: UTILDAD | D83: =D81-D68 -> 48543038
B85: CAPEX | D85: =SUMIFS(BBDD_GASTOS_FINAL!$Y:$Y,BBDD_GASTOS_FINAL!$J:$J,"Capex",BBDD_GASTOS_FINAL!$Z:$Z,$B$39) -> 0
B87: DEUDA | D87: =SUMIFS(BBDD_GASTOS_FINAL!$Y:$Y,BBDD_GASTOS_FINAL!$J:$J,"deuda",BBDD_GASTOS_FINAL!$V:$V,B67) -> 0
B89: Flujo de Caja al Accionista | D89: =D83-D87-D85 -> 48543038
B90: OPEX UN | C90: =D15+H15+L15+P15+P41+L41+H41+D41+#REF!+#REF!+#REF! -> #REF!
B91: OPEX total | C91: =C7 -> 2.4220987e+08
C92: =MROUND(C91,10000)=MROUND(C90,10000) -> #REF!
B94: CAPEX_UN | C94: =D33+H33+L33+P33+P59+L59+H59+D59+D67+H67+L67 -> 0
B95: CAPEX_TOTAL | C95: =C9 -> 0 | D95: =C94=C95 -> TRUE
B96: DEUDA_UN | C96: =D35+H35+L35+P35+P61+L61+H61+D61+D69+H69+L69 -> 1.5495853e+08
B97: DEUDA_TOTAL | C97: =C10 -> 0 | D97: =C96=C97 -> FALSE
B101: UTILIDAD_TOTAL | C101: =C8 -> 48686199
B102: UTILIDAD_UN | C102: =D31+H31+L31+P31+P57+L57+H57+D57+#REF!+#REF!+#REF! -> #REF! | D102: =MROUND(C102,10000)=MROUND(C101,10000) -> #REF!
B105: Flujo_TOTAL | C105: =C11 -> 48686199
B106: FLUJO_UN | C106: =D37+H37+L37+P37+P63+L63+H63+D63+D71+H71+L71 -> 11602439 | D106: =MROUND(C106,10000)=MROUND(C105,10000) -> FALSE
B107: Margen de utilidad | D107: =D83/D81 -> 0.16687417

Sheet lote_3125
A1: LOTE | B1: 3125 | C1: Mortandad-SITIO 2 | G1: CALZIM
C2: Mortandad-SITIO 3 | D2: =SUMIFS(produccion!G:G,produccion!$A:$A,B1) -> -0.062289562
B5: TOTALES | F5: FIJO/VARIABLE | J5: DIRECTO/INDERECTO
B6: VENTAS SITIO 3 | C6: =D55 -> 1.5088326e+08 | F6: VENTAS | G6: =C6 -> 1.5088326e+08 | J6: VENTAS | K6: =G6 -> 1.5088326e+08
B7: OPEX | C7: =SUMIFS(BBDD_GASTOS_FINAL!$Z:$Z,BBDD_GASTOS_FINAL!$V:$V,lote_3125!$B$1,BBDD_GASTOS_FINAL!$J:$J,"OPEX")*-1 -> 1.2414727e+08 | F7: Fijo | G7: =SUMIFS(BBDD_GASTOS_FINAL!$Z:$Z,BBDD_GASTOS_FINAL!$V:$V,lote_3125!$B$1,BBDD_GASTOS_FINAL!$J:$J,"OPEX",BBDD_GASTOS_FINAL!$K:$K,lote_3125!F7)*-1 -> 28941108 | J7: DIRECTO | K7: =SUMIFS(BBDD_GASTOS_FINAL!$Z:$Z,BBDD_GASTOS_FINAL!$V:$V,lote_3125!$B$1,BBDD_GASTOS_FINAL!$J:$J,"OPEX",BBDD_GASTOS_FINAL!$L:$L,lote_3125!J7)*-1 -> 95206165
B8: UTILIDAD | C8: =C6-C7 -> 26735986 | F8: Variable | G8: =SUMIFS(BBDD_GASTOS_FINAL!$Z:$Z,BBDD_GASTOS_FINAL!$V:$V,lote_3125!$B$1,BBDD_GASTOS_FINAL!$J:$J,"OPEX",BBDD_GASTOS_FINAL!$K:$K,lote_todos!F8)*-1 -> 95206165 | J8: INDIRECTO | K8: =SUMIFS(BBDD_GASTOS_FINAL!$Z:$Z,BBDD_GASTOS_FINAL!$V:$V,lote_3125!$B$1,BBDD_GASTOS_FINAL!$J:$J,"OPEX",BBDD_GASTOS_FINAL!$L:$L,lote_3125!J8)*-1 -> 28941108
B9: CAPEX | C9: =SUMIFS(BBDD_GASTOS_FINAL!$Y:$Y,BBDD_GASTOS_FINAL!$J:$J,lote_3125!B9) -> 0
B10: DEUDA | C10: =SUMIFS(BBDD_GASTOS_FINAL!$Y:$Y,BBDD_GASTOS_FINAL!$J:$J,lote_3125!B10) -> 0
B11: Flujo de Caja al Accionista | C11: =C6-C7-C9-C10 -> 26735986 | F11: Flujo de Caja al Accionista | G11: =G6-G7-G8 -> 26735986 | J11: Flujo de Caja al Accionista | K11: =K6-K7-K8 -> 26735986
A13: id | B13: 4 | E13: id | F13: 3 | I13: id | J13: 7 | M13: id
B14: GESTACIÓN | F14: MATERNIDAD | J14: SITIO 2
B15: OPEX | D15: =SUM(D16:D26) -> 20907772 | F15: OPEX | H15: =SUM(H16:H26) -> 19210095 | J15: OPEX | L15: =SUM(L16:L26) -> 19210095 | M15: 1
A16: 1 | B16: =D16/$D$15 -> 0.45203697 | C16: NUTRICIÓN | D16: =SUMIFS(BBDD_GASTOS_FINAL!$Z:$Z,BBDD_GASTOS_FINAL!$V:$V,$B$1,BBDD_GASTOS_FINAL!$W:$W,$B$14,BBDD_GASTOS_FINAL!$AC:$AC,lote_3125!$C16)*-1 -> 9451085.7 | E16: 1 | F16: =H16/$H$15 -> 0.32631252 | G16: NUTRICIÓN | H16: =SUMIFS(BBDD_GASTOS_FINAL!$Z:$Z,BBDD_GASTOS_FINAL!$V:$V,$B$1,BBDD_GASTOS_FINAL!$W:$W,$F$14,BBDD_GASTOS_FINAL!$AC:$AC,$G16)*-1 -> 6268494.7 | I16: 1 | J16: =L16/$L$15 -> 0.32631252 | K16: NUTRICIÓN | L16: =SUMIFS(BBDD_GASTOS_FINAL!$Z:$Z,BBDD_GASTOS_FINAL!$V:$V,$B$1,BBDD_GASTOS_FINAL!$W:$W,$F$14,BBDD_GASTOS_FINAL!$AC:$AC,$G16)*-1 -> 6268494.7 | M16: 1
A17: =A16+1 -> 2 | B17: =D17/$D$15 -> 0.24520019 | C17: PERSONAL | D17: =SUMIFS(BBDD_GASTOS_FINAL!$Z:$Z,BBDD_GASTOS_FINAL!$V:$V,$B$1,BBDD_GASTOS_FINAL!$W:$W,$B$14,BBDD_GASTOS_FINAL!AC:AC,lote_3125!$C17)*-1 -> 5126589.5 | E17: 2 | F17: =H17/$H$15 -> 0.4542479 | G17: PERSONAL | H17: =SUMIFS(BBDD_GASTOS_FINAL!$Z:$Z,BBDD_GASTOS_FINAL!$V:$V,$B$1,BBDD_GASTOS_FINAL!$W:$W,$F$14,BBDD_GASTOS_FINAL!$AC:$AC,$G17)*-1 -> 8726145.4 | I17: =I16+1 -> 2 | J17: =L17/$L$15 -> 0.4542479 | K17: PERSONAL | L17: =SUMIFS(BBDD_GASTOS_FINAL!$Z:$Z,BBDD_GASTOS_FINAL!$V:$V,$B$1,BBDD_GASTOS_FINAL!$W:$W,$F$14,BBDD_GASTOS_FINAL!$AC:$AC,$G17)*-1 -> 8726145.4 | M17: =M16+1 -> 2
A18: =A17+1 -> 3 | B18: =D18/$D$15 -> 0.02837345 | C18: SANIDAD | D18: =SUMIFS(BBDD_GASTOS_FINAL!$Z:$Z,BBDD_GASTOS_FINAL!$V:$V,$B$1,BBDD_GASTOS_FINAL!$W:$W,$B$14,BBDD_GASTOS_FINAL!AC:AC,lote_3125!$C18)*-1 -> 593225.61 | E18: 3 | F18: =H18/$H$15 -> 0.018383301 | G18: SANIDAD | H18: =SUMIFS(BBDD_GASTOS_FINAL!$Z:$Z,BBDD_GASTOS_FINAL!$V:$V,$B$1,BBDD_GASTOS_FINAL!$W:$W,$F$14,BBDD_GASTOS_FINAL!$AC:$AC,$G18)*-1 -> 353144.96 | I18: =I17+12 -> 14 | J18: =L18/$L$15 -> 0.018383301 | K18: SANIDAD | L18: =SUMIFS(BBDD_GASTOS_FINAL!$Z:$Z,BBDD_GASTOS_FINAL!$V:$V,$B$1,BBDD_GASTOS_FINAL!$W:$W,$F$14,BBDD_GASTOS_FINAL!$AC:$AC,$G18)*-1 -> 353144.96 | M18: =M17+1 -> 3
A19: =A18+1 -> 4 | B19: =D19/$D$15 -> 0.13728658 | C19: GENÉTICA | D19: =SUMIFS(BBDD_GASTOS_FINAL!$Z:$Z,BBDD_GASTOS_FINAL!$V:$V,$B$1,BBDD_GASTOS_FINAL!$W:$W,$B$14,BBDD_GASTOS_FINAL!AC:AC,lote_3125!$C19)*-1 -> 2870356.5 | E19: 4 | F19: =H19/$H$15 -> 0 | G19: GENÉTICA | H19: =SUMIFS(BBDD_GASTOS_FINAL!$Z:$Z,BBDD_GASTOS_FINAL!$V:$V,$B$1,BBDD_GASTOS_FINAL!$W:$W,$F$14,BBDD_GASTOS_FINAL!$AC:$AC,$G19)*-1 -> 0 | I19: =I18+1 -> 15 | J19: =L19/$L$15 -> 0 | K19: GENÉTICA | L19: =SUMIFS(BBDD_GASTOS_FINAL!$Z:$Z,BBDD_GASTOS_FINAL!$V:$V,$B$1,BBDD_GASTOS_FINAL!$W:$W,$F$14,BBDD_GASTOS_FINAL!$AC:$AC,$G19)*-1 -> 0 | M19: =M18+1 -> 4
A20: =A19+1 -> 5 | B20: =D20/$D$15 -> 0 | C20: FLETES | D20: =SUMIFS(BBDD_GASTOS_FINAL!$Z:$Z,BBDD_GASTOS_FINAL!$V:$V,$B$1,BBDD_GASTOS_FINAL!$W:$W,$B$14,BBDD_GASTOS_FINAL!AC:AC,lote_3125!$C20)*-1 -> 0 | E20: 5 | F20: =H20/$H$15 -> 0 | G20: FLETES | H20: =SUMIFS(BBDD_GASTOS_FINAL!$Z:$Z,BBDD_GASTOS_FINAL!$V:$V,$B$1,BBDD_GASTOS_FINAL!$W:$W,$F$14,BBDD_GASTOS_FINAL!$AC:$AC,$G20)*-1 -> 0 | I20: =I19+1 -> 16 | J20: =L20/$L$15 -> 0 | K20: FLETES | L20: =SUMIFS(BBDD_GASTOS_FINAL!$Z:$Z,BBDD_GASTOS_FINAL!$V:$V,$B$1,BBDD_GASTOS_FINAL!$W:$W,$F$14,BBDD_GASTOS_FINAL!$AC:$AC,$G20)*-1 -> 0 | M20: =M19+1 -> 5
A21: =A20+1 -> 6 | B21: =D21/$D$15 -> 0 | C21: ENERGÍA | D21: =SUMIFS(BBDD_GASTOS_FINAL!$Z:$Z,BBDD_GASTOS_FINAL!$V:$V,$B$1,BBDD_GASTOS_FINAL!$W:$W,$B$14,BBDD_GASTOS_FINAL!AC:AC,lote_3125!$C21)*-1 -> 0 | E21: 6 | F21: =H21/$H$15 -> 0 | G21: ENERGÍA | H21: =SUMIFS(BBDD_GASTOS_FINAL!$Z:$Z,BBDD_GASTOS_FINAL!$V:$V,$B$1,BBDD_GASTOS_FINAL!$W:$W,$F$14,BBDD_GASTOS_FINAL!$AC:$AC,$G21)*-1 -> 0 | I21: =I20+1 -> 17 | J21: =L21/$L$15 -> 0 | K21: ENERGÍA | L21: =SUMIFS(BBDD_GASTOS_FINAL!$Z:$Z,BBDD_GASTOS_FINAL!$V:$V,$B$1,BBDD_GASTOS_FINAL!$W:$W,$F$14,BBDD_GASTOS_FINAL!$AC:$AC,$G21)*-1 -> 0 | M21: =M20+1 -> 6
A22: =A21+1 -> 7 | B22: =D22/$D$15 -> 0 | C22: MENTENIMIENTO | D22: =SUMIFS(BBDD_GASTOS_FINAL!$Z:$Z,BBDD_GASTOS_FINAL!$V:$V,$B$1,BBDD_GASTOS_FINAL!$W:$W,$B$14,BBDD_GASTOS_FINAL!AC:AC,lote_3125!$C22)*-1 -> 0 | E22: 7 | F22: =H22/$H$15 -> 0 | G22: MENTENIMIENTO | H22: =SUMIFS(BBDD_GASTOS_FINAL!$Z:$Z,BBDD_GASTOS_FINAL!$V:$V,$B$1,BBDD_GASTOS_FINAL!$W:$W,$F$14,BBDD_GASTOS_FINAL!$AC:$AC,$G22)*-1 -> 0 | I22: =I21+1 -> 18 | J22: =L22/$L$15 -> 0 | K22: MENTENIMIENTO | L22: =SUMIFS(BBDD_GASTOS_FINAL!$Z:$Z,BBDD_GASTOS_FINAL!$V:$V,$B$1,BBDD_GASTOS_FINAL!$W:$W,$F$14,BBDD_GASTOS_FINAL!$AC:$AC,$G22)*-1 -> 0 | M22: =M21+1 -> 7
A23: =A22+1 -> 8 | B23: =D23/$D$15 -> 0.073454347 | C23: GASTOS OPERATIVOS | D23: =SUMIFS(BBDD_GASTOS_FINAL!$Z:$Z,BBDD_GASTOS_FINAL!$V:$V,$B$1,BBDD_GASTOS_FINAL!$W:$W,$B$14,BBDD_GASTOS_FINAL!AC:AC,lote_3125!$C23)*-1 -> 1535766.7 | E23: 8 | F23: =H23/$H$15 -> 0.079945814 | G23: GASTOS OPERATIVOS | H23: =SUMIFS(BBDD_GASTOS_FINAL!$Z:$Z,BBDD_GASTOS_FINAL!$V:$V,$B$1,BBDD_GASTOS_FINAL!$W:$W,$F$14,BBDD_GASTOS_FINAL!$AC:$AC,$G23)*-1 -> 1535766.7 | I23: =I22+1 -> 19 | J23: =L23/$L$15 -> 0.079945814 | K23: GASTOS OPERATIVOS | L23: =SUMIFS(BBDD_GASTOS_FINAL!$Z:$Z,BBDD_GASTOS_FINAL!$V:$V,$B$1,BBDD_GASTOS_FINAL!$W:$W,$F$14,BBDD_GASTOS_FINAL!$AC:$AC,$G23)*-1 -> 1535766.7 | M23: =M22+1 -> 8
A24: =A23+1 -> 9 | B24: =D24/$D$15 -> 0.043139597 | C24: IMPUESTOS | D24: =SUMIFS(BBDD_GASTOS_FINAL!$Z:$Z,BBDD_GASTOS_FINAL!$V:$V,$B$1,BBDD_GASTOS_FINAL!$W:$W,$B$14,BBDD_GASTOS_FINAL!AC:AC,lote_3125!$C24)*-1 -> 901952.84 | E24: 9 | F24: =H24/$H$15 -> 0.09878914 | G24: IMPUESTOS | H24: =SUMIFS(BBDD_GASTOS_FINAL!$Z:$Z,BBDD_GASTOS_FINAL!$V:$V,$B$1,BBDD_GASTOS_FINAL!$W:$W,$F$14,BBDD_GASTOS_FINAL!$AC:$AC,$G24)*-1 -> 1897748.8 | I24: =I23+1 -> 20 | J24: =L24/$L$15 -> 0.09878914 | K24: IMPUESTOS | L24: =SUMIFS(BBDD_GASTOS_FINAL!$Z:$Z,BBDD_GASTOS_FINAL!$V:$V,$B$1,BBDD_GASTOS_FINAL!$W:$W,$F$14,BBDD_GASTOS_FINAL!$AC:$AC,$G24)*-1 -> 1897748.8 | M24: =M23+1 -> 9
A25: =A24+1 -> 10 | B25: =D25/$D$15 -> 0.020508868 | C25: HONORARIOS | D25: =SUMIFS(BBDD_GASTOS_FINAL!$Z:$Z,BBDD_GASTOS_FINAL!$V:$V,$B$1,BBDD_GASTOS_FINAL!$W:$W,$B$14,BBDD_GASTOS_FINAL!AC:AC,lote_3125!$C25)*-1 -> 428794.73 | E25: 10 | F25: =H25/$H$15 -> 0.022321323 | G25: HONORARIOS | H25: =SUMIFS(BBDD_GASTOS_FINAL!$Z:$Z,BBDD_GASTOS_FINAL!$V:$V,$B$1,BBDD_GASTOS_FINAL!$W:$W,$F$14,BBDD_GASTOS_FINAL!$AC:$AC,$G25)*-1 -> 428794.73 | I25: =I24+1 -> 21 | J25: =L25/$L$15 -> 0.022321323 | K25: HONORARIOS | L25: =SUMIFS(BBDD_GASTOS_FINAL!$Z:$Z,BBDD_GASTOS_FINAL!$V:$V,$B$1,BBDD_GASTOS_FINAL!$W:$W,$F$14,BBDD_GASTOS_FINAL!$AC:$AC,$G25)*-1 -> 428794.73 | M25: =M24+1 -> 10
B26: =D26/$D$15 -> 0 | C26: SERVICIOS | D26: =SUMIFS(BBDD_GASTOS_FINAL!$Z:$Z,BBDD_GASTOS_FINAL!$V:$V,$B$1,BBDD_GASTOS_FINAL!$W:$W,$B$14,BBDD_GASTOS_FINAL!AC:AC,lote_3125!$C26)*-1 -> 0 | F26: =H26/$H$15 -> 0 | G26: SERVICIOS | H26: =SUMIFS(BBDD_GASTOS_FINAL!$Z:$Z,BBDD_GASTOS_FINAL!$V:$V,$B$1,BBDD_GASTOS_FINAL!$W:$W,$F$14,BBDD_GASTOS_FINAL!$AC:$AC,$G26)*-1 -> 0 | J26: =L26/$L$15 -> 0 | K26: OTROS | L26: =SUMIFS(BBDD_GASTOS_FINAL!$Z:$Z,BBDD_GASTOS_FINAL!$V:$V,$B$1,BBDD_GASTOS_FINAL!$W:$W,$F$14,BBDD_GASTOS_FINAL!$AC:$AC,$G26)*-1 -> 0
F28: COMPRAS EN GESTACION | H28: =D15 -> 20907772 | J28: COMPRAS EN MATERNIDAD | L28: =H29 -> 28146183
B29: VENTAS | D29: =SUMIFS(produccion!$H:$H,produccion!$A:$A,lote_3125!$B$1,produccion!$B:$B,lote_3125!B14) -> 0 | F29: VENTAS | H29: =SUMIFS(produccion!$H:$H,produccion!$A:$A,lote_3125!$B$1,produccion!$B:$B,lote_3125!F14) -> 28146183 | J29: VENTAS | L29: =SUMIFS(produccion!$H:$H,produccion!$A:$A,lote_3125!$B$1,produccion!$B:$B,lote_3125!J14) -> 52310749
B31: UTILDAD | D31: =D29-D15-D28 -> -20907772 | F31: UTILDAD | H31: =H29-H15-H28 -> -11971684 | J31: UTILDAD | L31: =L29-L15-L28 -> 4954470.6
B33: CAPEX | D33: =SUMIFS(BBDD_GASTOS_FINAL!$Y:$Y,BBDD_GASTOS_FINAL!$J:$J,"Capex",BBDD_GASTOS_FINAL!$Z:$Z,$B$13) -> 0 | F33: CAPEX | H33: =SUMIFS(BBDD_GASTOS_FINAL!$Y:$Y,BBDD_GASTOS_FINAL!$J:$J,"Capex",BBDD_GASTOS_FINAL!$Z:$Z,$F$13) -> 0 | J33: CAPEX | L33: =SUMIFS(BBDD_GASTOS_FINAL!$Y:$Y,BBDD_GASTOS_FINAL!$J:$J,"Capex",BBDD_GASTOS_FINAL!$Z:$Z,$J$13) -> 0
B35: DEUDA | D35: =SUMIFS(BBDD_GASTOS_FINAL!$Y:$Y,BBDD_GASTOS_FINAL!$J:$J,"Deuda",BBDD_GASTOS_FINAL!$V:$V,B14) -> 0 | F35: DEUDA | H35: =SUMIFS(BBDD_GASTOS_FINAL!$Y:$Y,BBDD_GASTOS_FINAL!$J:$J,"Deuda",BBDD_GASTOS_FINAL!$V:$V,F14) -> 0 | J35: DEUDA | L35: =SUMIFS(BBDD_GASTOS_FINAL!$Y:$Y,BBDD_GASTOS_FINAL!$J:$J,"deuda",BBDD_GASTOS_FINAL!$V:$V,J14) -> 0
B37: Flujo de Caja al Accionista | D37: =D31-D35-D33 -> -20907772 | F37: Flujo de Caja al Accionista | H37: =H31-H35-H33 -> -11971684 | J37: Flujo de Caja al Accionista | L37: =L31-L35-L33 -> 4954470.6
F38: Margen de utilidad | H38: =H31/H29 -> -0.42533952 | J38: Margen de utilidad | L38: =L31/L29 -> 0.094712286
A39: id | B39: 1 | M39: id
B40: SITIO 3
B41: OPEX | D41: =SUM(D42:D52) -> 65269906
A42: 1 | B42: =D42/$D$41 -> 0.85082417 | C42: NUTRICIÓN | D42: =SUMIFS(BBDD_GASTOS_FINAL!$Z:$Z,BBDD_GASTOS_FINAL!$V:$V,$B$1,BBDD_GASTOS_FINAL!$W:$W,$B$40,BBDD_GASTOS_FINAL!$AC:$AC,lote_3125!$C42)*-1 -> 55533213
A43: =A42+1 -> 2 | B43: =D43/$D$41 -> 0.072171564 | C43: PERSONAL | D43: =SUMIFS(BBDD_GASTOS_FINAL!$Z:$Z,BBDD_GASTOS_FINAL!$V:$V,$B$1,BBDD_GASTOS_FINAL!$W:$W,$B$40,BBDD_GASTOS_FINAL!AC:AC,lote_3125!$C43)*-1 -> 4710631.2
A44: =A43+1 -> 3 | B44: =D44/$D$41 -> 0 | C44: SANIDAD | D44: =SUMIFS(BBDD_GASTOS_FINAL!$Z:$Z,BBDD_GASTOS_FINAL!$V:$V,$B$1,BBDD_GASTOS_FINAL!$W:$W,$B$40,BBDD_GASTOS_FINAL!AC:AC,lote_3125!$C44)*-1 -> 0
A45: =A44+1 -> 4 | B45: =D45/$D$41 -> 0 | C45: GENÉTICA | D45: =SUMIFS(BBDD_GASTOS_FINAL!$Z:$Z,BBDD_GASTOS_FINAL!$V:$V,$B$1,BBDD_GASTOS_FINAL!$W:$W,$B$40,BBDD_GASTOS_FINAL!AC:AC,lote_3125!$C45)*-1 -> 0
A46: =A45+1 -> 5 | B46: =D46/$D$41 -> 0.033086415 | C46: FLETES | D46: =SUMIFS(BBDD_GASTOS_FINAL!$Z:$Z,BBDD_GASTOS_FINAL!$V:$V,$B$1,BBDD_GASTOS_FINAL!$W:$W,$B$40,BBDD_GASTOS_FINAL!AC:AC,lote_3125!$C46)*-1 -> 2159547.2
A47: =A46+1 -> 6 | B47: =D47/$D$41 -> 0 | C47: ENERGÍA | D47: =SUMIFS(BBDD_GASTOS_FINAL!$Z:$Z,BBDD_GASTOS_FINAL!$V:$V,$B$1,BBDD_GASTOS_FINAL!$W:$W,$B$40,BBDD_GASTOS_FINAL!AC:AC,lote_3125!$C47)*-1 -> 0
A48: =A47+1 -> 7 | B48: =D48/$D$41 -> 0 | C48: MENTENIMIENTO | D48: =SUMIFS(BBDD_GASTOS_FINAL!$Z:$Z,BBDD_GASTOS_FINAL!$V:$V,$B$1,BBDD_GASTOS_FINAL!$W:$W,$B$40,BBDD_GASTOS_FINAL!AC:AC,lote_3125!$C48)*-1 -> 0
A49: =A48+1 -> 8 | B49: =D49/$D$41 -> 0.023529476 | C49: GASTOS OPERATIVOS | D49: =SUMIFS(BBDD_GASTOS_FINAL!$Z:$Z,BBDD_GASTOS_FINAL!$V:$V,$B$1,BBDD_GASTOS_FINAL!$W:$W,$B$40,BBDD_GASTOS_FINAL!AC:AC,lote_3125!$C49)*-1 -> 1535766.7
A50: =A49+1 -> 9 | B50: =D50/$D$41 -> 0.013818816 | C50: IMPUESTOS | D50: =SUMIFS(BBDD_GASTOS_FINAL!$Z:$Z,BBDD_GASTOS_FINAL!$V:$V,$B$1,BBDD_GASTOS_FINAL!$W:$W,$B$40,BBDD_GASTOS_FINAL!AC:AC,lote_3125!$C50)*-1 -> 901952.84
A51: =A50+1 -> 10 | B51: =D51/$D$41 -> 0.0065695626 | C51: HONORARIOS | D51: =SUMIFS(BBDD_GASTOS_FINAL!$Z:$Z,BBDD_GASTOS_FINAL!$V:$V,$B$1,BBDD_GASTOS_FINAL!$W:$W,$B$40,BBDD_GASTOS_FINAL!AC:AC,lote_3125!$C51)*-1 -> 428794.73
B52: =D52/$D$41 -> 0 | C52: SERVICIOS | D52: =SUMIFS(BBDD_GASTOS_FINAL!$Z:$Z,BBDD_GASTOS_FINAL!$V:$V,$B$1,BBDD_GASTOS_FINAL!$W:$W,$B$40,BBDD_GASTOS_FINAL!AC:AC,lote_3125!$C52)*-1 -> 0
B54: COMPRAS EN SITIO 2 | D54: =L29 -> 52310749
B55: VENTAS | D55: =SUMIFS(produccion!$H:$H,produccion!$A:$A,lote_3125!$B$1,produccion!$B:$B,lote_3125!B40) -> 1.5088326e+08
B57: UTILDAD | D57: =D55-D41-D54 -> 33302605
B59: CAPEX | D59: =SUMIFS(BBDD_GASTOS_FINAL!$Y:$Y,BBDD_GASTOS_FINAL!$J:$J,"Capex",BBDD_GASTOS_FINAL!$Z:$Z,$B$39) -> 0
B61: DEUDA | D61: =SUMIFS(BBDD_GASTOS_FINAL!$Y:$Y,BBDD_GASTOS_FINAL!$J:$J,"deuda",BBDD_GASTOS_FINAL!$V:$V,B40) -> 0
B63: Flujo de Caja al Accionista | D63: =D57-D61-D59 -> 33302605
B64: Margen de utilidad | D64: =D57/D55 -> 0.22071769
A65: id | B65: 9 | E65: id
A66: LOTE | B66: =B1 -> 3125
A67: TOTAL | B67: <> & ""
B68: OPEX | D68: =SUM(D69:D79) -> 1.2417951e+08
B69: =D69/$D$68 -> 0.64865432 | C69: NUTRICIÓN | D69: =SUMIFS(BBDD_GASTOS_FINAL!$Z:$Z,BBDD_GASTOS_FINAL!$V:$V,$B$1,BBDD_GASTOS_FINAL!$W:$W,$B$67,BBDD_GASTOS_FINAL!$AC:$AC,lote_3125!$C69)*-1 -> 80549577
B70: =D70/$D$68 -> 0.18243396 | C70: PERSONAL | D70: =SUMIFS(BBDD_GASTOS_FINAL!$Z:$Z,BBDD_GASTOS_FINAL!$V:$V,$B$1,BBDD_GASTOS_FINAL!$W:$W,$B$67,BBDD_GASTOS_FINAL!$AC:$AC,lote_3125!$C70)*-1 -> 22654560
B71: =D71/$D$68 -> 0.028053079 | C71: SANIDAD | D71: =SUMIFS(BBDD_GASTOS_FINAL!$Z:$Z,BBDD_GASTOS_FINAL!$V:$V,$B$1,BBDD_GASTOS_FINAL!$W:$W,$B$67,BBDD_GASTOS_FINAL!$AC:$AC,lote_3125!$C71)*-1 -> 3483617.6
B72: =D72/$D$68 -> 0.023114574 | C72: GENÉTICA | D72: =SUMIFS(BBDD_GASTOS_FINAL!$Z:$Z,BBDD_GASTOS_FINAL!$V:$V,$B$1,BBDD_GASTOS_FINAL!$W:$W,$B$67,BBDD_GASTOS_FINAL!$AC:$AC,lote_3125!$C72)*-1 -> 2870356.5
B73: =D73/$D$68 -> 0.017390527 | C73: FLETES | D73: =SUMIFS(BBDD_GASTOS_FINAL!$Z:$Z,BBDD_GASTOS_FINAL!$V:$V,$B$1,BBDD_GASTOS_FINAL!$W:$W,$B$67,BBDD_GASTOS_FINAL!$AC:$AC,lote_3125!$C73)*-1 -> 2159547.2
B74: =D74/$D$68 -> 0 | C74: ENERGÍA | D74: =SUMIFS(BBDD_GASTOS_FINAL!$Z:$Z,BBDD_GASTOS_FINAL!$V:$V,$B$1,BBDD_GASTOS_FINAL!$W:$W,$B$67,BBDD_GASTOS_FINAL!$AC:$AC,lote_3125!$C74)*-1 -> 0
B75: =D75/$D$68 -> 0 | C75: MENTENIMIENTO | D75: =SUMIFS(BBDD_GASTOS_FINAL!$Z:$Z,BBDD_GASTOS_FINAL!$V:$V,$B$1,BBDD_GASTOS_FINAL!$W:$W,$B$67,BBDD_GASTOS_FINAL!$AC:$AC,lote_3125!$C75)*-1 -> 0
B76: =D76/$D$68 -> 0.049469246 | C76: GASTOS OPERATIVOS | D76: =SUMIFS(BBDD_GASTOS_FINAL!$Z:$Z,BBDD_GASTOS_FINAL!$V:$V,$B$1,BBDD_GASTOS_FINAL!$W:$W,$B$67,BBDD_GASTOS_FINAL!$AC:$AC,lote_3125!$C76)*-1 -> 6143066.8
B77: =D77/$D$68 -> 0.037072197 | C77: IMPUESTOS | D77: =SUMIFS(BBDD_GASTOS_FINAL!$Z:$Z,BBDD_GASTOS_FINAL!$V:$V,$B$1,BBDD_GASTOS_FINAL!$W:$W,$B$67,BBDD_GASTOS_FINAL!$AC:$AC,lote_3125!$C77)*-1 -> 4603607.3
B78: =D78/$D$68 -> 0.013812093 | C78: HONORARIOS | D78: =SUMIFS(BBDD_GASTOS_FINAL!$Z:$Z,BBDD_GASTOS_FINAL!$V:$V,$B$1,BBDD_GASTOS_FINAL!$W:$W,$B$67,BBDD_GASTOS_FINAL!$AC:$AC,lote_3125!$C78)*-1 -> 1715178.9
B79: =D79/$D$68 -> 0 | C79: SERVICIOS | D79: =SUMIFS(BBDD_GASTOS_FINAL!$Z:$Z,BBDD_GASTOS_FINAL!$V:$V,$B$1,BBDD_GASTOS_FINAL!$W:$W,$B$67,BBDD_GASTOS_FINAL!$AC:$AC,lote_3125!$C79)*-1 -> 0
B81: VENTAS | D81: =C6 -> 1.5088326e+08
B83: UTILDAD | D83: =D81-D68 -> 26703748
B85: CAPEX | D85: =SUMIFS(BBDD_GASTOS_FINAL!$Y:$Y,BBDD_GASTOS_FINAL!$J:$J,"Capex",BBDD_GASTOS_FINAL!$Z:$Z,$B$39) -> 0
B87: DEUDA | D87: =SUMIFS(BBDD_GASTOS_FINAL!$Y:$Y,BBDD_GASTOS_FINAL!$J:$J,"deuda",BBDD_GASTOS_FINAL!$V:$V,B67) -> 0
B89: Flujo de Caja al Accionista | D89: =D83-D87-D85 -> 26703748
B90: OPEX UN | C90: =D15+H15+L15+P15+P41+L41+H41+D41+#REF!+#REF!+#REF! -> #REF!
B91: OPEX total | C91: =C7 -> 1.2414727e+08
C92: =MROUND(C91,10000)=MROUND(C90,10000) -> #REF!
B94: CAPEX_UN | C94: =D33+H33+L33+P33+P59+L59+H59+D59+D67+H67+L67 -> 0
B95: CAPEX_TOTAL | C95: =C9 -> 0 | D95: =C94=C95 -> TRUE
B96: DEUDA_UN | C96: =D35+H35+L35+P35+P61+L61+H61+D61+D69+H69+L69 -> 80549577
B97: DEUDA_TOTAL | C97: =C10 -> 0 | D97: =C96=C97 -> FALSE
B101: UTILIDAD_TOTAL | C101: =C8 -> 26735986
B102: UTILIDAD_UN | C102: =D31+H31+L31+P31+P57+L57+H57+D57+#REF!+#REF!+#REF! -> #REF! | D102: =MROUND(C102,10000)=MROUND(C101,10000) -> #REF!
B105: Flujo_TOTAL | C105: =C11 -> 26735986
B106: FLUJO_UN | C106: =D37+H37+L37+P37+P63+L63+H63+D63+D71+H71+L71 -> 8861237.8 | D106: =MROUND(C106,10000)=MROUND(C105,10000) -> FALSE
B107: Margen de utilidad | D107: =D83/D81 -> 0.17698284

Sheet lote_2925
A1: LOTE | B1: 2925 | C1: Mortandad-SITIO 2 | G1: CALZIM
C2: Mortandad-SITIO 3 | D2: =SUMIFS(produccion!G:G,produccion!$A:$A,B1) -> -0.046931408
B5: TOTALES | F5: FIJO/VARIABLE | J5: DIRECTO/INDERECTO
B6: VENTAS SITIO 3 | C6: =D55 -> 1.4001281e+08 | F6: VENTAS | G6: =C6 -> 1.4001281e+08 | J6: VENTAS | K6: =G6 -> 1.4001281e+08
B7: OPEX | C7: =SUMIFS(BBDD_GASTOS_FINAL!$Z:$Z,BBDD_GASTOS_FINAL!$V:$V,lote_2925!$B$1,BBDD_GASTOS_FINAL!$J:$J,"OPEX")*-1 -> 1.1806259e+08 | F7: Fijo | G7: =SUMIFS(BBDD_GASTOS_FINAL!$Z:$Z,BBDD_GASTOS_FINAL!$V:$V,lote_2925!$B$1,BBDD_GASTOS_FINAL!$J:$J,"OPEX",BBDD_GASTOS_FINAL!$K:$K,lote_2925!F7)*-1 -> 28941112 | J7: DIRECTO | K7: =SUMIFS(BBDD_GASTOS_FINAL!$Z:$Z,BBDD_GASTOS_FINAL!$V:$V,lote_2925!$B$1,BBDD_GASTOS_FINAL!$J:$J,"OPEX",BBDD_GASTOS_FINAL!$L:$L,lote_2925!J7)*-1 -> 89121480
B8: UTILIDAD | C8: =C6-C7 -> 21950213 | F8: Variable | G8: =SUMIFS(BBDD_GASTOS_FINAL!$Z:$Z,BBDD_GASTOS_FINAL!$V:$V,lote_2925!$B$1,BBDD_GASTOS_FINAL!$J:$J,"OPEX",BBDD_GASTOS_FINAL!$K:$K,lote_2925!F8)*-1 -> 89121480 | J8: INDIRECTO | K8: =SUMIFS(BBDD_GASTOS_FINAL!$Z:$Z,BBDD_GASTOS_FINAL!$V:$V,lote_2925!$B$1,BBDD_GASTOS_FINAL!$J:$J,"OPEX",BBDD_GASTOS_FINAL!$L:$L,lote_2925!J8)*-1 -> 28941112
B9: CAPEX | C9: =SUMIFS(BBDD_GASTOS_FINAL!$Y:$Y,BBDD_GASTOS_FINAL!$J:$J,lote_2925!B9) -> 0
B10: DEUDA | C10: =SUMIFS(BBDD_GASTOS_FINAL!$Y:$Y,BBDD_GASTOS_FINAL!$J:$J,lote_2925!B10) -> 0
B11: Flujo de Caja al Accionista | C11: =C6-C7-C9-C10 -> 21950213 | F11: Flujo de Caja al Accionista | G11: =G6-G7-G8 -> 21950213 | J11: Flujo de Caja al Accionista | K11: =K6-K7-K8 -> 21950213
A13: id | B13: 4 | E13: id | F13: 3 | I13: id | J13: 7 | M13: id
B14: GESTACIÓN | F14: MATERNIDAD | J14: SITIO 2
B15: OPEX | D15: =SUM(D16:D26) -> 21119488 | F15: OPEX | H15: =SUM(H16:H26) -> 19258302 | J15: OPEX | L15: =SUM(L16:L26) -> 19258302 | M15: 1
A16: 1 | B16: =D16/$D$15 -> 0.45484158 | C16: NUTRICIÓN | D16: =SUMIFS(BBDD_GASTOS_FINAL!$Z:$Z,BBDD_GASTOS_FINAL!$V:$V,$B$1,BBDD_GASTOS_FINAL!$W:$W,$B$14,BBDD_GASTOS_FINAL!$AC:$AC,lote_2925!$C16)*-1 -> 9606021.6 | E16: 1 | F16: =H16/$H$15 -> 0.32804255 | G16: NUTRICIÓN | H16: =SUMIFS(BBDD_GASTOS_FINAL!$Z:$Z,BBDD_GASTOS_FINAL!$V:$V,$B$1,BBDD_GASTOS_FINAL!$W:$W,$F$14,BBDD_GASTOS_FINAL!$AC:$AC,$G16)*-1 -> 6317542.5 | I16: 1 | J16: =L16/$L$15 -> 0.32804255 | K16: NUTRICIÓN | L16: =SUMIFS(BBDD_GASTOS_FINAL!$Z:$Z,BBDD_GASTOS_FINAL!$V:$V,$B$1,BBDD_GASTOS_FINAL!$W:$W,$F$14,BBDD_GASTOS_FINAL!$AC:$AC,$G16)*-1 -> 6317542.5 | M16: 1
A17: =A16+1 -> 2 | B17: =D17/$D$15 -> 0.24274215 | C17: PERSONAL | D17: =SUMIFS(BBDD_GASTOS_FINAL!$Z:$Z,BBDD_GASTOS_FINAL!$V:$V,$B$1,BBDD_GASTOS_FINAL!$W:$W,$B$14,BBDD_GASTOS_FINAL!AC:AC,lote_2925!$C17)*-1 -> 5126590.1 | E17: 2 | F17: =H17/$H$15 -> 0.45311089 | G17: PERSONAL | H17: =SUMIFS(BBDD_GASTOS_FINAL!$Z:$Z,BBDD_GASTOS_FINAL!$V:$V,$B$1,BBDD_GASTOS_FINAL!$W:$W,$F$14,BBDD_GASTOS_FINAL!$AC:$AC,$G17)*-1 -> 8726146.5 | I17: =I16+1 -> 2 | J17: =L17/$L$15 -> 0.45311089 | K17: PERSONAL | L17: =SUMIFS(BBDD_GASTOS_FINAL!$Z:$Z,BBDD_GASTOS_FINAL!$V:$V,$B$1,BBDD_GASTOS_FINAL!$W:$W,$F$14,BBDD_GASTOS_FINAL!$AC:$AC,$G17)*-1 -> 8726146.5 | M17: =M16+1 -> 2
A18: =A17+1 -> 3 | B18: =D18/$D$15 -> 0.02854949 | C18: SANIDAD | D18: =SUMIFS(BBDD_GASTOS_FINAL!$Z:$Z,BBDD_GASTOS_FINAL!$V:$V,$B$1,BBDD_GASTOS_FINAL!$W:$W,$B$14,BBDD_GASTOS_FINAL!AC:AC,lote_2925!$C18)*-1 -> 602950.62 | E18: 3 | F18: =H18/$H$15 -> 0.01829354 | G18: SANIDAD | H18: =SUMIFS(BBDD_GASTOS_FINAL!$Z:$Z,BBDD_GASTOS_FINAL!$V:$V,$B$1,BBDD_GASTOS_FINAL!$W:$W,$F$14,BBDD_GASTOS_FINAL!$AC:$AC,$G18)*-1 -> 352302.52 | I18: =I17+12 -> 14 | J18: =L18/$L$15 -> 0.01829354 | K18: SANIDAD | L18: =SUMIFS(BBDD_GASTOS_FINAL!$Z:$Z,BBDD_GASTOS_FINAL!$V:$V,$B$1,BBDD_GASTOS_FINAL!$W:$W,$F$14,BBDD_GASTOS_FINAL!$AC:$AC,$G18)*-1 -> 352302.52 | M18: =M17+1 -> 3
A19: =A18+1 -> 4 | B19: =D19/$D$15 -> 0.13813836 | C19: GENÉTICA | D19: =SUMIFS(BBDD_GASTOS_FINAL!$Z:$Z,BBDD_GASTOS_FINAL!$V:$V,$B$1,BBDD_GASTOS_FINAL!$W:$W,$B$14,BBDD_GASTOS_FINAL!AC:AC,lote_2925!$C19)*-1 -> 2917411.5 | E19: 4 | F19: =H19/$H$15 -> 0 | G19: GENÉTICA | H19: =SUMIFS(BBDD_GASTOS_FINAL!$Z:$Z,BBDD_GASTOS_FINAL!$V:$V,$B$1,BBDD_GASTOS_FINAL!$W:$W,$F$14,BBDD_GASTOS_FINAL!$AC:$AC,$G19)*-1 -> 0 | I19: =I18+1 -> 15 | J19: =L19/$L$15 -> 0 | K19: GENÉTICA | L19: =SUMIFS(BBDD_GASTOS_FINAL!$Z:$Z,BBDD_GASTOS_FINAL!$V:$V,$B$1,BBDD_GASTOS_FINAL!$W:$W,$F$14,BBDD_GASTOS_FINAL!$AC:$AC,$G19)*-1 -> 0 | M19: =M18+1 -> 4
A20: =A19+1 -> 5 | B20: =D20/$D$15 -> 0 | C20: FLETES | D20: =SUMIFS(BBDD_GASTOS_FINAL!$Z:$Z,BBDD_GASTOS_FINAL!$V:$V,$B$1,BBDD_GASTOS_FINAL!$W:$W,$B$14,BBDD_GASTOS_FINAL!AC:AC,lote_2925!$C20)*-1 -> 0 | E20: 5 | F20: =H20/$H$15 -> 0 | G20: FLETES | H20: =SUMIFS(BBDD_GASTOS_FINAL!$Z:$Z,BBDD_GASTOS_FINAL!$V:$V,$B$1,BBDD_GASTOS_FINAL!$W:$W,$F$14,BBDD_GASTOS_FINAL!$AC:$AC,$G20)*-1 -> 0 | I20: =I19+1 -> 16 | J20: =L20/$L$15 -> 0 | K20: FLETES | L20: =SUMIFS(BBDD_GASTOS_FINAL!$Z:$Z,BBDD_GASTOS_FINAL!$V:$V,$B$1,BBDD_GASTOS_FINAL!$W:$W,$F$14,BBDD_GASTOS_FINAL!$AC:$AC,$G20)*-1 -> 0 | M20: =M19+1 -> 5
A21: =A20+1 -> 6 | B21: =D21/$D$15 -> 0 | C21: ENERGÍA | D21: =SUMIFS(BBDD_GASTOS_FINAL!$Z:$Z,BBDD_GASTOS_FINAL!$V:$V,$B$1,BBDD_GASTOS_FINAL!$W:$W,$B$14,BBDD_GASTOS_FINAL!AC:AC,lote_2925!$C21)*-1 -> 0 | E21: 6 | F21: =H21/$H$15 -> 0 | G21: ENERGÍA | H21: =SUMIFS(BBDD_GASTOS_FINAL!$Z:$Z,BBDD_GASTOS_FINAL!$V:$V,$B$1,BBDD_GASTOS_FINAL!$W:$W,$F$14,BBDD_GASTOS_FINAL!$AC:$AC,$G21)*-1 -> 0 | I21: =I20+1 -> 17 | J21: =L21/$L$15 -> 0 | K21: ENERGÍA | L21: =SUMIFS(BBDD_GASTOS_FINAL!$Z:$Z,BBDD_GASTOS_FINAL!$V:$V,$B$1,BBDD_GASTOS_FINAL!$W:$W,$F$14,BBDD_GASTOS_FINAL!$AC:$AC,$G21)*-1 -> 0 | M21: =M20+1 -> 6
A22: =A21+1 -> 7 | B22: =D22/$D$15 -> 0 | C22: MENTENIMIENTO | D22: =SUMIFS(BBDD_GASTOS_FINAL!$Z:$Z,BBDD_GASTOS_FINAL!$V:$V,$B$1,BBDD_GASTOS_FINAL!$W:$W,$B$14,BBDD_GASTOS_FINAL!AC:AC,lote_2925!$C22)*-1 -> 0 | E22: 7 | F22: =H22/$H$15 -> 0 | G22: MENTENIMIENTO | H22: =SUMIFS(BBDD_GASTOS_FINAL!$Z:$Z,BBDD_GASTOS_FINAL!$V:$V,$B$1,BBDD_GASTOS_FINAL!$W:$W,$F$14,BBDD_GASTOS_FINAL!$AC:$AC,$G22)*-1 -> 0 | I22: =I21+1 -> 18 | J22: =L22/$L$15 -> 0 | K22: MENTENIMIENTO | L22: =SUMIFS(BBDD_GASTOS_FINAL!$Z:$Z,BBDD_GASTOS_FINAL!$V:$V,$B$1,BBDD_GASTOS_FINAL!$W:$W,$F$14,BBDD_GASTOS_FINAL!$AC:$AC,$G22)*-1 -> 0 | M22: =M21+1 -> 7
A23: =A22+1 -> 8 | B23: =D23/$D$15 -> 0.072717997 | C23: GASTOS OPERATIVOS | D23: =SUMIFS(BBDD_GASTOS_FINAL!$Z:$Z,BBDD_GASTOS_FINAL!$V:$V,$B$1,BBDD_GASTOS_FINAL!$W:$W,$B$14,BBDD_GASTOS_FINAL!AC:AC,lote_2925!$C23)*-1 -> 1535766.9 | E23: 8 | F23: =H23/$H$15 -> 0.079745705 | G23: GASTOS OPERATIVOS | H23: =SUMIFS(BBDD_GASTOS_FINAL!$Z:$Z,BBDD_GASTOS_FINAL!$V:$V,$B$1,BBDD_GASTOS_FINAL!$W:$W,$F$14,BBDD_GASTOS_FINAL!$AC:$AC,$G23)*-1 -> 1535766.9 | I23: =I22+1 -> 19 | J23: =L23/$L$15 -> 0.079745705 | K23: GASTOS OPERATIVOS | L23: =SUMIFS(BBDD_GASTOS_FINAL!$Z:$Z,BBDD_GASTOS_FINAL!$V:$V,$B$1,BBDD_GASTOS_FINAL!$W:$W,$F$14,BBDD_GASTOS_FINAL!$AC:$AC,$G23)*-1 -> 1535766.9 | M23: =M22+1 -> 8
A24: =A23+1 -> 9 | B24: =D24/$D$15 -> 0.04270714 | C24: IMPUESTOS | D24: =SUMIFS(BBDD_GASTOS_FINAL!$Z:$Z,BBDD_GASTOS_FINAL!$V:$V,$B$1,BBDD_GASTOS_FINAL!$W:$W,$B$14,BBDD_GASTOS_FINAL!AC:AC,lote_2925!$C24)*-1 -> 901952.95 | E24: 9 | F24: =H24/$H$15 -> 0.098541866 | G24: IMPUESTOS | H24: =SUMIFS(BBDD_GASTOS_FINAL!$Z:$Z,BBDD_GASTOS_FINAL!$V:$V,$B$1,BBDD_GASTOS_FINAL!$W:$W,$F$14,BBDD_GASTOS_FINAL!$AC:$AC,$G24)*-1 -> 1897749 | I24: =I23+1 -> 20 | J24: =L24/$L$15 -> 0.098541866 | K24: IMPUESTOS | L24: =SUMIFS(BBDD_GASTOS_FINAL!$Z:$Z,BBDD_GASTOS_FINAL!$V:$V,$B$1,BBDD_GASTOS_FINAL!$W:$W,$F$14,BBDD_GASTOS_FINAL!$AC:$AC,$G24)*-1 -> 1897749 | M24: =M23+1 -> 9
A25: =A24+1 -> 10 | B25: =D25/$D$15 -> 0.020303275 | C25: HONORARIOS | D25: =SUMIFS(BBDD_GASTOS_FINAL!$Z:$Z,BBDD_GASTOS_FINAL!$V:$V,$B$1,BBDD_GASTOS_FINAL!$W:$W,$B$14,BBDD_GASTOS_FINAL!AC:AC,lote_2925!$C25)*-1 -> 428794.79 | E25: 10 | F25: =H25/$H$15 -> 0.022265451 | G25: HONORARIOS | H25: =SUMIFS(BBDD_GASTOS_FINAL!$Z:$Z,BBDD_GASTOS_FINAL!$V:$V,$B$1,BBDD_GASTOS_FINAL!$W:$W,$F$14,BBDD_GASTOS_FINAL!$AC:$AC,$G25)*-1 -> 428794.79 | I25: =I24+1 -> 21 | J25: =L25/$L$15 -> 0.022265451 | K25: HONORARIOS | L25: =SUMIFS(BBDD_GASTOS_FINAL!$Z:$Z,BBDD_GASTOS_FINAL!$V:$V,$B$1,BBDD_GASTOS_FINAL!$W:$W,$F$14,BBDD_GASTOS_FINAL!$AC:$AC,$G25)*-1 -> 428794.79 | M25: =M24+1 -> 10
B26: =D26/$D$15 -> 0 | C26: SERVICIOS | D26: =SUMIFS(BBDD_GASTOS_FINAL!$Z:$Z,BBDD_GASTOS_FINAL!$V:$V,$B$1,BBDD_GASTOS_FINAL!$W:$W,$B$14,BBDD_GASTOS_FINAL!AC:AC,lote_2925!$C26)*-1 -> 0 | F26: =H26/$H$15 -> 0 | G26: SERVICIOS | H26: =SUMIFS(BBDD_GASTOS_FINAL!$Z:$Z,BBDD_GASTOS_FINAL!$V:$V,$B$1,BBDD_GASTOS_FINAL!$W:$W,$F$14,BBDD_GASTOS_FINAL!$AC:$AC,$G26)*-1 -> 0 | J26: =L26/$L$15 -> 0 | K26: OTROS | L26: =SUMIFS(BBDD_GASTOS_FINAL!$Z:$Z,BBDD_GASTOS_FINAL!$V:$V,$B$1,BBDD_GASTOS_FINAL!$W:$W,$F$14,BBDD_GASTOS_FINAL!$AC:$AC,$G26)*-1 -> 0
F28: COMPRAS EN GESTACION | H28: =D15 -> 21119488 | J28: COMPRAS EN MATERNIDAD | L28: =H29 -> 27342169
B29: VENTAS | D29: =SUMIFS(produccion!$H:$H,produccion!$A:$A,lote_2925!$B$1,produccion!$B:$B,lote_2925!B14) -> 0 | F29: VENTAS | H29: =SUMIFS(produccion!$H:$H,produccion!$A:$A,lote_2925!$B$1,produccion!$B:$B,lote_2925!F14) -> 27342169 | J29: VENTAS | L29: =SUMIFS(produccion!$H:$H,produccion!$A:$A,lote_2925!$B$1,produccion!$B:$B,lote_2925!J14) -> 49109114
B31: UTILDAD | D31: =D29-D15-D28 -> -21119488 | F31: UTILDAD | H31: =H29-H15-H28 -> -13035622 | J31: UTILDAD | L31: =L29-L15-L28 -> 2508643.2
B33: CAPEX | D33: =SUMIFS(BBDD_GASTOS_FINAL!$Y:$Y,BBDD_GASTOS_FINAL!$J:$J,"Capex",BBDD_GASTOS_FINAL!$Z:$Z,$B$13) -> 0 | F33: CAPEX | H33: =SUMIFS(BBDD_GASTOS_FINAL!$Y:$Y,BBDD_GASTOS_FINAL!$J:$J,"Capex",BBDD_GASTOS_FINAL!$Z:$Z,$F$13) -> 0 | J33: CAPEX | L33: =SUMIFS(BBDD_GASTOS_FINAL!$Y:$Y,BBDD_GASTOS_FINAL!$J:$J,"Capex",BBDD_GASTOS_FINAL!$Z:$Z,$J$13) -> 0
B35: DEUDA | D35: =SUMIFS(BBDD_GASTOS_FINAL!$Y:$Y,BBDD_GASTOS_FINAL!$J:$J,"Deuda",BBDD_GASTOS_FINAL!$V:$V,B14) -> 0 | F35: DEUDA | H35: =SUMIFS(BBDD_GASTOS_FINAL!$Y:$Y,BBDD_GASTOS_FINAL!$J:$J,"Deuda",BBDD_GASTOS_FINAL!$V:$V,F14) -> 0 | J35: DEUDA | L35: =SUMIFS(BBDD_GASTOS_FINAL!$Y:$Y,BBDD_GASTOS_FINAL!$J:$J,"deuda",BBDD_GASTOS_FINAL!$V:$V,J14) -> 0
B37: Flujo de Caja al Accionista | D37: =D31-D35-D33 -> -21119488 | F37: Flujo de Caja al Accionista | H37: =H31-H35-H33 -> -13035622 | J37: Flujo de Caja al Accionista | L37: =L31-L35-L33 -> 2508643.2
F38: Margen de utilidad | H38: =H31/H29 -> -0.47675889 | J38: Margen de utilidad | L38: =L31/L29 -> 0.051083048
A39: id | B39: 1 | M39: id
B40: SITIO 3
B41: OPEX | D41: =SUM(D42:D52) -> 60008523
A42: 1 | B42: =D42/$D$41 -> 0.83774482 | C42: NUTRICIÓN | D42: =SUMIFS(BBDD_GASTOS_FINAL!$Z:$Z,BBDD_GASTOS_FINAL!$V:$V,$B$1,BBDD_GASTOS_FINAL!$W:$W,$B$40,BBDD_GASTOS_FINAL!$AC:$AC,lote_2925!$C42)*-1 -> 50271829
A43: =A42+1 -> 2 | B43: =D43/$D$41 -> 0.078499379 | C43: PERSONAL | D43: =SUMIFS(BBDD_GASTOS_FINAL!$Z:$Z,BBDD_GASTOS_FINAL!$V:$V,$B$1,BBDD_GASTOS_FINAL!$W:$W,$B$40,BBDD_GASTOS_FINAL!AC:AC,lote_2925!$C43)*-1 -> 4710631.8
A44: =A43+1 -> 3 | B44: =D44/$D$41 -> 0 | C44: SANIDAD | D44: =SUMIFS(BBDD_GASTOS_FINAL!$Z:$Z,BBDD_GASTOS_FINAL!$V:$V,$B$1,BBDD_GASTOS_FINAL!$W:$W,$B$40,BBDD_GASTOS_FINAL!AC:AC,lote_2925!$C44)*-1 -> 0
A45: =A44+1 -> 4 | B45: =D45/$D$41 -> 0 | C45: GENÉTICA | D45: =SUMIFS(BBDD_GASTOS_FINAL!$Z:$Z,BBDD_GASTOS_FINAL!$V:$V,$B$1,BBDD_GASTOS_FINAL!$W:$W,$B$40,BBDD_GASTOS_FINAL!AC:AC,lote_2925!$C45)*-1 -> 0
A46: =A45+1 -> 5 | B46: =D46/$D$41 -> 0.035987346 | C46: FLETES | D46: =SUMIFS(BBDD_GASTOS_FINAL!$Z:$Z,BBDD_GASTOS_FINAL!$V:$V,$B$1,BBDD_GASTOS_FINAL!$W:$W,$B$40,BBDD_GASTOS_FINAL!AC:AC,lote_2925!$C46)*-1 -> 2159547.5
A47: =A46+1 -> 6 | B47: =D47/$D$41 -> 0 | C47: ENERGÍA | D47: =SUMIFS(BBDD_GASTOS_FINAL!$Z:$Z,BBDD_GASTOS_FINAL!$V:$V,$B$1,BBDD_GASTOS_FINAL!$W:$W,$B$40,BBDD_GASTOS_FINAL!AC:AC,lote_2925!$C47)*-1 -> 0
A48: =A47+1 -> 7 | B48: =D48/$D$41 -> 0 | C48: MENTENIMIENTO | D48: =SUMIFS(BBDD_GASTOS_FINAL!$Z:$Z,BBDD_GASTOS_FINAL!$V:$V,$B$1,BBDD_GASTOS_FINAL!$W:$W,$B$40,BBDD_GASTOS_FINAL!AC:AC,lote_2925!$C48)*-1 -> 0
A49: =A48+1 -> 8 | B49: =D49/$D$41 -> 0.025592479 | C49: GASTOS OPERATIVOS | D49: =SUMIFS(BBDD_GASTOS_FINAL!$Z:$Z,BBDD_GASTOS_FINAL!$V:$V,$B$1,BBDD_GASTOS_FINAL!$W:$W,$B$40,BBDD_GASTOS_FINAL!AC:AC,lote_2925!$C49)*-1 -> 1535766.9
A50: =A49+1 -> 9 | B50: =D50/$D$41 -> 0.015030414 | C50: IMPUESTOS | D50: =SUMIFS(BBDD_GASTOS_FINAL!$Z:$Z,BBDD_GASTOS_FINAL!$V:$V,$B$1,BBDD_GASTOS_FINAL!$W:$W,$B$40,BBDD_GASTOS_FINAL!AC:AC,lote_2925!$C50)*-1 -> 901952.95
A51: =A50+1 -> 10 | B51: =D51/$D$41 -> 0.0071455647 | C51: HONORARIOS | D51: =SUMIFS(BBDD_GASTOS_FINAL!$Z:$Z,BBDD_GASTOS_FINAL!$V:$V,$B$1,BBDD_GASTOS_FINAL!$W:$W,$B$40,BBDD_GASTOS_FINAL!AC:AC,lote_2925!$C51)*-1 -> 428794.79
B52: =D52/$D$41 -> 0 | C52: SERVICIOS | D52: =SUMIFS(BBDD_GASTOS_FINAL!$Z:$Z,BBDD_GASTOS_FINAL!$V:$V,$B$1,BBDD_GASTOS_FINAL!$W:$W,$B$40,BBDD_GASTOS_FINAL!AC:AC,lote_2925!$C52)*-1 -> 0
B54: COMPRAS EN SITIO 2 | D54: =L29 -> 49109114
B55: VENTAS | D55: =SUMIFS(produccion!$H:$H,produccion!$A:$A,lote_2925!$B$1,produccion!$B:$B,lote_2925!B40) -> 1.4001281e+08
B57: UTILDAD | D57: =D55-D41-D54 -> 30895168
B59: CAPEX | D59: =SUMIFS(BBDD_GASTOS_FINAL!$Y:$Y,BBDD_GASTOS_FINAL!$J:$J,"Capex",BBDD_GASTOS_FINAL!$Z:$Z,$B$39) -> 0
B61: DEUDA | D61: =SUMIFS(BBDD_GASTOS_FINAL!$Y:$Y,BBDD_GASTOS_FINAL!$J:$J,"deuda",BBDD_GASTOS_FINAL!$V:$V,B40) -> 0
B63: Flujo de Caja al Accionista | D63: =D57-D61-D59 -> 30895168
B64: Margen de utilidad | D64: =D57/D55 -> 0.22065959
A65: id | B65: 9 | E65: id
A66: LOTE | B66: =B1 -> 2925
A67: TOTAL | B67: <> & ""
B68: OPEX | D68: =SUM(D69:D79) -> 1.1817352e+08
B69: =D69/$D$68 -> 0.62965846 | C69: NUTRICIÓN | D69: =SUMIFS(BBDD_GASTOS_FINAL!$Z:$Z,BBDD_GASTOS_FINAL!$V:$V,$B$1,BBDD_GASTOS_FINAL!$W:$W,$B$67,BBDD_GASTOS_FINAL!$AC:$AC,lote_2925!$C69)*-1 -> 74408954
B70: =D70/$D$68 -> 0.19170592 | C70: PERSONAL | D70: =SUMIFS(BBDD_GASTOS_FINAL!$Z:$Z,BBDD_GASTOS_FINAL!$V:$V,$B$1,BBDD_GASTOS_FINAL!$W:$W,$B$67,BBDD_GASTOS_FINAL!$AC:$AC,lote_2925!$C70)*-1 -> 22654563
B71: =D71/$D$68 -> 0.029554001 | C71: SANIDAD | D71: =SUMIFS(BBDD_GASTOS_FINAL!$Z:$Z,BBDD_GASTOS_FINAL!$V:$V,$B$1,BBDD_GASTOS_FINAL!$W:$W,$B$67,BBDD_GASTOS_FINAL!$AC:$AC,lote_2925!$C71)*-1 -> 3492500.2
B72: =D72/$D$68 -> 0.024687524 | C72: GENÉTICA | D72: =SUMIFS(BBDD_GASTOS_FINAL!$Z:$Z,BBDD_GASTOS_FINAL!$V:$V,$B$1,BBDD_GASTOS_FINAL!$W:$W,$B$67,BBDD_GASTOS_FINAL!$AC:$AC,lote_2925!$C72)*-1 -> 2917411.5
B73: =D73/$D$68 -> 0.018274378 | C73: FLETES | D73: =SUMIFS(BBDD_GASTOS_FINAL!$Z:$Z,BBDD_GASTOS_FINAL!$V:$V,$B$1,BBDD_GASTOS_FINAL!$W:$W,$B$67,BBDD_GASTOS_FINAL!$AC:$AC,lote_2925!$C73)*-1 -> 2159547.5
B74: =D74/$D$68 -> 0 | C74: ENERGÍA | D74: =SUMIFS(BBDD_GASTOS_FINAL!$Z:$Z,BBDD_GASTOS_FINAL!$V:$V,$B$1,BBDD_GASTOS_FINAL!$W:$W,$B$67,BBDD_GASTOS_FINAL!$AC:$AC,lote_2925!$C74)*-1 -> 0
B75: =D75/$D$68 -> 0 | C75: MENTENIMIENTO | D75: =SUMIFS(BBDD_GASTOS_FINAL!$Z:$Z,BBDD_GASTOS_FINAL!$V:$V,$B$1,BBDD_GASTOS_FINAL!$W:$W,$B$67,BBDD_GASTOS_FINAL!$AC:$AC,lote_2925!$C75)*-1 -> 0
B76: =D76/$D$68 -> 0.051983455 | C76: GASTOS OPERATIVOS | D76: =SUMIFS(BBDD_GASTOS_FINAL!$Z:$Z,BBDD_GASTOS_FINAL!$V:$V,$B$1,BBDD_GASTOS_FINAL!$W:$W,$B$67,BBDD_GASTOS_FINAL!$AC:$AC,lote_2925!$C76)*-1 -> 6143067.6
B77: =D77/$D$68 -> 0.039622184 | C77: IMPUESTOS | D77: =SUMIFS(BBDD_GASTOS_FINAL!$Z:$Z,BBDD_GASTOS_FINAL!$V:$V,$B$1,BBDD_GASTOS_FINAL!$W:$W,$B$67,BBDD_GASTOS_FINAL!$AC:$AC,lote_2925!$C77)*-1 -> 4682292.7
B78: =D78/$D$68 -> 0.014514074 | C78: HONORARIOS | D78: =SUMIFS(BBDD_GASTOS_FINAL!$Z:$Z,BBDD_GASTOS_FINAL!$V:$V,$B$1,BBDD_GASTOS_FINAL!$W:$W,$B$67,BBDD_GASTOS_FINAL!$AC:$AC,lote_2925!$C78)*-1 -> 1715179.1
B79: =D79/$D$68 -> 0 | C79: SERVICIOS | D79: =SUMIFS(BBDD_GASTOS_FINAL!$Z:$Z,BBDD_GASTOS_FINAL!$V:$V,$B$1,BBDD_GASTOS_FINAL!$W:$W,$B$67,BBDD_GASTOS_FINAL!$AC:$AC,lote_2925!$C79)*-1 -> 0
B81: VENTAS | D81: =C6 -> 1.4001281e+08
B83: UTILDAD | D83: =D81-D68 -> 21839290
B85: CAPEX | D85: =SUMIFS(BBDD_GASTOS_FINAL!$Y:$Y,BBDD_GASTOS_FINAL!$J:$J,"Capex",BBDD_GASTOS_FINAL!$Z:$Z,$B$39) -> 0
B87: DEUDA | D87: =SUMIFS(BBDD_GASTOS_FINAL!$Y:$Y,BBDD_GASTOS_FINAL!$J:$J,"deuda",BBDD_GASTOS_FINAL!$V:$V,B67) -> 0
B89: Flujo de Caja al Accionista | D89: =D83-D87-D85 -> 21839290
B90: OPEX UN | C90: =D15+H15+L15+P15+P41+L41+H41+D41+#REF!+#REF!+#REF! -> #REF!
B91: OPEX total | C91: =C7 -> 1.1806259e+08
C92: =MROUND(C91,10000)=MROUND(C90,10000) -> #REF!
B94: CAPEX_UN | C94: =D33+H33+L33+P33+P59+L59+H59+D59+D67+H67+L67 -> 0
B95: CAPEX_TOTAL | C95: =C9 -> 0 | D95: =C94=C95 -> TRUE
B96: DEUDA_UN | C96: =D35+H35+L35+P35+P61+L61+H61+D61+D69+H69+L69 -> 74408954
B97: DEUDA_TOTAL | C97: =C10 -> 0 | D97: =C96=C97 -> FALSE
B101: UTILIDAD_TOTAL | C101: =C8 -> 21950213
B102: UTILIDAD_UN | C102: =D31+H31+L31+P31+P57+L57+H57+D57+#REF!+#REF!+#REF! -> #REF! | D102: =MROUND(C102,10000)=MROUND(C101,10000) -> #REF!
B105: Flujo_TOTAL | C105: =C11 -> 21950213
B106: FLUJO_UN | C106: =D37+H37+L37+P37+P63+L63+H63+D63+D71+H71+L71 -> 2741201.3 | D106: =MROUND(C106,10000)=MROUND(C105,10000) -> FALSE
B107: Margen de utilidad | D107: =D83/D81 -> 0.15598066

Sheet RRHH
C1: TOTAL 1+2 | D1: COMPONENTE
A2: ADMINISTRACION | B2: =_xlfn.CONCAT("RRHH-",A2) -> RRHH-ADMINISTRACION | C2: 67124149 | D2: 100% ADMINISTRACION - 100% DIRECTOR | E2: CC1
A3: INTENDENCIA | B3: =_xlfn.CONCAT("RRHH-",A3) -> RRHH-INTENDENCIA | C3: 9375237.7 | D3: 100% INTENDENCIA - 6,67% PRODUCCION | E3: CC1
A4: LABORATORIO | B4: =_xlfn.CONCAT("RRHH-",A4) -> RRHH-LABORATORIO | C4: 12249966 | D4: 100% LABORATORIO - 6,67% PRODUCCION | E4: CC1
A5: LOGISTICA | B5: =_xlfn.CONCAT("RRHH-",A5) -> RRHH-LOGISTICA | C5: 6459899.7 | D5: 75% LOGISTICA - 6,67% PRODUCCION | E5: CC1
A6: MANTENIMIENTO | B6: =_xlfn.CONCAT("RRHH-",A6) -> RRHH-MANTENIMIENTO | C6: 7742399.7 | D6: 100% MANTENIMIENTO - 6,67% PRODUCCION | E6: CC1
A7: NFU | B7: =_xlfn.CONCAT("RRHH-",A7) -> RRHH-NFU | C7: 29572095 | D7: 25% LOGISTICA - 100% CAT - 100% EXTERNO NFU - 6,67% PRODUCCION - 95% NFU | E7: CC7
A8: PORTERIA | B8: =_xlfn.CONCAT("RRHH-",A8) -> RRHH-PORTERIA | C8: 10797311 | D8: 100% PORTERIA - 6,67% PRODUCCION | E8: CC1
A9: COMPOST Y FERTILIZANTES | B9: =_xlfn.CONCAT("RRHH-",A9) -> RRHH-COMPOST Y FERTILIZANTES | C9: 1833599.1 | D9: 60% COMPOST Y FERTILIZANTES - 6,67% PRODUCCION | E9: CC14
A10: CEREAL Y POLVILLO | B10: =_xlfn.CONCAT("RRHH-",A10) -> RRHH-CEREAL Y POLVILLO | C10: 0 | D10: 0% CEREAL Y POLVILLO - 0% PRODUCCION | E10: NO
A11: TALLER MECANICO | B11: =_xlfn.CONCAT("RRHH-",A11) -> RRHH-TALLER MECANICO | C11: 6300478.7 | D11: 100% TALLER MECANICO - 6,67% PRODUCCION | E11: CC1
A12: TIERRAS FILTRANTES | B12: =_xlfn.CONCAT("RRHH-",A12) -> RRHH-TIERRAS FILTRANTES | C12: 0 | D12: 0% TIERRAS FILTRANTES - 0% PRODUCCION | E12: NO
A13: VIGILANCIA | B13: =_xlfn.CONCAT("RRHH-",A13) -> RRHH-VIGILANCIA | C13: 6294101.7 | D13: 100% VIGILANCIA - 6,67% PRODUCCION | E13: CC1
... A21: SALES | B21: =_xlfn.CONCAT("RRHH-",A21) -> RRHH-SALES | C21: 0 | D21: 0% SALES - 0% PRODUCCION | E21: NO

Sheet ref_rrhh
A1: Sector | B1: f/v | C1: d/i
A2: ADMINISTRACION | B2: Fijo | C2: Indirecto
A3: INTENDENCIA | B3: Fijo | C3: Indirecto
A4: REACTOR | B4: Variable | C4: Directo
A5: NFU | B5: Variable | C5: Directo
A6: DISPOSICION FINAL DE R. LIQUIDOS | B6: Variable | C6: Directo
A7: DIRECTOR | B7: Fijo | C7: Indirecto
A8: TALLER MECANICO | B8: Fijo | C8: Indirecto
A9: PRODUCCION | B9: Variable | C9: Directo
A10: CAT | B10: Variable | C10: Directo
A11: MANTENIMIENTO | B11: Fijo | C11: Indirecto
A12: PORTERIA | B12: Fijo | C12: Indirecto
... A17: COMPOST Y FERTILIZANTES | B17: Variable | C17: Directo

Sheet aperturado_por_empresa.p2
A1: {=_xlfn._xlws.PY(0,0,#REF!)} -> #REF!

Sheet bbdd_ape.p3
A1: Fecha de Factura/Recibo | B1: Nombre de la empresa a mostrar en la factura | C1: Número | D1: Total con signo | E1: Líneas de factura/Etiqueta | F1: Líneas de factura/Cantidad | G1: Líneas de factura/Precio unitario | H1: Líneas de factura/Unidad de medida | I1: Líneas de factura/Producto | J1: Concepto | K1: Tipo de Gasto 1 | L1: Tipo de Gasto 2 | M1: CCO EMPRESA | N1: CCO - SECTOR | O1: SECTOR_ODOO | P1: # SECTORES | Q1: LISTA_SECTORES | R1: Column1 | S1: Column2 | T1: Column3 | U1: Column4
A2: 45958 | B2: H.S.E. Ingenieria S R L | C2: FA-A 00003-00027849 | D2: -3315400 | E2: OC 0001-00001756: SERVICIOS Monitoreo | F2: 1 | G2: 2740000 | H2: UN | I2: SERVICIOS | J2: OPEX | K2: VARIABLE | L2: INDIRECTO | M2: 0 | N2: CC1 | O2: #NUM! | P2: 10 | Q2: BACHAS, CEREAL & POLVILLO, COMPOST & FERTILIZANTES, DISPOSICIÓN FINAL RESIDUOS LIQUIDOS, DISPOSICIÓN FINAL RESIDUOS SOLIDOS, EXPORTACION, NFU, PILETAS, REACTORES, TIERRAS FILTRANTES | R2: 1 | S2: -3315400 | T2: 1 | U2: APERTURADO POR EMPRESA
A3: 45933 | B3: Alvarez, Alejandro Dario | C3: FA-C 00002-00000250 | D3: -509644 | E3: OC 0001-00001364: HIGIENE Y SEGURIDAD Servicio de asesoramiento para la gestión ambiental en el cumplimiento de la normativa vigente para la provincia de Santa Fe. Servicio de higiene y seguridad de trabajo con cumplimiento de actividades s/Resol. SRT 905/15- MES 09/2025 | F3: 1 | G3: 509644 | H3: UN | I3: HIGIENE Y SEGURIDAD | J3: OPEX | K3: FIJO | L3: DIRECTO | M3: 0 | N3: CC1 | O3: #NUM! | P3: 10 | Q3: BACHAS, CEREAL & POLVILLO, COMPOST & FERTILIZANTES, DISPOSICIÓN FINAL RESIDUOS LIQUIDOS, DISPOSICIÓN FINAL RESIDUOS SOLIDOS, EXPORTACION, NFU, PILETAS, REACTORES, TIERRAS FILTRANTES | R3: 1 | S3: -509644 | T3: 1 | U3: APERTURADO POR EMPRESA
A4: 45931 | B4: Quiroz, Maria Ines | C4: FA-C 00002-00000031 | D4: -2097200 | E4: OC 0001-00001801: PERSONAL horas soldador | F4: 1 | G4: 2097200 | H4: UN | I4: PERSONAL | J4: OPEX | K4: FIJO | L4: INDIRECTO | M4: 0 | N4: CC1 | O4: #NUM! | P4: 10 | Q4: BACHAS, CEREAL & POLVILLO, COMPOST & FERTILIZANTES, DISPOSICIÓN FINAL RESIDUOS LIQUIDOS, DISPOSICIÓN FINAL RESIDUOS SOLIDOS, EXPORTACION, NFU, PILETAS, REACTORES, TIERRAS FILTRANTES | R4: 1 | S4: -2097200 | T4: 1 | U4: APERTURADO POR EMPRESA
A5: 45947 | B5: Lopez, Jesus Rodrigo | C5: OCOM/2025/0470 | D5: -180000 | E5: OC 0001-00001345: LOGISTICA puerto | F5: 1 | G5: 180000 | H5: UN | I5: LOGISTICA | J5: OPEX | K5: VARIABLE | L5: DIRECTO | M5: 0 | N5: CC9 | O5: #NUM! | P5: 1 | Q5: CEREAL & POLVILLO | R5: 1 | S5: -180000 | T5: 1 | U5: APERTURADO POR EMPRESA
A6: 45938 | B6: Lopez, Jesus Rodrigo | C6: OCOM/2025/0458 | D6: -180000 | E6: OC 0001-00001804: LOGISTICA | F6: 1 | G6: 180000 | H6: UN | I6: LOGISTICA | J6: OPEX | K6: VARIABLE | L6: DIRECTO | M6: 0 | N6: CC9 | O6: #NUM! | P6: 1 | Q6: CEREAL & POLVILLO | R6: 1 | S6: -180000 | T6: 1 | U6: APERTURADO POR EMPRESA
A7: 45931 | B7: Lopez, Jesus Rodrigo | C7: OCOM/2025/0443 | D7: -156000 | E7: OC 0001-00000944: LOGISTICA | F7: 1 | G7: 156000 | H7: UN | I7: LOGISTICA | J7: OPEX | K7: VARIABLE | L7: DIRECTO | M7: 0 | N7: CC9 | O7: #NUM! | P7: 1 | Q7: CEREAL & POLVILLO | R7: 1 | S7: -156000 | T7: 1 | U7: APERTURADO POR EMPRESA
A8: 45950 | B8: Area Abierta S.A. | C8: FA-A 00001-00001146 | D8: -798367.68 | E8: OC 0001-00001924: REPOSICION paño zda luz 6.50 2.50 mm 4 x1,60 metros (NFU) | F8: 1 | G8: 659808 | H8: UN | I8: REPOSICION | J8: OPEX | K8: VARIABLE | L8: DIRECTO | M8: 0 | N8: CC7 | O8: #NUM! | P8: 2 | Q8: NFU | R8: 1 | S8: -798367.68 | T8: 1 | U8: APERTURADO POR EMPRESA
A9: 45958 | B9: Bernis, Carlos Oscar | C9: FA-A 00006-00000175 | D9: -968000 | E9: OC 0001-00002255: LOGISTICA Viaje realizado fecha 28/10 | F9: 1 | G9: 800000 | H9: UN | I9: LOGISTICA | J9: OPEX | K9: VARIABLE | L9: DIRECTO | M9: 0 | N9: CC7 | O9: #NUM! | P9: 2 | Q9: NFU | R9: 1 | S9: -968000 | T9: 1 | U9: APERTURADO POR EMPRESA
A10: 45952 | B10: Bernis, Carlos Oscar | C10: FA-A 00006-00000174 | D10: -968000 | E10: OC 0001-00002218: LOGISTICA Viaje realizado fecha 20-10 worms - Parque industrial guernica | F10: 1 | G10: 800000 | H10: UN | I10: LOGISTICA | J10: OPEX | K10: VARIABLE | L10: DIRECTO | M10: 0 | N10: CC7 | O10: #NUM! | P10: 2 | Q10: NFU | R10: 1 | S10: -968000 | T10: 1 | U10: APERTURADO POR EMPRESA
A11: 45939 | B11: Bernis, Carlos Oscar | C11: FA-A 00006-00000171 | D11: -302500 | E11: OC 0001-00001836: LOGISTICA Viaje: 4 de septiembre origen: lujan worms con cubiertas en desuso . Destino :worms | F11: 1 | G11: 250000 | H11: UN | I11: LOGISTICA | J11: OPEX | K11: VARIABLE | L11: DIRECTO | M11: 0 | N11: CC7 | O11: #NUM! | P11: 2 | Q11: NFU | R11: 1 | S11: -302500 | T11: 1 | U11: APERTURADO POR EMPRESA
A12: 45939 | B12: Bernis, Carlos Oscar | C12: FA-A 00006-00000170 | D12: -968000 | E12: OC 0001-00002228: LOGISTICA Viaje realizado fecha 8/10 neumáticos | F12: 1 | G12: 800000 | H12: UN | I12: LOGISTICA | J12: OPEX | K12: VARIABLE | L12: DIRECTO | M12: 0 | N12: CC7 | O12: #NUM! | P12: 2 | Q12: NFU | R12: 1 | S12: -968000 | T12: 1 | U12: APERTURADO POR EMPRESA
A13: 45958 | B13: Comercial Uritorco S. R. L. (w) | C13: FA-A 00001-00007089 | D13: -66182.16 | E13: OC 0001-00002229: REPOSICION Adaptador 3/4 | F13: 2 | G13: 19578.51 | H13: UN | I13: REPOSICION | J13: OPEX | K13: VARIABLE | L13: INDIRECTO | M13: 0 | N13: CC7 | O13: #NUM! | P13: 2 | Q13: NFU | R13: 1 | S13: -66182.16 | T13: 2 | U13: APERTURADO POR EMPRESA
... A77: 45932 | B77: Acosta, Roberto Maximiliano | C77: FA-C 00001-00000616 | D77: -4632990 | E77: OC 0001-00001709: SERVICIOS de limpieza +ipc julio y agosto 3,8% | F77: 1 | G77: 4632990 | H77: UN | I77: SERVICIOS | J77: OPEX | K77: VARIABLE | L77: INDIRECTO | M77: 0 | N77: CC1 | O77: #NUM! | P77: 10 | Q77: BACHAS, CEREAL & POLVILLO, COMPOST & FERTILIZANTES, DISPOSICIÓN FINAL RESIDUOS LIQUIDOS, DISPOSICIÓN FINAL RESIDUOS SOLIDOS, EXPORTACION, NFU, PILETAS, REACTORES, TIERRAS FILTRANTES | R77: 1 | S77: -4632990 | T77: 1 | U77: APERTURADO POR EMPRESA
A78: 45931 | B78: Adhoc S.A. | C78: FA-A 00003-00019779 | D78: -2004596.6 | E78: OC 0001-00001367: SERVICIOS Sistema contable | F78: 1 | G78: 1656691.4 | H78: UN | I78: SERVICIOS | J78: OPEX | K78: FIJO | L78: INDIRECTO | M78: CC13 | N78: CC1 | O78: #NUM! | P78: 10 | Q78: BACHAS, CEREAL & POLVILLO, COMPOST & FERTILIZANTES, DISPOSICIÓN FINAL RESIDUOS LIQUIDOS, DISPOSICIÓN FINAL RESIDUOS SOLIDOS, EXPORTACION, NFU, PILETAS, REACTORES, TIERRAS FILTRANTES | R78: 0.7 | S78: -1403217.6 | T78: 0.7 | U78: APERTURADO POR EMPRESA
A79: 45950 | B79: American Express Argentina S. A. | C79: OCOM/2025/0472 | D79: -344000.85 | E79: OC 0001-00001936: PERSONAL | F79: 1 | G79: 344000.85 | H79: UN | I79: PERSONAL | J79: OPEX | K79: VARIABLE | L79: INDIRECTO | M79: 0 | N79: CC1 | O79: #NUM! | P79: 10 | Q79: BACHAS, CEREAL & POLVILLO, COMPOST & FERTILIZANTES, DISPOSICIÓN FINAL RESIDUOS LIQUIDOS, DISPOSICIÓN FINAL RESIDUOS SOLIDOS, EXPORTACION, NFU, PILETAS, REACTORES, TIERRAS FILTRANTES | R79: 1 | S79: -344000.85 | T79: 1 | U79: APERTURADO POR EMPRESA
A80: 45949 | B80: Amx Argentina Sociedad Anonima | C80: FA-A 01331-01351660 | D80: -40348.6 | E80: OC 0001-00002225: SERVICIOS Servicio Móvil | F80: 1 | G80: 10605 | H80: UN | I80: SERVICIOS | J80: OPEX | K80: VARIABLE | L80: INDIRECTO | M80: 0 | N80: CC1 | O80: #NUM! | P80: 10 | Q80: BACHAS, CEREAL & POLVILLO, COMPOST & FERTILIZANTES, DISPOSICIÓN FINAL RESIDUOS LIQUIDOS, DISPOSICIÓN FINAL RESIDUOS SOLIDOS, EXPORTACION, NFU, PILETAS, REACTORES, TIERRAS FILTRANTES | R80: 1 | S80: -40348.6 | T80: 1 | U80: APERTURADO POR EMPRESA
A81: 45931 | B81: Aranda, Marisa Isabel | C81: FA-C 00005-00000212 | D81: -720000 | E81: OC 0001-00001711: SERVICIOS servicio de parquización | F81: 9 | G81: 80000 | H81: UN | I81: SERVICIOS | J81: OPEX | K81: VARIABLE | L81: INDIRECTO | M81: 0 | N81: CC1 | O81: #NUM! | P81: 10 | Q81: BACHAS, CEREAL & POLVILLO, COMPOST & FERTILIZANTES, DISPOSICIÓN FINAL RESIDUOS LIQUIDOS, DISPOSICIÓN FINAL RESIDUOS SOLIDOS, EXPORTACION, NFU, PILETAS, REACTORES, TIERRAS FILTRANTES | R81: 1 | S81: -720000 | T81: 9 | U81: APERTURADO POR EMPRESA
A82: 45952 | B82: ARCA | C82: OCOM/2025/0481 | D82: -3840846 | E82: OC 0001-00002049: IMPUESTOS anticipo | F82: 1 | G82: 3840846 | H82: UN | I82: IMPUESTOS | J82: OPEX | K82: VARIABLE | L82: INDIRECTO | M82: 0 | N82: CC1 | O82: #NUM! | P82: 10 | Q82: BACHAS, CEREAL & POLVILLO, COMPOST & FERTILIZANTES, DISPOSICIÓN FINAL RESIDUOS LIQUIDOS, DISPOSICIÓN FINAL RESIDUOS SOLIDOS, EXPORTACION, NFU, PILETAS, REACTORES, TIERRAS FILTRANTES | R82: 1 | S82: -3840846 | T82: 1 | U82: APERTURADO POR EMPRESA
A83: 45952 | B83: ARCA | C83: OCOM/2025/0479 | D83: -1311921.2 | E83: OC 0001-00002043: IMPUESTOS Multa suse | F83: 1 | G83: 1311921.2 | H83: UN | I83: IMPUESTOS | J83: DEUDA | K83: VARIABLE | L83: INDIRECTO | M83: 0 | N83: CC1 | O83: #NUM! | P83: 10 | Q83: BACHAS, CEREAL & POLVILLO, COMPOST & FERTILIZANTES, DISPOSICIÓN FINAL RESIDUOS LIQUIDOS, DISPOSICIÓN FINAL RESIDUOS SOLIDOS, EXPORTACION, NFU, PILETAS, REACTORES, TIERRAS FILTRANTES | R83: 1 | S83: -1311921.2 | T83: 1 | U83: APERTURADO POR EMPRESA
A84: 45946 | B84: ARCA | C84: OCOM/2025/0466 | D84: -552778.24 | E84: OC 0001-00001904: HONORARIOS Didomenico | F84: 1 | G84: 552778.24 | H84: UN | I84: HONORARIOS | J84: DEUDA | K84: VARIABLE | L84: INDIRECTO | M84: 0 | N84: CC1 | O84: #NUM! | P84: 10 | Q84: BACHAS, CEREAL & POLVILLO, COMPOST & FERTILIZANTES, DISPOSICIÓN FINAL RESIDUOS LIQUIDOS, DISPOSICIÓN FINAL RESIDUOS SOLIDOS, EXPORTACION, NFU, PILETAS, REACTORES, TIERRAS FILTRANTES | R84: 1 | S84: -552778.24 | T84: 1 | U84: APERTURADO POR EMPRESA
A85: 45946 | B85: ARCA | C85: OCOM/2025/0464 | D85: -15235035 | E85: OC 0001-00001869: IMPUESTOS Deuda, Planes de pago | F85: 1 | G85: 15235035 | H85: UN | I85: IMPUESTOS | J85: DEUDA | K85: VARIABLE | L85: INDIRECTO | M85: 0 | N85: CC1 | O85: #NUM! | P85: 10 | Q85: BACHAS, CEREAL & POLVILLO, COMPOST & FERTILIZANTES, DISPOSICIÓN FINAL RESIDUOS LIQUIDOS, DISPOSICIÓN FINAL RESIDUOS SOLIDOS, EXPORTACION, NFU, PILETAS, REACTORES, TIERRAS FILTRANTES | R85: 1 | S85: -15235035 | T85: 1 | U85: APERTURADO POR EMPRESA
A86: 45954 | B86: Asociacion Empleados De Comercio De Rosario | C86: OCOM/2025/0504 | D86: -1383181 | E86: OC 0001-00002124: SERVICIOS | F86: 1 | G86: 1383181 | H86: UN | I86: SERVICIOS | J86: DEUDA | K86: VARIABLE | L86: INDIRECTO | M86: 0 | N86: CC1 | O86: #NUM! | P86: 10 | Q86: BACHAS, CEREAL & POLVILLO, COMPOST & FERTILIZANTES, DISPOSICIÓN FINAL RESIDUOS LIQUIDOS, DISPOSICIÓN FINAL RESIDUOS SOLIDOS, EXPORTACION, NFU, PILETAS, REACTORES, TIERRAS FILTRANTES | R86: 1 | S86: -1383181 | T86: 1 | U86: APERTURADO POR EMPRESA
A87: 45951 | B87: Asociacion Mutual 23 De Setiembre | C87: OCOM/2025/0477 | D87: -10000000 | E87: OC 0001-00002032: SERVICIOS mutual | F87: 1 | G87: 10000000 | H87: UN | I87: SERVICIOS | J87: DEUDA | K87: VARIABLE | L87: INDIRECTO | M87: 0 | N87: CC1 | O87: #NUM! | P87: 10 | Q87: BACHAS, CEREAL & POLVILLO, COMPOST & FERTILIZANTES, DISPOSICIÓN FINAL RESIDUOS LIQUIDOS, DISPOSICIÓN FINAL RESIDUOS SOLIDOS, EXPORTACION, NFU, PILETAS, REACTORES, TIERRAS FILTRANTES | R87: 1 | S87: -10000000 | T87: 1 | U87: APERTURADO POR EMPRESA
A88: 45931 | B88: Berardi, Alberto Jose - | C88: FA-C 00005-00000184 | D88: -560000 | E88: OC 0001-00001696: SERVICIOS Abono mensual | F88: 1 | G88: 560000 | H88: UN | I88: SERVICIOS | J88: OPEX | K88: VARIABLE | L88: INDIRECTO | M88: 0 | N88: CC1 | O88: #NUM! | P88: 10 | Q88: BACHAS, CEREAL & POLVILLO, COMPOST & FERTILIZANTES, DISPOSICIÓN FINAL RESIDUOS LIQUIDOS, DISPOSICIÓN FINAL RESIDUOS SOLIDOS, EXPORTACION, NFU, PILETAS, REACTORES, TIERRAS FILTRANTES | R88: 1 | S88: -560000 | T88: 1 | U88: APERTURADO POR EMPRESA
A89: 45943 | B89: Bollini, Tomas Maria | C89: OCOM/2025/0461 | D89: -114000 | E89: OC 0001-00001835: PERSONAL CARTA DOCUMENTO | F89: 1 | G89: 114000 | H89: UN | I89: PERSONAL | J89: OPEX | K89: VARIABLE | L89: INDIRECTO | M89: 0 | N89: CC1 | O89: #NUM! | P89: 10 | Q89: BACHAS, CEREAL & POLVILLO, COMPOST & FERTILIZANTES, DISPOSICIÓN FINAL RESIDUOS LIQUIDOS, DISPOSICIÓN FINAL RESIDUOS SOLIDOS, EXPORTACION, NFU, PILETAS, REACTORES, TIERRAS FILTRANTES | R89: 1 | S89: -114000 | T89: 1 | U89: APERTURADO POR EMPRESA
A90: 45937 | B90: Castelli, Guillermo Alejandro | C90: OCOM/2025/0457 | D90: -1500000 | E90: OC 0001-00001799: PERSONAL personal, acuerdo. | F90: 1 | G90: 1500000 | H90: UN | I90: PERSONAL | J90: DEUDA | K90: VARIABLE | L90: INDIRECTO | M90: 0 | N90: CC1 | O90: #NUM! | P90: 10 | Q90: BACHAS, CEREAL & POLVILLO, COMPOST & FERTILIZANTES, DISPOSICIÓN FINAL RESIDUOS LIQUIDOS, DISPOSICIÓN FINAL RESIDUOS SOLIDOS, EXPORTACION, NFU, PILETAS, REACTORES, TIERRAS FILTRANTES | R90: 1 | S90: -1500000 | T90: 1 | U90: APERTURADO POR EMPRESA
... A152: 45961 | B152: PROVEEDOR | C152: MT-0004 | D152: -3029264148 | E152: AFE (S) | F152: 2236.94 | G152: 925 | H152: TN | I152: MATERIA PRIMA | J152: OPEX | K152: VARIABLE | L152: DIRECTO | M152: 0 | N152: CC11 | O152: #NUM! | P152: 1 | Q152: EXPORTACION | R152: 1 | S152: -3029264148 | T152: 2236.94 | U152: APERTURADO POR EMPRESA
A153: 45961 | B153: PILETAS | C153: MT-0005 | D153: 0 | E153: AG- A | F153: #NUM! | G153: 850 | H153: TN | I153: MATERIA PRIMA | J153: OPEX | K153: VARIABLE | L153: DIRECTO | M153: 0 | N153: CC11 | O153: #NUM! | P153: 1 | Q153: EXPORTACION | R153: 1 | S153: 0 | T153: #NUM! | U153: APERTURADO POR EMPRESA
A154: 45961 | B154: PILETAS | C154: MT-0006 | D154: -24537811 | E154: AG- B | F154: 20.44 | G154: 820 | H154: TN | I154: MATERIA PRIMA | J154: OPEX | K154: VARIABLE | L154: DIRECTO | M154: 0 | N154: CC11 | O154: #NUM! | P154: 1 | Q154: EXPORTACION | R154: 1 | S154: -24537811 | T154: 20.44 | U154: APERTURADO POR EMPRESA
A155: 45961 | B155: PILETAS | C155: MT-0007 | D155: -12127190 | E155: AG- C | F155: 15.34 | G155: 540 | H155: TN | I155: MATERIA PRIMA | J155: OPEX | K155: VARIABLE | L155: DIRECTO | M155: 0 | N155: CC11 | O155: #NUM! | P155: 1 | Q155: EXPORTACION | R155: 1 | S155: -12127190 | T155: 15.34 | U155: APERTURADO POR EMPRESA
A156: 45961 | B156: REACTORES | C156: MT-0008 | D156: 0 | E156: ARE- A | F156: #NUM! | G156: 820 | H156: TN | I156: MATERIA PRIMA | J156: OPEX | K156: VARIABLE | L156: DIRECTO | M156: 0 | N156: CC11 | O156: #NUM! | P156: 1 | Q156: EXPORTACION | R156: 1 | S156: 0 | T156: #NUM! | U156: APERTURADO POR EMPRESA
A157: 45961 | B157: REACTORES | C157: MT-0009 | D157: 0 | E157: ARE- B | F157: #NUM! | G157: 820 | H157: TN | I157: MATERIA PRIMA | J157: OPEX | K157: VARIABLE | L157: DIRECTO | M157: 0 | N157: CC11 | O157: #NUM! | P157: 1 | Q157: EXPORTACION | R157: 1 | S157: 0 | T157: #NUM! | U157: APERTURADO POR EMPRESA
A158: 45961 | B158: REACTORES -PZ | C158: MT-0010 | D158: -246338496 | E158: ARE- A | F158: 205.2 | G158: 820 | H158: TN | I158: MATERIA PRIMA | J158: OPEX | K158: VARIABLE | L158: DIRECTO | M158: 0 | N158: NO | O158: #NUM! | P158: 1 | Q158: ANULADO | R158: 1 | S158: -246338496 | T158: 205.2 | U158: APERTURADO POR EMPRESA
A159: 45961 | B159: REACTORES - PZ | C159: MT-0011 | D159: 0 | E159: ARE- B | F159: #NUM! | G159: 820 | H159: TN | I159: MATERIA PRIMA | J159: OPEX | K159: VARIABLE | L159: DIRECTO | M159: 0 | N159: NO | O159: #NUM! | P159: 1 | Q159: ANULADO | R159: 1 | S159: 0 | T159: #NUM! | U159: APERTURADO POR EMPRESA
A160: 45961 | B160: WORMS 2 | C160: MT-0012 | D160: -154255824 | E160: AG- A | F160: 123.96 | G160: 850 | H160: TN | I160: MATERIA PRIMA | J160: OPEX | K160: VARIABLE | L160: DIRECTO | M160: 0 | N160: NO | O160: #NUM! | P160: 1 | Q160: ANULADO | R160: 1 | S160: -154255824 | T160: 123.96 | U160: APERTURADO POR EMPRESA
A161: 45961 | B161: WORMS 2 | C161: MT-0013 | D161: 0 | E161: AG- B | F161: #NUM! | G161: 820 | H161: TN | I161: MATERIA PRIMA | J161: OPEX | K161: VARIABLE | L161: DIRECTO | M161: 0 | N161: NO | O161: #NUM! | P161: 1 | Q161: ANULADO | R161: 1 | S161: 0 | T161: #NUM! | U161: APERTURADO POR EMPRESA
A162: 45961 | B162: WORMS 2 | C162: MT-0014 | D162: -8300880 | E162: AG- C | F162: 10.5 | G162: 540 | H162: TN | I162: MATERIA PRIMA | J162: OPEX | K162: VARIABLE | L162: DIRECTO | M162: 0 | N162: NO | O162: #NUM! | P162: 1 | Q162: ANULADO | R162: 1 | S162: -8300880 | T162: 10.5 | U162: APERTURADO POR EMPRESA
A163: 45961 | B163: PZ ( BORRA + PROVEEDOR) | C163: MT-0021 | D163: -91072512 | E163: AG- C | F163: 115.2 | G163: 540 | H163: TN | I163: MATERIA PRIMA | J163: OPEX | K163: VARIABLE | L163: DIRECTO | M163: 0 | N163: NO | O163: #NUM! | P163: 1 | Q163: ANULADO | R163: 1 | S163: -91072512 | T163: 115.2 | U163: APERTURADO POR EMPRESA
A164: 45961 | B164: PILETAS | C164: MT-0022 | D164: 0 | E164: AG- C | F164: #NUM! | G164: 540 | H164: TN | I164: MATERIA PRIMA | J164: OPEX | K164: VARIABLE | L164: DIRECTO | M164: 0 | N164: CC5 | O164: #NUM! | P164: 1 | Q164: REACTORES | R164: 1 | S164: 0 | T164: #NUM! | U164: APERTURADO POR EMPRESA
A165: 45961 | B165: PROVEEDOR | C165: MT-0023 | D165: -1.6548757e+08 | E165: AG - E | F165: 124.32 | G165: 909.25 | H165: TN | I165: MATERIA PRIMA | J165: OPEX | K165: VARIABLE | L165: DIRECTO | M165: 0 | N165: CC11 | O165: #NUM! | P165: 1 | Q165: EXPORTACION | R165: 1 | S165: -1.6548757e+08 | T165: 124.32 | U165: APERTURADO POR EMPRESA
A166: 45961 | B166: WORMS 2 | C166: MT-0024 | D166: 0 | E166: SEBO C - 2da | F166: #NUM! | G166: #NUM! | H166: TN | I166: MATERIA PRIMA | J166: OPEX | K166: VARIABLE | L166: DIRECTO | M166: 0 | N166: NO | O166: #NUM! | P166: 1 | Q166: ANULADO | R166: 1 | S166: 0 | T166: #NUM! | U166: APERTURADO POR EMPRESA
A167: 45961 | B167: WORMS 2 | C167: MT-0025 | D167: 0 | E167: BORRA A VEGETAL | F167: 126.22 | G167: #NUM! | H167: TN | I167: MATERIA PRIMA | J167: OPEX | K167: VARIABLE | L167: DIRECTO | M167: 0 | N167: NO | O167: #NUM! | P167: 1 | Q167: ANULADO | R167: 1 | S167: 0 | T167: 126.22 | U167: APERTURADO POR EMPRESA
A168: 45961 | B168: WORMS 2 | C168: MT-0026 | D168: 0 | E168: FONDO TK | F168: 22.2 | G168: #NUM! | H168: TN | I168: MATERIA PRIMA | J168: OPEX | K168: VARIABLE | L168: DIRECTO | M168: 0 | N168: NO | O168: #NUM! | P168: 1 | Q168: ANULADO | R168: 1 | S168: 0 | T168: 22.2 | U168: APERTURADO POR EMPRESA
A169: 45961 | B169: WORMS 2 | C169: MT-0027 | D169: 0 | E169: BORRA ANIMAL | F169: 34.1 | G169: #NUM! | H169: TN | I169: MATERIA PRIMA | J169: OPEX | K169: VARIABLE | L169: DIRECTO | M169: 0 | N169: NO | O169: #NUM! | P169: 1 | Q169: ANULADO | R169: 1 | S169: 0 | T169: 34.1 | U169: APERTURADO POR EMPRESA
A170: 45961 | B170: PROVEEDOR | C170: MT-0028 | D170: 0 | E170: BORRA PESCADO | F170: 86.28 | G170: #NUM! | H170: TN | I170: MATERIA PRIMA | J170: OPEX | K170: VARIABLE | L170: DIRECTO | M170: 0 | N170: NO | O170: #NUM! | P170: 1 | Q170: ANULADO | R170: 1 | S170: 0 | T170: 86.28 | U170: APERTURADO POR EMPRESA
A171: 45961 | B171: PILETAS | C171: MT-0029 | D171: -26088480 | E171: EMULSION | F171: 35.64 | G171: 500 | H171: TN | I171: MATERIA PRIMA | J171: OPEX | K171: VARIABLE | L171: DIRECTO | M171: 0 | N171: CC4 | O171: #NUM! | P171: 1 | Q171: PILETAS | R171: 1 | S171: -26088480 | T171: 35.64 | U171: APERTURADO POR EMPRESA
A172: 45961 | B172: PILETAS | C172: MT-0030 | D172: 0 | E172: AG-D | F172: 82.26 | G172: #NUM! | H172: TN | I172: MATERIA PRIMA | J172: 0 | K172: 0 | L172: 0 | M172: 0 | N172: 0 | O172: #NUM! | P172: 0 | Q172: 0 | R172: 1 | S172: 0 | T172: 82.26 | U172: APERTURADO POR EMPRESA
A173: 45961 | B173: Martins, Joaquin | C173: AD-0001 | D173: 0 | E173: ENERGIA GASOIL G3 | F173: #NUM! | G173: 1754 | H173: Lts | I173: ENERGIA | J173: OPEX | K173: VARIABLE | L173: DIRECTO | M173: 0 | N173: CC1 | O173: #NUM! | P173: CCO NO DEFINIDO | Q173: CCO NO DEFINIDO | R173: 1 | S173: 0 | T173: #NUM! | U173: APERTURADO POR EMPRESA
A174: 45961 | B174: Martins, Joaquin | C174: AD-0001 | D174: -2679040 | E174: ENERGIA G2 | F174: 1820 | G174: 1472 | H174: Lts | I174: ENERGIA | J174: OPEX | K174: VARIABLE | L174: DIRECTO | M174: 0 | N174: CC6 | O174: #NUM! | P174: 1 | Q174: BACHAS | R174: 1 | S174: -2679040 | T174: 1820 | U174: APERTURADO POR EMPRESA
A175: 45961 | B175: Martins, Joaquin | C175: AD-0001 | D175: 0 | E175: ENERGIA G2 | F175: 0 | G175: 1472 | H175: Lts | I175: ENERGIA | J175: OPEX | K175: VARIABLE | L175: DIRECTO | M175: 0 | N175: CC5 | O175: #NUM! | P175: 1 | Q175: REACTORES | R175: 1 | S175: 0 | T175: 0 | U175: APERTURADO POR EMPRESA
A176: 45961 | B176: Martins, Joaquin | C176: AD-0001 | D176: -149500 | E176: ENERGIA Nafta | F176: 100 | G176: 1495 | H176: Lts | I176: ENERGIA | J176: OPEX | K176: VARIABLE | L176: DIRECTO | M176: 0 | N176: CC6 | O176: #NUM! | P176: 1 | Q176: BACHAS | R176: 1 | S176: -149500 | T176: 100 | U176: APERTURADO POR EMPRESA
A177: 45961 | B177: Martins, Joaquin | C177: AD-0001 | D177: -1644500 | E177: ENERGIA Nafta | F177: 1100 | G177: 1495 | H177: Lts | I177: ENERGIA | J177: OPEX | K177: VARIABLE | L177: DIRECTO | M177: 0 | N177: CC4 | O177: #NUM! | P177: 1 | Q177: PILETAS | R177: 1 | S177: -1644500 | T177: 1100 | U177: APERTURADO POR EMPRESA
A178: 45961 | B178: Martins, Joaquin | C178: AD-0001 | D178: -448500 | E178: ENERGIA Nafta | F178: 300 | G178: 1495 | H178: Lts | I178: ENERGIA | J178: OPEX | K178: VARIABLE | L178: DIRECTO | M178: 0 | N178: CC3 | O178: #NUM! | P178: 1 | Q178: DISPOSICIÓN FINAL RESIDUOS LIQUIDOS | R178: 1 | S178: -448500 | T178: 300 | U178: APERTURADO POR EMPRESA
A179: 45961 | B179: Ultraonix Srl | C179: AD-0001 | D179: -14998192 | E179: ENERGIA Fuel Oil | F179: 24400 | G179: 614.68 | H179: KG | I179: ENERGIA | J179: OPEX | K179: VARIABLE | L179: DIRECTO | M179: 0 | N179: CC5 | O179: #NUM! | P179: 1 | Q179: REACTORES | R179: 1 | S179: -14998192 | T179: 24400 | U179: APERTURADO POR EMPRESA
A180: 45961 | B180: Ultraonix Srl | C180: AD-0001 | D180: -5224780 | E180: ENERGIA Fuel Oil | F180: 8500 | G180: 614.68 | H180: KG | I180: ENERGIA | J180: OPEX | K180: VARIABLE | L180: DIRECTO | M180: 0 | N180: CC6 | O180: #NUM! | P180: 1 | Q180: BACHAS | R180: 1 | S180: -5224780 | T180: 8500 | U180: APERTURADO POR EMPRESA
A181: 45961 | B181: Total Quimica S.A. | C181: AD-0001 | D181: -7342440.6 | E181: INSUMOS Acido Sulfúrico 70/80 | F181: 19860 | G181: 369.71 | H181: KG | I181: INSUMOS | J181: OPEX | K181: VARIABLE | L181: DIRECTO | M181: 0 | N181: CC6 | O181: #NUM! | P181: 1 | Q181: BACHAS | R181: 1 | S181: -7342440.6 | T181: 19860 | U181: APERTURADO POR EMPRESA
A182: 45961 | B182: Total Quimica S.A. | C182: AD-0001 | D182: -547520 | E182: INSUMOS Acido Clorhidrico | F182: 1180 | G182: 464 | H182: KG | I182: INSUMOS | J182: OPEX | K182: VARIABLE | L182: DIRECTO | M182: 0 | N182: CC6 | O182: #NUM! | P182: 1 | Q182: BACHAS | R182: 1 | S182: -547520 | T182: 1180 | U182: APERTURADO POR EMPRESA
A183: 45961 | B183: Total Quimica S.A. | C183: AD-0001 | D183: -691147.5 | E183: INSUMOS Soda Caustica | F183: 750 | G183: 921.53 | H183: KG | I183: INSUMOS | J183: OPEX | K183: VARIABLE | L183: DIRECTO | M183: 0 | N183: CC5 | O183: #NUM! | P183: 1 | Q183: REACTORES | R183: 1 | S183: -691147.5 | T183: 750 | U183: APERTURADO POR EMPRESA
A184: 45961 | B184: Salinera Jaisal S. A. | C184: AD-0001 | D184: -59774 | E184: INSUMOS Cloruro de Sodio (SAL) | F184: 520 | G184: 114.95 | H184: KG | I184: INSUMOS | J184: OPEX | K184: VARIABLE | L184: DIRECTO | M184: 0 | N184: CC6 | O184: #NUM! | P184: 1 | Q184: BACHAS | R184: 1 | S184: -59774 | T184: 520 | U184: APERTURADO POR EMPRESA
A185: 45961 | B185: Cremer Y Asociados Sociedad Anonima | C185: AD-0001 | D185: -11525588 | E185: INSUMOS Glicerina cruda | F185: 28.75 | G185: 400890 | H185: TN | I185: INSUMOS | J185: OPEX | K185: VARIABLE | L185: DIRECTO | M185: 0 | N185: CC5 | O185: #NUM! | P185: 1 | Q185: REACTORES | R185: 1 | S185: -11525588 | T185: 28.75 | U185: APERTURADO POR EMPRESA
A186: 45961 | B186: Meri-mar SRL | C186: AD-0001 | D186: 0 | E186: LOGISTICA | F186: 97.4 | G186: 19500 | H186: TN | I186: SERVICIOS | J186: OPEX | K186: VARIABLE | L186: DIRECTO | M186: 0 | N186: CC11 | O186: #NUM! | P186: 1 | Q186: EXPORTACION | R186: 1 | S186: 0 | T186: 97.4 | U186: APERTURADO POR EMPRESA
A187: 45961 | B187: Mercomar SA | C187: AD-0001 | D187: 0 | E187: LOGISTICA | F187: 852.25 | G187: 19500 | H187: TN | I187: SERVICIOS | J187: 0 | K187: 0 | L187: 0 | M187: 0 | N187: 0 | O187: #NUM! | P187: 0 | Q187: 0 | R187: 1 | S187: 0 | T187: 852.25 | U187: APERTURADO POR EMPRESA
A188: 45961 | B188: Transportes Padilla Sociedad Anonima | C188: AD-0001 | D188: 0 | E188: LOGISTICA | F188: 876.6 | G188: #NUM! | H188: TN | I188: SERVICIOS | J188: OPEX | K188: VARIABLE | L188: DIRECTO | M188: 0 | N188: CC11 | O188: #NUM! | P188: 1 | Q188: EXPORTACION | R188: 1 | S188: 0 | T188: 876.6 | U188: APERTURADO POR EMPRESA
A189: 45961 | B189: Cronos Soluciones Sustentables Sa | C189: AD-0001 | D189: -11261875 | E189: LOGISTICA | F189: 608.75 | G189: 18500 | H189: TN | I189: LOGISTICA | J189: OPEX | K189: VARIABLE | L189: DIRECTO | M189: 0 | N189: NO | O189: #NUM! | P189: 1 | Q189: ANULADO | R189: 1 | S189: -11261875 | T189: 608.75 | U189: APERTURADO POR EMPRESA
A190: 45961 | B190: Transporte Automotor El Loco Srl | C190: AD-0001 | D190: 0 | E190: LOGISTICA | F190: 97.4 | G190: #NUM! | H190: TN | I190: LOGISTICA | J190: OPEX | K190: VARIABLE | L190: DIRECTO | M190: 0 | N190: NO | O190: #NUM! | P190: 1 | Q190: ANULADO | R190: 1 | S190: 0 | T190: 97.4 | U190: APERTURADO POR EMPRESA
A191: 45961 | B191: Energia Del Sur Srl | C191: AD-0001 | D191: -1461000 | E191: LOGISTICA | F191: 97.4 | G191: 15000 | H191: TN | I191: LOGISTICA | J191: OPEX | K191: VARIABLE | L191: DIRECTO | M191: 0 | N191: NO | O191: #NUM! | P191: 1 | Q191: ANULADO | R191: 1 | S191: -1461000 | T191: 97.4 | U191: APERTURADO POR EMPRESA
A192: 45961 | B192: Duport Sociedad De Responsabilidad Limitada | C192: AD-0001 | D192: 0 | E192: LOGISTICA | F192: 194.8 | G192: #NUM! | H192: TN | I192: LOGISTICA | J192: OPEX | K192: VARIABLE | L192: DIRECTO | M192: 0 | N192: NO | O192: #NUM! | P192: 1 | Q192: ANULADO | R192: 1 | S192: 0 | T192: 194.8 | U192: APERTURADO POR EMPRESA
A193: 45931 | B193: GANANCIAS EXPORTACION | C193: AD_10-2025 | D193: -2067241.2 | E193: IMPUESTOS | F193: 2824.1 | G193: 0.5 | H193: UN | I193: IMPUESTOS | J193: OPEX | K193: VARIABLE | L193: DIRECTO | M193: 0 | N193: CC11 | O193: #NUM! | P193: 1 | Q193: EXPORTACION | R193: 1 | S193: -2067241.2 | T193: 2824.1 | U193: APERTURADO POR EMPRESA
A194: 45960 | B194: GASTOS BANCARIOS | C194: OCOM/2025/10 | D194: -6924925.3 | E194: IMPUESTOS | F194: 1 | G194: 6924925.3 | H194: UN | I194: IMPUESTOS | J194: OPEX | K194: VARIABLE | L194: INDIRECTO | M194: 0 | N194: CC1 | O194: #NUM! | P194: CCO NO DEFINIDO | Q194: CCO NO DEFINIDO | R194: 1 | S194: -6924925.3 | T194: 1 | U194: APERTURADO POR EMPRESA
A195: 45960 | B195: IB | C195: OCOM/2025/10 | D195: -32811.49 | E195: IMPUESTOS | F195: 1 | G195: 32811.49 | H195: UN | I195: IMPUESTOS | J195: OPEX | K195: VARIABLE | L195: INDIRECTO | M195: 0 | N195: CC1 | O195: #NUM! | P195: 10 | Q195: BACHAS, CEREAL & POLVILLO, COMPOST & FERTILIZANTES, DISPOSICIÓN FINAL RESIDUOS LIQUIDOS, DISPOSICIÓN FINAL RESIDUOS SOLIDOS, EXPORTACION, NFU, PILETAS, REACTORES, TIERRAS FILTRANTES | R195: 1 | S195: -32811.49 | T195: 1 | U195: APERTURADO POR EMPRESA
A196: 45960 | B196: DREI DISPOSICIÓN FINAL RESIDUOS LIQUIDOS | C196: OCOM/2025/10 | D196: -656141 | E196: IMPUESTOS | F196: 1 | G196: 656141 | H196: UN | I196: IMPUESTOS | J196: OPEX | K196: VARIABLE | L196: INDIRECTO | M196: 0 | N196: CC3 | O196: #NUM! | P196: 1 | Q196: DISPOSICIÓN FINAL RESIDUOS LIQUIDOS | R196: 1 | S196: -656141 | T196: 1 | U196: APERTURADO POR EMPRESA
A197: 45960 | B197: DREI COMPOST & FERTILIZANTES | C197: OCOM/2025/10 | D197: -485805 | E197: IMPUESTOS | F197: 1 | G197: 485805 | H197: UN | I197: IMPUESTOS | J197: OPEX | K197: VARIABLE | L197: INDIRECTO | M197: 0 | N197: CC8 | O197: #NUM! | P197: 1 | Q197: COMPOST & FERTILIZANTES | R197: 1 | S197: -485805 | T197: 1 | U197: APERTURADO POR EMPRESA
A198: 45960 | B198: DREI PILETAS | C198: OCOM/2025/10 | D198: -374523 | E198: IMPUESTOS | F198: 1 | G198: 374523 | H198: UN | I198: IMPUESTOS | J198: OPEX | K198: VARIABLE | L198: INDIRECTO | M198: 0 | N198: CC4 | O198: #NUM! | P198: 1 | Q198: PILETAS | R198: 1 | S198: -374523 | T198: 1 | U198: APERTURADO POR EMPRESA
A199: 45960 | B199: DREI NFU | C199: OCOM/2025/10 | D199: -386033 | E199: IMPUESTOS | F199: 1 | G199: 386033 | H199: UN | I199: IMPUESTOS | J199: OPEX | K199: VARIABLE | L199: INDIRECTO | M199: 0 | N199: CC7 | O199: #NUM! | P199: 2 | Q199: NFU | R199: 1 | S199: -386033 | T199: 1 | U199: APERTURADO POR EMPRESA
A200: 45931 | B200: WORMS-RRHH | C200: MAIDANA, JOSE RAMON | D200: -2078949.5 | E200: INTENDENCIA | F200: 1 | G200: 2078949.5 | H200: #RRHH | I200: PERSONAL | J200: Opex | K200: Fijo | L200: Indirecto | M200: 0 | N200: CC27 | O200: #NUM! | P200: 10 | Q200: BACHAS, CEREAL Y POLVILLO, COMPOST Y FERTILIZANTES, DISPOSICION FINAL DE R. LIQUIDOS, DISPOSICION FINAL DE R. SOLIDOS, EXPORTACION, NFU, PILETAS, REACTORES, TIERRAS FILTRANTES | R200: 1 | S200: -2078949.5 | T200: 1 | U200: APERTURADO POR EMPRESA
A201: 45931 | B201: WORMS-RRHH | C201: PEREZ, MATIAS ROMAN | D201: -5104642.3 | E201: INTENDENCIA | F201: 1 | G201: 5104642.3 | H201: #RRHH | I201: PERSONAL | J201: Opex | K201: Fijo | L201: Indirecto | M201: 0 | N201: CC27 | O201: #NUM! | P201: 10 | Q201: BACHAS, CEREAL Y POLVILLO, COMPOST Y FERTILIZANTES, DISPOSICION FINAL DE R. LIQUIDOS, DISPOSICION FINAL DE R. SOLIDOS, EXPORTACION, NFU, PILETAS, REACTORES, TIERRAS FILTRANTES | R201: 1 | S201: -5104642.3 | T201: 1 | U201: APERTURADO POR EMPRESA
A202: 45931 | B202: WORMS-RRHH | C202: PANZANELLA, EDUARDO JAVIER | D202: -2117008.3 | E202: PORTERIA | F202: 1 | G202: 2117008.3 | H202: #RRHH | I202: PERSONAL | J202: Opex | K202: Fijo | L202: Indirecto | M202: 0 | N202: CC22 | O202: #NUM! | P202: 7 | Q202: BACHAS, COMPOST Y FERTILIZANTES, DISPOSICION FINAL DE R. LIQUIDOS, DISPOSICION FINAL DE R. SOLIDOS, EXPORTACION, NFU, REACTORES | R202: 1 | S202: -2117008.3 | T202: 1 | U202: APERTURADO POR EMPRESA
A203: 45931 | B203: WORMS-RRHH | C203: ENRIQUEZ, MAXIMO GUSTAVO | D203: -2067002 | E203: DISPOSICION FINAL DE R. LIQUIDOS | F203: 1 | G203: 2067002 | H203: #RRHH | I203: PERSONAL | J203: Opex | K203: Variable | L203: Directo | M203: 0 | N203: CC25 | O203: #NUM! | P203: 2 | Q203: DISPOSICION FINAL DE R. LIQUIDOS, EXPORTACION | R203: 1 | S203: -2067002 | T203: 1 | U203: APERTURADO POR EMPRESA
A204: 45931 | B204: WORMS-RRHH | C204: PORCU, MIGUEL ANGEL | D204: -1085682.2 | E204: PILETAS | F204: 1 | G204: 1085682.2 | H204: #RRHH | I204: PERSONAL | J204: Opex | K204: Variable | L204: Directo | M204: 0 | N204: CC21 | O204: #NUM! | P204: 2 | Q204: BACHAS, PILETAS | R204: 1 | S204: -1085682.2 | T204: 1 | U204: APERTURADO POR EMPRESA
A205: 45931 | B205: WORMS-RRHH | C205: PETERS CORZO, JOSE LUIS | D205: -2513045.7 | E205: LABORATORIO | F205: 1 | G205: 2513045.7 | H205: #RRHH | I205: PERSONAL | J205: Opex | K205: Fijo | L205: Indirecto | M205: 0 | N205: CC17 | O205: #NUM! | P205: 6 | Q205: BACHAS, DISPOSICION FINAL DE R. LIQUIDOS, EXPORTACION, NFU, PILETAS, REACTORES | R205: 1 | S205: -2513045.7 | T205: 1 | U205: APERTURADO POR EMPRESA
A206: 45931 | B206: WORMS-RRHH | C206: ALTAMIRANO, GUSTAVO | D206: -2156572.8 | E206: NFU | F206: 1 | G206: 2156572.8 | H206: #RRHH | I206: PERSONAL | J206: Opex | K206: Variable | L206: Directo | M206: 0 | N206: CC20 | O206: #NUM! | P206: 2 | Q206: DISPOSICION FINAL DE R. SOLIDOS, NFU | R206: 1 | S206: -2156572.8 | T206: 1 | U206: APERTURADO POR EMPRESA
... A302: 45931 | B302: WORMS-RRHH | C302: ADROVER, JUAN HORACIO | D302: -1876296.3 | E302: TALLER MECANICO | F302: 15 | G302: 1876296.3 | H302: #RRHH | I302: PERSONAL | J302: Opex | K302: Fijo | L302: Indirecto | M302: 0 | N302: CC23 | O302: #NUM! | P302: 10 | Q302: BACHAS, CEREAL Y POLVILLO, COMPOST Y FERTILIZANTES, DISPOSICION FINAL DE R. LIQUIDOS, DISPOSICION FINAL DE R. SOLIDOS, EXPORTACION, NFU, PILETAS, REACTORES, TIERRAS FILTRANTES | R302: 1 | S302: -1876296.3 | T302: 15 | U302: APERTURADO POR EMPRESA

Sheet cco_bbdd_asignado.p4 
A1: {=_xlfn._xlws.PY(1,0,bbdd2[#All])} -> 0 | B1: 1 | C1: 2 | D1: 3 | E1: 4 | F1: 5 | G1: 6 | H1: 7 | I1: 8 | J1: 9 | K1: 10 | L1: 11 | M1: 12 | N1: 13 | O1: 14 | P1: 15 | Q1: 16 | R1: 17 | S1: 18 | T1: 19 | U1: 20 | V1: SECTOR APERTURADO
A2: Fecha de Factura/Recibo | B2: Nombre de la empresa a mostrar en la factura | C2: Número | D2: Total con signo | E2: Líneas de factura/Etiqueta | F2: Líneas de factura/Cantidad | G2: Líneas de factura/Precio unitario | H2: Líneas de factura/Unidad de medida | I2: Líneas de factura/Producto | J2: Concepto | K2: Tipo de Gasto 1 | L2: Tipo de Gasto 2 | M2: CCO EMPRESA | N2: CCO - SECTOR | O2: SECTOR_ODOO | P2: # SECTORES | Q2: LISTA_SECTORES | R2: Column1 | S2: Column2 | T2: Column3 | U2: Column4 | V2: LISTA_SECTORES
A3: 45958 | B3: H.S.E. Ingenieria S R L | C3: FA-A 00003-00027849 | D3: -3315400 | E3: OC 0001-00001756: SERVICIOS Monitoreo | F3: 1 | G3: 2740000 | H3: UN | I3: SERVICIOS | J3: OPEX | K3: VARIABLE | L3: INDIRECTO | M3: 0 | N3: CC1 | O3: #NUM! | P3: 10 | Q3: BACHAS, CEREAL & POLVILLO, COMPOST & FERTILIZANTES, DISPOSICIÓN FINAL RESIDUOS LIQUIDOS, DISPOSICIÓN FINAL RESIDUOS SOLIDOS, EXPORTACION, NFU, PILETAS, REACTORES, TIERRAS FILTRANTES | R3: 1 | S3: -3315400 | T3: 1 | U3: APERTURADO POR EMPRESA | V3: BACHAS
A4: 45958 | B4: H.S.E. Ingenieria S R L | C4: FA-A 00003-00027849 | D4: -3315400 | E4: OC 0001-00001756: SERVICIOS Monitoreo | F4: 1 | G4: 2740000 | H4: UN | I4: SERVICIOS | J4: OPEX | K4: VARIABLE | L4: INDIRECTO | M4: 0 | N4: CC1 | O4: #NUM! | P4: 10 | Q4: BACHAS, CEREAL & POLVILLO, COMPOST & FERTILIZANTES, DISPOSICIÓN FINAL RESIDUOS LIQUIDOS, DISPOSICIÓN FINAL RESIDUOS SOLIDOS, EXPORTACION, NFU, PILETAS, REACTORES, TIERRAS FILTRANTES | R4: 1 | S4: -3315400 | T4: 1 | U4: APERTURADO POR EMPRESA | V4: CEREAL & POLVILLO
A5: 45958 | B5: H.S.E. Ingenieria S R L | C5: FA-A 00003-00027849 | D5: -3315400 | E5: OC 0001-00001756: SERVICIOS Monitoreo | F5: 1 | G5: 2740000 | H5: UN | I5: SERVICIOS | J5: OPEX | K5: VARIABLE | L5: INDIRECTO | M5: 0 | N5: CC1 | O5: #NUM! | P5: 10 | Q5: BACHAS, CEREAL & POLVILLO, COMPOST & FERTILIZANTES, DISPOSICIÓN FINAL RESIDUOS LIQUIDOS, DISPOSICIÓN FINAL RESIDUOS SOLIDOS, EXPORTACION, NFU, PILETAS, REACTORES, TIERRAS FILTRANTES | R5: 1 | S5: -3315400 | T5: 1 | U5: APERTURADO POR EMPRESA | V5: COMPOST & FERTILIZANTES
A6: 45958 | B6: H.S.E. Ingenieria S R L | C6: FA-A 00003-00027849 | D6: -3315400 | E6: OC 0001-00001756: SERVICIOS Monitoreo | F6: 1 | G6: 2740000 | H6: UN | I6: SERVICIOS | J6: OPEX | K6: VARIABLE | L6: INDIRECTO | M6: 0 | N6: CC1 | O6: #NUM! | P6: 10 | Q6: BACHAS, CEREAL & POLVILLO, COMPOST & FERTILIZANTES, DISPOSICIÓN FINAL RESIDUOS LIQUIDOS, DISPOSICIÓN FINAL RESIDUOS SOLIDOS, EXPORTACION, NFU, PILETAS, REACTORES, TIERRAS FILTRANTES | R6: 1 | S6: -3315400 | T6: 1 | U6: APERTURADO POR EMPRESA | V6: DISPOSICIÓN FINAL RESIDUOS LIQUIDOS
A7: 45958 | B7: H.S.E. Ingenieria S R L | C7: FA-A 00003-00027849 | D7: -3315400 | E7: OC 0001-00001756: SERVICIOS Monitoreo | F7: 1 | G7: 2740000 | H7: UN | I7: SERVICIOS | J7: OPEX | K7: VARIABLE | L7: INDIRECTO | M7: 0 | N7: CC1 | O7: #NUM! | P7: 10 | Q7: BACHAS, CEREAL & POLVILLO, COMPOST & FERTILIZANTES, DISPOSICIÓN FINAL RESIDUOS LIQUIDOS, DISPOSICIÓN FINAL RESIDUOS SOLIDOS, EXPORTACION, NFU, PILETAS, REACTORES, TIERRAS FILTRANTES | R7: 1 | S7: -3315400 | T7: 1 | U7: APERTURADO POR EMPRESA | V7: DISPOSICIÓN FINAL RESIDUOS SOLIDOS
A8: 45958 | B8: H.S.E. Ingenieria S R L | C8: FA-A 00003-00027849 | D8: -3315400 | E8: OC 0001-00001756: SERVICIOS Monitoreo | F8: 1 | G8: 2740000 | H8: UN | I8: SERVICIOS | J8: OPEX | K8: VARIABLE | L8: INDIRECTO | M8: 0 | N8: CC1 | O8: #NUM! | P8: 10 | Q8: BACHAS, CEREAL & POLVILLO, COMPOST & FERTILIZANTES, DISPOSICIÓN FINAL RESIDUOS LIQUIDOS, DISPOSICIÓN FINAL RESIDUOS SOLIDOS, EXPORTACION, NFU, PILETAS, REACTORES, TIERRAS FILTRANTES | R8: 1 | S8: -3315400 | T8: 1 | U8: APERTURADO POR EMPRESA | V8: EXPORTACION
A9: 45958 | B9: H.S.E. Ingenieria S R L | C9: FA-A 00003-00027849 | D9: -3315400 | E9: OC 0001-00001756: SERVICIOS Monitoreo | F9: 1 | G9: 2740000 | H9: UN | I9: SERVICIOS | J9: OPEX | K9: VARIABLE | L9: INDIRECTO | M9: 0 | N9: CC1 | O9: #NUM! | P9: 10 | Q9: BACHAS, CEREAL & POLVILLO, COMPOST & FERTILIZANTES, DISPOSICIÓN FINAL RESIDUOS LIQUIDOS, DISPOSICIÓN FINAL RESIDUOS SOLIDOS, EXPORTACION, NFU, PILETAS, REACTORES, TIERRAS FILTRANTES | R9: 1 | S9: -3315400 | T9: 1 | U9: APERTURADO POR EMPRESA | V9: NFU
A10: 45958 | B10: H.S.E. Ingenieria S R L | C10: FA-A 00003-00027849 | D10: -3315400 | E10: OC 0001-00001756: SERVICIOS Monitoreo | F10: 1 | G10: 2740000 | H10: UN | I10: SERVICIOS | J10: OPEX | K10: VARIABLE | L10: INDIRECTO | M10: 0 | N10: CC1 | O10: #NUM! | P10: 10 | Q10: BACHAS, CEREAL & POLVILLO, COMPOST & FERTILIZANTES, DISPOSICIÓN FINAL RESIDUOS LIQUIDOS, DISPOSICIÓN FINAL RESIDUOS SOLIDOS, EXPORTACION, NFU, PILETAS, REACTORES, TIERRAS FILTRANTES | R10: 1 | S10: -3315400 | T10: 1 | U10: APERTURADO POR EMPRESA | V10: PILETAS
A11: 45958 | B11: H.S.E. Ingenieria S R L | C11: FA-A 00003-00027849 | D11: -3315400 | E11: OC 0001-00001756: SERVICIOS Monitoreo | F11: 1 | G11: 2740000 | H11: UN | I11: SERVICIOS | J11: OPEX | K11: VARIABLE | L11: INDIRECTO | M11: 0 | N11: CC1 | O11: #NUM! | P11: 10 | Q11: BACHAS, CEREAL & POLVILLO, COMPOST & FERTILIZANTES, DISPOSICIÓN FINAL RESIDUOS LIQUIDOS, DISPOSICIÓN FINAL RESIDUOS SOLIDOS, EXPORTACION, NFU, PILETAS, REACTORES, TIERRAS FILTRANTES | R11: 1 | S11: -3315400 | T11: 1 | U11: APERTURADO POR EMPRESA | V11: REACTORES
A12: 45958 | B12: H.S.E. Ingenieria S R L | C12: FA-A 00003-00027849 | D12: -3315400 | E12: OC 0001-00001756: SERVICIOS Monitoreo | F12: 1 | G12: 2740000 | H12: UN | I12: SERVICIOS | J12: OPEX | K12: VARIABLE | L12: INDIRECTO | M12: 0 | N12: CC1 | O12: #NUM! | P12: 10 | Q12: BACHAS, CEREAL & POLVILLO, COMPOST & FERTILIZANTES, DISPOSICIÓN FINAL RESIDUOS LIQUIDOS, DISPOSICIÓN FINAL RESIDUOS SOLIDOS, EXPORTACION, NFU, PILETAS, REACTORES, TIERRAS FILTRANTES | R12: 1 | S12: -3315400 | T12: 1 | U12: APERTURADO POR EMPRESA | V12: TIERRAS FILTRANTES
A13: 45933 | B13: Alvarez, Alejandro Dario | C13: FA-C 00002-00000250 | D13: -509644 | E13: OC 0001-00001364: HIGIENE Y SEGURIDAD Servicio de asesoramiento para la gestión ambiental en el cumplimiento de la normativa vigente para la provincia de Santa Fe. Servicio de higiene y seguridad de trabajo con cumplimiento de actividades s/Resol. SRT 905/15- MES 09/2025 | F13: 1 | G13: 509644 | H13: UN | I13: HIGIENE Y SEGURIDAD | J13: OPEX | K13: FIJO | L13: DIRECTO | M13: 0 | N13: CC1 | O13: #NUM! | P13: 10 | Q13: BACHAS, CEREAL & POLVILLO, COMPOST & FERTILIZANTES, DISPOSICIÓN FINAL RESIDUOS LIQUIDOS, DISPOSICIÓN FINAL RESIDUOS SOLIDOS, EXPORTACION, NFU, PILETAS, REACTORES, TIERRAS FILTRANTES | R13: 1 | S13: -509644 | T13: 1 | U13: APERTURADO POR EMPRESA | V13: BACHAS
A14: 45933 | B14: Alvarez, Alejandro Dario | C14: FA-C 00002-00000250 | D14: -509644 | E14: OC 0001-00001364: HIGIENE Y SEGURIDAD Servicio de asesoramiento para la gestión ambiental en el cumplimiento de la normativa vigente para la provincia de Santa Fe. Servicio de higiene y seguridad de trabajo con cumplimiento de actividades s/Resol. SRT 905/15- MES 09/2025 | F14: 1 | G14: 509644 | H14: UN | I14: HIGIENE Y SEGURIDAD | J14: OPEX | K14: FIJO | L14: DIRECTO | M14: 0 | N14: CC1 | O14: #NUM! | P14: 10 | Q14: BACHAS, CEREAL & POLVILLO, COMPOST & FERTILIZANTES, DISPOSICIÓN FINAL RESIDUOS LIQUIDOS, DISPOSICIÓN FINAL RESIDUOS SOLIDOS, EXPORTACION, NFU, PILETAS, REACTORES, TIERRAS FILTRANTES | R14: 1 | S14: -509644 | T14: 1 | U14: APERTURADO POR EMPRESA | V14: CEREAL & POLVILLO
... A141: 45932 | B141: Acosta, Roberto Maximiliano | C141: FA-C 00001-00000616 | D141: -4632990 | E141: OC 0001-00001709: SERVICIOS de limpieza +ipc julio y agosto 3,8% | F141: 1 | G141: 4632990 | H141: UN | I141: SERVICIOS | J141: OPEX | K141: VARIABLE | L141: INDIRECTO | M141: 0 | N141: CC1 | O141: #NUM! | P141: 10 | Q141: BACHAS, CEREAL & POLVILLO, COMPOST & FERTILIZANTES, DISPOSICIÓN FINAL RESIDUOS LIQUIDOS, DISPOSICIÓN FINAL RESIDUOS SOLIDOS, EXPORTACION, NFU, PILETAS, REACTORES, TIERRAS FILTRANTES | R141: 1 | S141: -4632990 | T141: 1 | U141: APERTURADO POR EMPRESA | V141: TIERRAS FILTRANTES
A142: 45931 | B142: Adhoc S.A. | C142: FA-A 00003-00019779 | D142: -2004596.6 | E142: OC 0001-00001367: SERVICIOS Sistema contable | F142: 1 | G142: 1656691.4 | H142: UN | I142: SERVICIOS | J142: OPEX | K142: FIJO | L142: INDIRECTO | M142: CC13 | N142: CC1 | O142: #NUM! | P142: 10 | Q142: BACHAS, CEREAL & POLVILLO, COMPOST & FERTILIZANTES, DISPOSICIÓN FINAL RESIDUOS LIQUIDOS, DISPOSICIÓN FINAL RESIDUOS SOLIDOS, EXPORTACION, NFU, PILETAS, REACTORES, TIERRAS FILTRANTES | R142: 0.7 | S142: -1403217.6 | T142: 0.7 | U142: APERTURADO POR EMPRESA | V142: BACHAS
A143: 45931 | B143: Adhoc S.A. | C143: FA-A 00003-00019779 | D143: -2004596.6 | E143: OC 0001-00001367: SERVICIOS Sistema contable | F143: 1 | G143: 1656691.4 | H143: UN | I143: SERVICIOS | J143: OPEX | K143: FIJO | L143: INDIRECTO | M143: CC13 | N143: CC1 | O143: #NUM! | P143: 10 | Q143: BACHAS, CEREAL & POLVILLO, COMPOST & FERTILIZANTES, DISPOSICIÓN FINAL RESIDUOS LIQUIDOS, DISPOSICIÓN FINAL RESIDUOS SOLIDOS, EXPORTACION, NFU, PILETAS, REACTORES, TIERRAS FILTRANTES | R143: 0.7 | S143: -1403217.6 | T143: 0.7 | U143: APERTURADO POR EMPRESA | V143: CEREAL & POLVILLO
A144: 45931 | B144: Adhoc S.A. | C144: FA-A 00003-00019779 | D144: -2004596.6 | E144: OC 0001-00001367: SERVICIOS Sistema contable | F144: 1 | G144: 1656691.4 | H144: UN | I144: SERVICIOS | J144: OPEX | K144: FIJO | L144: INDIRECTO | M144: CC13 | N144: CC1 | O144: #NUM! | P144: 10 | Q144: BACHAS, CEREAL & POLVILLO, COMPOST & FERTILIZANTES, DISPOSICIÓN FINAL RESIDUOS LIQUIDOS, DISPOSICIÓN FINAL RESIDUOS SOLIDOS, EXPORTACION, NFU, PILETAS, REACTORES, TIERRAS FILTRANTES | R144: 0.7 | S144: -1403217.6 | T144: 0.7 | U144: APERTURADO POR EMPRESA | V144: COMPOST & FERTILIZANTES
A145: 45931 | B145: Adhoc S.A. | C145: FA-A 00003-00019779 | D145: -2004596.6 | E145: OC 0001-00001367: SERVICIOS Sistema contable | F145: 1 | G145: 1656691.4 | H145: UN | I145: SERVICIOS | J145: OPEX | K145: FIJO | L145: INDIRECTO | M145: CC13 | N145: CC1 | O145: #NUM! | P145: 10 | Q145: BACHAS, CEREAL & POLVILLO, COMPOST & FERTILIZANTES, DISPOSICIÓN FINAL RESIDUOS LIQUIDOS, DISPOSICIÓN FINAL RESIDUOS SOLIDOS, EXPORTACION, NFU, PILETAS, REACTORES, TIERRAS FILTRANTES | R145: 0.7 | S145: -1403217.6 | T145: 0.7 | U145: APERTURADO POR EMPRESA | V145: DISPOSICIÓN FINAL RESIDUOS LIQUIDOS
A146: 45931 | B146: Adhoc S.A. | C146: FA-A 00003-00019779 | D146: -2004596.6 | E146: OC 0001-00001367: SERVICIOS Sistema contable | F146: 1 | G146: 1656691.4 | H146: UN | I146: SERVICIOS | J146: OPEX | K146: FIJO | L146: INDIRECTO | M146: CC13 | N146: CC1 | O146: #NUM! | P146: 10 | Q146: BACHAS, CEREAL & POLVILLO, COMPOST & FERTILIZANTES, DISPOSICIÓN FINAL RESIDUOS LIQUIDOS, DISPOSICIÓN FINAL RESIDUOS SOLIDOS, EXPORTACION, NFU, PILETAS, REACTORES, TIERRAS FILTRANTES | R146: 0.7 | S146: -1403217.6 | T146: 0.7 | U146: APERTURADO POR EMPRESA | V146: DISPOSICIÓN FINAL RESIDUOS SOLIDOS
A147: 45931 | B147: Adhoc S.A. | C147: FA-A 00003-00019779 | D147: -2004596.6 | E147: OC 0001-00001367: SERVICIOS Sistema contable | F147: 1 | G147: 1656691.4 | H147: UN | I147: SERVICIOS | J147: OPEX | K147: FIJO | L147: INDIRECTO | M147: CC13 | N147: CC1 | O147: #NUM! | P147: 10 | Q147: BACHAS, CEREAL & POLVILLO, COMPOST & FERTILIZANTES, DISPOSICIÓN FINAL RESIDUOS LIQUIDOS, DISPOSICIÓN FINAL RESIDUOS SOLIDOS, EXPORTACION, NFU, PILETAS, REACTORES, TIERRAS FILTRANTES | R147: 0.7 | S147: -1403217.6 | T147: 0.7 | U147: APERTURADO POR EMPRESA | V147: EXPORTACION
A148: 45931 | B148: Adhoc S.A. | C148: FA-A 00003-00019779 | D148: -2004596.6 | E148: OC 0001-00001367: SERVICIOS Sistema contable | F148: 1 | G148: 1656691.4 | H148: UN | I148: SERVICIOS | J148: OPEX | K148: FIJO | L148: INDIRECTO | M148: CC13 | N148: CC1 | O148: #NUM! | P148: 10 | Q148: BACHAS, CEREAL & POLVILLO, COMPOST & FERTILIZANTES, DISPOSICIÓN FINAL RESIDUOS LIQUIDOS, DISPOSICIÓN FINAL RESIDUOS SOLIDOS, EXPORTACION, NFU, PILETAS, REACTORES, TIERRAS FILTRANTES | R148: 0.7 | S148: -1403217.6 | T148: 0.7 | U148: APERTURADO POR EMPRESA | V148: NFU
A149: 45931 | B149: Adhoc S.A. | C149: FA-A 00003-00019779 | D149: -2004596.6 | E149: OC 0001-00001367: SERVICIOS Sistema contable | F149: 1 | G149: 1656691.4 | H149: UN | I149: SERVICIOS | J149: OPEX | K149: FIJO | L149: INDIRECTO | M149: CC13 | N149: CC1 | O149: #NUM! | P149: 10 | Q149: BACHAS, CEREAL & POLVILLO, COMPOST & FERTILIZANTES, DISPOSICIÓN FINAL RESIDUOS LIQUIDOS, DISPOSICIÓN FINAL RESIDUOS SOLIDOS, EXPORTACION, NFU, PILETAS, REACTORES, TIERRAS FILTRANTES | R149: 0.7 | S149: -1403217.6 | T149: 0.7 | U149: APERTURADO POR EMPRESA | V149: PILETAS
A150: 45931 | B150: Adhoc S.A. | C150: FA-A 00003-00019779 | D150: -2004596.6 | E150: OC 0001-00001367: SERVICIOS Sistema contable | F150: 1 | G150: 1656691.4 | H150: UN | I150: SERVICIOS | J150: OPEX | K150: FIJO | L150: INDIRECTO | M150: CC13 | N150: CC1 | O150: #NUM! | P150: 10 | Q150: BACHAS, CEREAL & POLVILLO, COMPOST & FERTILIZANTES, DISPOSICIÓN FINAL RESIDUOS LIQUIDOS, DISPOSICIÓN FINAL RESIDUOS SOLIDOS, EXPORTACION, NFU, PILETAS, REACTORES, TIERRAS FILTRANTES | R150: 0.7 | S150: -1403217.6 | T150: 0.7 | U150: APERTURADO POR EMPRESA | V150: REACTORES
A151: 45931 | B151: Adhoc S.A. | C151: FA-A 00003-00019779 | D151: -2004596.6 | E151: OC 0001-00001367: SERVICIOS Sistema contable | F151: 1 | G151: 1656691.4 | H151: UN | I151: SERVICIOS | J151: OPEX | K151: FIJO | L151: INDIRECTO | M151: CC13 | N151: CC1 | O151: #NUM! | P151: 10 | Q151: BACHAS, CEREAL & POLVILLO, COMPOST & FERTILIZANTES, DISPOSICIÓN FINAL RESIDUOS LIQUIDOS, DISPOSICIÓN FINAL RESIDUOS SOLIDOS, EXPORTACION, NFU, PILETAS, REACTORES, TIERRAS FILTRANTES | R151: 0.7 | S151: -1403217.6 | T151: 0.7 | U151: APERTURADO POR EMPRESA | V151: TIERRAS FILTRANTES
A152: 45950 | B152: American Express Argentina S. A. | C152: OCOM/2025/0472 | D152: -344000.85 | E152: OC 0001-00001936: PERSONAL | F152: 1 | G152: 344000.85 | H152: UN | I152: PERSONAL | J152: OPEX | K152: VARIABLE | L152: INDIRECTO | M152: 0 | N152: CC1 | O152: #NUM! | P152: 10 | Q152: BACHAS, CEREAL & POLVILLO, COMPOST & FERTILIZANTES, DISPOSICIÓN FINAL RESIDUOS LIQUIDOS, DISPOSICIÓN FINAL RESIDUOS SOLIDOS, EXPORTACION, NFU, PILETAS, REACTORES, TIERRAS FILTRANTES | R152: 1 | S152: -344000.85 | T152: 1 | U152: APERTURADO POR EMPRESA | V152: BACHAS
A153: 45950 | B153: American Express Argentina S. A. | C153: OCOM/2025/0472 | D153: -344000.85 | E153: OC 0001-00001936: PERSONAL | F153: 1 | G153: 344000.85 | H153: UN | I153: PERSONAL | J153: OPEX | K153: VARIABLE | L153: INDIRECTO | M153: 0 | N153: CC1 | O153: #NUM! | P153: 10 | Q153: BACHAS, CEREAL & POLVILLO, COMPOST & FERTILIZANTES, DISPOSICIÓN FINAL RESIDUOS LIQUIDOS, DISPOSICIÓN FINAL RESIDUOS SOLIDOS, EXPORTACION, NFU, PILETAS, REACTORES, TIERRAS FILTRANTES | R153: 1 | S153: -344000.85 | T153: 1 | U153: APERTURADO POR EMPRESA | V153: CEREAL & POLVILLO
A154: 45950 | B154: American Express Argentina S. A. | C154: OCOM/2025/0472 | D154: -344000.85 | E154: OC 0001-00001936: PERSONAL | F154: 1 | G154: 344000.85 | H154: UN | I154: PERSONAL | J154: OPEX | K154: VARIABLE | L154: INDIRECTO | M154: 0 | N154: CC1 | O154: #NUM! | P154: 10 | Q154: BACHAS, CEREAL & POLVILLO, COMPOST & FERTILIZANTES, DISPOSICIÓN FINAL RESIDUOS LIQUIDOS, DISPOSICIÓN FINAL RESIDUOS SOLIDOS, EXPORTACION, NFU, PILETAS, REACTORES, TIERRAS FILTRANTES | R154: 1 | S154: -344000.85 | T154: 1 | U154: APERTURADO POR EMPRESA | V154: COMPOST & FERTILIZANTES
A155: 45950 | B155: American Express Argentina S. A. | C155: OCOM/2025/0472 | D155: -344000.85 | E155: OC 0001-00001936: PERSONAL | F155: 1 | G155: 344000.85 | H155: UN | I155: PERSONAL | J155: OPEX | K155: VARIABLE | L155: INDIRECTO | M155: 0 | N155: CC1 | O155: #NUM! | P155: 10 | Q155: BACHAS, CEREAL & POLVILLO, COMPOST & FERTILIZANTES, DISPOSICIÓN FINAL RESIDUOS LIQUIDOS, DISPOSICIÓN FINAL RESIDUOS SOLIDOS, EXPORTACION, NFU, PILETAS, REACTORES, TIERRAS FILTRANTES | R155: 1 | S155: -344000.85 | T155: 1 | U155: APERTURADO POR EMPRESA | V155: DISPOSICIÓN FINAL RESIDUOS LIQUIDOS
A156: 45950 | B156: American Express Argentina S. A. | C156: OCOM/2025/0472 | D156: -344000.85 | E156: OC 0001-00001936: PERSONAL | F156: 1 | G156: 344000.85 | H156: UN | I156: PERSONAL | J156: OPEX | K156: VARIABLE | L156: INDIRECTO | M156: 0 | N156: CC1 | O156: #NUM! | P156: 10 | Q156: BACHAS, CEREAL & POLVILLO, COMPOST & FERTILIZANTES, DISPOSICIÓN FINAL RESIDUOS LIQUIDOS, DISPOSICIÓN FINAL RESIDUOS SOLIDOS, EXPORTACION, NFU, PILETAS, REACTORES, TIERRAS FILTRANTES | R156: 1 | S156: -344000.85 | T156: 1 | U156: APERTURADO POR EMPRESA | V156: DISPOSICIÓN FINAL RESIDUOS SOLIDOS
A157: 45950 | B157: American Express Argentina S. A. | C157: OCOM/2025/0472 | D157: -344000.85 | E157: OC 0001-00001936: PERSONAL | F157: 1 | G157: 344000.85 | H157: UN | I157: PERSONAL | J157: OPEX | K157: VARIABLE | L157: INDIRECTO | M157: 0 | N157: CC1 | O157: #NUM! | P157: 10 | Q157: BACHAS, CEREAL & POLVILLO, COMPOST & FERTILIZANTES, DISPOSICIÓN FINAL RESIDUOS LIQUIDOS, DISPOSICIÓN FINAL RESIDUOS SOLIDOS, EXPORTACION, NFU, PILETAS, REACTORES, TIERRAS FILTRANTES | R157: 1 | S157: -344000.85 | T157: 1 | U157: APERTURADO POR EMPRESA | V157: EXPORTACION
A158: 45950 | B158: American Express Argentina S. A. | C158: OCOM/2025/0472 | D158: -344000.85 | E158: OC 0001-00001936: PERSONAL | F158: 1 | G158: 344000.85 | H158: UN | I158: PERSONAL | J158: OPEX | K158: VARIABLE | L158: INDIRECTO | M158: 0 | N158: CC1 | O158: #NUM! | P158: 10 | Q158: BACHAS, CEREAL & POLVILLO, COMPOST & FERTILIZANTES, DISPOSICIÓN FINAL RESIDUOS LIQUIDOS, DISPOSICIÓN FINAL RESIDUOS SOLIDOS, EXPORTACION, NFU, PILETAS, REACTORES, TIERRAS FILTRANTES | R158: 1 | S158: -344000.85 | T158: 1 | U158: APERTURADO POR EMPRESA | V158: NFU
A159: 45950 | B159: American Express Argentina S. A. | C159: OCOM/2025/0472 | D159: -344000.85 | E159: OC 0001-00001936: PERSONAL | F159: 1 | G159: 344000.85 | H159: UN | I159: PERSONAL | J159: OPEX | K159: VARIABLE | L159: INDIRECTO | M159: 0 | N159: CC1 | O159: #NUM! | P159: 10 | Q159: BACHAS, CEREAL & POLVILLO, COMPOST & FERTILIZANTES, DISPOSICIÓN FINAL RESIDUOS LIQUIDOS, DISPOSICIÓN FINAL RESIDUOS SOLIDOS, EXPORTACION, NFU, PILETAS, REACTORES, TIERRAS FILTRANTES | R159: 1 | S159: -344000.85 | T159: 1 | U159: APERTURADO POR EMPRESA | V159: PILETAS
A160: 45950 | B160: American Express Argentina S. A. | C160: OCOM/2025/0472 | D160: -344000.85 | E160: OC 0001-00001936: PERSONAL | F160: 1 | G160: 344000.85 | H160: UN | I160: PERSONAL | J160: OPEX | K160: VARIABLE | L160: INDIRECTO | M160: 0 | N160: CC1 | O160: #NUM! | P160: 10 | Q160: BACHAS, CEREAL & POLVILLO, COMPOST & FERTILIZANTES, DISPOSICIÓN FINAL RESIDUOS LIQUIDOS, DISPOSICIÓN FINAL RESIDUOS SOLIDOS, EXPORTACION, NFU, PILETAS, REACTORES, TIERRAS FILTRANTES | R160: 1 | S160: -344000.85 | T160: 1 | U160: APERTURADO POR EMPRESA | V160: REACTORES
A161: 45950 | B161: American Express Argentina S. A. | C161: OCOM/2025/0472 | D161: -344000.85 | E161: OC 0001-00001936: PERSONAL | F161: 1 | G161: 344000.85 | H161: UN | I161: PERSONAL | J161: OPEX | K161: VARIABLE | L161: INDIRECTO | M161: 0 | N161: CC1 | O161: #NUM! | P161: 10 | Q161: BACHAS, CEREAL & POLVILLO, COMPOST & FERTILIZANTES, DISPOSICIÓN FINAL RESIDUOS LIQUIDOS, DISPOSICIÓN FINAL RESIDUOS SOLIDOS, EXPORTACION, NFU, PILETAS, REACTORES, TIERRAS FILTRANTES | R161: 1 | S161: -344000.85 | T161: 1 | U161: APERTURADO POR EMPRESA | V161: TIERRAS FILTRANTES
A162: 45949 | B162: Amx Argentina Sociedad Anonima | C162: FA-A 01331-01351660 | D162: -40348.6 | E162: OC 0001-00002225: SERVICIOS Servicio Móvil | F162: 1 | G162: 10605 | H162: UN | I162: SERVICIOS | J162: OPEX | K162: VARIABLE | L162: INDIRECTO | M162: 0 | N162: CC1 | O162: #NUM! | P162: 10 | Q162: BACHAS, CEREAL & POLVILLO, COMPOST & FERTILIZANTES, DISPOSICIÓN FINAL RESIDUOS LIQUIDOS, DISPOSICIÓN FINAL RESIDUOS SOLIDOS, EXPORTACION, NFU, PILETAS, REACTORES, TIERRAS FILTRANTES | R162: 1 | S162: -40348.6 | T162: 1 | U162: APERTURADO POR EMPRESA | V162: BACHAS
A163: 45949 | B163: Amx Argentina Sociedad Anonima | C163: FA-A 01331-01351660 | D163: -40348.6 | E163: OC 0001-00002225: SERVICIOS Servicio Móvil | F163: 1 | G163: 10605 | H163: UN | I163: SERVICIOS | J163: OPEX | K163: VARIABLE | L163: INDIRECTO | M163: 0 | N163: CC1 | O163: #NUM! | P163: 10 | Q163: BACHAS, CEREAL & POLVILLO, COMPOST & FERTILIZANTES, DISPOSICIÓN FINAL RESIDUOS LIQUIDOS, DISPOSICIÓN FINAL RESIDUOS SOLIDOS, EXPORTACION, NFU, PILETAS, REACTORES, TIERRAS FILTRANTES | R163: 1 | S163: -40348.6 | T163: 1 | U163: APERTURADO POR EMPRESA | V163: CEREAL & POLVILLO
... A855: 45961 | B855: PROVEEDOR | C855: MT-0004 | D855: -3029264148 | E855: AFE (S) | F855: 2236.94 | G855: 925 | H855: TN | I855: MATERIA PRIMA | J855: OPEX | K855: VARIABLE | L855: DIRECTO | M855: 0 | N855: CC11 | O855: #NUM! | P855: 1 | Q855: EXPORTACION | R855: 1 | S855: -3029264148 | T855: 2236.94 | U855: APERTURADO POR EMPRESA | V855: EXPORTACION
A856: 45961 | B856: PILETAS | C856: MT-0005 | D856: 0 | E856: AG- A | F856: #NUM! | G856: 850 | H856: TN | I856: MATERIA PRIMA | J856: OPEX | K856: VARIABLE | L856: DIRECTO | M856: 0 | N856: CC11 | O856: #NUM! | P856: 1 | Q856: EXPORTACION | R856: 1 | S856: 0 | T856: #NUM! | U856: APERTURADO POR EMPRESA | V856: EXPORTACION
A857: 45961 | B857: PILETAS | C857: MT-0006 | D857: -24537811 | E857: AG- B | F857: 20.44 | G857: 820 | H857: TN | I857: MATERIA PRIMA | J857: OPEX | K857: VARIABLE | L857: DIRECTO | M857: 0 | N857: CC11 | O857: #NUM! | P857: 1 | Q857: EXPORTACION | R857: 1 | S857: -24537811 | T857: 20.44 | U857: APERTURADO POR EMPRESA | V857: EXPORTACION
A858: 45961 | B858: PILETAS | C858: MT-0007 | D858: -12127190 | E858: AG- C | F858: 15.34 | G858: 540 | H858: TN | I858: MATERIA PRIMA | J858: OPEX | K858: VARIABLE | L858: DIRECTO | M858: 0 | N858: CC11 | O858: #NUM! | P858: 1 | Q858: EXPORTACION | R858: 1 | S858: -12127190 | T858: 15.34 | U858: APERTURADO POR EMPRESA | V858: EXPORTACION
A859: 45961 | B859: REACTORES | C859: MT-0008 | D859: 0 | E859: ARE- A | F859: #NUM! | G859: 820 | H859: TN | I859: MATERIA PRIMA | J859: OPEX | K859: VARIABLE | L859: DIRECTO | M859: 0 | N859: CC11 | O859: #NUM! | P859: 1 | Q859: EXPORTACION | R859: 1 | S859: 0 | T859: #NUM! | U859: APERTURADO POR EMPRESA | V859: EXPORTACION
A860: 45961 | B860: REACTORES | C860: MT-0009 | D860: 0 | E860: ARE- B | F860: #NUM! | G860: 820 | H860: TN | I860: MATERIA PRIMA | J860: OPEX | K860: VARIABLE | L860: DIRECTO | M860: 0 | N860: CC11 | O860: #NUM! | P860: 1 | Q860: EXPORTACION | R860: 1 | S860: 0 | T860: #NUM! | U860: APERTURADO POR EMPRESA | V860: EXPORTACION
A861: 45961 | B861: REACTORES -PZ | C861: MT-0010 | D861: -246338496 | E861: ARE- A | F861: 205.2 | G861: 820 | H861: TN | I861: MATERIA PRIMA | J861: OPEX | K861: VARIABLE | L861: DIRECTO | M861: 0 | N861: NO | O861: #NUM! | P861: 1 | Q861: ANULADO | R861: 1 | S861: -246338496 | T861: 205.2 | U861: APERTURADO POR EMPRESA | V861: ANULADO
A862: 45961 | B862: REACTORES - PZ | C862: MT-0011 | D862: 0 | E862: ARE- B | F862: #NUM! | G862: 820 | H862: TN | I862: MATERIA PRIMA | J862: OPEX | K862: VARIABLE | L862: DIRECTO | M862: 0 | N862: NO | O862: #NUM! | P862: 1 | Q862: ANULADO | R862: 1 | S862: 0 | T862: #NUM! | U862: APERTURADO POR EMPRESA | V862: ANULADO
A863: 45961 | B863: WORMS 2 | C863: MT-0012 | D863: -154255824 | E863: AG- A | F863: 123.96 | G863: 850 | H863: TN | I863: MATERIA PRIMA | J863: OPEX | K863: VARIABLE | L863: DIRECTO | M863: 0 | N863: NO | O863: #NUM! | P863: 1 | Q863: ANULADO | R863: 1 | S863: -154255824 | T863: 123.96 | U863: APERTURADO POR EMPRESA | V863: ANULADO
A864: 45961 | B864: WORMS 2 | C864: MT-0013 | D864: 0 | E864: AG- B | F864: #NUM! | G864: 820 | H864: TN | I864: MATERIA PRIMA | J864: OPEX | K864: VARIABLE | L864: DIRECTO | M864: 0 | N864: NO | O864: #NUM! | P864: 1 | Q864: ANULADO | R864: 1 | S864: 0 | T864: #NUM! | U864: APERTURADO POR EMPRESA | V864: ANULADO
A865: 45961 | B865: WORMS 2 | C865: MT-0014 | D865: -8300880 | E865: AG- C | F865: 10.5 | G865: 540 | H865: TN | I865: MATERIA PRIMA | J865: OPEX | K865: VARIABLE | L865: DIRECTO | M865: 0 | N865: NO | O865: #NUM! | P865: 1 | Q865: ANULADO | R865: 1 | S865: -8300880 | T865: 10.5 | U865: APERTURADO POR EMPRESA | V865: ANULADO
A866: 45961 | B866: PZ ( BORRA + PROVEEDOR) | C866: MT-0021 | D866: -91072512 | E866: AG- C | F866: 115.2 | G866: 540 | H866: TN | I866: MATERIA PRIMA | J866: OPEX | K866: VARIABLE | L866: DIRECTO | M866: 0 | N866: NO | O866: #NUM! | P866: 1 | Q866: ANULADO | R866: 1 | S866: -91072512 | T866: 115.2 | U866: APERTURADO POR EMPRESA | V866: ANULADO
A867: 45961 | B867: PILETAS | C867: MT-0022 | D867: 0 | E867: AG- C | F867: #NUM! | G867: 540 | H867: TN | I867: MATERIA PRIMA | J867: OPEX | K867: VARIABLE | L867: DIRECTO | M867: 0 | N867: CC5 | O867: #NUM! | P867: 1 | Q867: REACTORES | R867: 1 | S867: 0 | T867: #NUM! | U867: APERTURADO POR EMPRESA | V867: REACTORES
A868: 45961 | B868: PROVEEDOR | C868: MT-0023 | D868: -1.6548757e+08 | E868: AG - E | F868: 124.32 | G868: 909.25 | H868: TN | I868: MATERIA PRIMA | J868: OPEX | K868: VARIABLE | L868: DIRECTO | M868: 0 | N868: CC11 | O868: #NUM! | P868: 1 | Q868: EXPORTACION | R868: 1 | S868: -1.6548757e+08 | T868: 124.32 | U868: APERTURADO POR EMPRESA | V868: EXPORTACION
A869: 45961 | B869: WORMS 2 | C869: MT-0024 | D869: 0 | E869: SEBO C - 2da | F869: #NUM! | G869: #NUM! | H869: TN | I869: MATERIA PRIMA | J869: OPEX | K869: VARIABLE | L869: DIRECTO | M869: 0 | N869: NO | O869: #NUM! | P869: 1 | Q869: ANULADO | R869: 1 | S869: 0 | T869: #NUM! | U869: APERTURADO POR EMPRESA | V869: ANULADO
A870: 45961 | B870: WORMS 2 | C870: MT-0025 | D870: 0 | E870: BORRA A VEGETAL | F870: 126.22 | G870: #NUM! | H870: TN | I870: MATERIA PRIMA | J870: OPEX | K870: VARIABLE | L870: DIRECTO | M870: 0 | N870: NO | O870: #NUM! | P870: 1 | Q870: ANULADO | R870: 1 | S870: 0 | T870: 126.22 | U870: APERTURADO POR EMPRESA | V870: ANULADO
A871: 45961 | B871: WORMS 2 | C871: MT-0026 | D871: 0 | E871: FONDO TK | F871: 22.2 | G871: #NUM! | H871: TN | I871: MATERIA PRIMA | J871: OPEX | K871: VARIABLE | L871: DIRECTO | M871: 0 | N871: NO | O871: #NUM! | P871: 1 | Q871: ANULADO | R871: 1 | S871: 0 | T871: 22.2 | U871: APERTURADO POR EMPRESA | V871: ANULADO
A872: 45961 | B872: WORMS 2 | C872: MT-0027 | D872: 0 | E872: BORRA ANIMAL | F872: 34.1 | G872: #NUM! | H872: TN | I872: MATERIA PRIMA | J872: OPEX | K872: VARIABLE | L872: DIRECTO | M872: 0 | N872: NO | O872: #NUM! | P872: 1 | Q872: ANULADO | R872: 1 | S872: 0 | T872: 34.1 | U872: APERTURADO POR EMPRESA | V872: ANULADO
A873: 45961 | B873: PROVEEDOR | C873: MT-0028 | D873: 0 | E873: BORRA PESCADO | F873: 86.28 | G873: #NUM! | H873: TN | I873: MATERIA PRIMA | J873: OPEX | K873: VARIABLE | L873: DIRECTO | M873: 0 | N873: NO | O873: #NUM! | P873: 1 | Q873: ANULADO | R873: 1 | S873: 0 | T873: 86.28 | U873: APERTURADO POR EMPRESA | V873: ANULADO
A874: 45961 | B874: PILETAS | C874: MT-0029 | D874: -26088480 | E874: EMULSION | F874: 35.64 | G874: 500 | H874: TN | I874: MATERIA PRIMA | J874: OPEX | K874: VARIABLE | L874: DIRECTO | M874: 0 | N874: CC4 | O874: #NUM! | P874: 1 | Q874: PILETAS | R874: 1 | S874: -26088480 | T874: 35.64 | U874: APERTURADO POR EMPRESA | V874: PILETAS
A875: 45961 | B875: PILETAS | C875: MT-0030 | D875: 0 | E875: AG-D | F875: 82.26 | G875: #NUM! | H875: TN | I875: MATERIA PRIMA | J875: 0 | K875: 0 | L875: 0 | M875: 0 | N875: 0 | O875: #NUM! | P875: 0 | Q875: 0 | R875: 1 | S875: 0 | T875: 82.26 | U875: APERTURADO POR EMPRESA | V875: 0
A876: 45961 | B876: Martins, Joaquin | C876: AD-0001 | D876: 0 | E876: ENERGIA GASOIL G3 | F876: #NUM! | G876: 1754 | H876: Lts | I876: ENERGIA | J876: OPEX | K876: VARIABLE | L876: DIRECTO | M876: 0 | N876: CC1 | O876: #NUM! | P876: CCO NO DEFINIDO | Q876: CCO NO DEFINIDO | R876: 1 | S876: 0 | T876: #NUM! | U876: APERTURADO POR EMPRESA | V876: CCO NO DEFINIDO
A877: 45961 | B877: Martins, Joaquin | C877: AD-0001 | D877: -2679040 | E877: ENERGIA G2 | F877: 1820 | G877: 1472 | H877: Lts | I877: ENERGIA | J877: OPEX | K877: VARIABLE | L877: DIRECTO | M877: 0 | N877: CC6 | O877: #NUM! | P877: 1 | Q877: BACHAS | R877: 1 | S877: -2679040 | T877: 1820 | U877: APERTURADO POR EMPRESA | V877: BACHAS
A878: 45961 | B878: Martins, Joaquin | C878: AD-0001 | D878: 0 | E878: ENERGIA G2 | F878: 0 | G878: 1472 | H878: Lts | I878: ENERGIA | J878: OPEX | K878: VARIABLE | L878: DIRECTO | M878: 0 | N878: CC5 | O878: #NUM! | P878: 1 | Q878: REACTORES | R878: 1 | S878: 0 | T878: 0 | U878: APERTURADO POR EMPRESA | V878: REACTORES
A879: 45961 | B879: Martins, Joaquin | C879: AD-0001 | D879: -149500 | E879: ENERGIA Nafta | F879: 100 | G879: 1495 | H879: Lts | I879: ENERGIA | J879: OPEX | K879: VARIABLE | L879: DIRECTO | M879: 0 | N879: CC6 | O879: #NUM! | P879: 1 | Q879: BACHAS | R879: 1 | S879: -149500 | T879: 100 | U879: APERTURADO POR EMPRESA | V879: BACHAS
A880: 45961 | B880: Martins, Joaquin | C880: AD-0001 | D880: -1644500 | E880: ENERGIA Nafta | F880: 1100 | G880: 1495 | H880: Lts | I880: ENERGIA | J880: OPEX | K880: VARIABLE | L880: DIRECTO | M880: 0 | N880: CC4 | O880: #NUM! | P880: 1 | Q880: PILETAS | R880: 1 | S880: -1644500 | T880: 1100 | U880: APERTURADO POR EMPRESA | V880: PILETAS
A881: 45961 | B881: Martins, Joaquin | C881: AD-0001 | D881: -448500 | E881: ENERGIA Nafta | F881: 300 | G881: 1495 | H881: Lts | I881: ENERGIA | J881: OPEX | K881: VARIABLE | L881: DIRECTO | M881: 0 | N881: CC3 | O881: #NUM! | P881: 1 | Q881: DISPOSICIÓN FINAL RESIDUOS LIQUIDOS | R881: 1 | S881: -448500 | T881: 300 | U881: APERTURADO POR EMPRESA | V881: DISPOSICIÓN FINAL RESIDUOS LIQUIDOS
A882: 45961 | B882: Ultraonix Srl | C882: AD-0001 | D882: -14998192 | E882: ENERGIA Fuel Oil | F882: 24400 | G882: 614.68 | H882: KG | I882: ENERGIA | J882: OPEX | K882: VARIABLE | L882: DIRECTO | M882: 0 | N882: CC5 | O882: #NUM! | P882: 1 | Q882: REACTORES | R882: 1 | S882: -14998192 | T882: 24400 | U882: APERTURADO POR EMPRESA | V882: REACTORES
A883: 45961 | B883: Ultraonix Srl | C883: AD-0001 | D883: -5224780 | E883: ENERGIA Fuel Oil | F883: 8500 | G883: 614.68 | H883: KG | I883: ENERGIA | J883: OPEX | K883: VARIABLE | L883: DIRECTO | M883: 0 | N883: CC6 | O883: #NUM! | P883: 1 | Q883: BACHAS | R883: 1 | S883: -5224780 | T883: 8500 | U883: APERTURADO POR EMPRESA | V883: BACHAS
A884: 45961 | B884: Total Quimica S.A. | C884: AD-0001 | D884: -7342440.6 | E884: INSUMOS Acido Sulfúrico 70/80 | F884: 19860 | G884: 369.71 | H884: KG | I884: INSUMOS | J884: OPEX | K884: VARIABLE | L884: DIRECTO | M884: 0 | N884: CC6 | O884: #NUM! | P884: 1 | Q884: BACHAS | R884: 1 | S884: -7342440.6 | T884: 19860 | U884: APERTURADO POR EMPRESA | V884: BACHAS
A885: 45961 | B885: Total Quimica S.A. | C885: AD-0001 | D885: -547520 | E885: INSUMOS Acido Clorhidrico | F885: 1180 | G885: 464 | H885: KG | I885: INSUMOS | J885: OPEX | K885: VARIABLE | L885: DIRECTO | M885: 0 | N885: CC6 | O885: #NUM! | P885: 1 | Q885: BACHAS | R885: 1 | S885: -547520 | T885: 1180 | U885: APERTURADO POR EMPRESA | V885: BACHAS
A886: 45961 | B886: Total Quimica S.A. | C886: AD-0001 | D886: -691147.5 | E886: INSUMOS Soda Caustica | F886: 750 | G886: 921.53 | H886: KG | I886: INSUMOS | J886: OPEX | K886: VARIABLE | L886: DIRECTO | M886: 0 | N886: CC5 | O886: #NUM! | P886: 1 | Q886: REACTORES | R886: 1 | S886: -691147.5 | T886: 750 | U886: APERTURADO POR EMPRESA | V886: REACTORES
A887: 45961 | B887: Salinera Jaisal S. A. | C887: AD-0001 | D887: -59774 | E887: INSUMOS Cloruro de Sodio (SAL) | F887: 520 | G887: 114.95 | H887: KG | I887: INSUMOS | J887: OPEX | K887: VARIABLE | L887: DIRECTO | M887: 0 | N887: CC6 | O887: #NUM! | P887: 1 | Q887: BACHAS | R887: 1 | S887: -59774 | T887: 520 | U887: APERTURADO POR EMPRESA | V887: BACHAS
A888: 45961 | B888: Cremer Y Asociados Sociedad Anonima | C888: AD-0001 | D888: -11525588 | E888: INSUMOS Glicerina cruda | F888: 28.75 | G888: 400890 | H888: TN | I888: INSUMOS | J888: OPEX | K888: VARIABLE | L888: DIRECTO | M888: 0 | N888: CC5 | O888: #NUM! | P888: 1 | Q888: REACTORES | R888: 1 | S888: -11525588 | T888: 28.75 | U888: APERTURADO POR EMPRESA | V888: REACTORES
A889: 45961 | B889: Meri-mar SRL | C889: AD-0001 | D889: 0 | E889: LOGISTICA | F889: 97.4 | G889: 19500 | H889: TN | I889: SERVICIOS | J889: OPEX | K889: VARIABLE | L889: DIRECTO | M889: 0 | N889: CC11 | O889: #NUM! | P889: 1 | Q889: EXPORTACION | R889: 1 | S889: 0 | T889: 97.4 | U889: APERTURADO POR EMPRESA | V889: EXPORTACION
A890: 45961 | B890: Mercomar SA | C890: AD-0001 | D890: 0 | E890: LOGISTICA | F890: 852.25 | G890: 19500 | H890: TN | I890: SERVICIOS | J890: 0 | K890: 0 | L890: 0 | M890: 0 | N890: 0 | O890: #NUM! | P890: 0 | Q890: 0 | R890: 1 | S890: 0 | T890: 852.25 | U890: APERTURADO POR EMPRESA | V890: 0
A891: 45961 | B891: Transportes Padilla Sociedad Anonima | C891: AD-0001 | D891: 0 | E891: LOGISTICA | F891: 876.6 | G891: #NUM! | H891: TN | I891: SERVICIOS | J891: OPEX | K891: VARIABLE | L891: DIRECTO | M891: 0 | N891: CC11 | O891: #NUM! | P891: 1 | Q891: EXPORTACION | R891: 1 | S891: 0 | T891: 876.6 | U891: APERTURADO POR EMPRESA | V891: EXPORTACION
A892: 45961 | B892: Cronos Soluciones Sustentables Sa | C892: AD-0001 | D892: -11261875 | E892: LOGISTICA | F892: 608.75 | G892: 18500 | H892: TN | I892: LOGISTICA | J892: OPEX | K892: VARIABLE | L892: DIRECTO | M892: 0 | N892: NO | O892: #NUM! | P892: 1 | Q892: ANULADO | R892: 1 | S892: -11261875 | T892: 608.75 | U892: APERTURADO POR EMPRESA | V892: ANULADO
A893: 45961 | B893: Transporte Automotor El Loco Srl | C893: AD-0001 | D893: 0 | E893: LOGISTICA | F893: 97.4 | G893: #NUM! | H893: TN | I893: LOGISTICA | J893: OPEX | K893: VARIABLE | L893: DIRECTO | M893: 0 | N893: NO | O893: #NUM! | P893: 1 | Q893: ANULADO | R893: 1 | S893: 0 | T893: 97.4 | U893: APERTURADO POR EMPRESA | V893: ANULADO
A894: 45961 | B894: Energia Del Sur Srl | C894: AD-0001 | D894: -1461000 | E894: LOGISTICA | F894: 97.4 | G894: 15000 | H894: TN | I894: LOGISTICA | J894: OPEX | K894: VARIABLE | L894: DIRECTO | M894: 0 | N894: NO | O894: #NUM! | P894: 1 | Q894: ANULADO | R894: 1 | S894: -1461000 | T894: 97.4 | U894: APERTURADO POR EMPRESA | V894: ANULADO
A895: 45961 | B895: Duport Sociedad De Responsabilidad Limitada | C895: AD-0001 | D895: 0 | E895: LOGISTICA | F895: 194.8 | G895: #NUM! | H895: TN | I895: LOGISTICA | J895: OPEX | K895: VARIABLE | L895: DIRECTO | M895: 0 | N895: NO | O895: #NUM! | P895: 1 | Q895: ANULADO | R895: 1 | S895: 0 | T895: 194.8 | U895: APERTURADO POR EMPRESA | V895: ANULADO
A896: 45931 | B896: GANANCIAS EXPORTACION | C896: AD_10-2025 | D896: -2067241.2 | E896: IMPUESTOS | F896: 2824.1 | G896: 0.5 | H896: UN | I896: IMPUESTOS | J896: OPEX | K896: VARIABLE | L896: DIRECTO | M896: 0 | N896: CC11 | O896: #NUM! | P896: 1 | Q896: EXPORTACION | R896: 1 | S896: -2067241.2 | T896: 2824.1 | U896: APERTURADO POR EMPRESA | V896: EXPORTACION
A897: 45960 | B897: GASTOS BANCARIOS | C897: OCOM/2025/10 | D897: -6924925.3 | E897: IMPUESTOS | F897: 1 | G897: 6924925.3 | H897: UN | I897: IMPUESTOS | J897: OPEX | K897: VARIABLE | L897: INDIRECTO | M897: 0 | N897: CC1 | O897: #NUM! | P897: CCO NO DEFINIDO | Q897: CCO NO DEFINIDO | R897: 1 | S897: -6924925.3 | T897: 1 | U897: APERTURADO POR EMPRESA | V897: CCO NO DEFINIDO
A898: 45960 | B898: IB | C898: OCOM/2025/10 | D898: -32811.49 | E898: IMPUESTOS | F898: 1 | G898: 32811.49 | H898: UN | I898: IMPUESTOS | J898: OPEX | K898: VARIABLE | L898: INDIRECTO | M898: 0 | N898: CC1 | O898: #NUM! | P898: 10 | Q898: BACHAS, CEREAL & POLVILLO, COMPOST & FERTILIZANTES, DISPOSICIÓN FINAL RESIDUOS LIQUIDOS, DISPOSICIÓN FINAL RESIDUOS SOLIDOS, EXPORTACION, NFU, PILETAS, REACTORES, TIERRAS FILTRANTES | R898: 1 | S898: -32811.49 | T898: 1 | U898: APERTURADO POR EMPRESA | V898: BACHAS
A899: 45960 | B899: IB | C899: OCOM/2025/10 | D899: -32811.49 | E899: IMPUESTOS | F899: 1 | G899: 32811.49 | H899: UN | I899: IMPUESTOS | J899: OPEX | K899: VARIABLE | L899: INDIRECTO | M899: 0 | N899: CC1 | O899: #NUM! | P899: 10 | Q899: BACHAS, CEREAL & POLVILLO, COMPOST & FERTILIZANTES, DISPOSICIÓN FINAL RESIDUOS LIQUIDOS, DISPOSICIÓN FINAL RESIDUOS SOLIDOS, EXPORTACION, NFU, PILETAS, REACTORES, TIERRAS FILTRANTES | R899: 1 | S899: -32811.49 | T899: 1 | U899: APERTURADO POR EMPRESA | V899: CEREAL & POLVILLO
A900: 45960 | B900: IB | C900: OCOM/2025/10 | D900: -32811.49 | E900: IMPUESTOS | F900: 1 | G900: 32811.49 | H900: UN | I900: IMPUESTOS | J900: OPEX | K900: VARIABLE | L900: INDIRECTO | M900: 0 | N900: CC1 | O900: #NUM! | P900: 10 | Q900: BACHAS, CEREAL & POLVILLO, COMPOST & FERTILIZANTES, DISPOSICIÓN FINAL RESIDUOS LIQUIDOS, DISPOSICIÓN FINAL RESIDUOS SOLIDOS, EXPORTACION, NFU, PILETAS, REACTORES, TIERRAS FILTRANTES | R900: 1 | S900: -32811.49 | T900: 1 | U900: APERTURADO POR EMPRESA | V900: COMPOST & FERTILIZANTES
A901: 45960 | B901: IB | C901: OCOM/2025/10 | D901: -32811.49 | E901: IMPUESTOS | F901: 1 | G901: 32811.49 | H901: UN | I901: IMPUESTOS | J901: OPEX | K901: VARIABLE | L901: INDIRECTO | M901: 0 | N901: CC1 | O901: #NUM! | P901: 10 | Q901: BACHAS, CEREAL & POLVILLO, COMPOST & FERTILIZANTES, DISPOSICIÓN FINAL RESIDUOS LIQUIDOS, DISPOSICIÓN FINAL RESIDUOS SOLIDOS, EXPORTACION, NFU, PILETAS, REACTORES, TIERRAS FILTRANTES | R901: 1 | S901: -32811.49 | T901: 1 | U901: APERTURADO POR EMPRESA | V901: DISPOSICIÓN FINAL RESIDUOS LIQUIDOS
A902: 45960 | B902: IB | C902: OCOM/2025/10 | D902: -32811.49 | E902: IMPUESTOS | F902: 1 | G902: 32811.49 | H902: UN | I902: IMPUESTOS | J902: OPEX | K902: VARIABLE | L902: INDIRECTO | M902: 0 | N902: CC1 | O902: #NUM! | P902: 10 | Q902: BACHAS, CEREAL & POLVILLO, COMPOST & FERTILIZANTES, DISPOSICIÓN FINAL RESIDUOS LIQUIDOS, DISPOSICIÓN FINAL RESIDUOS SOLIDOS, EXPORTACION, NFU, PILETAS, REACTORES, TIERRAS FILTRANTES | R902: 1 | S902: -32811.49 | T902: 1 | U902: APERTURADO POR EMPRESA | V902: DISPOSICIÓN FINAL RESIDUOS SOLIDOS
A903: 45960 | B903: IB | C903: OCOM/2025/10 | D903: -32811.49 | E903: IMPUESTOS | F903: 1 | G903: 32811.49 | H903: UN | I903: IMPUESTOS | J903: OPEX | K903: VARIABLE | L903: INDIRECTO | M903: 0 | N903: CC1 | O903: #NUM! | P903: 10 | Q903: BACHAS, CEREAL & POLVILLO, COMPOST & FERTILIZANTES, DISPOSICIÓN FINAL RESIDUOS LIQUIDOS, DISPOSICIÓN FINAL RESIDUOS SOLIDOS, EXPORTACION, NFU, PILETAS, REACTORES, TIERRAS FILTRANTES | R903: 1 | S903: -32811.49 | T903: 1 | U903: APERTURADO POR EMPRESA | V903: EXPORTACION
A904: 45960 | B904: IB | C904: OCOM/2025/10 | D904: -32811.49 | E904: IMPUESTOS | F904: 1 | G904: 32811.49 | H904: UN | I904: IMPUESTOS | J904: OPEX | K904: VARIABLE | L904: INDIRECTO | M904: 0 | N904: CC1 | O904: #NUM! | P904: 10 | Q904: BACHAS, CEREAL & POLVILLO, COMPOST & FERTILIZANTES, DISPOSICIÓN FINAL RESIDUOS LIQUIDOS, DISPOSICIÓN FINAL RESIDUOS SOLIDOS, EXPORTACION, NFU, PILETAS, REACTORES, TIERRAS FILTRANTES | R904: 1 | S904: -32811.49 | T904: 1 | U904: APERTURADO POR EMPRESA | V904: NFU
A905: 45960 | B905: IB | C905: OCOM/2025/10 | D905: -32811.49 | E905: IMPUESTOS | F905: 1 | G905: 32811.49 | H905: UN | I905: IMPUESTOS | J905: OPEX | K905: VARIABLE | L905: INDIRECTO | M905: 0 | N905: CC1 | O905: #NUM! | P905: 10 | Q905: BACHAS, CEREAL & POLVILLO, COMPOST & FERTILIZANTES, DISPOSICIÓN FINAL RESIDUOS LIQUIDOS, DISPOSICIÓN FINAL RESIDUOS SOLIDOS, EXPORTACION, NFU, PILETAS, REACTORES, TIERRAS FILTRANTES | R905: 1 | S905: -32811.49 | T905: 1 | U905: APERTURADO POR EMPRESA | V905: PILETAS
A906: 45960 | B906: IB | C906: OCOM/2025/10 | D906: -32811.49 | E906: IMPUESTOS | F906: 1 | G906: 32811.49 | H906: UN | I906: IMPUESTOS | J906: OPEX | K906: VARIABLE | L906: INDIRECTO | M906: 0 | N906: CC1 | O906: #NUM! | P906: 10 | Q906: BACHAS, CEREAL & POLVILLO, COMPOST & FERTILIZANTES, DISPOSICIÓN FINAL RESIDUOS LIQUIDOS, DISPOSICIÓN FINAL RESIDUOS SOLIDOS, EXPORTACION, NFU, PILETAS, REACTORES, TIERRAS FILTRANTES | R906: 1 | S906: -32811.49 | T906: 1 | U906: APERTURADO POR EMPRESA | V906: REACTORES
A907: 45960 | B907: IB | C907: OCOM/2025/10 | D907: -32811.49 | E907: IMPUESTOS | F907: 1 | G907: 32811.49 | H907: UN | I907: IMPUESTOS | J907: OPEX | K907: VARIABLE | L907: INDIRECTO | M907: 0 | N907: CC1 | O907: #NUM! | P907: 10 | Q907: BACHAS, CEREAL & POLVILLO, COMPOST & FERTILIZANTES, DISPOSICIÓN FINAL RESIDUOS LIQUIDOS, DISPOSICIÓN FINAL RESIDUOS SOLIDOS, EXPORTACION, NFU, PILETAS, REACTORES, TIERRAS FILTRANTES | R907: 1 | S907: -32811.49 | T907: 1 | U907: APERTURADO POR EMPRESA | V907: TIERRAS FILTRANTES
A908: 45960 | B908: DREI DISPOSICIÓN FINAL RESIDUOS LIQUIDOS | C908: OCOM/2025/10 | D908: -656141 | E908: IMPUESTOS | F908: 1 | G908: 656141 | H908: UN | I908: IMPUESTOS | J908: OPEX | K908: VARIABLE | L908: INDIRECTO | M908: 0 | N908: CC3 | O908: #NUM! | P908: 1 | Q908: DISPOSICIÓN FINAL RESIDUOS LIQUIDOS | R908: 1 | S908: -656141 | T908: 1 | U908: APERTURADO POR EMPRESA | V908: DISPOSICIÓN FINAL RESIDUOS LIQUIDOS
A909: 45960 | B909: DREI COMPOST & FERTILIZANTES | C909: OCOM/2025/10 | D909: -485805 | E909: IMPUESTOS | F909: 1 | G909: 485805 | H909: UN | I909: IMPUESTOS | J909: OPEX | K909: VARIABLE | L909: INDIRECTO | M909: 0 | N909: CC8 | O909: #NUM! | P909: 1 | Q909: COMPOST & FERTILIZANTES | R909: 1 | S909: -485805 | T909: 1 | U909: APERTURADO POR EMPRESA | V909: COMPOST & FERTILIZANTES
... A1522: 45931 | B1522: WORMS-RRHH | C1522: ADROVER, JUAN HORACIO | D1522: -1876296.3 | E1522: TALLER MECANICO | F1522: 15 | G1522: 1876296.3 | H1522: #RRHH | I1522: PERSONAL | J1522: Opex | K1522: Fijo | L1522: Indirecto | M1522: 0 | N1522: CC23 | O1522: #NUM! | P1522: 10 | Q1522: BACHAS, CEREAL Y POLVILLO, COMPOST Y FERTILIZANTES, DISPOSICION FINAL DE R. LIQUIDOS, DISPOSICION FINAL DE R. SOLIDOS, EXPORTACION, NFU, PILETAS, REACTORES, TIERRAS FILTRANTES | R1522: 1 | S1522: -1876296.3 | T1522: 15 | U1522: APERTURADO POR EMPRESA | V1522: TIERRAS FILTRANTES

Sheet ingresos_ingresos
A1: FECHA CARGA | B1: CANAL | C1: AREA | D1: SECTOR | E1: PRODUCTO | F1: CLIENTE | G1: DESCRIPCION | H1: UM | I1: Q | J1: PRECIO | K1: MONEDA | L1: SUBTOTAL | M1: T.C | N1: IVA | O1: TOTAL | P1: Fuente
A2: 45931 | B2: 1 | C2: RECEPCION DE RESIDUOS SOLIDOS | D2: COMPOST_Y_FERTILIZANTES | E2: DESCARTE SEMILLAS | F2: TECNORED ENERGIA S.A. | H2: TN | I2: 184.94 | J2: 6 | K2: USD | L2: 1611197.3 | M2: 1452 | N2: 0.21 | O2: 1949548.7
A3: 45931 | B3: 1 | C3: RECEPCION DE RESIDUOS SOLIDOS | D3: DISP FINAL RESIDUOS SOLIDOS | E3: CERTIFICADO DISP FINAL SOLIDOS | G3: NFU | H3: KG | I3: 7920 | J3: 70 | K3: ARS | L3: 554400 | M3: 0 | N3: 0.21 | O3: 670824
A4: 45931 | B4: 1 | C4: RECEPCION DE RESIDUOS SOLIDOS | D4: DISP FINAL RESIDUOS SOLIDOS | E4: TIERRA TOSCA | F4: Aceitera Lonatte SRL | H4: TN | I4: 133.24
A5: 45931 | B5: 1 | C5: RECEPCION DE RESIDUOS SOLIDOS | D5: DISP FINAL RESIDUOS SOLIDOS | E5: CERTIFICADO DISP FINAL SOLIDOS | F5: Boortmalt | H5: TN | I5: 64.66 | J5: 3000 | K5: ARS | L5: 193980 | M5: 1 | N5: 0.21 | O5: 234715.8
A6: 45931 | B6: 1 | C6: RECEPCION DE RESIDUOS SOLIDOS | D6: DISP FINAL RESIDUOS SOLIDOS | E6: CERTIFICADO DISP FINAL SOLIDOS | F6: Bunge Argentina S A - San Jeronimo Sud | H6: TN | I6: 46.66 | J6: 4.93 | K6: USD | L6: 334009.08 | M6: 1452 | N6: 0.21 | O6: 404150.98
A7: 45931 | B7: 1 | C7: RECEPCION DE RESIDUOS SOLIDOS | D7: DISP FINAL RESIDUOS SOLIDOS | E7: SEMILLAS | F7: Bunge Argentina S A - San Jeronimo Sud | H7: TN | I7: 583.72 | J7: 0 | K7: 0
A8: 45931 | B8: 1 | C8: RECEPCION DE RESIDUOS SOLIDOS | D8: DISP FINAL RESIDUOS SOLIDOS | E8: CERTIFICADO DISP FINAL SOLIDOS | F8: Quickfood S.A. | H8: TN | I8: 145.56 | J8: 1140 | K8: ARS | L8: 165938.4 | M8: 1 | N8: 0.21 | O8: 200785.46
A9: 45931 | B9: 1 | C9: RECEPCION DE RESIDUOS SOLIDOS | D9: DISP FINAL RESIDUOS SOLIDOS | E9: CERTIFICADO DISP FINAL SOLIDOS | F9: Unilever de Argentina S.A. | H9: TN | I9: 31 | J9: 6500 | K9: ARS | L9: 201500 | M9: 1 | N9: 0.21 | O9: 243815
A10: 45931 | B10: 1 | C10: RECEPCION DE RESIDUOS SOLIDOS | D10: DISP FINAL RESIDUOS SOLIDOS | E10: CERTIFICADO DISP FINAL SOLIDOS | F10: Adm Agro S.R.L. - Arroyo Seco | H10: TN | I10: 38.62 | J10: 1600 | K10: ARS | L10: 61792 | M10: 1 | N10: 0.21 | O10: 74768.32
A11: 45931 | B11: 1 | C11: RECEPCION DE RESIDUOS SOLIDOS | D11: DISP FINAL RESIDUOS SOLIDOS | E11: CERTIFICADO DISP FINAL SOLIDOS | F11: Bunge Argentina S A - Puerto Gral San Martín | H11: TN | I11: 370.59 | J11: 0 | K11: ARS | L11: 0 | M11: 1 | N11: 0.21 | O11: 0
A12: 45931 | B12: 1 | C12: RECEPCION DE RESIDUOS SOLIDOS | D12: DISP FINAL RESIDUOS SOLIDOS | E12: CERTIFICADO DISP FINAL SOLIDOS | F12: Cargill - Alvear | H12: TN | I12: 14.94 | J12: 1305 | K12: ARS | L12: 19496.7 | M12: 1 | N12: 0.21 | O12: 23591.007
A13: 45931 | B13: 1 | C13: RECEPCION DE RESIDUOS SOLIDOS | D13: DISP FINAL RESIDUOS SOLIDOS | E13: CERTIFICADO DISP FINAL SOLIDOS | F13: Cargill - VGG | H13: TN | I13: 82.32 | J13: 1305 | K13: ARS | L13: 107427.6 | M13: 1 | N13: 0.21 | O13: 129987.4
A14: 45931 | B14: 1 | C14: RECEPCION DE RESIDUOS SOLIDOS | D14: DISP FINAL RESIDUOS SOLIDOS | E14: CERTIFICADO DISP FINAL SOLIDOS | F14: LDC Argentina S.A. - Lagos | H14: TN | I14: 43.74 | J14: 0 | K14: ARS | L14: 0 | M14: 1 | N14: 0.21 | O14: 0
A15: 45931 | B15: 1 | C15: RECEPCION DE RESIDUOS SOLIDOS | D15: DISP FINAL RESIDUOS SOLIDOS | E15: CERTIFICADO DISP FINAL SOLIDOS | F15: Molinos Rio De La Plata S.A. | H15: TN | I15: 37.33 | J15: 1760 | K15: ARS | L15: 65700.8 | M15: 1 | N15: 0.21 | O15: 79497.968
A16: 45931 | B16: 2 | C16: RECEPCION DE RESIDUOS SOLIDOS | D16: CEREAL & POLVILLO | E16: BARRIDO | F16: Alvarez Daniel Fabian | H16: TN | I16: 386.6 | J16: 40000 | K16: ARS | L16: 15464000 | M16: 1 | N16: 0 | O16: 15464000
A17: 45931 | B17: 2 | C17: RECEPCION DE RESIDUOS SOLIDOS | D17: CEREAL & POLVILLO | E17: BARRIDO | F17: Aquilino Pruzzo | H17: TN | I17: 19.12 | J17: 45000 | K17: ARS | L17: 860400 | M17: 1 | N17: 0 | O17: 860400
A18: 45931 | B18: 2 | C18: RECEPCION DE RESIDUOS SOLIDOS | D18: CEREAL & POLVILLO | E18: BARRIDO | F18: Batistelli | H18: TN | I18: 60.38 | J18: 30000 | K18: ARS | L18: 1811400 | M18: 1 | N18: 0 | O18: 1811400
A19: 45931 | B19: 2 | C19: RECEPCION DE RESIDUOS SOLIDOS | D19: CEREAL & POLVILLO | E19: BARRIDO | F19: Pascual | H19: TN | I19: 28 | J19: 40000 | K19: ARS | L19: 1120000 | M19: 1 | N19: 0 | O19: 1120000
... A22: 45931 | B22: 1 | C22: RECEPCION DE RESIDUOS LIQUIDOS | D22: DISP FINAL RESIDUOS LIQUIDOS | E22: CERTIFICADO DISP FINAL LIQUIDOS | F22: Bio Nogoya S.A. | H22: TN | I22: 281.86 | J22: 1770 | K22: ARS | L22: 498892.2 | M22: 1 | N22: 0.21 | O22: 603659.56
A23: 45931 | B23: 2 | C23: RECEPCION DE RESIDUOS LIQUIDOS | D23: DISP FINAL RESIDUOS LIQUIDOS | E23: CERTIFICADO DISP FINAL LIQUIDOS | F23: CREMER - CRONOS | H23: TN | I23: 176.32
A24: 45931 | B24: 2 | C24: RECEPCION DE RESIDUOS LIQUIDOS | D24: DISP FINAL RESIDUOS LIQUIDOS | E24: CERTIFICADO DISP FINAL LIQUIDOS | F24: DESIDERIO ZERIAL | H24: TN | I24: 50.74
A25: 45931 | B25: 1 | C25: RECEPCION DE RESIDUOS LIQUIDOS | D25: DISP FINAL RESIDUOS LIQUIDOS | E25: CERTIFICADO DISP FINAL LIQUIDOS | F25: Duport S.R.L. | H25: TN | I25: 3358.68 | J25: 5000 | K25: ARS | L25: 16793400 | M25: 1 | N25: 0.21 | O25: 20320014
A26: 45931 | B26: 1 | C26: RECEPCION DE RESIDUOS SOLIDOS | D26: DISP FINAL RESIDUOS SOLIDOS | E26: CERTIFICADO DISP FINAL SOLIDOS | F26: Emsade | H26: TN | I26: 65.48 | J26: 11500 | K26: ARS | L26: 753020 | M26: 1 | N26: 0.21 | O26: 911154.2
A27: 45931 | B27: 1 | C27: RECEPCION DE RESIDUOS LIQUIDOS | D27: DISP FINAL RESIDUOS LIQUIDOS | E27: CERTIFICADO DISP FINAL LIQUIDOS | F27: ERA S.A. | H27: TN | I27: 112.7 | J27: 7.5 | K27: USD | L27: 1227303 | M27: 1452 | N27: 0.21 | O27: 1485036.6
A28: 45931 | B28: 1 | C28: RECEPCION DE RESIDUOS LIQUIDOS | D28: DISP FINAL RESIDUOS LIQUIDOS | E28: CERTIFICADO DISP FINAL LIQUIDOS | F28: Geo S.R.L. | H28: TN | I28: 1727.49 | J28: 7.5 | K28: USD | L28: 18812366 | M28: 1452 | N28: 0.21 | O28: 22762963
A29: 45931 | B29: 1 | C29: RECEPCION DE RESIDUOS LIQUIDOS | D29: DISP FINAL RESIDUOS LIQUIDOS | E29: CERTIFICADO DISP FINAL LIQUIDOS | F29: Glardon Anibal Mauricio | H29: TN | I29: 221.04 | J29: 3937 | K29: ARS | L29: 870234.48 | M29: 1 | N29: 0.21 | O29: 1052983.7
A30: 45931 | B30: 1 | C30: RECEPCION DE RESIDUOS LIQUIDOS | D30: DISP FINAL RESIDUOS LIQUIDOS | E30: CERTIFICADO DISP FINAL LIQUIDOS | F30: Glycopharma S.A. | H30: TN | I30: 766.64 | J30: 1770 | K30: ARS | L30: 1356952.8 | M30: 1 | N30: 0.21 | O30: 1641912.9
A31: 45931 | B31: 1 | C31: RECEPCION DE RESIDUOS LIQUIDOS | D31: DISP FINAL RESIDUOS LIQUIDOS | E31: CERTIFICADO DISP FINAL LIQUIDOS | F31: Inagro S.R.L. | H31: TN | I31: 3835.94 | J31: 4.5 | K31: USD | L31: 25064032 | M31: 1452 | N31: 0.21 | O31: 30327479
A32: 45931 | B32: 1 | C32: RECEPCION DE RESIDUOS LIQUIDOS | D32: DISP FINAL RESIDUOS LIQUIDOS | E32: CERTIFICADO DISP FINAL LIQUIDOS | F32: Patagonia Bioenergía S.A. | H32: TN | I32: 98.44 | J32: 11120 | K32: ARS | L32: 1094652.8 | M32: 1 | N32: 0.21 | O32: 1324529.9
A33: 45931 | B33: 1 | C33: RECEPCION DE RESIDUOS LIQUIDOS | D33: DISP FINAL RESIDUOS LIQUIDOS | E33: CERTIFICADO DISP FINAL LIQUIDOS | F33: Renopack S.A. | H33: TN | I33: 8.43 | J33: 4380 | K33: ARS | L33: 36923.4 | M33: 1 | N33: 0.21 | O33: 44677.314
A34: 45931 | B34: 1 | C34: RECEPCION DE RESIDUOS LIQUIDOS | D34: DISP FINAL RESIDUOS LIQUIDOS | E34: CERTIFICADO DISP FINAL LIQUIDOS | F34: Renova S.A. | H34: TN | I34: 563.7 | J34: 11120 | K34: ARS | L34: 6268344 | M34: 1 | N34: 0.21 | O34: 7584696.2
A35: 45931 | B35: 1 | C35: RECEPCION DE RESIDUOS LIQUIDOS | D35: DISP FINAL RESIDUOS LIQUIDOS | E35: CERTIFICADO DISP FINAL LIQUIDOS | F35: Rosario Bio Energy S.A. | H35: TN | I35: 304.18 | J35: 6800 | K35: ARS | L35: 2068424 | M35: 1 | N35: 0.21 | O35: 2502793
A36: 45931 | B36: 1 | C36: RECEPCION DE RESIDUOS LIQUIDOS | D36: DISP FINAL RESIDUOS LIQUIDOS | E36: CERTIFICADO DISP FINAL LIQUIDOS | F36: Santa Fe Aceites S.R.L. | H36: TN | I36: 3937.74 | J36: 3937 | K36: ARS | L36: 15502882 | M36: 1 | N36: 0.21 | O36: 18758488
... A50: 45931 | B50: 1 | C50: TRATAMIENTO DE RESIDUOS SOLIDOS | D50: COMPOST_Y_FERTILIZANTES | E50: COMPOST | F50: Zamparo | H50: KG | I50: 3840 | J50: 91.79 | K50: ARS | L50: 352473.6 | M50: 1 | N50: 0.21 | O50: 426493.06

Sheet ingresos_produccion
A1: FECHA CARGA | B1: CANAL | C1: AREA | D1: SECTOR | E1: PRODUCTO | F1: CLIENTE | G1: DESCRIPCION | H1: UM | I1: Q | J1: PRECIO | K1: MONEDA | L1: SUBTOTAL | M1: T.C | N1: IVA | O1: TOTAL | P1: Fuente
A2: 45961 | B2: 1 | C2: EXPORTACION | D2: EXPORTACION | E2: AG - E | F2: PARAGUAY LOGISTIC | G2: EGRESOS | H2: TN | I2: 0 | J2: 172 | K2: USD | L2: 0 | M2: 1464 | N2: 0 | O2: 0
A3: 45961 | B3: 1 | C3: EXPORTACION | D3: EXPORTACION | E3: AG - E | F3: EGNITRADE | G3: EGRESOS | H3: TN | I3: 2824.1 | J3: 1072 | K3: USD | L3: 3027830.6 | M3: 1464 | N3: 0 | O3: 4.432744e+09 | P3: 116 cam
A4: 45961 | B4: 1 | C4: EXPORTACION | D4: EXPORTACION | E4: ARE (AN) | F4: SWIFT | G4: EGRESOS | H4: TN | I4: 58.48 | J4: 760 | K4: USD | L4: 44444.8 | M4: 1464 | N4: 0 | O4: 65067187 | P4: 2 CAM
A5: 45961 | B5: 1 | C5: EXPORTACION | D5: EXPORTACION | E5: ARE (AN)/SEBO 2DA A | F5: MILO | G5: EGRESOS | H5: TN | I5: 74.8 | K5: USD | L5: 0 | M5: 1464 | N5: 0 | O5: 0 | P5: 4 CAM
A6: 45961 | B6: 1 | C6: TRATAMIENTO DE RESIDUOS LIQUIDOS | D6: REACTORES | E6: ARE(V) - B | F6: MILO | G6: EGRESOS | H6: TN | I6: 193.86 | J6: 83 | K6: USD | L6: 16090.38 | M6: 1464 | N6: 0 | O6: 23556316 | P6: 8 CAM
A7: 45961 | B7: 2 | C7: TRATAMIENTO DE RESIDUOS LIQUIDOS | D7: REACTORES | E7: ARE (V) -A | F7: WORMS | G7: PRODUCCION | H7: TN | J7: 820 | K7: USD | L7: 0 | M7: 1464 | N7: 0 | O7: 0
A8: 45961 | B8: 2 | C8: TRATAMIENTO DE RESIDUOS LIQUIDOS | D8: REACTORES | E8: ARE (V) -B | F8: WORMS | G8: PRODUCCION | H8: TN | I8: 83 | J8: 820 | K8: USD | L8: 68060 | M8: 1464 | N8: 0 | O8: 99639840
A9: 45961 | B9: 2 | C9: TRATAMIENTO DE RESIDUOS LIQUIDOS | D9: REACTORES | E9: ARE (V) -A | F9: WORMS 2 | G9: FASON | H9: TN | J9: 90 | K9: USD | L9: 0 | M9: 1464 | N9: 0 | O9: 0
A10: 45961 | B10: 2 | C10: TRATAMIENTO DE RESIDUOS LIQUIDOS | D10: REACTORES | E10: ARE (V) -B | F10: WORMS 2 | G10: FASON | H10: TN | J10: 90 | K10: USD | L10: 0 | M10: 1464 | N10: 0 | O10: 0
A11: 45961 | B11: 2 | C11: TRATAMIENTO DE RESIDUOS LIQUIDOS | D11: REACTORES | E11: ARE (AN) | F11: WORMS 2 | G11: FASON | H11: TN | J11: 90 | K11: USD | L11: 0 | M11: 1464 | N11: 0 | O11: 0
A12: 45961 | B12: 2 | C12: TRATAMIENTO DE RESIDUOS LIQUIDOS | D12: REACTORES | E12: ARE (AN) | F12: WORMS | G12: PRODUCCION | H12: TN | J12: 760 | K12: USD | L12: 0 | M12: 1464 | N12: 0 | O12: 0
A13: 45961 | B13: 1 | C13: TRATAMIENTO DE RESIDUOS LIQUIDOS | D13: PILETAS | E13: AG - C | F13: BAHIA | G13: EGRESOS | H13: TN | I13: 29.5 | J13: 740 | K13: USD | L13: 21830 | M13: 1464 | N13: 0 | O13: 31959120 | P13: 1 CAM
A14: 45961 | B14: 1 | C14: TRATAMIENTO DE RESIDUOS LIQUIDOS | D14: PILETAS | E14: AG - C | F14: STA FE ACEITES | G14: EGRESOS | H14: TN | I14: 26.84 | J14: 740 | K14: USD | L14: 19861.6 | M14: 1464 | N14: 0 | O14: 29077382 | P14: 1 CAM
A15: 45961 | B15: 2 | C15: TRATAMIENTO DE RESIDUOS LIQUIDOS | D15: PILETAS | E15: AG - A | F15: WORMS | G15: RECUPERADO AG DE PILETAS | H15: TN | I15: 0 | J15: 850 | K15: USD | L15: 0 | M15: 1464 | N15: 0 | O15: 0
A16: 45961 | B16: 2 | C16: TRATAMIENTO DE RESIDUOS LIQUIDOS | D16: PILETAS | E16: AG - B | F16: WORMS | G16: RECUPERADO AG DE PILETAS | H16: TN | I16: 32.16 | J16: 820 | K16: USD | L16: 26371.2 | M16: 1464 | N16: 0 | O16: 38607437
A17: 45961 | B17: 2 | C17: TRATAMIENTO DE RESIDUOS LIQUIDOS | D17: PILETAS | E17: AG - C | F17: WORMS | G17: RECUPERADO AG DE PILETAS | H17: TN | I17: 461.12 | J17: 740 | K17: USD | L17: 341228.8 | M17: 1464 | N17: 0 | O17: 4.9955896e+08
A18: 45961 | B18: 2 | C18: TRATAMIENTO DE RESIDUOS LIQUIDOS | D18: PILETAS | E18: AG - D | F18: WORMS | G18: RECUPERADO AG DE PILETAS | H18: TN | I18: 44.49 | J18: 500 | K18: USD | L18: 22245 | M18: 1464 | N18: 0 | O18: 32566680
A19: 45961 | B19: 2 | C19: TRATAMIENTO DE RESIDUOS LIQUIDOS | D19: PILETAS | E19: EMULSION | F19: WORMS | G19: RECUPERADO EMUL DE PILETAS | H19: TN | I19: 50.26 | J19: 500 | K19: USD | L19: 25130 | M19: 1464 | N19: 0 | O19: 36790320
A20: 45961 | B20: 1 | C20: TRATAMIENTO DE RESIDUOS LIQUIDOS | D20: BACHAS | E20: AG (PES) | F20: DABID ABBIAD | G20: EGRESOS | H20: TN | I20: 25.96 | K20: USD | L20: 0 | M20: 1464 | N20: 0 | O20: 0 | P20: 1 CAM
A21: 45961 | B21: 2 | C21: TRATAMIENTO DE RESIDUOS LIQUIDOS | D21: BACHAS | E21: AG - C | F21: WORMS | G21: PRODUCCION | H21: TN | I21: 80.96 | J21: 740 | K21: USD | L21: 59910.4 | M21: 1464 | N21: 0 | O21: 87708826
A22: 45961 | B22: 2 | C22: TRATAMIENTO DE RESIDUOS LIQUIDOS | D22: BACHAS | E22: AG - C | F22: WORMS 2 | G22: FASON DE BORRAS DE TERCEROS | H22: TN | I22: 31.6 | J22: 740 | K22: USD | L22: 23384 | M22: 1464 | N22: 0 | O22: 34234176
A23: 45961 | B23: 2 | C23: TRATAMIENTO DE RESIDUOS LIQUIDOS | D23: BACHAS | E23: SEBO 2DA - C | F23: WORMS 2 | G23: FASON DE BORRAS DE TERCEROS | H23: TN | I23: 7.1 | K23: USD | L23: 0 | M23: 1464 | N23: 0 | O23: 0
A24: 45961 | B24: 2 | C24: TRATAMIENTO DE RESIDUOS LIQUIDOS | D24: BACHAS | E24: ACEITE PESCADO | F24: WORMS | G24: PRODUCCION | H24: TN | I24: 9.14 | K24: USD | L24: 0 | M24: 1464 | N24: 0 | O24: 0
A25: 45961 | B25: 2 | C25: TRATAMIENTO DE RESIDUOS LIQUIDOS | D25: BACHAS | E25: ACEITE PESCADO | F25: D ABIAD | G25: FASON DE BORRAS DE TERCEROS | H25: TN | I25: 41.18 | K25: USD | L25: 0 | M25: 1464 | N25: 0 | O25: 0
A26: 45961 | B26: 1 | C26: TRATAMIENTO DE RESIDUOS SOLIDOS | D26: NFU | E26: GRANULADO DE CAUCHO 1 - P1 | F26: WORMS | G26: PRODUCCION | H26: TN | I26: 47.08 | J26: 850 | K26: USD | L26: 40018 | M26: 1464 | N26: 0 | O26: 58586352
A27: 45961 | B27: 1 | C27: TRATAMIENTO DE RESIDUOS SOLIDOS | D27: NFU | E27: GRANULADO DE CAUCHO 2- P1 | F27: WORMS | G27: PRODUCCION | H27: TN | I27: 76.4 | J27: 650 | K27: USD | L27: 49660 | M27: 1464 | N27: 0 | O27: 72702240
A28: 45961 | B28: 1 | C28: TRATAMIENTO DE RESIDUOS SOLIDOS | D28: NFU | E28: GRANULADO DE CAUCHO 3 - P1 | F28: WORMS | G28: PRODUCCION | H28: TN | I28: 87.52 | J28: 450 | K28: USD | L28: 39384 | M28: 1464 | N28: 0 | O28: 57658176
A29: 45961 | B29: 1 | C29: TRATAMIENTO DE RESIDUOS SOLIDOS | D29: NFU | E29: ACERO | F29: WORMS | G29: PRODUCCION | H29: TN | I29: 110.7 | J29: 90000 | K29: ARG | L29: 9963000 | M29: 1464 | N29: 0 | O29: 14585832000
A30: 45961 | B30: 2 | C30: TRATAMIENTO DE RESIDUOS LIQUIDOS | D30: SALES | E30: GLICERINA -FE | F30: WORMS | G30: PRODUCCION | H30: TN | K30: USD | L30: 0 | M30: 1464 | N30: 0 | O30: 0

Sheet gastos_rrhh
A1: Fecha de Factura/Recibo | B1: Nombre de la empresa a mostrar en la factura | C1: Número | D1: Total con signo | E1: Líneas de factura/Etiqueta | F1: Líneas de factura/Cantidad | G1: Líneas de factura/Precio unitario | H1: Líneas de factura/Unidad de medida | I1: Líneas de factura/Producto | J1: Concepto | K1: Tipo de Gasto 1 | L1: Tipo de Gasto 2 | M1: CCO EMPRESA | N1: CCO - SECTOR
A2: 45931 | B2: WORMS-RRHH | C2: MAIDANA, JOSE RAMON | D2: -2078949.5 | E2: INTENDENCIA | F2: 1 | G2: 2078949.5 | H2: #RRHH | I2: PERSONAL | J2: Opex | K2: Fijo | L2: Indirecto | N2: CC27
A3: 45931 | B3: WORMS-RRHH | C3: PEREZ, MATIAS ROMAN | D3: -5104642.3 | E3: INTENDENCIA | F3: 1 | G3: 5104642.3 | H3: #RRHH | I3: PERSONAL | J3: Opex | K3: Fijo | L3: Indirecto | N3: CC27
A4: 45931 | B4: WORMS-RRHH | C4: PANZANELLA, EDUARDO JAVIER | D4: -2117008.3 | E4: PORTERIA | F4: 1 | G4: 2117008.3 | H4: #RRHH | I4: PERSONAL | J4: Opex | K4: Fijo | L4: Indirecto | N4: CC22
A5: 45931 | B5: WORMS-RRHH | C5: ENRIQUEZ, MAXIMO GUSTAVO | D5: -2067002 | E5: DISPOSICION FINAL DE R. LIQUIDOS | F5: 1 | G5: 2067002 | H5: #RRHH | I5: PERSONAL | J5: Opex | K5: Variable | L5: Directo | N5: CC25
A6: 45931 | B6: WORMS-RRHH | C6: PORCU, MIGUEL ANGEL | D6: -1085682.2 | E6: PILETAS | F6: 1 | G6: 1085682.2 | H6: #RRHH | I6: PERSONAL | J6: Opex | K6: Variable | L6: Directo | N6: CC21
A7: 45931 | B7: WORMS-RRHH | C7: PETERS CORZO, JOSE LUIS | D7: -2513045.7 | E7: LABORATORIO | F7: 1 | G7: 2513045.7 | H7: #RRHH | I7: PERSONAL | J7: Opex | K7: Fijo | L7: Indirecto | N7: CC17
A8: 45931 | B8: WORMS-RRHH | C8: ALTAMIRANO, GUSTAVO | D8: -2156572.8 | E8: NFU | F8: 1 | G8: 2156572.8 | H8: #RRHH | I8: PERSONAL | J8: Opex | K8: Variable | L8: Directo | N8: CC20
A9: 45931 | B9: WORMS-RRHH | C9: MARTINEZ, FRANCO ALBERTO | D9: -1290098.8 | E9: CAT | F9: 1 | G9: 1290098.8 | H9: #RRHH | I9: PERSONAL | J9: Opex | K9: Variable | L9: Directo | N9: CC7
A10: 45931 | B10: WORMS-RRHH | C10: PARDEL, MAURO | D10: -2430242.5 | E10: PORTERIA | F10: 1 | G10: 2430242.5 | H10: #RRHH | I10: PERSONAL | J10: Opex | K10: Fijo | L10: Indirecto | N10: CC22
A11: 45931 | B11: WORMS-RRHH | C11: MONTENEGRO, GUSTAVO | D11: -2174118.9 | E11: INTENDENCIA | F11: 1 | G11: 2174118.9 | H11: #RRHH | I11: PERSONAL | J11: Opex | K11: Fijo | L11: Indirecto | N11: CC27
A12: 45931 | B12: WORMS-RRHH | C12: CEBALLEZ, MARIA EUGENIA | D12: -5514943.3 | E12: PRODUCCION | F12: 1 | G12: 5514943.3 | H12: #RRHH | I12: PERSONAL | J12: Opex | K12: Fijo | L12: Indirecto | N12: CC28
A13: 45931 | B13: WORMS-RRHH | C13: LOPEZ CAMARGO BERLITZ, BEATRIZ | D13: -2756590.4 | E13: LABORATORIO | F13: 1 | G13: 2756590.4 | H13: #RRHH | I13: PERSONAL | J13: Opex | K13: Fijo | L13: Indirecto | N13: CC17
... A104: 45931 | B104: WORMS-RRHH | C104: ADROVER, JUAN HORACIO | D104: -1876296.3 | E104: TALLER MECANICO | F104: 15 | G104: 1876296.3 | H104: #RRHH | I104: PERSONAL | J104: Opex | K104: Fijo | L104: Indirecto | N104: CC23

Sheet gastos_impuestos
A1: Fecha de Factura/Recibo | B1: Nombre de la empresa a mostrar en la factura | C1: Número | D1: Total con signo | E1: Líneas de factura/Etiqueta | F1: Líneas de factura/Cantidad | G1: Líneas de factura/Precio unitario | H1: Líneas de factura/Unidad de medida | I1: Líneas de factura/Producto | J1: Concepto | K1: Tipo de Gasto 1 | L1: Tipo de Gasto 2 | M1: CCO EMPRESA | N1: CCO - SECTOR | O1: TC
A2: 45931 | B2: GANANCIAS EXPORTACION | C2: AD_10-2025 | D2: -2067241.2 | E2: IMPUESTOS | F2: 2824.1 | G2: 0.5 | H2: UN | I2: IMPUESTOS | J2: OPEX | K2: VARIABLE | L2: DIRECTO | N2: CC11 | O2: 1464
A3: 45960 | B3: GASTOS BANCARIOS | C3: OCOM/2025/10 | D3: -6924925.3 | E3: IMPUESTOS | F3: 1 | G3: 6924925.3 | H3: UN | I3: IMPUESTOS | J3: OPEX | K3: VARIABLE | L3: INDIRECTO | N3: CC1
A4: 45960 | B4: IB | C4: OCOM/2025/10 | D4: -32811.49 | E4: IMPUESTOS | F4: 1 | G4: 32811.49 | H4: UN | I4: IMPUESTOS | J4: OPEX | K4: VARIABLE | L4: INDIRECTO | N4: CC1
A5: 45960 | B5: DREI DISPOSICIÓN FINAL RESIDUOS LIQUIDOS | C5: OCOM/2025/10 | D5: -656141 | E5: IMPUESTOS | F5: 1 | G5: 656141 | H5: UN | I5: IMPUESTOS | J5: OPEX | K5: VARIABLE | L5: INDIRECTO | N5: CC3
A6: 45960 | B6: DREI COMPOST & FERTILIZANTES | C6: OCOM/2025/10 | D6: -485805 | E6: IMPUESTOS | F6: 1 | G6: 485805 | H6: UN | I6: IMPUESTOS | J6: OPEX | K6: VARIABLE | L6: INDIRECTO | N6: CC8
A7: 45960 | B7: DREI PILETAS | C7: OCOM/2025/10 | D7: -374523 | E7: IMPUESTOS | F7: 1 | G7: 374523 | H7: UN | I7: IMPUESTOS | J7: OPEX | K7: VARIABLE | L7: INDIRECTO | N7: CC4
A8: 45960 | B8: DREI NFU | C8: OCOM/2025/10 | D8: -386033 | E8: IMPUESTOS | F8: 1 | G8: 386033 | H8: UN | I8: IMPUESTOS | J8: OPEX | K8: VARIABLE | L8: INDIRECTO | N8: CC7

Sheet gastos_produccion
A1: Fecha de Factura/Recibo | B1: Nombre de la empresa a mostrar en la factura | C1: Número | D1: Total con signo | E1: Líneas de factura/Etiqueta | F1: Líneas de factura/Cantidad | G1: Líneas de factura/Precio unitario | H1: Líneas de factura/Unidad de medida | I1: Líneas de factura/Producto | J1: Concepto | K1: Tipo de Gasto 1 | L1: Tipo de Gasto 2 | M1: CCO EMPRESA | N1: CCO - SECTOR | O1: USD | P1: SECTOR | Q1: Column17 | R1: Column18
A2: 45961 | B2: WORMS 2 | C2: MT-0001 | D2: -90094560 | E2: AFE (AL) | F2: 72.4 | G2: 850 | H2: TN | I2: MATERIA PRIMA | J2: OPEX | K2: VARIABLE | L2: DIRECTO | N2: CC11 | O2: 1464 | P2: EXPORTACION
A3: 45961 | B3: WORMS 2 | C3: MT-0002 | D3: -5861856 | E3: AFE (G) | F3: 4.4 | G3: 910 | H3: TN | I3: MATERIA PRIMA | J3: OPEX | K3: VARIABLE | L3: DIRECTO | N3: CC11 | O3: 1464 | P3: EXPORTACION
A4: 45961 | B4: WORMS 2 | C4: MT-0003 | D4: -59830752 | E4: AFE (P) | F4: 60.1 | G4: 680 | H4: TN | I4: MATERIA PRIMA | J4: OPEX | K4: VARIABLE | L4: DIRECTO | N4: CC11 | O4: 1464 | P4: EXPORTACION
A5: 45961 | B5: WORMS 2 | C5: MT-0004 | D5: -3029264148 | E5: AFE (S) | F5: 2236.94 | G5: 925 | H5: TN | I5: MATERIA PRIMA | J5: OPEX | K5: VARIABLE | L5: DIRECTO | N5: CC11 | O5: 1464 | P5: EXPORTACION
A6: 45961 | B6: WORMS 1 | C6: MT-0005 | D6: 0 | E6: AG- A | G6: 850 | H6: TN | I6: MATERIA PRIMA | J6: OPEX | K6: VARIABLE | L6: DIRECTO | N6: CC11 | O6: 1464 | P6: EXPORTACION
A7: 45961 | B7: WORMS 1 | C7: MT-0006 | D7: -24537811 | E7: AG- B | F7: 20.44 | G7: 820 | H7: TN | I7: MATERIA PRIMA | J7: OPEX | K7: VARIABLE | L7: DIRECTO | N7: CC11 | O7: 1464 | P7: EXPORTACION
A8: 45961 | B8: WORMS 1 | C8: MT-0007 | D8: -12127190 | E8: AG- C | F8: 15.34 | G8: 540 | H8: TN | I8: MATERIA PRIMA | J8: OPEX | K8: VARIABLE | L8: DIRECTO | N8: CC11 | O8: 1464 | P8: EXPORTACION
A9: 45961 | B9: WORMS 1 | C9: MT-0008 | D9: 0 | E9: ARE- A | G9: 820 | H9: TN | I9: MATERIA PRIMA | J9: OPEX | K9: VARIABLE | L9: DIRECTO | N9: CC11 | O9: 1464 | P9: EXPORTACION
A10: 45961 | B10: WORMS 1 | C10: MT-0009 | D10: 0 | E10: ARE- B | G10: 820 | H10: TN | I10: MATERIA PRIMA | J10: OPEX | K10: VARIABLE | L10: DIRECTO | N10: CC11 | O10: 1464 | P10: EXPORTACION
A11: 45961 | B11: WORMS 2 | C11: MT-0010 | D11: -246338496 | E11: ARE- A | F11: 205.2 | G11: 820 | H11: TN | I11: MATERIA PRIMA | J11: OPEX | K11: VARIABLE | L11: DIRECTO | N11: CC11 | O11: 1464 | P11: EXPORTACION
A12: 45961 | B12: WORMS 2 | C12: MT-0011 | D12: 0 | E12: ARE- B | G12: 820 | H12: TN | I12: MATERIA PRIMA | J12: OPEX | K12: VARIABLE | L12: DIRECTO | N12: CC11 | O12: 1464 | P12: EXPORTACION
A13: 45961 | B13: WORMS 2 | C13: MT-0012 | D13: -117570912 | E13: AG- A | F13: 94.48 | G13: 850 | H13: TN | I13: MATERIA PRIMA | J13: OPEX | K13: VARIABLE | L13: DIRECTO | N13: CC11 | O13: 1464 | P13: EXPORTACION
A14: 45961 | B14: WORMS 2 | C14: MT-0013 | D14: 0 | E14: AG- B | G14: 820 | H14: TN | I14: MATERIA PRIMA | J14: OPEX | K14: VARIABLE | L14: DIRECTO | N14: CC11 | O14: 1464 | P14: EXPORTACION
A15: 45961 | B15: WORMS 2 | C15: MT-0014 | D15: -8300880 | E15: AG- C | F15: 10.5 | G15: 540 | H15: TN | I15: MATERIA PRIMA | J15: OPEX | K15: VARIABLE | L15: DIRECTO | N15: CC11 | O15: 1464 | P15: EXPORTACION
A16: 45961 | B16: WORMS 2 | C16: MT-0021 | D16: -91072512 | E16: AG- C | F16: 115.2 | G16: 540 | H16: TN | I16: MATERIA PRIMA | J16: OPEX | K16: VARIABLE | L16: DIRECTO | N16: CC5 | O16: 1464 | P16: REACTORES
A17: 45961 | B17: WORMS 1 | C17: MT-0022 | D17: 0 | E17: AG- C | G17: 540 | H17: TN | I17: MATERIA PRIMA | J17: OPEX | K17: VARIABLE | L17: DIRECTO | N17: CC5 | O17: 1464 | P17: REACTORES
A18: 45961 | B18: WORMS 2 | C18: MT-0023 | D18: -1.6548757e+08 | E18: AG - E | F18: 124.32 | G18: 909.25 | H18: TN | I18: MATERIA PRIMA | J18: OPEX | K18: VARIABLE | L18: DIRECTO | N18: CC11 | O18: 1464 | P18: EXPORTACION
A19: 45961 | B19: WORMS 2 | C19: MT-0024 | D19: 0 | E19: SEBO C - 2da | G19: 760 | H19: TN | I19: MATERIA PRIMA | J19: OPEX | K19: VARIABLE | L19: DIRECTO | N19: CC5 | O19: 1464 | P19: REACTORES
A20: 45961 | B20: WORMS 2 | C20: MT-0025 | D20: 0 | E20: BORRA A VEGETAL | F20: 126.22 | H20: TN | I20: MATERIA PRIMA | J20: OPEX | K20: VARIABLE | L20: DIRECTO | N20: CC6 | O20: 1464 | P20: BACHAS
A21: 45961 | B21: WORMS 2 | C21: MT-0026 | D21: 0 | E21: FONDO TK | F21: 22.2 | H21: TN | I21: MATERIA PRIMA | J21: OPEX | K21: VARIABLE | L21: DIRECTO | N21: CC6 | O21: 1464 | P21: BACHAS
A22: 45961 | B22: WORMS 2 | C22: MT-0027 | D22: 0 | E22: BORRA ANIMAL | F22: 34.1 | H22: TN | I22: MATERIA PRIMA | J22: OPEX | K22: VARIABLE | L22: DIRECTO | N22: CC6 | O22: 1464 | P22: BACHAS
A23: 45961 | B23: WORMS 2 | C23: MT-0028 | D23: 0 | E23: BORRA PESCADO | F23: 86.28 | H23: TN | I23: MATERIA PRIMA | J23: OPEX | K23: VARIABLE | L23: DIRECTO | N23: CC6 | O23: 1464 | P23: BACHAS
A24: 45961 | B24: WORMS 1 | C24: MT-0029 | D24: -26088480 | E24: EMULSION | F24: 35.64 | G24: 500 | H24: TN | I24: MATERIA PRIMA | J24: OPEX | K24: VARIABLE | L24: DIRECTO | N24: CC6 | O24: 1464 | P24: BACHAS
A25: 45961 | B25: WORMS 1 | C25: MT-0030 | D25: -60214320 | E25: AG-D | F25: 82.26 | G25: 500 | H25: TN | I25: MATERIA PRIMA | J25: OPEX | K25: VARIABLE | L25: DIRECTO | N25: CC6 | O25: 1464 | P25: BACHAS
A26: 45961 | B26: Martins, Joaquin | C26: AD-0001 | D26: 0 | E26: ENERGIA GASOIL G3 | G26: 1754 | H26: Lts | I26: ENERGIA | J26: OPEX | K26: VARIABLE | L26: DIRECTO | N26: CC1 | O26: 1 | P26: GENERAL
A27: 45961 | B27: Martins, Joaquin | C27: AD-0001 | D27: -2679040 | E27: ENERGIA G2 | F27: 1820 | G27: 1472 | H27: Lts | I27: ENERGIA | J27: OPEX | K27: VARIABLE | L27: DIRECTO | N27: CC6 | O27: 1 | P27: BACHAS
A28: 45961 | B28: Martins, Joaquin | C28: AD-0001 | D28: 0 | E28: ENERGIA G2 | F28: 0 | G28: 1472 | H28: Lts | I28: ENERGIA | J28: OPEX | K28: VARIABLE | L28: DIRECTO | N28: CC5 | O28: 1 | P28: REACTORES
A29: 45961 | B29: Martins, Joaquin | C29: AD-0001 | D29: -149500 | E29: ENERGIA Nafta | F29: 100 | G29: 1495 | H29: Lts | I29: ENERGIA | J29: OPEX | K29: VARIABLE | L29: DIRECTO | N29: CC6 | O29: 1 | P29: BACHAS
A30: 45961 | B30: Martins, Joaquin | C30: AD-0001 | D30: -1644500 | E30: ENERGIA Nafta | F30: 1100 | G30: 1495 | H30: Lts | I30: ENERGIA | J30: OPEX | K30: VARIABLE | L30: DIRECTO | N30: CC4 | O30: 1 | P30: PILETAS
A31: 45961 | B31: Martins, Joaquin | C31: AD-0001 | D31: -448500 | E31: ENERGIA Nafta | F31: 300 | G31: 1495 | H31: Lts | I31: ENERGIA | J31: OPEX | K31: VARIABLE | L31: DIRECTO | N31: CC3 | O31: 1 | P31: DISP FINAL RESIDUOS LIQUIDOS
A32: 45961 | B32: Ultraonix Srl | C32: AD-0001 | D32: -17241774 | E32: ENERGIA Fuel Oil | F32: 28050 | G32: 614.68 | H32: KG | I32: ENERGIA | J32: OPEX | K32: VARIABLE | L32: DIRECTO | N32: CC5 | O32: 1 | P32: REACTORES
A33: 45961 | B33: Ultraonix Srl | C33: AD-0001 | D33: -5808726 | E33: ENERGIA Fuel Oil | F33: 9450 | G33: 614.68 | H33: KG | I33: ENERGIA | J33: OPEX | K33: VARIABLE | L33: DIRECTO | N33: CC6 | O33: 1 | P33: BACHAS
A34: 45961 | B34: Total Quimica S.A. | C34: AD-0001 | D34: -7342440.6 | E34: INSUMOS Acido Sulfúrico 70/80 | F34: 19860 | G34: 369.71 | H34: KG | I34: INSUMOS | J34: OPEX | K34: VARIABLE | L34: DIRECTO | N34: CC6 | O34: 1 | P34: BACHAS
A35: 45961 | B35: Total Quimica S.A. | C35: AD-0001 | D35: -547520 | E35: INSUMOS Acido Clorhidrico | F35: 1180 | G35: 464 | H35: KG | I35: INSUMOS | J35: OPEX | K35: VARIABLE | L35: DIRECTO | N35: CC6 | O35: 1 | P35: BACHAS
A36: 45961 | B36: Total Quimica S.A. | C36: AD-0001 | D36: -691147.5 | E36: INSUMOS Soda Caustica | F36: 750 | G36: 921.53 | H36: KG | I36: INSUMOS | J36: OPEX | K36: VARIABLE | L36: DIRECTO | N36: CC5 | O36: 1 | P36: REACTORES
A37: 45961 | B37: Salinera Jaisal S. A. | C37: AD-0001 | D37: -59774 | E37: INSUMOS Cloruro de Sodio (SAL) | F37: 520 | G37: 114.95 | H37: KG | I37: INSUMOS | J37: OPEX | K37: VARIABLE | L37: DIRECTO | N37: CC6 | O37: 1 | P37: BACHAS
A38: 45961 | B38: Cremer Y Asociados Sociedad Anonima | C38: AD-0001 | D38: -11525588 | E38: INSUMOS Glicerina cruda | F38: 28.75 | G38: 400890 | H38: TN | I38: INSUMOS | J38: OPEX | K38: VARIABLE | L38: DIRECTO | N38: CC5 | O38: 1 | P38: REACTORES
... A40: 45961 | B40: Mercomar SA | C40: AD-0001 | D40: 0 | E40: LOGISTICA | F40: 852.25 | G40: 0 | H40: TN | I40: SERVICIOS | J40: OPEX | K40: VARIABLE | L40: DIRECTO | N40: CC11 | O40: 0 | P40: EXPORTACION
A41: 45961 | B41: Transportes Padilla Sociedad Anonima | C41: AD-0001 | D41: -27700560 | E41: LOGISTICA | F41: 876.6 | G41: 31600 | H41: TN | I41: SERVICIOS | J41: OPEX | K41: VARIABLE | L41: DIRECTO | N41: CC11 | O41: 1 | P41: EXPORTACION | R41: 220
A42: 45961 | B42: Cronos Soluciones Sustentables Sa | C42: AD-0001 | D42: -11261875 | E42: LOGISTICA | F42: 608.75 | G42: 18500 | H42: TN | I42: LOGISTICA | J42: OPEX | K42: VARIABLE | L42: DIRECTO | N42: CC11 | O42: 1 | P42: EXPORTACION
A43: 45961 | B43: Transporte Automotor El Loco Srl | C43: AD-0001 | D43: -1850600 | E43: LOGISTICA | F43: 97.4 | G43: 19000 | H43: TN | I43: LOGISTICA | J43: OPEX | K43: VARIABLE | L43: DIRECTO | N43: CC11 | O43: 1 | P43: EXPORTACION
A44: 45961 | B44: Energia Del Sur Srl | C44: AD-0001 | D44: -1461000 | E44: LOGISTICA | F44: 97.4 | G44: 15000 | H44: TN | I44: LOGISTICA | J44: OPEX | K44: VARIABLE | L44: DIRECTO | N44: CC11 | O44: 1 | P44: EXPORTACION
A45: 45961 | B45: Duport Sociedad De Responsabilidad Limitada | C45: AD-0001 | D45: -3798600 | E45: LOGISTICA | F45: 194.8 | G45: 19500 | H45: TN | I45: LOGISTICA | J45: OPEX | K45: VARIABLE | L45: DIRECTO | N45: CC11 | O45: 1 | P45: EXPORTACION
A46: 45961 | B46: Cooperativa De Trabajo Comercio Exterior Limitada | C46: AD-0001 | D46: -35141856 | E46: LOGISTICA | F46: 2824 | G46: 8.5 | H46: TN | I46: LOGISTICA | J46: OPEX | K46: VARIABLE | L46: DIRECTO | N46: CC11 | O46: 1464 | P46: EXPORTACION
A47: 45961 | B47: Exolgan Sociedad Anonima | C47: AD-0001 | D47: -21109140 | E47: LOGISTICA | F47: 36 | G47: 586365 | H47: UN | I47: SERVICIOS | J47: OPEX | K47: VARIABLE | L47: DIRECTO | N47: CC11 | O47: 1 | P47: EXPORTACION
A48: 45961 | B48: Pigini, Norberto Omar Marino | C48: AD-0001 | D48: -6030000 | E48: LOGISTICA | F48: 9 | G48: 670000 | H48: UN | I48: LOGISTICA | J48: OPEX | K48: VARIABLE | L48: DIRECTO | N48: CC7 | O48: 1 | P48: NFU
A49: 45961 | B49: Bernis, Carlos Oscar | C49: AD-0001 | D49: -4000000 | E49: LOGISTICA | F49: 5 | G49: 800000 | H49: UN | I49: LOGISTICA | J49: OPEX | K49: VARIABLE | L49: DIRECTO | N49: CC7 | O49: 1 | P49: NFU
A50: 45961 | B50: Bunge Argentina S A | C50: AD-0001 | D50: -97514 | E50: MATERIA PRIMA | F50: 975140 | G50: 0.1 | H50: UN | I50: MATERIA PRIMA | J50: OPEX | K50: VARIABLE | L50: DIRECTO | N50: CC2 | O50: 1 | P50: DISPOSICIÓN FINAL RESIDUOS SOLIDOS
A51: 45961 | B51: WORMS 2 | D51: 0 | E51: AFE (SG) | F51: 173.32 | H51: TN | I51: MATERIA PRIMA | J51: OPEX | K51: VARIABLE | L51: DIRECTO | N51: NO | O51: 1464 | P51: REACTORES
A52: 45961 | B52: WORMS 2 | D52: 0 | E52: AFE (P) | F52: 18.36 | H52: TN | I52: MATERIA PRIMA | J52: OPEX | K52: VARIABLE | L52: DIRECTO | N52: NO | O52: 1464 | P52: REACTORES

Sheet gastos_facturas
A1: Fecha de Factura/Recibo | B1: Nombre de la empresa a mostrar en la factura | C1: Número | D1: Total con signo | E1: Líneas de factura/Etiqueta | F1: Líneas de factura/Cantidad | G1: Líneas de factura/Precio unitario | H1: Líneas de factura/Unidad de medida | I1: Líneas de factura/Producto | J1: Concepto | K1: Tipo de Gasto 1 | L1: Tipo de Gasto 2 | M1: CCO EMPRESA | N1: CCO - SECTOR | O1: Column15
A2: 45958 | B2: H.S.E. Ingenieria S R L | C2: FA-A 00003-00027849 | D2: -3315400 | E2: OC 0001-00001756: SERVICIOS Monitoreo | F2: 1 | G2: 2740000 | H2: UN | I2: SERVICIOS | J2: OPEX | K2: VARIABLE | L2: INDIRECTO | N2: CC1
A3: 45933 | B3: Alvarez, Alejandro Dario | C3: FA-C 00002-00000250 | D3: -509644 | E3: OC 0001-00001364: HIGIENE Y SEGURIDAD Servicio de asesoramiento para la gestión ambiental en el cumplimiento de la normativa vigente para la provincia de Santa Fe. Servicio de higiene y seguridad de trabajo con cumplimiento de actividades s/Resol. SRT 905/15- MES 09/2025 | F3: 1 | G3: 509644 | H3: UN | I3: HIGIENE Y SEGURIDAD | J3: OPEX | K3: FIJO | L3: DIRECTO | N3: CC1
A4: 45931 | B4: Quiroz, Maria Ines | C4: FA-C 00002-00000031 | D4: -2097200 | E4: OC 0001-00001801: PERSONAL horas soldador | F4: 1 | G4: 2097200 | H4: UN | I4: PERSONAL | J4: OPEX | K4: FIJO | L4: INDIRECTO | N4: CC1
A5: 45947 | B5: Lopez, Jesus Rodrigo | C5: OCOM/2025/0470 | D5: -180000 | E5: OC 0001-00001345: LOGISTICA puerto | F5: 1 | G5: 180000 | H5: UN | I5: LOGISTICA | J5: OPEX | K5: VARIABLE | L5: DIRECTO | N5: CC9
A6: 45938 | B6: Lopez, Jesus Rodrigo | C6: OCOM/2025/0458 | D6: -180000 | E6: OC 0001-00001804: LOGISTICA | F6: 1 | G6: 180000 | H6: UN | I6: LOGISTICA | J6: OPEX | K6: VARIABLE | L6: DIRECTO | N6: CC9
A7: 45931 | B7: Lopez, Jesus Rodrigo | C7: OCOM/2025/0443 | D7: -156000 | E7: OC 0001-00000944: LOGISTICA | F7: 1 | G7: 156000 | H7: UN | I7: LOGISTICA | J7: OPEX | K7: VARIABLE | L7: DIRECTO | N7: CC9
A8: 45950 | B8: Area Abierta S.A. | C8: FA-A 00001-00001146 | D8: -798367.68 | E8: OC 0001-00001924: REPOSICION paño zda luz 6.50 2.50 mm 4 x1,60 metros (NFU) | F8: 1 | G8: 659808 | H8: UN | I8: REPOSICION | J8: OPEX | K8: VARIABLE | L8: DIRECTO | N8: CC7
A9: 45958 | B9: Bernis, Carlos Oscar | C9: FA-A 00006-00000175 | D9: -968000 | E9: OC 0001-00002255: LOGISTICA Viaje realizado fecha 28/10 | F9: 1 | G9: 800000 | H9: UN | I9: LOGISTICA | J9: OPEX | K9: VARIABLE | L9: DIRECTO | N9: CC7
A10: 45952 | B10: Bernis, Carlos Oscar | C10: FA-A 00006-00000174 | D10: -968000 | E10: OC 0001-00002218: LOGISTICA Viaje realizado fecha 20-10 worms - Parque industrial guernica | F10: 1 | G10: 800000 | H10: UN | I10: LOGISTICA | J10: OPEX | K10: VARIABLE | L10: DIRECTO | N10: CC7
A11: 45939 | B11: Bernis, Carlos Oscar | C11: FA-A 00006-00000171 | D11: -302500 | E11: OC 0001-00001836: LOGISTICA Viaje: 4 de septiembre origen: lujan worms con cubiertas en desuso . Destino :worms | F11: 1 | G11: 250000 | H11: UN | I11: LOGISTICA | J11: OPEX | K11: VARIABLE | L11: DIRECTO | N11: CC7
A12: 45939 | B12: Bernis, Carlos Oscar | C12: FA-A 00006-00000170 | D12: -968000 | E12: OC 0001-00002228: LOGISTICA Viaje realizado fecha 8/10 neumáticos | F12: 1 | G12: 800000 | H12: UN | I12: LOGISTICA | J12: OPEX | K12: VARIABLE | L12: DIRECTO | N12: CC7
A13: 45958 | B13: Comercial Uritorco S. R. L. (w) | C13: FA-A 00001-00007089 | D13: -66182.16 | E13: OC 0001-00002229: REPOSICION Adaptador 3/4 | F13: 2 | G13: 19578.51 | H13: UN | I13: REPOSICION | J13: OPEX | K13: VARIABLE | L13: INDIRECTO | N13: CC7
... A77: 45932 | B77: Acosta, Roberto Maximiliano | C77: FA-C 00001-00000616 | D77: -4632990 | E77: OC 0001-00001709: SERVICIOS de limpieza +ipc julio y agosto 3,8% | F77: 1 | G77: 4632990 | H77: UN | I77: SERVICIOS | J77: OPEX | K77: VARIABLE | L77: INDIRECTO | N77: CC1
A78: 45931 | B78: Adhoc S.A. | C78: FA-A 00003-00019779 | D78: -2004596.6 | E78: OC 0001-00001367: SERVICIOS Sistema contable | F78: 1 | G78: 1656691.4 | H78: UN | I78: SERVICIOS | J78: OPEX | K78: FIJO | L78: INDIRECTO | M78: CC13 | N78: CC1
A79: 45950 | B79: American Express Argentina S. A. | C79: OCOM/2025/0472 | D79: -344000.85 | E79: OC 0001-00001936: PERSONAL | F79: 1 | G79: 344000.85 | H79: UN | I79: PERSONAL | J79: OPEX | K79: VARIABLE | L79: INDIRECTO | N79: CC1
A80: 45949 | B80: Amx Argentina Sociedad Anonima | C80: FA-A 01331-01351660 | D80: -40348.6 | E80: OC 0001-00002225: SERVICIOS Servicio Móvil | F80: 1 | G80: 10605 | H80: UN | I80: SERVICIOS | J80: OPEX | K80: VARIABLE | L80: INDIRECTO | N80: CC1
A81: 45931 | B81: Aranda, Marisa Isabel | C81: FA-C 00005-00000212 | D81: -720000 | E81: OC 0001-00001711: SERVICIOS servicio de parquización | F81: 9 | G81: 80000 | H81: UN | I81: SERVICIOS | J81: OPEX | K81: VARIABLE | L81: INDIRECTO | N81: CC1
A82: 45952 | B82: ARCA | C82: OCOM/2025/0481 | D82: -3840846 | E82: OC 0001-00002049: IMPUESTOS anticipo | F82: 1 | G82: 3840846 | H82: UN | I82: IMPUESTOS | J82: OPEX | K82: VARIABLE | L82: INDIRECTO | N82: CC1
A83: 45952 | B83: ARCA | C83: OCOM/2025/0479 | D83: -1311921.2 | E83: OC 0001-00002043: IMPUESTOS Multa suse | F83: 1 | G83: 1311921.2 | H83: UN | I83: IMPUESTOS | J83: DEUDA | K83: VARIABLE | L83: INDIRECTO | N83: CC1
A84: 45946 | B84: ARCA | C84: OCOM/2025/0466 | D84: -552778.24 | E84: OC 0001-00001904: HONORARIOS Didomenico | F84: 1 | G84: 552778.24 | H84: UN | I84: HONORARIOS | J84: DEUDA | K84: VARIABLE | L84: INDIRECTO | N84: CC1
A85: 45946 | B85: ARCA | C85: OCOM/2025/0464 | D85: -15235035 | E85: OC 0001-00001869: IMPUESTOS Deuda, Planes de pago | F85: 1 | G85: 15235035 | H85: UN | I85: IMPUESTOS | J85: DEUDA | K85: VARIABLE | L85: INDIRECTO | N85: CC1
A86: 45954 | B86: Asociacion Empleados De Comercio De Rosario | C86: OCOM/2025/0504 | D86: -1383181 | E86: OC 0001-00002124: SERVICIOS | F86: 1 | G86: 1383181 | H86: UN | I86: SERVICIOS | J86: DEUDA | K86: VARIABLE | L86: INDIRECTO | N86: CC1
A87: 45951 | B87: Asociacion Mutual 23 De Setiembre | C87: OCOM/2025/0477 | D87: -10000000 | E87: OC 0001-00002032: SERVICIOS mutual | F87: 1 | G87: 10000000 | H87: UN | I87: SERVICIOS | J87: DEUDA | K87: VARIABLE | L87: INDIRECTO | N87: CC1
A88: 45931 | B88: Berardi, Alberto Jose - | C88: FA-C 00005-00000184 | D88: -560000 | E88: OC 0001-00001696: SERVICIOS Abono mensual | F88: 1 | G88: 560000 | H88: UN | I88: SERVICIOS | J88: OPEX | K88: VARIABLE | L88: INDIRECTO | N88: CC1
A89: 45943 | B89: Bollini, Tomas Maria | C89: OCOM/2025/0461 | D89: -114000 | E89: OC 0001-00001835: PERSONAL CARTA DOCUMENTO | F89: 1 | G89: 114000 | H89: UN | I89: PERSONAL | J89: OPEX | K89: VARIABLE | L89: INDIRECTO | N89: CC1
A90: 45937 | B90: Castelli, Guillermo Alejandro | C90: OCOM/2025/0457 | D90: -1500000 | E90: OC 0001-00001799: PERSONAL personal, acuerdo. | F90: 1 | G90: 1500000 | H90: UN | I90: PERSONAL | J90: DEUDA | K90: VARIABLE | L90: INDIRECTO | N90: CC1
... A148: 45931 | B148: Union Emergencias Regionales S A Acion | C148: FA-A 00005-00015075 | D148: -468967.64 | E148: OC 0001-00001362: SERVICIOS Amas Octubre 2025 | F148: 1 | G148: 424405.1 | H148: UN | I148: SERVICIOS | J148: OPEX | K148: VARIABLE | L148: INDIRECTO | N148: CC1

Sheet BBDD_GASTOS_FINAL
A1: Fecha de Factura/Recibo | B1: Nombre de la empresa a mostrar en la factura | C1: Número | D1: Total con signo | E1: Líneas de factura/Etiqueta | F1: Líneas de factura/Cantidad | G1: Líneas de factura/Precio unitario | H1: Líneas de factura/Unidad de medida | I1: RUBRO | J1: Concepto | K1: Tipo de Gasto 1 | L1: Tipo de Gasto 2 | M1: CCO LOTE | N1: CCO - SECTOR | O1: Column15 | P1: lote | Q1: Origen | R1: LOTES | S1: prc_lote | T1: etapas | U1: prc_etapa | V1: lote_desglosado | W1: etapa_desglosada | X1: peso_lote | Y1: peso_etapa | Z1: Total_desglosado | AA1: Cantidad_desglosada | AB1: rubro_id | AC1: rubro_final | AD1: formu_nutri_0 | AE1: formu_final | AF1: id_ | AG1: id_2 | AH1: precio_ars | AI1: usado | AJ1: total_nuevo | AK1: total_viejo | AL1: var
A2: 46022 | B2: SITIO 3 | C2: 2925 | D2: -14580646 | E2: 2925-{desarrollo}-{capones} | F2: 37760 | G2: 386.14 | H2: Kg. | I2: {desarrollo} | J2: Opex | K2: VARIABLE | L2: =IF(K2="variable","DIRECTO","INDIRECTO") -> DIRECTO | M2: 2925 | N2: CC5 | O2: 0 | P2: 0 | Q2: nutricion_nico | R2: 2925 | S2: {1} | T2: SITIO 3 | U2: {1} | V2: 2925 | W2: SITIO 3 | X2: 1 | Y2: 1 | Z2: =AJ2*-1 -> -14274307 | AA2: 37760 | AB2: =_xlfn.XLOOKUP(I2,'rubros_id_opex '!A:A,'rubros_id_opex '!B:B) -> 1 | AC2: =_xlfn.XLOOKUP(AB2,'rubros_unicos'!B:B,'rubros_unicos'!A:A) -> NUTRICIÓN | AD2: =MID(E2,FIND("-",E2),LEN(E2)) -> -{desarrollo}-{capones} | AE2: =_xlfn.CONCAT(W2,AD2) -> SITIO 3-{desarrollo}-{capones} | AF2: =_xlfn.XLOOKUP(BBDD_GASTOS_FINAL!AE2,formula_ciclos!A:A,formula_ciclos!B:B) -> desarrollo_c_arveja | AG2: =IF(AF2="NO",_xlfn.XLOOKUP(AE2,formula_ciclos!A:A,formula_ciclos!E:E),AF2) -> desarrollo_c_arveja | AH2: =_xlfn.XLOOKUP(AG2,formulas!D:D,formulas!M:M) -> 378.0272 | AI2: 1 | AJ2: =AH2*F2 -> 14274307 | AK2: =F2*G2 -> 14580646 | AL2: =AJ2/AK2-1 -> -0.021009996
A3: 46022 | B3: SITIO 3 | C3: 3125 | D3: -15630947 | E3: 3125-{desarrollo}-{capones} | F3: 40480 | G3: 386.14 | H3: Kg. | I3: {desarrollo} | J3: Opex | K3: VARIABLE | L3: =IF(K3="variable","DIRECTO","INDIRECTO") -> DIRECTO | M3: 3125 | N3: CC5 | O3: 0 | P3: 0 | Q3: nutricion_nico | R3: 3125 | S3: {1} | T3: SITIO 3 | U3: {1} | V3: 3125 | W3: SITIO 3 | X3: 1 | Y3: 1 | Z3: =AJ3*-1 -> -15302541 | AA3: 40480 | AB3: =_xlfn.XLOOKUP(I3,'rubros_id_opex '!A:A,'rubros_id_opex '!B:B) -> 1 | AC3: =_xlfn.XLOOKUP(AB3,'rubros_unicos'!B:B,'rubros_unicos'!A:A) -> NUTRICIÓN | AD3: =MID(E3,FIND("-",E3),LEN(E3)) -> -{desarrollo}-{capones} | AE3: =_xlfn.CONCAT(W3,AD3) -> SITIO 3-{desarrollo}-{capones} | AF3: =_xlfn.XLOOKUP(BBDD_GASTOS_FINAL!AE3,formula_ciclos!A:A,formula_ciclos!B:B) -> desarrollo_c_arveja | AG3: =IF(AF3="NO",_xlfn.XLOOKUP(AE3,formula_ciclos!A:A,formula_ciclos!E:E),AF3) -> desarrollo_c_arveja | AH3: =_xlfn.XLOOKUP(AG3,formulas!D:D,formulas!M:M) -> 378.0272 | AI3: 1 | AJ3: =AH3*F3 -> 15302541 | AK3: =F3*G3 -> 15630947 | AL3: =AJ3/AK3-1 -> -0.021009996
A4: 46022 | B4: MATERNIDAD | C4: 2925 | D4: -473347.66 | E4: 2925-{fase0}-{lechones} | F4: 191 | G4: 2478.26 | H4: Kg. | I4: {fase0} | J4: Opex | K4: VARIABLE | L4: =IF(K4="variable","DIRECTO","INDIRECTO") -> DIRECTO | M4: 2925 | N4: CC3 | O4: 0 | P4: 0 | Q4: nutricion_nico | R4: 2925 | S4: {1} | T4: MATERNIDAD | U4: {1} | V4: 2925 | W4: MATERNIDAD | X4: 1 | Y4: 1 | Z4: =AJ4*-1 -> -427437.95 | AA4: 191 | AB4: =_xlfn.XLOOKUP(I4,'rubros_id_opex '!A:A,'rubros_id_opex '!B:B) -> 1 | AC4: =_xlfn.XLOOKUP(AB4,'rubros_unicos'!B:B,'rubros_unicos'!A:A) -> NUTRICIÓN | AD4: =MID(E4,FIND("-",E4),LEN(E4)) -> -{fase0}-{lechones} | AE4: =_xlfn.CONCAT(W4,AD4) -> MATERNIDAD-{fase0}-{lechones} | AF4: =_xlfn.XLOOKUP(BBDD_GASTOS_FINAL!AE4,formula_ciclos!A:A,formula_ciclos!B:B) -> NO | AG4: =IF(AF4="NO",_xlfn.XLOOKUP(AE4,formula_ciclos!A:A,formula_ciclos!E:E),AF4) -> E3 | AH4: =_xlfn.XLOOKUP(AG4,formulas!D:D,formulas!M:M,_xlfn.XLOOKUP(AG4,precios_mp_ac!A:A,precios_mp_ac!N:N)) -> 2237.895 | AI4: 1 | AJ4: =AH4*F4 -> 427437.95 | AK4: =F4*G4 -> 473347.66 | AL4: =AJ4/AK4-1 -> -0.09698942
A5: 46022 | B5: MATERNIDAD | C5: 3125 | D5: -490695.48 | E5: 3125-{fase0}-{lechones} | F5: 198 | G5: 2478.26 | H5: Kg. | I5: {fase0} | J5: Opex | K5: VARIABLE | L5: =IF(K5="variable","DIRECTO","INDIRECTO") -> DIRECTO | M5: 3125 | N5: CC3 | O5: 0 | P5: 0 | Q5: nutricion_nico | R5: 3125 | S5: {1} | T5: MATERNIDAD | U5: {1} | V5: 3125 | W5: MATERNIDAD | X5: 1 | Y5: 1 | Z5: =AJ5*-1 -> -443103.21 | AA5: 198 | AB5: =_xlfn.XLOOKUP(I5,'rubros_id_opex '!A:A,'rubros_id_opex '!B:B) -> 1 | AC5: =_xlfn.XLOOKUP(AB5,'rubros_unicos'!B:B,'rubros_unicos'!A:A) -> NUTRICIÓN | AD5: =MID(E5,FIND("-",E5),LEN(E5)) -> -{fase0}-{lechones} | AE5: =_xlfn.CONCAT(W5,AD5) -> MATERNIDAD-{fase0}-{lechones} | AF5: =_xlfn.XLOOKUP(BBDD_GASTOS_FINAL!AE5,formula_ciclos!A:A,formula_ciclos!B:B) -> NO | AG5: =IF(AF5="NO",_xlfn.XLOOKUP(AE5,formula_ciclos!A:A,formula_ciclos!E:E),AF5) -> E3 | AH5: =_xlfn.XLOOKUP(AG5,formulas!D:D,formulas!M:M,_xlfn.XLOOKUP(AG5,precios_mp_ac!A:A,precios_mp_ac!N:N)) -> 2237.895 | AI5: 1 | AJ5: =AH5*F5 -> 443103.21 | AK5: =F5*G5 -> 490695.48 | AL5: =AJ5/AK5-1 -> -0.09698942
A6: 46022 | B6: MATERNIDAD | C6: 2925 | D6: -919053.8 | E6: 2925-{fase1}-{lechones} | F6: 382 | G6: 2405.9 | H6: Kg. | I6: {fase1} | J6: Opex | K6: VARIABLE | L6: =IF(K6="variable","DIRECTO","INDIRECTO") -> DIRECTO | M6: 2925 | N6: CC3 | O6: 0 | P6: 0 | Q6: nutricion_nico | R6: 2925 | S6: {1} | T6: MATERNIDAD | U6: {1} | V6: 2925 | W6: MATERNIDAD | X6: 1 | Y6: 1 | Z6: =AJ6*-1 -> -836155.98 | AA6: 382 | AB6: =_xlfn.XLOOKUP(I6,'rubros_id_opex '!A:A,'rubros_id_opex '!B:B) -> 1 | AC6: =_xlfn.XLOOKUP(AB6,'rubros_unicos'!B:B,'rubros_unicos'!A:A) -> NUTRICIÓN | AD6: =MID(E6,FIND("-",E6),LEN(E6)) -> -{fase1}-{lechones} | AE6: =_xlfn.CONCAT(W6,AD6) -> MATERNIDAD-{fase1}-{lechones} | AF6: =_xlfn.XLOOKUP(BBDD_GASTOS_FINAL!AE6,formula_ciclos!A:A,formula_ciclos!B:B) -> NO | AG6: =IF(AF6="NO",_xlfn.XLOOKUP(AE6,formula_ciclos!A:A,formula_ciclos!E:E),AF6) -> E6 | AH6: =_xlfn.XLOOKUP(AG6,formulas!D:D,formulas!M:M,_xlfn.XLOOKUP(AG6,precios_mp_ac!A:A,precios_mp_ac!N:N)) -> 2188.89 | AI6: 1 | AJ6: =AH6*F6 -> 836155.98 | AK6: =F6*G6 -> 919053.8 | AL6: =AJ6/AK6-1 -> -0.090199094
A7: 46022 | B7: MATERNIDAD | C7: 3125 | D7: -952736.4 | E7: 3125-{fase1}-{lechones} | F7: 396 | G7: 2405.9 | H7: Kg. | I7: {fase1} | J7: Opex | K7: VARIABLE | L7: =IF(K7="variable","DIRECTO","INDIRECTO") -> DIRECTO | M7: 3125 | N7: CC3 | O7: 0 | P7: 0 | Q7: nutricion_nico | R7: 3125 | S7: {1} | T7: MATERNIDAD | U7: {1} | V7: 3125 | W7: MATERNIDAD | X7: 1 | Y7: 1 | Z7: =AJ7*-1 -> -866800.44 | AA7: 396 | AB7: =_xlfn.XLOOKUP(I7,'rubros_id_opex '!A:A,'rubros_id_opex '!B:B) -> 1 | AC7: =_xlfn.XLOOKUP(AB7,'rubros_unicos'!B:B,'rubros_unicos'!A:A) -> NUTRICIÓN | AD7: =MID(E7,FIND("-",E7),LEN(E7)) -> -{fase1}-{lechones} | AE7: =_xlfn.CONCAT(W7,AD7) -> MATERNIDAD-{fase1}-{lechones} | AF7: =_xlfn.XLOOKUP(BBDD_GASTOS_FINAL!AE7,formula_ciclos!A:A,formula_ciclos!B:B) -> NO | AG7: =IF(AF7="NO",_xlfn.XLOOKUP(AE7,formula_ciclos!A:A,formula_ciclos!E:E),AF7) -> E6 | AH7: =_xlfn.XLOOKUP(AG7,formulas!D:D,formulas!M:M,_xlfn.XLOOKUP(AG7,precios_mp_ac!A:A,precios_mp_ac!N:N)) -> 2188.89 | AI7: 1 | AJ7: =AH7*F7 -> 866800.44 | AK7: =F7*G7 -> 952736.4 | AL7: =AJ7/AK7-1 -> -0.090199094
A8: 46022 | B8: SITIO 2 | C8: 3125 | D8: -962360 | E8: 3125-{fase1}-{lechones} | F8: 400 | G8: 2405.9 | H8: Kg. | I8: {fase1} | J8: Opex | K8: VARIABLE | L8: =IF(K8="variable","DIRECTO","INDIRECTO") -> DIRECTO | M8: 3125 | N8: CC4 | O8: 0 | P8: 0 | Q8: nutricion_nico | R8: 3125 | S8: {1} | T8: SITIO 2 | U8: {1} | V8: 3125 | W8: SITIO 2 | X8: 1 | Y8: 1 | Z8: =AJ8*-1 -> -705672 | AA8: 400 | AB8: =_xlfn.XLOOKUP(I8,'rubros_id_opex '!A:A,'rubros_id_opex '!B:B) -> 1 | AC8: =_xlfn.XLOOKUP(AB8,'rubros_unicos'!B:B,'rubros_unicos'!A:A) -> NUTRICIÓN | AD8: =MID(E8,FIND("-",E8),LEN(E8)) -> -{fase1}-{lechones} | AE8: =_xlfn.CONCAT(W8,AD8) -> SITIO 2-{fase1}-{lechones} | AF8: =_xlfn.XLOOKUP(BBDD_GASTOS_FINAL!AE8,formula_ciclos!A:A,formula_ciclos!B:B) -> NO | AG8: =IF(AF8="NO",_xlfn.XLOOKUP(AE8,formula_ciclos!A:A,formula_ciclos!E:E),AF8) -> E7 | AH8: =_xlfn.XLOOKUP(AG8,formulas!D:D,formulas!M:M,_xlfn.XLOOKUP(AG8,precios_mp_ac!A:A,precios_mp_ac!N:N)) -> 1764.18 | AI8: 1 | AJ8: =AH8*F8 -> 705672 | AK8: =F8*G8 -> 962360 | AL8: =AJ8/AK8-1 -> -0.26672763
A9: 46022 | B9: SITIO 2 | C9: 2925 | D9: -4935729 | E9: 2925-{fase2}-{lechones} | F9: 2550 | G9: 1935.58 | H9: Kg. | I9: {fase2} | J9: Opex | K9: VARIABLE | L9: =IF(K9="variable","DIRECTO","INDIRECTO") -> DIRECTO | M9: 2925 | N9: CC4 | O9: 0 | P9: 0 | Q9: nutricion_nico | R9: 2925 | S9: {1} | T9: SITIO 2 | U9: {1} | V9: 2925 | W9: SITIO 2 | X9: 1 | Y9: 1 | Z9: =AJ9*-1 -> -4498659 | AA9: 2550 | AB9: =_xlfn.XLOOKUP(I9,'rubros_id_opex '!A:A,'rubros_id_opex '!B:B) -> 1 | AC9: =_xlfn.XLOOKUP(AB9,'rubros_unicos'!B:B,'rubros_unicos'!A:A) -> NUTRICIÓN | AD9: =MID(E9,FIND("-",E9),LEN(E9)) -> -{fase2}-{lechones} | AE9: =_xlfn.CONCAT(W9,AD9) -> SITIO 2-{fase2}-{lechones} | AF9: =_xlfn.XLOOKUP(BBDD_GASTOS_FINAL!AE9,formula_ciclos!A:A,formula_ciclos!B:B) -> NO | AG9: =IF(AF9="NO",_xlfn.XLOOKUP(AE9,formula_ciclos!A:A,formula_ciclos!E:E),AF9) -> E7 | AH9: =_xlfn.XLOOKUP(AG9,formulas!D:D,formulas!M:M,_xlfn.XLOOKUP(AG9,precios_mp_ac!A:A,precios_mp_ac!N:N)) -> 1764.18 | AI9: 1 | AJ9: =AH9*F9 -> 4498659 | AK9: =F9*G9 -> 4935729 | AL9: =AJ9/AK9-1 -> -0.088552269
A10: 46022 | B10: SITIO 2 | C10: 3125 | D10: -4258276 | E10: 3125-{fase2}-{lechones} | F10: 2200 | G10: 1935.58 | H10: Kg. | I10: {fase2} | J10: Opex | K10: VARIABLE | L10: =IF(K10="variable","DIRECTO","INDIRECTO") -> DIRECTO | M10: 3125 | N10: CC4 | O10: 0 | P10: 0 | Q10: nutricion_nico | R10: 3125 | S10: {1} | T10: SITIO 2 | U10: {1} | V10: 3125 | W10: SITIO 2 | X10: 1 | Y10: 1 | Z10: =AJ10*-1 -> -3881196 | AA10: 2200 | AB10: =_xlfn.XLOOKUP(I10,'rubros_id_opex '!A:A,'rubros_id_opex '!B:B) -> 1 | AC10: =_xlfn.XLOOKUP(AB10,'rubros_unicos'!B:B,'rubros_unicos'!A:A) -> NUTRICIÓN | AD10: =MID(E10,FIND("-",E10),LEN(E10)) -> -{fase2}-{lechones} | AE10: =_xlfn.CONCAT(W10,AD10) -> SITIO 2-{fase2}-{lechones} | AF10: =_xlfn.XLOOKUP(BBDD_GASTOS_FINAL!AE10,formula_ciclos!A:A,formula_ciclos!B:B) -> NO | AG10: =IF(AF10="NO",_xlfn.XLOOKUP(AE10,formula_ciclos!A:A,formula_ciclos!E:E),AF10) -> E7 | AH10: =_xlfn.XLOOKUP(AG10,formulas!D:D,formulas!M:M,_xlfn.XLOOKUP(AG10,precios_mp_ac!A:A,precios_mp_ac!N:N)) -> 1764.18 | AI10: 1 | AJ10: =AH10*F10 -> 3881196 | AK10: =F10*G10 -> 4258276 | AL10: =AJ10/AK10-1 -> -0.088552269
A11: 46022 | B11: SITIO 2 | C11: 2925 | D11: -2489770.5 | E11: 2925-{fase3}-{lechones} | F11: 4425 | G11: 562.66 | H11: Kg. | I11: {fase3} | J11: Opex | K11: VARIABLE | L11: =IF(K11="variable","DIRECTO","INDIRECTO") -> DIRECTO | M11: 2925 | N11: CC4 | O11: 0 | P11: 0 | Q11: nutricion_nico | R11: 2925 | S11: {1} | T11: SITIO 2 | U11: {1} | V11: 2925 | W11: SITIO 2 | X11: 1 | Y11: 1 | Z11: =AJ11*-1 -> -3170994.2 | AA11: 4425 | AB11: =_xlfn.XLOOKUP(I11,'rubros_id_opex '!A:A,'rubros_id_opex '!B:B) -> 1 | AC11: =_xlfn.XLOOKUP(AB11,'rubros_unicos'!B:B,'rubros_unicos'!A:A) -> NUTRICIÓN | AD11: =MID(E11,FIND("-",E11),LEN(E11)) -> -{fase3}-{lechones} | AE11: =_xlfn.CONCAT(W11,AD11) -> SITIO 2-{fase3}-{lechones} | AF11: =_xlfn.XLOOKUP(BBDD_GASTOS_FINAL!AE11,formula_ciclos!A:A,formula_ciclos!B:B) -> fase3 | AG11: =IF(AF11="NO",_xlfn.XLOOKUP(AE11,formula_ciclos!A:A,formula_ciclos!E:E),AF11) -> fase3 | AH11: =_xlfn.XLOOKUP(AG11,formulas!D:D,formulas!M:M,_xlfn.XLOOKUP(AG11,precios_mp_ac!A:A,precios_mp_ac!N:N)) -> 716.60885 | AI11: 1 | AJ11: =AH11*F11 -> 3170994.2 | AK11: =F11*G11 -> 2489770.5 | AL11: =AJ11/AK11-1 -> 0.27360902
A12: 46022 | B12: SITIO 2 | C12: 3125 | D12: -2630435.5 | E12: 3125-{fase3}-{lechones} | F12: 4675 | G12: 562.66 | H12: Kg. | I12: {fase3} | J12: Opex | K12: VARIABLE | L12: =IF(K12="variable","DIRECTO","INDIRECTO") -> DIRECTO | M12: 3125 | N12: CC4 | O12: 0 | P12: 0 | Q12: nutricion_nico | R12: 3125 | S12: {1} | T12: SITIO 2 | U12: {1} | V12: 3125 | W12: SITIO 2 | X12: 1 | Y12: 1 | Z12: =AJ12*-1 -> -3350146.4 | AA12: 4675 | AB12: =_xlfn.XLOOKUP(I12,'rubros_id_opex '!A:A,'rubros_id_opex '!B:B) -> 1 | AC12: =_xlfn.XLOOKUP(AB12,'rubros_unicos'!B:B,'rubros_unicos'!A:A) -> NUTRICIÓN | AD12: =MID(E12,FIND("-",E12),LEN(E12)) -> -{fase3}-{lechones} | AE12: =_xlfn.CONCAT(W12,AD12) -> SITIO 2-{fase3}-{lechones} | AF12: =_xlfn.XLOOKUP(BBDD_GASTOS_FINAL!AE12,formula_ciclos!A:A,formula_ciclos!B:B) -> fase3 | AG12: =IF(AF12="NO",_xlfn.XLOOKUP(AE12,formula_ciclos!A:A,formula_ciclos!E:E),AF12) -> fase3 | AH12: =_xlfn.XLOOKUP(AG12,formulas!D:D,formulas!M:M,_xlfn.XLOOKUP(AG12,precios_mp_ac!A:A,precios_mp_ac!N:N)) -> 716.60885 | AI12: 1 | AJ12: =AH12*F12 -> 3350146.4 | AK12: =F12*G12 -> 2630435.5 | AL12: =AJ12/AK12-1 -> 0.27360902
A13: 46022 | B13: SITIO 2 | C13: 2925 | D13: -569411.92 | E13: 2925-{fase4}-{lechones} | F13: 1012 | G13: 562.66 | H13: Kg. | I13: {fase4} | J13: Opex | K13: VARIABLE | L13: =IF(K13="variable","DIRECTO","INDIRECTO") -> DIRECTO | M13: 2925 | N13: CC4 | O13: 0 | P13: 0 | Q13: nutricion_nico | R13: 2925 | S13: {1} | T13: SITIO 2 | U13: {1} | V13: 2925 | W13: SITIO 2 | X13: 1 | Y13: 1 | Z13: =AJ13*-1 -> -543907.5 | AA13: 1012 | AB13: =_xlfn.XLOOKUP(I13,'rubros_id_opex '!A:A,'rubros_id_opex '!B:B) -> 1 | AC13: =_xlfn.XLOOKUP(AB13,'rubros_unicos'!B:B,'rubros_unicos'!A:A) -> NUTRICIÓN | AD13: =MID(E13,FIND("-",E13),LEN(E13)) -> -{fase4}-{lechones} | AE13: =_xlfn.CONCAT(W13,AD13) -> SITIO 2-{fase4}-{lechones} | AF13: =_xlfn.XLOOKUP(BBDD_GASTOS_FINAL!AE13,formula_ciclos!A:A,formula_ciclos!B:B) -> fase_4 | AG13: =IF(AF13="NO",_xlfn.XLOOKUP(AE13,formula_ciclos!A:A,formula_ciclos!E:E),AF13) -> fase_4 | AH13: =_xlfn.XLOOKUP(AG13,formulas!D:D,formulas!M:M,_xlfn.XLOOKUP(AG13,precios_mp_ac!A:A,precios_mp_ac!N:N)) -> 537.458 | AI13: 1 | AJ13: =AH13*F13 -> 543907.5 | AK13: =F13*G13 -> 569411.92 | AL13: =AJ13/AK13-1 -> -0.044790815
A14: 46022 | B14: SITIO 3 | C14: 2925 | D14: -6206139.8 | E14: 2925-{fase4}-{capones} | F14: 11030 | G14: 562.66 | H14: Kg. | I14: {fase4} | J14: Opex | K14: VARIABLE | L14: =IF(K14="variable","DIRECTO","INDIRECTO") -> DIRECTO | M14: 2925 | N14: CC5 | O14: 0 | P14: 0 | Q14: nutricion_nico | R14: 2925 | S14: {1} | T14: SITIO 3 | U14: {1} | V14: 2925 | W14: SITIO 3 | X14: 1 | Y14: 1 | Z14: =AJ14*-1 -> -5928161.7 | AA14: 11030 | AB14: =_xlfn.XLOOKUP(I14,'rubros_id_opex '!A:A,'rubros_id_opex '!B:B) -> 1 | AC14: =_xlfn.XLOOKUP(AB14,'rubros_unicos'!B:B,'rubros_unicos'!A:A) -> NUTRICIÓN | AD14: =MID(E14,FIND("-",E14),LEN(E14)) -> -{fase4}-{capones} | AE14: =_xlfn.CONCAT(W14,AD14) -> SITIO 3-{fase4}-{capones} | AF14: =_xlfn.XLOOKUP(BBDD_GASTOS_FINAL!AE14,formula_ciclos!A:A,formula_ciclos!B:B) -> fase_4 | AG14: =IF(AF14="NO",_xlfn.XLOOKUP(AE14,formula_ciclos!A:A,formula_ciclos!E:E),AF14) -> fase_4 | AH14: =_xlfn.XLOOKUP(AG14,formulas!D:D,formulas!M:M,_xlfn.XLOOKUP(AG14,precios_mp_ac!A:A,precios_mp_ac!N:N)) -> 537.458 | AI14: 1 | AJ14: =AH14*F14 -> 5928161.7 | AK14: =F14*G14 -> 6206139.8 | AL14: =AJ14/AK14-1 -> -0.044790815
A15: 46022 | B15: SITIO 2 | C15: 3125 | D15: -1423529.8 | E15: 3125-{fase4}-{lechones} | F15: 2530 | G15: 562.66 | H15: Kg. | I15: {fase4} | J15: Opex | K15: VARIABLE | L15: =IF(K15="variable","DIRECTO","INDIRECTO") -> DIRECTO | M15: 3125 | N15: CC4 | O15: 0 | P15: 0 | Q15: nutricion_nico | R15: 3125 | S15: {1} | T15: SITIO 2 | U15: {1} | V15: 3125 | W15: SITIO 2 | X15: 1 | Y15: 1 | Z15: =AJ15*-1 -> -1359768.7 | AA15: 2530 | AB15: =_xlfn.XLOOKUP(I15,'rubros_id_opex '!A:A,'rubros_id_opex '!B:B) -> 1 | AC15: =_xlfn.XLOOKUP(AB15,'rubros_unicos'!B:B,'rubros_unicos'!A:A) -> NUTRICIÓN | AD15: =MID(E15,FIND("-",E15),LEN(E15)) -> -{fase4}-{lechones} | AE15: =_xlfn.CONCAT(W15,AD15) -> SITIO 2-{fase4}-{lechones} | AF15: =_xlfn.XLOOKUP(BBDD_GASTOS_FINAL!AE15,formula_ciclos!A:A,formula_ciclos!B:B) -> fase_4 | AG15: =IF(AF15="NO",_xlfn.XLOOKUP(AE15,formula_ciclos!A:A,formula_ciclos!E:E),AF15) -> fase_4 | AH15: =_xlfn.XLOOKUP(AG15,formulas!D:D,formulas!M:M,_xlfn.XLOOKUP(AG15,precios_mp_ac!A:A,precios_mp_ac!N:N)) -> 537.458 | AI15: 1 | AJ15: =AH15*F15 -> 1359768.7 | AK15: =F15*G15 -> 1423529.8 | AL15: =AJ15/AK15-1 -> -0.044790815
... A20: 46022 | B20: MATERNIDAD | C20: 3125 | D20: -5100264 | E20: 3125-{lactancia}-{madres} | F20: 11700 | G20: 435.92 | H20: Kg. | I20: {lactancia} | J20: Opex | K20: VARIABLE | L20: =IF(K20="variable","DIRECTO","INDIRECTO") -> DIRECTO | M20: 3125 | N20: CC3 | O20: 0 | P20: 0 | Q20: nutricion_nico | R20: 3125 | S20: {1} | T20: MATERNIDAD | U20: {1} | V20: 3125 | W20: MATERNIDAD | X20: 1 | Y20: 1 | Z20: =AJ20*-1 -> -4958591 | AA20: 11700 | AB20: =_xlfn.XLOOKUP(I20,'rubros_id_opex '!A:A,'rubros_id_opex '!B:B) -> 1 | AC20: =_xlfn.XLOOKUP(AB20,'rubros_unicos'!B:B,'rubros_unicos'!A:A) -> NUTRICIÓN | AD20: =MID(E20,FIND("-",E20),LEN(E20)) -> -{lactancia}-{madres} | AE20: =_xlfn.CONCAT(W20,AD20) -> MATERNIDAD-{lactancia}-{madres} | AF20: =_xlfn.XLOOKUP(BBDD_GASTOS_FINAL!AE20,formula_ciclos!A:A,formula_ciclos!B:B) -> lactancia | AG20: =IF(AF20="NO",_xlfn.XLOOKUP(AE20,formula_ciclos!A:A,formula_ciclos!E:E),AF20) -> lactancia | AH20: =_xlfn.XLOOKUP(AG20,formulas!D:D,formulas!M:M,_xlfn.XLOOKUP(AG20,precios_mp_ac!A:A,precios_mp_ac!N:N)) -> 423.8112 | AI20: 1 | AJ20: =AH20*F20 -> 4958591 | AK20: =F20*G20 -> 5100264 | AL20: =AJ20/AK20-1 -> -0.027777574
A21: 46022 | B21: MATERNIDAD | C21: 2925 | D21: -134907.12 | E21: 2925-q_lechones/capones-{lechones} | F21: 678 | G21: 176.58 | H21: q_lechones/capones | I21: {lechones} | J21: Opex | K21: VARIABLE | L21: =IF(K21="variable","DIRECTO","INDIRECTO") -> DIRECTO | M21: 2925 | N21: CC3 | O21: 0 | P21: 0 | Q21: sanidad_nico | R21: 2925 | S21: {1} | T21: MATERNIDAD | U21: {1} | V21: 2925 | W21: MATERNIDAD | X21: 1 | Y21: 1 | Z21: -134907.12 | AA21: 678 | AB21: 3 | AC21: =_xlfn.XLOOKUP(AB21,'rubros_unicos'!B:B,'rubros_unicos'!A:A) -> SANIDAD
A22: 46022 | B22: SITIO 2 | C22: 2925 | D22: -2537247.1 | E22: 2925-q_lechones/capones-{lechones} | F22: 593 | G22: 4307.72 | H22: q_lechones/capones | I22: {lechones} | J22: Opex | K22: VARIABLE | L22: =IF(K22="variable","DIRECTO","INDIRECTO") -> DIRECTO | M22: 2925 | N22: CC4 | O22: 0 | P22: 0 | Q22: sanidad_nico | R22: 2925 | S22: {1} | T22: SITIO 2 | U22: {1} | V22: 2925 | W22: SITIO 2 | X22: 1 | Y22: 1 | Z22: -2537247.1 | AA22: 593 | AB22: 3 | AC22: =_xlfn.XLOOKUP(AB22,'rubros_unicos'!B:B,'rubros_unicos'!A:A) -> SANIDAD
A23: 46022 | B23: MATERNIDAD | C23: 3125 | D23: -139851.36 | E23: 3125-q_lechones/capones-{lechones} | F23: 811 | G23: 176.58 | H23: q_lechones/capones | I23: {lechones} | J23: Opex | K23: VARIABLE | L23: =IF(K23="variable","DIRECTO","INDIRECTO") -> DIRECTO | M23: 3125 | N23: CC3 | O23: 0 | P23: 0 | Q23: sanidad_nico | R23: 3125 | S23: {1} | T23: MATERNIDAD | U23: {1} | V23: 3125 | W23: MATERNIDAD | X23: 1 | Y23: 1 | Z23: -139851.36 | AA23: 811 | AB23: 3 | AC23: =_xlfn.XLOOKUP(AB23,'rubros_unicos'!B:B,'rubros_unicos'!A:A) -> SANIDAD
A24: 46022 | B24: SITIO 2 | C24: 3125 | D24: -2537247.1 | E24: 3125-q_lechones/capones-{lechones} | F24: 627 | G24: 4307.72 | H24: q_lechones/capones | I24: {lechones} | J24: Opex | K24: VARIABLE | L24: =IF(K24="variable","DIRECTO","INDIRECTO") -> DIRECTO | M24: 3125 | N24: CC4 | O24: 0 | P24: 0 | Q24: sanidad_nico | R24: 3125 | S24: {1} | T24: SITIO 2 | U24: {1} | V24: 3125 | W24: SITIO 2 | X24: 1 | Y24: 1 | Z24: -2537247.1 | AA24: 627 | AB24: 3 | AC24: =_xlfn.XLOOKUP(AB24,'rubros_unicos'!B:B,'rubros_unicos'!A:A) -> SANIDAD
A25: 46022 | B25: GESTACIÓN | C25: 2925 | D25: -602950.62 | E25: 2925-q_servicios-{madres} | F25: 56 | G25: 9725.01 | H25: q_servicios | I25: {madres} | J25: Opex | K25: VARIABLE | L25: =IF(K25="variable","DIRECTO","INDIRECTO") -> DIRECTO | M25: 2925 | N25: CC2 | O25: 0 | P25: 0 | Q25: sanidad_nico | R25: 2925 | S25: {1} | T25: GESTACIÓN | U25: {1} | V25: 2925 | W25: GESTACIÓN | X25: 1 | Y25: 1 | Z25: -602950.62 | AA25: 56 | AB25: 3 | AC25: =_xlfn.XLOOKUP(AB25,'rubros_unicos'!B:B,'rubros_unicos'!A:A) -> SANIDAD
A26: 46022 | B26: MATERNIDAD | C26: 2925 | D26: -217395.4 | E26: 2925-q_partos-{madres} | F26: 47 | G26: 4101.8 | H26: q_partos | I26: {madres} | J26: Opex | K26: VARIABLE | L26: =IF(K26="variable","DIRECTO","INDIRECTO") -> DIRECTO | M26: 2925 | N26: CC3 | O26: 0 | P26: 0 | Q26: sanidad_nico | R26: 2925 | S26: {1} | T26: MATERNIDAD | U26: {1} | V26: 2925 | W26: MATERNIDAD | X26: 1 | Y26: 1 | Z26: -217395.4 | AA26: 47 | AB26: 3 | AC26: =_xlfn.XLOOKUP(AB26,'rubros_unicos'!B:B,'rubros_unicos'!A:A) -> SANIDAD
A27: 46022 | B27: GESTACIÓN | C27: 3125 | D27: -593225.61 | E27: 3125-q_servicios-{madres} | F27: 58 | G27: 9725.01 | H27: q_servicios | I27: {madres} | J27: Opex | K27: VARIABLE | L27: =IF(K27="variable","DIRECTO","INDIRECTO") -> DIRECTO | M27: 3125 | N27: CC2 | O27: 0 | P27: 0 | Q27: sanidad_nico | R27: 3125 | S27: {1} | T27: GESTACIÓN | U27: {1} | V27: 3125 | W27: GESTACIÓN | X27: 1 | Y27: 1 | Z27: -593225.61 | AA27: 58 | AB27: 3 | AC27: =_xlfn.XLOOKUP(AB27,'rubros_unicos'!B:B,'rubros_unicos'!A:A) -> SANIDAD
A28: 46022 | B28: MATERNIDAD | C28: 3125 | D28: -213293.6 | E28: 3125-q_partos-{madres} | F28: 54 | G28: 4101.8 | H28: q_partos | I28: {madres} | J28: Opex | K28: VARIABLE | L28: =IF(K28="variable","DIRECTO","INDIRECTO") -> DIRECTO | M28: 3125 | N28: CC3 | O28: 0 | P28: 0 | Q28: sanidad_nico | R28: 3125 | S28: {1} | T28: MATERNIDAD | U28: {1} | V28: 3125 | W28: MATERNIDAD | X28: 1 | Y28: 1 | Z28: -213293.6 | AA28: 54 | AB28: 3 | AC28: =_xlfn.XLOOKUP(AB28,'rubros_unicos'!B:B,'rubros_unicos'!A:A) -> SANIDAD
A29: 46022 | B29: SITIO 3 | C29: 2925 | D29: -15423673 | E29: 2925-{t1}-{capones} | F29: 45240 | G29: 340.93 | H29: Kg. | I29: {t1} | J29: Opex | K29: VARIABLE | L29: =IF(K29="variable","DIRECTO","INDIRECTO") -> DIRECTO | M29: 2925 | N29: CC5 | O29: 0 | P29: 0 | Q29: nutricion_nico | R29: 2925 | S29: {1} | T29: SITIO 3 | U29: {1} | V29: 2925 | W29: SITIO 3 | X29: 1 | Y29: 1 | Z29: =AJ29*-1 -> -15147336 | AA29: 45240 | AB29: =_xlfn.XLOOKUP(I29,'rubros_id_opex '!A:A,'rubros_id_opex '!B:B) -> 1 | AC29: =_xlfn.XLOOKUP(AB29,'rubros_unicos'!B:B,'rubros_unicos'!A:A) -> NUTRICIÓN | AD29: =MID(E29,FIND("-",E29),LEN(E29)) -> -{t1}-{capones} | AE29: =_xlfn.CONCAT(W29,AD29) -> SITIO 3-{t1}-{capones} | AF29: =_xlfn.XLOOKUP(BBDD_GASTOS_FINAL!AE29,formula_ciclos!A:A,formula_ciclos!B:B) -> terminador_c_arveja_1a | AG29: =IF(AF29="NO",_xlfn.XLOOKUP(AE29,formula_ciclos!A:A,formula_ciclos!E:E),AF29) -> terminador_c_arveja_1a | AH29: =_xlfn.XLOOKUP(AG29,formulas!D:D,formulas!M:M) -> 334.82175 | AI29: 1 | AJ29: =AH29*F29 -> 15147336 | AK29: =F29*G29 -> 15423673 | AL29: =AJ29/AK29-1 -> -0.017916434
A30: 46022 | B30: SITIO 3 | C30: 3125 | D30: -15710054 | E30: 3125-{t1}-{capones} | F30: 46080 | G30: 340.93 | H30: Kg. | I30: {t1} | J30: Opex | K30: VARIABLE | L30: =IF(K30="variable","DIRECTO","INDIRECTO") -> DIRECTO | M30: 3125 | N30: CC5 | O30: 0 | P30: 0 | Q30: nutricion_nico | R30: 3125 | S30: {1} | T30: SITIO 3 | U30: {1} | V30: 3125 | W30: SITIO 3 | X30: 1 | Y30: 1 | Z30: =AJ30*-1 -> -15428586 | AA30: 46080 | AB30: =_xlfn.XLOOKUP(I30,'rubros_id_opex '!A:A,'rubros_id_opex '!B:B) -> 1 | AC30: =_xlfn.XLOOKUP(AB30,'rubros_unicos'!B:B,'rubros_unicos'!A:A) -> NUTRICIÓN | AD30: =MID(E30,FIND("-",E30),LEN(E30)) -> -{t1}-{capones} | AE30: =_xlfn.CONCAT(W30,AD30) -> SITIO 3-{t1}-{capones} | AF30: =_xlfn.XLOOKUP(BBDD_GASTOS_FINAL!AE30,formula_ciclos!A:A,formula_ciclos!B:B) -> terminador_c_arveja_1a | AG30: =IF(AF30="NO",_xlfn.XLOOKUP(AE30,formula_ciclos!A:A,formula_ciclos!E:E),AF30) -> terminador_c_arveja_1a | AH30: =_xlfn.XLOOKUP(AG30,formulas!D:D,formulas!M:M) -> 334.82175 | AI30: 1 | AJ30: =AH30*F30 -> 15428586 | AK30: =F30*G30 -> 15710054 | AL30: =AJ30/AK30-1 -> -0.017916434
A31: 46022 | B31: SITIO 3 | C31: 2925 | D31: -15149200 | E31: 2925-{t2}-{capones} | F31: 46056 | G31: 328.93 | H31: Kg. | I31: {t2} | J31: Opex | K31: VARIABLE | L31: =IF(K31="variable","DIRECTO","INDIRECTO") -> DIRECTO | M31: 2925 | N31: CC5 | O31: 0 | P31: 0 | Q31: nutricion_nico | R31: 2925 | S31: {1} | T31: SITIO 3 | U31: {1} | V31: 2925 | W31: SITIO 3 | X31: 1 | Y31: 1 | Z31: =AJ31*-1 -> -14922024 | AA31: 46056 | AB31: =_xlfn.XLOOKUP(I31,'rubros_id_opex '!A:A,'rubros_id_opex '!B:B) -> 1 | AC31: =_xlfn.XLOOKUP(AB31,'rubros_unicos'!B:B,'rubros_unicos'!A:A) -> NUTRICIÓN | AD31: =MID(E31,FIND("-",E31),LEN(E31)) -> -{t2}-{capones} | AE31: =_xlfn.CONCAT(W31,AD31) -> SITIO 3-{t2}-{capones} | AF31: =_xlfn.XLOOKUP(BBDD_GASTOS_FINAL!AE31,formula_ciclos!A:A,formula_ciclos!B:B) -> terminador_c_arveja_2b | AG31: =IF(AF31="NO",_xlfn.XLOOKUP(AE31,formula_ciclos!A:A,formula_ciclos!E:E),AF31) -> terminador_c_arveja_2b | AH31: =_xlfn.XLOOKUP(AG31,formulas!D:D,formulas!M:M) -> 323.9974 | AI31: 1 | AJ31: =AH31*F31 -> 14922024 | AK31: =F31*G31 -> 15149200 | AL31: =AJ31/AK31-1 -> -0.014995896
A32: 46022 | B32: SITIO 3 | C32: 3125 | D32: -17813533 | E32: 3125-{t2}-{capones} | F32: 54156 | G32: 328.93 | H32: Kg. | I32: {t2} | J32: Opex | K32: VARIABLE | L32: =IF(K32="variable","DIRECTO","INDIRECTO") -> DIRECTO | M32: 3125 | N32: CC5 | O32: 0 | P32: 0 | Q32: nutricion_nico | R32: 3125 | S32: {1} | T32: SITIO 3 | U32: {1} | V32: 3125 | W32: SITIO 3 | X32: 1 | Y32: 1 | Z32: =AJ32*-1 -> -17546403 | AA32: 54156 | AB32: =_xlfn.XLOOKUP(I32,'rubros_id_opex '!A:A,'rubros_id_opex '!B:B) -> 1 | AC32: =_xlfn.XLOOKUP(AB32,'rubros_unicos'!B:B,'rubros_unicos'!A:A) -> NUTRICIÓN | AD32: =MID(E32,FIND("-",E32),LEN(E32)) -> -{t2}-{capones} | AE32: =_xlfn.CONCAT(W32,AD32) -> SITIO 3-{t2}-{capones} | AF32: =_xlfn.XLOOKUP(BBDD_GASTOS_FINAL!AE32,formula_ciclos!A:A,formula_ciclos!B:B) -> terminador_c_arveja_2b | AG32: =IF(AF32="NO",_xlfn.XLOOKUP(AE32,formula_ciclos!A:A,formula_ciclos!E:E),AF32) -> terminador_c_arveja_2b | AH32: =_xlfn.XLOOKUP(AG32,formulas!D:D,formulas!M:M) -> 323.9974 | AI32: 1 | AJ32: =AH32*F32 -> 17546403 | AK32: =F32*G32 -> 17813533 | AL32: =AJ32/AK32-1 -> -0.014995896
A33: 46036 | B33: Arrieta, Fernando Gabriel | C33: FA-A 00003-00000458 | D33: -4392300 | E33: OC 0001-00003813: Fletes (C) Camión doble 22/12 15/12 19/12 18/12 26/12 | F33: 5 | G33: 550000 | H33: Unidad(es) | I33: Fletes (C) | J33: OPEX | K33: VARIABLE | L33: =IF(K33="variable","DIRECTO","INDIRECTO") -> DIRECTO | M33: CCC _ene26 | N33: CC5 | O33: 0 | P33: 0 | Q33: facturas_final | R33: {2925,3125} | S33: {0.49166666,0.4916666} | T33: SITIO 3 | U33: {1} | V33: 2925 | W33: SITIO 3 | X33: 0.49166666 | Y33: 1 | Z33: -2159547.5 | AA33: 2.4583333 | AB33: =_xlfn.XLOOKUP(I33,'rubros_id_opex '!A:A,'rubros_id_opex '!B:B) -> 5 | AC33: =_xlfn.XLOOKUP(AB33,'rubros_unicos'!B:B,'rubros_unicos'!A:A) -> FLETES
A34: 46036 | B34: Arrieta, Fernando Gabriel | C34: FA-A 00003-00000458 | D34: -4392300 | E34: OC 0001-00003813: Fletes (C) Camión doble 22/12 15/12 19/12 18/12 26/12 | F34: 5 | G34: 550000 | H34: Unidad(es) | I34: Fletes (C) | J34: OPEX | K34: VARIABLE | L34: =IF(K34="variable","DIRECTO","INDIRECTO") -> DIRECTO | M34: CCC _ene26 | N34: CC5 | O34: 0 | P34: 0 | Q34: facturas_final | R34: {2925,3125} | S34: {0.49166666,0.4916666} | T34: SITIO 3 | U34: {1} | V34: 3125 | W34: SITIO 3 | X34: 0.4916666 | Y34: 1 | Z34: -2159547.2 | AA34: 2.458333 | AB34: =_xlfn.XLOOKUP(I34,'rubros_id_opex '!A:A,'rubros_id_opex '!B:B) -> 5 | AC34: =_xlfn.XLOOKUP(AB34,'rubros_unicos'!B:B,'rubros_unicos'!A:A) -> FLETES
A35: 46053 | B35: Barrera, Adrian Jesus | C35: FA-C 00001-00000419 | D35: -189200 | E35: OC 0001-00003833: Gastos Operativos (C) | F35: 43 | G35: 4400 | H35: Unidad(es) | I35: Gastos Operativos (C) | J35: OPEX | K35: VARIABLE | L35: =IF(K35="variable","DIRECTO","INDIRECTO") -> DIRECTO | M35: CCC _ene26 | N35: CC1 | O35: 0 | P35: 0 | Q35: facturas_final | R35: {2925,3125} | S35: {0.49166666,0.4916666} | T35: GESTACIÓN , MATERNIDAD, SITIO 2, SITIO 3 | U35: {0.25,0.25,0.25,0.25} | V35: 2925 | W35: GESTACIÓN | X35: 0.49166666 | Y35: 0.25 | Z35: -23255.833 | AA35: 5.2854166 | AB35: =_xlfn.XLOOKUP(I35,'rubros_id_opex '!A:A,'rubros_id_opex '!B:B) -> 7 | AC35: =_xlfn.XLOOKUP(AB35,'rubros_unicos'!B:B,'rubros_unicos'!A:A) -> GASTOS OPERATIVOS
A36: 46053 | B36: Barrera, Adrian Jesus | C36: FA-C 00001-00000419 | D36: -189200 | E36: OC 0001-00003833: Gastos Operativos (C) | F36: 43 | G36: 4400 | H36: Unidad(es) | I36: Gastos Operativos (C) | J36: OPEX | K36: VARIABLE | L36: =IF(K36="variable","DIRECTO","INDIRECTO") -> DIRECTO | M36: CCC _ene26 | N36: CC1 | O36: 0 | P36: 0 | Q36: facturas_final | R36: {2925,3125} | S36: {0.49166666,0.4916666} | T36: GESTACIÓN , MATERNIDAD, SITIO 2, SITIO 3 | U36: {0.25,0.25,0.25,0.25} | V36: 2925 | W36: MATERNIDAD | X36: 0.49166666 | Y36: 0.25 | Z36: -23255.833 | AA36: 5.2854166 | AB36: =_xlfn.XLOOKUP(I36,'rubros_id_opex '!A:A,'rubros_id_opex '!B:B) -> 7 | AC36: =_xlfn.XLOOKUP(AB36,'rubros_unicos'!B:B,'rubros_unicos'!A:A) -> GASTOS OPERATIVOS
A37: 46053 | B37: Barrera, Adrian Jesus | C37: FA-C 00001-00000419 | D37: -189200 | E37: OC 0001-00003833: Gastos Operativos (C) | F37: 43 | G37: 4400 | H37: Unidad(es) | I37: Gastos Operativos (C) | J37: OPEX | K37: VARIABLE | L37: =IF(K37="variable","DIRECTO","INDIRECTO") -> DIRECTO | M37: CCC _ene26 | N37: CC1 | O37: 0 | P37: 0 | Q37: facturas_final | R37: {2925,3125} | S37: {0.49166666,0.4916666} | T37: GESTACIÓN , MATERNIDAD, SITIO 2, SITIO 3 | U37: {0.25,0.25,0.25,0.25} | V37: 2925 | W37: SITIO 2 | X37: 0.49166666 | Y37: 0.25 | Z37: -23255.833 | AA37: 5.2854166 | AB37: =_xlfn.XLOOKUP(I37,'rubros_id_opex '!A:A,'rubros_id_opex '!B:B) -> 7 | AC37: =_xlfn.XLOOKUP(AB37,'rubros_unicos'!B:B,'rubros_unicos'!A:A) -> GASTOS OPERATIVOS
A38: 46053 | B38: Barrera, Adrian Jesus | C38: FA-C 00001-00000419 | D38: -189200 | E38: OC 0001-00003833: Gastos Operativos (C) | F38: 43 | G38: 4400 | H38: Unidad(es) | I38: Gastos Operativos (C) | J38: OPEX | K38: VARIABLE | L38: =IF(K38="variable","DIRECTO","INDIRECTO") -> DIRECTO | M38: CCC _ene26 | N38: CC1 | O38: 0 | P38: 0 | Q38: facturas_final | R38: {2925,3125} | S38: {0.49166666,0.4916666} | T38: GESTACIÓN , MATERNIDAD, SITIO 2, SITIO 3 | U38: {0.25,0.25,0.25,0.25} | V38: 2925 | W38: SITIO 3 | X38: 0.49166666 | Y38: 0.25 | Z38: -23255.833 | AA38: 5.2854166 | AB38: =_xlfn.XLOOKUP(I38,'rubros_id_opex '!A:A,'rubros_id_opex '!B:B) -> 7 | AC38: =_xlfn.XLOOKUP(AB38,'rubros_unicos'!B:B,'rubros_unicos'!A:A) -> GASTOS OPERATIVOS
A39: 46053 | B39: Barrera, Adrian Jesus | C39: FA-C 00001-00000419 | D39: -189200 | E39: OC 0001-00003833: Gastos Operativos (C) | F39: 43 | G39: 4400 | H39: Unidad(es) | I39: Gastos Operativos (C) | J39: OPEX | K39: VARIABLE | L39: =IF(K39="variable","DIRECTO","INDIRECTO") -> DIRECTO | M39: CCC _ene26 | N39: CC1 | O39: 0 | P39: 0 | Q39: facturas_final | R39: {2925,3125} | S39: {0.49166666,0.4916666} | T39: GESTACIÓN , MATERNIDAD, SITIO 2, SITIO 3 | U39: {0.25,0.25,0.25,0.25} | V39: 3125 | W39: GESTACIÓN | X39: 0.4916666 | Y39: 0.25 | Z39: -23255.83 | AA39: 5.2854159 | AB39: =_xlfn.XLOOKUP(I39,'rubros_id_opex '!A:A,'rubros_id_opex '!B:B) -> 7 | AC39: =_xlfn.XLOOKUP(AB39,'rubros_unicos'!B:B,'rubros_unicos'!A:A) -> GASTOS OPERATIVOS
A40: 46053 | B40: Barrera, Adrian Jesus | C40: FA-C 00001-00000419 | D40: -189200 | E40: OC 0001-00003833: Gastos Operativos (C) | F40: 43 | G40: 4400 | H40: Unidad(es) | I40: Gastos Operativos (C) | J40: OPEX | K40: VARIABLE | L40: =IF(K40="variable","DIRECTO","INDIRECTO") -> DIRECTO | M40: CCC _ene26 | N40: CC1 | O40: 0 | P40: 0 | Q40: facturas_final | R40: {2925,3125} | S40: {0.49166666,0.4916666} | T40: GESTACIÓN , MATERNIDAD, SITIO 2, SITIO 3 | U40: {0.25,0.25,0.25,0.25} | V40: 3125 | W40: MATERNIDAD | X40: 0.4916666 | Y40: 0.25 | Z40: -23255.83 | AA40: 5.2854159 | AB40: =_xlfn.XLOOKUP(I40,'rubros_id_opex '!A:A,'rubros_id_opex '!B:B) -> 7 | AC40: =_xlfn.XLOOKUP(AB40,'rubros_unicos'!B:B,'rubros_unicos'!A:A) -> GASTOS OPERATIVOS
A41: 46053 | B41: Barrera, Adrian Jesus | C41: FA-C 00001-00000419 | D41: -189200 | E41: OC 0001-00003833: Gastos Operativos (C) | F41: 43 | G41: 4400 | H41: Unidad(es) | I41: Gastos Operativos (C) | J41: OPEX | K41: VARIABLE | L41: =IF(K41="variable","DIRECTO","INDIRECTO") -> DIRECTO | M41: CCC _ene26 | N41: CC1 | O41: 0 | P41: 0 | Q41: facturas_final | R41: {2925,3125} | S41: {0.49166666,0.4916666} | T41: GESTACIÓN , MATERNIDAD, SITIO 2, SITIO 3 | U41: {0.25,0.25,0.25,0.25} | V41: 3125 | W41: SITIO 2 | X41: 0.4916666 | Y41: 0.25 | Z41: -23255.83 | AA41: 5.2854159 | AB41: =_xlfn.XLOOKUP(I41,'rubros_id_opex '!A:A,'rubros_id_opex '!B:B) -> 7 | AC41: =_xlfn.XLOOKUP(AB41,'rubros_unicos'!B:B,'rubros_unicos'!A:A) -> GASTOS OPERATIVOS
A42: 46053 | B42: Barrera, Adrian Jesus | C42: FA-C 00001-00000419 | D42: -189200 | E42: OC 0001-00003833: Gastos Operativos (C) | F42: 43 | G42: 4400 | H42: Unidad(es) | I42: Gastos Operativos (C) | J42: OPEX | K42: VARIABLE | L42: =IF(K42="variable","DIRECTO","INDIRECTO") -> DIRECTO | M42: CCC _ene26 | N42: CC1 | O42: 0 | P42: 0 | Q42: facturas_final | R42: {2925,3125} | S42: {0.49166666,0.4916666} | T42: GESTACIÓN , MATERNIDAD, SITIO 2, SITIO 3 | U42: {0.25,0.25,0.25,0.25} | V42: 3125 | W42: SITIO 3 | X42: 0.4916666 | Y42: 0.25 | Z42: -23255.83 | AA42: 5.2854159 | AB42: =_xlfn.XLOOKUP(I42,'rubros_id_opex '!A:A,'rubros_id_opex '!B:B) -> 7 | AC42: =_xlfn.XLOOKUP(AB42,'rubros_unicos'!B:B,'rubros_unicos'!A:A) -> GASTOS OPERATIVOS
A43: 46049 | B43: Cooperativa Agricola Ganadera Aaron Castellanos Ltda De Esperanza | C43: FA-A 00002-00004202 | D43: -1170000 | E43: OC 0001-00004478: Gastos Operativos (C) Servicio de faena | F43: 90 | G43: 10743.8 | H43: Unidad(es) | I43: Gastos Operativos (C) | J43: OPEX | K43: VARIABLE | L43: =IF(K43="variable","DIRECTO","INDIRECTO") -> DIRECTO | M43: CCC _ene26 | N43: CC1 | O43: 0 | P43: 0 | Q43: facturas_final | R43: {2925,3125} | S43: {0.49166666,0.4916666} | T43: GESTACIÓN , MATERNIDAD, SITIO 2, SITIO 3 | U43: {0.25,0.25,0.25,0.25} | V43: 2925 | W43: GESTACIÓN | X43: 0.49166666 | Y43: 0.25 | Z43: -143812.5 | AA43: 11.0625 | AB43: =_xlfn.XLOOKUP(I43,'rubros_id_opex '!A:A,'rubros_id_opex '!B:B) -> 7 | AC43: =_xlfn.XLOOKUP(AB43,'rubros_unicos'!B:B,'rubros_unicos'!A:A) -> GASTOS OPERATIVOS
A44: 46049 | B44: Cooperativa Agricola Ganadera Aaron Castellanos Ltda De Esperanza | C44: FA-A 00002-00004202 | D44: -1170000 | E44: OC 0001-00004478: Gastos Operativos (C) Servicio de faena | F44: 90 | G44: 10743.8 | H44: Unidad(es) | I44: Gastos Operativos (C) | J44: OPEX | K44: VARIABLE | L44: =IF(K44="variable","DIRECTO","INDIRECTO") -> DIRECTO | M44: CCC _ene26 | N44: CC1 | O44: 0 | P44: 0 | Q44: facturas_final | R44: {2925,3125} | S44: {0.49166666,0.4916666} | T44: GESTACIÓN , MATERNIDAD, SITIO 2, SITIO 3 | U44: {0.25,0.25,0.25,0.25} | V44: 2925 | W44: MATERNIDAD | X44: 0.49166666 | Y44: 0.25 | Z44: -143812.5 | AA44: 11.0625 | AB44: =_xlfn.XLOOKUP(I44,'rubros_id_opex '!A:A,'rubros_id_opex '!B:B) -> 7 | AC44: =_xlfn.XLOOKUP(AB44,'rubros_unicos'!B:B,'rubros_unicos'!A:A) -> GASTOS OPERATIVOS
