Workbook

Sheet rubros_id_opex
A1: nombre | B1: id
A2: ENERGIA | B2: 1
A3: HABILITACIONES Y CERT | B3: 2
A4: HIGIENE Y SEGURIDAD | B4: 3
A5: IMPUESTOS | B5: 4
A6: INSUMOS | B6: 5
A7: INVERSION | B7: 6
A8: LOGISTICA | B8: 7
A9: M.PRIMAS | B9: 8
A10: MANTENIMIENTO PREVENTIVO | B10: 9
A11: PERSONAL | B11: 10
A12: REPARACIONES | B12: 11
A13: REPOSICION | B13: 12
A14: SERVICIOS | B14: 12

Sheet fer_gral
C29: DEUDA
C30: FARO | D30: UNI
C31: M23 WORMS | D31: UNI
C32: M23 BROKER WORLD | D32: UNI
C33: SOUTHCROSS | D33: UNI
C34: RAUL BRINGAS | D34: UNI
C35: MOLLINS | D35: UNI
C36: NICOLAS AVELLINO | D36: UNI
C37: JORGE FERNANDEZ | D37: UNI
C38: CARBO | D38: UNI
C39: GARANTIZAR | D39: UNI
C40: CIRCULO CERRADO | D40: UNI
C41: SANTIAGO BORSONE | D41: UNI
... C48: CRISTIAN AMEGHINI | D48: UNI

Sheet fer_expo
B2: RUBRO + GASTO | C2: UM | D2: Q | E2: MONEDA | F2: P | G2: TOTAL
B3: ENERGIA
B4: NAFTA | C4: LTS
B5: ENERGIA ELECTRICA | C5: KW/H
B6: GASOIL G2 | C6: LTS
B7: GASOIL G3 | C7: LTS
B8: FULL OIL | C8: KG
B10: HABILITACION & CERT
B11: ISCC | C11: UNI
B12: AMBIENTAL | C12: UNI
B13: MUNICIPAL | C13: UNI
B15: HIGIENE & SEGURIDAD
B16: EPP | C16: UNI
B17: HONORARIOS SERVICIOS | C17: UNI
B19: INSUMO
B20: PRESINTOS ISO TANUQE | C20: UNI
B21: BOBINA PAPEL | C21: UNI
B23: LOGISTICA
B24: FOB | C24: TN
B25: FSA | C25: TN
B26: CIF | C26: TN
B28: MATERIA PRIMA
B29: AFE (S) | C29: TN
B30: AFE (G) | C30: TN
B31: AFE (SG) | C31: TN
B32: TSO | C32: TN
B33: AFE (AL) | C33: TN
B34: ARE (V) - A | C34: TN
B35: ARE (V) - B | C35: TN
B36: AG - A | C36: TN
B37: AG - B | C37: TN
B38: AG - C | C38: TN
B40: MANTENIMIENTO
B41: LIMPIEZA | C41: UNI
B44: RR.HH
B45: SUPERVISOR | C45: UNI
B46: COORDINADOR | C46: UNI
B47: OPERARIO | C47: UNI
B49: REPARACIONES
B50: BIENES DE USO + PARTES | C50: UNI | D50: 51
B52: REPOSICION
B53: BIENES DE USO + PARTES | C53: UNI | D53: 51
B55: SERVICIO
B56: COMEX | C56: TN
B57: TERMINAL | C57: TN
B58: SURBEIOR | C58: TN
B60: COMERCIAL
B61: COMISIONES | C61: UNI
B63: IMPUESTO
B64: GANANCIA | C64: UNI
B65: DREI | C65: UNI
G66: =SUM(G3:G65) -> 0
B68: VENTA
B69: AE FOB | C69: TN
B70: AE FSA | C70: TN
G71: =SUM(G69:G70) -> 0
B73: RESULTADO 1 | G73: =G71-G66 -> 0
B75: SOPERTE
B76: ADMINISTRACION
B77: LABORATORIO
B78: INTENDENCIA
B79: PORTERIA
B80: TALLER
B81: DIRECCION
B82: SEGURIDAD
G83: =SUM(G76:G82) -> 0
A85: EBITDA | B85: RESULTADO 2 | G85: =G73-G83 -> 0
B87: CAPEX
B88: PROYECTO 1 | C88: UNI
B89: PROYECTO 1 | C89: UNI
B90: PROYECTO 1 | C90: UNI
G91: =SUM(G88:G90) -> 0
B93: RESULTADO 3 | G93: =G85-G91 -> 0

Sheet Vista
B2: WORMS
B5: TOTALES | F5: FIJO/VARIABLE | J5: DIRECTO/INDERECTO
B6: VENTAS | C6: =SUM(BBDD_INGRESOS_FINAL!$O:$O) -> 3.1786083e+09 | F6: VENTAS | G6: =SUM(BBDD_INGRESOS_FINAL!$O:$O) -> 3.1786083e+09 | J6: VENTAS | K6: =SUM(BBDD_INGRESOS_FINAL!$O:$O) -> 3.1786083e+09
B7: OPEX | C7: =SUMIFS('bbdd.5.final'!$Y:$Y,'bbdd.5.final'!$J:$J,Vista!B7) -> 2.7341314e+09 | F7: Fijo | G7: =SUMIFS(BBDD_GASTOS!$H:$H,BBDD_GASTOS!$J:$J,Vista!F7) -> 6805002.2 | J7: DIRECTO | K7: =SUMIFS('bbdd.5.final'!$Y:$Y,'bbdd.5.final'!$L:$L,$J$7) -> 2.5445771e+09
B8: UTILIDAD | C8: =C6-C7 -> 4.4447693e+08 | F8: Variable | G8: =SUMIFS(BBDD_GASTOS!$H:$H,BBDD_GASTOS!$J:$J,Vista!F8) -> 2.7213994e+09 | J8: INDIRECTO | K8: =SUMIFS('bbdd.5.final'!$Y:$Y,'bbdd.5.final'!$L:$L,$J$8) -> 1.8279075e+08
B9: CAPEX | C9: =SUMIFS('bbdd.5.final'!$Y:$Y,'bbdd.5.final'!$J:$J,Vista!B9) -> 1.8781251e+08
B10: DEUDA | C10: =SUMIFS('bbdd.5.final'!$Y:$Y,'bbdd.5.final'!$J:$J,Vista!B10) -> 1511155.8
B11: Flujo de Caja al Accionista | C11: =C6-C7-C9-C10 -> 2.5515326e+08 | F11: Flujo de Caja al Accionista | G11: =G6-G7-G8 -> 4.5040396e+08 | J11: Flujo de Caja al Accionista | K11: =K6-K7-K8 -> 4.5124053e+08
A13: id | B13: 4 | E13: id | F13: 3 | I13: id | J13: 7 | M13: id | N13: 8
B14: DISPOSICIÓN FINAL RESIDUOS SOLIDOS | F14: DISPOSICIÓN FINAL RESIDUOS LIQUIDOS | J14: PILETAS | N14: REACTORES
B15: OPEX | D15: =SUM(D16:D29) -> 18958267 | F15: OPEX | H15: =SUM(H16:H29) -> 32566130 | J15: OPEX | L15: =SUM(L16:L28) -> 41966910 | M15: 1 | N15: OPEX | P15: =SUM(P16:P29) -> 1.1071668e+08
A16: 1 | B16: =D16/$D$15 -> 0.0020162034 | C16: =_xlfn.XLOOKUP($A16,'rubros_id_opex (2)'!$B:$B,'rubros_id_opex (2)'!$A:$A) -> ENERGIA | D16: =SUMIFS('bbdd.5.final'!$Y:$Y,'bbdd.5.final'!$AA:$AA,Vista!A16,'bbdd.5.final'!$Z:$Z,$B$13,'bbdd.5.final'!$J:$J,"Opex") -> 38223.723 | E16: 1 | F16: =H16/$H$15 -> 0.087681751 | G16: =_xlfn.XLOOKUP($E16,'rubros_id_opex (2)'!$B:$B,'rubros_id_opex (2)'!$A:$A) -> ENERGIA | H16: =SUMIFS('bbdd.5.final'!$Y:$Y,'bbdd.5.final'!$AA:$AA,Vista!E16,'bbdd.5.final'!$Z:$Z,$F$13,'bbdd.5.final'!$J:$J,"Opex") -> 2855455.4 | I16: 1 | J16: =L16/$L$15 -> 0.11080139 | K16: =_xlfn.XLOOKUP($I16,'rubros_id_opex (2)'!$B:$B,'rubros_id_opex (2)'!$A:$A) -> ENERGIA | L16: =SUMIFS('bbdd.5.final'!$Y:$Y,'bbdd.5.final'!$AA:$AA,Vista!I16,'bbdd.5.final'!$Z:$Z,$J$13,'bbdd.5.final'!$J:$J,"Opex") -> 4649992 | M16: 1 | N16: =P16/$P$15 -> 0.22433558 | O16: =_xlfn.XLOOKUP($M16,'rubros_id_opex (2)'!$B:$B,'rubros_id_opex (2)'!$A:$A) -> ENERGIA | P16: =SUMIFS('bbdd.5.final'!$Y:$Y,'bbdd.5.final'!$AA:$AA,Vista!M16,'bbdd.5.final'!$Z:$Z,$N$13,'bbdd.5.final'!$J:$J,"Opex") -> 24837690
A17: =A16+1 -> 2 | B17: =D17/$D$15 -> 0 | C17: =_xlfn.XLOOKUP($A17,'rubros_id_opex (2)'!$B:$B,'rubros_id_opex (2)'!$A:$A) -> HABILITACIONES Y CERT | D17: =SUMIFS('bbdd.5.final'!$Y:$Y,'bbdd.5.final'!$AA:$AA,Vista!A17,'bbdd.5.final'!$Z:$Z,$B$13,'bbdd.5.final'!$J:$J,"Opex") -> 0 | E17: =E16+1 -> 2 | F17: =H17/$H$15 -> 0 | G17: =_xlfn.XLOOKUP($E17,'rubros_id_opex (2)'!$B:$B,'rubros_id_opex (2)'!$A:$A) -> HABILITACIONES Y CERT | H17: =SUMIFS('bbdd.5.final'!$Y:$Y,'bbdd.5.final'!$AA:$AA,Vista!E17,'bbdd.5.final'!$Z:$Z,$F$13,'bbdd.5.final'!$J:$J,"Opex") -> 0 | I17: =I16+1 -> 2 | J17: =L17/$L$15 -> 0 | K17: =_xlfn.XLOOKUP($I17,'rubros_id_opex (2)'!$B:$B,'rubros_id_opex (2)'!$A:$A) -> HABILITACIONES Y CERT | L17: =SUMIFS('bbdd.5.final'!$Y:$Y,'bbdd.5.final'!$AA:$AA,Vista!I17,'bbdd.5.final'!$Z:$Z,$J$13,'bbdd.5.final'!$J:$J,"Opex") -> 0 | M17: =M16+1 -> 2 | N17: =P17/$P$15 -> 0 | O17: =_xlfn.XLOOKUP($M17,'rubros_id_opex (2)'!$B:$B,'rubros_id_opex (2)'!$A:$A) -> HABILITACIONES Y CERT | P17: =SUMIFS('bbdd.5.final'!$Y:$Y,'bbdd.5.final'!$AA:$AA,Vista!M17,'bbdd.5.final'!$Z:$Z,$N$13,'bbdd.5.final'!$J:$J,"Opex") -> 0
A18: =A17+1 -> 3 | B18: =D18/$D$15 -> 0.0011283211 | C18: =_xlfn.XLOOKUP($A18,'rubros_id_opex (2)'!$B:$B,'rubros_id_opex (2)'!$A:$A) -> HIGIENE Y SEGURIDAD | D18: =SUMIFS('bbdd.5.final'!$Y:$Y,'bbdd.5.final'!$AA:$AA,Vista!A18,'bbdd.5.final'!$Z:$Z,$B$13,'bbdd.5.final'!$J:$J,"Opex") -> 21391.014 | E18: =E17+1 -> 3 | F18: =H18/$H$15 -> 0.0080581024 | G18: =_xlfn.XLOOKUP($E18,'rubros_id_opex (2)'!$B:$B,'rubros_id_opex (2)'!$A:$A) -> HIGIENE Y SEGURIDAD | H18: =SUMIFS('bbdd.5.final'!$Y:$Y,'bbdd.5.final'!$AA:$AA,Vista!E18,'bbdd.5.final'!$Z:$Z,$F$13,'bbdd.5.final'!$J:$J,"Opex") -> 262421.21 | I18: =I17+1 -> 3 | J18: =L18/$L$15 -> 0.011253022 | K18: =_xlfn.XLOOKUP($I18,'rubros_id_opex (2)'!$B:$B,'rubros_id_opex (2)'!$A:$A) -> HIGIENE Y SEGURIDAD | L18: =SUMIFS('bbdd.5.final'!$Y:$Y,'bbdd.5.final'!$AA:$AA,Vista!I18,'bbdd.5.final'!$Z:$Z,$J$13,'bbdd.5.final'!$J:$J,"Opex") -> 472254.55 | M18: =M17+1 -> 3 | N18: =P18/$P$15 -> 0.0015727911 | O18: =_xlfn.XLOOKUP($M18,'rubros_id_opex (2)'!$B:$B,'rubros_id_opex (2)'!$A:$A) -> HIGIENE Y SEGURIDAD | P18: =SUMIFS('bbdd.5.final'!$Y:$Y,'bbdd.5.final'!$AA:$AA,Vista!M18,'bbdd.5.final'!$Z:$Z,$N$13,'bbdd.5.final'!$J:$J,"Opex") -> 174134.2
A19: =A18+1 -> 4 | B19: =D19/$D$15 -> 0.001303926 | C19: =_xlfn.XLOOKUP($A19,'rubros_id_opex (2)'!$B:$B,'rubros_id_opex (2)'!$A:$A) -> IMPUESTOS | D19: =SUMIFS('bbdd.5.final'!$Y:$Y,'bbdd.5.final'!$AA:$AA,Vista!A19,'bbdd.5.final'!$Z:$Z,$B$13,'bbdd.5.final'!$J:$J,"Opex") -> 24720.178 | E19: =E18+1 -> 4 | F19: =H19/$H$15 -> 0.030013783 | G19: =_xlfn.XLOOKUP($E19,'rubros_id_opex (2)'!$B:$B,'rubros_id_opex (2)'!$A:$A) -> IMPUESTOS | H19: =SUMIFS('bbdd.5.final'!$Y:$Y,'bbdd.5.final'!$AA:$AA,Vista!E19,'bbdd.5.final'!$Z:$Z,$F$13,'bbdd.5.final'!$J:$J,"Opex") -> 977432.76 | I19: =I18+1 -> 4 | J19: =L19/$L$15 -> 0.019544083 | K19: =_xlfn.XLOOKUP($I19,'rubros_id_opex (2)'!$B:$B,'rubros_id_opex (2)'!$A:$A) -> IMPUESTOS | L19: =SUMIFS('bbdd.5.final'!$Y:$Y,'bbdd.5.final'!$AA:$AA,Vista!I19,'bbdd.5.final'!$Z:$Z,$J$13,'bbdd.5.final'!$J:$J,"Opex") -> 820204.79 | M19: =M18+1 -> 4 | N19: =P19/$P$15 -> 0.0018175705 | O19: =_xlfn.XLOOKUP($M19,'rubros_id_opex (2)'!$B:$B,'rubros_id_opex (2)'!$A:$A) -> IMPUESTOS | P19: =SUMIFS('bbdd.5.final'!$Y:$Y,'bbdd.5.final'!$AA:$AA,Vista!M19,'bbdd.5.final'!$Z:$Z,$N$13,'bbdd.5.final'!$J:$J,"Opex") -> 201235.36
A20: =A19+1 -> 5 | B20: =D20/$D$15 -> 0.00050329615 | C20: =_xlfn.XLOOKUP($A20,'rubros_id_opex (2)'!$B:$B,'rubros_id_opex (2)'!$A:$A) -> INSUMOS | D20: =SUMIFS('bbdd.5.final'!$Y:$Y,'bbdd.5.final'!$AA:$AA,Vista!A20,'bbdd.5.final'!$Z:$Z,$B$13,'bbdd.5.final'!$J:$J,"Opex") -> 9541.6229 | E20: =E19+1 -> 5 | F20: =H20/$H$15 -> 0.0035943773 | G20: =_xlfn.XLOOKUP($E20,'rubros_id_opex (2)'!$B:$B,'rubros_id_opex (2)'!$A:$A) -> INSUMOS | H20: =SUMIFS('bbdd.5.final'!$Y:$Y,'bbdd.5.final'!$AA:$AA,Vista!E20,'bbdd.5.final'!$Z:$Z,$F$13,'bbdd.5.final'!$J:$J,"Opex") -> 117054.96 | I20: =I19+1 -> 5 | J20: =L20/$L$15 -> 0.0050194951 | K20: =_xlfn.XLOOKUP($I20,'rubros_id_opex (2)'!$B:$B,'rubros_id_opex (2)'!$A:$A) -> INSUMOS | L20: =SUMIFS('bbdd.5.final'!$Y:$Y,'bbdd.5.final'!$AA:$AA,Vista!I20,'bbdd.5.final'!$Z:$Z,$J$13,'bbdd.5.final'!$J:$J,"Opex") -> 210652.7 | M20: =M19+1 -> 5 | N20: =P20/$P$15 -> 0.63928482 | O20: =_xlfn.XLOOKUP($M20,'rubros_id_opex (2)'!$B:$B,'rubros_id_opex (2)'!$A:$A) -> INSUMOS | P20: =SUMIFS('bbdd.5.final'!$Y:$Y,'bbdd.5.final'!$AA:$AA,Vista!M20,'bbdd.5.final'!$Z:$Z,$N$13,'bbdd.5.final'!$J:$J,"Opex") -> 70779491
A21: =A20+1 -> 6 | B21: =D21/$D$15 -> 0 | C21: =_xlfn.XLOOKUP($A21,'rubros_id_opex (2)'!$B:$B,'rubros_id_opex (2)'!$A:$A) -> INVERSION | D21: =SUMIFS('bbdd.5.final'!$Y:$Y,'bbdd.5.final'!$AA:$AA,Vista!A21,'bbdd.5.final'!$Z:$Z,$B$13,'bbdd.5.final'!$J:$J,"Opex") -> 0 | E21: =E20+1 -> 6 | F21: =H21/$H$15 -> 0 | G21: =_xlfn.XLOOKUP($E21,'rubros_id_opex (2)'!$B:$B,'rubros_id_opex (2)'!$A:$A) -> INVERSION | H21: =SUMIFS('bbdd.5.final'!$Y:$Y,'bbdd.5.final'!$AA:$AA,Vista!E21,'bbdd.5.final'!$Z:$Z,$F$13,'bbdd.5.final'!$J:$J,"Opex") -> 0 | I21: =I20+1 -> 6 | J21: =L21/$L$15 -> 0 | K21: =_xlfn.XLOOKUP($I21,'rubros_id_opex (2)'!$B:$B,'rubros_id_opex (2)'!$A:$A) -> INVERSION | L21: =SUMIFS('bbdd.5.final'!$Y:$Y,'bbdd.5.final'!$AA:$AA,Vista!I21,'bbdd.5.final'!$Z:$Z,$J$13,'bbdd.5.final'!$J:$J,"Opex") -> 0 | M21: =M20+1 -> 6 | N21: =P21/$P$15 -> 0 | O21: =_xlfn.XLOOKUP($M21,'rubros_id_opex (2)'!$B:$B,'rubros_id_opex (2)'!$A:$A) -> INVERSION | P21: =SUMIFS('bbdd.5.final'!$Y:$Y,'bbdd.5.final'!$AA:$AA,Vista!M21,'bbdd.5.final'!$Z:$Z,$N$13,'bbdd.5.final'!$J:$J,"Opex") -> 0
A22: =A21+1 -> 7 | B22: =D22/$D$15 -> 0 | C22: =_xlfn.XLOOKUP($A22,'rubros_id_opex (2)'!$B:$B,'rubros_id_opex (2)'!$A:$A) -> LOGISTICA | D22: =SUMIFS('bbdd.5.final'!$Y:$Y,'bbdd.5.final'!$AA:$AA,Vista!A22,'bbdd.5.final'!$Z:$Z,$B$13,'bbdd.5.final'!$J:$J,"Opex") -> 0 | E22: =E21+1 -> 7 | F22: =H22/$H$15 -> 0 | G22: =_xlfn.XLOOKUP($E22,'rubros_id_opex (2)'!$B:$B,'rubros_id_opex (2)'!$A:$A) -> LOGISTICA | H22: =SUMIFS('bbdd.5.final'!$Y:$Y,'bbdd.5.final'!$AA:$AA,Vista!E22,'bbdd.5.final'!$Z:$Z,$F$13,'bbdd.5.final'!$J:$J,"Opex") -> 0 | I22: =I21+1 -> 7 | J22: =L22/$L$15 -> 0 | K22: =_xlfn.XLOOKUP($I22,'rubros_id_opex (2)'!$B:$B,'rubros_id_opex (2)'!$A:$A) -> LOGISTICA | L22: =SUMIFS('bbdd.5.final'!$Y:$Y,'bbdd.5.final'!$AA:$AA,Vista!I22,'bbdd.5.final'!$Z:$Z,$J$13,'bbdd.5.final'!$J:$J,"Opex") -> 0 | M22: =M21+1 -> 7 | N22: =P22/$P$15 -> 0 | O22: =_xlfn.XLOOKUP($M22,'rubros_id_opex (2)'!$B:$B,'rubros_id_opex (2)'!$A:$A) -> LOGISTICA | P22: =SUMIFS('bbdd.5.final'!$Y:$Y,'bbdd.5.final'!$AA:$AA,Vista!M22,'bbdd.5.final'!$Z:$Z,$N$13,'bbdd.5.final'!$J:$J,"Opex") -> 0
A23: =A22+1 -> 8 | B23: =D23/$D$15 -> 0.045125088 | C23: =_xlfn.XLOOKUP($A23,'rubros_id_opex (2)'!$B:$B,'rubros_id_opex (2)'!$A:$A) -> M.PRIMAS | D23: =SUMIFS('bbdd.5.final'!$Y:$Y,'bbdd.5.final'!$AA:$AA,Vista!A23,'bbdd.5.final'!$Z:$Z,$B$13,'bbdd.5.final'!$J:$J,"Opex") -> 855493.48 | E23: =E22+1 -> 8 | F23: =H23/$H$15 -> 0 | G23: =_xlfn.XLOOKUP($E23,'rubros_id_opex (2)'!$B:$B,'rubros_id_opex (2)'!$A:$A) -> M.PRIMAS | H23: =SUMIFS('bbdd.5.final'!$Y:$Y,'bbdd.5.final'!$AA:$AA,Vista!E23,'bbdd.5.final'!$Z:$Z,$F$13,'bbdd.5.final'!$J:$J,"Opex") -> 0 | I23: =I22+1 -> 8 | J23: =L23/$L$15 -> 0 | K23: =_xlfn.XLOOKUP($I23,'rubros_id_opex (2)'!$B:$B,'rubros_id_opex (2)'!$A:$A) -> M.PRIMAS | L23: =SUMIFS('bbdd.5.final'!$Y:$Y,'bbdd.5.final'!$AA:$AA,Vista!I23,'bbdd.5.final'!$Z:$Z,$J$13,'bbdd.5.final'!$J:$J,"Opex") -> 0 | M23: =M22+1 -> 8 | N23: =P23/$P$15 -> 0 | O23: =_xlfn.XLOOKUP($M23,'rubros_id_opex (2)'!$B:$B,'rubros_id_opex (2)'!$A:$A) -> M.PRIMAS | P23: =SUMIFS('bbdd.5.final'!$Y:$Y,'bbdd.5.final'!$AA:$AA,Vista!M23,'bbdd.5.final'!$Z:$Z,$N$13,'bbdd.5.final'!$J:$J,"Opex") -> 0
A24: =A23+1 -> 9 | B24: =D24/$D$15 -> 0.00091949148 | C24: =_xlfn.XLOOKUP($A24,'rubros_id_opex (2)'!$B:$B,'rubros_id_opex (2)'!$A:$A) -> MANTENIMIENTO PREVENTIVO | D24: =SUMIFS('bbdd.5.final'!$Y:$Y,'bbdd.5.final'!$AA:$AA,Vista!A24,'bbdd.5.final'!$Z:$Z,$B$13,'bbdd.5.final'!$J:$J,"Opex") -> 17431.965 | E24: =E23+1 -> 9 | F24: =H24/$H$15 -> 0.0065667089 | G24: =_xlfn.XLOOKUP($E24,'rubros_id_opex (2)'!$B:$B,'rubros_id_opex (2)'!$A:$A) -> MANTENIMIENTO PREVENTIVO | H24: =SUMIFS('bbdd.5.final'!$Y:$Y,'bbdd.5.final'!$AA:$AA,Vista!E24,'bbdd.5.final'!$Z:$Z,$F$13,'bbdd.5.final'!$J:$J,"Opex") -> 213852.3 | I24: =I23+1 -> 9 | J24: =L24/$L$15 -> 0.0091703126 | K24: =_xlfn.XLOOKUP($I24,'rubros_id_opex (2)'!$B:$B,'rubros_id_opex (2)'!$A:$A) -> MANTENIMIENTO PREVENTIVO | L24: =SUMIFS('bbdd.5.final'!$Y:$Y,'bbdd.5.final'!$AA:$AA,Vista!I24,'bbdd.5.final'!$Z:$Z,$J$13,'bbdd.5.final'!$J:$J,"Opex") -> 384849.69 | M24: =M23+1 -> 9 | N24: =P24/$P$15 -> 0.0057338924 | O24: =_xlfn.XLOOKUP($M24,'rubros_id_opex (2)'!$B:$B,'rubros_id_opex (2)'!$A:$A) -> MANTENIMIENTO PREVENTIVO | P24: =SUMIFS('bbdd.5.final'!$Y:$Y,'bbdd.5.final'!$AA:$AA,Vista!M24,'bbdd.5.final'!$Z:$Z,$N$13,'bbdd.5.final'!$J:$J,"Opex") -> 634837.51
A25: =A24+1 -> 10 | B25: =D25/$D$15 -> 0.9415857 | C25: =_xlfn.XLOOKUP($A25,'rubros_id_opex (2)'!$B:$B,'rubros_id_opex (2)'!$A:$A) -> PERSONAL | D25: =SUMIFS('bbdd.5.final'!$Y:$Y,'bbdd.5.final'!$AA:$AA,Vista!A25,'bbdd.5.final'!$Z:$Z,$B$13,'bbdd.5.final'!$J:$J,"Opex") -> 17850833 | E25: =E24+1 -> 10 | F25: =H25/$H$15 -> 0.75585347 | G25: =_xlfn.XLOOKUP($E25,'rubros_id_opex (2)'!$B:$B,'rubros_id_opex (2)'!$A:$A) -> PERSONAL | H25: =SUMIFS('bbdd.5.final'!$Y:$Y,'bbdd.5.final'!$AA:$AA,Vista!E25,'bbdd.5.final'!$Z:$Z,$F$13,'bbdd.5.final'!$J:$J,"Opex") -> 24615223 | I25: =I24+1 -> 10 | J25: =L25/$L$15 -> 0.75643576 | K25: =_xlfn.XLOOKUP($I25,'rubros_id_opex (2)'!$B:$B,'rubros_id_opex (2)'!$A:$A) -> PERSONAL | L25: =SUMIFS('bbdd.5.final'!$Y:$Y,'bbdd.5.final'!$AA:$AA,Vista!I25,'bbdd.5.final'!$Z:$Z,$J$13,'bbdd.5.final'!$J:$J,"Opex") -> 31745272 | M25: =M24+1 -> 10 | N25: =P25/$P$15 -> 0.11452515 | O25: =_xlfn.XLOOKUP($M25,'rubros_id_opex (2)'!$B:$B,'rubros_id_opex (2)'!$A:$A) -> PERSONAL | P25: =SUMIFS('bbdd.5.final'!$Y:$Y,'bbdd.5.final'!$AA:$AA,Vista!M25,'bbdd.5.final'!$Z:$Z,$N$13,'bbdd.5.final'!$J:$J,"Opex") -> 12679844
A26: =A25+1 -> 11 | B26: =D26/$D$15 -> 0.00022327495 | C26: =_xlfn.XLOOKUP($A26,'rubros_id_opex (2)'!$B:$B,'rubros_id_opex (2)'!$A:$A) -> REPARACIONES | D26: =SUMIFS('bbdd.5.final'!$Y:$Y,'bbdd.5.final'!$AA:$AA,Vista!A26,'bbdd.5.final'!$Z:$Z,$B$13,'bbdd.5.final'!$J:$J,"Opex") -> 4232.9062 | E26: =E25+1 -> 11 | F26: =H26/$H$15 -> 0.001594557 | G26: =_xlfn.XLOOKUP($E26,'rubros_id_opex (2)'!$B:$B,'rubros_id_opex (2)'!$A:$A) -> REPARACIONES | H26: =SUMIFS('bbdd.5.final'!$Y:$Y,'bbdd.5.final'!$AA:$AA,Vista!E26,'bbdd.5.final'!$Z:$Z,$F$13,'bbdd.5.final'!$J:$J,"Opex") -> 51928.553 | I26: =I25+1 -> 11 | J26: =L26/$L$15 -> 0.0022267755 | K26: =_xlfn.XLOOKUP($I26,'rubros_id_opex (2)'!$B:$B,'rubros_id_opex (2)'!$A:$A) -> REPARACIONES | L26: =SUMIFS('bbdd.5.final'!$Y:$Y,'bbdd.5.final'!$AA:$AA,Vista!I26,'bbdd.5.final'!$Z:$Z,$J$13,'bbdd.5.final'!$J:$J,"Opex") -> 93450.888 | M26: =M25+1 -> 11 | N26: =P26/$P$15 -> 0.0027013463 | O26: =_xlfn.XLOOKUP($M26,'rubros_id_opex (2)'!$B:$B,'rubros_id_opex (2)'!$A:$A) -> REPARACIONES | P26: =SUMIFS('bbdd.5.final'!$Y:$Y,'bbdd.5.final'!$AA:$AA,Vista!M26,'bbdd.5.final'!$Z:$Z,$N$13,'bbdd.5.final'!$J:$J,"Opex") -> 299084.08
A27: =A26+1 -> 12 | B27: =D27/$D$15 -> 0.00037186012 | C27: =_xlfn.XLOOKUP($A27,'rubros_id_opex (2)'!$B:$B,'rubros_id_opex (2)'!$A:$A) -> REPOSICION | D27: =SUMIFS('bbdd.5.final'!$Y:$Y,'bbdd.5.final'!$AA:$AA,Vista!A27,'bbdd.5.final'!$Z:$Z,$B$13,'bbdd.5.final'!$J:$J,"Opex") -> 7049.8235 | E27: =E26+1 -> 12 | F27: =H27/$H$15 -> 0.057910753 | G27: =_xlfn.XLOOKUP($E27,'rubros_id_opex (2)'!$B:$B,'rubros_id_opex (2)'!$A:$A) -> REPOSICION | H27: =SUMIFS('bbdd.5.final'!$Y:$Y,'bbdd.5.final'!$AA:$AA,Vista!E27,'bbdd.5.final'!$Z:$Z,$F$13,'bbdd.5.final'!$J:$J,"Opex") -> 1885929.1 | I27: =I26+1 -> 12 | J27: =L27/$L$15 -> 0.017503327 | K27: =_xlfn.XLOOKUP($I27,'rubros_id_opex (2)'!$B:$B,'rubros_id_opex (2)'!$A:$A) -> REPOSICION | L27: =SUMIFS('bbdd.5.final'!$Y:$Y,'bbdd.5.final'!$AA:$AA,Vista!I27,'bbdd.5.final'!$Z:$Z,$J$13,'bbdd.5.final'!$J:$J,"Opex") -> 734560.57 | M27: =M26+1 -> 12 | N27: =P27/$P$15 -> 0.00051834381 | O27: =_xlfn.XLOOKUP($M27,'rubros_id_opex (2)'!$B:$B,'rubros_id_opex (2)'!$A:$A) -> REPOSICION | P27: =SUMIFS('bbdd.5.final'!$Y:$Y,'bbdd.5.final'!$AA:$AA,Vista!M27,'bbdd.5.final'!$Z:$Z,$N$13,'bbdd.5.final'!$J:$J,"Opex") -> 57389.304
A28: =A27+1 -> 13 | B28: =D28/$D$15 -> 0.0068228391 | C28: =_xlfn.XLOOKUP($A28,'rubros_id_opex (2)'!$B:$B,'rubros_id_opex (2)'!$A:$A) -> SERVICIOS | D28: =SUMIFS('bbdd.5.final'!$Y:$Y,'bbdd.5.final'!$AA:$AA,Vista!A28,'bbdd.5.final'!$Z:$Z,$B$13,'bbdd.5.final'!$J:$J,"Opex") -> 129349.21 | E28: =E27+1 -> 13 | F28: =H28/$H$15 -> 0.048726497 | G28: =_xlfn.XLOOKUP($E28,'rubros_id_opex (2)'!$B:$B,'rubros_id_opex (2)'!$A:$A) -> SERVICIOS | H28: =SUMIFS('bbdd.5.final'!$Y:$Y,'bbdd.5.final'!$AA:$AA,Vista!E28,'bbdd.5.final'!$Z:$Z,$F$13,'bbdd.5.final'!$J:$J,"Opex") -> 1586833.4 | I28: =I27+1 -> 13 | J28: =L28/$L$15 -> 0.068045837 | K28: =_xlfn.XLOOKUP($I28,'rubros_id_opex (2)'!$B:$B,'rubros_id_opex (2)'!$A:$A) -> SERVICIOS | L28: =SUMIFS('bbdd.5.final'!$Y:$Y,'bbdd.5.final'!$AA:$AA,Vista!I28,'bbdd.5.final'!$Z:$Z,$J$13,'bbdd.5.final'!$J:$J,"Opex") -> 2855673.5 | M28: =M27+1 -> 13 | N28: =P28/$P$15 -> 0.0095105022 | O28: =_xlfn.XLOOKUP($M28,'rubros_id_opex (2)'!$B:$B,'rubros_id_opex (2)'!$A:$A) -> SERVICIOS | P28: =SUMIFS('bbdd.5.final'!$Y:$Y,'bbdd.5.final'!$AA:$AA,Vista!M28,'bbdd.5.final'!$Z:$Z,$N$13,'bbdd.5.final'!$J:$J,"Opex") -> 1052971.2
A29: =A28+1 -> 14 | B29: =D29/$D$15 -> 0 | C29: =_xlfn.XLOOKUP($A29,'rubros_id_opex (2)'!$B:$B,'rubros_id_opex (2)'!$A:$A) -> COMERCIAL | D29: =SUMIFS('bbdd.5.final'!$Y:$Y,'bbdd.5.final'!$AA:$AA,Vista!A29,'bbdd.5.final'!$Z:$Z,$B$13,'bbdd.5.final'!$J:$J,"Opex") -> 0 | E29: =E28+1 -> 14 | F29: =H29/$H$15 -> 0 | G29: =_xlfn.XLOOKUP($E29,'rubros_id_opex (2)'!$B:$B,'rubros_id_opex (2)'!$A:$A) -> COMERCIAL | H29: =SUMIFS('bbdd.5.final'!$Y:$Y,'bbdd.5.final'!$AA:$AA,Vista!E29,'bbdd.5.final'!$Z:$Z,$F$13,'bbdd.5.final'!$J:$J,"Opex") -> 0 | I29: =I28+1 -> 14 | J29: =L29/$L$15 -> 0 | K29: =_xlfn.XLOOKUP($I29,'rubros_id_opex (2)'!$B:$B,'rubros_id_opex (2)'!$A:$A) -> COMERCIAL | L29: =SUMIFS('bbdd.5.final'!$Y:$Y,'bbdd.5.final'!$AA:$AA,Vista!I29,'bbdd.5.final'!$Z:$Z,$J$13,'bbdd.5.final'!$J:$J,"Opex") -> 0 | M29: =M28+1 -> 14 | N29: =P29/$P$15 -> 0 | O29: =_xlfn.XLOOKUP($M29,'rubros_id_opex (2)'!$B:$B,'rubros_id_opex (2)'!$A:$A) -> COMERCIAL | P29: =SUMIFS('bbdd.5.final'!$Y:$Y,'bbdd.5.final'!$AA:$AA,Vista!M29,'bbdd.5.final'!$Z:$Z,$N$13,'bbdd.5.final'!$J:$J,"Opex") -> 0
B31: VENTAS | D31: =SUMIFS(BBDD_INGRESOS_FINAL!$O:$O,BBDD_INGRESOS_FINAL!$D:$D,B14) -> 15491941 | F31: VENTAS | H31: =SUMIFS(BBDD_INGRESOS_FINAL!$O:$O,BBDD_INGRESOS_FINAL!$D:$D,F14) -> 1.9005242e+08 | J31: VENTAS | L31: =SUMIFS(BBDD_INGRESOS_FINAL!$O:$O,BBDD_INGRESOS_FINAL!$D:$D,J14) -> 3.420193e+08 | N31: VENTAS | P31: =SUMIFS(BBDD_INGRESOS_FINAL!$O:$O,BBDD_INGRESOS_FINAL!$D:$D,N14) -> 1.2611262e+08
B33: UTILDAD | D33: =D31-D15 -> -3466326.3 | F33: UTILDAD | H33: =H31-H15 -> 1.5748629e+08 | J33: UTILDAD | L33: =L31-L15 -> 3.0005239e+08 | N33: UTILDAD | P33: =P31-P15 -> 15395944
B35: CAPEX | D35: =SUMIFS('bbdd.5.final'!$Y:$Y,'bbdd.5.final'!$J:$J,"Capex",'bbdd.5.final'!$Z:$Z,$B$13) -> 32937.085 | F35: CAPEX | H35: =SUMIFS('bbdd.5.final'!$Y:$Y,'bbdd.5.final'!$J:$J,"Capex",'bbdd.5.final'!$Z:$Z,$F$13) -> 1.5116069e+08 | J35: CAPEX | L35: =SUMIFS('bbdd.5.final'!$Y:$Y,'bbdd.5.final'!$J:$J,"Capex",'bbdd.5.final'!$Z:$Z,$J$13) -> 4670762.8 | N35: CAPEX | P35: =SUMIFS('bbdd.5.final'!$Y:$Y,'bbdd.5.final'!$J:$J,"Capex",'bbdd.5.final'!$Z:$Z,$N$13) -> 996837.73
B37: DEUDA | D37: =SUMIFS('bbdd.5.final'!$Y:$Y,'bbdd.5.final'!$J:$J,"Deuda",'bbdd.5.final'!$V:$V,B14) -> 7365.0902 | F37: DEUDA | H37: =SUMIFS('bbdd.5.final'!$Y:$Y,'bbdd.5.final'!$J:$J,"Deuda",'bbdd.5.final'!$V:$V,F14) -> 90353.638 | J37: DEUDA | L37: =SUMIFS('bbdd.5.final'!$Y:$Y,'bbdd.5.final'!$J:$J,"deuda",'bbdd.5.final'!$V:$V,J14) -> 162600.87 | N37: DEUDA | P37: =SUMIFS('bbdd.5.final'!$Y:$Y,'bbdd.5.final'!$J:$J,"deuda",'bbdd.5.final'!$V:$V,N14) -> 59955.743
B39: Flujo de Caja al Accionista | D39: =D33-D37-D35 -> -3506628.5 | F39: Flujo de Caja al Accionista | H39: =H33-H37-H35 -> 6235251.6 | J39: Flujo de Caja al Accionista | L39: =L33-L37-L35 -> 2.9521903e+08 | N39: Flujo de Caja al Accionista | P39: =P33-P37-P35 -> 14339151
A41: id | B41: 1 | E41: id | F41: 6 | I41: id | J41: 10 | M41: id | N41: 2
B42: BACHAS | F42: NFU | J42: COMPOST & FERTILIZANTES | N42: CEREAL & POLVILLO
B43: OPEX | D43: =SUM(D44:D57) -> 1.4810693e+08 | F43: OPEX | H43: =SUM(H44:H57) -> 51486940 | J43: OPEX | L43: =SUM(L44:L57) -> 9378920.8 | N43: OPEX | P43: =SUM(P44:P57) -> 10563263
A44: 1 | B44: =D44/$D$43 -> 0.051410619 | C44: =_xlfn.XLOOKUP($A44,'rubros_id_opex (2)'!$B:$B,'rubros_id_opex (2)'!$A:$A) -> ENERGIA | D44: =SUMIFS('bbdd.5.final'!$Y:$Y,'bbdd.5.final'!$AA:$AA,Vista!A44,'bbdd.5.final'!$Z:$Z,$B$41,'bbdd.5.final'!$J:$J,"Opex") -> 7614268.9 | E44: 1 | F44: =H44/$H$43 -> 0.3042523 | G44: =_xlfn.XLOOKUP($A44,'rubros_id_opex (2)'!$B:$B,'rubros_id_opex (2)'!$A:$A) -> ENERGIA | H44: =SUMIFS('bbdd.5.final'!$Y:$Y,'bbdd.5.final'!$AA:$AA,Vista!E44,'bbdd.5.final'!$Z:$Z,$F$41,'bbdd.5.final'!$J:$J,"Opex") -> 15665020 | I44: 1 | J44: =L44/$L$43 -> 0.00048472998 | K44: =_xlfn.XLOOKUP($A44,'rubros_id_opex (2)'!$B:$B,'rubros_id_opex (2)'!$A:$A) -> ENERGIA | L44: =SUMIFS('bbdd.5.final'!$Y:$Y,'bbdd.5.final'!$AA:$AA,Vista!I44,'bbdd.5.final'!$Z:$Z,$J$41,'bbdd.5.final'!$J:$J,"Opex") -> 4546.2441 | M44: 1 | N44: =P44/$P$43 -> 0.0071483316 | O44: =_xlfn.XLOOKUP($A44,'rubros_id_opex (2)'!$B:$B,'rubros_id_opex (2)'!$A:$A) -> ENERGIA | P44: =SUMIFS('bbdd.5.final'!$Y:$Y,'bbdd.5.final'!$AA:$AA,Vista!M44,'bbdd.5.final'!$Z:$Z,$N$41,'bbdd.5.final'!$J:$J,"Opex") -> 75509.708
A45: =A44+1 -> 2 | B45: =D45/$D$43 -> 0 | C45: =_xlfn.XLOOKUP($A45,'rubros_id_opex (2)'!$B:$B,'rubros_id_opex (2)'!$A:$A) -> HABILITACIONES Y CERT | D45: =SUMIFS('bbdd.5.final'!$Y:$Y,'bbdd.5.final'!$AA:$AA,Vista!A45,'bbdd.5.final'!$Z:$Z,$B$41,'bbdd.5.final'!$J:$J,"Opex") -> 0 | E45: =E44+1 -> 2 | F45: =H45/$H$43 -> 0 | G45: =_xlfn.XLOOKUP($A45,'rubros_id_opex (2)'!$B:$B,'rubros_id_opex (2)'!$A:$A) -> HABILITACIONES Y CERT | H45: =SUMIFS('bbdd.5.final'!$Y:$Y,'bbdd.5.final'!$AA:$AA,Vista!E45,'bbdd.5.final'!$Z:$Z,$F$41,'bbdd.5.final'!$J:$J,"Opex") -> 0 | I45: =I44+1 -> 2 | J45: =L45/$L$43 -> 0 | K45: =_xlfn.XLOOKUP($A45,'rubros_id_opex (2)'!$B:$B,'rubros_id_opex (2)'!$A:$A) -> HABILITACIONES Y CERT | L45: =SUMIFS('bbdd.5.final'!$Y:$Y,'bbdd.5.final'!$AA:$AA,Vista!I45,'bbdd.5.final'!$Z:$Z,$J$41,'bbdd.5.final'!$J:$J,"Opex") -> 0 | M45: =M44+1 -> 2 | N45: =P45/$P$43 -> 0 | O45: =_xlfn.XLOOKUP($A45,'rubros_id_opex (2)'!$B:$B,'rubros_id_opex (2)'!$A:$A) -> HABILITACIONES Y CERT | P45: =SUMIFS('bbdd.5.final'!$Y:$Y,'bbdd.5.final'!$AA:$AA,Vista!M45,'bbdd.5.final'!$Z:$Z,$N$41,'bbdd.5.final'!$J:$J,"Opex") -> 0
A46: =A45+1 -> 3 | B46: =D46/$D$43 -> 0.00096064554 | C46: =_xlfn.XLOOKUP($A46,'rubros_id_opex (2)'!$B:$B,'rubros_id_opex (2)'!$A:$A) -> HIGIENE Y SEGURIDAD | D46: =SUMIFS('bbdd.5.final'!$Y:$Y,'bbdd.5.final'!$AA:$AA,Vista!A46,'bbdd.5.final'!$Z:$Z,$B$41,'bbdd.5.final'!$J:$J,"Opex") -> 142278.26 | E46: =E45+1 -> 3 | F46: =H46/$H$43 -> 0.0011989944 | G46: =_xlfn.XLOOKUP($A46,'rubros_id_opex (2)'!$B:$B,'rubros_id_opex (2)'!$A:$A) -> HIGIENE Y SEGURIDAD | H46: =SUMIFS('bbdd.5.final'!$Y:$Y,'bbdd.5.final'!$AA:$AA,Vista!E46,'bbdd.5.final'!$Z:$Z,$F$41,'bbdd.5.final'!$J:$J,"Opex") -> 61732.551 | I46: =I45+1 -> 3 | J46: =L46/$L$43 -> 0.00019024136 | K46: =_xlfn.XLOOKUP($A46,'rubros_id_opex (2)'!$B:$B,'rubros_id_opex (2)'!$A:$A) -> HIGIENE Y SEGURIDAD | L46: =SUMIFS('bbdd.5.final'!$Y:$Y,'bbdd.5.final'!$AA:$AA,Vista!I46,'bbdd.5.final'!$Z:$Z,$J$41,'bbdd.5.final'!$J:$J,"Opex") -> 1784.2587 | M46: =M45+1 -> 3 | N46: =P46/$P$43 -> 0.0029332672 | O46: =_xlfn.XLOOKUP($A46,'rubros_id_opex (2)'!$B:$B,'rubros_id_opex (2)'!$A:$A) -> HIGIENE Y SEGURIDAD | P46: =SUMIFS('bbdd.5.final'!$Y:$Y,'bbdd.5.final'!$AA:$AA,Vista!M46,'bbdd.5.final'!$Z:$Z,$N$41,'bbdd.5.final'!$J:$J,"Opex") -> 30984.873
A47: =A46+1 -> 4 | B47: =D47/$D$43 -> 0.0011101544 | C47: =_xlfn.XLOOKUP($A47,'rubros_id_opex (2)'!$B:$B,'rubros_id_opex (2)'!$A:$A) -> IMPUESTOS | D47: =SUMIFS('bbdd.5.final'!$Y:$Y,'bbdd.5.final'!$AA:$AA,Vista!A47,'bbdd.5.final'!$Z:$Z,$B$41,'bbdd.5.final'!$J:$J,"Opex") -> 164421.56 | E47: =E46+1 -> 4 | F47: =H47/$H$43 -> 0.017955747 | G47: =_xlfn.XLOOKUP($A47,'rubros_id_opex (2)'!$B:$B,'rubros_id_opex (2)'!$A:$A) -> IMPUESTOS | H47: =SUMIFS('bbdd.5.final'!$Y:$Y,'bbdd.5.final'!$AA:$AA,Vista!E47,'bbdd.5.final'!$Z:$Z,$F$41,'bbdd.5.final'!$J:$J,"Opex") -> 924486.49 | I47: =I46+1 -> 4 | J47: =L47/$L$43 -> 0.01796493 | K47: =_xlfn.XLOOKUP($A47,'rubros_id_opex (2)'!$B:$B,'rubros_id_opex (2)'!$A:$A) -> IMPUESTOS | L47: =SUMIFS('bbdd.5.final'!$Y:$Y,'bbdd.5.final'!$AA:$AA,Vista!I47,'bbdd.5.final'!$Z:$Z,$J$41,'bbdd.5.final'!$J:$J,"Opex") -> 168491.66 | M47: =M46+1 -> 4 | N47: =P47/$P$43 -> 0.0033897826 | O47: =_xlfn.XLOOKUP($A47,'rubros_id_opex (2)'!$B:$B,'rubros_id_opex (2)'!$A:$A) -> IMPUESTOS | P47: =SUMIFS('bbdd.5.final'!$Y:$Y,'bbdd.5.final'!$AA:$AA,Vista!M47,'bbdd.5.final'!$Z:$Z,$N$41,'bbdd.5.final'!$J:$J,"Opex") -> 35807.165
A48: =A47+1 -> 5 | B48: =D48/$D$43 -> 0.02273382 | C48: =_xlfn.XLOOKUP($A48,'rubros_id_opex (2)'!$B:$B,'rubros_id_opex (2)'!$A:$A) -> INSUMOS | D48: =SUMIFS('bbdd.5.final'!$Y:$Y,'bbdd.5.final'!$AA:$AA,Vista!A48,'bbdd.5.final'!$Z:$Z,$B$41,'bbdd.5.final'!$J:$J,"Opex") -> 3367036.3 | E48: =E47+1 -> 5 | F48: =H48/$H$43 -> 0.00053482048 | G48: =_xlfn.XLOOKUP($A48,'rubros_id_opex (2)'!$B:$B,'rubros_id_opex (2)'!$A:$A) -> INSUMOS | H48: =SUMIFS('bbdd.5.final'!$Y:$Y,'bbdd.5.final'!$AA:$AA,Vista!E48,'bbdd.5.final'!$Z:$Z,$F$41,'bbdd.5.final'!$J:$J,"Opex") -> 27536.27 | I48: =I47+1 -> 5 | J48: =L48/$L$43 -> 8.4858593e-05 | K48: =_xlfn.XLOOKUP($A48,'rubros_id_opex (2)'!$B:$B,'rubros_id_opex (2)'!$A:$A) -> INSUMOS | L48: =SUMIFS('bbdd.5.final'!$Y:$Y,'bbdd.5.final'!$AA:$AA,Vista!I48,'bbdd.5.final'!$Z:$Z,$J$41,'bbdd.5.final'!$J:$J,"Opex") -> 795.88202 | M48: =M47+1 -> 5 | N48: =P48/$P$43 -> 0.0013084059 | O48: =_xlfn.XLOOKUP($A48,'rubros_id_opex (2)'!$B:$B,'rubros_id_opex (2)'!$A:$A) -> INSUMOS | P48: =SUMIFS('bbdd.5.final'!$Y:$Y,'bbdd.5.final'!$AA:$AA,Vista!M48,'bbdd.5.final'!$Z:$Z,$N$41,'bbdd.5.final'!$J:$J,"Opex") -> 13821.036
A49: =A48+1 -> 6 | B49: =D49/$D$43 -> 0 | C49: =_xlfn.XLOOKUP($A49,'rubros_id_opex (2)'!$B:$B,'rubros_id_opex (2)'!$A:$A) -> INVERSION | D49: =SUMIFS('bbdd.5.final'!$Y:$Y,'bbdd.5.final'!$AA:$AA,Vista!A49,'bbdd.5.final'!$Z:$Z,$B$41,'bbdd.5.final'!$J:$J,"Opex") -> 0 | E49: =E48+1 -> 6 | F49: =H49/$H$43 -> 0 | G49: =_xlfn.XLOOKUP($A49,'rubros_id_opex (2)'!$B:$B,'rubros_id_opex (2)'!$A:$A) -> INVERSION | H49: =SUMIFS('bbdd.5.final'!$Y:$Y,'bbdd.5.final'!$AA:$AA,Vista!E49,'bbdd.5.final'!$Z:$Z,$F$41,'bbdd.5.final'!$J:$J,"Opex") -> 0 | I49: =I48+1 -> 6 | J49: =L49/$L$43 -> 0 | K49: =_xlfn.XLOOKUP($A49,'rubros_id_opex (2)'!$B:$B,'rubros_id_opex (2)'!$A:$A) -> INVERSION | L49: =SUMIFS('bbdd.5.final'!$Y:$Y,'bbdd.5.final'!$AA:$AA,Vista!I49,'bbdd.5.final'!$Z:$Z,$J$41,'bbdd.5.final'!$J:$J,"Opex") -> 0 | M49: =M48+1 -> 6 | N49: =P49/$P$43 -> 0 | O49: =_xlfn.XLOOKUP($A49,'rubros_id_opex (2)'!$B:$B,'rubros_id_opex (2)'!$A:$A) -> INVERSION | P49: =SUMIFS('bbdd.5.final'!$Y:$Y,'bbdd.5.final'!$AA:$AA,Vista!M49,'bbdd.5.final'!$Z:$Z,$N$41,'bbdd.5.final'!$J:$J,"Opex") -> 0
A50: =A49+1 -> 7 | B50: =D50/$D$43 -> 0 | C50: =_xlfn.XLOOKUP($A50,'rubros_id_opex (2)'!$B:$B,'rubros_id_opex (2)'!$A:$A) -> LOGISTICA | D50: =SUMIFS('bbdd.5.final'!$Y:$Y,'bbdd.5.final'!$AA:$AA,Vista!A50,'bbdd.5.final'!$Z:$Z,$B$41,'bbdd.5.final'!$J:$J,"Opex") -> 0 | E50: =E49+1 -> 7 | F50: =H50/$H$43 -> 7.5203537e-05 | G50: =_xlfn.XLOOKUP($A50,'rubros_id_opex (2)'!$B:$B,'rubros_id_opex (2)'!$A:$A) -> LOGISTICA | H50: =SUMIFS('bbdd.5.final'!$Y:$Y,'bbdd.5.final'!$AA:$AA,Vista!E50,'bbdd.5.final'!$Z:$Z,$F$41,'bbdd.5.final'!$J:$J,"Opex") -> 3872 | I50: =I49+1 -> 7 | J50: =L50/$L$43 -> 0 | K50: =_xlfn.XLOOKUP($A50,'rubros_id_opex (2)'!$B:$B,'rubros_id_opex (2)'!$A:$A) -> LOGISTICA | L50: =SUMIFS('bbdd.5.final'!$Y:$Y,'bbdd.5.final'!$AA:$AA,Vista!I50,'bbdd.5.final'!$Z:$Z,$J$41,'bbdd.5.final'!$J:$J,"Opex") -> 0 | M50: =M49+1 -> 7 | N50: =P50/$P$43 -> 0.048564538 | O50: =_xlfn.XLOOKUP($A50,'rubros_id_opex (2)'!$B:$B,'rubros_id_opex (2)'!$A:$A) -> LOGISTICA | P50: =SUMIFS('bbdd.5.final'!$Y:$Y,'bbdd.5.final'!$AA:$AA,Vista!M50,'bbdd.5.final'!$Z:$Z,$N$41,'bbdd.5.final'!$J:$J,"Opex") -> 513000
A51: =A50+1 -> 8 | B51: =D51/$D$43 -> 0.80662785 | C51: =_xlfn.XLOOKUP($A51,'rubros_id_opex (2)'!$B:$B,'rubros_id_opex (2)'!$A:$A) -> M.PRIMAS | D51: =SUMIFS('bbdd.5.final'!$Y:$Y,'bbdd.5.final'!$AA:$AA,Vista!A51,'bbdd.5.final'!$Z:$Z,$B$41,'bbdd.5.final'!$J:$J,"Opex") -> 1.1946717e+08 | E51: =E50+1 -> 8 | F51: =H51/$H$43 -> 0 | G51: =_xlfn.XLOOKUP($A51,'rubros_id_opex (2)'!$B:$B,'rubros_id_opex (2)'!$A:$A) -> M.PRIMAS | H51: =SUMIFS('bbdd.5.final'!$Y:$Y,'bbdd.5.final'!$AA:$AA,Vista!E51,'bbdd.5.final'!$Z:$Z,$F$41,'bbdd.5.final'!$J:$J,"Opex") -> 0 | I51: =I50+1 -> 8 | J51: =L51/$L$43 -> 0 | K51: =_xlfn.XLOOKUP($A51,'rubros_id_opex (2)'!$B:$B,'rubros_id_opex (2)'!$A:$A) -> M.PRIMAS | L51: =SUMIFS('bbdd.5.final'!$Y:$Y,'bbdd.5.final'!$AA:$AA,Vista!I51,'bbdd.5.final'!$Z:$Z,$J$41,'bbdd.5.final'!$J:$J,"Opex") -> 0 | M51: =M50+1 -> 8 | N51: =P51/$P$43 -> 0 | O51: =_xlfn.XLOOKUP($A51,'rubros_id_opex (2)'!$B:$B,'rubros_id_opex (2)'!$A:$A) -> M.PRIMAS | P51: =SUMIFS('bbdd.5.final'!$Y:$Y,'bbdd.5.final'!$AA:$AA,Vista!M51,'bbdd.5.final'!$Z:$Z,$N$41,'bbdd.5.final'!$J:$J,"Opex") -> 0
A52: =A51+1 -> 9 | B52: =D52/$D$43 -> 0.00078284928 | C52: =_xlfn.XLOOKUP($A52,'rubros_id_opex (2)'!$B:$B,'rubros_id_opex (2)'!$A:$A) -> MANTENIMIENTO PREVENTIVO | D52: =SUMIFS('bbdd.5.final'!$Y:$Y,'bbdd.5.final'!$AA:$AA,Vista!A52,'bbdd.5.final'!$Z:$Z,$B$41,'bbdd.5.final'!$J:$J,"Opex") -> 115945.4 | E52: =E51+1 -> 9 | F52: =H52/$H$43 -> 0.00097708452 | G52: =_xlfn.XLOOKUP($A52,'rubros_id_opex (2)'!$B:$B,'rubros_id_opex (2)'!$A:$A) -> MANTENIMIENTO PREVENTIVO | H52: =SUMIFS('bbdd.5.final'!$Y:$Y,'bbdd.5.final'!$AA:$AA,Vista!E52,'bbdd.5.final'!$Z:$Z,$F$41,'bbdd.5.final'!$J:$J,"Opex") -> 50307.092 | I52: =I51+1 -> 9 | J52: =L52/$L$43 -> 0.00015503149 | K52: =_xlfn.XLOOKUP($A52,'rubros_id_opex (2)'!$B:$B,'rubros_id_opex (2)'!$A:$A) -> MANTENIMIENTO PREVENTIVO | L52: =SUMIFS('bbdd.5.final'!$Y:$Y,'bbdd.5.final'!$AA:$AA,Vista!I52,'bbdd.5.final'!$Z:$Z,$J$41,'bbdd.5.final'!$J:$J,"Opex") -> 1454.0281 | M52: =M51+1 -> 9 | N52: =P52/$P$43 -> 0.0023903781 | O52: =_xlfn.XLOOKUP($A52,'rubros_id_opex (2)'!$B:$B,'rubros_id_opex (2)'!$A:$A) -> MANTENIMIENTO PREVENTIVO | P52: =SUMIFS('bbdd.5.final'!$Y:$Y,'bbdd.5.final'!$AA:$AA,Vista!M52,'bbdd.5.final'!$Z:$Z,$N$41,'bbdd.5.final'!$J:$J,"Opex") -> 25250.193
A53: =A52+1 -> 10 | B53: =D53/$D$43 -> 0.11005844 | C53: =_xlfn.XLOOKUP($A53,'rubros_id_opex (2)'!$B:$B,'rubros_id_opex (2)'!$A:$A) -> PERSONAL | D53: =SUMIFS('bbdd.5.final'!$Y:$Y,'bbdd.5.final'!$AA:$AA,Vista!A53,'bbdd.5.final'!$Z:$Z,$B$41,'bbdd.5.final'!$J:$J,"Opex") -> 16300418 | E53: =E52+1 -> 10 | F53: =H53/$H$43 -> 0.59425252 | G53: =_xlfn.XLOOKUP($A53,'rubros_id_opex (2)'!$B:$B,'rubros_id_opex (2)'!$A:$A) -> PERSONAL | H53: =SUMIFS('bbdd.5.final'!$Y:$Y,'bbdd.5.final'!$AA:$AA,Vista!E53,'bbdd.5.final'!$Z:$Z,$F$41,'bbdd.5.final'!$J:$J,"Opex") -> 30596244 | I53: =I52+1 -> 10 | J53: =L53/$L$43 -> 0.9798695 | K53: =_xlfn.XLOOKUP($A53,'rubros_id_opex (2)'!$B:$B,'rubros_id_opex (2)'!$A:$A) -> PERSONAL | L53: =SUMIFS('bbdd.5.final'!$Y:$Y,'bbdd.5.final'!$AA:$AA,Vista!I53,'bbdd.5.final'!$Z:$Z,$J$41,'bbdd.5.final'!$J:$J,"Opex") -> 9190118.4 | M53: =M52+1 -> 10 | N53: =P53/$P$43 -> 0.91498098 | O53: =_xlfn.XLOOKUP($A53,'rubros_id_opex (2)'!$B:$B,'rubros_id_opex (2)'!$A:$A) -> PERSONAL | P53: =SUMIFS('bbdd.5.final'!$Y:$Y,'bbdd.5.final'!$AA:$AA,Vista!M53,'bbdd.5.final'!$Z:$Z,$N$41,'bbdd.5.final'!$J:$J,"Opex") -> 9665184.9
A54: =A53+1 -> 11 | B54: =D54/$D$43 -> 0.00019009489 | C54: =_xlfn.XLOOKUP($A54,'rubros_id_opex (2)'!$B:$B,'rubros_id_opex (2)'!$A:$A) -> REPARACIONES | D54: =SUMIFS('bbdd.5.final'!$Y:$Y,'bbdd.5.final'!$AA:$AA,Vista!A54,'bbdd.5.final'!$Z:$Z,$B$41,'bbdd.5.final'!$J:$J,"Opex") -> 28154.371 | E54: =E53+1 -> 11 | F54: =H54/$H$43 -> 0.00023725995 | G54: =_xlfn.XLOOKUP($A54,'rubros_id_opex (2)'!$B:$B,'rubros_id_opex (2)'!$A:$A) -> REPARACIONES | H54: =SUMIFS('bbdd.5.final'!$Y:$Y,'bbdd.5.final'!$AA:$AA,Vista!E54,'bbdd.5.final'!$Z:$Z,$F$41,'bbdd.5.final'!$J:$J,"Opex") -> 12215.789 | I54: =I53+1 -> 11 | J54: =L54/$L$43 -> 3.7645427e-05 | K54: =_xlfn.XLOOKUP($A54,'rubros_id_opex (2)'!$B:$B,'rubros_id_opex (2)'!$A:$A) -> REPARACIONES | L54: =SUMIFS('bbdd.5.final'!$Y:$Y,'bbdd.5.final'!$AA:$AA,Vista!I54,'bbdd.5.final'!$Z:$Z,$J$41,'bbdd.5.final'!$J:$J,"Opex") -> 353.07348 | M54: =M53+1 -> 11 | N54: =P54/$P$43 -> 0.00058044209 | O54: =_xlfn.XLOOKUP($A54,'rubros_id_opex (2)'!$B:$B,'rubros_id_opex (2)'!$A:$A) -> REPARACIONES | P54: =SUMIFS('bbdd.5.final'!$Y:$Y,'bbdd.5.final'!$AA:$AA,Vista!M54,'bbdd.5.final'!$Z:$Z,$N$41,'bbdd.5.final'!$J:$J,"Opex") -> 6131.3626
A55: =A54+1 -> 12 | B55: =D55/$D$43 -> 0.00031659937 | C55: =_xlfn.XLOOKUP($A55,'rubros_id_opex (2)'!$B:$B,'rubros_id_opex (2)'!$A:$A) -> REPOSICION | D55: =SUMIFS('bbdd.5.final'!$Y:$Y,'bbdd.5.final'!$AA:$AA,Vista!A55,'bbdd.5.final'!$Z:$Z,$B$41,'bbdd.5.final'!$J:$J,"Opex") -> 46890.56 | E55: =E54+1 -> 12 | F55: =H55/$H$43 -> 0.024989046 | G55: =_xlfn.XLOOKUP($A55,'rubros_id_opex (2)'!$B:$B,'rubros_id_opex (2)'!$A:$A) -> REPOSICION | H55: =SUMIFS('bbdd.5.final'!$Y:$Y,'bbdd.5.final'!$AA:$AA,Vista!E55,'bbdd.5.final'!$Z:$Z,$F$41,'bbdd.5.final'!$J:$J,"Opex") -> 1286609.5 | I55: =I54+1 -> 12 | J55: =L55/$L$43 -> 6.269773e-05 | K55: =_xlfn.XLOOKUP($A55,'rubros_id_opex (2)'!$B:$B,'rubros_id_opex (2)'!$A:$A) -> REPOSICION | L55: =SUMIFS('bbdd.5.final'!$Y:$Y,'bbdd.5.final'!$AA:$AA,Vista!I55,'bbdd.5.final'!$Z:$Z,$J$41,'bbdd.5.final'!$J:$J,"Opex") -> 588.03705 | M55: =M54+1 -> 12 | N55: =P55/$P$43 -> 0.00096671508 | O55: =_xlfn.XLOOKUP($A55,'rubros_id_opex (2)'!$B:$B,'rubros_id_opex (2)'!$A:$A) -> REPOSICION | P55: =SUMIFS('bbdd.5.final'!$Y:$Y,'bbdd.5.final'!$AA:$AA,Vista!M55,'bbdd.5.final'!$Z:$Z,$N$41,'bbdd.5.final'!$J:$J,"Opex") -> 10211.666
A56: =A55+1 -> 13 | B56: =D56/$D$43 -> 0.0058089224 | C56: =_xlfn.XLOOKUP($A56,'rubros_id_opex (2)'!$B:$B,'rubros_id_opex (2)'!$A:$A) -> SERVICIOS | D56: =SUMIFS('bbdd.5.final'!$Y:$Y,'bbdd.5.final'!$AA:$AA,Vista!A56,'bbdd.5.final'!$Z:$Z,$B$41,'bbdd.5.final'!$J:$J,"Opex") -> 860341.66 | E56: =E55+1 -> 13 | F56: =H56/$H$43 -> 0.055527018 | G56: =_xlfn.XLOOKUP($A56,'rubros_id_opex (2)'!$B:$B,'rubros_id_opex (2)'!$A:$A) -> SERVICIOS | H56: =SUMIFS('bbdd.5.final'!$Y:$Y,'bbdd.5.final'!$AA:$AA,Vista!E56,'bbdd.5.final'!$Z:$Z,$F$41,'bbdd.5.final'!$J:$J,"Opex") -> 2858916.2 | I56: =I55+1 -> 13 | J56: =L56/$L$43 -> 0.0011503695 | K56: =_xlfn.XLOOKUP($A56,'rubros_id_opex (2)'!$B:$B,'rubros_id_opex (2)'!$A:$A) -> SERVICIOS | L56: =SUMIFS('bbdd.5.final'!$Y:$Y,'bbdd.5.final'!$AA:$AA,Vista!I56,'bbdd.5.final'!$Z:$Z,$J$41,'bbdd.5.final'!$J:$J,"Opex") -> 10789.224 | M56: =M55+1 -> 13 | N56: =P56/$P$43 -> 0.017737158 | O56: =_xlfn.XLOOKUP($A56,'rubros_id_opex (2)'!$B:$B,'rubros_id_opex (2)'!$A:$A) -> SERVICIOS | P56: =SUMIFS('bbdd.5.final'!$Y:$Y,'bbdd.5.final'!$AA:$AA,Vista!M56,'bbdd.5.final'!$Z:$Z,$N$41,'bbdd.5.final'!$J:$J,"Opex") -> 187362.26
A57: =A56+1 -> 14 | B57: =D57/$D$43 -> 0 | C57: =_xlfn.XLOOKUP($A57,'rubros_id_opex (2)'!$B:$B,'rubros_id_opex (2)'!$A:$A) -> COMERCIAL | D57: =SUMIFS('bbdd.5.final'!$Y:$Y,'bbdd.5.final'!$AA:$AA,Vista!A57,'bbdd.5.final'!$Z:$Z,$B$41,'bbdd.5.final'!$J:$J,"Opex") -> 0 | E57: =E56+1 -> 14 | F57: =H57/$H$43 -> 0 | G57: =_xlfn.XLOOKUP($A57,'rubros_id_opex (2)'!$B:$B,'rubros_id_opex (2)'!$A:$A) -> COMERCIAL | H57: =SUMIFS('bbdd.5.final'!$Y:$Y,'bbdd.5.final'!$AA:$AA,Vista!E57,'bbdd.5.final'!$Z:$Z,$F$41,'bbdd.5.final'!$J:$J,"Opex") -> 0 | I57: =I56+1 -> 14 | J57: =L57/$L$43 -> 0 | K57: =_xlfn.XLOOKUP($A57,'rubros_id_opex (2)'!$B:$B,'rubros_id_opex (2)'!$A:$A) -> COMERCIAL | L57: =SUMIFS('bbdd.5.final'!$Y:$Y,'bbdd.5.final'!$AA:$AA,Vista!I57,'bbdd.5.final'!$Z:$Z,$J$41,'bbdd.5.final'!$J:$J,"Opex") -> 0 | M57: =M56+1 -> 14 | N57: =P57/$P$43 -> 0 | O57: =_xlfn.XLOOKUP($A57,'rubros_id_opex (2)'!$B:$B,'rubros_id_opex (2)'!$A:$A) -> COMERCIAL | P57: =SUMIFS('bbdd.5.final'!$Y:$Y,'bbdd.5.final'!$AA:$AA,Vista!M57,'bbdd.5.final'!$Z:$Z,$N$41,'bbdd.5.final'!$J:$J,"Opex") -> 0
B59: VENTAS | D59: =SUMIFS(BBDD_INGRESOS_FINAL!$O:$O,BBDD_INGRESOS_FINAL!$D:$D,B42) -> 1.030417e+08 | F59: VENTAS | H59: =SUMIFS(BBDD_INGRESOS_FINAL!$O:$O,BBDD_INGRESOS_FINAL!$D:$D,F42) -> 44708355 | J59: VENTAS | L59: =SUMIFS(BBDD_INGRESOS_FINAL!$O:$O,BBDD_INGRESOS_FINAL!$D:$D,J42) -> 1292207.6 | N59: VENTAS | P59: =SUMIFS(BBDD_INGRESOS_FINAL!$O:$O,BBDD_INGRESOS_FINAL!$D:$D,N42) -> 22440069
B61: UTILDAD | D61: =D59-D43 -> -45065229 | F61: UTILDAD | H61: =H59-H43 -> -6778584.5 | J61: UTILDAD | L61: =L59-L43 -> -8086713.3 | N61: UTILDAD | P61: =P59-P43 -> 11876806
B63: CAPEX | D63: =SUMIFS('bbdd.5.final'!$Y:$Y,'bbdd.5.final'!$J:$J,"Capex",'bbdd.5.final'!$Z:$Z,$B$41) -> 23865410 | F63: CAPEX | H63: =SUMIFS('bbdd.5.final'!$Y:$Y,'bbdd.5.final'!$J:$J,"Capex",'bbdd.5.final'!$Z:$Z,$F$41) -> 95053.479 | J63: CAPEX | L63: =SUMIFS('bbdd.5.final'!$Y:$Y,'bbdd.5.final'!$J:$J,"Capex",'bbdd.5.final'!$Z:$Z,$J$41) -> 2747.3349 | N63: CAPEX | P63: =SUMIFS('bbdd.5.final'!$Y:$Y,'bbdd.5.final'!$J:$J,"Capex",'bbdd.5.final'!$Z:$Z,$N$41) -> 47709.351
O64: INVERSION
B65: DEUDA | D65: =SUMIFS('bbdd.5.final'!$Y:$Y,'bbdd.5.final'!$J:$J,"deuda",'bbdd.5.final'!$V:$V,B42) -> 48987.497 | F65: DEUDA | H65: =SUMIFS('bbdd.5.final'!$Y:$Y,'bbdd.5.final'!$J:$J,"deuda",'bbdd.5.final'!$V:$V,F42) -> 21254.991 | J65: DEUDA | L65: =SUMIFS('bbdd.5.final'!$Y:$Y,'bbdd.5.final'!$J:$J,"deuda",'bbdd.5.final'!$V:$V,J42) -> 614.33395 | N65: DEUDA | P65: =SUMIFS('bbdd.5.final'!$Y:$Y,'bbdd.5.final'!$J:$J,"deuda",'bbdd.5.final'!$V:$V,N42) -> 10668.33
B67: Flujo de Caja al Accionista | D67: =D61-D65-D63 -> -68979626 | F67: Flujo de Caja al Accionista | H67: =H61-H65-H63 -> -6894893 | J67: Flujo de Caja al Accionista | L67: =L61-L65-L63 -> -8090074.9 | N67: Flujo de Caja al Accionista | P67: =P61-P65-P63 -> 11818428
A69: id | B69: 9 | E69: id | F69: 5
B70: EXPORTACION
B71: OPEX | D71: =SUM(D72:D85) -> 2.3103874e+09
A72: 1 | B72: =D72/D71 -> 0.0038371603 | C72: =_xlfn.XLOOKUP($E72,'rubros_id_opex (2)'!$B:$B,'rubros_id_opex (2)'!$A:$A) -> ENERGIA | D72: =SUMIFS('bbdd.5.final'!$Y:$Y,'bbdd.5.final'!$AA:$AA,Vista!E72,'bbdd.5.final'!$Z:$Z,$F$69,'bbdd.5.final'!$J:$J,"Opex") -> 8865326.8 | E72: 1 | I72: 1
A73: =A72+1 -> 2 | B73: =D73/$D$71 -> 0.00062586907 | C73: =_xlfn.XLOOKUP($E73,'rubros_id_opex (2)'!$B:$B,'rubros_id_opex (2)'!$A:$A) -> HABILITACIONES Y CERT | D73: =SUMIFS('bbdd.5.final'!$Y:$Y,'bbdd.5.final'!$AA:$AA,Vista!E73,'bbdd.5.final'!$Z:$Z,$F$69,'bbdd.5.final'!$J:$J,"Opex") -> 1446000 | E73: =E72+1 -> 2 | I73: =I72+1 -> 2
A74: =A73+1 -> 3 | B74: =D74/$D$71 -> 0.0013945663 | C74: =_xlfn.XLOOKUP($E74,'rubros_id_opex (2)'!$B:$B,'rubros_id_opex (2)'!$A:$A) -> HIGIENE Y SEGURIDAD | D74: =SUMIFS('bbdd.5.final'!$Y:$Y,'bbdd.5.final'!$AA:$AA,Vista!E74,'bbdd.5.final'!$Z:$Z,$F$69,'bbdd.5.final'!$J:$J,"Opex") -> 3221988.5 | E74: =E73+1 -> 3 | I74: =I73+1 -> 3
A75: =A74+1 -> 4 | B75: =D75/$D$71 -> 0.002788246 | C75: =_xlfn.XLOOKUP($E75,'rubros_id_opex (2)'!$B:$B,'rubros_id_opex (2)'!$A:$A) -> IMPUESTOS | D75: =SUMIFS('bbdd.5.final'!$Y:$Y,'bbdd.5.final'!$AA:$AA,Vista!E75,'bbdd.5.final'!$Z:$Z,$F$69,'bbdd.5.final'!$J:$J,"Opex") -> 6441928.5 | E75: =E74+1 -> 4 | I75: =I74+1 -> 4
A76: =A75+1 -> 5 | B76: =D76/$D$71 -> 0.00065668305 | C76: =_xlfn.XLOOKUP($E76,'rubros_id_opex (2)'!$B:$B,'rubros_id_opex (2)'!$A:$A) -> INSUMOS | D76: =SUMIFS('bbdd.5.final'!$Y:$Y,'bbdd.5.final'!$AA:$AA,Vista!E76,'bbdd.5.final'!$Z:$Z,$F$69,'bbdd.5.final'!$J:$J,"Opex") -> 1517192.2 | E76: =E75+1 -> 5 | I76: =I75+1 -> 5
A77: =A76+1 -> 6 | B77: =D77/$D$71 -> 0 | C77: =_xlfn.XLOOKUP($E77,'rubros_id_opex (2)'!$B:$B,'rubros_id_opex (2)'!$A:$A) -> INVERSION | D77: =SUMIFS('bbdd.5.final'!$Y:$Y,'bbdd.5.final'!$AA:$AA,Vista!E77,'bbdd.5.final'!$Z:$Z,$F$69,'bbdd.5.final'!$J:$J,"Opex") -> 0 | E77: =E76+1 -> 6 | I77: =I76+1 -> 6
A78: =A77+1 -> 7 | B78: =D78/$D$71 -> 0.010709673 | C78: =_xlfn.XLOOKUP($E78,'rubros_id_opex (2)'!$B:$B,'rubros_id_opex (2)'!$A:$A) -> LOGISTICA | D78: =SUMIFS('bbdd.5.final'!$Y:$Y,'bbdd.5.final'!$AA:$AA,Vista!E78,'bbdd.5.final'!$Z:$Z,$F$69,'bbdd.5.final'!$J:$J,"Opex") -> 24743492 | E78: =E77+1 -> 7 | I78: =I77+1 -> 7
A79: =A78+1 -> 8 | B79: =D79/$D$71 -> 0.9364996 | C79: =_xlfn.XLOOKUP($E79,'rubros_id_opex (2)'!$B:$B,'rubros_id_opex (2)'!$A:$A) -> M.PRIMAS | D79: =SUMIFS('bbdd.5.final'!$Y:$Y,'bbdd.5.final'!$AA:$AA,Vista!E79,'bbdd.5.final'!$Z:$Z,$F$69,'bbdd.5.final'!$J:$J,"Opex") -> 2.1636769e+09 | E79: =E78+1 -> 8 | I79: =I78+1 -> 8
A80: =A79+1 -> 9 | B80: =D80/$D$71 -> 0.00113646 | C80: =_xlfn.XLOOKUP($E80,'rubros_id_opex (2)'!$B:$B,'rubros_id_opex (2)'!$A:$A) -> MANTENIMIENTO PREVENTIVO | D80: =SUMIFS('bbdd.5.final'!$Y:$Y,'bbdd.5.final'!$AA:$AA,Vista!E80,'bbdd.5.final'!$Z:$Z,$F$69,'bbdd.5.final'!$J:$J,"Opex") -> 2625662.9 | E80: =E79+1 -> 9 | I80: =I79+1 -> 9
A81: =A80+1 -> 10 | B81: =D81/$D$71 -> 0.020370557 | C81: =_xlfn.XLOOKUP($E81,'rubros_id_opex (2)'!$B:$B,'rubros_id_opex (2)'!$A:$A) -> PERSONAL | D81: =SUMIFS('bbdd.5.final'!$Y:$Y,'bbdd.5.final'!$AA:$AA,Vista!E81,'bbdd.5.final'!$Z:$Z,$F$69,'bbdd.5.final'!$J:$J,"Opex") -> 47063878 | E81: =E80+1 -> 10 | I81: =I80+1 -> 10
A82: =A81+1 -> 11 | B82: =D82/$D$71 -> 0.0002759602 | C82: =_xlfn.XLOOKUP($E82,'rubros_id_opex (2)'!$B:$B,'rubros_id_opex (2)'!$A:$A) -> REPARACIONES | D82: =SUMIFS('bbdd.5.final'!$Y:$Y,'bbdd.5.final'!$AA:$AA,Vista!E82,'bbdd.5.final'!$Z:$Z,$F$69,'bbdd.5.final'!$J:$J,"Opex") -> 637574.97 | E82: =E81+1 -> 11 | I82: =I81+1 -> 11
A83: =A82+1 -> 12 | B83: =D83/$D$71 -> 0.00045960638 | C83: =_xlfn.XLOOKUP($E83,'rubros_id_opex (2)'!$B:$B,'rubros_id_opex (2)'!$A:$A) -> REPOSICION | D83: =SUMIFS('bbdd.5.final'!$Y:$Y,'bbdd.5.final'!$AA:$AA,Vista!E83,'bbdd.5.final'!$Z:$Z,$F$69,'bbdd.5.final'!$J:$J,"Opex") -> 1061868.8 | E83: =E82+1 -> 12 | I83: =I82+1 -> 12
A84: =A83+1 -> 13 | B84: =D84/$D$71 -> 0.021245614 | C84: =_xlfn.XLOOKUP($E84,'rubros_id_opex (2)'!$B:$B,'rubros_id_opex (2)'!$A:$A) -> SERVICIOS | D84: =SUMIFS('bbdd.5.final'!$Y:$Y,'bbdd.5.final'!$AA:$AA,Vista!E84,'bbdd.5.final'!$Z:$Z,$F$69,'bbdd.5.final'!$J:$J,"Opex") -> 49085599 | E84: =E83+1 -> 13 | I84: =I83+1 -> 13
A85: =A84+1 -> 14 | B85: =D85/$D$71 -> 0 | C85: =_xlfn.XLOOKUP($E85,'rubros_id_opex (2)'!$B:$B,'rubros_id_opex (2)'!$A:$A) -> COMERCIAL | D85: =SUMIFS('bbdd.5.final'!$Y:$Y,'bbdd.5.final'!$AA:$AA,Vista!E85,'bbdd.5.final'!$Z:$Z,$F$69,'bbdd.5.final'!$J:$J,"Opex") -> 0 | E85: =E84+1 -> 14 | I85: =I84+1 -> 14
B88: VENTAS | D88: =SUMIFS(BBDD_INGRESOS_FINAL!$O:$O,BBDD_INGRESOS_FINAL!$D:$D,B70) -> 2.3334497e+09
B90: UTILDAD | D90: =D88-D71 -> 23062348
B92: CAPEX | D92: =SUMIFS('bbdd.5.final'!$Y:$Y,'bbdd.5.final'!$J:$J,"Capex",'bbdd.5.final'!$Z:$Z,$F$69) -> 6940369.8
B94: DEUDA | D94: =SUMIFS('bbdd.5.final'!$Y:$Y,'bbdd.5.final'!$J:$J,"deuda",'bbdd.5.final'!$V:$V,B70) -> 1109355.4
B96: Flujo de Caja al Accionista | D96: =D90-D94-D92 -> 15012623
B109: CHECK
B111: PRODUCCION_UN | C111: =#REF!+D59+H59+L59+P59+P31+L31+H31+D31+D88 -> #REF!
B112: PRODUCCION_TOTAL | C112: =C6 -> 3.1786083e+09
C113: =C111=C112 -> #REF!
B115: OPEX UN | C115: =D15+H15+L15+P15+P43+L43+H43+D43+#REF!+D71+L71 -> #REF!
B116: OPEX total | C116: =C7 -> 2.7341314e+09
C117: =MROUND(C116,10000)=MROUND(C115,10000) -> #REF!
B119: CAPEX_UN | C119: =D35+H35+L35+P35+P63+L63+H63+D63+#REF!+D92+L92 -> #REF!
B120: CAPEX_TOTAL | C120: =C9 -> 1.8781251e+08 | D120: =C119=C120 -> #REF!
B121: DEUDA_UN | C121: =D37+H37+L37+P37+P65+L65+H65+D65+#REF!+D94+L94 -> #REF!
B122: DEUDA_TOTAL | C122: =C10 -> 1511155.8 | D122: =C121=C122 -> #REF!
B126: UTILIDAD_TOTAL | C126: =C8 -> 4.4447693e+08
B127: UTILIDAD_UN | C127: =D33+H33+L33+P33+P61+L61+H61+D61+#REF!+D90+L90 -> #REF! | D127: =MROUND(C127,10000)=MROUND(C126,10000) -> #REF!
B130: Flujo_TOTAL | C130: =C11 -> 2.5515326e+08
B131: FLUJO_UN | C131: =D39+H39+L39+P39+P67+L67+H67+D67+#REF!+D96+L96 -> #REF! | D131: =MROUND(C131,10000)=MROUND(C130,10000) -> #REF!

Sheet val1
A1: VENTAS
A2: CEREAL & POLVILLO | B2: =Vista!P59 -> 22440069
A3: DISPOSICIÓN FINAL RESIDUOS SOLIDOS | B3: =Vista!D31 -> 15491941 | E3: Row Labels | F3: Sum of TOTAL
A4: DISPOSICIÓN FINAL RESIDUOS LIQUIDOS | B4: =Vista!$H$31 -> 1.9005242e+08 | E4: BACHAS | F4: 1.030417e+08
A5: =Vista!J14 -> PILETAS | B5: =Vista!$L$31 -> 3.420193e+08 | E5: CEREAL & POLVILLO | F5: 22440069
A6: =Vista!N14 -> REACTORES | B6: =Vista!$P$31 -> 1.2611262e+08 | E6: COMPOST & FERTILIZANTES | F6: 1292207.6
A7: =Vista!B42 -> BACHAS | B7: =Vista!D59 -> 1.030417e+08 | E7: DISPOSICIÓN FINAL RESIDUOS LIQUIDOS | F7: 1.9005242e+08
A8: =Vista!F42 -> NFU | B8: =Vista!H59 -> 44708355 | E8: DISPOSICIÓN FINAL RESIDUOS SOLIDOS | F8: 15491941
A9: =Vista!J42 -> COMPOST & FERTILIZANTES | B9: =Vista!L59 -> 1292207.6 | E9: EXPORTACION | F9: 2.3334497e+09
A10: =Vista!#REF! -> #REF! | B10: =Vista!#REF! -> #REF! | E10: NFU | F10: 44708355
A11: =Vista!B70 -> EXPORTACION | B11: =Vista!D88 -> 2.3334497e+09 | E11: PILETAS | F11: 3.420193e+08
A12: SALES | B12: =GETPIVOTDATA("TOTAL",$E$3,"SECTOR","SALES") -> #REF! | E12: REACTORES | F12: 1.2611262e+08
A13: SUB-TOTAL | B13: =SUM(B2:B12) -> #REF! | E13: Grand Total | F13: 3.1786083e+09
A15: TOTAL | B15: =GETPIVOTDATA("TOTAL",$E$3) -> 3.1786083e+09
B18: =B15=B13 -> #REF!

Sheet Vista_R_sin_expo
B2: SIN EXPORTACIÓN
B3: TOTAL
B4: OPEX | D4: =SUM(D5:D18) -> 4.2374404e+08
A5: 1 | B5: =D5/$D$4 -> 0.13154334 | C5: =_xlfn.XLOOKUP($A5,'rubros_id_opex (2)'!$B:$B,'rubros_id_opex (2)'!$A:$A) -> ENERGIA | D5: =SUMIFS('bbdd.5.final'!$Y:$Y,'bbdd.5.final'!$AA:$AA,A5,'bbdd.5.final'!$J:$J,"Opex",'bbdd.5.final'!$Z:$Z,"<>5") -> 55740706
A6: =A5+1 -> 2 | B6: =D6/$D$4 -> 0 | C6: =_xlfn.XLOOKUP($A6,'rubros_id_opex (2)'!$B:$B,'rubros_id_opex (2)'!$A:$A) -> HABILITACIONES Y CERT | D6: =SUMIFS('bbdd.5.final'!$Y:$Y,'bbdd.5.final'!$AA:$AA,A6,'bbdd.5.final'!$J:$J,"Opex",'bbdd.5.final'!$Z:$Z,"<>5") -> 0
A7: =A6+1 -> 3 | B7: =D7/$D$4 -> 0.002753976 | C7: =_xlfn.XLOOKUP($A7,'rubros_id_opex (2)'!$B:$B,'rubros_id_opex (2)'!$A:$A) -> HIGIENE Y SEGURIDAD | D7: =SUMIFS('bbdd.5.final'!$Y:$Y,'bbdd.5.final'!$AA:$AA,A7,'bbdd.5.final'!$J:$J,"Opex",'bbdd.5.final'!$Z:$Z,"<>5") -> 1166980.9
A8: =A7+1 -> 4 | B8: =D8/$D$4 -> 0.0078273667 | C8: =_xlfn.XLOOKUP($A8,'rubros_id_opex (2)'!$B:$B,'rubros_id_opex (2)'!$A:$A) -> IMPUESTOS | D8: =SUMIFS('bbdd.5.final'!$Y:$Y,'bbdd.5.final'!$AA:$AA,A8,'bbdd.5.final'!$J:$J,"Opex",'bbdd.5.final'!$Z:$Z,"<>5") -> 3316800
A9: =A8+1 -> 5 | B9: =D9/$D$4 -> 0.17587487 | C9: =_xlfn.XLOOKUP($A9,'rubros_id_opex (2)'!$B:$B,'rubros_id_opex (2)'!$A:$A) -> INSUMOS | D9: =SUMIFS('bbdd.5.final'!$Y:$Y,'bbdd.5.final'!$AA:$AA,A9,'bbdd.5.final'!$J:$J,"Opex",'bbdd.5.final'!$Z:$Z,"<>5") -> 74525929
A10: =A9+1 -> 6 | B10: =D10/$D$4 -> 0 | C10: =_xlfn.XLOOKUP($A10,'rubros_id_opex (2)'!$B:$B,'rubros_id_opex (2)'!$A:$A) -> INVERSION | D10: =SUMIFS('bbdd.5.final'!$Y:$Y,'bbdd.5.final'!$AA:$AA,A10,'bbdd.5.final'!$J:$J,"Opex",'bbdd.5.final'!$Z:$Z,"<>5") -> 0
A11: =A10+1 -> 7 | B11: =D11/$D$4 -> 0.0012197741 | C11: =_xlfn.XLOOKUP($A11,'rubros_id_opex (2)'!$B:$B,'rubros_id_opex (2)'!$A:$A) -> LOGISTICA | D11: =SUMIFS('bbdd.5.final'!$Y:$Y,'bbdd.5.final'!$AA:$AA,A11,'bbdd.5.final'!$J:$J,"Opex",'bbdd.5.final'!$Z:$Z,"<>5") -> 516872
A12: =A11+1 -> 8 | B12: =D12/$D$4 -> 0.28395129 | C12: =_xlfn.XLOOKUP($A12,'rubros_id_opex (2)'!$B:$B,'rubros_id_opex (2)'!$A:$A) -> M.PRIMAS | D12: =SUMIFS('bbdd.5.final'!$Y:$Y,'bbdd.5.final'!$AA:$AA,A12,'bbdd.5.final'!$J:$J,"Opex",'bbdd.5.final'!$Z:$Z,"<>5") -> 1.2032267e+08
A13: =A12+1 -> 9 | B13: =D13/$D$4 -> 0.0034075481 | C13: =_xlfn.XLOOKUP($A13,'rubros_id_opex (2)'!$B:$B,'rubros_id_opex (2)'!$A:$A) -> MANTENIMIENTO PREVENTIVO | D13: =SUMIFS('bbdd.5.final'!$Y:$Y,'bbdd.5.final'!$AA:$AA,A13,'bbdd.5.final'!$J:$J,"Opex",'bbdd.5.final'!$Z:$Z,"<>5") -> 1443928.2
A14: =A13+1 -> 10 | B14: =D14/$D$4 -> 0.36022486 | C14: =_xlfn.XLOOKUP($A14,'rubros_id_opex (2)'!$B:$B,'rubros_id_opex (2)'!$A:$A) -> PERSONAL | D14: =SUMIFS('bbdd.5.final'!$Y:$Y,'bbdd.5.final'!$AA:$AA,A14,'bbdd.5.final'!$J:$J,"Opex",'bbdd.5.final'!$Z:$Z,"<>5") -> 1.5264314e+08
A15: =A14+1 -> 11 | B15: =D15/$D$4 -> 0.0011694584 | C15: =_xlfn.XLOOKUP($A15,'rubros_id_opex (2)'!$B:$B,'rubros_id_opex (2)'!$A:$A) -> REPARACIONES | D15: =SUMIFS('bbdd.5.final'!$Y:$Y,'bbdd.5.final'!$AA:$AA,A15,'bbdd.5.final'!$J:$J,"Opex",'bbdd.5.final'!$Z:$Z,"<>5") -> 495551.03
A16: =A15+1 -> 12 | B16: =D16/$D$4 -> 0.0095086379 | C16: =_xlfn.XLOOKUP($A16,'rubros_id_opex (2)'!$B:$B,'rubros_id_opex (2)'!$A:$A) -> REPOSICION | D16: =SUMIFS('bbdd.5.final'!$Y:$Y,'bbdd.5.final'!$AA:$AA,A16,'bbdd.5.final'!$J:$J,"Opex",'bbdd.5.final'!$Z:$Z,"<>5") -> 4029228.6
A17: =A16+1 -> 13 | B17: =D17/$D$4 -> 0.02251887 | C17: =_xlfn.XLOOKUP($A17,'rubros_id_opex (2)'!$B:$B,'rubros_id_opex (2)'!$A:$A) -> SERVICIOS | D17: =SUMIFS('bbdd.5.final'!$Y:$Y,'bbdd.5.final'!$AA:$AA,A17,'bbdd.5.final'!$J:$J,"Opex",'bbdd.5.final'!$Z:$Z,"<>5") -> 9542236.8
A18: =A17+1 -> 14 | B18: =D18/$D$4 -> 0 | C18: =_xlfn.XLOOKUP($A18,'rubros_id_opex (2)'!$B:$B,'rubros_id_opex (2)'!$A:$A) -> COMERCIAL | D18: =SUMIFS('bbdd.5.final'!$Y:$Y,'bbdd.5.final'!$AA:$AA,A18,'bbdd.5.final'!$J:$J,"Opex",'bbdd.5.final'!$Z:$Z,"<>5") -> 0
B20: VENTAS | D20: =SUMIFS(BBDD_INGRESOS_FINAL!$O:$O,BBDD_INGRESOS_FINAL!$R:$R,"<>5") -> 8.4515862e+08
B22: UTILDAD | D22: =D20-D4 -> 4.2141458e+08
B24: CAPEX | D24: =SUMIFS('bbdd.5.final'!$Y:$Y,'bbdd.5.final'!$J:$J,"Capex",'bbdd.5.final'!$Z:$Z,"<>5") -> 1.8087214e+08
B26: DEUDA | D26: =SUMIFS('bbdd.5.final'!$Y:$Y,'bbdd.5.final'!$J:$J,"Deuda",'bbdd.5.final'!$Z:$Z,"<>5") -> 401800.49
B28: Flujo de Caja al Accionista | D28: =D22-D24-D26 -> 2.4014064e+08
B31: VENTAS
B32: Row Labels | C32: Sum of TOTAL | D32: prc
B33: PILETAS | C33: 3.420193e+08 | D33: =C33/$C$41 -> 0.40468061
B34: DISPOSICIÓN FINAL RESIDUOS LIQUIDOS | C34: 1.9005242e+08 | D34: =C34/$C$41 -> 0.2248719
B35: REACTORES | C35: 1.2611262e+08 | D35: =C35/$C$41 -> 0.1492177
B36: BACHAS | C36: 1.030417e+08 | D36: =C36/$C$41 -> 0.12191995
B37: NFU | C37: 44708355 | D37: =C37/$C$41 -> 0.052899366
B38: CEREAL & POLVILLO | C38: 22440069 | D38: =C38/$C$41 -> 0.026551311
B39: DISPOSICIÓN FINAL RESIDUOS SOLIDOS | C39: 15491941 | D39: =C39/$C$41 -> 0.018330217
B40: COMPOST & FERTILIZANTES | C40: 1292207.6 | D40: =C40/$C$41 -> 0.0015289527
B41: Grand Total | C41: 8.4515862e+08 | D41: =C41/$C$41 -> 1
B44: COSTOS
B45: Row Labels | C45: Sum of MONTO_FINAL
B46: DISP. FINAL RESIDUOS LÍQUIDOS | C46: 2.3490818e+08 | D46: =C46/$C$54 -> 0.3571559
B47: BACHAS | C47: 1.7240266e+08 | D47: =C47/$C$54 -> 0.26212211
B48: REACTORES | C48: 1.1198631e+08 | D48: =C48/$C$54 -> 0.1702647
B49: NFU | C49: 51768705 | D49: =C49/$C$54 -> 0.07870947
B50: PILETAS | C50: 47505376 | D50: =C50/$C$54 -> 0.072227477
B51: DISP. FINAL RESIDUOS SÓLIDOS | C51: 19055902 | D51: =C51/$C$54 -> 0.028972715
B52: CEREAL & POLVILLO | C52: 10704687 | D52: =C52/$C$54 -> 0.016275475
B53: COMPOST & FERTILIZANTES | C53: 9387064.7 | D53: =C53/$C$54 -> 0.014272153
B54: Grand Total | C54: 6.5771889e+08 | D54: =C54/$C$54 -> 1

Sheet Vista_RUBRO
B2: CON EXPORTACIÓN INCLUÍDA
B3: TOTAL
B4: OPEX | D4: =SUM(D5:D18) -> 2.7341314e+09
A5: 1 | B5: =D5/$D$4 -> 0.023629454 | C5: =_xlfn.XLOOKUP($A5,'rubros_id_opex (2)'!$B:$B,'rubros_id_opex (2)'!$A:$A) -> ENERGIA | D5: =SUMIFS('bbdd.5.final'!$Y:$Y,'bbdd.5.final'!$AA:$AA,A5,'bbdd.5.final'!$J:$J,"Opex") -> 64606033
A6: =A5+1 -> 2 | B6: =D6/$D$4 -> 0.00052886997 | C6: =_xlfn.XLOOKUP($A6,'rubros_id_opex (2)'!$B:$B,'rubros_id_opex (2)'!$A:$A) -> HABILITACIONES Y CERT | D6: =SUMIFS('bbdd.5.final'!$Y:$Y,'bbdd.5.final'!$AA:$AA,A6,'bbdd.5.final'!$J:$J,"Opex") -> 1446000
A7: =A6+1 -> 3 | B7: =D7/$D$4 -> 0.0016052518 | C7: =_xlfn.XLOOKUP($A7,'rubros_id_opex (2)'!$B:$B,'rubros_id_opex (2)'!$A:$A) -> HIGIENE Y SEGURIDAD | D7: =SUMIFS('bbdd.5.final'!$Y:$Y,'bbdd.5.final'!$AA:$AA,A7,'bbdd.5.final'!$J:$J,"Opex") -> 4388969.4
A8: =A7+1 -> 4 | B8: =D8/$D$4 -> 0.0035692244 | C8: =_xlfn.XLOOKUP($A8,'rubros_id_opex (2)'!$B:$B,'rubros_id_opex (2)'!$A:$A) -> IMPUESTOS | D8: =SUMIFS('bbdd.5.final'!$Y:$Y,'bbdd.5.final'!$AA:$AA,A8,'bbdd.5.final'!$J:$J,"Opex") -> 9758728.5
A9: =A8+1 -> 5 | B9: =D9/$D$4 -> 0.027812533 | C9: =_xlfn.XLOOKUP($A9,'rubros_id_opex (2)'!$B:$B,'rubros_id_opex (2)'!$A:$A) -> INSUMOS | D9: =SUMIFS('bbdd.5.final'!$Y:$Y,'bbdd.5.final'!$AA:$AA,A9,'bbdd.5.final'!$J:$J,"Opex") -> 76043122
A10: =A9+1 -> 6 | B10: =D10/$D$4 -> 0 | C10: =_xlfn.XLOOKUP($A10,'rubros_id_opex (2)'!$B:$B,'rubros_id_opex (2)'!$A:$A) -> INVERSION | D10: =SUMIFS('bbdd.5.final'!$Y:$Y,'bbdd.5.final'!$AA:$AA,A10,'bbdd.5.final'!$J:$J,"Opex") -> 0
A11: =A10+1 -> 7 | B11: =D11/$D$4 -> 0.0092388991 | C11: =_xlfn.XLOOKUP($A11,'rubros_id_opex (2)'!$B:$B,'rubros_id_opex (2)'!$A:$A) -> LOGISTICA | D11: =SUMIFS('bbdd.5.final'!$Y:$Y,'bbdd.5.final'!$AA:$AA,A11,'bbdd.5.final'!$J:$J,"Opex") -> 25260364
A12: =A11+1 -> 8 | B12: =D12/$D$4 -> 0.83536567 | C12: =_xlfn.XLOOKUP($A12,'rubros_id_opex (2)'!$B:$B,'rubros_id_opex (2)'!$A:$A) -> M.PRIMAS | D12: =SUMIFS('bbdd.5.final'!$Y:$Y,'bbdd.5.final'!$AA:$AA,A12,'bbdd.5.final'!$J:$J,"Opex") -> 2.2839995e+09
A13: =A12+1 -> 9 | B13: =D13/$D$4 -> 0.0014884402 | C13: =_xlfn.XLOOKUP($A13,'rubros_id_opex (2)'!$B:$B,'rubros_id_opex (2)'!$A:$A) -> MANTENIMIENTO PREVENTIVO | D13: =SUMIFS('bbdd.5.final'!$Y:$Y,'bbdd.5.final'!$AA:$AA,A13,'bbdd.5.final'!$J:$J,"Opex") -> 4069591.1
A14: =A13+1 -> 10 | B14: =D14/$D$4 -> 0.073042215 | C14: =_xlfn.XLOOKUP($A14,'rubros_id_opex (2)'!$B:$B,'rubros_id_opex (2)'!$A:$A) -> PERSONAL | D14: =SUMIFS('bbdd.5.final'!$Y:$Y,'bbdd.5.final'!$AA:$AA,A14,'bbdd.5.final'!$J:$J,"Opex") -> 1.9970702e+08
A15: =A14+1 -> 11 | B15: =D15/$D$4 -> 0.00041443728 | C15: =_xlfn.XLOOKUP($A15,'rubros_id_opex (2)'!$B:$B,'rubros_id_opex (2)'!$A:$A) -> REPARACIONES | D15: =SUMIFS('bbdd.5.final'!$Y:$Y,'bbdd.5.final'!$AA:$AA,A15,'bbdd.5.final'!$J:$J,"Opex") -> 1133126
A16: =A15+1 -> 12 | B16: =D16/$D$4 -> 0.0018620529 | C16: =_xlfn.XLOOKUP($A16,'rubros_id_opex (2)'!$B:$B,'rubros_id_opex (2)'!$A:$A) -> REPOSICION | D16: =SUMIFS('bbdd.5.final'!$Y:$Y,'bbdd.5.final'!$AA:$AA,A16,'bbdd.5.final'!$J:$J,"Opex") -> 5091097.4
A17: =A16+1 -> 13 | B17: =D17/$D$4 -> 0.021442947 | C17: =_xlfn.XLOOKUP($A17,'rubros_id_opex (2)'!$B:$B,'rubros_id_opex (2)'!$A:$A) -> SERVICIOS | D17: =SUMIFS('bbdd.5.final'!$Y:$Y,'bbdd.5.final'!$AA:$AA,A17,'bbdd.5.final'!$J:$J,"Opex") -> 58627836
A18: =A17+1 -> 14 | B18: =D18/$D$4 -> 0 | C18: =_xlfn.XLOOKUP($A18,'rubros_id_opex (2)'!$B:$B,'rubros_id_opex (2)'!$A:$A) -> COMERCIAL | D18: =SUMIFS('bbdd.5.final'!$Y:$Y,'bbdd.5.final'!$AA:$AA,A18,'bbdd.5.final'!$J:$J,"Opex") -> 0
B20: VENTAS | D20: =SUM(BBDD_INGRESOS_FINAL!$O:$O) -> 3.1786083e+09
B22: UTILDAD | D22: =D20-D4 -> 4.4447693e+08
B24: CAPEX | D24: =SUMIFS('bbdd.5.final'!$Y:$Y,'bbdd.5.final'!$J:$J,"Capex") -> 1.8781251e+08
B26: DEUDA | D26: =SUMIFS('bbdd.5.final'!$Y:$Y,'bbdd.5.final'!$J:$J,"Deuda") -> 1511155.8
B28: Flujo de Caja al Accionista | D28: =D22-D24-D26 -> 2.5515326e+08
B31: VENTAS
B32: Row Labels | C32: sectores_id.id_sector_2 | D32: Sum of TOTAL
B33: EXPORTACION | C33: 5 | D33: 2.3334497e+09
B34: PILETAS | C34: 7 | D34: 3.420193e+08
B35: DISPOSICIÓN FINAL RESIDUOS LIQUIDOS | C35: 3 | D35: 1.9005242e+08
B36: REACTORES | C36: 8 | D36: 1.2611262e+08
B37: BACHAS | C37: 1 | D37: 1.030417e+08
B38: NFU | C38: 6 | D38: 44708355
B39: CEREAL & POLVILLO | C39: 2 | D39: 22440069
B40: DISPOSICIÓN FINAL RESIDUOS SOLIDOS | C40: 4 | D40: 15491941
B41: COMPOST & FERTILIZANTES | C41: 10 | D41: 1292207.6
B42: Grand Total | C42: 10 | D42: 3.1786083e+09
B43: Concepto | C43: OPEX
B44: COSTOS_OPEX
B45: Row Labels | C45: Max of id_sector | D45: Sum of monto_final2
B46: EXPORTACION | C46: 5 | D46: 2.3103874e+09
B47: BACHAS | C47: 1 | D47: 1.4810693e+08
B48: REACTORES | C48: 8 | D48: 1.1071668e+08
B49: NFU | C49: 6 | D49: 51486940
B50: PILETAS | C50: 7 | D50: 41966910
B51: DISP. FINAL RESIDUOS LÍQUIDOS | C51: 3 | D51: 32566130
B52: DISP. FINAL RESIDUOS SÓLIDOS | C52: 4 | D52: 18958267
B53: CEREAL & POLVILLO | C53: 2 | D53: 10563263
B54: COMPOST & FERTILIZANTES | C54: 10 | D54: 9378920.8
B55: TIERRAS FILTRANTES | C55: 9 | D55: 0
B56: Grand Total | C56: 10 | D56: 2.7341314e+09
B60: SECTOR | C60: id | D60: VENTAS | E60: COSTOS_OPEX | F60: UTILIDAD
B61: EXPORTACION | C61: =_xlfn.XLOOKUP(B61,$B$46:$B$55,$C$46:$C$55) -> 5 | D61: =_xlfn.XLOOKUP(C61,$C$33:$C$41,$D$33:$D$41) -> 2.3334497e+09 | E61: =_xlfn.XLOOKUP(C61,$C$46:$C$55,$D$46:$D$55) -> 2.3103874e+09 | F61: =D61-E61 -> 23062348
B62: DISP. FINAL RESIDUOS LÍQUIDOS | C62: =_xlfn.XLOOKUP(B62,$B$46:$B$55,$C$46:$C$55) -> 3 | D62: =_xlfn.XLOOKUP(C62,$C$33:$C$41,$D$33:$D$41) -> 1.9005242e+08 | E62: =_xlfn.XLOOKUP(C62,$C$46:$C$55,$D$46:$D$55) -> 32566130 | F62: =D62-E62 -> 1.5748629e+08
B63: BACHAS | C63: =_xlfn.XLOOKUP(B63,$B$46:$B$55,$C$46:$C$55) -> 1 | D63: =_xlfn.XLOOKUP(C63,$C$33:$C$41,$D$33:$D$41) -> 1.030417e+08 | E63: =_xlfn.XLOOKUP(C63,$C$46:$C$55,$D$46:$D$55) -> 1.4810693e+08 | F63: =D63-E63 -> -45065229
B64: REACTORES | C64: =_xlfn.XLOOKUP(B64,$B$46:$B$55,$C$46:$C$55) -> 8 | D64: =_xlfn.XLOOKUP(C64,$C$33:$C$41,$D$33:$D$41) -> 1.2611262e+08 | E64: =_xlfn.XLOOKUP(C64,$C$46:$C$55,$D$46:$D$55) -> 1.1071668e+08 | F64: =D64-E64 -> 15395944
B65: NFU | C65: =_xlfn.XLOOKUP(B65,$B$46:$B$55,$C$46:$C$55) -> 6 | D65: =_xlfn.XLOOKUP(C65,$C$33:$C$41,$D$33:$D$41) -> 44708355 | E65: =_xlfn.XLOOKUP(C65,$C$46:$C$55,$D$46:$D$55) -> 51486940 | F65: =D65-E65 -> -6778584.5
B66: PILETAS | C66: =_xlfn.XLOOKUP(B66,$B$46:$B$55,$C$46:$C$55) -> 7 | D66: =_xlfn.XLOOKUP(C66,$C$33:$C$41,$D$33:$D$41) -> 3.420193e+08 | E66: =_xlfn.XLOOKUP(C66,$C$46:$C$55,$D$46:$D$55) -> 41966910 | F66: =D66-E66 -> 3.0005239e+08
B67: DISP. FINAL RESIDUOS SÓLIDOS | C67: =_xlfn.XLOOKUP(B67,$B$46:$B$55,$C$46:$C$55) -> 4 | D67: =_xlfn.XLOOKUP(C67,$C$33:$C$41,$D$33:$D$41) -> 15491941 | E67: =_xlfn.XLOOKUP(C67,$C$46:$C$55,$D$46:$D$55) -> 18958267 | F67: =D67-E67 -> -3466326.3
B68: COMPOST & FERTILIZANTES | C68: =_xlfn.XLOOKUP(B68,$B$46:$B$55,$C$46:$C$55) -> 10 | D68: =_xlfn.XLOOKUP(C68,$C$33:$C$41,$D$33:$D$41) -> 1292207.6 | E68: =_xlfn.XLOOKUP(C68,$C$46:$C$55,$D$46:$D$55) -> 9378920.8 | F68: =D68-E68 -> -8086713.3
B69: CEREAL & POLVILLO | C69: =_xlfn.XLOOKUP(B69,$B$46:$B$55,$C$46:$C$55) -> 2 | D69: =_xlfn.XLOOKUP(C69,$C$33:$C$41,$D$33:$D$41) -> 22440069 | E69: =_xlfn.XLOOKUP(C69,$C$46:$C$55,$D$46:$D$55) -> 10563263 | F69: =D69-E69 -> 11876806
B70: TIERRAS FILTRANTES | C70: =_xlfn.XLOOKUP(B70,$B$46:$B$55,$C$46:$C$55) -> 9 | D70: =_xlfn.XLOOKUP(C70,$C$33:$C$41,$D$33:$D$41,0) -> 0 | E70: =_xlfn.XLOOKUP(C70,$C$46:$C$55,$D$46:$D$55) -> 0 | F70: =D70-E70 -> 0

Sheet RRHH
C1: TOTAL 1+2 | D1: COMPONENTE
A2: ADMINISTRACION | B2: =_xlfn.CONCAT("RRHH-",A2) -> RRHH-ADMINISTRACION | C2: 67124149 | D2: 100% ADMINISTRACION - 100% DIRECTOR | E2: CC1
A3: INTENDENCIA | B3: =_xlfn.CONCAT("RRHH-",A3) -> RRHH-INTENDENCIA | C3: 9375237.7 | D3: 100% INTENDENCIA - 6,67% PRODUCCION | E3: CC1
A4: LABORATORIO | B4: =_xlfn.CONCAT("RRHH-",A4) -> RRHH-LABORATORIO | C4: 12249966 | D4: 100% LABORATORIO - 6,67% PRODUCCION | E4: CC1
A5: LOGISTICA | B5: =_xlfn.CONCAT("RRHH-",A5) -> RRHH-LOGISTICA | C5: 6459899.7 | D5: 75% LOGISTICA - 6,67% PRODUCCION | E5: CC1
A6: MANTENIMIENTO | B6: =_xlfn.CONCAT("RRHH-",A6) -> RRHH-MANTENIMIENTO | C6: 7742399.7 | D6: 100% MANTENIMIENTO - 6,67% PRODUCCION | E6: CC1
A7: NFU | B7: =_xlfn.CONCAT("RRHH-",A7) -> RRHH-NFU | C7: 29572095 | D7: 25% LOGISTICA - 100% CAT - 100% EXTERNO NFU - 6,67% PRODUCCION - 95% NFU | E7: CC7
A8: PORTERIA | B8: =_xlfn.CONCAT("RRHH-",A8) -> RRHH-PORTERIA | C8: 10797311 | D8: 100% PORTERIA - 6,67% PRODUCCION | E8: CC1
A9: COMPOST Y FERTILIZANTES | B9: =_xlfn.CONCAT("RRHH-",A9) -> RRHH-COMPOST Y FERTILIZANTES | C9: 1833599.1 | D9: 60% COMPOST Y FERTILIZANTES - 6,67% PRODUCCION | E9: CC14
A10: CEREAL Y POLVILLO | B10: =_xlfn.CONCAT("RRHH-",A10) -> RRHH-CEREAL Y POLVILLO | C10: 0 | D10: 0% CEREAL Y POLVILLO - 0% PRODUCCION | E10: NO
A11: TALLER MECANICO | B11: =_xlfn.CONCAT("RRHH-",A11) -> RRHH-TALLER MECANICO | C11: 6300478.7 | D11: 100% TALLER MECANICO - 6,67% PRODUCCION | E11: CC1
A12: TIERRAS FILTRANTES | B12: =_xlfn.CONCAT("RRHH-",A12) -> RRHH-TIERRAS FILTRANTES | C12: 0 | D12: 0% TIERRAS FILTRANTES - 0% PRODUCCION | E12: NO
A13: VIGILANCIA | B13: =_xlfn.CONCAT("RRHH-",A13) -> RRHH-VIGILANCIA | C13: 6294101.7 | D13: 100% VIGILANCIA - 6,67% PRODUCCION | E13: CC1
... A21: SALES | B21: =_xlfn.CONCAT("RRHH-",A21) -> RRHH-SALES | C21: 0 | D21: 0% SALES - 0% PRODUCCION | E21: NO

Sheet ref_rrhh
A1: Sector | B1: f/v | C1: d/i
A2: ADMINISTRACION | B2: Fijo | C2: Indirecto
A3: INTENDENCIA | B3: Fijo | C3: Indirecto
A4: REACTOR | B4: Variable | C4: Directo
A5: NFU | B5: Variable | C5: Directo
A6: DISPOSICION FINAL DE R. LIQUIDOS | B6: Variable | C6: Directo
A7: DIRECTOR | B7: Fijo | C7: Indirecto
A8: TALLER MECANICO | B8: Fijo | C8: Indirecto
A9: PRODUCCION | B9: Variable | C9: Directo
A10: CAT | B10: Variable | C10: Directo
A11: MANTENIMIENTO | B11: Fijo | C11: Indirecto
A12: PORTERIA | B12: Fijo | C12: Indirecto
... A17: COMPOST Y FERTILIZANTES | B17: Variable | C17: Directo

Sheet gastos_unificado.p0
A1: Fecha de Factura/Recibo | B1: Nombre de la empresa a mostrar en la factura | C1: Número | D1: Total con signo | E1: Líneas de factura/Etiqueta | F1: Líneas de factura/Cantidad | G1: Líneas de factura/Precio unitario | H1: Líneas de factura/Unidad de medida | I1: Líneas de factura/Producto | J1: Concepto | K1: Tipo de Gasto 1 | L1: Tipo de Gasto 2 | M1: CCO EMPRESA | N1: SECTOR | O1: Origen | P1: USD | Q1: SECTOR2 | R1: SUBRUBRO | S1: TC | T1: Total
A2: 46081 | B2: WORMS 2 | C2: prod17 | D2: -1.9004255e+09 | E2: AFE (S) | F2: 1403.96 | G2: 945 | H2: TN | I2: MATERIA PRIMA | J2: OPEX | K2: VARIABLE | L2: DIRECTO | N2: CC11 | O2: gastos_produccion | P2: 1432 | Q2: EXPORTACION | R2: AFE (S)
A3: 46081 | B3: WORMS 2 | C3: prod15 | D3: -1.1459658e+08 | E3: AFE (G) | F3: 86.96 | G3: 920 | H3: TN | I3: MATERIA PRIMA | J3: OPEX | K3: VARIABLE | L3: DIRECTO | N3: CC11 | O3: gastos_produccion | P3: 1432 | Q3: EXPORTACION | R3: AFE (G)
A4: 46081 | B4: WORMS 2 | C4: prod29 | D4: -87594125 | E4: ARE- B | F4: 72.8 | G4: 840 | H4: TN | I4: MATERIA PRIMA | J4: OPEX | K4: VARIABLE | L4: DIRECTO | N4: CC11 | O4: gastos_produccion | P4: 1432 | Q4: EXPORTACION | R4: ARE- B
A5: 46081 | B5: WORMS 1 | C5: prod26 | D5: -78996860 | E5: AG-D | F5: 110.3 | G5: 500 | H5: TN | I5: MATERIA PRIMA | J5: OPEX | K5: VARIABLE | L5: DIRECTO | N5: CC6 | O5: gastos_produccion | P5: 1432 | Q5: BACHAS | R5: AG-D
A6: 46081 | B6: MILO - DENIS LUQUE | C6: prod13 | D6: -67513309 | E6: GLICERINA CRUDA | F6: 130.925 | G6: 360 | H6: TN | I6: INSUMOS | J6: OPEX | K6: VARIABLE | L6: DIRECTO | N6: CC5 | O6: gastos_produccion | P6: 1432 | Q6: REACTORES | R6: GLICERINA CRUDA
A7: 46066 | B7: Construcciones Industriales Y Portuarias S.A. | C7: FA-A 00003-00001286 | D7: -54208000 | E7: INVERSION Planta de efluentes | F7: 1 | G7: 44800000 | H7: UN | I7: INVERSION | J7: CAPEX | K7: VARIABLE | L7: INDIRECTO | N7: CC3 | O7: gastos_produccion | R7: PROYECTO 4
A8: 46056 | B8: Construcciones Industriales Y Portuarias S.A. | C8: FA-A 00003-00001279 | D8: -54208000 | E8: OC 0001-00004263: INVERSION Planta de efluentes | F8: 1 | G8: 44800000 | H8: UN | I8: INVERSION | J8: CAPEX | K8: VARIABLE | L8: INDIRECTO | N8: CC3 | O8: gastos_produccion | R8: PROYECTO 4
A9: 46081 | B9: WORMS 2 | C9: prod19 | D9: -42638251 | E9: AG- A | F9: 35.02 | G9: 850 | H9: TN | I9: MATERIA PRIMA | J9: OPEX | K9: VARIABLE | L9: DIRECTO | N9: CC11 | O9: gastos_produccion | P9: 1432 | Q9: EXPORTACION | R9: AG- A
A10: 46055 | B10: Gmc Valores Sociedad Anonima | C10: OCOM/2026/0113 | D10: -32228280 | E10: OC 0001-00004462: INVERSION NORDIC | F10: 1 | G10: 32228280 | H10: UN | I10: INVERSION | J10: CAPEX | K10: VARIABLE | L10: DIRECTO | N10: CC3 | O10: gastos_produccion | R10: PROYECTO X
A11: 46063 | B11: Empresa Provincial De La Energia De Santa Fe (W) | C11: FA-A 00069-00037349 | D11: -30539110 | E11: OC 0001-00003944: ENERGIA Luz | F11: 1 | G11: 20913570 | H11: UN | I11: ENERGIA | J11: OPEX | K11: VARIABLE | L11: DIRECTO | N11: CC14 | O11: gastos_produccion | R11: ENERGIA
A12: 46081 | B12: LOGISTICA EXPORTACION | C12: FA-C 2-2026-1 | D12: -24743492 | E12: FOB | F12: 692.61 | G12: 35725 | H12: TN | I12: LOGISTICA | J12: OPEX | K12: VARIABLE | L12: DIRECTO | N12: CC11 | O12: gastos_produccion | P12: 1 | Q12: EXPORTACION | R12: FOB
A13: 46081 | B13: WORMS 1 | C13: prod33 | D13: -23997713 | E13: FONDO TK | F13: 33.507 | G13: 500 | H13: TN | I13: MATERIA PRIMA | J13: OPEX | K13: VARIABLE | L13: DIRECTO | N13: CC6 | O13: gastos_produccion | P13: 1432 | Q13: BACHAS
A14: 46081 | B14: COOPERATIVA DE TRABAJO COMERCIO EXTERIOR LIMITADA | C14: FA-C 2-2026-5 | D14: -19676907 | E14: SERVICIO DE DESPACHO | F14: 1616.12 | G14: 8.5 | H14: UN | I14: SERVICIOS | J14: OPEX | K14: VARIABLE | L14: DIRECTO | N14: CC11 | O14: gastos_produccion | P14: 1432 | R14: COMEX
A15: 46081 | B15: WORMS 2 | C15: prod23 | D15: -18422383 | E15: AG- C | F15: 17.38 | G15: 740 | H15: TN | I15: MATERIA PRIMA | J15: OPEX | K15: VARIABLE | L15: DIRECTO | N15: CC11 | O15: gastos_produccion | P15: 1432 | Q15: EXPORTACION | R15: AG- C
A16: 46081 | B16: ULTRAONIX SRL | C16: prod4 | D16: -17799734 | E16: FUEL OIL | F16: 27393.9 | G16: 649.77 | H16: KG | I16: ENERGIA | J16: OPEX | K16: VARIABLE | L16: DIRECTO | N16: CC5 | O16: gastos_produccion | P16: 1 | Q16: REACTORES | R16: FUEL OIL
A17: 46081 | B17: WORMS 1 | C17: prod34 | D17: -16472600 | E17: EMULSION | F17: 23 | G17: 500 | H17: KG | I17: MATERIA PRIMA | J17: OPEX | K17: VARIABLE | L17: DIRECTO | N17: CC6 | O17: gastos_produccion | P17: 1432 | Q17: BACHAS
A18: 46059 | B18: Bca Distribuciones Sa | C18: FA-A 00001-00005780 | D18: -11030401 | E18: OC 0001-00004176: INVERSION Proyecto 35 Bomba a pedido de Fernando T | F18: 1 | G18: 9116034.2 | H18: UN | I18: INVERSION | J18: CAPEX | K18: VARIABLE | L18: DIRECTO | N18: CC6 | O18: gastos_produccion | R18: POYECTO 35
A19: 46081 | B19: WORMS-RRHH | C19: ZIMMERMAN PABLO MAURICIO | D19: -10890280 | E19: DIRECTOR | F19: 1 | G19: 10890280 | H19: #RRHH | I19: PERSONAL | J19: OPEX | N19: CC16 | O19: gastos_rrhh | R19: DIRECTOR | T19: 10890280
A20: 46081 | B20: WORMS-RRHH | C20: FERREYRA GRACES JORGE BENJAMIN | D20: -8861694.3 | E20: DIRECTOR | F20: 1 | G20: 8861694.3 | H20: #RRHH | I20: PERSONAL | J20: OPEX | N20: CC16 | O20: gastos_rrhh | R20: DIRECTOR | T20: 8861694.3
A21: 46072 | B21: Cina, Dario Ruben | C21: FA-A 00002-00000007 | D21: -7763698.8 | E21: INVERSION Nunevo pozo de agua | F21: 1 | G21: 6416280 | H21: UN | I21: INVERSION | J21: CAPEX | K21: VARIABLE | L21: INDIRECTO | N21: CC3 | O21: gastos_produccion | R21: PROYECTO 50
A22: 46081 | B22: MARTINS, JOAQUIN | C22: prod8 | D22: -7070374 | E22: GASOIL G3 | F22: 4031 | G22: 1754 | H22: Lts | I22: ENERGIA | J22: OPEX | K22: VARIABLE | L22: DIRECTO | N22: CC1 | O22: gastos_produccion | P22: 1 | Q22: INTENDENCIA | R22: GASOIL G3
A23: 46081 | B23: WORMS-RRHH | C23: PAGANI, PABLO ALFONSO | D23: -6116414.9 | E23: PRODUCCION | F23: 1 | G23: 6116414.9 | H23: #RRHH | I23: PERSONAL | J23: OPEX | N23: CC28 | O23: gastos_rrhh | R23: PRODUCCION | T23: 6116414.9
A24: 46081 | B24: WORMS-RRHH | C24: MAZZALI CARLA JUDIT | D24: -6032968.4 | E24: ADMINISTRACION | F24: 1 | G24: 6032968.4 | H24: #RRHH | I24: PERSONAL | J24: OPEX | N24: CC15 | O24: gastos_rrhh | R24: ADMINISTRACION | T24: 6032968.4
A25: 46077 | B25: Southcross Logistics S.A real | C25: FA-A 00004-00037163 | D25: -5693050 | E25: SERVICIOS flete terrestre | F25: 5 | G25: 500000 | H25: UN | I25: SERVICIOS | J25: OPEX | K25: VARIABLE | L25: DIRECTO | N25: CC11 | O25: gastos_produccion
A26: 46072 | B26: Mastrangelo Productos Electricos Sa | C26: FA-A 00015-00069801 | D26: -5525708 | E26: INVERSION Proyecto 35 Pedido eléctrico | F26: 1 | G26: 4566700.8 | H26: UN | I26: INVERSION | J26: CAPEX | K26: VARIABLE | L26: DIRECTO | N26: CC6 | O26: gastos_produccion | R26: PROYECTO 35
A27: 46081 | B27: ULTRAONIX SRL | C27: prod5 | D27: -5458221.7 | E27: FUEL OIL | F27: 8410.203 | G27: 649 | H27: KG | I27: ENERGIA | J27: OPEX | K27: VARIABLE | L27: DIRECTO | N27: CC6 | O27: gastos_produccion | P27: 1 | Q27: BACHAS | R27: FUEL OIL
A28: 46081 | B28: IMPUESTOS | C28: imp2 | D28: -5039229.7 | E28: IMPUESTOS | F28: 1 | G28: 5039229.7 | H28: UN | I28: IMPUESTOS | J28: OPEX | K28: VARIABLE | L28: INDIRECTO | N28: CC1 | O28: gastos_impuestos | R28: GASTOS BANCARIOS
A29: 46081 | B29: WORMS-RRHH | C29: DIAZ PABLO EMMANUEL | D29: -4660517 | E29: NFU | F29: 1 | G29: 4660517 | H29: #RRHH | I29: PERSONAL | J29: OPEX | N29: CC7 | O29: gastos_rrhh | R29: NFU | T29: 4660517
A30: 46081 | B30: WORMS-RRHH | C30: CEBALLEZ, MARIA EUGENIA | D30: -4555960.9 | E30: PRODUCCION | F30: 1 | G30: 4555960.9 | H30: #RRHH | I30: PERSONAL | J30: OPEX | N30: CC28 | O30: gastos_rrhh | R30: PRODUCCION | T30: 4555960.9
A31: 46081 | B31: WORMS-RRHH | C31: TISCORNIA FERNANDO | D31: -4207865.4 | E31: DIRECTOR | F31: 1 | G31: 4207865.4 | H31: #RRHH | I31: PERSONAL | J31: OPEX | N31: CC16 | O31: gastos_rrhh | R31: DIRECTOR | T31: 4207865.4
A32: 46081 | B32: WORMS-RRHH | C32: LUQUE, ADRIAN | D32: -4107684.4 | E32: TALLER MECANICO | F32: 1 | G32: 4107684.4 | H32: #RRHH | I32: PERSONAL | J32: OPEX | N32: CC23 | O32: gastos_rrhh | R32: TALLER MECANICO | T32: 4107684.4
A33: 46072 | B33: Bordon, Carlos Roberto | C33: FA-C 00004-00000002 | D33: -4000000 | E33: INVERSION trabajo varios | F33: 1 | G33: 4000000 | H33: UN | I33: INVERSION | J33: CAPEX | K33: VARIABLE | L33: INDIRECTO | N33: CC6 | O33: gastos_produccion | R33: POYECTO X
A34: 46081 | B34: WORMS-RRHH | C34: HONORES ANDRES | D34: -3780940.7 | E34: REACTOR | F34: 1 | G34: 3780940.7 | H34: #RRHH | I34: PERSONAL | J34: OPEX | N34: CC15 | O34: gastos_rrhh | R34: REACTOR | T34: 3780940.7
A35: 46081 | B35: WORMS-RRHH | C35: PEREZ, MATIAS ROMAN | D35: -3671564.8 | E35: INTENDENCIA | F35: 1 | G35: 3671564.8 | H35: #RRHH | I35: PERSONAL | J35: OPEX | N35: CC27 | O35: gastos_rrhh | R35: INTENDENCIA | T35: 3671564.8
A36: 46056 | B36: Exportdeniv Internacional Sa | C36: FA-A 00002-00000604 | D36: -3455620.3 | E36: OC 0001-00004507: SERVICIOS Almacenaje cargas generales 1/26 | F36: 3969.24 | G36: 870.6 | H36: UN | I36: SERVICIOS | J36: OPEX | K36: VARIABLE | L36: DIRECTO | N36: CC11 | O36: gastos_produccion
A37: 46081 | B37: WORMS-RRHH | C37: LOPEZ CAMARGO BERLITZ, BEATRIZ | D37: -3415916.1 | E37: LABORATORIO | F37: 1 | G37: 3415916.1 | H37: #RRHH | I37: PERSONAL | J37: OPEX | N37: CC17 | O37: gastos_rrhh | R37: LABORATORIO | T37: 3415916.1
A38: 46081 | B38: WORMS-RRHH | C38: PELUZZA, CLAUDIA | D38: -3387545.4 | E38: ADMINISTRACION | F38: 1 | G38: 3387545.4 | H38: #RRHH | I38: PERSONAL | J38: OPEX | N38: CC15 | O38: gastos_rrhh | R38: ADMINISTRACION | T38: 3387545.4
A39: 46081 | B39: MARTINS, JOAQUIN | C39: prod10 | D39: -3363750 | E39: NAFTA | F39: 2250 | G39: 1495 | H39: Lts | I39: ENERGIA | J39: OPEX | K39: VARIABLE | L39: DIRECTO | N39: CC4 | O39: gastos_produccion | P39: 1 | Q39: PILETAS | R39: NAFTA
A40: 46081 | B40: WORMS-RRHH | C40: CHIANEA ERWIN | D40: -3349666.3 | E40: PRODUCCION | F40: 1 | G40: 3349666.3 | H40: #RRHH | I40: PERSONAL | J40: OPEX | N40: CC28 | O40: gastos_rrhh | R40: PRODUCCION | T40: 3349666.3
A41: 46081 | B41: WORMS-RRHH | C41: ISOLA, GIULIANA | D41: -3167990 | E41: ADMINISTRACION | F41: 1 | G41: 3167990 | H41: #RRHH | I41: PERSONAL | J41: OPEX | N41: CC15 | O41: gastos_rrhh | R41: ADMINISTRACION | T41: 3167990
A42: 46081 | B42: WORMS-RRHH | C42: CULOTA ANDRES | D42: -3102992.3 | E42: ADMINISTRACION | F42: 1 | G42: 3102992.3 | H42: #RRHH | I42: PERSONAL | J42: OPEX | N42: CC15 | O42: gastos_rrhh | R42: ADMINISTRACION | T42: 3102992.3
A43: 46081 | B43: WORMS-RRHH | C43: LARREY VANINA | D43: -3096266.9 | E43: PORTERIA | F43: 1 | G43: 3096266.9 | H43: #RRHH | I43: PERSONAL | J43: OPEX | N43: CC22 | O43: gastos_rrhh | R43: PORTERIA | T43: 3096266.9
A44: 46081 | B44: WORMS-RRHH | C44: PETERS CORZO, JOSE LUIS | D44: -3091668.4 | E44: LABORATORIO | F44: 1 | G44: 3091668.4 | H44: #RRHH | I44: PERSONAL | J44: OPEX | N44: CC17 | O44: gastos_rrhh | R44: LABORATORIO | T44: 3091668.4
A45: 46057 | B45: El Laboral Srl | C45: FA-A 00001-00009552 | D45: -3091668.1 | E45: OC 0001-00004006: PERSONAL Indumentaria Remeras, pantalón gorras | F45: 1 | G45: 2555097.6 | H45: UN | I45: PERSONAL | J45: OPEX | K45: VARIABLE | L45: DIRECTO | N45: CC1 | O45: gastos_produccion | R45: EPP
A46: 46071 | B46: Epp Y Mas S.A. | C46: FA-A 00006-00019294 | D46: -3059361.1 | E46: HIGIENE Y SEGURIDAD Elementos de protección personal | F46: 1 | G46: 2528397.6 | H46: UN | I46: HIGIENE Y SEGURIDAD | J46: OPEX | K46: VARIABLE | L46: DIRECTO | N46: CC1 | O46: gastos_produccion | R46: EPP
A47: 46054 | B47: Bustamante, Eduardo Maria(W) | C47: FA-A 00003-00000158 | D47: -3025000 | E47: OC 0001-00004493: HONORARIOS Servicios jurídicos Prestados en la ciudad autónoma de buenos aires | F47: 1 | G47: 2500000 | H47: UN | I47: HONORARIOS | J47: OPEX | K47: VARIABLE | L47: INDIRECTO | N47: CC1 | O47: gastos_produccion | Q47: ADMINISTRACION | R47: LEGALES
A48: 46081 | B48: WORMS-RRHH | C48: BUSTAMANTE ULISES BENIGNO | D48: -2951310.2 | E48: PILETAS | F48: 1 | G48: 2951310.2 | H48: #RRHH | I48: PERSONAL | J48: OPEX | N48: CC4 | O48: gastos_rrhh | R48: PILETAS | T48: 2951310.2
A49: 46055 | B49: Acosta, Roberto Maximiliano | C49: FA-C 00001-00000674 | D49: -2950000 | E49: OC 0001-00004297: SERVICIOS Servicio de limpieza enero 2026 | F49: 1 | G49: 2950000 | H49: UN | I49: SERVICIOS | J49: OPEX | K49: VARIABLE | L49: INDIRECTO | N49: CC1 | O49: gastos_produccion | Q49: INTENDENCIA | R49: LIMPIEZA
A50: 46055 | B50: Gonzalez, Delia | C50: FA-C 00001-00000012 | D50: -2950000 | E50: OC 0001-00004298: SERVICIOS Servicio de limpieza Enero 2026 | F50: 1 | G50: 2950000 | H50: UN | I50: SERVICIOS | J50: OPEX | K50: VARIABLE | L50: INDIRECTO | N50: CC1 | O50: gastos_produccion | Q50: INTENDENCIA | R50: LIMPIEZA
A51: 46081 | B51: TOTAL QUIMICA S.A. | C51: prod2 | D51: -2928103.2 | E51: ACIDO SULFÚRICO 70/80 | F51: 7920 | G51: 369.71 | H51: KG | I51: INSUMOS | J51: OPEX | K51: VARIABLE | L51: DIRECTO | N51: CC6 | O51: gastos_produccion | P51: 1 | Q51: BACHAS | R51: ACIDO SULFÚRICO 70/80
A52: 46081 | B52: WORMS-RRHH | C52: MONTENEGRO, GUSTAVO | D52: -2898353.7 | E52: INTENDENCIA | F52: 1 | G52: 2898353.7 | H52: #RRHH | I52: PERSONAL | J52: OPEX | N52: CC27 | O52: gastos_rrhh | R52: INTENDENCIA | T52: 2898353.7
A53: 46081 | B53: TOTAL QUIMICA S.A. | C53: prod12 | D53: -2871487.5 | E53: SODA CAUSTICA | F53: 3116 | G53: 921.53 | H53: KG | I53: INSUMOS | J53: OPEX | K53: VARIABLE | L53: DIRECTO | N53: CC5 | O53: gastos_produccion | P53: 1 | Q53: REACTORES | R53: SODA CAUSTICA
A54: 46061 | B54: Zavalia Lagos, Marina | C54: FA-C 00002-00000085 | D54: -2850000 | E54: OC 0001-00004592: HONORARIOS Servicios profesionales Tomas Bollini Enero 26 | F54: 1 | G54: 2850000 | H54: UN | I54: HONORARIOS | J54: OPEX | K54: VARIABLE | L54: INDIRECTO | N54: CC1 | O54: gastos_produccion | Q54: ADMINISTRACION | R54: LEGALES
A55: 46081 | B55: WORMS-RRHH | C55: BARRERA, MAXIMILIANO ESEQUIEL | D55: -2792560.3 | E55: DISPOSICION FINAL DE R. LIQUIDOS | F55: 1 | G55: 2792560.3 | H55: #RRHH | I55: PERSONAL | J55: OPEX | N55: CC25 | O55: gastos_rrhh | R55: DISPOSICION FINAL DE R. LIQUIDOS | T55: 2792560.3
A56: 46072 | B56: Chirichigno, Mario Alejandro | C56: FA-C 00003-00000212 | D56: -2727314 | E56: INVERSION etapa 2 proyecto 50 | F56: 1 | G56: 2727314 | H56: UN | I56: INVERSION | J56: CAPEX | K56: VARIABLE | L56: INDIRECTO | N56: CC1 | O56: gastos_produccion | Q56: INTENDENCIA | R56: PROYECTO 50
A57: 46081 | B57: WORMS-RRHH | C57: TULLIANI ROMINA | D57: -2652084.9 | E57: DISPOSICION FINAL DE R. LIQUIDOS | F57: 1 | G57: 2652084.9 | H57: #RRHH | I57: PERSONAL | J57: OPEX | N57: CC25 | O57: gastos_rrhh | R57: DISPOSICION FINAL DE R. LIQUIDOS | T57: 2652084.9
A58: 46081 | B58: WORMS-RRHH | C58: PARDEL, MAURO | D58: -2629398.4 | E58: PORTERIA | F58: 1 | G58: 2629398.4 | H58: #RRHH | I58: PERSONAL | J58: OPEX | N58: CC22 | O58: gastos_rrhh | R58: PORTERIA | T58: 2629398.4
A59: 46081 | B59: WORMS-RRHH | C59: DI PAOLO ANDREA ANALI | D59: -2603553.4 | E59: ADMINISTRACION | F59: 1 | G59: 2603553.4 | H59: #RRHH | I59: PERSONAL | J59: OPEX | N59: CC15 | O59: gastos_rrhh | R59: ADMINISTRACION | T59: 2603553.4
A60: 46081 | B60: WORMS-RRHH | C60: LOPEZ, AGUSTÍN ALBERTO | D60: -2599197.3 | E60: PORTERIA | F60: 1 | G60: 2599197.3 | H60: #RRHH | I60: PERSONAL | J60: OPEX | N60: CC22 | O60: gastos_rrhh | R60: PORTERIA | T60: 2599197.3
A61: 46081 | B61: WORMS-RRHH | C61: MAIDANA, JOSE RAMON | D61: -2416515 | E61: INTENDENCIA | F61: 1 | G61: 2416515 | H61: #RRHH | I61: PERSONAL | J61: OPEX | N61: CC27 | O61: gastos_rrhh | R61: INTENDENCIA | T61: 2416515
A62: 46081 | B62: WORMS-RRHH | C62: LOPEZ JESUS | D62: -2394868.4 | E62: LOGISTICA | F62: 1 | G62: 2394868.4 | H62: #RRHH | I62: PERSONAL | J62: OPEX | N62: CC18 | O62: gastos_rrhh | R62: LOGISTICA | T62: 2394868.4
A63: 46081 | B63: WORMS-RRHH | C63: BUSTAMANTE, GUSTAVO GASTON | D63: -2366793.4 | E63: DISPOSICION FINAL DE R. LIQUIDOS | F63: 1 | G63: 2366793.4 | H63: #RRHH | I63: PERSONAL | J63: OPEX | N63: CC25 | O63: gastos_rrhh | R63: DISPOSICION FINAL DE R. LIQUIDOS | T63: 2366793.4
A64: 46063 | B64: Mil Propiedades Srl | C64: FA-A 00001-00000734 | D64: -2359500 | E64: SERVICIOS alquiler Mod STD C/AA Sauce Viejo Desde 16/02 al 15/03 Baradero 07/02 al 06/03 Coronda 11/02 al 10/03 Timbues 14/02 al 13/03 | F64: 4 | G64: 390000 | H64: UN | I64: SERVICIOS | J64: OPEX | K64: VARIABLE | L64: INDIRECTO | N64: CC7 | O64: gastos_produccion | R64: CAT'S
A65: 46063 | B65: Servitubos S.R.L. | C65: FA-A 00005-00015672 | D65: -2348640.4 | E65: OC 0001-00004633: INVERSION T.Pvc.san.clot.160x3,2z4m | F65: 70 | G65: 27728.93 | H65: UN | I65: INVERSION | J65: CAPEX | K65: VARIABLE | L65: INDIRECTO | N65: CC3 | O65: gastos_produccion
A66: 46081 | B66: WORMS-RRHH | C66: BRAVO FRANCISCO NICOLAS | D66: -2339355.3 | E66: DISPOSICION FINAL DE R. LIQUIDOS | F66: 1 | G66: 2339355.3 | H66: #RRHH | I66: PERSONAL | J66: OPEX | N66: CC25 | O66: gastos_rrhh | R66: DISPOSICION FINAL DE R. LIQUIDOS | T66: 2339355.3
A67: 46081 | B67: WORMS-RRHH | C67: ENRIQUEZ, MAXIMO GUSTAVO | D67: -2318520.2 | E67: DISPOSICION FINAL DE R. LIQUIDOS | F67: 1 | G67: 2318520.2 | H67: #RRHH | I67: PERSONAL | J67: OPEX | N67: CC25 | O67: gastos_rrhh | R67: DISPOSICION FINAL DE R. LIQUIDOS | T67: 2318520.2
A68: 46081 | B68: WORMS-RRHH | C68: PANZANELLA, EDUARDO JAVIER | D68: -2316608.1 | E68: PORTERIA | F68: 1 | G68: 2316608.1 | H68: #RRHH | I68: PERSONAL | J68: OPEX | N68: CC22 | O68: gastos_rrhh | R68: PORTERIA | T68: 2316608.1
A69: 46081 | B69: WORMS-RRHH | C69: NUÑEZ ALAN OSVALDO | D69: -2289443.2 | E69: PILETAS | F69: 1 | G69: 2289443.2 | H69: #RRHH | I69: PERSONAL | J69: OPEX | N69: CC4 | O69: gastos_rrhh | R69: PILETAS | T69: 2289443.2
A70: 46081 | B70: WORMS-RRHH | C70: ACOSTA JORGE SEBASTIAN | D70: -2242802.5 | E70: BACHAS | F70: 1 | G70: 2242802.5 | H70: #RRHH | I70: PERSONAL | J70: OPEX | N70: CC6 | O70: gastos_rrhh | R70: BACHAS | T70: 2242802.5
A71: 46055 | B71: Adhoc S.A.(W) | C71: FA-A 00003-00021368 | D71: -2212671.5 | E71: OC 0001-00003852: SERVICIOS Sistema contable | F71: 1 | G71: 1828654.1 | H71: UN | I71: SERVICIOS | J71: OPEX | K71: FIJO | L71: INDIRECTO | N71: CC1 | O71: gastos_produccion | Q71: ADMINISTRACION | R71: SISTEMA
A72: 46081 | B72: WORMS-RRHH | C72: RODRIGUEZ, HORACIO | D72: -2197552.3 | E72: TALLER MECANICO | F72: 1 | G72: 2197552.3 | H72: #RRHH | I72: PERSONAL | J72: OPEX | N72: CC23 | O72: gastos_rrhh | R72: TALLER MECANICO | T72: 2197552.3
A73: 46081 | B73: WORMS-RRHH | C73: PACHECO MAURICIO | D73: -2184449.2 | E73: VIGILANCIA | F73: 1 | G73: 2184449.2 | H73: #RRHH | I73: PERSONAL | J73: OPEX | N73: CC29 | O73: gastos_rrhh | R73: VIGILANCIA | T73: 2184449.2
A74: 46081 | B74: WORMS-RRHH | C74: ALVAREZ ALEJANDRO | D74: -2183724.5 | E74: PILETAS | F74: 1 | G74: 2183724.5 | H74: #RRHH | I74: PERSONAL | J74: OPEX | N74: CC4 | O74: gastos_rrhh | R74: PILETAS | T74: 2183724.5
A75: 46081 | B75: WORMS-RRHH | C75: RODRIGUEZ, AYRTON | D75: -2171482.7 | E75: DISPOSICION FINAL DE R. LIQUIDOS | F75: 1 | G75: 2171482.7 | H75: #RRHH | I75: PERSONAL | J75: OPEX | N75: CC25 | O75: gastos_rrhh | R75: DISPOSICION FINAL DE R. LIQUIDOS | T75: 2171482.7
A76: 46081 | B76: WORMS-RRHH | C76: ALTAMIRANO, GUSTAVO | D76: -2164958.5 | E76: NFU | F76: 1 | G76: 2164958.5 | H76: #RRHH | I76: PERSONAL | J76: OPEX | N76: CC7 | O76: gastos_rrhh | R76: NFU | T76: 2164958.5
A77: 46081 | B77: WORMS-RRHH | C77: PORCU, MIGUEL ANGEL | D77: -2153887.5 | E77: PILETAS | F77: 1 | G77: 2153887.5 | H77: #RRHH | I77: PERSONAL | J77: OPEX | N77: CC4 | O77: gastos_rrhh | R77: PILETAS | T77: 2153887.5
A78: 46081 | B78: WORMS-RRHH | C78: GOMEZ, FRANCO JAVIER | D78: -2140538.4 | E78: DISPOSICION FINAL DE R. LIQUIDOS | F78: 1 | G78: 2140538.4 | H78: #RRHH | I78: PERSONAL | J78: OPEX | N78: CC25 | O78: gastos_rrhh | R78: DISPOSICION FINAL DE R. LIQUIDOS | T78: 2140538.4
A79: 46081 | B79: WORMS-RRHH | C79: PETERS DIAZ, RAMÓN RICARDO | D79: -2081874.7 | E79: LABORATORIO | F79: 1 | G79: 2081874.7 | H79: #RRHH | I79: PERSONAL | J79: OPEX | N79: CC17 | O79: gastos_rrhh | R79: LABORATORIO | T79: 2081874.7
A80: 46081 | B80: WORMS-RRHH | C80: DE AVELENDA VALENTIN | D80: -2057254.4 | E80: DISPOSICION FINAL DE R. LIQUIDOS | F80: 1 | G80: 2057254.4 | H80: #RRHH | I80: PERSONAL | J80: OPEX | N80: CC25 | O80: gastos_rrhh | R80: DISPOSICION FINAL DE R. LIQUIDOS | T80: 2057254.4
A81: 46081 | B81: WORMS-RRHH | C81: MATTAROLO EDITH | D81: -2056682.7 | E81: PORTERIA | F81: 1 | G81: 2056682.7 | H81: #RRHH | I81: PERSONAL | J81: OPEX | N81: CC22 | O81: gastos_rrhh | R81: PORTERIA | T81: 2056682.7
A82: 46081 | B82: WORMS-RRHH | C82: ALVAREZ IVAN DARIO | D82: -2041933.5 | E82: ADMINISTRACION | F82: 1 | G82: 2041933.5 | H82: #RRHH | I82: PERSONAL | J82: OPEX | N82: CC15 | O82: gastos_rrhh | R82: ADMINISTRACION | T82: 2041933.5
A83: 46081 | B83: WORMS-RRHH | C83: FRANCO BRUNO | D83: -2029819 | E83: DISPOSICION FINAL DE R. LIQUIDOS | F83: 1 | G83: 2029819 | H83: #RRHH | I83: PERSONAL | J83: OPEX | N83: CC25 | O83: gastos_rrhh | R83: DISPOSICION FINAL DE R. LIQUIDOS | T83: 2029819
... A86: 46081 | B86: WORMS-RRHH | C86: AREVALO MARCOS AXEL | D86: -1992393.4 | E86: TALLER MECANICO | F86: 1 | G86: 1992393.4 | H86: #RRHH | I86: PERSONAL | J86: OPEX | N86: CC23 | O86: gastos_rrhh | R86: TALLER MECANICO | T86: 1992393.4
A87: 46063 | B87: Strupeni, Federico Lisandro | C87: FA-A 00008-00000058 | D87: -1979272.1 | E87: OC 0001-00004631: INVERSION Disco 4tb para grabación nvr | F87: 4 | G87: 342403.2 | H87: UN | I87: INVERSION | J87: CAPEX | K87: VARIABLE | L87: INDIRECTO | N87: CC11 | O87: gastos_produccion
A88: 46081 | B88: WORMS-RRHH | C88: BORDON CAMILO RAFAEL | D88: -1972720.5 | E88: REACTOR | F88: 1 | G88: 1972720.5 | H88: #RRHH | I88: PERSONAL | J88: OPEX | N88: CC15 | O88: gastos_rrhh | R88: REACTOR | T88: 1972720.5
A89: 46081 | B89: WORMS-RRHH | C89: FERNANDEZ, HECTOR OSCAR | D89: -1958595.1 | E89: VIGILANCIA | F89: 1 | G89: 1958595.1 | H89: #RRHH | I89: PERSONAL | J89: OPEX | N89: CC29 | O89: gastos_rrhh | R89: VIGILANCIA | T89: 1958595.1
A90: 46081 | B90: WORMS-RRHH | C90: MORENO RAMIRO ROMAN | D90: -1942874.4 | E90: PILETAS | F90: 1 | G90: 1942874.4 | H90: #RRHH | I90: PERSONAL | J90: OPEX | N90: CC4 | O90: gastos_rrhh | R90: PILETAS | T90: 1942874.4
A91: 46081 | B91: WORMS-RRHH | C91: MARTINEZ JUAN PABLO | D91: -1942605.2 | E91: MANTENIMIENTO | F91: 1 | G91: 1942605.2 | H91: #RRHH | I91: PERSONAL | J91: OPEX | N91: CC19 | O91: gastos_rrhh | R91: MANTENIMIENTO | T91: 1942605.2
A92: 46081 | B92: WORMS-RRHH | C92: CORDOBA GABRIEL | D92: -1930813.4 | E92: ADMINISTRACION | F92: 1 | G92: 1930813.4 | H92: #RRHH | I92: PERSONAL | J92: OPEX | N92: CC15 | O92: gastos_rrhh | R92: ADMINISTRACION | T92: 1930813.4
A93: 46081 | B93: WORMS-RRHH | C93: OVANDO, BRYAN EZEQUIEL | D93: -1928700.1 | E93: MANTENIMIENTO | F93: 1 | G93: 1928700.1 | H93: #RRHH | I93: PERSONAL | J93: OPEX | N93: CC19 | O93: gastos_rrhh | R93: MANTENIMIENTO | T93: 1928700.1
A94: 46081 | B94: WORMS-RRHH | C94: CABRERA JULIAN LEON | D94: -1914723.4 | E94: REACTOR | F94: 1 | G94: 1914723.4 | H94: #RRHH | I94: PERSONAL | J94: OPEX | N94: CC15 | O94: gastos_rrhh | R94: REACTOR | T94: 1914723.4
A95: 46081 | B95: WORMS-RRHH | C95: CARIAGA, SOFIA | D95: -1898057.5 | E95: ADMINISTRACION | F95: 1 | G95: 1898057.5 | H95: #RRHH | I95: PERSONAL | J95: OPEX | N95: CC15 | O95: gastos_rrhh | R95: ADMINISTRACION | T95: 1898057.5
A96: 46081 | B96: WORMS-RRHH | C96: FERNANDEZ JEREMIAS EDGARDO NAHUEL | D96: -1848040.3 | E96: BACHAS | F96: 1 | G96: 1848040.3 | H96: #RRHH | I96: PERSONAL | J96: OPEX | N96: CC6 | O96: gastos_rrhh | R96: BACHAS | T96: 1848040.3
A97: 46081 | B97: WORMS-RRHH | C97: RODRIGUEZ LEANDRO | D97: -1841830.6 | E97: REACTOR | F97: 1 | G97: 1841830.6 | H97: #RRHH | I97: PERSONAL | J97: OPEX | N97: CC15 | O97: gastos_rrhh | R97: REACTOR | T97: 1841830.6
A98: 46081 | B98: WORMS-RRHH | C98: VAZQUEZ MATIAS EMANUEL | D98: -1836940.1 | E98: PILETAS | F98: 1 | G98: 1836940.1 | H98: #RRHH | I98: PERSONAL | J98: OPEX | N98: CC4 | O98: gastos_rrhh | R98: PILETAS | T98: 1836940.1
A99: 46081 | B99: WORMS-RRHH | C99: REY ROLANDO | D99: -1824756.7 | E99: LOGISTICA | F99: 1 | G99: 1824756.7 | H99: #RRHH | I99: PERSONAL | J99: OPEX | N99: CC18 | O99: gastos_rrhh | R99: LOGISTICA | T99: 1824756.7
... A113: 46081 | B113: WORMS-RRHH | C113: BALBUENA MAXIMILIANO EZEQUIEL | D113: -1589809.1 | E113: PILETAS | F113: 1 | G113: 1589809.1 | H113: #RRHH | I113: PERSONAL | J113: OPEX | N113: CC4 | O113: gastos_rrhh | R113: PILETAS | T113: 1589809.1
A114: 46055 | B114: Centauro Alpha S R L | C114: FA-A 00003-00010896 | D114: -1580819.6 | E114: OC 0001-00004383: MANTENIMIENTO PREVENTIVO | F114: 175 | G114: 6541.5 | H114: UN | I114: MANTENIMIENTO PREVENTIVO | J114: OPEX | K114: VARIABLE | L114: INDIRECTO | N114: CC1 | O114: gastos_produccion | Q114: LABORATORIO | R114: MANTENIMIENTO Y ORDEN
A115: 46057 | B115: Tecnogran S R L | C115: FA-A 00012-00000385 | D115: -1580036.1 | E115: OC 0001-00003876: SERVICIOS Control de plagas Marzo 2026 | F115: 1 | G115: 1305815 | H115: UN | I115: SERVICIOS | J115: OPEX | K115: FIJO | L115: INDIRECTO | N115: CC1 | O115: gastos_produccion | Q115: INTENDENCIA | R115: MANTENIMIENTO Y ORDEN
...

Sheet bbdd_total.p1
A1: Fecha de Factura/Recibo | B1: Nombre de la empresa a mostrar en la factura | C1: Número | D1: Total con signo | E1: Líneas de factura/Etiqueta | F1: Líneas de factura/Cantidad | G1: Líneas de factura/Precio unitario | H1: Líneas de factura/Unidad de medida | I1: Líneas de factura/Producto | J1: Concepto | K1: Tipo de Gasto 1 | L1: Tipo de Gasto 2 | M1: CCO EMPRESA | N1: CCO - SECTOR | O1: SECTOR_ODOO | P1: # SECTORES | Q1: LISTA_SECTORES | R1: prc_empresa
A2: 46081 | B2: WORMS 2 | C2: prod17 | D2: -1.9004255e+09 | E2: AFE (S) | F2: 1403.96 | G2: 945 | H2: TN | I2: MATERIA PRIMA | J2: OPEX | K2: VARIABLE | L2: DIRECTO | N2: CC11 | O2: gastos_produccion | P2: =_xlfn.XLOOKUP(bbdd3[[#This Row],[CCO - SECTOR]],'cco '!$A:$A,'cco '!F:F,"CCO NO DEFINIDO") -> 1 | Q2: =_xlfn.XLOOKUP(bbdd3[[#This Row],[CCO - SECTOR]],'cco '!$A:$A,'cco '!I:I,"CCO NO DEFINIDO") -> EXPORTACION | R2: =IF(ISBLANK(bbdd3[[#This Row],[CCO EMPRESA]]),1,_xlfn.XLOOKUP(bbdd3[[#This Row],[CCO EMPRESA]],'cco_worms_empresa'!$A:$A,'cco_worms_empresa'!$G:$G)) -> 1
A3: 46081 | B3: WORMS 2 | C3: prod15 | D3: -1.1459658e+08 | E3: AFE (G) | F3: 86.96 | G3: 920 | H3: TN | I3: MATERIA PRIMA | J3: OPEX | K3: VARIABLE | L3: DIRECTO | N3: CC11 | O3: gastos_produccion | P3: =_xlfn.XLOOKUP(bbdd3[[#This Row],[CCO - SECTOR]],'cco '!$A:$A,'cco '!F:F,"CCO NO DEFINIDO") -> 1 | Q3: =_xlfn.XLOOKUP(bbdd3[[#This Row],[CCO - SECTOR]],'cco '!$A:$A,'cco '!I:I,"CCO NO DEFINIDO") -> EXPORTACION | R3: =IF(ISBLANK(bbdd3[[#This Row],[CCO EMPRESA]]),1,_xlfn.XLOOKUP(bbdd3[[#This Row],[CCO EMPRESA]],'cco_worms_empresa'!$A:$A,'cco_worms_empresa'!$G:$G)) -> 1
A4: 46081 | B4: WORMS 2 | C4: prod29 | D4: -87594125 | E4: ARE- B | F4: 72.8 | G4: 840 | H4: TN | I4: MATERIA PRIMA | J4: OPEX | K4: VARIABLE | L4: DIRECTO | N4: CC11 | O4: gastos_produccion | P4: =_xlfn.XLOOKUP(bbdd3[[#This Row],[CCO - SECTOR]],'cco '!$A:$A,'cco '!F:F,"CCO NO DEFINIDO") -> 1 | Q4: =_xlfn.XLOOKUP(bbdd3[[#This Row],[CCO - SECTOR]],'cco '!$A:$A,'cco '!I:I,"CCO NO DEFINIDO") -> EXPORTACION | R4: =IF(ISBLANK(bbdd3[[#This Row],[CCO EMPRESA]]),1,_xlfn.XLOOKUP(bbdd3[[#This Row],[CCO EMPRESA]],'cco_worms_empresa'!$A:$A,'cco_worms_empresa'!$G:$G)) -> 1
A5: 46081 | B5: WORMS 1 | C5: prod26 | D5: -78996860 | E5: AG-D | F5: 110.3 | G5: 500 | H5: TN | I5: MATERIA PRIMA | J5: OPEX | K5: VARIABLE | L5: DIRECTO | N5: CC6 | O5: gastos_produccion | P5: =_xlfn.XLOOKUP(bbdd3[[#This Row],[CCO - SECTOR]],'cco '!$A:$A,'cco '!F:F,"CCO NO DEFINIDO") -> 1 | Q5: =_xlfn.XLOOKUP(bbdd3[[#This Row],[CCO - SECTOR]],'cco '!$A:$A,'cco '!I:I,"CCO NO DEFINIDO") -> BACHAS | R5: =IF(ISBLANK(bbdd3[[#This Row],[CCO EMPRESA]]),1,_xlfn.XLOOKUP(bbdd3[[#This Row],[CCO EMPRESA]],'cco_worms_empresa'!$A:$A,'cco_worms_empresa'!$G:$G)) -> 1
A6: 46081 | B6: MILO - DENIS LUQUE | C6: prod13 | D6: -67513309 | E6: GLICERINA CRUDA | F6: 130.925 | G6: 360 | H6: TN | I6: INSUMOS | J6: OPEX | K6: VARIABLE | L6: DIRECTO | N6: CC5 | O6: gastos_produccion | P6: =_xlfn.XLOOKUP(bbdd3[[#This Row],[CCO - SECTOR]],'cco '!$A:$A,'cco '!F:F,"CCO NO DEFINIDO") -> 1 | Q6: =_xlfn.XLOOKUP(bbdd3[[#This Row],[CCO - SECTOR]],'cco '!$A:$A,'cco '!I:I,"CCO NO DEFINIDO") -> REACTORES | R6: =IF(ISBLANK(bbdd3[[#This Row],[CCO EMPRESA]]),1,_xlfn.XLOOKUP(bbdd3[[#This Row],[CCO EMPRESA]],'cco_worms_empresa'!$A:$A,'cco_worms_empresa'!$G:$G)) -> 1
A7: 46066 | B7: Construcciones Industriales Y Portuarias S.A. | C7: FA-A 00003-00001286 | D7: -54208000 | E7: INVERSION Planta de efluentes | F7: 1 | G7: 44800000 | H7: UN | I7: INVERSION | J7: CAPEX | K7: VARIABLE | L7: INDIRECTO | N7: CC3 | O7: gastos_produccion | P7: =_xlfn.XLOOKUP(bbdd3[[#This Row],[CCO - SECTOR]],'cco '!$A:$A,'cco '!F:F,"CCO NO DEFINIDO") -> 1 | Q7: =_xlfn.XLOOKUP(bbdd3[[#This Row],[CCO - SECTOR]],'cco '!$A:$A,'cco '!I:I,"CCO NO DEFINIDO") -> DISPOSICIÓN FINAL RESIDUOS LIQUIDOS | R7: =IF(ISBLANK(bbdd3[[#This Row],[CCO EMPRESA]]),1,_xlfn.XLOOKUP(bbdd3[[#This Row],[CCO EMPRESA]],'cco_worms_empresa'!$A:$A,'cco_worms_empresa'!$G:$G)) -> 1
A8: 46056 | B8: Construcciones Industriales Y Portuarias S.A. | C8: FA-A 00003-00001279 | D8: -54208000 | E8: OC 0001-00004263: INVERSION Planta de efluentes | F8: 1 | G8: 44800000 | H8: UN | I8: INVERSION | J8: CAPEX | K8: VARIABLE | L8: INDIRECTO | N8: CC3 | O8: gastos_produccion | P8: =_xlfn.XLOOKUP(bbdd3[[#This Row],[CCO - SECTOR]],'cco '!$A:$A,'cco '!F:F,"CCO NO DEFINIDO") -> 1 | Q8: =_xlfn.XLOOKUP(bbdd3[[#This Row],[CCO - SECTOR]],'cco '!$A:$A,'cco '!I:I,"CCO NO DEFINIDO") -> DISPOSICIÓN FINAL RESIDUOS LIQUIDOS | R8: =IF(ISBLANK(bbdd3[[#This Row],[CCO EMPRESA]]),1,_xlfn.XLOOKUP(bbdd3[[#This Row],[CCO EMPRESA]],'cco_worms_empresa'!$A:$A,'cco_worms_empresa'!$G:$G)) -> 1
A9: 46081 | B9: WORMS 2 | C9: prod19 | D9: -42638251 | E9: AG- A | F9: 35.02 | G9: 850 | H9: TN | I9: MATERIA PRIMA | J9: OPEX | K9: VARIABLE | L9: DIRECTO | N9: CC11 | O9: gastos_produccion | P9: =_xlfn.XLOOKUP(bbdd3[[#This Row],[CCO - SECTOR]],'cco '!$A:$A,'cco '!F:F,"CCO NO DEFINIDO") -> 1 | Q9: =_xlfn.XLOOKUP(bbdd3[[#This Row],[CCO - SECTOR]],'cco '!$A:$A,'cco '!I:I,"CCO NO DEFINIDO") -> EXPORTACION | R9: =IF(ISBLANK(bbdd3[[#This Row],[CCO EMPRESA]]),1,_xlfn.XLOOKUP(bbdd3[[#This Row],[CCO EMPRESA]],'cco_worms_empresa'!$A:$A,'cco_worms_empresa'!$G:$G)) -> 1
A10: 46055 | B10: Gmc Valores Sociedad Anonima | C10: OCOM/2026/0113 | D10: -32228280 | E10: OC 0001-00004462: INVERSION NORDIC | F10: 1 | G10: 32228280 | H10: UN | I10: INVERSION | J10: CAPEX | K10: VARIABLE | L10: DIRECTO | N10: CC3 | O10: gastos_produccion | P10: =_xlfn.XLOOKUP(bbdd3[[#This Row],[CCO - SECTOR]],'cco '!$A:$A,'cco '!F:F,"CCO NO DEFINIDO") -> 1 | Q10: =_xlfn.XLOOKUP(bbdd3[[#This Row],[CCO - SECTOR]],'cco '!$A:$A,'cco '!I:I,"CCO NO DEFINIDO") -> DISPOSICIÓN FINAL RESIDUOS LIQUIDOS | R10: =IF(ISBLANK(bbdd3[[#This Row],[CCO EMPRESA]]),1,_xlfn.XLOOKUP(bbdd3[[#This Row],[CCO EMPRESA]],'cco_worms_empresa'!$A:$A,'cco_worms_empresa'!$G:$G)) -> 1
A11: 46063 | B11: Empresa Provincial De La Energia De Santa Fe (W) | C11: FA-A 00069-00037349 | D11: -30539110 | E11: OC 0001-00003944: ENERGIA Luz | F11: 1 | G11: 20913570 | H11: UN | I11: ENERGIA | J11: OPEX | K11: VARIABLE | L11: DIRECTO | N11: CC14 | O11: gastos_produccion | P11: =_xlfn.XLOOKUP(bbdd3[[#This Row],[CCO - SECTOR]],'cco '!$A:$A,'cco '!F:F,"CCO NO DEFINIDO") -> 10 | Q11: =_xlfn.XLOOKUP(bbdd3[[#This Row],[CCO - SECTOR]],'cco '!$A:$A,'cco '!I:I,"CCO NO DEFINIDO") -> BACHAS, CEREAL & POLVILLO, COMPOST & FERTILIZANTES, DISPOSICIÓN FINAL RESIDUOS LIQUIDOS, DISPOSICIÓN FINAL RESIDUOS SOLIDOS, EXPORTACION, NFU, PILETAS, REACTORES, TIERRAS FILTRANTES | R11: =IF(ISBLANK(bbdd3[[#This Row],[CCO EMPRESA]]),1,_xlfn.XLOOKUP(bbdd3[[#This Row],[CCO EMPRESA]],'cco_worms_empresa'!$A:$A,'cco_worms_empresa'!$G:$G)) -> 1
A12: 46081 | B12: LOGISTICA EXPORTACION | C12: FA-C 2-2026-1 | D12: -24743492 | E12: FOB | F12: 692.61 | G12: 35725 | H12: TN | I12: LOGISTICA | J12: OPEX | K12: VARIABLE | L12: DIRECTO | N12: CC11 | O12: gastos_produccion | P12: =_xlfn.XLOOKUP(bbdd3[[#This Row],[CCO - SECTOR]],'cco '!$A:$A,'cco '!F:F,"CCO NO DEFINIDO") -> 1 | Q12: =_xlfn.XLOOKUP(bbdd3[[#This Row],[CCO - SECTOR]],'cco '!$A:$A,'cco '!I:I,"CCO NO DEFINIDO") -> EXPORTACION | R12: =IF(ISBLANK(bbdd3[[#This Row],[CCO EMPRESA]]),1,_xlfn.XLOOKUP(bbdd3[[#This Row],[CCO EMPRESA]],'cco_worms_empresa'!$A:$A,'cco_worms_empresa'!$G:$G)) -> 1
A13: 46081 | B13: WORMS 1 | C13: prod33 | D13: -23997713 | E13: FONDO TK | F13: 33.507 | G13: 500 | H13: TN | I13: MATERIA PRIMA | J13: OPEX | K13: VARIABLE | L13: DIRECTO | N13: CC6 | O13: gastos_rrhh | P13: =_xlfn.XLOOKUP(bbdd3[[#This Row],[CCO - SECTOR]],'cco '!$A:$A,'cco '!F:F,"CCO NO DEFINIDO") -> 1 | Q13: =_xlfn.XLOOKUP(bbdd3[[#This Row],[CCO - SECTOR]],'cco '!$A:$A,'cco '!I:I,"CCO NO DEFINIDO") -> BACHAS | R13: =IF(ISBLANK(bbdd3[[#This Row],[CCO EMPRESA]]),1,_xlfn.XLOOKUP(bbdd3[[#This Row],[CCO EMPRESA]],'cco_worms_empresa'!$A:$A,'cco_worms_empresa'!$G:$G)) -> 1
... A18: 46059 | B18: Bca Distribuciones Sa | C18: FA-A 00001-00005780 | D18: -11030401 | E18: OC 0001-00004176: INVERSION Proyecto 35 Bomba a pedido de Fernando T | F18: 1 | G18: 9116034.2 | H18: UN | I18: INVERSION | J18: CAPEX | K18: VARIABLE | L18: DIRECTO | N18: CC6 | O18: gastos_produccion | P18: =_xlfn.XLOOKUP(bbdd3[[#This Row],[CCO - SECTOR]],'cco '!$A:$A,'cco '!F:F,"CCO NO DEFINIDO") -> 1 | Q18: =_xlfn.XLOOKUP(bbdd3[[#This Row],[CCO - SECTOR]],'cco '!$A:$A,'cco '!I:I,"CCO NO DEFINIDO") -> BACHAS | R18: =IF(ISBLANK(bbdd3[[#This Row],[CCO EMPRESA]]),1,_xlfn.XLOOKUP(bbdd3[[#This Row],[CCO EMPRESA]],'cco_worms_empresa'!$A:$A,'cco_worms_empresa'!$G:$G)) -> 1
A19: 46081 | B19: WORMS-RRHH | C19: ZIMMERMAN PABLO MAURICIO | D19: -10890280 | E19: DIRECTOR | F19: 1 | G19: 10890280 | H19: #RRHH | I19: PERSONAL | J19: OPEX | N19: CC16 | O19: gastos_produccion | P19: =_xlfn.XLOOKUP(bbdd3[[#This Row],[CCO - SECTOR]],'cco '!$A:$A,'cco '!F:F,"CCO NO DEFINIDO") -> 10 | Q19: =_xlfn.XLOOKUP(bbdd3[[#This Row],[CCO - SECTOR]],'cco '!$A:$A,'cco '!I:I,"CCO NO DEFINIDO") -> BACHAS, CEREAL Y POLVILLO, COMPOST Y FERTILIZANTES, DISPOSICION FINAL DE R. LIQUIDOS, DISPOSICION FINAL DE R. SOLIDOS, EXPORTACION, NFU, PILETAS, REACTORES, TIERRAS FILTRANTES | R19: =IF(ISBLANK(bbdd3[[#This Row],[CCO EMPRESA]]),1,_xlfn.XLOOKUP(bbdd3[[#This Row],[CCO EMPRESA]],'cco_worms_empresa'!$A:$A,'cco_worms_empresa'!$G:$G)) -> 1
A20: 46081 | B20: WORMS-RRHH | C20: FERREYRA GRACES JORGE BENJAMIN | D20: -8861694.3 | E20: DIRECTOR | F20: 1 | G20: 8861694.3 | H20: #RRHH | I20: PERSONAL | J20: OPEX | N20: CC16 | O20: gastos_produccion | P20: =_xlfn.XLOOKUP(bbdd3[[#This Row],[CCO - SECTOR]],'cco '!$A:$A,'cco '!F:F,"CCO NO DEFINIDO") -> 10 | Q20: =_xlfn.XLOOKUP(bbdd3[[#This Row],[CCO - SECTOR]],'cco '!$A:$A,'cco '!I:I,"CCO NO DEFINIDO") -> BACHAS, CEREAL Y POLVILLO, COMPOST Y FERTILIZANTES, DISPOSICION FINAL DE R. LIQUIDOS, DISPOSICION FINAL DE R. SOLIDOS, EXPORTACION, NFU, PILETAS, REACTORES, TIERRAS FILTRANTES | R20: =IF(ISBLANK(bbdd3[[#This Row],[CCO EMPRESA]]),1,_xlfn.XLOOKUP(bbdd3[[#This Row],[CCO EMPRESA]],'cco_worms_empresa'!$A:$A,'cco_worms_empresa'!$G:$G)) -> 1
A21: 46072 | B21: Cina, Dario Ruben | C21: FA-A 00002-00000007 | D21: -7763698.8 | E21: INVERSION Nunevo pozo de agua | F21: 1 | G21: 6416280 | H21: UN | I21: INVERSION | J21: CAPEX | K21: VARIABLE | L21: INDIRECTO | N21: CC3 | O21: gastos_rrhh | P21: =_xlfn.XLOOKUP(bbdd3[[#This Row],[CCO - SECTOR]],'cco '!$A:$A,'cco '!F:F,"CCO NO DEFINIDO") -> 1 | Q21: =_xlfn.XLOOKUP(bbdd3[[#This Row],[CCO - SECTOR]],'cco '!$A:$A,'cco '!I:I,"CCO NO DEFINIDO") -> DISPOSICIÓN FINAL RESIDUOS LIQUIDOS | R21: =IF(ISBLANK(bbdd3[[#This Row],[CCO EMPRESA]]),1,_xlfn.XLOOKUP(bbdd3[[#This Row],[CCO EMPRESA]],'cco_worms_empresa'!$A:$A,'cco_worms_empresa'!$G:$G)) -> 1
A22: 46081 | B22: MARTINS, JOAQUIN | C22: prod8 | D22: -7070374 | E22: GASOIL G3 | F22: 4031 | G22: 1754 | H22: Lts | I22: ENERGIA | J22: OPEX | K22: VARIABLE | L22: DIRECTO | N22: CC1 | O22: gastos_produccion | P22: =_xlfn.XLOOKUP(bbdd3[[#This Row],[CCO - SECTOR]],'cco '!$A:$A,'cco '!F:F,"CCO NO DEFINIDO") -> 10 | Q22: =_xlfn.XLOOKUP(bbdd3[[#This Row],[CCO - SECTOR]],'cco '!$A:$A,'cco '!I:I,"CCO NO DEFINIDO") -> BACHAS, CEREAL & POLVILLO, COMPOST & FERTILIZANTES, DISPOSICIÓN FINAL RESIDUOS LIQUIDOS, DISPOSICIÓN FINAL RESIDUOS SOLIDOS, EXPORTACION, NFU, PILETAS, REACTORES, TIERRAS FILTRANTES | R22: =IF(ISBLANK(bbdd3[[#This Row],[CCO EMPRESA]]),1,_xlfn.XLOOKUP(bbdd3[[#This Row],[CCO EMPRESA]],'cco_worms_empresa'!$A:$A,'cco_worms_empresa'!$G:$G)) -> 1
A23: 46081 | B23: WORMS-RRHH | C23: PAGANI, PABLO ALFONSO | D23: -6116414.9 | E23: PRODUCCION | F23: 1 | G23: 6116414.9 | H23: #RRHH | I23: PERSONAL | J23: OPEX | N23: CC28 | O23: gastos_produccion | P23: =_xlfn.XLOOKUP(bbdd3[[#This Row],[CCO - SECTOR]],'cco '!$A:$A,'cco '!F:F,"CCO NO DEFINIDO") -> 10 | Q23: =_xlfn.XLOOKUP(bbdd3[[#This Row],[CCO - SECTOR]],'cco '!$A:$A,'cco '!I:I,"CCO NO DEFINIDO") -> BACHAS, CEREAL & POLVILLO, COMPOST & FERTILIZANTES, DISPOSICIÓN FINAL RESIDUOS LIQUIDOS, DISPOSICIÓN FINAL RESIDUOS SOLIDOS, EXPORTACION, NFU, PILETAS, REACTORES, TIERRAS FILTRANTES | R23: =IF(ISBLANK(bbdd3[[#This Row],[CCO EMPRESA]]),1,_xlfn.XLOOKUP(bbdd3[[#This Row],[CCO EMPRESA]],'cco_worms_empresa'!$A:$A,'cco_worms_empresa'!$G:$G)) -> 1
A24: 46081 | B24: WORMS-RRHH | C24: MAZZALI CARLA JUDIT | D24: -6032968.4 | E24: ADMINISTRACION | F24: 1 | G24: 6032968.4 | H24: #RRHH | I24: PERSONAL | J24: OPEX | N24: CC15 | O24: gastos_rrhh | P24: =_xlfn.XLOOKUP(bbdd3[[#This Row],[CCO - SECTOR]],'cco '!$A:$A,'cco '!F:F,"CCO NO DEFINIDO") -> 10 | Q24: =_xlfn.XLOOKUP(bbdd3[[#This Row],[CCO - SECTOR]],'cco '!$A:$A,'cco '!I:I,"CCO NO DEFINIDO") -> BACHAS, CEREAL Y POLVILLO, COMPOST Y FERTILIZANTES, DISPOSICION FINAL DE R. LIQUIDOS, DISPOSICION FINAL DE R. SOLIDOS, EXPORTACION, NFU, PILETAS, REACTORES, TIERRAS FILTRANTES | R24: =IF(ISBLANK(bbdd3[[#This Row],[CCO EMPRESA]]),1,_xlfn.XLOOKUP(bbdd3[[#This Row],[CCO EMPRESA]],'cco_worms_empresa'!$A:$A,'cco_worms_empresa'!$G:$G)) -> 1
A25: 46077 | B25: Southcross Logistics S.A real | C25: FA-A 00004-00037163 | D25: -5693050 | E25: SERVICIOS flete terrestre | F25: 5 | G25: 500000 | H25: UN | I25: SERVICIOS | J25: OPEX | K25: VARIABLE | L25: DIRECTO | N25: CC11 | O25: gastos_produccion | P25: =_xlfn.XLOOKUP(bbdd3[[#This Row],[CCO - SECTOR]],'cco '!$A:$A,'cco '!F:F,"CCO NO DEFINIDO") -> 1 | Q25: =_xlfn.XLOOKUP(bbdd3[[#This Row],[CCO - SECTOR]],'cco '!$A:$A,'cco '!I:I,"CCO NO DEFINIDO") -> EXPORTACION | R25: =IF(ISBLANK(bbdd3[[#This Row],[CCO EMPRESA]]),1,_xlfn.XLOOKUP(bbdd3[[#This Row],[CCO EMPRESA]],'cco_worms_empresa'!$A:$A,'cco_worms_empresa'!$G:$G)) -> 1
A26: 46072 | B26: Mastrangelo Productos Electricos Sa | C26: FA-A 00015-00069801 | D26: -5525708 | E26: INVERSION Proyecto 35 Pedido eléctrico | F26: 1 | G26: 4566700.8 | H26: UN | I26: INVERSION | J26: CAPEX | K26: VARIABLE | L26: DIRECTO | N26: CC6 | O26: gastos_produccion | P26: =_xlfn.XLOOKUP(bbdd3[[#This Row],[CCO - SECTOR]],'cco '!$A:$A,'cco '!F:F,"CCO NO DEFINIDO") -> 1 | Q26: =_xlfn.XLOOKUP(bbdd3[[#This Row],[CCO - SECTOR]],'cco '!$A:$A,'cco '!I:I,"CCO NO DEFINIDO") -> BACHAS | R26: =IF(ISBLANK(bbdd3[[#This Row],[CCO EMPRESA]]),1,_xlfn.XLOOKUP(bbdd3[[#This Row],[CCO EMPRESA]],'cco_worms_empresa'!$A:$A,'cco_worms_empresa'!$G:$G)) -> 1
A27: 46081 | B27: ULTRAONIX SRL | C27: prod5 | D27: -5458221.7 | E27: FUEL OIL | F27: 8410.203 | G27: 649 | H27: KG | I27: ENERGIA | J27: OPEX | K27: VARIABLE | L27: DIRECTO | N27: CC6 | O27: gastos_produccion | P27: =_xlfn.XLOOKUP(bbdd3[[#This Row],[CCO - SECTOR]],'cco '!$A:$A,'cco '!F:F,"CCO NO DEFINIDO") -> 1 | Q27: =_xlfn.XLOOKUP(bbdd3[[#This Row],[CCO - SECTOR]],'cco '!$A:$A,'cco '!I:I,"CCO NO DEFINIDO") -> BACHAS | R27: =IF(ISBLANK(bbdd3[[#This Row],[CCO EMPRESA]]),1,_xlfn.XLOOKUP(bbdd3[[#This Row],[CCO EMPRESA]],'cco_worms_empresa'!$A:$A,'cco_worms_empresa'!$G:$G)) -> 1
A28: 46081 | B28: IMPUESTOS | C28: imp2 | D28: -5039229.7 | E28: IMPUESTOS | F28: 1 | G28: 5039229.7 | H28: UN | I28: IMPUESTOS | J28: OPEX | K28: VARIABLE | L28: INDIRECTO | N28: CC1 | O28: gastos_rrhh | P28: =_xlfn.XLOOKUP(bbdd3[[#This Row],[CCO - SECTOR]],'cco '!$A:$A,'cco '!F:F,"CCO NO DEFINIDO") -> 10 | Q28: =_xlfn.XLOOKUP(bbdd3[[#This Row],[CCO - SECTOR]],'cco '!$A:$A,'cco '!I:I,"CCO NO DEFINIDO") -> BACHAS, CEREAL & POLVILLO, COMPOST & FERTILIZANTES, DISPOSICIÓN FINAL RESIDUOS LIQUIDOS, DISPOSICIÓN FINAL RESIDUOS SOLIDOS, EXPORTACION, NFU, PILETAS, REACTORES, TIERRAS FILTRANTES | R28: =IF(ISBLANK(bbdd3[[#This Row],[CCO EMPRESA]]),1,_xlfn.XLOOKUP(bbdd3[[#This Row],[CCO EMPRESA]],'cco_worms_empresa'!$A:$A,'cco_worms_empresa'!$G:$G)) -> 1
A29: 46081 | B29: WORMS-RRHH | C29: DIAZ PABLO EMMANUEL | D29: -4660517 | E29: NFU | F29: 1 | G29: 4660517 | H29: #RRHH | I29: PERSONAL | J29: OPEX | N29: CC7 | O29: gastos_impuestos | P29: =_xlfn.XLOOKUP(bbdd3[[#This Row],[CCO - SECTOR]],'cco '!$A:$A,'cco '!F:F,"CCO NO DEFINIDO") -> 1 | Q29: =_xlfn.XLOOKUP(bbdd3[[#This Row],[CCO - SECTOR]],'cco '!$A:$A,'cco '!I:I,"CCO NO DEFINIDO") -> NFU | R29: =IF(ISBLANK(bbdd3[[#This Row],[CCO EMPRESA]]),1,_xlfn.XLOOKUP(bbdd3[[#This Row],[CCO EMPRESA]],'cco_worms_empresa'!$A:$A,'cco_worms_empresa'!$G:$G)) -> 1
A30: 46081 | B30: WORMS-RRHH | C30: CEBALLEZ, MARIA EUGENIA | D30: -4555960.9 | E30: PRODUCCION | F30: 1 | G30: 4555960.9 | H30: #RRHH | I30: PERSONAL | J30: OPEX | N30: CC28 | O30: gastos_produccion | P30: =_xlfn.XLOOKUP(bbdd3[[#This Row],[CCO - SECTOR]],'cco '!$A:$A,'cco '!F:F,"CCO NO DEFINIDO") -> 10 | Q30: =_xlfn.XLOOKUP(bbdd3[[#This Row],[CCO - SECTOR]],'cco '!$A:$A,'cco '!I:I,"CCO NO DEFINIDO") -> BACHAS, CEREAL & POLVILLO, COMPOST & FERTILIZANTES, DISPOSICIÓN FINAL RESIDUOS LIQUIDOS, DISPOSICIÓN FINAL RESIDUOS SOLIDOS, EXPORTACION, NFU, PILETAS, REACTORES, TIERRAS FILTRANTES | R30: =IF(ISBLANK(bbdd3[[#This Row],[CCO EMPRESA]]),1,_xlfn.XLOOKUP(bbdd3[[#This Row],[CCO EMPRESA]],'cco_worms_empresa'!$A:$A,'cco_worms_empresa'!$G:$G)) -> 1
A31: 46081 | B31: WORMS-RRHH | C31: TISCORNIA FERNANDO | D31: -4207865.4 | E31: DIRECTOR | F31: 1 | G31: 4207865.4 | H31: #RRHH | I31: PERSONAL | J31: OPEX | N31: CC16 | O31: gastos_produccion | P31: =_xlfn.XLOOKUP(bbdd3[[#This Row],[CCO - SECTOR]],'cco '!$A:$A,'cco '!F:F,"CCO NO DEFINIDO") -> 10 | Q31: =_xlfn.XLOOKUP(bbdd3[[#This Row],[CCO - SECTOR]],'cco '!$A:$A,'cco '!I:I,"CCO NO DEFINIDO") -> BACHAS, CEREAL Y POLVILLO, COMPOST Y FERTILIZANTES, DISPOSICION FINAL DE R. LIQUIDOS, DISPOSICION FINAL DE R. SOLIDOS, EXPORTACION, NFU, PILETAS, REACTORES, TIERRAS FILTRANTES | R31: =IF(ISBLANK(bbdd3[[#This Row],[CCO EMPRESA]]),1,_xlfn.XLOOKUP(bbdd3[[#This Row],[CCO EMPRESA]],'cco_worms_empresa'!$A:$A,'cco_worms_empresa'!$G:$G)) -> 1
A32: 46081 | B32: WORMS-RRHH | C32: LUQUE, ADRIAN | D32: -4107684.4 | E32: TALLER MECANICO | F32: 1 | G32: 4107684.4 | H32: #RRHH | I32: PERSONAL | J32: OPEX | N32: CC23 | O32: gastos_produccion | P32: =_xlfn.XLOOKUP(bbdd3[[#This Row],[CCO - SECTOR]],'cco '!$A:$A,'cco '!F:F,"CCO NO DEFINIDO") -> 10 | Q32: =_xlfn.XLOOKUP(bbdd3[[#This Row],[CCO - SECTOR]],'cco '!$A:$A,'cco '!I:I,"CCO NO DEFINIDO") -> BACHAS, CEREAL Y POLVILLO, COMPOST Y FERTILIZANTES, DISPOSICION FINAL DE R. LIQUIDOS, DISPOSICION FINAL DE R. SOLIDOS, EXPORTACION, NFU, PILETAS, REACTORES, TIERRAS FILTRANTES | R32: =IF(ISBLANK(bbdd3[[#This Row],[CCO EMPRESA]]),1,_xlfn.XLOOKUP(bbdd3[[#This Row],[CCO EMPRESA]],'cco_worms_empresa'!$A:$A,'cco_worms_empresa'!$G:$G)) -> 1
A33: 46072 | B33: Bordon, Carlos Roberto | C33: FA-C 00004-00000002 | D33: -4000000 | E33: INVERSION trabajo varios | F33: 1 | G33: 4000000 | H33: UN | I33: INVERSION | J33: CAPEX | K33: VARIABLE | L33: INDIRECTO | N33: CC6 | O33: gastos_rrhh | P33: =_xlfn.XLOOKUP(bbdd3[[#This Row],[CCO - SECTOR]],'cco '!$A:$A,'cco '!F:F,"CCO NO DEFINIDO") -> 1 | Q33: =_xlfn.XLOOKUP(bbdd3[[#This Row],[CCO - SECTOR]],'cco '!$A:$A,'cco '!I:I,"CCO NO DEFINIDO") -> BACHAS | R33: =IF(ISBLANK(bbdd3[[#This Row],[CCO EMPRESA]]),1,_xlfn.XLOOKUP(bbdd3[[#This Row],[CCO EMPRESA]],'cco_worms_empresa'!$A:$A,'cco_worms_empresa'!$G:$G)) -> 1
A34: 46081 | B34: WORMS-RRHH | C34: HONORES ANDRES | D34: -3780940.7 | E34: REACTOR | F34: 1 | G34: 3780940.7 | H34: #RRHH | I34: PERSONAL | J34: OPEX | N34: CC15 | O34: gastos_rrhh | P34: =_xlfn.XLOOKUP(bbdd3[[#This Row],[CCO - SECTOR]],'cco '!$A:$A,'cco '!F:F,"CCO NO DEFINIDO") -> 10 | Q34: =_xlfn.XLOOKUP(bbdd3[[#This Row],[CCO - SECTOR]],'cco '!$A:$A,'cco '!I:I,"CCO NO DEFINIDO") -> BACHAS, CEREAL Y POLVILLO, COMPOST Y FERTILIZANTES, DISPOSICION FINAL DE R. LIQUIDOS, DISPOSICION FINAL DE R. SOLIDOS, EXPORTACION, NFU, PILETAS, REACTORES, TIERRAS FILTRANTES | R34: =IF(ISBLANK(bbdd3[[#This Row],[CCO EMPRESA]]),1,_xlfn.XLOOKUP(bbdd3[[#This Row],[CCO EMPRESA]],'cco_worms_empresa'!$A:$A,'cco_worms_empresa'!$G:$G)) -> 1
A35: 46081 | B35: WORMS-RRHH | C35: PEREZ, MATIAS ROMAN | D35: -3671564.8 | E35: INTENDENCIA | F35: 1 | G35: 3671564.8 | H35: #RRHH | I35: PERSONAL | J35: OPEX | N35: CC27 | O35: gastos_rrhh | P35: =_xlfn.XLOOKUP(bbdd3[[#This Row],[CCO - SECTOR]],'cco '!$A:$A,'cco '!F:F,"CCO NO DEFINIDO") -> 10 | Q35: =_xlfn.XLOOKUP(bbdd3[[#This Row],[CCO - SECTOR]],'cco '!$A:$A,'cco '!I:I,"CCO NO DEFINIDO") -> BACHAS, CEREAL Y POLVILLO, COMPOST Y FERTILIZANTES, DISPOSICION FINAL DE R. LIQUIDOS, DISPOSICION FINAL DE R. SOLIDOS, EXPORTACION, NFU, PILETAS, REACTORES, TIERRAS FILTRANTES | R35: =IF(ISBLANK(bbdd3[[#This Row],[CCO EMPRESA]]),1,_xlfn.XLOOKUP(bbdd3[[#This Row],[CCO EMPRESA]],'cco_worms_empresa'!$A:$A,'cco_worms_empresa'!$G:$G)) -> 1
A36: 46056 | B36: Exportdeniv Internacional Sa | C36: FA-A 00002-00000604 | D36: -3455620.3 | E36: OC 0001-00004507: SERVICIOS Almacenaje cargas generales 1/26 | F36: 3969.24 | G36: 870.6 | H36: UN | I36: SERVICIOS | J36: OPEX | K36: VARIABLE | L36: DIRECTO | N36: CC11 | O36: gastos_produccion | P36: =_xlfn.XLOOKUP(bbdd3[[#This Row],[CCO - SECTOR]],'cco '!$A:$A,'cco '!F:F,"CCO NO DEFINIDO") -> 1 | Q36: =_xlfn.XLOOKUP(bbdd3[[#This Row],[CCO - SECTOR]],'cco '!$A:$A,'cco '!I:I,"CCO NO DEFINIDO") -> EXPORTACION | R36: =IF(ISBLANK(bbdd3[[#This Row],[CCO EMPRESA]]),1,_xlfn.XLOOKUP(bbdd3[[#This Row],[CCO EMPRESA]],'cco_worms_empresa'!$A:$A,'cco_worms_empresa'!$G:$G)) -> 1
A37: 46081 | B37: WORMS-RRHH | C37: LOPEZ CAMARGO BERLITZ, BEATRIZ | D37: -3415916.1 | E37: LABORATORIO | F37: 1 | G37: 3415916.1 | H37: #RRHH | I37: PERSONAL | J37: OPEX | N37: CC17 | O37: gastos_rrhh | P37: =_xlfn.XLOOKUP(bbdd3[[#This Row],[CCO - SECTOR]],'cco '!$A:$A,'cco '!F:F,"CCO NO DEFINIDO") -> 6 | Q37: =_xlfn.XLOOKUP(bbdd3[[#This Row],[CCO - SECTOR]],'cco '!$A:$A,'cco '!I:I,"CCO NO DEFINIDO") -> BACHAS, DISPOSICION FINAL DE R. LIQUIDOS, EXPORTACION, NFU, PILETAS, REACTORES | R37: =IF(ISBLANK(bbdd3[[#This Row],[CCO EMPRESA]]),1,_xlfn.XLOOKUP(bbdd3[[#This Row],[CCO EMPRESA]],'cco_worms_empresa'!$A:$A,'cco_worms_empresa'!$G:$G)) -> 1
A38: 46081 | B38: WORMS-RRHH | C38: PELUZZA, CLAUDIA | D38: -3387545.4 | E38: ADMINISTRACION | F38: 1 | G38: 3387545.4 | H38: #RRHH | I38: PERSONAL | J38: OPEX | N38: CC15 | O38: gastos_rrhh | P38: =_xlfn.XLOOKUP(bbdd3[[#This Row],[CCO - SECTOR]],'cco '!$A:$A,'cco '!F:F,"CCO NO DEFINIDO") -> 10 | Q38: =_xlfn.XLOOKUP(bbdd3[[#This Row],[CCO - SECTOR]],'cco '!$A:$A,'cco '!I:I,"CCO NO DEFINIDO") -> BACHAS, CEREAL Y POLVILLO, COMPOST Y FERTILIZANTES, DISPOSICION FINAL DE R. LIQUIDOS, DISPOSICION FINAL DE R. SOLIDOS, EXPORTACION, NFU, PILETAS, REACTORES, TIERRAS FILTRANTES | R38: =IF(ISBLANK(bbdd3[[#This Row],[CCO EMPRESA]]),1,_xlfn.XLOOKUP(bbdd3[[#This Row],[CCO EMPRESA]],'cco_worms_empresa'!$A:$A,'cco_worms_empresa'!$G:$G)) -> 1
A39: 46081 | B39: MARTINS, JOAQUIN | C39: prod10 | D39: -3363750 | E39: NAFTA | F39: 2250 | G39: 1495 | H39: Lts | I39: ENERGIA | J39: OPEX | K39: VARIABLE | L39: DIRECTO | N39: CC4 | O39: gastos_rrhh | P39: =_xlfn.XLOOKUP(bbdd3[[#This Row],[CCO - SECTOR]],'cco '!$A:$A,'cco '!F:F,"CCO NO DEFINIDO") -> 1 | Q39: =_xlfn.XLOOKUP(bbdd3[[#This Row],[CCO - SECTOR]],'cco '!$A:$A,'cco '!I:I,"CCO NO DEFINIDO") -> PILETAS | R39: =IF(ISBLANK(bbdd3[[#This Row],[CCO EMPRESA]]),1,_xlfn.XLOOKUP(bbdd3[[#This Row],[CCO EMPRESA]],'cco_worms_empresa'!$A:$A,'cco_worms_empresa'!$G:$G)) -> 1
A40: 46081 | B40: WORMS-RRHH | C40: CHIANEA ERWIN | D40: -3349666.3 | E40: PRODUCCION | F40: 1 | G40: 3349666.3 | H40: #RRHH | I40: PERSONAL | J40: OPEX | N40: CC28 | O40: gastos_rrhh | P40: =_xlfn.XLOOKUP(bbdd3[[#This Row],[CCO - SECTOR]],'cco '!$A:$A,'cco '!F:F,"CCO NO DEFINIDO") -> 10 | Q40: =_xlfn.XLOOKUP(bbdd3[[#This Row],[CCO - SECTOR]],'cco '!$A:$A,'cco '!I:I,"CCO NO DEFINIDO") -> BACHAS, CEREAL & POLVILLO, COMPOST & FERTILIZANTES, DISPOSICIÓN FINAL RESIDUOS LIQUIDOS, DISPOSICIÓN FINAL RESIDUOS SOLIDOS, EXPORTACION, NFU, PILETAS, REACTORES, TIERRAS FILTRANTES | R40: =IF(ISBLANK(bbdd3[[#This Row],[CCO EMPRESA]]),1,_xlfn.XLOOKUP(bbdd3[[#This Row],[CCO EMPRESA]],'cco_worms_empresa'!$A:$A,'cco_worms_empresa'!$G:$G)) -> 1
A41: 46081 | B41: WORMS-RRHH | C41: ISOLA, GIULIANA | D41: -3167990 | E41: ADMINISTRACION | F41: 1 | G41: 3167990 | H41: #RRHH | I41: PERSONAL | J41: OPEX | N41: CC15 | O41: gastos_impuestos | P41: =_xlfn.XLOOKUP(bbdd3[[#This Row],[CCO - SECTOR]],'cco '!$A:$A,'cco '!F:F,"CCO NO DEFINIDO") -> 10 | Q41: =_xlfn.XLOOKUP(bbdd3[[#This Row],[CCO - SECTOR]],'cco '!$A:$A,'cco '!I:I,"CCO NO DEFINIDO") -> BACHAS, CEREAL Y POLVILLO, COMPOST Y FERTILIZANTES, DISPOSICION FINAL DE R. LIQUIDOS, DISPOSICION FINAL DE R. SOLIDOS, EXPORTACION, NFU, PILETAS, REACTORES, TIERRAS FILTRANTES | R41: =IF(ISBLANK(bbdd3[[#This Row],[CCO EMPRESA]]),1,_xlfn.XLOOKUP(bbdd3[[#This Row],[CCO EMPRESA]],'cco_worms_empresa'!$A:$A,'cco_worms_empresa'!$G:$G)) -> 1
A42: 46081 | B42: WORMS-RRHH | C42: CULOTA ANDRES | D42: -3102992.3 | E42: ADMINISTRACION | F42: 1 | G42: 3102992.3 | H42: #RRHH | I42: PERSONAL | J42: OPEX | N42: CC15 | O42: gastos_rrhh | P42: =_xlfn.XLOOKUP(bbdd3[[#This Row],[CCO - SECTOR]],'cco '!$A:$A,'cco '!F:F,"CCO NO DEFINIDO") -> 10 | Q42: =_xlfn.XLOOKUP(bbdd3[[#This Row],[CCO - SECTOR]],'cco '!$A:$A,'cco '!I:I,"CCO NO DEFINIDO") -> BACHAS, CEREAL Y POLVILLO, COMPOST Y FERTILIZANTES, DISPOSICION FINAL DE R. LIQUIDOS, DISPOSICION FINAL DE R. SOLIDOS, EXPORTACION, NFU, PILETAS, REACTORES, TIERRAS FILTRANTES | R42: =IF(ISBLANK(bbdd3[[#This Row],[CCO EMPRESA]]),1,_xlfn.XLOOKUP(bbdd3[[#This Row],[CCO EMPRESA]],'cco_worms_empresa'!$A:$A,'cco_worms_empresa'!$G:$G)) -> 1
A43: 46081 | B43: WORMS-RRHH | C43: LARREY VANINA | D43: -3096266.9 | E43: PORTERIA | F43: 1 | G43: 3096266.9 | H43: #RRHH | I43: PERSONAL | J43: OPEX | N43: CC22 | O43: gastos_produccion | P43: =_xlfn.XLOOKUP(bbdd3[[#This Row],[CCO - SECTOR]],'cco '!$A:$A,'cco '!F:F,"CCO NO DEFINIDO") -> 7 | Q43: =_xlfn.XLOOKUP(bbdd3[[#This Row],[CCO - SECTOR]],'cco '!$A:$A,'cco '!I:I,"CCO NO DEFINIDO") -> BACHAS, COMPOST Y FERTILIZANTES, DISPOSICION FINAL DE R. LIQUIDOS, DISPOSICION FINAL DE R. SOLIDOS, EXPORTACION, NFU, REACTORES | R43: =IF(ISBLANK(bbdd3[[#This Row],[CCO EMPRESA]]),1,_xlfn.XLOOKUP(bbdd3[[#This Row],[CCO EMPRESA]],'cco_worms_empresa'!$A:$A,'cco_worms_empresa'!$G:$G)) -> 1
A44: 46081 | B44: WORMS-RRHH | C44: PETERS CORZO, JOSE LUIS | D44: -3091668.4 | E44: LABORATORIO | F44: 1 | G44: 3091668.4 | H44: #RRHH | I44: PERSONAL | J44: OPEX | N44: CC17 | O44: gastos_rrhh | P44: =_xlfn.XLOOKUP(bbdd3[[#This Row],[CCO - SECTOR]],'cco '!$A:$A,'cco '!F:F,"CCO NO DEFINIDO") -> 6 | Q44: =_xlfn.XLOOKUP(bbdd3[[#This Row],[CCO - SECTOR]],'cco '!$A:$A,'cco '!I:I,"CCO NO DEFINIDO") -> BACHAS, DISPOSICION FINAL DE R. LIQUIDOS, EXPORTACION, NFU, PILETAS, REACTORES | R44: =IF(ISBLANK(bbdd3[[#This Row],[CCO EMPRESA]]),1,_xlfn.XLOOKUP(bbdd3[[#This Row],[CCO EMPRESA]],'cco_worms_empresa'!$A:$A,'cco_worms_empresa'!$G:$G)) -> 1
A45: 46057 | B45: El Laboral Srl | C45: FA-A 00001-00009552 | D45: -3091668.1 | E45: OC 0001-00004006: PERSONAL Indumentaria Remeras, pantalón gorras | F45: 1 | G45: 2555097.6 | H45: UN | I45: PERSONAL | J45: OPEX | K45: VARIABLE | L45: DIRECTO | N45: CC1 | O45: gastos_rrhh | P45: =_xlfn.XLOOKUP(bbdd3[[#This Row],[CCO - SECTOR]],'cco '!$A:$A,'cco '!F:F,"CCO NO DEFINIDO") -> 10 | Q45: =_xlfn.XLOOKUP(bbdd3[[#This Row],[CCO - SECTOR]],'cco '!$A:$A,'cco '!I:I,"CCO NO DEFINIDO") -> BACHAS, CEREAL & POLVILLO, COMPOST & FERTILIZANTES, DISPOSICIÓN FINAL RESIDUOS LIQUIDOS, DISPOSICIÓN FINAL RESIDUOS SOLIDOS, EXPORTACION, NFU, PILETAS, REACTORES, TIERRAS FILTRANTES | R45: =IF(ISBLANK(bbdd3[[#This Row],[CCO EMPRESA]]),1,_xlfn.XLOOKUP(bbdd3[[#This Row],[CCO EMPRESA]],'cco_worms_empresa'!$A:$A,'cco_worms_empresa'!$G:$G)) -> 1
A46: 46071 | B46: Epp Y Mas S.A. | C46: FA-A 00006-00019294 | D46: -3059361.1 | E46: HIGIENE Y SEGURIDAD Elementos de protección personal | F46: 1 | G46: 2528397.6 | H46: UN | I46: HIGIENE Y SEGURIDAD | J46: OPEX | K46: VARIABLE | L46: DIRECTO | N46: CC1 | O46: gastos_rrhh | P46: =_xlfn.XLOOKUP(bbdd3[[#This Row],[CCO - SECTOR]],'cco '!$A:$A,'cco '!F:F,"CCO NO DEFINIDO") -> 10 | Q46: =_xlfn.XLOOKUP(bbdd3[[#This Row],[CCO - SECTOR]],'cco '!$A:$A,'cco '!I:I,"CCO NO DEFINIDO") -> BACHAS, CEREAL & POLVILLO, COMPOST & FERTILIZANTES, DISPOSICIÓN FINAL RESIDUOS LIQUIDOS, DISPOSICIÓN FINAL RESIDUOS SOLIDOS, EXPORTACION, NFU, PILETAS, REACTORES, TIERRAS FILTRANTES | R46: =IF(ISBLANK(bbdd3[[#This Row],[CCO EMPRESA]]),1,_xlfn.XLOOKUP(bbdd3[[#This Row],[CCO EMPRESA]],'cco_worms_empresa'!$A:$A,'cco_worms_empresa'!$G:$G)) -> 1
A47: 46054 | B47: Bustamante, Eduardo Maria(W) | C47: FA-A 00003-00000158 | D47: -3025000 | E47: OC 0001-00004493: HONORARIOS Servicios jurídicos Prestados en la ciudad autónoma de buenos aires | F47: 1 | G47: 2500000 | H47: UN | I47: HONORARIOS | J47: OPEX | K47: VARIABLE | L47: INDIRECTO | N47: CC1 | O47: gastos_rrhh | P47: =_xlfn.XLOOKUP(bbdd3[[#This Row],[CCO - SECTOR]],'cco '!$A:$A,'cco '!F:F,"CCO NO DEFINIDO") -> 10 | Q47: =_xlfn.XLOOKUP(bbdd3[[#This Row],[CCO - SECTOR]],'cco '!$A:$A,'cco '!I:I,"CCO NO DEFINIDO") -> BACHAS, CEREAL & POLVILLO, COMPOST & FERTILIZANTES, DISPOSICIÓN FINAL RESIDUOS LIQUIDOS, DISPOSICIÓN FINAL RESIDUOS SOLIDOS, EXPORTACION, NFU, PILETAS, REACTORES, TIERRAS FILTRANTES | R47: =IF(ISBLANK(bbdd3[[#This Row],[CCO EMPRESA]]),1,_xlfn.XLOOKUP(bbdd3[[#This Row],[CCO EMPRESA]],'cco_worms_empresa'!$A:$A,'cco_worms_empresa'!$G:$G)) -> 1
A48: 46081 | B48: WORMS-RRHH | C48: BUSTAMANTE ULISES BENIGNO | D48: -2951310.2 | E48: PILETAS | F48: 1 | G48: 2951310.2 | H48: #RRHH | I48: PERSONAL | J48: OPEX | N48: CC4 | O48: gastos_rrhh | P48: =_xlfn.XLOOKUP(bbdd3[[#This Row],[CCO - SECTOR]],'cco '!$A:$A,'cco '!F:F,"CCO NO DEFINIDO") -> 1 | Q48: =_xlfn.XLOOKUP(bbdd3[[#This Row],[CCO - SECTOR]],'cco '!$A:$A,'cco '!I:I,"CCO NO DEFINIDO") -> PILETAS | R48: =IF(ISBLANK(bbdd3[[#This Row],[CCO EMPRESA]]),1,_xlfn.XLOOKUP(bbdd3[[#This Row],[CCO EMPRESA]],'cco_worms_empresa'!$A:$A,'cco_worms_empresa'!$G:$G)) -> 1
A49: 46055 | B49: Acosta, Roberto Maximiliano | C49: FA-C 00001-00000674 | D49: -2950000 | E49: OC 0001-00004297: SERVICIOS Servicio de limpieza enero 2026 | F49: 1 | G49: 2950000 | H49: UN | I49: SERVICIOS | J49: OPEX | K49: VARIABLE | L49: INDIRECTO | N49: CC1 | O49: gastos_produccion | P49: =_xlfn.XLOOKUP(bbdd3[[#This Row],[CCO - SECTOR]],'cco '!$A:$A,'cco '!F:F,"CCO NO DEFINIDO") -> 10 | Q49: =_xlfn.XLOOKUP(bbdd3[[#This Row],[CCO - SECTOR]],'cco '!$A:$A,'cco '!I:I,"CCO NO DEFINIDO") -> BACHAS, CEREAL & POLVILLO, COMPOST & FERTILIZANTES, DISPOSICIÓN FINAL RESIDUOS LIQUIDOS, DISPOSICIÓN FINAL RESIDUOS SOLIDOS, EXPORTACION, NFU, PILETAS, REACTORES, TIERRAS FILTRANTES | R49: =IF(ISBLANK(bbdd3[[#This Row],[CCO EMPRESA]]),1,_xlfn.XLOOKUP(bbdd3[[#This Row],[CCO EMPRESA]],'cco_worms_empresa'!$A:$A,'cco_worms_empresa'!$G:$G)) -> 1
A50: 46055 | B50: Gonzalez, Delia | C50: FA-C 00001-00000012 | D50: -2950000 | E50: OC 0001-00004298: SERVICIOS Servicio de limpieza Enero 2026 | F50: 1 | G50: 2950000 | H50: UN | I50: SERVICIOS | J50: OPEX | K50: VARIABLE | L50: INDIRECTO | N50: CC1 | O50: gastos_produccion | P50: =_xlfn.XLOOKUP(bbdd3[[#This Row],[CCO - SECTOR]],'cco '!$A:$A,'cco '!F:F,"CCO NO DEFINIDO") -> 10 | Q50: =_xlfn.XLOOKUP(bbdd3[[#This Row],[CCO - SECTOR]],'cco '!$A:$A,'cco '!I:I,"CCO NO DEFINIDO") -> BACHAS, CEREAL & POLVILLO, COMPOST & FERTILIZANTES, DISPOSICIÓN FINAL RESIDUOS LIQUIDOS, DISPOSICIÓN FINAL RESIDUOS SOLIDOS, EXPORTACION, NFU, PILETAS, REACTORES, TIERRAS FILTRANTES | R50: =IF(ISBLANK(bbdd3[[#This Row],[CCO EMPRESA]]),1,_xlfn.XLOOKUP(bbdd3[[#This Row],[CCO EMPRESA]],'cco_worms_empresa'!$A:$A,'cco_worms_empresa'!$G:$G)) -> 1
A51: 46081 | B51: TOTAL QUIMICA S.A. | C51: prod2 | D51: -2928103.2 | E51: ACIDO SULFÚRICO 70/80 | F51: 7920 | G51: 369.71 | H51: KG | I51: INSUMOS | J51: OPEX | K51: VARIABLE | L51: DIRECTO | N51: CC6 | O51: gastos_rrhh | P51: =_xlfn.XLOOKUP(bbdd3[[#This Row],[CCO - SECTOR]],'cco '!$A:$A,'cco '!F:F,"CCO NO DEFINIDO") -> 1 | Q51: =_xlfn.XLOOKUP(bbdd3[[#This Row],[CCO - SECTOR]],'cco '!$A:$A,'cco '!I:I,"CCO NO DEFINIDO") -> BACHAS | R51: =IF(ISBLANK(bbdd3[[#This Row],[CCO EMPRESA]]),1,_xlfn.XLOOKUP(bbdd3[[#This Row],[CCO EMPRESA]],'cco_worms_empresa'!$A:$A,'cco_worms_empresa'!$G:$G)) -> 1
A52: 46081 | B52: WORMS-RRHH | C52: MONTENEGRO, GUSTAVO | D52: -2898353.7 | E52: INTENDENCIA | F52: 1 | G52: 2898353.7 | H52: #RRHH | I52: PERSONAL | J52: OPEX | N52: CC27 | O52: gastos_rrhh | P52: =_xlfn.XLOOKUP(bbdd3[[#This Row],[CCO - SECTOR]],'cco '!$A:$A,'cco '!F:F,"CCO NO DEFINIDO") -> 10 | Q52: =_xlfn.XLOOKUP(bbdd3[[#This Row],[CCO - SECTOR]],'cco '!$A:$A,'cco '!I:I,"CCO NO DEFINIDO") -> BACHAS, CEREAL Y POLVILLO, COMPOST Y FERTILIZANTES, DISPOSICION FINAL DE R. LIQUIDOS, DISPOSICION FINAL DE R. SOLIDOS, EXPORTACION, NFU, PILETAS, REACTORES, TIERRAS FILTRANTES | R52: =IF(ISBLANK(bbdd3[[#This Row],[CCO EMPRESA]]),1,_xlfn.XLOOKUP(bbdd3[[#This Row],[CCO EMPRESA]],'cco_worms_empresa'!$A:$A,'cco_worms_empresa'!$G:$G)) -> 1
A53: 46081 | B53: TOTAL QUIMICA S.A. | C53: prod12 | D53: -2871487.5 | E53: SODA CAUSTICA | F53: 3116 | G53: 921.53 | H53: KG | I53: INSUMOS | J53: OPEX | K53: VARIABLE | L53: DIRECTO | N53: CC5 | O53: gastos_rrhh | P53: =_xlfn.XLOOKUP(bbdd3[[#This Row],[CCO - SECTOR]],'cco '!$A:$A,'cco '!F:F,"CCO NO DEFINIDO") -> 1 | Q53: =_xlfn.XLOOKUP(bbdd3[[#This Row],[CCO - SECTOR]],'cco '!$A:$A,'cco '!I:I,"CCO NO DEFINIDO") -> REACTORES | R53: =IF(ISBLANK(bbdd3[[#This Row],[CCO EMPRESA]]),1,_xlfn.XLOOKUP(bbdd3[[#This Row],[CCO EMPRESA]],'cco_worms_empresa'!$A:$A,'cco_worms_empresa'!$G:$G)) -> 1
A54: 46061 | B54: Zavalia Lagos, Marina | C54: FA-C 00002-00000085 | D54: -2850000 | E54: OC 0001-00004592: HONORARIOS Servicios profesionales Tomas Bollini Enero 26 | F54: 1 | G54: 2850000 | H54: UN | I54: HONORARIOS | J54: OPEX | K54: VARIABLE | L54: INDIRECTO | N54: CC1 | O54: gastos_rrhh | P54: =_xlfn.XLOOKUP(bbdd3[[#This Row],[CCO - SECTOR]],'cco '!$A:$A,'cco '!F:F,"CCO NO DEFINIDO") -> 10 | Q54: =_xlfn.XLOOKUP(bbdd3[[#This Row],[CCO - SECTOR]],'cco '!$A:$A,'cco '!I:I,"CCO NO DEFINIDO") -> BACHAS, CEREAL & POLVILLO, COMPOST & FERTILIZANTES, DISPOSICIÓN FINAL RESIDUOS LIQUIDOS, DISPOSICIÓN FINAL RESIDUOS SOLIDOS, EXPORTACION, NFU, PILETAS, REACTORES, TIERRAS FILTRANTES | R54: =IF(ISBLANK(bbdd3[[#This Row],[CCO EMPRESA]]),1,_xlfn.XLOOKUP(bbdd3[[#This Row],[CCO EMPRESA]],'cco_worms_empresa'!$A:$A,'cco_worms_empresa'!$G:$G)) -> 1
A55: 46081 | B55: WORMS-RRHH | C55: BARRERA, MAXIMILIANO ESEQUIEL | D55: -2792560.3 | E55: DISPOSICION FINAL DE R. LIQUIDOS | F55: 1 | G55: 2792560.3 | H55: #RRHH | I55: PERSONAL | J55: OPEX | N55: CC25 | O55: gastos_produccion | P55: =_xlfn.XLOOKUP(bbdd3[[#This Row],[CCO - SECTOR]],'cco '!$A:$A,'cco '!F:F,"CCO NO DEFINIDO") -> 2 | Q55: =_xlfn.XLOOKUP(bbdd3[[#This Row],[CCO - SECTOR]],'cco '!$A:$A,'cco '!I:I,"CCO NO DEFINIDO") -> DISPOSICION FINAL DE R. LIQUIDOS, EXPORTACION | R55: =IF(ISBLANK(bbdd3[[#This Row],[CCO EMPRESA]]),1,_xlfn.XLOOKUP(bbdd3[[#This Row],[CCO EMPRESA]],'cco_worms_empresa'!$A:$A,'cco_worms_empresa'!$G:$G)) -> 1
A56: 46072 | B56: Chirichigno, Mario Alejandro | C56: FA-C 00003-00000212 | D56: -2727314 | E56: INVERSION etapa 2 proyecto 50 | F56: 1 | G56: 2727314 | H56: UN | I56: INVERSION | J56: CAPEX | K56: VARIABLE | L56: INDIRECTO | N56: CC1 | O56: gastos_produccion | P56: =_xlfn.XLOOKUP(bbdd3[[#This Row],[CCO - SECTOR]],'cco '!$A:$A,'cco '!F:F,"CCO NO DEFINIDO") -> 10 | Q56: =_xlfn.XLOOKUP(bbdd3[[#This Row],[CCO - SECTOR]],'cco '!$A:$A,'cco '!I:I,"CCO NO DEFINIDO") -> BACHAS, CEREAL & POLVILLO, COMPOST & FERTILIZANTES, DISPOSICIÓN FINAL RESIDUOS LIQUIDOS, DISPOSICIÓN FINAL RESIDUOS SOLIDOS, EXPORTACION, NFU, PILETAS, REACTORES, TIERRAS FILTRANTES | R56: =IF(ISBLANK(bbdd3[[#This Row],[CCO EMPRESA]]),1,_xlfn.XLOOKUP(bbdd3[[#This Row],[CCO EMPRESA]],'cco_worms_empresa'!$A:$A,'cco_worms_empresa'!$G:$G)) -> 1
A57: 46081 | B57: WORMS-RRHH | C57: TULLIANI ROMINA | D57: -2652084.9 | E57: DISPOSICION FINAL DE R. LIQUIDOS | F57: 1 | G57: 2652084.9 | H57: #RRHH | I57: PERSONAL | J57: OPEX | N57: CC25 | O57: gastos_rrhh | P57: =_xlfn.XLOOKUP(bbdd3[[#This Row],[CCO - SECTOR]],'cco '!$A:$A,'cco '!F:F,"CCO NO DEFINIDO") -> 2 | Q57: =_xlfn.XLOOKUP(bbdd3[[#This Row],[CCO - SECTOR]],'cco '!$A:$A,'cco '!I:I,"CCO NO DEFINIDO") -> DISPOSICION FINAL DE R. LIQUIDOS, EXPORTACION | R57: =IF(ISBLANK(bbdd3[[#This Row],[CCO EMPRESA]]),1,_xlfn.XLOOKUP(bbdd3[[#This Row],[CCO EMPRESA]],'cco_worms_empresa'!$A:$A,'cco_worms_empresa'!$G:$G)) -> 1
A58: 46081 | B58: WORMS-RRHH | C58: PARDEL, MAURO | D58: -2629398.4 | E58: PORTERIA | F58: 1 | G58: 2629398.4 | H58: #RRHH | I58: PERSONAL | J58: OPEX | N58: CC22 | O58: gastos_rrhh | P58: =_xlfn.XLOOKUP(bbdd3[[#This Row],[CCO - SECTOR]],'cco '!$A:$A,'cco '!F:F,"CCO NO DEFINIDO") -> 7 | Q58: =_xlfn.XLOOKUP(bbdd3[[#This Row],[CCO - SECTOR]],'cco '!$A:$A,'cco '!I:I,"CCO NO DEFINIDO") -> BACHAS, COMPOST Y FERTILIZANTES, DISPOSICION FINAL DE R. LIQUIDOS, DISPOSICION FINAL DE R. SOLIDOS, EXPORTACION, NFU, REACTORES | R58: =IF(ISBLANK(bbdd3[[#This Row],[CCO EMPRESA]]),1,_xlfn.XLOOKUP(bbdd3[[#This Row],[CCO EMPRESA]],'cco_worms_empresa'!$A:$A,'cco_worms_empresa'!$G:$G)) -> 1
A59: 46081 | B59: WORMS-RRHH | C59: DI PAOLO ANDREA ANALI | D59: -2603553.4 | E59: ADMINISTRACION | F59: 1 | G59: 2603553.4 | H59: #RRHH | I59: PERSONAL | J59: OPEX | N59: CC15 | O59: gastos_produccion | P59: =_xlfn.XLOOKUP(bbdd3[[#This Row],[CCO - SECTOR]],'cco '!$A:$A,'cco '!F:F,"CCO NO DEFINIDO") -> 10 | Q59: =_xlfn.XLOOKUP(bbdd3[[#This Row],[CCO - SECTOR]],'cco '!$A:$A,'cco '!I:I,"CCO NO DEFINIDO") -> BACHAS, CEREAL Y POLVILLO, COMPOST Y FERTILIZANTES, DISPOSICION FINAL DE R. LIQUIDOS, DISPOSICION FINAL DE R. SOLIDOS, EXPORTACION, NFU, PILETAS, REACTORES, TIERRAS FILTRANTES | R59: =IF(ISBLANK(bbdd3[[#This Row],[CCO EMPRESA]]),1,_xlfn.XLOOKUP(bbdd3[[#This Row],[CCO EMPRESA]],'cco_worms_empresa'!$A:$A,'cco_worms_empresa'!$G:$G)) -> 1
A60: 46081 | B60: WORMS-RRHH | C60: LOPEZ, AGUSTÍN ALBERTO | D60: -2599197.3 | E60: PORTERIA | F60: 1 | G60: 2599197.3 | H60: #RRHH | I60: PERSONAL | J60: OPEX | N60: CC22 | O60: gastos_rrhh | P60: =_xlfn.XLOOKUP(bbdd3[[#This Row],[CCO - SECTOR]],'cco '!$A:$A,'cco '!F:F,"CCO NO DEFINIDO") -> 7 | Q60: =_xlfn.XLOOKUP(bbdd3[[#This Row],[CCO - SECTOR]],'cco '!$A:$A,'cco '!I:I,"CCO NO DEFINIDO") -> BACHAS, COMPOST Y FERTILIZANTES, DISPOSICION FINAL DE R. LIQUIDOS, DISPOSICION FINAL DE R. SOLIDOS, EXPORTACION, NFU, REACTORES | R60: =IF(ISBLANK(bbdd3[[#This Row],[CCO EMPRESA]]),1,_xlfn.XLOOKUP(bbdd3[[#This Row],[CCO EMPRESA]],'cco_worms_empresa'!$A:$A,'cco_worms_empresa'!$G:$G)) -> 1
A61: 46081 | B61: WORMS-RRHH | C61: MAIDANA, JOSE RAMON | D61: -2416515 | E61: INTENDENCIA | F61: 1 | G61: 2416515 | H61: #RRHH | I61: PERSONAL | J61: OPEX | N61: CC27 | O61: gastos_rrhh | P61: =_xlfn.XLOOKUP(bbdd3[[#This Row],[CCO - SECTOR]],'cco '!$A:$A,'cco '!F:F,"CCO NO DEFINIDO") -> 10 | Q61: =_xlfn.XLOOKUP(bbdd3[[#This Row],[CCO - SECTOR]],'cco '!$A:$A,'cco '!I:I,"CCO NO DEFINIDO") -> BACHAS, CEREAL Y POLVILLO, COMPOST Y FERTILIZANTES, DISPOSICION FINAL DE R. LIQUIDOS, DISPOSICION FINAL DE R. SOLIDOS, EXPORTACION, NFU, PILETAS, REACTORES, TIERRAS FILTRANTES | R61: =IF(ISBLANK(bbdd3[[#This Row],[CCO EMPRESA]]),1,_xlfn.XLOOKUP(bbdd3[[#This Row],[CCO EMPRESA]],'cco_worms_empresa'!$A:$A,'cco_worms_empresa'!$G:$G)) -> 1
A62: 46081 | B62: WORMS-RRHH | C62: LOPEZ JESUS | D62: -2394868.4 | E62: LOGISTICA | F62: 1 | G62: 2394868.4 | H62: #RRHH | I62: PERSONAL | J62: OPEX | N62: CC18 | O62: gastos_rrhh | P62: =_xlfn.XLOOKUP(bbdd3[[#This Row],[CCO - SECTOR]],'cco '!$A:$A,'cco '!F:F,"CCO NO DEFINIDO") -> 5 | Q62: =_xlfn.XLOOKUP(bbdd3[[#This Row],[CCO - SECTOR]],'cco '!$A:$A,'cco '!I:I,"CCO NO DEFINIDO") -> DISPOSICION FINAL DE R. SOLIDOS, EXPORTACION, NFU, PILETAS, REACTORES | R62: =IF(ISBLANK(bbdd3[[#This Row],[CCO EMPRESA]]),1,_xlfn.XLOOKUP(bbdd3[[#This Row],[CCO EMPRESA]],'cco_worms_empresa'!$A:$A,'cco_worms_empresa'!$G:$G)) -> 1
A63: 46081 | B63: WORMS-RRHH | C63: BUSTAMANTE, GUSTAVO GASTON | D63: -2366793.4 | E63: DISPOSICION FINAL DE R. LIQUIDOS | F63: 1 | G63: 2366793.4 | H63: #RRHH | I63: PERSONAL | J63: OPEX | N63: CC25 | O63: gastos_rrhh | P63: =_xlfn.XLOOKUP(bbdd3[[#This Row],[CCO - SECTOR]],'cco '!$A:$A,'cco '!F:F,"CCO NO DEFINIDO") -> 2 | Q63: =_xlfn.XLOOKUP(bbdd3[[#This Row],[CCO - SECTOR]],'cco '!$A:$A,'cco '!I:I,"CCO NO DEFINIDO") -> DISPOSICION FINAL DE R. LIQUIDOS, EXPORTACION | R63: =IF(ISBLANK(bbdd3[[#This Row],[CCO EMPRESA]]),1,_xlfn.XLOOKUP(bbdd3[[#This Row],[CCO EMPRESA]],'cco_worms_empresa'!$A:$A,'cco_worms_empresa'!$G:$G)) -> 1
A64: 46063 | B64: Mil Propiedades Srl | C64: FA-A 00001-00000734 | D64: -2359500 | E64: SERVICIOS alquiler Mod STD C/AA Sauce Viejo Desde 16/02 al 15/03 Baradero 07/02 al 06/03 Coronda 11/02 al 10/03 Timbues 14/02 al 13/03 | F64: 4 | G64: 390000 | H64: UN | I64: SERVICIOS | J64: OPEX | K64: VARIABLE | L64: INDIRECTO | N64: CC7 | O64: gastos_produccion | P64: =_xlfn.XLOOKUP(bbdd3[[#This Row],[CCO - SECTOR]],'cco '!$A:$A,'cco '!F:F,"CCO NO DEFINIDO") -> 1 | Q64: =_xlfn.XLOOKUP(bbdd3[[#This Row],[CCO - SECTOR]],'cco '!$A:$A,'cco '!I:I,"CCO NO DEFINIDO") -> NFU | R64: =IF(ISBLANK(bbdd3[[#This Row],[CCO EMPRESA]]),1,_xlfn.XLOOKUP(bbdd3[[#This Row],[CCO EMPRESA]],'cco_worms_empresa'!$A:$A,'cco_worms_empresa'!$G:$G)) -> 1
A65: 46063 | B65: Servitubos S.R.L. | C65: FA-A 00005-00015672 | D65: -2348640.4 | E65: OC 0001-00004633: INVERSION T.Pvc.san.clot.160x3,2z4m | F65: 70 | G65: 27728.93 | H65: UN | I65: INVERSION | J65: CAPEX | K65: VARIABLE | L65: INDIRECTO | N65: CC3 | O65: gastos_rrhh | P65: =_xlfn.XLOOKUP(bbdd3[[#This Row],[CCO - SECTOR]],'cco '!$A:$A,'cco '!F:F,"CCO NO DEFINIDO") -> 1 | Q65: =_xlfn.XLOOKUP(bbdd3[[#This Row],[CCO - SECTOR]],'cco '!$A:$A,'cco '!I:I,"CCO NO DEFINIDO") -> DISPOSICIÓN FINAL RESIDUOS LIQUIDOS | R65: =IF(ISBLANK(bbdd3[[#This Row],[CCO EMPRESA]]),1,_xlfn.XLOOKUP(bbdd3[[#This Row],[CCO EMPRESA]],'cco_worms_empresa'!$A:$A,'cco_worms_empresa'!$G:$G)) -> 1
A66: 46081 | B66: WORMS-RRHH | C66: BRAVO FRANCISCO NICOLAS | D66: -2339355.3 | E66: DISPOSICION FINAL DE R. LIQUIDOS | F66: 1 | G66: 2339355.3 | H66: #RRHH | I66: PERSONAL | J66: OPEX | N66: CC25 | O66: gastos_produccion | P66: =_xlfn.XLOOKUP(bbdd3[[#This Row],[CCO - SECTOR]],'cco '!$A:$A,'cco '!F:F,"CCO NO DEFINIDO") -> 2 | Q66: =_xlfn.XLOOKUP(bbdd3[[#This Row],[CCO - SECTOR]],'cco '!$A:$A,'cco '!I:I,"CCO NO DEFINIDO") -> DISPOSICION FINAL DE R. LIQUIDOS, EXPORTACION | R66: =IF(ISBLANK(bbdd3[[#This Row],[CCO EMPRESA]]),1,_xlfn.XLOOKUP(bbdd3[[#This Row],[CCO EMPRESA]],'cco_worms_empresa'!$A:$A,'cco_worms_empresa'!$G:$G)) -> 1
A67: 46081 | B67: WORMS-RRHH | C67: ENRIQUEZ, MAXIMO GUSTAVO | D67: -2318520.2 | E67: DISPOSICION FINAL DE R. LIQUIDOS | F67: 1 | G67: 2318520.2 | H67: #RRHH | I67: PERSONAL | J67: OPEX | N67: CC25 | O67: gastos_produccion | P67: =_xlfn.XLOOKUP(bbdd3[[#This Row],[CCO - SECTOR]],'cco '!$A:$A,'cco '!F:F,"CCO NO DEFINIDO") -> 2 | Q67: =_xlfn.XLOOKUP(bbdd3[[#This Row],[CCO - SECTOR]],'cco '!$A:$A,'cco '!I:I,"CCO NO DEFINIDO") -> DISPOSICION FINAL DE R. LIQUIDOS, EXPORTACION | R67: =IF(ISBLANK(bbdd3[[#This Row],[CCO EMPRESA]]),1,_xlfn.XLOOKUP(bbdd3[[#This Row],[CCO EMPRESA]],'cco_worms_empresa'!$A:$A,'cco_worms_empresa'!$G:$G)) -> 1
A68: 46081 | B68: WORMS-RRHH | C68: PANZANELLA, EDUARDO JAVIER | D68: -2316608.1 | E68: PORTERIA | F68: 1 | G68: 2316608.1 | H68: #RRHH | I68: PERSONAL | J68: OPEX | N68: CC22 | O68: gastos_rrhh | P68: =_xlfn.XLOOKUP(bbdd3[[#This Row],[CCO - SECTOR]],'cco '!$A:$A,'cco '!F:F,"CCO NO DEFINIDO") -> 7 | Q68: =_xlfn.XLOOKUP(bbdd3[[#This Row],[CCO - SECTOR]],'cco '!$A:$A,'cco '!I:I,"CCO NO DEFINIDO") -> BACHAS, COMPOST Y FERTILIZANTES, DISPOSICION FINAL DE R. LIQUIDOS, DISPOSICION FINAL DE R. SOLIDOS, EXPORTACION, NFU, REACTORES | R68: =IF(ISBLANK(bbdd3[[#This Row],[CCO EMPRESA]]),1,_xlfn.XLOOKUP(bbdd3[[#This Row],[CCO EMPRESA]],'cco_worms_empresa'!$A:$A,'cco_worms_empresa'!$G:$G)) -> 1
A69: 46081 | B69: WORMS-RRHH | C69: NUÑEZ ALAN OSVALDO | D69: -2289443.2 | E69: PILETAS | F69: 1 | G69: 2289443.2 | H69: #RRHH | I69: PERSONAL | J69: OPEX | N69: CC4 | O69: gastos_rrhh | P69: =_xlfn.XLOOKUP(bbdd3[[#This Row],[CCO - SECTOR]],'cco '!$A:$A,'cco '!F:F,"CCO NO DEFINIDO") -> 1 | Q69: =_xlfn.XLOOKUP(bbdd3[[#This Row],[CCO - SECTOR]],'cco '!$A:$A,'cco '!I:I,"CCO NO DEFINIDO") -> PILETAS | R69: =IF(ISBLANK(bbdd3[[#This Row],[CCO EMPRESA]]),1,_xlfn.XLOOKUP(bbdd3[[#This Row],[CCO EMPRESA]],'cco_worms_empresa'!$A:$A,'cco_worms_empresa'!$G:$G)) -> 1
A70: 46081 | B70: WORMS-RRHH | C70: ACOSTA JORGE SEBASTIAN | D70: -2242802.5 | E70: BACHAS | F70: 1 | G70: 2242802.5 | H70: #RRHH | I70: PERSONAL | J70: OPEX | N70: CC6 | O70: gastos_rrhh | P70: =_xlfn.XLOOKUP(bbdd3[[#This Row],[CCO - SECTOR]],'cco '!$A:$A,'cco '!F:F,"CCO NO DEFINIDO") -> 1 | Q70: =_xlfn.XLOOKUP(bbdd3[[#This Row],[CCO - SECTOR]],'cco '!$A:$A,'cco '!I:I,"CCO NO DEFINIDO") -> BACHAS | R70: =IF(ISBLANK(bbdd3[[#This Row],[CCO EMPRESA]]),1,_xlfn.XLOOKUP(bbdd3[[#This Row],[CCO EMPRESA]],'cco_worms_empresa'!$A:$A,'cco_worms_empresa'!$G:$G)) -> 1
A71: 46055 | B71: Adhoc S.A.(W) | C71: FA-A 00003-00021368 | D71: -2212671.5 | E71: OC 0001-00003852: SERVICIOS Sistema contable | F71: 1 | G71: 1828654.1 | H71: UN | I71: SERVICIOS | J71: OPEX | K71: FIJO | L71: INDIRECTO | N71: CC1 | O71: gastos_rrhh | P71: =_xlfn.XLOOKUP(bbdd3[[#This Row],[CCO - SECTOR]],'cco '!$A:$A,'cco '!F:F,"CCO NO DEFINIDO") -> 10 | Q71: =_xlfn.XLOOKUP(bbdd3[[#This Row],[CCO - SECTOR]],'cco '!$A:$A,'cco '!I:I,"CCO NO DEFINIDO") -> BACHAS, CEREAL & POLVILLO, COMPOST & FERTILIZANTES, DISPOSICIÓN FINAL RESIDUOS LIQUIDOS, DISPOSICIÓN FINAL RESIDUOS SOLIDOS, EXPORTACION, NFU, PILETAS, REACTORES, TIERRAS FILTRANTES | R71: =IF(ISBLANK(bbdd3[[#This Row],[CCO EMPRESA]]),1,_xlfn.XLOOKUP(bbdd3[[#This Row],[CCO EMPRESA]],'cco_worms_empresa'!$A:$A,'cco_worms_empresa'!$G:$G)) -> 1
A72: 46081 | B72: WORMS-RRHH | C72: RODRIGUEZ, HORACIO | D72: -2197552.3 | E72: TALLER MECANICO | F72: 1 | G72: 2197552.3 | H72: #RRHH | I72: PERSONAL | J72: OPEX | N72: CC23 | O72: gastos_rrhh | P72: =_xlfn.XLOOKUP(bbdd3[[#This Row],[CCO - SECTOR]],'cco '!$A:$A,'cco '!F:F,"CCO NO DEFINIDO") -> 10 | Q72: =_xlfn.XLOOKUP(bbdd3[[#This Row],[CCO - SECTOR]],'cco '!$A:$A,'cco '!I:I,"CCO NO DEFINIDO") -> BACHAS, CEREAL Y POLVILLO, COMPOST Y FERTILIZANTES, DISPOSICION FINAL DE R. LIQUIDOS, DISPOSICION FINAL DE R. SOLIDOS, EXPORTACION, NFU, PILETAS, REACTORES, TIERRAS FILTRANTES | R72: =IF(ISBLANK(bbdd3[[#This Row],[CCO EMPRESA]]),1,_xlfn.XLOOKUP(bbdd3[[#This Row],[CCO EMPRESA]],'cco_worms_empresa'!$A:$A,'cco_worms_empresa'!$G:$G)) -> 1
A73: 46081 | B73: WORMS-RRHH | C73: PACHECO MAURICIO | D73: -2184449.2 | E73: VIGILANCIA | F73: 1 | G73: 2184449.2 | H73: #RRHH | I73: PERSONAL | J73: OPEX | N73: CC29 | O73: gastos_produccion | P73: =_xlfn.XLOOKUP(bbdd3[[#This Row],[CCO - SECTOR]],'cco '!$A:$A,'cco '!F:F,"CCO NO DEFINIDO") -> 10 | Q73: =_xlfn.XLOOKUP(bbdd3[[#This Row],[CCO - SECTOR]],'cco '!$A:$A,'cco '!I:I,"CCO NO DEFINIDO") -> BACHAS, CEREAL Y POLVILLO, COMPOST Y FERTILIZANTES, DISPOSICION FINAL DE R. LIQUIDOS, DISPOSICION FINAL DE R. SOLIDOS, EXPORTACION, NFU, PILETAS, REACTORES, TIERRAS FILTRANTES | R73: =IF(ISBLANK(bbdd3[[#This Row],[CCO EMPRESA]]),1,_xlfn.XLOOKUP(bbdd3[[#This Row],[CCO EMPRESA]],'cco_worms_empresa'!$A:$A,'cco_worms_empresa'!$G:$G)) -> 1
A74: 46081 | B74: WORMS-RRHH | C74: ALVAREZ ALEJANDRO | D74: -2183724.5 | E74: PILETAS | F74: 1 | G74: 2183724.5 | H74: #RRHH | I74: PERSONAL | J74: OPEX | N74: CC4 | O74: gastos_rrhh | P74: =_xlfn.XLOOKUP(bbdd3[[#This Row],[CCO - SECTOR]],'cco '!$A:$A,'cco '!F:F,"CCO NO DEFINIDO") -> 1 | Q74: =_xlfn.XLOOKUP(bbdd3[[#This Row],[CCO - SECTOR]],'cco '!$A:$A,'cco '!I:I,"CCO NO DEFINIDO") -> PILETAS | R74: =IF(ISBLANK(bbdd3[[#This Row],[CCO EMPRESA]]),1,_xlfn.XLOOKUP(bbdd3[[#This Row],[CCO EMPRESA]],'cco_worms_empresa'!$A:$A,'cco_worms_empresa'!$G:$G)) -> 1
A75: 46081 | B75: WORMS-RRHH | C75: RODRIGUEZ, AYRTON | D75: -2171482.7 | E75: DISPOSICION FINAL DE R. LIQUIDOS | F75: 1 | G75: 2171482.7 | H75: #RRHH | I75: PERSONAL | J75: OPEX | N75: CC25 | O75: gastos_rrhh | P75: =_xlfn.XLOOKUP(bbdd3[[#This Row],[CCO - SECTOR]],'cco '!$A:$A,'cco '!F:F,"CCO NO DEFINIDO") -> 2 | Q75: =_xlfn.XLOOKUP(bbdd3[[#This Row],[CCO - SECTOR]],'cco '!$A:$A,'cco '!I:I,"CCO NO DEFINIDO") -> DISPOSICION FINAL DE R. LIQUIDOS, EXPORTACION | R75: =IF(ISBLANK(bbdd3[[#This Row],[CCO EMPRESA]]),1,_xlfn.XLOOKUP(bbdd3[[#This Row],[CCO EMPRESA]],'cco_worms_empresa'!$A:$A,'cco_worms_empresa'!$G:$G)) -> 1
A76: 46081 | B76: WORMS-RRHH | C76: ALTAMIRANO, GUSTAVO | D76: -2164958.5 | E76: NFU | F76: 1 | G76: 2164958.5 | H76: #RRHH | I76: PERSONAL | J76: OPEX | N76: CC7 | O76: gastos_rrhh | P76: =_xlfn.XLOOKUP(bbdd3[[#This Row],[CCO - SECTOR]],'cco '!$A:$A,'cco '!F:F,"CCO NO DEFINIDO") -> 1 | Q76: =_xlfn.XLOOKUP(bbdd3[[#This Row],[CCO - SECTOR]],'cco '!$A:$A,'cco '!I:I,"CCO NO DEFINIDO") -> NFU | R76: =IF(ISBLANK(bbdd3[[#This Row],[CCO EMPRESA]]),1,_xlfn.XLOOKUP(bbdd3[[#This Row],[CCO EMPRESA]],'cco_worms_empresa'!$A:$A,'cco_worms_empresa'!$G:$G)) -> 1
A77: 46081 | B77: WORMS-RRHH | C77: PORCU, MIGUEL ANGEL | D77: -2153887.5 | E77: PILETAS | F77: 1 | G77: 2153887.5 | H77: #RRHH | I77: PERSONAL | J77: OPEX | N77: CC4 | O77: gastos_rrhh | P77: =_xlfn.XLOOKUP(bbdd3[[#This Row],[CCO - SECTOR]],'cco '!$A:$A,'cco '!F:F,"CCO NO DEFINIDO") -> 1 | Q77: =_xlfn.XLOOKUP(bbdd3[[#This Row],[CCO - SECTOR]],'cco '!$A:$A,'cco '!I:I,"CCO NO DEFINIDO") -> PILETAS | R77: =IF(ISBLANK(bbdd3[[#This Row],[CCO EMPRESA]]),1,_xlfn.XLOOKUP(bbdd3[[#This Row],[CCO EMPRESA]],'cco_worms_empresa'!$A:$A,'cco_worms_empresa'!$G:$G)) -> 1
A78: 46081 | B78: WORMS-RRHH | C78: GOMEZ, FRANCO JAVIER | D78: -2140538.4 | E78: DISPOSICION FINAL DE R. LIQUIDOS | F78: 1 | G78: 2140538.4 | H78: #RRHH | I78: PERSONAL | J78: OPEX | N78: CC25 | O78: gastos_rrhh | P78: =_xlfn.XLOOKUP(bbdd3[[#This Row],[CCO - SECTOR]],'cco '!$A:$A,'cco '!F:F,"CCO NO DEFINIDO") -> 2 | Q78: =_xlfn.XLOOKUP(bbdd3[[#This Row],[CCO - SECTOR]],'cco '!$A:$A,'cco '!I:I,"CCO NO DEFINIDO") -> DISPOSICION FINAL DE R. LIQUIDOS, EXPORTACION | R78: =IF(ISBLANK(bbdd3[[#This Row],[CCO EMPRESA]]),1,_xlfn.XLOOKUP(bbdd3[[#This Row],[CCO EMPRESA]],'cco_worms_empresa'!$A:$A,'cco_worms_empresa'!$G:$G)) -> 1
A79: 46081 | B79: WORMS-RRHH | C79: PETERS DIAZ, RAMÓN RICARDO | D79: -2081874.7 | E79: LABORATORIO | F79: 1 | G79: 2081874.7 | H79: #RRHH | I79: PERSONAL | J79: OPEX | N79: CC17 | O79: gastos_produccion | P79: =_xlfn.XLOOKUP(bbdd3[[#This Row],[CCO - SECTOR]],'cco '!$A:$A,'cco '!F:F,"CCO NO DEFINIDO") -> 6 | Q79: =_xlfn.XLOOKUP(bbdd3[[#This Row],[CCO - SECTOR]],'cco '!$A:$A,'cco '!I:I,"CCO NO DEFINIDO") -> BACHAS, DISPOSICION FINAL DE R. LIQUIDOS, EXPORTACION, NFU, PILETAS, REACTORES | R79: =IF(ISBLANK(bbdd3[[#This Row],[CCO EMPRESA]]),1,_xlfn.XLOOKUP(bbdd3[[#This Row],[CCO EMPRESA]],'cco_worms_empresa'!$A:$A,'cco_worms_empresa'!$G:$G)) -> 1
A80: 46081 | B80: WORMS-RRHH | C80: DE AVELENDA VALENTIN | D80: -2057254.4 | E80: DISPOSICION FINAL DE R. LIQUIDOS | F80: 1 | G80: 2057254.4 | H80: #RRHH | I80: PERSONAL | J80: OPEX | N80: CC25 | O80: gastos_rrhh | P80: =_xlfn.XLOOKUP(bbdd3[[#This Row],[CCO - SECTOR]],'cco '!$A:$A,'cco '!F:F,"CCO NO DEFINIDO") -> 2 | Q80: =_xlfn.XLOOKUP(bbdd3[[#This Row],[CCO - SECTOR]],'cco '!$A:$A,'cco '!I:I,"CCO NO DEFINIDO") -> DISPOSICION FINAL DE R. LIQUIDOS, EXPORTACION | R80: =IF(ISBLANK(bbdd3[[#This Row],[CCO EMPRESA]]),1,_xlfn.XLOOKUP(bbdd3[[#This Row],[CCO EMPRESA]],'cco_worms_empresa'!$A:$A,'cco_worms_empresa'!$G:$G)) -> 1
A81: 46081 | B81: WORMS-RRHH | C81: MATTAROLO EDITH | D81: -2056682.7 | E81: PORTERIA | F81: 1 | G81: 2056682.7 | H81: #RRHH | I81: PERSONAL | J81: OPEX | N81: CC22 | O81: gastos_rrhh | P81: =_xlfn.XLOOKUP(bbdd3[[#This Row],[CCO - SECTOR]],'cco '!$A:$A,'cco '!F:F,"CCO NO DEFINIDO") -> 7 | Q81: =_xlfn.XLOOKUP(bbdd3[[#This Row],[CCO - SECTOR]],'cco '!$A:$A,'cco '!I:I,"CCO NO DEFINIDO") -> BACHAS, COMPOST Y FERTILIZANTES, DISPOSICION FINAL DE R. LIQUIDOS, DISPOSICION FINAL DE R. SOLIDOS, EXPORTACION, NFU, REACTORES | R81: =IF(ISBLANK(bbdd3[[#This Row],[CCO EMPRESA]]),1,_xlfn.XLOOKUP(bbdd3[[#This Row],[CCO EMPRESA]],'cco_worms_empresa'!$A:$A,'cco_worms_empresa'!$G:$G)) -> 1
A82: 46081 | B82: WORMS-RRHH | C82: ALVAREZ IVAN DARIO | D82: -2041933.5 | E82: ADMINISTRACION | F82: 1 | G82: 2041933.5 | H82: #RRHH | I82: PERSONAL | J82: OPEX | N82: CC15 | O82: gastos_rrhh | P82: =_xlfn.XLOOKUP(bbdd3[[#This Row],[CCO - SECTOR]],'cco '!$A:$A,'cco '!F:F,"CCO NO DEFINIDO") -> 10 | Q82: =_xlfn.XLOOKUP(bbdd3[[#This Row],[CCO - SECTOR]],'cco '!$A:$A,'cco '!I:I,"CCO NO DEFINIDO") -> BACHAS, CEREAL Y POLVILLO, COMPOST Y FERTILIZANTES, DISPOSICION FINAL DE R. LIQUIDOS, DISPOSICION FINAL DE R. SOLIDOS, EXPORTACION, NFU, PILETAS, REACTORES, TIERRAS FILTRANTES | R82: =IF(ISBLANK(bbdd3[[#This Row],[CCO EMPRESA]]),1,_xlfn.XLOOKUP(bbdd3[[#This Row],[CCO EMPRESA]],'cco_worms_empresa'!$A:$A,'cco_worms_empresa'!$G:$G)) -> 1
A83: 46081 | B83: WORMS-RRHH | C83: FRANCO BRUNO | D83: -2029819 | E83: DISPOSICION FINAL DE R. LIQUIDOS | F83: 1 | G83: 2029819 | H83: #RRHH | I83: PERSONAL | J83: OPEX | N83: CC25 | O83: gastos_rrhh | P83: =_xlfn.XLOOKUP(bbdd3[[#This Row],[CCO - SECTOR]],'cco '!$A:$A,'cco '!F:F,"CCO NO DEFINIDO") -> 2 | Q83: =_xlfn.XLOOKUP(bbdd3[[#This Row],[CCO - SECTOR]],'cco '!$A:$A,'cco '!I:I,"CCO NO DEFINIDO") -> DISPOSICION FINAL DE R. LIQUIDOS, EXPORTACION | R83: =IF(ISBLANK(bbdd3[[#This Row],[CCO EMPRESA]]),1,_xlfn.XLOOKUP(bbdd3[[#This Row],[CCO EMPRESA]],'cco_worms_empresa'!$A:$A,'cco_worms_empresa'!$G:$G)) -> 1
... A86: 46081 | B86: WORMS-RRHH | C86: AREVALO MARCOS AXEL | D86: -1992393.4 | E86: TALLER MECANICO | F86: 1 | G86: 1992393.4 | H86: #RRHH | I86: PERSONAL | J86: OPEX | N86: CC23 | O86: gastos_produccion | P86: =_xlfn.XLOOKUP(bbdd3[[#This Row],[CCO - SECTOR]],'cco '!$A:$A,'cco '!F:F,"CCO NO DEFINIDO") -> 10 | Q86: =_xlfn.XLOOKUP(bbdd3[[#This Row],[CCO - SECTOR]],'cco '!$A:$A,'cco '!I:I,"CCO NO DEFINIDO") -> BACHAS, CEREAL Y POLVILLO, COMPOST Y FERTILIZANTES, DISPOSICION FINAL DE R. LIQUIDOS, DISPOSICION FINAL DE R. SOLIDOS, EXPORTACION, NFU, PILETAS, REACTORES, TIERRAS FILTRANTES | R86: =IF(ISBLANK(bbdd3[[#This Row],[CCO EMPRESA]]),1,_xlfn.XLOOKUP(bbdd3[[#This Row],[CCO EMPRESA]],'cco_worms_empresa'!$A:$A,'cco_worms_empresa'!$G:$G)) -> 1
A87: 46063 | B87: Strupeni, Federico Lisandro | C87: FA-A 00008-00000058 | D87: -1979272.1 | E87: OC 0001-00004631: INVERSION Disco 4tb para grabación nvr | F87: 4 | G87: 342403.2 | H87: UN | I87: INVERSION | J87: CAPEX | K87: VARIABLE | L87: INDIRECTO | N87: CC11 | O87: gastos_rrhh | P87: =_xlfn.XLOOKUP(bbdd3[[#This Row],[CCO - SECTOR]],'cco '!$A:$A,'cco '!F:F,"CCO NO DEFINIDO") -> 1 | Q87: =_xlfn.XLOOKUP(bbdd3[[#This Row],[CCO - SECTOR]],'cco '!$A:$A,'cco '!I:I,"CCO NO DEFINIDO") -> EXPORTACION | R87: =IF(ISBLANK(bbdd3[[#This Row],[CCO EMPRESA]]),1,_xlfn.XLOOKUP(bbdd3[[#This Row],[CCO EMPRESA]],'cco_worms_empresa'!$A:$A,'cco_worms_empresa'!$G:$G)) -> 1
A88: 46081 | B88: WORMS-RRHH | C88: BORDON CAMILO RAFAEL | D88: -1972720.5 | E88: REACTOR | F88: 1 | G88: 1972720.5 | H88: #RRHH | I88: PERSONAL | J88: OPEX | N88: CC15 | O88: gastos_rrhh | P88: =_xlfn.XLOOKUP(bbdd3[[#This Row],[CCO - SECTOR]],'cco '!$A:$A,'cco '!F:F,"CCO NO DEFINIDO") -> 10 | Q88: =_xlfn.XLOOKUP(bbdd3[[#This Row],[CCO - SECTOR]],'cco '!$A:$A,'cco '!I:I,"CCO NO DEFINIDO") -> BACHAS, CEREAL Y POLVILLO, COMPOST Y FERTILIZANTES, DISPOSICION FINAL DE R. LIQUIDOS, DISPOSICION FINAL DE R. SOLIDOS, EXPORTACION, NFU, PILETAS, REACTORES, TIERRAS FILTRANTES | R88: =IF(ISBLANK(bbdd3[[#This Row],[CCO EMPRESA]]),1,_xlfn.XLOOKUP(bbdd3[[#This Row],[CCO EMPRESA]],'cco_worms_empresa'!$A:$A,'cco_worms_empresa'!$G:$G)) -> 1
A89: 46081 | B89: WORMS-RRHH | C89: FERNANDEZ, HECTOR OSCAR | D89: -1958595.1 | E89: VIGILANCIA | F89: 1 | G89: 1958595.1 | H89: #RRHH | I89: PERSONAL | J89: OPEX | N89: CC29 | O89: gastos_rrhh | P89: =_xlfn.XLOOKUP(bbdd3[[#This Row],[CCO - SECTOR]],'cco '!$A:$A,'cco '!F:F,"CCO NO DEFINIDO") -> 10 | Q89: =_xlfn.XLOOKUP(bbdd3[[#This Row],[CCO - SECTOR]],'cco '!$A:$A,'cco '!I:I,"CCO NO DEFINIDO") -> BACHAS, CEREAL Y POLVILLO, COMPOST Y FERTILIZANTES, DISPOSICION FINAL DE R. LIQUIDOS, DISPOSICION FINAL DE R. SOLIDOS, EXPORTACION, NFU, PILETAS, REACTORES, TIERRAS FILTRANTES | R89: =IF(ISBLANK(bbdd3[[#This Row],[CCO EMPRESA]]),1,_xlfn.XLOOKUP(bbdd3[[#This Row],[CCO EMPRESA]],'cco_worms_empresa'!$A:$A,'cco_worms_empresa'!$G:$G)) -> 1
A90: 46081 | B90: WORMS-RRHH | C90: MORENO RAMIRO ROMAN | D90: -1942874.4 | E90: PILETAS | F90: 1 | G90: 1942874.4 | H90: #RRHH | I90: PERSONAL | J90: OPEX | N90: CC4 | O90: gastos_rrhh | P90: =_xlfn.XLOOKUP(bbdd3[[#This Row],[CCO - SECTOR]],'cco '!$A:$A,'cco '!F:F,"CCO NO DEFINIDO") -> 1 | Q90: =_xlfn.XLOOKUP(bbdd3[[#This Row],[CCO - SECTOR]],'cco '!$A:$A,'cco '!I:I,"CCO NO DEFINIDO") -> PILETAS | R90: =IF(ISBLANK(bbdd3[[#This Row],[CCO EMPRESA]]),1,_xlfn.XLOOKUP(bbdd3[[#This Row],[CCO EMPRESA]],'cco_worms_empresa'!$A:$A,'cco_worms_empresa'!$G:$G)) -> 1
A91: 46081 | B91: WORMS-RRHH | C91: MARTINEZ JUAN PABLO | D91: -1942605.2 | E91: MANTENIMIENTO | F91: 1 | G91: 1942605.2 | H91: #RRHH | I91: PERSONAL | J91: OPEX | N91: CC19 | O91: gastos_rrhh | P91: =_xlfn.XLOOKUP(bbdd3[[#This Row],[CCO - SECTOR]],'cco '!$A:$A,'cco '!F:F,"CCO NO DEFINIDO") -> 6 | Q91: =_xlfn.XLOOKUP(bbdd3[[#This Row],[CCO - SECTOR]],'cco '!$A:$A,'cco '!I:I,"CCO NO DEFINIDO") -> BACHAS, DISPOSICION FINAL DE R. LIQUIDOS, EXPORTACION, NFU, PILETAS, REACTORES | R91: =IF(ISBLANK(bbdd3[[#This Row],[CCO EMPRESA]]),1,_xlfn.XLOOKUP(bbdd3[[#This Row],[CCO EMPRESA]],'cco_worms_empresa'!$A:$A,'cco_worms_empresa'!$G:$G)) -> 1
A92: 46081 | B92: WORMS-RRHH | C92: CORDOBA GABRIEL | D92: -1930813.4 | E92: ADMINISTRACION | F92: 1 | G92: 1930813.4 | H92: #RRHH | I92: PERSONAL | J92: OPEX | N92: CC15 | O92: gastos_rrhh | P92: =_xlfn.XLOOKUP(bbdd3[[#This Row],[CCO - SECTOR]],'cco '!$A:$A,'cco '!F:F,"CCO NO DEFINIDO") -> 10 | Q92: =_xlfn.XLOOKUP(bbdd3[[#This Row],[CCO - SECTOR]],'cco '!$A:$A,'cco '!I:I,"CCO NO DEFINIDO") -> BACHAS, CEREAL Y POLVILLO, COMPOST Y FERTILIZANTES, DISPOSICION FINAL DE R. LIQUIDOS, DISPOSICION FINAL DE R. SOLIDOS, EXPORTACION, NFU, PILETAS, REACTORES, TIERRAS FILTRANTES | R92: =IF(ISBLANK(bbdd3[[#This Row],[CCO EMPRESA]]),1,_xlfn.XLOOKUP(bbdd3[[#This Row],[CCO EMPRESA]],'cco_worms_empresa'!$A:$A,'cco_worms_empresa'!$G:$G)) -> 1
A93: 46081 | B93: WORMS-RRHH | C93: OVANDO, BRYAN EZEQUIEL | D93: -1928700.1 | E93: MANTENIMIENTO | F93: 1 | G93: 1928700.1 | H93: #RRHH | I93: PERSONAL | J93: OPEX | N93: CC19 | O93: gastos_rrhh | P93: =_xlfn.XLOOKUP(bbdd3[[#This Row],[CCO - SECTOR]],'cco '!$A:$A,'cco '!F:F,"CCO NO DEFINIDO") -> 6 | Q93: =_xlfn.XLOOKUP(bbdd3[[#This Row],[CCO - SECTOR]],'cco '!$A:$A,'cco '!I:I,"CCO NO DEFINIDO") -> BACHAS, DISPOSICION FINAL DE R. LIQUIDOS, EXPORTACION, NFU, PILETAS, REACTORES | R93: =IF(ISBLANK(bbdd3[[#This Row],[CCO EMPRESA]]),1,_xlfn.XLOOKUP(bbdd3[[#This Row],[CCO EMPRESA]],'cco_worms_empresa'!$A:$A,'cco_worms_empresa'!$G:$G)) -> 1
A94: 46081 | B94: WORMS-RRHH | C94: CABRERA JULIAN LEON | D94: -1914723.4 | E94: REACTOR | F94: 1 | G94: 1914723.4 | H94: #RRHH | I94: PERSONAL | J94: OPEX | N94: CC15 | O94: gastos_rrhh | P94: =_xlfn.XLOOKUP(bbdd3[[#This Row],[CCO - SECTOR]],'cco '!$A:$A,'cco '!F:F,"CCO NO DEFINIDO") -> 10 | Q94: =_xlfn.XLOOKUP(bbdd3[[#This Row],[CCO - SECTOR]],'cco '!$A:$A,'cco '!I:I,"CCO NO DEFINIDO") -> BACHAS, CEREAL Y POLVILLO, COMPOST Y FERTILIZANTES, DISPOSICION FINAL DE R. LIQUIDOS, DISPOSICION FINAL DE R. SOLIDOS, EXPORTACION, NFU, PILETAS, REACTORES, TIERRAS FILTRANTES | R94: =IF(ISBLANK(bbdd3[[#This Row],[CCO EMPRESA]]),1,_xlfn.XLOOKUP(bbdd3[[#This Row],[CCO EMPRESA]],'cco_worms_empresa'!$A:$A,'cco_worms_empresa'!$G:$G)) -> 1
A95: 46081 | B95: WORMS-RRHH | C95: CARIAGA, SOFIA | D95: -1898057.5 | E95: ADMINISTRACION | F95: 1 | G95: 1898057.5 | H95: #RRHH | I95: PERSONAL | J95: OPEX | N95: CC15 | O95: gastos_rrhh | P95: =_xlfn.XLOOKUP(bbdd3[[#This Row],[CCO - SECTOR]],'cco '!$A:$A,'cco '!F:F,"CCO NO DEFINIDO") -> 10 | Q95: =_xlfn.XLOOKUP(bbdd3[[#This Row],[CCO - SECTOR]],'cco '!$A:$A,'cco '!I:I,"CCO NO DEFINIDO") -> BACHAS, CEREAL Y POLVILLO, COMPOST Y FERTILIZANTES, DISPOSICION FINAL DE R. LIQUIDOS, DISPOSICION FINAL DE R. SOLIDOS, EXPORTACION, NFU, PILETAS, REACTORES, TIERRAS FILTRANTES | R95: =IF(ISBLANK(bbdd3[[#This Row],[CCO EMPRESA]]),1,_xlfn.XLOOKUP(bbdd3[[#This Row],[CCO EMPRESA]],'cco_worms_empresa'!$A:$A,'cco_worms_empresa'!$G:$G)) -> 1
A96: 46081 | B96: WORMS-RRHH | C96: FERNANDEZ JEREMIAS EDGARDO NAHUEL | D96: -1848040.3 | E96: BACHAS | F96: 1 | G96: 1848040.3 | H96: #RRHH | I96: PERSONAL | J96: OPEX | N96: CC6 | O96: gastos_rrhh | P96: =_xlfn.XLOOKUP(bbdd3[[#This Row],[CCO - SECTOR]],'cco '!$A:$A,'cco '!F:F,"CCO NO DEFINIDO") -> 1 | Q96: =_xlfn.XLOOKUP(bbdd3[[#This Row],[CCO - SECTOR]],'cco '!$A:$A,'cco '!I:I,"CCO NO DEFINIDO") -> BACHAS | R96: =IF(ISBLANK(bbdd3[[#This Row],[CCO EMPRESA]]),1,_xlfn.XLOOKUP(bbdd3[[#This Row],[CCO EMPRESA]],'cco_worms_empresa'!$A:$A,'cco_worms_empresa'!$G:$G)) -> 1
A97: 46081 | B97: WORMS-RRHH | C97: RODRIGUEZ LEANDRO | D97: -1841830.6 | E97: REACTOR | F97: 1 | G97: 1841830.6 | H97: #RRHH | I97: PERSONAL | J97: OPEX | N97: CC15 | O97: gastos_rrhh | P97: =_xlfn.XLOOKUP(bbdd3[[#This Row],[CCO - SECTOR]],'cco '!$A:$A,'cco '!F:F,"CCO NO DEFINIDO") -> 10 | Q97: =_xlfn.XLOOKUP(bbdd3[[#This Row],[CCO - SECTOR]],'cco '!$A:$A,'cco '!I:I,"CCO NO DEFINIDO") -> BACHAS, CEREAL Y POLVILLO, COMPOST Y FERTILIZANTES, DISPOSICION FINAL DE R. LIQUIDOS, DISPOSICION FINAL DE R. SOLIDOS, EXPORTACION, NFU, PILETAS, REACTORES, TIERRAS FILTRANTES | R97: =IF(ISBLANK(bbdd3[[#This Row],[CCO EMPRESA]]),1,_xlfn.XLOOKUP(bbdd3[[#This Row],[CCO EMPRESA]],'cco_worms_empresa'!$A:$A,'cco_worms_empresa'!$G:$G)) -> 1
A98: 46081 | B98: WORMS-RRHH | C98: VAZQUEZ MATIAS EMANUEL | D98: -1836940.1 | E98: PILETAS | F98: 1 | G98: 1836940.1 | H98: #RRHH | I98: PERSONAL | J98: OPEX | N98: CC4 | O98: gastos_rrhh | P98: =_xlfn.XLOOKUP(bbdd3[[#This Row],[CCO - SECTOR]],'cco '!$A:$A,'cco '!F:F,"CCO NO DEFINIDO") -> 1 | Q98: =_xlfn.XLOOKUP(bbdd3[[#This Row],[CCO - SECTOR]],'cco '!$A:$A,'cco '!I:I,"CCO NO DEFINIDO") -> PILETAS | R98: =IF(ISBLANK(bbdd3[[#This Row],[CCO EMPRESA]]),1,_xlfn.XLOOKUP(bbdd3[[#This Row],[CCO EMPRESA]],'cco_worms_empresa'!$A:$A,'cco_worms_empresa'!$G:$G)) -> 1
A99: 46081 | B99: WORMS-RRHH | C99: REY ROLANDO | D99: -1824756.7 | E99: LOGISTICA | F99: 1 | G99: 1824756.7 | H99: #RRHH | I99: PERSONAL | J99: OPEX | N99: CC18 | O99: gastos_rrhh | P99: =_xlfn.XLOOKUP(bbdd3[[#This Row],[CCO - SECTOR]],'cco '!$A:$A,'cco '!F:F,"CCO NO DEFINIDO") -> 5 | Q99: =_xlfn.XLOOKUP(bbdd3[[#This Row],[CCO - SECTOR]],'cco '!$A:$A,'cco '!I:I,"CCO NO DEFINIDO") -> DISPOSICION FINAL DE R. SOLIDOS, EXPORTACION, NFU, PILETAS, REACTORES | R99: =IF(ISBLANK(bbdd3[[#This Row],[CCO EMPRESA]]),1,_xlfn.XLOOKUP(bbdd3[[#This Row],[CCO EMPRESA]],'cco_worms_empresa'!$A:$A,'cco_worms_empresa'!$G:$G)) -> 1
... A113: 46081 | B113: WORMS-RRHH | C113: BALBUENA MAXIMILIANO EZEQUIEL | D113: -1589809.1 | E113: PILETAS | F113: 1 | G113: 1589809.1 | H113: #RRHH | I113: PERSONAL | J113: OPEX | N113: CC4 | O113: gastos_produccion | P113: =_xlfn.XLOOKUP(bbdd3[[#This Row],[CCO - SECTOR]],'cco '!$A:$A,'cco '!F:F,"CCO NO DEFINIDO") -> 1 | Q113: =_xlfn.XLOOKUP(bbdd3[[#This Row],[CCO - SECTOR]],'cco '!$A:$A,'cco '!I:I,"CCO NO DEFINIDO") -> PILETAS | R113: =IF(ISBLANK(bbdd3[[#This Row],[CCO EMPRESA]]),1,_xlfn.XLOOKUP(bbdd3[[#This Row],[CCO EMPRESA]],'cco_worms_empresa'!$A:$A,'cco_worms_empresa'!$G:$G)) -> 1
A114: 46055 | B114: Centauro Alpha S R L | C114: FA-A 00003-00010896 | D114: -1580819.6 | E114: OC 0001-00004383: MANTENIMIENTO PREVENTIVO | F114: 175 | G114: 6541.5 | H114: UN | I114: MANTENIMIENTO PREVENTIVO | J114: OPEX | K114: VARIABLE | L114: INDIRECTO | N114: CC1 | O114: gastos_produccion | P114: =_xlfn.XLOOKUP(bbdd3[[#This Row],[CCO - SECTOR]],'cco '!$A:$A,'cco '!F:F,"CCO NO DEFINIDO") -> 10 | Q114: =_xlfn.XLOOKUP(bbdd3[[#This Row],[CCO - SECTOR]],'cco '!$A:$A,'cco '!I:I,"CCO NO DEFINIDO") -> BACHAS, CEREAL & POLVILLO, COMPOST & FERTILIZANTES, DISPOSICIÓN FINAL RESIDUOS LIQUIDOS, DISPOSICIÓN FINAL RESIDUOS SOLIDOS, EXPORTACION, NFU, PILETAS, REACTORES, TIERRAS FILTRANTES | R114: =IF(ISBLANK(bbdd3[[#This Row],[CCO EMPRESA]]),1,_xlfn.XLOOKUP(bbdd3[[#This Row],[CCO EMPRESA]],'cco_worms_empresa'!$A:$A,'cco_worms_empresa'!$G:$G)) -> 1
A115: 46057 | B115: Tecnogran S R L | C115: FA-A 00012-00000385 | D115: -1580036.1 | E115: OC 0001-00003876: SERVICIOS Control de plagas Marzo 2026 | F115: 1 | G115: 1305815 | H115: UN | I115: SERVICIOS | J115: OPEX | K115: FIJO | L115: INDIRECTO | N115: CC1 | O115: gastos_produccion | P115: =_xlfn.XLOOKUP(bbdd3[[#This Row],[CCO - SECTOR]],'cco '!$A:$A,'cco '!F:F,"CCO NO DEFINIDO") -> 10 | Q115: =_xlfn.XLOOKUP(bbdd3[[#This Row],[CCO - SECTOR]],'cco '!$A:$A,'cco '!I:I,"CCO NO DEFINIDO") -> BACHAS, CEREAL & POLVILLO, COMPOST & FERTILIZANTES, DISPOSICIÓN FINAL RESIDUOS LIQUIDOS, DISPOSICIÓN FINAL RESIDUOS SOLIDOS, EXPORTACION, NFU, PILETAS, REACTORES, TIERRAS FILTRANTES | R115: =IF(ISBLANK(bbdd3[[#This Row],[CCO EMPRESA]]),1,_xlfn.XLOOKUP(bbdd3[[#This Row],[CCO EMPRESA]],'cco_worms_empresa'!$A:$A,'cco_worms_empresa'!$G:$G)) -> 1
A116: 46073 | B116: Huxley S.A. | C116: FA-A 00005-00041434 | D116: -1535490 | E116: LOGISTICA | F116: 15 | G116: 84600 | H116: UN | I116: IMPUESTOS | J116: OPEX | K116: VARIABLE | L116: DIRECTO | N116: CC11 | O116: gastos_rrhh | P116: =_xlfn.XLOOKUP(bbdd3[[#This Row],[CCO - SECTOR]],'cco '!$A:$A,'cco '!F:F,"CCO NO DEFINIDO") -> 1 | Q116: =_xlfn.XLOOKUP(bbdd3[[#This Row],[CCO - SECTOR]],'cco '!$A:$A,'cco '!I:I,"CCO NO DEFINIDO") -> EXPORTACION | R116: =IF(ISBLANK(bbdd3[[#This Row],[CCO EMPRESA]]),1,_xlfn.XLOOKUP(bbdd3[[#This Row],[CCO EMPRESA]],'cco_worms_empresa'!$A:$A,'cco_worms_empresa'!$G:$G)) -> 1
A117: 46081 | B117: WORMS-RRHH | C117: MARTINEZ, FRANCO ALBERTO | D117: -1480271.3 | E117: CAT | F117: 1 | G117: 1480271.3 | H117: #RRHH | I117: PERSONAL | J117: OPEX | N117: CC7 | O117: gastos_rrhh | P117: =_xlfn.XLOOKUP(bbdd3[[#This Row],[CCO - SECTOR]],'cco '!$A:$A,'cco '!F:F,"CCO NO DEFINIDO") -> 1 | Q117: =_xlfn.XLOOKUP(bbdd3[[#This Row],[CCO - SECTOR]],'cco '!$A:$A,'cco '!I:I,"CCO NO DEFINIDO") -> NFU | R117: =IF(ISBLANK(bbdd3[[#This Row],[CCO EMPRESA]]),1,_xlfn.XLOOKUP(bbdd3[[#This Row],[CCO EMPRESA]],'cco_worms_empresa'!$A:$A,'cco_worms_empresa'!$G:$G)) -> 1
A118: 46081 | B118: WORMS-RRHH | C118: LISARDO, MATIAS IVAN | D118: -1476009.9 | E118: REACTOR | F118: 1 | G118: 1476009.9 | H118: #RRHH | I118: PERSONAL | J118: OPEX | N118: CC15 | O118: gastos_rrhh | P118: =_xlfn.XLOOKUP(bbdd3[[#This Row],[CCO - SECTOR]],'cco '!$A:$A,'cco '!F:F,"CCO NO DEFINIDO") -> 10 | Q118: =_xlfn.XLOOKUP(bbdd3[[#This Row],[CCO - SECTOR]],'cco '!$A:$A,'cco '!I:I,"CCO NO DEFINIDO") -> BACHAS, CEREAL Y POLVILLO, COMPOST Y FERTILIZANTES, DISPOSICION FINAL DE R. LIQUIDOS, DISPOSICION FINAL DE R. SOLIDOS, EXPORTACION, NFU, PILETAS, REACTORES, TIERRAS FILTRANTES | R118: =IF(ISBLANK(bbdd3[[#This Row],[CCO EMPRESA]]),1,_xlfn.XLOOKUP(bbdd3[[#This Row],[CCO EMPRESA]],'cco_worms_empresa'!$A:$A,'cco_worms_empresa'!$G:$G)) -> 1
A119: 46081 | B119: WORMS-RRHH | C119: PASQUALINI, FLORENCIA | D119: -1456024.6 | E119: ADMINISTRACION | F119: 1 | G119: 1456024.6 | H119: #RRHH | I119: PERSONAL | J119: OPEX | N119: CC15 | O119: gastos_rrhh | P119: =_xlfn.XLOOKUP(bbdd3[[#This Row],[CCO - SECTOR]],'cco '!$A:$A,'cco '!F:F,"CCO NO DEFINIDO") -> 10 | Q119: =_xlfn.XLOOKUP(bbdd3[[#This Row],[CCO - SECTOR]],'cco '!$A:$A,'cco '!I:I,"CCO NO DEFINIDO") -> BACHAS, CEREAL Y POLVILLO, COMPOST Y FERTILIZANTES, DISPOSICION FINAL DE R. LIQUIDOS, DISPOSICION FINAL DE R. SOLIDOS, EXPORTACION, NFU, PILETAS, REACTORES, TIERRAS FILTRANTES | R119: =IF(ISBLANK(bbdd3[[#This Row],[CCO EMPRESA]]),1,_xlfn.XLOOKUP(bbdd3[[#This Row],[CCO EMPRESA]],'cco_worms_empresa'!$A:$A,'cco_worms_empresa'!$G:$G)) -> 1
...

Sheet aperturado_por_empresa.p2
A1: {=_xlfn._xlws.PY(0,0,bbdd3[])} -> 0 | B1: 1 | C1: 2 | D1: 3 | E1: 4 | F1: 5 | G1: 6 | H1: 7 | I1: 8 | J1: 9 | K1: 10 | L1: 11 | M1: 12 | N1: 13 | O1: 14 | P1: 15 | Q1: 16 | R1: 17 | S1: Total*prc (D×R) | T1: Cantidad*prc (F×R) | U1: APERTURADO POR EMPRESA
A2: 46081 | B2: WORMS 2 | C2: prod17 | D2: -1.9004255e+09 | E2: AFE (S) | F2: 1403.96 | G2: 945 | H2: TN | I2: MATERIA PRIMA | J2: OPEX | K2: VARIABLE | L2: DIRECTO | M2: 0 | N2: CC11 | O2: gastos_produccion | P2: 1 | Q2: EXPORTACION | R2: 1 | S2: -1.9004255e+09 | T2: 1403.96 | U2: APERTURADO POR EMPRESA
A3: 46081 | B3: WORMS 2 | C3: prod15 | D3: -1.1459658e+08 | E3: AFE (G) | F3: 86.96 | G3: 920 | H3: TN | I3: MATERIA PRIMA | J3: OPEX | K3: VARIABLE | L3: DIRECTO | M3: 0 | N3: CC11 | O3: gastos_produccion | P3: 1 | Q3: EXPORTACION | R3: 1 | S3: -1.1459658e+08 | T3: 86.96 | U3: APERTURADO POR EMPRESA
A4: 46081 | B4: WORMS 2 | C4: prod29 | D4: -87594125 | E4: ARE- B | F4: 72.8 | G4: 840 | H4: TN | I4: MATERIA PRIMA | J4: OPEX | K4: VARIABLE | L4: DIRECTO | M4: 0 | N4: CC11 | O4: gastos_produccion | P4: 1 | Q4: EXPORTACION | R4: 1 | S4: -87594125 | T4: 72.8 | U4: APERTURADO POR EMPRESA
A5: 46081 | B5: WORMS 1 | C5: prod26 | D5: -78996860 | E5: AG-D | F5: 110.3 | G5: 500 | H5: TN | I5: MATERIA PRIMA | J5: OPEX | K5: VARIABLE | L5: DIRECTO | M5: 0 | N5: CC6 | O5: gastos_produccion | P5: 1 | Q5: BACHAS | R5: 1 | S5: -78996860 | T5: 110.3 | U5: APERTURADO POR EMPRESA
A6: 46081 | B6: MILO - DENIS LUQUE | C6: prod13 | D6: -67513309 | E6: GLICERINA CRUDA | F6: 130.925 | G6: 360 | H6: TN | I6: INSUMOS | J6: OPEX | K6: VARIABLE | L6: DIRECTO | M6: 0 | N6: CC5 | O6: gastos_produccion | P6: 1 | Q6: REACTORES | R6: 1 | S6: -67513309 | T6: 130.925 | U6: APERTURADO POR EMPRESA
A7: 46066 | B7: Construcciones Industriales Y Portuarias S.A. | C7: FA-A 00003-00001286 | D7: -54208000 | E7: INVERSION Planta de efluentes | F7: 1 | G7: 44800000 | H7: UN | I7: INVERSION | J7: CAPEX | K7: VARIABLE | L7: INDIRECTO | M7: 0 | N7: CC3 | O7: gastos_produccion | P7: 1 | Q7: DISPOSICIÓN FINAL RESIDUOS LIQUIDOS | R7: 1 | S7: -54208000 | T7: 1 | U7: APERTURADO POR EMPRESA
A8: 46056 | B8: Construcciones Industriales Y Portuarias S.A. | C8: FA-A 00003-00001279 | D8: -54208000 | E8: OC 0001-00004263: INVERSION Planta de efluentes | F8: 1 | G8: 44800000 | H8: UN | I8: INVERSION | J8: CAPEX | K8: VARIABLE | L8: INDIRECTO | M8: 0 | N8: CC3 | O8: gastos_produccion | P8: 1 | Q8: DISPOSICIÓN FINAL RESIDUOS LIQUIDOS | R8: 1 | S8: -54208000 | T8: 1 | U8: APERTURADO POR EMPRESA
A9: 46081 | B9: WORMS 2 | C9: prod19 | D9: -42638251 | E9: AG- A | F9: 35.02 | G9: 850 | H9: TN | I9: MATERIA PRIMA | J9: OPEX | K9: VARIABLE | L9: DIRECTO | M9: 0 | N9: CC11 | O9: gastos_produccion | P9: 1 | Q9: EXPORTACION | R9: 1 | S9: -42638251 | T9: 35.02 | U9: APERTURADO POR EMPRESA
A10: 46055 | B10: Gmc Valores Sociedad Anonima | C10: OCOM/2026/0113 | D10: -32228280 | E10: OC 0001-00004462: INVERSION NORDIC | F10: 1 | G10: 32228280 | H10: UN | I10: INVERSION | J10: CAPEX | K10: VARIABLE | L10: DIRECTO | M10: 0 | N10: CC3 | O10: gastos_produccion | P10: 1 | Q10: DISPOSICIÓN FINAL RESIDUOS LIQUIDOS | R10: 1 | S10: -32228280 | T10: 1 | U10: APERTURADO POR EMPRESA
A11: 46063 | B11: Empresa Provincial De La Energia De Santa Fe (W) | C11: FA-A 00069-00037349 | D11: -30539110 | E11: OC 0001-00003944: ENERGIA Luz | F11: 1 | G11: 20913570 | H11: UN | I11: ENERGIA | J11: OPEX | K11: VARIABLE | L11: DIRECTO | M11: 0 | N11: CC14 | O11: gastos_produccion | P11: 10 | Q11: BACHAS, CEREAL & POLVILLO, COMPOST & FERTILIZANTES, DISPOSICIÓN FINAL RESIDUOS LIQUIDOS, DISPOSICIÓN FINAL RESIDUOS SOLIDOS, EXPORTACION, NFU, PILETAS, REACTORES, TIERRAS FILTRANTES | R11: 1 | S11: -30539110 | T11: 1 | U11: APERTURADO POR EMPRESA
A12: 46081 | B12: LOGISTICA EXPORTACION | C12: FA-C 2-2026-1 | D12: -24743492 | E12: FOB | F12: 692.61 | G12: 35725 | H12: TN | I12: LOGISTICA | J12: OPEX | K12: VARIABLE | L12: DIRECTO | M12: 0 | N12: CC11 | O12: gastos_produccion | P12: 1 | Q12: EXPORTACION | R12: 1 | S12: -24743492 | T12: 692.61 | U12: APERTURADO POR EMPRESA
A13: 46081 | B13: WORMS 1 | C13: prod33 | D13: -23997713 | E13: FONDO TK | F13: 33.507 | G13: 500 | H13: TN | I13: MATERIA PRIMA | J13: OPEX | K13: VARIABLE | L13: DIRECTO | M13: 0 | N13: CC6 | O13: gastos_rrhh | P13: 1 | Q13: BACHAS | R13: 1 | S13: -23997713 | T13: 33.507 | U13: APERTURADO POR EMPRESA
... A18: 46059 | B18: Bca Distribuciones Sa | C18: FA-A 00001-00005780 | D18: -11030401 | E18: OC 0001-00004176: INVERSION Proyecto 35 Bomba a pedido de Fernando T | F18: 1 | G18: 9116034.2 | H18: UN | I18: INVERSION | J18: CAPEX | K18: VARIABLE | L18: DIRECTO | M18: 0 | N18: CC6 | O18: gastos_produccion | P18: 1 | Q18: BACHAS | R18: 1 | S18: -11030401 | T18: 1 | U18: APERTURADO POR EMPRESA
A19: 46081 | B19: WORMS-RRHH | C19: ZIMMERMAN PABLO MAURICIO | D19: -10890280 | E19: DIRECTOR | F19: 1 | G19: 10890280 | H19: #RRHH | I19: PERSONAL | J19: OPEX | K19: 0 | L19: 0 | M19: 0 | N19: CC16 | O19: gastos_produccion | P19: 10 | Q19: BACHAS, CEREAL Y POLVILLO, COMPOST Y FERTILIZANTES, DISPOSICION FINAL DE R. LIQUIDOS, DISPOSICION FINAL DE R. SOLIDOS, EXPORTACION, NFU, PILETAS, REACTORES, TIERRAS FILTRANTES | R19: 1 | S19: -10890280 | T19: 1 | U19: APERTURADO POR EMPRESA
A20: 46081 | B20: WORMS-RRHH | C20: FERREYRA GRACES JORGE BENJAMIN | D20: -8861694.3 | E20: DIRECTOR | F20: 1 | G20: 8861694.3 | H20: #RRHH | I20: PERSONAL | J20: OPEX | K20: 0 | L20: 0 | M20: 0 | N20: CC16 | O20: gastos_produccion | P20: 10 | Q20: BACHAS, CEREAL Y POLVILLO, COMPOST Y FERTILIZANTES, DISPOSICION FINAL DE R. LIQUIDOS, DISPOSICION FINAL DE R. SOLIDOS, EXPORTACION, NFU, PILETAS, REACTORES, TIERRAS FILTRANTES | R20: 1 | S20: -8861694.3 | T20: 1 | U20: APERTURADO POR EMPRESA
A21: 46072 | B21: Cina, Dario Ruben | C21: FA-A 00002-00000007 | D21: -7763698.8 | E21: INVERSION Nunevo pozo de agua | F21: 1 | G21: 6416280 | H21: UN | I21: INVERSION | J21: CAPEX | K21: VARIABLE | L21: INDIRECTO | M21: 0 | N21: CC3 | O21: gastos_rrhh | P21: 1 | Q21: DISPOSICIÓN FINAL RESIDUOS LIQUIDOS | R21: 1 | S21: -7763698.8 | T21: 1 | U21: APERTURADO POR EMPRESA
A22: 46081 | B22: MARTINS, JOAQUIN | C22: prod8 | D22: -7070374 | E22: GASOIL G3 | F22: 4031 | G22: 1754 | H22: Lts | I22: ENERGIA | J22: OPEX | K22: VARIABLE | L22: DIRECTO | M22: 0 | N22: CC1 | O22: gastos_produccion | P22: 10 | Q22: BACHAS, CEREAL & POLVILLO, COMPOST & FERTILIZANTES, DISPOSICIÓN FINAL RESIDUOS LIQUIDOS, DISPOSICIÓN FINAL RESIDUOS SOLIDOS, EXPORTACION, NFU, PILETAS, REACTORES, TIERRAS FILTRANTES | R22: 1 | S22: -7070374 | T22: 4031 | U22: APERTURADO POR EMPRESA
A23: 46081 | B23: WORMS-RRHH | C23: PAGANI, PABLO ALFONSO | D23: -6116414.9 | E23: PRODUCCION | F23: 1 | G23: 6116414.9 | H23: #RRHH | I23: PERSONAL | J23: OPEX | K23: 0 | L23: 0 | M23: 0 | N23: CC28 | O23: gastos_produccion | P23: 10 | Q23: BACHAS, CEREAL & POLVILLO, COMPOST & FERTILIZANTES, DISPOSICIÓN FINAL RESIDUOS LIQUIDOS, DISPOSICIÓN FINAL RESIDUOS SOLIDOS, EXPORTACION, NFU, PILETAS, REACTORES, TIERRAS FILTRANTES | R23: 1 | S23: -6116414.9 | T23: 1 | U23: APERTURADO POR EMPRESA
A24: 46081 | B24: WORMS-RRHH | C24: MAZZALI CARLA JUDIT | D24: -6032968.4 | E24: ADMINISTRACION | F24: 1 | G24: 6032968.4 | H24: #RRHH | I24: PERSONAL | J24: OPEX | K24: 0 | L24: 0 | M24: 0 | N24: CC15 | O24: gastos_rrhh | P24: 10 | Q24: BACHAS, CEREAL Y POLVILLO, COMPOST Y FERTILIZANTES, DISPOSICION FINAL DE R. LIQUIDOS, DISPOSICION FINAL DE R. SOLIDOS, EXPORTACION, NFU, PILETAS, REACTORES, TIERRAS FILTRANTES | R24: 1 | S24: -6032968.4 | T24: 1 | U24: APERTURADO POR EMPRESA
A25: 46077 | B25: Southcross Logistics S.A real | C25: FA-A 00004-00037163 | D25: -5693050 | E25: SERVICIOS flete terrestre | F25: 5 | G25: 500000 | H25: UN | I25: SERVICIOS | J25: OPEX | K25: VARIABLE | L25: DIRECTO | M25: 0 | N25: CC11 | O25: gastos_produccion | P25: 1 | Q25: EXPORTACION | R25: 1 | S25: -5693050 | T25: 5 | U25: APERTURADO POR EMPRESA
A26: 46072 | B26: Mastrangelo Productos Electricos Sa | C26: FA-A 00015-00069801 | D26: -5525708 | E26: INVERSION Proyecto 35 Pedido eléctrico | F26: 1 | G26: 4566700.8 | H26: UN | I26: INVERSION | J26: CAPEX | K26: VARIABLE | L26: DIRECTO | M26: 0 | N26: CC6 | O26: gastos_produccion | P26: 1 | Q26: BACHAS | R26: 1 | S26: -5525708 | T26: 1 | U26: APERTURADO POR EMPRESA
A27: 46081 | B27: ULTRAONIX SRL | C27: prod5 | D27: -5458221.7 | E27: FUEL OIL | F27: 8410.203 | G27: 649 | H27: KG | I27: ENERGIA | J27: OPEX | K27: VARIABLE | L27: DIRECTO | M27: 0 | N27: CC6 | O27: gastos_produccion | P27: 1 | Q27: BACHAS | R27: 1 | S27: -5458221.7 | T27: 8410.203 | U27: APERTURADO POR EMPRESA
A28: 46081 | B28: IMPUESTOS | C28: imp2 | D28: -5039229.7 | E28: IMPUESTOS | F28: 1 | G28: 5039229.7 | H28: UN | I28: IMPUESTOS | J28: OPEX | K28: VARIABLE | L28: INDIRECTO | M28: 0 | N28: CC1 | O28: gastos_rrhh | P28: 10 | Q28: BACHAS, CEREAL & POLVILLO, COMPOST & FERTILIZANTES, DISPOSICIÓN FINAL RESIDUOS LIQUIDOS, DISPOSICIÓN FINAL RESIDUOS SOLIDOS, EXPORTACION, NFU, PILETAS, REACTORES, TIERRAS FILTRANTES | R28: 1 | S28: -5039229.7 | T28: 1 | U28: APERTURADO POR EMPRESA
A29: 46081 | B29: WORMS-RRHH | C29: DIAZ PABLO EMMANUEL | D29: -4660517 | E29: NFU | F29: 1 | G29: 4660517 | H29: #RRHH | I29: PERSONAL | J29: OPEX | K29: 0 | L29: 0 | M29: 0 | N29: CC7 | O29: gastos_impuestos | P29: 1 | Q29: NFU | R29: 1 | S29: -4660517 | T29: 1 | U29: APERTURADO POR EMPRESA
A30: 46081 | B30: WORMS-RRHH | C30: CEBALLEZ, MARIA EUGENIA | D30: -4555960.9 | E30: PRODUCCION | F30: 1 | G30: 4555960.9 | H30: #RRHH | I30: PERSONAL | J30: OPEX | K30: 0 | L30: 0 | M30: 0 | N30: CC28 | O30: gastos_produccion | P30: 10 | Q30: BACHAS, CEREAL & POLVILLO, COMPOST & FERTILIZANTES, DISPOSICIÓN FINAL RESIDUOS LIQUIDOS, DISPOSICIÓN FINAL RESIDUOS SOLIDOS, EXPORTACION, NFU, PILETAS, REACTORES, TIERRAS FILTRANTES | R30: 1 | S30: -4555960.9 | T30: 1 | U30: APERTURADO POR EMPRESA
A31: 46081 | B31: WORMS-RRHH | C31: TISCORNIA FERNANDO | D31: -4207865.4 | E31: DIRECTOR | F31: 1 | G31: 4207865.4 | H31: #RRHH | I31: PERSONAL | J31: OPEX | K31: 0 | L31: 0 | M31: 0 | N31: CC16 | O31: gastos_produccion | P31: 10 | Q31: BACHAS, CEREAL Y POLVILLO, COMPOST Y FERTILIZANTES, DISPOSICION FINAL DE R. LIQUIDOS, DISPOSICION FINAL DE R. SOLIDOS, EXPORTACION, NFU, PILETAS, REACTORES, TIERRAS FILTRANTES | R31: 1 | S31: -4207865.4 | T31: 1 | U31: APERTURADO POR EMPRESA
A32: 46081 | B32: WORMS-RRHH | C32: LUQUE, ADRIAN | D32: -4107684.4 | E32: TALLER MECANICO | F32: 1 | G32: 4107684.4 | H32: #RRHH | I32: PERSONAL | J32: OPEX | K32: 0 | L32: 0 | M32: 0 | N32: CC23 | O32: gastos_produccion | P32: 10 | Q32: BACHAS, CEREAL Y POLVILLO, COMPOST Y FERTILIZANTES, DISPOSICION FINAL DE R. LIQUIDOS, DISPOSICION FINAL DE R. SOLIDOS, EXPORTACION, NFU, PILETAS, REACTORES, TIERRAS FILTRANTES | R32: 1 | S32: -4107684.4 | T32: 1 | U32: APERTURADO POR EMPRESA
A33: 46072 | B33: Bordon, Carlos Roberto | C33: FA-C 00004-00000002 | D33: -4000000 | E33: INVERSION trabajo varios | F33: 1 | G33: 4000000 | H33: UN | I33: INVERSION | J33: CAPEX | K33: VARIABLE | L33: INDIRECTO | M33: 0 | N33: CC6 | O33: gastos_rrhh | P33: 1 | Q33: BACHAS | R33: 1 | S33: -4000000 | T33: 1 | U33: APERTURADO POR EMPRESA
A34: 46081 | B34: WORMS-RRHH | C34: HONORES ANDRES | D34: -3780940.7 | E34: REACTOR | F34: 1 | G34: 3780940.7 | H34: #RRHH | I34: PERSONAL | J34: OPEX | K34: 0 | L34: 0 | M34: 0 | N34: CC15 | O34: gastos_rrhh | P34: 10 | Q34: BACHAS, CEREAL Y POLVILLO, COMPOST Y FERTILIZANTES, DISPOSICION FINAL DE R. LIQUIDOS, DISPOSICION FINAL DE R. SOLIDOS, EXPORTACION, NFU, PILETAS, REACTORES, TIERRAS FILTRANTES | R34: 1 | S34: -3780940.7 | T34: 1 | U34: APERTURADO POR EMPRESA
A35: 46081 | B35: WORMS-RRHH | C35: PEREZ, MATIAS ROMAN | D35: -3671564.8 | E35: INTENDENCIA | F35: 1 | G35: 3671564.8 | H35: #RRHH | I35: PERSONAL | J35: OPEX | K35: 0 | L35: 0 | M35: 0 | N35: CC27 | O35: gastos_rrhh | P35: 10 | Q35: BACHAS, CEREAL Y POLVILLO, COMPOST Y FERTILIZANTES, DISPOSICION FINAL DE R. LIQUIDOS, DISPOSICION FINAL DE R. SOLIDOS, EXPORTACION, NFU, PILETAS, REACTORES, TIERRAS FILTRANTES | R35: 1 | S35: -3671564.8 | T35: 1 | U35: APERTURADO POR EMPRESA
A36: 46056 | B36: Exportdeniv Internacional Sa | C36: FA-A 00002-00000604 | D36: -3455620.3 | E36: OC 0001-00004507: SERVICIOS Almacenaje cargas generales 1/26 | F36: 3969.24 | G36: 870.6 | H36: UN | I36: SERVICIOS | J36: OPEX | K36: VARIABLE | L36: DIRECTO | M36: 0 | N36: CC11 | O36: gastos_produccion | P36: 1 | Q36: EXPORTACION | R36: 1 | S36: -3455620.3 | T36: 3969.24 | U36: APERTURADO POR EMPRESA
A37: 46081 | B37: WORMS-RRHH | C37: LOPEZ CAMARGO BERLITZ, BEATRIZ | D37: -3415916.1 | E37: LABORATORIO | F37: 1 | G37: 3415916.1 | H37: #RRHH | I37: PERSONAL | J37: OPEX | K37: 0 | L37: 0 | M37: 0 | N37: CC17 | O37: gastos_rrhh | P37: 6 | Q37: BACHAS, DISPOSICION FINAL DE R. LIQUIDOS, EXPORTACION, NFU, PILETAS, REACTORES | R37: 1 | S37: -3415916.1 | T37: 1 | U37: APERTURADO POR EMPRESA
A38: 46081 | B38: WORMS-RRHH | C38: PELUZZA, CLAUDIA | D38: -3387545.4 | E38: ADMINISTRACION | F38: 1 | G38: 3387545.4 | H38: #RRHH | I38: PERSONAL | J38: OPEX | K38: 0 | L38: 0 | M38: 0 | N38: CC15 | O38: gastos_rrhh | P38: 10 | Q38: BACHAS, CEREAL Y POLVILLO, COMPOST Y FERTILIZANTES, DISPOSICION FINAL DE R. LIQUIDOS, DISPOSICION FINAL DE R. SOLIDOS, EXPORTACION, NFU, PILETAS, REACTORES, TIERRAS FILTRANTES | R38: 1 | S38: -3387545.4 | T38: 1 | U38: APERTURADO POR EMPRESA
A39: 46081 | B39: MARTINS, JOAQUIN | C39: prod10 | D39: -3363750 | E39: NAFTA | F39: 2250 | G39: 1495 | H39: Lts | I39: ENERGIA | J39: OPEX | K39: VARIABLE | L39: DIRECTO | M39: 0 | N39: CC4 | O39: gastos_rrhh | P39: 1 | Q39: PILETAS | R39: 1 | S39: -3363750 | T39: 2250 | U39: APERTURADO POR EMPRESA
A40: 46081 | B40: WORMS-RRHH | C40: CHIANEA ERWIN | D40: -3349666.3 | E40: PRODUCCION | F40: 1 | G40: 3349666.3 | H40: #RRHH | I40: PERSONAL | J40: OPEX | K40: 0 | L40: 0 | M40: 0 | N40: CC28 | O40: gastos_rrhh | P40: 10 | Q40: BACHAS, CEREAL & POLVILLO, COMPOST & FERTILIZANTES, DISPOSICIÓN FINAL RESIDUOS LIQUIDOS, DISPOSICIÓN FINAL RESIDUOS SOLIDOS, EXPORTACION, NFU, PILETAS, REACTORES, TIERRAS FILTRANTES | R40: 1 | S40: -3349666.3 | T40: 1 | U40: APERTURADO POR EMPRESA
A41: 46081 | B41: WORMS-RRHH | C41: ISOLA, GIULIANA | D41: -3167990 | E41: ADMINISTRACION | F41: 1 | G41: 3167990 | H41: #RRHH | I41: PERSONAL | J41: OPEX | K41: 0 | L41: 0 | M41: 0 | N41: CC15 | O41: gastos_impuestos | P41: 10 | Q41: BACHAS, CEREAL Y POLVILLO, COMPOST Y FERTILIZANTES, DISPOSICION FINAL DE R. LIQUIDOS, DISPOSICION FINAL DE R. SOLIDOS, EXPORTACION, NFU, PILETAS, REACTORES, TIERRAS FILTRANTES | R41: 1 | S41: -3167990 | T41: 1 | U41: APERTURADO POR EMPRESA
A42: 46081 | B42: WORMS-RRHH | C42: CULOTA ANDRES | D42: -3102992.3 | E42: ADMINISTRACION | F42: 1 | G42: 3102992.3 | H42: #RRHH | I42: PERSONAL | J42: OPEX | K42: 0 | L42: 0 | M42: 0 | N42: CC15 | O42: gastos_rrhh | P42: 10 | Q42: BACHAS, CEREAL Y POLVILLO, COMPOST Y FERTILIZANTES, DISPOSICION FINAL DE R. LIQUIDOS, DISPOSICION FINAL DE R. SOLIDOS, EXPORTACION, NFU, PILETAS, REACTORES, TIERRAS FILTRANTES | R42: 1 | S42: -3102992.3 | T42: 1 | U42: APERTURADO POR EMPRESA
A43: 46081 | B43: WORMS-RRHH | C43: LARREY VANINA | D43: -3096266.9 | E43: PORTERIA | F43: 1 | G43: 3096266.9 | H43: #RRHH | I43: PERSONAL | J43: OPEX | K43: 0 | L43: 0 | M43: 0 | N43: CC22 | O43: gastos_produccion | P43: 7 | Q43: BACHAS, COMPOST Y FERTILIZANTES, DISPOSICION FINAL DE R. LIQUIDOS, DISPOSICION FINAL DE R. SOLIDOS, EXPORTACION, NFU, REACTORES | R43: 1 | S43: -3096266.9 | T43: 1 | U43: APERTURADO POR EMPRESA
A44: 46081 | B44: WORMS-RRHH | C44: PETERS CORZO, JOSE LUIS | D44: -3091668.4 | E44: LABORATORIO | F44: 1 | G44: 3091668.4 | H44: #RRHH | I44: PERSONAL | J44: OPEX | K44: 0 | L44: 0 | M44: 0 | N44: CC17 | O44: gastos_rrhh | P44: 6 | Q44: BACHAS, DISPOSICION FINAL DE R. LIQUIDOS, EXPORTACION, NFU, PILETAS, REACTORES | R44: 1 | S44: -3091668.4 | T44: 1 | U44: APERTURADO POR EMPRESA
A45: 46057 | B45: El Laboral Srl | C45: FA-A 00001-00009552 | D45: -3091668.1 | E45: OC 0001-00004006: PERSONAL Indumentaria Remeras, pantalón gorras | F45: 1 | G45: 2555097.6 | H45: UN | I45: PERSONAL | J45: OPEX | K45: VARIABLE | L45: DIRECTO | M45: 0 | N45: CC1 | O45: gastos_rrhh | P45: 10 | Q45: BACHAS, CEREAL & POLVILLO, COMPOST & FERTILIZANTES, DISPOSICIÓN FINAL RESIDUOS LIQUIDOS, DISPOSICIÓN FINAL RESIDUOS SOLIDOS, EXPORTACION, NFU, PILETAS, REACTORES, TIERRAS FILTRANTES | R45: 1 | S45: -3091668.1 | T45: 1 | U45: APERTURADO POR EMPRESA
A46: 46071 | B46: Epp Y Mas S.A. | C46: FA-A 00006-00019294 | D46: -3059361.1 | E46: HIGIENE Y SEGURIDAD Elementos de protección personal | F46: 1 | G46: 2528397.6 | H46: UN | I46: HIGIENE Y SEGURIDAD | J46: OPEX | K46: VARIABLE | L46: DIRECTO | M46: 0 | N46: CC1 | O46: gastos_rrhh | P46: 10 | Q46: BACHAS, CEREAL & POLVILLO, COMPOST & FERTILIZANTES, DISPOSICIÓN FINAL RESIDUOS LIQUIDOS, DISPOSICIÓN FINAL RESIDUOS SOLIDOS, EXPORTACION, NFU, PILETAS, REACTORES, TIERRAS FILTRANTES | R46: 1 | S46: -3059361.1 | T46: 1 | U46: APERTURADO POR EMPRESA
A47: 46054 | B47: Bustamante, Eduardo Maria(W) | C47: FA-A 00003-00000158 | D47: -3025000 | E47: OC 0001-00004493: HONORARIOS Servicios jurídicos Prestados en la ciudad autónoma de buenos aires | F47: 1 | G47: 2500000 | H47: UN | I47: HONORARIOS | J47: OPEX | K47: VARIABLE | L47: INDIRECTO | M47: 0 | N47: CC1 | O47: gastos_rrhh | P47: 10 | Q47: BACHAS, CEREAL & POLVILLO, COMPOST & FERTILIZANTES, DISPOSICIÓN FINAL RESIDUOS LIQUIDOS, DISPOSICIÓN FINAL RESIDUOS SOLIDOS, EXPORTACION, NFU, PILETAS, REACTORES, TIERRAS FILTRANTES | R47: 1 | S47: -3025000 | T47: 1 | U47: APERTURADO POR EMPRESA
A48: 46081 | B48: WORMS-RRHH | C48: BUSTAMANTE ULISES BENIGNO | D48: -2951310.2 | E48: PILETAS | F48: 1 | G48: 2951310.2 | H48: #RRHH | I48: PERSONAL | J48: OPEX | K48: 0 | L48: 0 | M48: 0 | N48: CC4 | O48: gastos_rrhh | P48: 1 | Q48: PILETAS | R48: 1 | S48: -2951310.2 | T48: 1 | U48: APERTURADO POR EMPRESA
A49: 46055 | B49: Acosta, Roberto Maximiliano | C49: FA-C 00001-00000674 | D49: -2950000 | E49: OC 0001-00004297: SERVICIOS Servicio de limpieza enero 2026 | F49: 1 | G49: 2950000 | H49: UN | I49: SERVICIOS | J49: OPEX | K49: VARIABLE | L49: INDIRECTO | M49: 0 | N49: CC1 | O49: gastos_produccion | P49: 10 | Q49: BACHAS, CEREAL & POLVILLO, COMPOST & FERTILIZANTES, DISPOSICIÓN FINAL RESIDUOS LIQUIDOS, DISPOSICIÓN FINAL RESIDUOS SOLIDOS, EXPORTACION, NFU, PILETAS, REACTORES, TIERRAS FILTRANTES | R49: 1 | S49: -2950000 | T49: 1 | U49: APERTURADO POR EMPRESA
A50: 46055 | B50: Gonzalez, Delia | C50: FA-C 00001-00000012 | D50: -2950000 | E50: OC 0001-00004298: SERVICIOS Servicio de limpieza Enero 2026 | F50: 1 | G50: 2950000 | H50: UN | I50: SERVICIOS | J50: OPEX | K50: VARIABLE | L50: INDIRECTO | M50: 0 | N50: CC1 | O50: gastos_produccion | P50: 10 | Q50: BACHAS, CEREAL & POLVILLO, COMPOST & FERTILIZANTES, DISPOSICIÓN FINAL RESIDUOS LIQUIDOS, DISPOSICIÓN FINAL RESIDUOS SOLIDOS, EXPORTACION, NFU, PILETAS, REACTORES, TIERRAS FILTRANTES | R50: 1 | S50: -2950000 | T50: 1 | U50: APERTURADO POR EMPRESA
A51: 46081 | B51: TOTAL QUIMICA S.A. | C51: prod2 | D51: -2928103.2 | E51: ACIDO SULFÚRICO 70/80 | F51: 7920 | G51: 369.71 | H51: KG | I51: INSUMOS | J51: OPEX | K51: VARIABLE | L51: DIRECTO | M51: 0 | N51: CC6 | O51: gastos_rrhh | P51: 1 | Q51: BACHAS | R51: 1 | S51: -2928103.2 | T51: 7920 | U51: APERTURADO POR EMPRESA
A52: 46081 | B52: WORMS-RRHH | C52: MONTENEGRO, GUSTAVO | D52: -2898353.7 | E52: INTENDENCIA | F52: 1 | G52: 2898353.7 | H52: #RRHH | I52: PERSONAL | J52: OPEX | K52: 0 | L52: 0 | M52: 0 | N52: CC27 | O52: gastos_rrhh | P52: 10 | Q52: BACHAS, CEREAL Y POLVILLO, COMPOST Y FERTILIZANTES, DISPOSICION FINAL DE R. LIQUIDOS, DISPOSICION FINAL DE R. SOLIDOS, EXPORTACION, NFU, PILETAS, REACTORES, TIERRAS FILTRANTES | R52: 1 | S52: -2898353.7 | T52: 1 | U52: APERTURADO POR EMPRESA
A53: 46081 | B53: TOTAL QUIMICA S.A. | C53: prod12 | D53: -2871487.5 | E53: SODA CAUSTICA | F53: 3116 | G53: 921.53 | H53: KG | I53: INSUMOS | J53: OPEX | K53: VARIABLE | L53: DIRECTO | M53: 0 | N53: CC5 | O53: gastos_rrhh | P53: 1 | Q53: REACTORES | R53: 1 | S53: -2871487.5 | T53: 3116 | U53: APERTURADO POR EMPRESA
A54: 46061 | B54: Zavalia Lagos, Marina | C54: FA-C 00002-00000085 | D54: -2850000 | E54: OC 0001-00004592: HONORARIOS Servicios profesionales Tomas Bollini Enero 26 | F54: 1 | G54: 2850000 | H54: UN | I54: HONORARIOS | J54: OPEX | K54: VARIABLE | L54: INDIRECTO | M54: 0 | N54: CC1 | O54: gastos_rrhh | P54: 10 | Q54: BACHAS, CEREAL & POLVILLO, COMPOST & FERTILIZANTES, DISPOSICIÓN FINAL RESIDUOS LIQUIDOS, DISPOSICIÓN FINAL RESIDUOS SOLIDOS, EXPORTACION, NFU, PILETAS, REACTORES, TIERRAS FILTRANTES | R54: 1 | S54: -2850000 | T54: 1 | U54: APERTURADO POR EMPRESA
A55: 46081 | B55: WORMS-RRHH | C55: BARRERA, MAXIMILIANO ESEQUIEL | D55: -2792560.3 | E55: DISPOSICION FINAL DE R. LIQUIDOS | F55: 1 | G55: 2792560.3 | H55: #RRHH | I55: PERSONAL | J55: OPEX | K55: 0 | L55: 0 | M55: 0 | N55: CC25 | O55: gastos_produccion | P55: 2 | Q55: DISPOSICION FINAL DE R. LIQUIDOS, EXPORTACION | R55: 1 | S55: -2792560.3 | T55: 1 | U55: APERTURADO POR EMPRESA
A56: 46072 | B56: Chirichigno, Mario Alejandro | C56: FA-C 00003-00000212 | D56: -2727314 | E56: INVERSION etapa 2 proyecto 50 | F56: 1 | G56: 2727314 | H56: UN | I56: INVERSION | J56: CAPEX | K56: VARIABLE | L56: INDIRECTO | M56: 0 | N56: CC1 | O56: gastos_produccion | P56: 10 | Q56: BACHAS, CEREAL & POLVILLO, COMPOST & FERTILIZANTES, DISPOSICIÓN FINAL RESIDUOS LIQUIDOS, DISPOSICIÓN FINAL RESIDUOS SOLIDOS, EXPORTACION, NFU, PILETAS, REACTORES, TIERRAS FILTRANTES | R56: 1 | S56: -2727314 | T56: 1 | U56: APERTURADO POR EMPRESA
A57: 46081 | B57: WORMS-RRHH | C57: TULLIANI ROMINA | D57: -2652084.9 | E57: DISPOSICION FINAL DE R. LIQUIDOS | F57: 1 | G57: 2652084.9 | H57: #RRHH | I57: PERSONAL | J57: OPEX | K57: 0 | L57: 0 | M57: 0 | N57: CC25 | O57: gastos_rrhh | P57: 2 | Q57: DISPOSICION FINAL DE R. LIQUIDOS, EXPORTACION | R57: 1 | S57: -2652084.9 | T57: 1 | U57: APERTURADO POR EMPRESA
A58: 46081 | B58: WORMS-RRHH | C58: PARDEL, MAURO | D58: -2629398.4 | E58: PORTERIA | F58: 1 | G58: 2629398.4 | H58: #RRHH | I58: PERSONAL | J58: OPEX | K58: 0 | L58: 0 | M58: 0 | N58: CC22 | O58: gastos_rrhh | P58: 7 | Q58: BACHAS, COMPOST Y FERTILIZANTES, DISPOSICION FINAL DE R. LIQUIDOS, DISPOSICION FINAL DE R. SOLIDOS, EXPORTACION, NFU, REACTORES | R58: 1 | S58: -2629398.4 | T58: 1 | U58: APERTURADO POR EMPRESA
A59: 46081 | B59: WORMS-RRHH | C59: DI PAOLO ANDREA ANALI | D59: -2603553.4 | E59: ADMINISTRACION | F59: 1 | G59: 2603553.4 | H59: #RRHH | I59: PERSONAL | J59: OPEX | K59: 0 | L59: 0 | M59: 0 | N59: CC15 | O59: gastos_produccion | P59: 10 | Q59: BACHAS, CEREAL Y POLVILLO, COMPOST Y FERTILIZANTES, DISPOSICION FINAL DE R. LIQUIDOS, DISPOSICION FINAL DE R. SOLIDOS, EXPORTACION, NFU, PILETAS, REACTORES, TIERRAS FILTRANTES | R59: 1 | S59: -2603553.4 | T59: 1 | U59: APERTURADO POR EMPRESA
A60: 46081 | B60: WORMS-RRHH | C60: LOPEZ, AGUSTÍN ALBERTO | D60: -2599197.3 | E60: PORTERIA | F60: 1 | G60: 2599197.3 | H60: #RRHH | I60: PERSONAL | J60: OPEX | K60: 0 | L60: 0 | M60: 0 | N60: CC22 | O60: gastos_rrhh | P60: 7 | Q60: BACHAS, COMPOST Y FERTILIZANTES, DISPOSICION FINAL DE R. LIQUIDOS, DISPOSICION FINAL DE R. SOLIDOS, EXPORTACION, NFU, REACTORES | R60: 1 | S60: -2599197.3 | T60: 1 | U60: APERTURADO POR EMPRESA
A61: 46081 | B61: WORMS-RRHH | C61: MAIDANA, JOSE RAMON | D61: -2416515 | E61: INTENDENCIA | F61: 1 | G61: 2416515 | H61: #RRHH | I61: PERSONAL | J61: OPEX | K61: 0 | L61: 0 | M61: 0 | N61: CC27 | O61: gastos_rrhh | P61: 10 | Q61: BACHAS, CEREAL Y POLVILLO, COMPOST Y FERTILIZANTES, DISPOSICION FINAL DE R. LIQUIDOS, DISPOSICION FINAL DE R. SOLIDOS, EXPORTACION, NFU, PILETAS, REACTORES, TIERRAS FILTRANTES | R61: 1 | S61: -2416515 | T61: 1 | U61: APERTURADO POR EMPRESA
A62: 46081 | B62: WORMS-RRHH | C62: LOPEZ JESUS | D62: -2394868.4 | E62: LOGISTICA | F62: 1 | G62: 2394868.4 | H62: #RRHH | I62: PERSONAL | J62: OPEX | K62: 0 | L62: 0 | M62: 0 | N62: CC18 | O62: gastos_rrhh | P62: 5 | Q62: DISPOSICION FINAL DE R. SOLIDOS, EXPORTACION, NFU, PILETAS, REACTORES | R62: 1 | S62: -2394868.4 | T62: 1 | U62: APERTURADO POR EMPRESA
A63: 46081 | B63: WORMS-RRHH | C63: BUSTAMANTE, GUSTAVO GASTON | D63: -2366793.4 | E63: DISPOSICION FINAL DE R. LIQUIDOS | F63: 1 | G63: 2366793.4 | H63: #RRHH | I63: PERSONAL | J63: OPEX | K63: 0 | L63: 0 | M63: 0 | N63: CC25 | O63: gastos_rrhh | P63: 2 | Q63: DISPOSICION FINAL DE R. LIQUIDOS, EXPORTACION | R63: 1 | S63: -2366793.4 | T63: 1 | U63: APERTURADO POR EMPRESA
A64: 46063 | B64: Mil Propiedades Srl | C64: FA-A 00001-00000734 | D64: -2359500 | E64: SERVICIOS alquiler Mod STD C/AA Sauce Viejo Desde 16/02 al 15/03 Baradero 07/02 al 06/03 Coronda 11/02 al 10/03 Timbues 14/02 al 13/03 | F64: 4 | G64: 390000 | H64: UN | I64: SERVICIOS | J64: OPEX | K64: VARIABLE | L64: INDIRECTO | M64: 0 | N64: CC7 | O64: gastos_produccion | P64: 1 | Q64: NFU | R64: 1 | S64: -2359500 | T64: 4 | U64: APERTURADO POR EMPRESA
A65: 46063 | B65: Servitubos S.R.L. | C65: FA-A 00005-00015672 | D65: -2348640.4 | E65: OC 0001-00004633: INVERSION T.Pvc.san.clot.160x3,2z4m | F65: 70 | G65: 27728.93 | H65: UN | I65: INVERSION | J65: CAPEX | K65: VARIABLE | L65: INDIRECTO | M65: 0 | N65: CC3 | O65: gastos_rrhh | P65: 1 | Q65: DISPOSICIÓN FINAL RESIDUOS LIQUIDOS | R65: 1 | S65: -2348640.4 | T65: 70 | U65: APERTURADO POR EMPRESA
A66: 46081 | B66: WORMS-RRHH | C66: BRAVO FRANCISCO NICOLAS | D66: -2339355.3 | E66: DISPOSICION FINAL DE R. LIQUIDOS | F66: 1 | G66: 2339355.3 | H66: #RRHH | I66: PERSONAL | J66: OPEX | K66: 0 | L66: 0 | M66: 0 | N66: CC25 | O66: gastos_produccion | P66: 2 | Q66: DISPOSICION FINAL DE R. LIQUIDOS, EXPORTACION | R66: 1 | S66: -2339355.3 | T66: 1 | U66: APERTURADO POR EMPRESA
A67: 46081 | B67: WORMS-RRHH | C67: ENRIQUEZ, MAXIMO GUSTAVO | D67: -2318520.2 | E67: DISPOSICION FINAL DE R. LIQUIDOS | F67: 1 | G67: 2318520.2 | H67: #RRHH | I67: PERSONAL | J67: OPEX | K67: 0 | L67: 0 | M67: 0 | N67: CC25 | O67: gastos_produccion | P67: 2 | Q67: DISPOSICION FINAL DE R. LIQUIDOS, EXPORTACION | R67: 1 | S67: -2318520.2 | T67: 1 | U67: APERTURADO POR EMPRESA
A68: 46081 | B68: WORMS-RRHH | C68: PANZANELLA, EDUARDO JAVIER | D68: -2316608.1 | E68: PORTERIA | F68: 1 | G68: 2316608.1 | H68: #RRHH | I68: PERSONAL | J68: OPEX | K68: 0 | L68: 0 | M68: 0 | N68: CC22 | O68: gastos_rrhh | P68: 7 | Q68: BACHAS, COMPOST Y FERTILIZANTES, DISPOSICION FINAL DE R. LIQUIDOS, DISPOSICION FINAL DE R. SOLIDOS, EXPORTACION, NFU, REACTORES | R68: 1 | S68: -2316608.1 | T68: 1 | U68: APERTURADO POR EMPRESA
A69: 46081 | B69: WORMS-RRHH | C69: NUÑEZ ALAN OSVALDO | D69: -2289443.2 | E69: PILETAS | F69: 1 | G69: 2289443.2 | H69: #RRHH | I69: PERSONAL | J69: OPEX | K69: 0 | L69: 0 | M69: 0 | N69: CC4 | O69: gastos_rrhh | P69: 1 | Q69: PILETAS | R69: 1 | S69: -2289443.2 | T69: 1 | U69: APERTURADO POR EMPRESA
A70: 46081 | B70: WORMS-RRHH | C70: ACOSTA JORGE SEBASTIAN | D70: -2242802.5 | E70: BACHAS | F70: 1 | G70: 2242802.5 | H70: #RRHH | I70: PERSONAL | J70: OPEX | K70: 0 | L70: 0 | M70: 0 | N70: CC6 | O70: gastos_rrhh | P70: 1 | Q70: BACHAS | R70: 1 | S70: -2242802.5 | T70: 1 | U70: APERTURADO POR EMPRESA
A71: 46055 | B71: Adhoc S.A.(W) | C71: FA-A 00003-00021368 | D71: -2212671.5 | E71: OC 0001-00003852: SERVICIOS Sistema contable | F71: 1 | G71: 1828654.1 | H71: UN | I71: SERVICIOS | J71: OPEX | K71: FIJO | L71: INDIRECTO | M71: 0 | N71: CC1 | O71: gastos_rrhh | P71: 10 | Q71: BACHAS, CEREAL & POLVILLO, COMPOST & FERTILIZANTES, DISPOSICIÓN FINAL RESIDUOS LIQUIDOS, DISPOSICIÓN FINAL RESIDUOS SOLIDOS, EXPORTACION, NFU, PILETAS, REACTORES, TIERRAS FILTRANTES | R71: 1 | S71: -2212671.5 | T71: 1 | U71: APERTURADO POR EMPRESA
A72: 46081 | B72: WORMS-RRHH | C72: RODRIGUEZ, HORACIO | D72: -2197552.3 | E72: TALLER MECANICO | F72: 1 | G72: 2197552.3 | H72: #RRHH | I72: PERSONAL | J72: OPEX | K72: 0 | L72: 0 | M72: 0 | N72: CC23 | O72: gastos_rrhh | P72: 10 | Q72: BACHAS, CEREAL Y POLVILLO, COMPOST Y FERTILIZANTES, DISPOSICION FINAL DE R. LIQUIDOS, DISPOSICION FINAL DE R. SOLIDOS, EXPORTACION, NFU, PILETAS, REACTORES, TIERRAS FILTRANTES | R72: 1 | S72: -2197552.3 | T72: 1 | U72: APERTURADO POR EMPRESA
A73: 46081 | B73: WORMS-RRHH | C73: PACHECO MAURICIO | D73: -2184449.2 | E73: VIGILANCIA | F73: 1 | G73: 2184449.2 | H73: #RRHH | I73: PERSONAL | J73: OPEX | K73: 0 | L73: 0 | M73: 0 | N73: CC29 | O73: gastos_produccion | P73: 10 | Q73: BACHAS, CEREAL Y POLVILLO, COMPOST Y FERTILIZANTES, DISPOSICION FINAL DE R. LIQUIDOS, DISPOSICION FINAL DE R. SOLIDOS, EXPORTACION, NFU, PILETAS, REACTORES, TIERRAS FILTRANTES | R73: 1 | S73: -2184449.2 | T73: 1 | U73: APERTURADO POR EMPRESA
A74: 46081 | B74: WORMS-RRHH | C74: ALVAREZ ALEJANDRO | D74: -2183724.5 | E74: PILETAS | F74: 1 | G74: 2183724.5 | H74: #RRHH | I74: PERSONAL | J74: OPEX | K74: 0 | L74: 0 | M74: 0 | N74: CC4 | O74: gastos_rrhh | P74: 1 | Q74: PILETAS | R74: 1 | S74: -2183724.5 | T74: 1 | U74: APERTURADO POR EMPRESA
A75: 46081 | B75: WORMS-RRHH | C75: RODRIGUEZ, AYRTON | D75: -2171482.7 | E75: DISPOSICION FINAL DE R. LIQUIDOS | F75: 1 | G75: 2171482.7 | H75: #RRHH | I75: PERSONAL | J75: OPEX | K75: 0 | L75: 0 | M75: 0 | N75: CC25 | O75: gastos_rrhh | P75: 2 | Q75: DISPOSICION FINAL DE R. LIQUIDOS, EXPORTACION | R75: 1 | S75: -2171482.7 | T75: 1 | U75: APERTURADO POR EMPRESA
A76: 46081 | B76: WORMS-RRHH | C76: ALTAMIRANO, GUSTAVO | D76: -2164958.5 | E76: NFU | F76: 1 | G76: 2164958.5 | H76: #RRHH | I76: PERSONAL | J76: OPEX | K76: 0 | L76: 0 | M76: 0 | N76: CC7 | O76: gastos_rrhh | P76: 1 | Q76: NFU | R76: 1 | S76: -2164958.5 | T76: 1 | U76: APERTURADO POR EMPRESA
A77: 46081 | B77: WORMS-RRHH | C77: PORCU, MIGUEL ANGEL | D77: -2153887.5 | E77: PILETAS | F77: 1 | G77: 2153887.5 | H77: #RRHH | I77: PERSONAL | J77: OPEX | K77: 0 | L77: 0 | M77: 0 | N77: CC4 | O77: gastos_rrhh | P77: 1 | Q77: PILETAS | R77: 1 | S77: -2153887.5 | T77: 1 | U77: APERTURADO POR EMPRESA
A78: 46081 | B78: WORMS-RRHH | C78: GOMEZ, FRANCO JAVIER | D78: -2140538.4 | E78: DISPOSICION FINAL DE R. LIQUIDOS | F78: 1 | G78: 2140538.4 | H78: #RRHH | I78: PERSONAL | J78: OPEX | K78: 0 | L78: 0 | M78: 0 | N78: CC25 | O78: gastos_rrhh | P78: 2 | Q78: DISPOSICION FINAL DE R. LIQUIDOS, EXPORTACION | R78: 1 | S78: -2140538.4 | T78: 1 | U78: APERTURADO POR EMPRESA
A79: 46081 | B79: WORMS-RRHH | C79: PETERS DIAZ, RAMÓN RICARDO | D79: -2081874.7 | E79: LABORATORIO | F79: 1 | G79: 2081874.7 | H79: #RRHH | I79: PERSONAL | J79: OPEX | K79: 0 | L79: 0 | M79: 0 | N79: CC17 | O79: gastos_produccion | P79: 6 | Q79: BACHAS, DISPOSICION FINAL DE R. LIQUIDOS, EXPORTACION, NFU, PILETAS, REACTORES | R79: 1 | S79: -2081874.7 | T79: 1 | U79: APERTURADO POR EMPRESA
A80: 46081 | B80: WORMS-RRHH | C80: DE AVELENDA VALENTIN | D80: -2057254.4 | E80: DISPOSICION FINAL DE R. LIQUIDOS | F80: 1 | G80: 2057254.4 | H80: #RRHH | I80: PERSONAL | J80: OPEX | K80: 0 | L80: 0 | M80: 0 | N80: CC25 | O80: gastos_rrhh | P80: 2 | Q80: DISPOSICION FINAL DE R. LIQUIDOS, EXPORTACION | R80: 1 | S80: -2057254.4 | T80: 1 | U80: APERTURADO POR EMPRESA
A81: 46081 | B81: WORMS-RRHH | C81: MATTAROLO EDITH | D81: -2056682.7 | E81: PORTERIA | F81: 1 | G81: 2056682.7 | H81: #RRHH | I81: PERSONAL | J81: OPEX | K81: 0 | L81: 0 | M81: 0 | N81: CC22 | O81: gastos_rrhh | P81: 7 | Q81: BACHAS, COMPOST Y FERTILIZANTES, DISPOSICION FINAL DE R. LIQUIDOS, DISPOSICION FINAL DE R. SOLIDOS, EXPORTACION, NFU, REACTORES | R81: 1 | S81: -2056682.7 | T81: 1 | U81: APERTURADO POR EMPRESA
A82: 46081 | B82: WORMS-RRHH | C82: ALVAREZ IVAN DARIO | D82: -2041933.5 | E82: ADMINISTRACION | F82: 1 | G82: 2041933.5 | H82: #RRHH | I82: PERSONAL | J82: OPEX | K82: 0 | L82: 0 | M82: 0 | N82: CC15 | O82: gastos_rrhh | P82: 10 | Q82: BACHAS, CEREAL Y POLVILLO, COMPOST Y FERTILIZANTES, DISPOSICION FINAL DE R. LIQUIDOS, DISPOSICION FINAL DE R. SOLIDOS, EXPORTACION, NFU, PILETAS, REACTORES, TIERRAS FILTRANTES | R82: 1 | S82: -2041933.5 | T82: 1 | U82: APERTURADO POR EMPRESA
A83: 46081 | B83: WORMS-RRHH | C83: FRANCO BRUNO | D83: -2029819 | E83: DISPOSICION FINAL DE R. LIQUIDOS | F83: 1 | G83: 2029819 | H83: #RRHH | I83: PERSONAL | J83: OPEX | K83: 0 | L83: 0 | M83: 0 | N83: CC25 | O83: gastos_rrhh | P83: 2 | Q83: DISPOSICION FINAL DE R. LIQUIDOS, EXPORTACION | R83: 1 | S83: -2029819 | T83: 1 | U83: APERTURADO POR EMPRESA
... A86: 46081 | B86: WORMS-RRHH | C86: AREVALO MARCOS AXEL | D86: -1992393.4 | E86: TALLER MECANICO | F86: 1 | G86: 1992393.4 | H86: #RRHH | I86: PERSONAL | J86: OPEX | K86: 0 | L86: 0 | M86: 0 | N86: CC23 | O86: gastos_produccion | P86: 10 | Q86: BACHAS, CEREAL Y POLVILLO, COMPOST Y FERTILIZANTES, DISPOSICION FINAL DE R. LIQUIDOS, DISPOSICION FINAL DE R. SOLIDOS, EXPORTACION, NFU, PILETAS, REACTORES, TIERRAS FILTRANTES | R86: 1 | S86: -1992393.4 | T86: 1 | U86: APERTURADO POR EMPRESA
A87: 46063 | B87: Strupeni, Federico Lisandro | C87: FA-A 00008-00000058 | D87: -1979272.1 | E87: OC 0001-00004631: INVERSION Disco 4tb para grabación nvr | F87: 4 | G87: 342403.2 | H87: UN | I87: INVERSION | J87: CAPEX | K87: VARIABLE | L87: INDIRECTO | M87: 0 | N87: CC11 | O87: gastos_rrhh | P87: 1 | Q87: EXPORTACION | R87: 1 | S87: -1979272.1 | T87: 4 | U87: APERTURADO POR EMPRESA
A88: 46081 | B88: WORMS-RRHH | C88: BORDON CAMILO RAFAEL | D88: -1972720.5 | E88: REACTOR | F88: 1 | G88: 1972720.5 | H88: #RRHH | I88: PERSONAL | J88: OPEX | K88: 0 | L88: 0 | M88: 0 | N88: CC15 | O88: gastos_rrhh | P88: 10 | Q88: BACHAS, CEREAL Y POLVILLO, COMPOST Y FERTILIZANTES, DISPOSICION FINAL DE R. LIQUIDOS, DISPOSICION FINAL DE R. SOLIDOS, EXPORTACION, NFU, PILETAS, REACTORES, TIERRAS FILTRANTES | R88: 1 | S88: -1972720.5 | T88: 1 | U88: APERTURADO POR EMPRESA
A89: 46081 | B89: WORMS-RRHH | C89: FERNANDEZ, HECTOR OSCAR | D89: -1958595.1 | E89: VIGILANCIA | F89: 1 | G89: 1958595.1 | H89: #RRHH | I89: PERSONAL | J89: OPEX | K89: 0 | L89: 0 | M89: 0 | N89: CC29 | O89: gastos_rrhh | P89: 10 | Q89: BACHAS, CEREAL Y POLVILLO, COMPOST Y FERTILIZANTES, DISPOSICION FINAL DE R. LIQUIDOS, DISPOSICION FINAL DE R. SOLIDOS, EXPORTACION, NFU, PILETAS, REACTORES, TIERRAS FILTRANTES | R89: 1 | S89: -1958595.1 | T89: 1 | U89: APERTURADO POR EMPRESA
A90: 46081 | B90: WORMS-RRHH | C90: MORENO RAMIRO ROMAN | D90: -1942874.4 | E90: PILETAS | F90: 1 | G90: 1942874.4 | H90: #RRHH | I90: PERSONAL | J90: OPEX | K90: 0 | L90: 0 | M90: 0 | N90: CC4 | O90: gastos_rrhh | P90: 1 | Q90: PILETAS | R90: 1 | S90: -1942874.4 | T90: 1 | U90: APERTURADO POR EMPRESA
A91: 46081 | B91: WORMS-RRHH | C91: MARTINEZ JUAN PABLO | D91: -1942605.2 | E91: MANTENIMIENTO | F91: 1 | G91: 1942605.2 | H91: #RRHH | I91: PERSONAL | J91: OPEX | K91: 0 | L91: 0 | M91: 0 | N91: CC19 | O91: gastos_rrhh | P91: 6 | Q91: BACHAS, DISPOSICION FINAL DE R. LIQUIDOS, EXPORTACION, NFU, PILETAS, REACTORES | R91: 1 | S91: -1942605.2 | T91: 1 | U91: APERTURADO POR EMPRESA
A92: 46081 | B92: WORMS-RRHH | C92: CORDOBA GABRIEL | D92: -1930813.4 | E92: ADMINISTRACION | F92: 1 | G92: 1930813.4 | H92: #RRHH | I92: PERSONAL | J92: OPEX | K92: 0 | L92: 0 | M92: 0 | N92: CC15 | O92: gastos_rrhh | P92: 10 | Q92: BACHAS, CEREAL Y POLVILLO, COMPOST Y FERTILIZANTES, DISPOSICION FINAL DE R. LIQUIDOS, DISPOSICION FINAL DE R. SOLIDOS, EXPORTACION, NFU, PILETAS, REACTORES, TIERRAS FILTRANTES | R92: 1 | S92: -1930813.4 | T92: 1 | U92: APERTURADO POR EMPRESA
A93: 46081 | B93: WORMS-RRHH | C93: OVANDO, BRYAN EZEQUIEL | D93: -1928700.1 | E93: MANTENIMIENTO | F93: 1 | G93: 1928700.1 | H93: #RRHH | I93: PERSONAL | J93: OPEX | K93: 0 | L93: 0 | M93: 0 | N93: CC19 | O93: gastos_rrhh | P93: 6 | Q93: BACHAS, DISPOSICION FINAL DE R. LIQUIDOS, EXPORTACION, NFU, PILETAS, REACTORES | R93: 1 | S93: -1928700.1 | T93: 1 | U93: APERTURADO POR EMPRESA
A94: 46081 | B94: WORMS-RRHH | C94: CABRERA JULIAN LEON | D94: -1914723.4 | E94: REACTOR | F94: 1 | G94: 1914723.4 | H94: #RRHH | I94: PERSONAL | J94: OPEX | K94: 0 | L94: 0 | M94: 0 | N94: CC15 | O94: gastos_rrhh | P94: 10 | Q94: BACHAS, CEREAL Y POLVILLO, COMPOST Y FERTILIZANTES, DISPOSICION FINAL DE R. LIQUIDOS, DISPOSICION FINAL DE R. SOLIDOS, EXPORTACION, NFU, PILETAS, REACTORES, TIERRAS FILTRANTES | R94: 1 | S94: -1914723.4 | T94: 1 | U94: APERTURADO POR EMPRESA
A95: 46081 | B95: WORMS-RRHH | C95: CARIAGA, SOFIA | D95: -1898057.5 | E95: ADMINISTRACION | F95: 1 | G95: 1898057.5 | H95: #RRHH | I95: PERSONAL | J95: OPEX | K95: 0 | L95: 0 | M95: 0 | N95: CC15 | O95: gastos_rrhh | P95: 10 | Q95: BACHAS, CEREAL Y POLVILLO, COMPOST Y FERTILIZANTES, DISPOSICION FINAL DE R. LIQUIDOS, DISPOSICION FINAL DE R. SOLIDOS, EXPORTACION, NFU, PILETAS, REACTORES, TIERRAS FILTRANTES | R95: 1 | S95: -1898057.5 | T95: 1 | U95: APERTURADO POR EMPRESA
A96: 46081 | B96: WORMS-RRHH | C96: FERNANDEZ JEREMIAS EDGARDO NAHUEL | D96: -1848040.3 | E96: BACHAS | F96: 1 | G96: 1848040.3 | H96: #RRHH | I96: PERSONAL | J96: OPEX | K96: 0 | L96: 0 | M96: 0 | N96: CC6 | O96: gastos_rrhh | P96: 1 | Q96: BACHAS | R96: 1 | S96: -1848040.3 | T96: 1 | U96: APERTURADO POR EMPRESA
A97: 46081 | B97: WORMS-RRHH | C97: RODRIGUEZ LEANDRO | D97: -1841830.6 | E97: REACTOR | F97: 1 | G97: 1841830.6 | H97: #RRHH | I97: PERSONAL | J97: OPEX | K97: 0 | L97: 0 | M97: 0 | N97: CC15 | O97: gastos_rrhh | P97: 10 | Q97: BACHAS, CEREAL Y POLVILLO, COMPOST Y FERTILIZANTES, DISPOSICION FINAL DE R. LIQUIDOS, DISPOSICION FINAL DE R. SOLIDOS, EXPORTACION, NFU, PILETAS, REACTORES, TIERRAS FILTRANTES | R97: 1 | S97: -1841830.6 | T97: 1 | U97: APERTURADO POR EMPRESA
A98: 46081 | B98: WORMS-RRHH | C98: VAZQUEZ MATIAS EMANUEL | D98: -1836940.1 | E98: PILETAS | F98: 1 | G98: 1836940.1 | H98: #RRHH | I98: PERSONAL | J98: OPEX | K98: 0 | L98: 0 | M98: 0 | N98: CC4 | O98: gastos_rrhh | P98: 1 | Q98: PILETAS | R98: 1 | S98: -1836940.1 | T98: 1 | U98: APERTURADO POR EMPRESA
A99: 46081 | B99: WORMS-RRHH | C99: REY ROLANDO | D99: -1824756.7 | E99: LOGISTICA | F99: 1 | G99: 1824756.7 | H99: #RRHH | I99: PERSONAL | J99: OPEX | K99: 0 | L99: 0 | M99: 0 | N99: CC18 | O99: gastos_rrhh | P99: 5 | Q99: DISPOSICION FINAL DE R. SOLIDOS, EXPORTACION, NFU, PILETAS, REACTORES | R99: 1 | S99: -1824756.7 | T99: 1 | U99: APERTURADO POR EMPRESA
... A113: 46081 | B113: WORMS-RRHH | C113: BALBUENA MAXIMILIANO EZEQUIEL | D113: -1589809.1 | E113: PILETAS | F113: 1 | G113: 1589809.1 | H113: #RRHH | I113: PERSONAL | J113: OPEX | K113: 0 | L113: 0 | M113: 0 | N113: CC4 | O113: gastos_produccion | P113: 1 | Q113: PILETAS | R113: 1 | S113: -1589809.1 | T113: 1 | U113: APERTURADO POR EMPRESA
A114: 46055 | B114: Centauro Alpha S R L | C114: FA-A 00003-00010896 | D114: -1580819.6 | E114: OC 0001-00004383: MANTENIMIENTO PREVENTIVO | F114: 175 | G114: 6541.5 | H114: UN | I114: MANTENIMIENTO PREVENTIVO | J114: OPEX | K114: VARIABLE | L114: INDIRECTO | M114: 0 | N114: CC1 | O114: gastos_produccion | P114: 10 | Q114: BACHAS, CEREAL & POLVILLO, COMPOST & FERTILIZANTES, DISPOSICIÓN FINAL RESIDUOS LIQUIDOS, DISPOSICIÓN FINAL RESIDUOS SOLIDOS, EXPORTACION, NFU, PILETAS, REACTORES, TIERRAS FILTRANTES | R114: 1 | S114: -1580819.6 | T114: 175 | U114: APERTURADO POR EMPRESA
A115: 46057 | B115: Tecnogran S R L | C115: FA-A 00012-00000385 | D115: -1580036.1 | E115: OC 0001-00003876: SERVICIOS Control de plagas Marzo 2026 | F115: 1 | G115: 1305815 | H115: UN | I115: SERVICIOS | J115: OPEX | K115: FIJO | L115: INDIRECTO | M115: 0 | N115: CC1 | O115: gastos_produccion | P115: 10 | Q115: BACHAS, CEREAL & POLVILLO, COMPOST & FERTILIZANTES, DISPOSICIÓN FINAL RESIDUOS LIQUIDOS, DISPOSICIÓN FINAL RESIDUOS SOLIDOS, EXPORTACION, NFU, PILETAS, REACTORES, TIERRAS FILTRANTES | R115: 1 | S115: -1580036.1 | T115: 1 | U115: APERTURADO POR EMPRESA
A116: 46073 | B116: Huxley S.A. | C116: FA-A 00005-00041434 | D116: -1535490 | E116: LOGISTICA | F116: 15 | G116: 84600 | H116: UN | I116: IMPUESTOS | J116: OPEX | K116: VARIABLE | L116: DIRECTO | M116: 0 | N116: CC11 | O116: gastos_rrhh | P116: 1 | Q116: EXPORTACION | R116: 1 | S116: -1535490 | T116: 15 | U116: APERTURADO POR EMPRESA
A117: 46081 | B117: WORMS-RRHH | C117: MARTINEZ, FRANCO ALBERTO | D117: -1480271.3 | E117: CAT | F117: 1 | G117: 1480271.3 | H117: #RRHH | I117: PERSONAL | J117: OPEX | K117: 0 | L117: 0 | M117: 0 | N117: CC7 | O117: gastos_rrhh | P117: 1 | Q117: NFU | R117: 1 | S117: -1480271.3 | T117: 1 | U117: APERTURADO POR EMPRESA
A118: 46081 | B118: WORMS-RRHH | C118: LISARDO, MATIAS IVAN | D118: -1476009.9 | E118: REACTOR | F118: 1 | G118: 1476009.9 | H118: #RRHH | I118: PERSONAL | J118: OPEX | K118: 0 | L118: 0 | M118: 0 | N118: CC15 | O118: gastos_rrhh | P118: 10 | Q118: BACHAS, CEREAL Y POLVILLO, COMPOST Y FERTILIZANTES, DISPOSICION FINAL DE R. LIQUIDOS, DISPOSICION FINAL DE R. SOLIDOS, EXPORTACION, NFU, PILETAS, REACTORES, TIERRAS FILTRANTES | R118: 1 | S118: -1476009.9 | T118: 1 | U118: APERTURADO POR EMPRESA
A119: 46081 | B119: WORMS-RRHH | C119: PASQUALINI, FLORENCIA | D119: -1456024.6 | E119: ADMINISTRACION | F119: 1 | G119: 1456024.6 | H119: #RRHH | I119: PERSONAL | J119: OPEX | K119: 0 | L119: 0 | M119: 0 | N119: CC15 | O119: gastos_rrhh | P119: 10 | Q119: BACHAS, CEREAL Y POLVILLO, COMPOST Y FERTILIZANTES, DISPOSICION FINAL DE R. LIQUIDOS, DISPOSICION FINAL DE R. SOLIDOS, EXPORTACION, NFU, PILETAS, REACTORES, TIERRAS FILTRANTES | R119: 1 | S119: -1456024.6 | T119: 1 | U119: APERTURADO POR EMPRESA
...

Sheet bbdd_ape.p3
A1: Fecha de Factura/Recibo | B1: Nombre de la empresa a mostrar en la factura | C1: Número | D1: Total con signo | E1: Líneas de factura/Etiqueta | F1: Líneas de factura/Cantidad | G1: Líneas de factura/Precio unitario | H1: Líneas de factura/Unidad de medida | I1: Líneas de factura/Producto | J1: Concepto | K1: Tipo de Gasto 1 | L1: Tipo de Gasto 2 | M1: CCO EMPRESA | N1: CCO - SECTOR | O1: SECTOR_ODOO | P1: # SECTORES | Q1: LISTA_SECTORES | R1: Column1 | S1: Column2 | T1: Column3 | U1: Column4
A2: 46081 | B2: WORMS 2 | C2: prod17 | D2: -1.9004255e+09 | E2: AFE (S) | F2: 1403.96 | G2: 945 | H2: TN | I2: MATERIA PRIMA | J2: OPEX | K2: VARIABLE | L2: DIRECTO | M2: 0 | N2: CC11 | O2: gastos_produccion | P2: 1 | Q2: EXPORTACION | R2: 1 | S2: -1.9004255e+09 | T2: 1403.96 | U2: APERTURADO POR EMPRESA
A3: 46081 | B3: WORMS 2 | C3: prod15 | D3: -1.1459658e+08 | E3: AFE (G) | F3: 86.96 | G3: 920 | H3: TN | I3: MATERIA PRIMA | J3: OPEX | K3: VARIABLE | L3: DIRECTO | M3: 0 | N3: CC11 | O3: gastos_produccion | P3: 1 | Q3: EXPORTACION | R3: 1 | S3: -1.1459658e+08 | T3: 86.96 | U3: APERTURADO POR EMPRESA
A4: 46081 | B4: WORMS 2 | C4: prod29 | D4: -87594125 | E4: ARE- B | F4: 72.8 | G4: 840 | H4: TN | I4: MATERIA PRIMA | J4: OPEX | K4: VARIABLE | L4: DIRECTO | M4: 0 | N4: CC11 | O4: gastos_produccion | P4: 1 | Q4: EXPORTACION | R4: 1 | S4: -87594125 | T4: 72.8 | U4: APERTURADO POR EMPRESA
A5: 46081 | B5: WORMS 1 | C5: prod26 | D5: -78996860 | E5: AG-D | F5: 110.3 | G5: 500 | H5: TN | I5: MATERIA PRIMA | J5: OPEX | K5: VARIABLE | L5: DIRECTO | M5: 0 | N5: CC6 | O5: gastos_produccion | P5: 1 | Q5: BACHAS | R5: 1 | S5: -78996860 | T5: 110.3 | U5: APERTURADO POR EMPRESA
A6: 46081 | B6: MILO - DENIS LUQUE | C6: prod13 | D6: -67513309 | E6: GLICERINA CRUDA | F6: 130.925 | G6: 360 | H6: TN | I6: INSUMOS | J6: OPEX | K6: VARIABLE | L6: DIRECTO | M6: 0 | N6: CC5 | O6: gastos_produccion | P6: 1 | Q6: REACTORES | R6: 1 | S6: -67513309 | T6: 130.925 | U6: APERTURADO POR EMPRESA
A7: 46066 | B7: Construcciones Industriales Y Portuarias S.A. | C7: FA-A 00003-00001286 | D7: -54208000 | E7: INVERSION Planta de efluentes | F7: 1 | G7: 44800000 | H7: UN | I7: INVERSION | J7: CAPEX | K7: VARIABLE | L7: INDIRECTO | M7: 0 | N7: CC3 | O7: gastos_produccion | P7: 1 | Q7: DISPOSICIÓN FINAL RESIDUOS LIQUIDOS | R7: 1 | S7: -54208000 | T7: 1 | U7: APERTURADO POR EMPRESA
A8: 46056 | B8: Construcciones Industriales Y Portuarias S.A. | C8: FA-A 00003-00001279 | D8: -54208000 | E8: OC 0001-00004263: INVERSION Planta de efluentes | F8: 1 | G8: 44800000 | H8: UN | I8: INVERSION | J8: CAPEX | K8: VARIABLE | L8: INDIRECTO | M8: 0 | N8: CC3 | O8: gastos_produccion | P8: 1 | Q8: DISPOSICIÓN FINAL RESIDUOS LIQUIDOS | R8: 1 | S8: -54208000 | T8: 1 | U8: APERTURADO POR EMPRESA
